{
 "type": "FeatureCollection",
 "generated": "2024-09-24T15:27:04.257389",
 "suburb": "BARBERTON",
 "features": [
  {
   "type": "Feature",
   "geometry": {
    "type": "Point",
    "coordinates": [
     116.11171164,
     -30.74837083
    ]
   },
   "properties": {
    "name": "974 BALARONG ROAD BARBERTON 6510",
    "locID": "LOC000006519470",
    "tech": "SATELLITE",
    "upgrade": "NULL_NA",
    "gnaf_pid": "GAWA_162258920",
    "tech_change_status": "Not Planned"
   }
  },
  {
   "type": "Feature",
   "geometry": {
    "type": "Point",
    "coordinates": [
     115.971542,
     -30.726752
    ]
   },
   "properties": {
    "name": "559 BARBERTON WEST ROAD BARBERTON 6510",
    "locID": "LOC000101811536",
    "tech": "SATELLITE",
    "upgrade": "NULL_NA",
    "gnaf_pid": "GAWA_162258994",
    "tech_change_status": "Not Planned"
   }
  },
  {
   "type": "Feature",
   "geometry": {
    "type": "Point",
    "coordinates": [
     116.03779789,
     -30.74582765
    ]
   },
   "properties": {
    "name": "7472 BINDOON-MOORA ROAD BARBERTON 6510",
    "locID": "LOC000094292799",
    "tech": "SATELLITE",
    "upgrade": "NULL_NA",
    "gnaf_pid": "GAWA_162259468",
    "tech_change_status": "Not Planned"
   }
  },
  {
   "type": "Feature",
   "geometry": {
    "type": "Point",
    "coordinates": [
     116.014981,
     -30.737999
    ]
   },
   "properties": {
    "name": "7567 BINDOON-MOORA ROAD BARBERTON 6510",
    "locID": "LOC000091633670",
    "tech": "NULL",
    "upgrade": "NULL_NA",
    "gnaf_pid": "GAWA_162259469",
    "tech_change_status": "Not Planned"
   }
  },
  {
   "type": "Feature",
   "geometry": {
    "type": "Point",
    "coordinates": [
     116.020865,
     -30.726574
    ]
   },
   "properties": {
    "name": "7641 BINDOON-MOORA ROAD BARBERTON 6510",
    "locID": "LOC000049779922",
    "tech": "SATELLITE",
    "upgrade": "NULL_NA",
    "gnaf_pid": "GAWA_162259470",
    "tech_change_status": "Not Planned"
   }
  },
  {
   "type": "Feature",
   "geometry": {
    "type": "Point",
    "coordinates": [
     116.016722,
     -30.70726
    ]
   },
   "properties": {
    "name": "7909 BINDOON-MOORA ROAD BARBERTON 6510",
    "locID": "LOC000100554741",
    "tech": "SATELLITE",
    "upgrade": "NULL_NA",
    "gnaf_pid": "GAWA_162259471",
    "tech_change_status": "Not Planned"
   }
  }
 ]
}