{
 "type": "FeatureCollection",
 "generated": "2023-12-21T16:09:35.403643",
 "suburb": "CANE",
 "features": [
  {
   "type": "Feature",
   "geometry": {
    "type": "Point",
    "coordinates": [
     115.71708683,
     -22.12062168
    ]
   },
   "properties": {
    "name": "151 NORTH WEST COASTAL HIGHWAY CANE 6710",
    "locID": "EipUb3VyaXN0IERyaXZlIDM1NCwgQ2FuZSBXQSA2NzEwLCBBdXN0cmFsaWEiLiosChQKEgkDJnXTfa_1KxELH8F4pFht_hIUChIJ1-xDA3eu8CsRkMt5JDj2AAQ",
    "tech": "SATELLITE",
    "upgrade": "UNKNOWN",
    "gnaf_pid": "GAWA_163382741"
   }
  }
 ]
}