{
 "type": "FeatureCollection",
 "generated": "2023-12-21T19:23:18.845681",
 "suburb": "EAST LYONS RIVER",
 "features": [
  {
   "type": "Feature",
   "geometry": {
    "type": "Point",
    "coordinates": [
     116.93298338,
     -24.76221837
    ]
   },
   "properties": {
    "name": "UNIT 1, LOT 50 LANDOR-MOUNT AUGUSTUS ROAD EAST LYONS RIVER 6705",
    "locID": "LOC100073786887",
    "tech": "SATELLITE",
    "upgrade": "NULL_NA",
    "gnaf_pid": "GAWA_163245618"
   }
  },
  {
   "type": "Feature",
   "geometry": {
    "type": "Point",
    "coordinates": [
     116.93298338,
     -24.76221837
    ]
   },
   "properties": {
    "name": "UNIT 2, LOT 50 LANDOR-MOUNT AUGUSTUS ROAD EAST LYONS RIVER 6705",
    "locID": "LOC100073786887",
    "tech": "SATELLITE",
    "upgrade": "NULL_NA",
    "gnaf_pid": "GAWA_163245619"
   }
  },
  {
   "type": "Feature",
   "geometry": {
    "type": "Point",
    "coordinates": [
     116.93298338,
     -24.76221837
    ]
   },
   "properties": {
    "name": "LOT 50 LANDOR-MOUNT AUGUSTUS ROAD EAST LYONS RIVER 6705",
    "locID": "LOC100073786887",
    "tech": "SATELLITE",
    "upgrade": "NULL_NA",
    "gnaf_pid": "GAWA_163247825"
   }
  }
 ]
}