{
 "type": "FeatureCollection",
 "generated": "2024-05-27T04:27:54.985982",
 "suburb": "ENNUIN",
 "features": [
  {
   "type": "Feature",
   "geometry": {
    "type": "Point",
    "coordinates": [
     118.92234634,
     -30.64989737
    ]
   },
   "properties": {
    "name": "LOT 1540 MOUNT JACKSON ROAD ENNUIN 6484",
    "locID": "LOC000133311685",
    "tech": "SATELLITE",
    "upgrade": "NULL_NA",
    "gnaf_pid": "GAWA_161566592"
   }
  },
  {
   "type": "Feature",
   "geometry": {
    "type": "Point",
    "coordinates": [
     118.92900469,
     -30.65736172
    ]
   },
   "properties": {
    "name": "LOT 79 MOUNT JACKSON ROAD ENNUIN 6484",
    "locID": "LOC000133311685",
    "tech": "SATELLITE",
    "upgrade": "NULL_NA",
    "gnaf_pid": "GAWA_162798898"
   }
  }
 ]
}