{
 "type": "FeatureCollection",
 "generated": "2023-12-21T20:46:10.923424",
 "suburb": "GNOOREA",
 "features": [
  {
   "type": "Feature",
   "geometry": {
    "type": "Point",
    "coordinates": [
     116.35990829,
     -20.84551992
    ]
   },
   "properties": {
    "name": "LOT 5008 FORTY MILE BEACH ROAD GNOOREA 6714",
    "locID": "Ei9Gb3J0eSBNaWxlIEJlYWNoIFJkLCBHbm9vcmVhIFdBIDY3MTQsIEF1c3RyYWxpYSIuKiwKFAoSCX8csu26tPcrEREdDh6g1WjsEhQKEgnLgIrH7rT3KxEwzHkkOPYABA",
    "tech": "SATELLITE",
    "upgrade": "UNKNOWN",
    "gnaf_pid": "GAWA_163278588"
   }
  },
  {
   "type": "Feature",
   "geometry": {
    "type": "Point",
    "coordinates": [
     116.35245145,
     -20.84554082
    ]
   },
   "properties": {
    "name": "LOT 5009 FORTY MILE BEACH ROAD GNOOREA 6714",
    "locID": "Ei9Gb3J0eSBNaWxlIEJlYWNoIFJkLCBHbm9vcmVhIFdBIDY3MTQsIEF1c3RyYWxpYSIuKiwKFAoSCX8csu26tPcrEREdDh6g1WjsEhQKEgnLgIrH7rT3KxEwzHkkOPYABA",
    "tech": "SATELLITE",
    "upgrade": "UNKNOWN",
    "gnaf_pid": "GAWA_163379296"
   }
  }
 ]
}