{
 "type": "FeatureCollection",
 "generated": "2023-11-12T13:59:48.474485",
 "suburb": "KARIJINI",
 "features": [
  {
   "type": "Feature",
   "geometry": {
    "type": "Point",
    "coordinates": [
     118.69022,
     -22.37711
    ]
   },
   "properties": {
    "name": "LOT 84 GREAT NORTHERN HIGHWAY KARIJINI 6751",
    "locID": "LOC000109588858",
    "tech": "SATELLITE",
    "upgrade": "NULL_NA",
    "gnaf_pid": "GAWA_147096615"
   }
  }
 ]
}