{
 "type": "FeatureCollection",
 "generated": "2023-10-26T01:15:14.811946",
 "suburb": "KARRAMINDIE",
 "features": [
  {
   "type": "Feature",
   "geometry": {
    "type": "Point",
    "coordinates": [
     121.42850211,
     -31.04224193
    ]
   },
   "properties": {
    "name": "LOT 105 COOLGARDIE-ESPERANCE HIGHWAY KARRAMINDIE 6429",
    "locID": "EjhDb29sZ2FyZGllLUVzcGVyYW5jZSBId3ksIEthcnJhbWluZGllIFdBIDY0MjksIEF1c3RyYWxpYSIuKiwKFAoSCa-no3Tl-k0qEekJXrID9siQEhQKEgmnexj2j5xNKhFA1XkkOPYABA",
    "tech": "SATELLITE",
    "upgrade": "UNKNOWN",
    "gnaf_pid": "GAWA_163271581"
   }
  },
  {
   "type": "Feature",
   "geometry": {
    "type": "Point",
    "coordinates": [
     121.20478778,
     -30.96527617
    ]
   },
   "properties": {
    "name": "LOT 50 COOLGARDIE-ESPERANCE HIGHWAY KARRAMINDIE 6429",
    "locID": "Ejs1MCBDb29sZ2FyZGllLUVzcGVyYW5jZSBId3ksIEthcnJhbWluZGllIFdBIDY0MjksIEF1c3RyYWxpYSIwEi4KFAoSCesb6A-ODU0qEQRon8_24sRFEDIqFAoSCa-no3Tl-k0qEekJXrID9siQ",
    "tech": "SATELLITE",
    "upgrade": "UNKNOWN",
    "gnaf_pid": "GAWA_718214061"
   }
  }
 ]
}