{
 "type": "FeatureCollection",
 "generated": "2024-07-07T18:10:11.973069",
 "suburb": "KING LEOPOLD RANGES",
 "features": [
  {
   "type": "Feature",
   "geometry": {
    "type": "Point",
    "coordinates": [
     125.30062,
     -17.91647
    ]
   },
   "properties": {
    "name": "LOT 143 LEOPOLD DOWNS ROAD KING LEOPOLD RANGES 6728",
    "locID": "LOC000133516424",
    "tech": "SATELLITE",
    "upgrade": "NULL_NA",
    "gnaf_pid": "GAWA_161992648",
    "tech_change_status": "Not Planned"
   }
  },
  {
   "type": "Feature",
   "geometry": {
    "type": "Point",
    "coordinates": [
     124.74889207,
     -17.37913809
    ]
   },
   "properties": {
    "name": "LOT 20 DERBY-GIBB RIVER ROAD KING LEOPOLD RANGES 6728",
    "locID": "LOC000142973726",
    "tech": "SATELLITE",
    "upgrade": "NULL_NA",
    "gnaf_pid": "GAWA_163150615",
    "tech_change_status": "Not Planned"
   }
  },
  {
   "type": "Feature",
   "geometry": {
    "type": "Point",
    "coordinates": [
     125.4506879,
     -17.15520374
    ]
   },
   "properties": {
    "name": "LOT 16 DERBY-GIBB RIVER ROAD KING LEOPOLD RANGES 6728",
    "locID": "LOC100081850135",
    "tech": "SATELLITE",
    "upgrade": "NULL_NA",
    "gnaf_pid": "GAWA_718339017",
    "tech_change_status": "Not Planned"
   }
  },
  {
   "type": "Feature",
   "geometry": {
    "type": "Point",
    "coordinates": [
     125.92899046,
     -16.7295228
    ]
   },
   "properties": {
    "name": "LOT 33 DERBY-GIBB RIVER ROAD KING LEOPOLD RANGES 6728",
    "locID": "LOC000133460926",
    "tech": "SATELLITE",
    "upgrade": "NULL_NA",
    "gnaf_pid": "GAWA_718339018",
    "tech_change_status": "Not Planned"
   }
  },
  {
   "type": "Feature",
   "geometry": {
    "type": "Point",
    "coordinates": [
     125.39219139,
     -17.14705477
    ]
   },
   "properties": {
    "name": "LOT 8 DERBY-GIBB RIVER ROAD KING LEOPOLD RANGES 6728",
    "locID": "LOC000070540620",
    "tech": "SATELLITE",
    "upgrade": "NULL_NA",
    "gnaf_pid": "GAWA_719503168",
    "tech_change_status": "Not Planned"
   }
  }
 ]
}