{
 "type": "FeatureCollection",
 "generated": "2024-09-25T01:08:43.723973",
 "suburb": "MILO",
 "features": [
  {
   "type": "Feature",
   "geometry": {
    "type": "Point",
    "coordinates": [
     115.23454606,
     -29.28464173
    ]
   },
   "properties": {
    "name": "226 LUDLOW ROAD MILO 6525",
    "locID": "LOC000116522768",
    "tech": "SATELLITE",
    "upgrade": "NULL_NA",
    "gnaf_pid": "GAWA_162001349",
    "tech_change_status": "Not Planned"
   }
  },
  {
   "type": "Feature",
   "geometry": {
    "type": "Point",
    "coordinates": [
     115.2284513,
     -29.22653062
    ]
   },
   "properties": {
    "name": "25033 MIDLANDS ROAD MILO 6525",
    "locID": "LOC000064590691",
    "tech": "SATELLITE",
    "upgrade": "NULL_NA",
    "gnaf_pid": "GAWA_162001548",
    "tech_change_status": "Not Planned"
   }
  },
  {
   "type": "Feature",
   "geometry": {
    "type": "Point",
    "coordinates": [
     115.201253,
     -29.230152
    ]
   },
   "properties": {
    "name": "25483 MIDLANDS ROAD MILO 6525",
    "locID": "LOC000100648159",
    "tech": "NULL",
    "upgrade": "NULL_NA",
    "gnaf_pid": "GAWA_162001549",
    "tech_change_status": "Not Planned"
   }
  },
  {
   "type": "Feature",
   "geometry": {
    "type": "Point",
    "coordinates": [
     115.11545,
     -29.230021
    ]
   },
   "properties": {
    "name": "26297 MIDLANDS ROAD MILO 6525",
    "locID": "LOC000031458245",
    "tech": "NULL",
    "upgrade": "NULL_NA",
    "gnaf_pid": "GAWA_162001550",
    "tech_change_status": "Not Planned"
   }
  },
  {
   "type": "Feature",
   "geometry": {
    "type": "Point",
    "coordinates": [
     115.10558205,
     -29.22322742
    ]
   },
   "properties": {
    "name": "26419 MIDLANDS ROAD MILO 6525",
    "locID": "LOC000046684352",
    "tech": "NULL",
    "upgrade": "NULL_NA",
    "gnaf_pid": "GAWA_162001551",
    "tech_change_status": "Not Planned"
   }
  },
  {
   "type": "Feature",
   "geometry": {
    "type": "Point",
    "coordinates": [
     115.193973,
     -29.288923
    ]
   },
   "properties": {
    "name": "1146 MILO ROAD MILO 6525",
    "locID": "LOC000038575040",
    "tech": "SATELLITE",
    "upgrade": "NULL_NA",
    "gnaf_pid": "GAWA_162001625",
    "tech_change_status": "Not Planned"
   }
  },
  {
   "type": "Feature",
   "geometry": {
    "type": "Point",
    "coordinates": [
     115.17050798,
     -29.28742595
    ]
   },
   "properties": {
    "name": "1359 MILO ROAD MILO 6525",
    "locID": "LOC000067756539",
    "tech": "NULL",
    "upgrade": "NULL_NA",
    "gnaf_pid": "GAWA_162001626",
    "tech_change_status": "Not Planned"
   }
  },
  {
   "type": "Feature",
   "geometry": {
    "type": "Point",
    "coordinates": [
     115.14420107,
     -29.33354055
    ]
   },
   "properties": {
    "name": "1835 MILO ROAD MILO 6525",
    "locID": "LOC000021535469",
    "tech": "SATELLITE",
    "upgrade": "NULL_NA",
    "gnaf_pid": "GAWA_162001627",
    "tech_change_status": "Not Planned"
   }
  },
  {
   "type": "Feature",
   "geometry": {
    "type": "Point",
    "coordinates": [
     115.120333,
     -29.276942
    ]
   },
   "properties": {
    "name": "1891 MILO ROAD MILO 6525",
    "locID": "LOC000070674852",
    "tech": "NULL",
    "upgrade": "NULL_NA",
    "gnaf_pid": "GAWA_162001628",
    "tech_change_status": "Not Planned"
   }
  },
  {
   "type": "Feature",
   "geometry": {
    "type": "Point",
    "coordinates": [
     115.21439422,
     -29.32969723
    ]
   },
   "properties": {
    "name": "296 WARRADONG SPRING ROAD MILO 6525",
    "locID": "LOC000094875072",
    "tech": "SATELLITE",
    "upgrade": "NULL_NA",
    "gnaf_pid": "GAWA_162003171",
    "tech_change_status": "Not Planned"
   }
  },
  {
   "type": "Feature",
   "geometry": {
    "type": "Point",
    "coordinates": [
     115.15755705,
     -29.2354812
    ]
   },
   "properties": {
    "name": "26451 MIDLANDS ROAD MILO 6525",
    "locID": "LOC000133388160",
    "tech": "SATELLITE",
    "upgrade": "NULL_NA",
    "gnaf_pid": "GAWA_163340365",
    "tech_change_status": "Not Planned"
   }
  },
  {
   "type": "Feature",
   "geometry": {
    "type": "Point",
    "coordinates": [
     115.23445136,
     -29.26381083
    ]
   },
   "properties": {
    "name": "699 MILO ROAD MILO 6525",
    "locID": "LOC000133399308",
    "tech": "SATELLITE",
    "upgrade": "NULL_NA",
    "gnaf_pid": "GAWA_718341393",
    "tech_change_status": "Not Planned"
   }
  }
 ]
}