{
 "type": "FeatureCollection",
 "generated": "2024-01-22T23:27:20.396549",
 "suburb": "MOUNT NEY",
 "features": [
  {
   "type": "Feature",
   "geometry": {
    "type": "Point",
    "coordinates": [
     122.47718616,
     -33.48198461
    ]
   },
   "properties": {
    "name": "LOT 421 HOWICK ROAD MOUNT NEY 6447",
    "locID": "Eis0MjEgSG93aWNrIFJkLCBNb3VudCBOZXkgV0EgNjQ0NywgQXVzdHJhbGlhIjESLwoUChIJfweqZyGsWyoRZeNosARyKncQpQMqFAoSCaMP_L_zu1sqEfXKaXo9Mv4P",
    "tech": "SATELLITE",
    "upgrade": "UNKNOWN",
    "gnaf_pid": "GAWA_162790393"
   }
  },
  {
   "type": "Feature",
   "geometry": {
    "type": "Point",
    "coordinates": [
     122.52333792,
     -33.46160196
    ]
   },
   "properties": {
    "name": "LOT 426 HOWICK ROAD MOUNT NEY 6447",
    "locID": "Eis0MjYgSG93aWNrIFJkLCBNb3VudCBOZXkgV0EgNjQ0NywgQXVzdHJhbGlhIjESLwoUChIJfweqZyGsWyoRZeNosARyKncQqgMqFAoSCaMP_L_zu1sqEfXKaXo9Mv4P",
    "tech": "SATELLITE",
    "upgrade": "UNKNOWN",
    "gnaf_pid": "GAWA_162790394"
   }
  },
  {
   "type": "Feature",
   "geometry": {
    "type": "Point",
    "coordinates": [
     122.47583227,
     -33.40557737
    ]
   },
   "properties": {
    "name": "LOT 429 HOWICK ROAD MOUNT NEY 6447",
    "locID": "Eis0MjkgSG93aWNrIFJkLCBNb3VudCBOZXkgV0EgNjQ0NywgQXVzdHJhbGlhIjESLwoUChIJfweqZyGsWyoRZeNosARyKncQrQMqFAoSCaMP_L_zu1sqEfXKaXo9Mv4P",
    "tech": "SATELLITE",
    "upgrade": "UNKNOWN",
    "gnaf_pid": "GAWA_162790397"
   }
  },
  {
   "type": "Feature",
   "geometry": {
    "type": "Point",
    "coordinates": [
     122.55492482,
     -33.47372197
    ]
   },
   "properties": {
    "name": "3899 COOLINUP ROAD MOUNT NEY 6447",
    "locID": "ChIJD89bLzewWyoRPOOIiOA3lCY",
    "tech": "SATELLITE",
    "upgrade": "UNKNOWN",
    "gnaf_pid": "GAWA_718483655"
   }
  },
  {
   "type": "Feature",
   "geometry": {
    "type": "Point",
    "coordinates": [
     122.48938203,
     -33.42551799
    ]
   },
   "properties": {
    "name": "4228 HOWICK ROAD MOUNT NEY 6447",
    "locID": "ChIJhZHOeTWsWyoRm-Vw1tvIVys",
    "tech": "SATELLITE",
    "upgrade": "UNKNOWN",
    "gnaf_pid": "GAWA_718484941"
   }
  },
  {
   "type": "Feature",
   "geometry": {
    "type": "Point",
    "coordinates": [
     122.50659488,
     -33.44396366
    ]
   },
   "properties": {
    "name": "4230 HOWICK ROAD MOUNT NEY 6447",
    "locID": "LOC000148370963",
    "tech": "SATELLITE",
    "upgrade": "NULL_NA",
    "gnaf_pid": "GAWA_718484942"
   }
  },
  {
   "type": "Feature",
   "geometry": {
    "type": "Point",
    "coordinates": [
     122.46147816,
     -33.46426084
    ]
   },
   "properties": {
    "name": "4349 HOWICK ROAD MOUNT NEY 6447",
    "locID": "LOC000148370963",
    "tech": "SATELLITE",
    "upgrade": "NULL_NA",
    "gnaf_pid": "GAWA_718484943"
   }
  },
  {
   "type": "Feature",
   "geometry": {
    "type": "Point",
    "coordinates": [
     122.39448932,
     -33.45504604
    ]
   },
   "properties": {
    "name": "1374 KAU ROCK ROAD MOUNT NEY 6447",
    "locID": "LOC000148370985",
    "tech": "SATELLITE",
    "upgrade": "NULL_NA",
    "gnaf_pid": "GAWA_718485085"
   }
  },
  {
   "type": "Feature",
   "geometry": {
    "type": "Point",
    "coordinates": [
     122.44578705,
     -33.52081793
    ]
   },
   "properties": {
    "name": "598 KAU ROCK ROAD MOUNT NEY 6447",
    "locID": "ChIJK89OJUyvWyoRs3BKVtyyp-U",
    "tech": "SATELLITE",
    "upgrade": "UNKNOWN",
    "gnaf_pid": "GAWA_718485086"
   }
  },
  {
   "type": "Feature",
   "geometry": {
    "type": "Point",
    "coordinates": [
     122.47750557,
     -33.44932581
    ]
   },
   "properties": {
    "name": "4222 HOWICK ROAD MOUNT NEY 6447",
    "locID": "LOC000148370963",
    "tech": "SATELLITE",
    "upgrade": "NULL_NA",
    "gnaf_pid": "GAWA_721282631"
   }
  }
 ]
}