{
 "type": "FeatureCollection",
 "generated": "2024-08-18T10:08:26.887648",
 "suburb": "MOUNT NEY",
 "features": [
  {
   "type": "Feature",
   "geometry": {
    "type": "Point",
    "coordinates": [
     122.50659488,
     -33.44396366
    ]
   },
   "properties": {
    "name": "4230 HOWICK ROAD MOUNT NEY 6447",
    "locID": "LOC000148370963",
    "tech": "SATELLITE",
    "upgrade": "NULL_NA",
    "gnaf_pid": "GAWA_718484942",
    "tech_change_status": "Not Planned"
   }
  },
  {
   "type": "Feature",
   "geometry": {
    "type": "Point",
    "coordinates": [
     122.46147816,
     -33.46426084
    ]
   },
   "properties": {
    "name": "4349 HOWICK ROAD MOUNT NEY 6447",
    "locID": "LOC000148370963",
    "tech": "SATELLITE",
    "upgrade": "NULL_NA",
    "gnaf_pid": "GAWA_718484943",
    "tech_change_status": "Not Planned"
   }
  },
  {
   "type": "Feature",
   "geometry": {
    "type": "Point",
    "coordinates": [
     122.39448932,
     -33.45504604
    ]
   },
   "properties": {
    "name": "1374 KAU ROCK ROAD MOUNT NEY 6447",
    "locID": "LOC000148370985",
    "tech": "SATELLITE",
    "upgrade": "NULL_NA",
    "gnaf_pid": "GAWA_718485085",
    "tech_change_status": "Not Planned"
   }
  },
  {
   "type": "Feature",
   "geometry": {
    "type": "Point",
    "coordinates": [
     122.47750557,
     -33.44932581
    ]
   },
   "properties": {
    "name": "4222 HOWICK ROAD MOUNT NEY 6447",
    "locID": "LOC000148370963",
    "tech": "SATELLITE",
    "upgrade": "NULL_NA",
    "gnaf_pid": "GAWA_721282631",
    "tech_change_status": "Not Planned"
   }
  }
 ]
}