{
 "type": "FeatureCollection",
 "generated": "2024-01-23T00:13:56.469755",
 "suburb": "MUNDRABILLA",
 "features": [
  {
   "type": "Feature",
   "geometry": {
    "type": "Point",
    "coordinates": [
     128.20739284,
     -31.81471229
    ]
   },
   "properties": {
    "name": "LOT 38 EYRE HIGHWAY MUNDRABILLA 6443",
    "locID": "EiwzOCBFeXJlIEh3eSwgRnJhc2VyIFJhbmdlIFdBIDY0NDMsIEF1c3RyYWxpYSIwEi4KFAoSCdkoOVrTYlcqEZ6w-f2yo-4RECYqFAoSCXM1EWSS-aZqEVYZ_GEr8D69",
    "tech": "SATELLITE",
    "upgrade": "UNKNOWN",
    "gnaf_pid": "GAWA_163239847"
   }
  },
  {
   "type": "Feature",
   "geometry": {
    "type": "Point",
    "coordinates": [
     128.22427156,
     -31.82133198
    ]
   },
   "properties": {
    "name": "LOT 39 EYRE HIGHWAY MUNDRABILLA 6443",
    "locID": "EiwzOSBFeXJlIEh3eSwgRnJhc2VyIFJhbmdlIFdBIDY0NDMsIEF1c3RyYWxpYSIwEi4KFAoSCdkoOVrTYlcqEZ6w-f2yo-4RECcqFAoSCXM1EWSS-aZqEVYZ_GEr8D69",
    "tech": "SATELLITE",
    "upgrade": "UNKNOWN",
    "gnaf_pid": "GAWA_163239848"
   }
  }
 ]
}