{
 "type": "FeatureCollection",
 "generated": "2024-09-06T16:28:46.201048",
 "suburb": "NAIRIBIN",
 "features": [
  {
   "type": "Feature",
   "geometry": {
    "type": "Point",
    "coordinates": [
     117.967444,
     -33.309454
    ]
   },
   "properties": {
    "name": "1526 ONE TWENTY FIVE ROAD NAIRIBIN 6350",
    "locID": "LOC000091582227",
    "tech": "NULL",
    "upgrade": "NULL_NA",
    "gnaf_pid": "GAWA_161931837",
    "tech_change_status": "Not Planned"
   }
  },
  {
   "type": "Feature",
   "geometry": {
    "type": "Point",
    "coordinates": [
     117.89981493,
     -33.28966413
    ]
   },
   "properties": {
    "name": "850 ONE TWENTY FIVE ROAD NAIRIBIN 6350",
    "locID": "LOC000021236843",
    "tech": "NULL",
    "upgrade": "NULL_NA",
    "gnaf_pid": "GAWA_161931843",
    "tech_change_status": "Not Planned"
   }
  },
  {
   "type": "Feature",
   "geometry": {
    "type": "Point",
    "coordinates": [
     117.95516,
     -33.37847
    ]
   },
   "properties": {
    "name": "2037 PETERSON ROAD NAIRIBIN 6350",
    "locID": "LOC000016183967",
    "tech": "NULL",
    "upgrade": "NULL_NA",
    "gnaf_pid": "GAWA_161931907",
    "tech_change_status": "Not Planned"
   }
  },
  {
   "type": "Feature",
   "geometry": {
    "type": "Point",
    "coordinates": [
     117.91268,
     -33.30475
    ]
   },
   "properties": {
    "name": "10976 RABBIT PROOF FENCE ROAD NAIRIBIN 6350",
    "locID": "LOC000073107678",
    "tech": "SATELLITE",
    "upgrade": "NULL_NA",
    "gnaf_pid": "GAWA_161931962",
    "tech_change_status": "Not Planned"
   }
  },
  {
   "type": "Feature",
   "geometry": {
    "type": "Point",
    "coordinates": [
     117.93242,
     -33.32782
    ]
   },
   "properties": {
    "name": "11198 RABBIT PROOF FENCE ROAD NAIRIBIN 6350",
    "locID": "LOC000107543485",
    "tech": "NULL",
    "upgrade": "NULL_NA",
    "gnaf_pid": "GAWA_161931963",
    "tech_change_status": "Not Planned"
   }
  },
  {
   "type": "Feature",
   "geometry": {
    "type": "Point",
    "coordinates": [
     117.855459,
     -33.331109
    ]
   },
   "properties": {
    "name": "978 WISHBONE ROAD NAIRIBIN 6350",
    "locID": "LOC000061420048",
    "tech": "NULL",
    "upgrade": "NULL_NA",
    "gnaf_pid": "GAWA_161932500",
    "tech_change_status": "Not Planned"
   }
  },
  {
   "type": "Feature",
   "geometry": {
    "type": "Point",
    "coordinates": [
     117.88173,
     -33.3226
    ]
   },
   "properties": {
    "name": "1261 ONE TWENTY NINE ROAD NAIRIBIN 6350",
    "locID": "LOC000011978826",
    "tech": "NULL",
    "upgrade": "NULL_NA",
    "gnaf_pid": "GAWA_161993700",
    "tech_change_status": "Not Planned"
   }
  },
  {
   "type": "Feature",
   "geometry": {
    "type": "Point",
    "coordinates": [
     117.90838,
     -33.33734
    ]
   },
   "properties": {
    "name": "1494 ONE TWENTY NINE ROAD NAIRIBIN 6350",
    "locID": "LOC000081023729",
    "tech": "NULL",
    "upgrade": "NULL_NA",
    "gnaf_pid": "GAWA_161993701",
    "tech_change_status": "Not Planned"
   }
  },
  {
   "type": "Feature",
   "geometry": {
    "type": "Point",
    "coordinates": [
     117.92182733,
     -33.34365672
    ]
   },
   "properties": {
    "name": "1590 ONE TWENTY NINE ROAD NAIRIBIN 6350",
    "locID": "LOC000049467311",
    "tech": "NULL",
    "upgrade": "NULL_NA",
    "gnaf_pid": "GAWA_161993702",
    "tech_change_status": "Not Planned"
   }
  },
  {
   "type": "Feature",
   "geometry": {
    "type": "Point",
    "coordinates": [
     117.9206,
     -33.35714
    ]
   },
   "properties": {
    "name": "1592 ONE TWENTY NINE ROAD NAIRIBIN 6350",
    "locID": "LOC000067025348",
    "tech": "NULL",
    "upgrade": "NULL_NA",
    "gnaf_pid": "GAWA_161993703",
    "tech_change_status": "Not Planned"
   }
  },
  {
   "type": "Feature",
   "geometry": {
    "type": "Point",
    "coordinates": [
     117.95774762,
     -33.34398112
    ]
   },
   "properties": {
    "name": "2062 ONE TWENTY NINE ROAD NAIRIBIN 6350",
    "locID": "LOC000076715326",
    "tech": "NULL",
    "upgrade": "NULL_NA",
    "gnaf_pid": "GAWA_161993704",
    "tech_change_status": "Not Planned"
   }
  },
  {
   "type": "Feature",
   "geometry": {
    "type": "Point",
    "coordinates": [
     117.98998,
     -33.346915
    ]
   },
   "properties": {
    "name": "2288 ONE TWENTY NINE ROAD NAIRIBIN 6350",
    "locID": "LOC000056704043",
    "tech": "NULL",
    "upgrade": "NULL_NA",
    "gnaf_pid": "GAWA_161993706",
    "tech_change_status": "Not Planned"
   }
  },
  {
   "type": "Feature",
   "geometry": {
    "type": "Point",
    "coordinates": [
     117.96431325,
     -33.31528622
    ]
   },
   "properties": {
    "name": "LOT 11 STANLEY HILL ROAD NAIRIBIN 6350",
    "locID": "LOC000133168825",
    "tech": "NULL",
    "upgrade": "NULL_NA",
    "gnaf_pid": "GAWA_718221280",
    "tech_change_status": "Not Planned"
   }
  }
 ]
}