{
 "type": "FeatureCollection",
 "generated": "2024-07-07T21:35:01.271225",
 "suburb": "NANUTARRA",
 "features": [
  {
   "type": "Feature",
   "geometry": {
    "type": "Point",
    "coordinates": [
     115.50082252,
     -22.54324852
    ]
   },
   "properties": {
    "name": "LOT 1 NORTH WEST COASTAL HIGHWAY NANUTARRA 6751",
    "locID": "LOC000109561230",
    "tech": "SATELLITE",
    "upgrade": "NULL_NA",
    "gnaf_pid": "GAWA_148291964",
    "tech_change_status": "Not Planned"
   }
  },
  {
   "type": "Feature",
   "geometry": {
    "type": "Point",
    "coordinates": [
     115.61729465,
     -22.36288232
    ]
   },
   "properties": {
    "name": "LOT 217 NORTH WEST COASTAL HIGHWAY NANUTARRA 6751",
    "locID": "LOC000190159770",
    "tech": "SATELLITE",
    "upgrade": "NULL_NA",
    "gnaf_pid": "GAWA_163153709",
    "tech_change_status": "Not Planned"
   }
  },
  {
   "type": "Feature",
   "geometry": {
    "type": "Point",
    "coordinates": [
     115.69005771,
     -22.53019734
    ]
   },
   "properties": {
    "name": "155 NORTH WEST COASTAL HIGHWAY NANUTARRA 6751",
    "locID": "LOC000190159770",
    "tech": "SATELLITE",
    "upgrade": "NULL_NA",
    "gnaf_pid": "GAWA_718486127",
    "tech_change_status": "Not Planned"
   }
  }
 ]
}