{
 "type": "FeatureCollection",
 "generated": "2023-11-12T17:36:28.824929",
 "suburb": "NANUTARRA",
 "features": [
  {
   "type": "Feature",
   "geometry": {
    "type": "Point",
    "coordinates": [
     115.50082252,
     -22.54324852
    ]
   },
   "properties": {
    "name": "LOT 1 NORTH WEST COASTAL HIGHWAY NANUTARRA 6751",
    "locID": "LOC000109561230",
    "tech": "SATELLITE",
    "upgrade": "NULL_NA",
    "gnaf_pid": "GAWA_148291964"
   }
  },
  {
   "type": "Feature",
   "geometry": {
    "type": "Point",
    "coordinates": [
     115.55407906,
     -22.72579514
    ]
   },
   "properties": {
    "name": "LOT 186 NORTH WEST COASTAL HIGHWAY NANUTARRA 6751",
    "locID": "ChIJresMdtRF2isR7bCJ8HstXCQ",
    "tech": "FTTP",
    "upgrade": "UNKNOWN",
    "gnaf_pid": "GAWA_163153708"
   }
  },
  {
   "type": "Feature",
   "geometry": {
    "type": "Point",
    "coordinates": [
     115.61729465,
     -22.36288232
    ]
   },
   "properties": {
    "name": "LOT 217 NORTH WEST COASTAL HIGHWAY NANUTARRA 6751",
    "locID": "LOC000190159770",
    "tech": "SATELLITE",
    "upgrade": "NULL_NA",
    "gnaf_pid": "GAWA_163153709"
   }
  },
  {
   "type": "Feature",
   "geometry": {
    "type": "Point",
    "coordinates": [
     115.5006131,
     -22.53951722
    ]
   },
   "properties": {
    "name": "LOT 4 NORTH WEST COASTAL HIGHWAY NANUTARRA 6751",
    "locID": "ChIJ-0K9aGxw-isRhn6RN1RM9b4",
    "tech": "SATELLITE",
    "upgrade": "UNKNOWN",
    "gnaf_pid": "GAWA_163153710"
   }
  },
  {
   "type": "Feature",
   "geometry": {
    "type": "Point",
    "coordinates": [
     115.50353687,
     -22.54181879
    ]
   },
   "properties": {
    "name": "LOT 5 NORTH WEST COASTAL HIGHWAY NANUTARRA 6751",
    "locID": "Ei81IE4gVyBDb2FzdGFsIEh3eSwgTmFudXRhcnJhIFdBIDY3NTEsIEF1c3RyYWxpYSIwEi4KFAoSCdEO58lscPorEbVdd3VF8aYsEAUqFAoSCQMmddN9r_UrEQsfwXikWG3-",
    "tech": "SATELLITE",
    "upgrade": "UNKNOWN",
    "gnaf_pid": "GAWA_163153711"
   }
  },
  {
   "type": "Feature",
   "geometry": {
    "type": "Point",
    "coordinates": [
     115.69005771,
     -22.53019734
    ]
   },
   "properties": {
    "name": "155 NORTH WEST COASTAL HIGHWAY NANUTARRA 6751",
    "locID": "LOC000190159770",
    "tech": "SATELLITE",
    "upgrade": "NULL_NA",
    "gnaf_pid": "GAWA_718486127"
   }
  }
 ]
}