{
 "type": "FeatureCollection",
 "generated": "2024-09-06T21:11:57.058717",
 "suburb": "ULARRING",
 "features": [
  {
   "type": "Feature",
   "geometry": {
    "type": "Point",
    "coordinates": [
     119.46834926,
     -29.76202631
    ]
   },
   "properties": {
    "name": "LOT 52 BULLFINCH-EVANSTON ROAD ULARRING 6436",
    "locID": "LOC000133338422",
    "tech": "SATELLITE",
    "upgrade": "NULL_NA",
    "gnaf_pid": "GAWA_161530217",
    "tech_change_status": "Not Planned"
   }
  },
  {
   "type": "Feature",
   "geometry": {
    "type": "Point",
    "coordinates": [
     119.46729505,
     -29.76154699
    ]
   },
   "properties": {
    "name": "LOT 53 BULLFINCH-EVANSTON ROAD ULARRING 6436",
    "locID": "LOC000133338433",
    "tech": "SATELLITE",
    "upgrade": "NULL_NA",
    "gnaf_pid": "GAWA_162776315",
    "tech_change_status": "Not Planned"
   }
  }
 ]
}