{
 "type": "FeatureCollection",
 "generated": "2023-12-02T04:03:20.793799",
 "suburb": "ULARRING",
 "features": [
  {
   "type": "Feature",
   "geometry": {
    "type": "Point",
    "coordinates": [
     119.46834926,
     -29.76202631
    ]
   },
   "properties": {
    "name": "LOT 52 BULLFINCH-EVANSTON ROAD ULARRING 6436",
    "locID": "LOC000133338422",
    "tech": "SATELLITE",
    "upgrade": "NULL_NA",
    "gnaf_pid": "GAWA_161530217"
   }
  },
  {
   "type": "Feature",
   "geometry": {
    "type": "Point",
    "coordinates": [
     119.46729505,
     -29.76154699
    ]
   },
   "properties": {
    "name": "LOT 53 BULLFINCH-EVANSTON ROAD ULARRING 6436",
    "locID": "LOC000133338433",
    "tech": "SATELLITE",
    "upgrade": "NULL_NA",
    "gnaf_pid": "GAWA_162776315"
   }
  },
  {
   "type": "Feature",
   "geometry": {
    "type": "Point",
    "coordinates": [
     120.62254802,
     -29.59626418
    ]
   },
   "properties": {
    "name": "153 RIVERINA-SNAKE HILL ROAD ULARRING 6436",
    "locID": "ChIJQ3RYd03HsysRosX9bXGGPdM",
    "tech": "SATELLITE",
    "upgrade": "UNKNOWN",
    "gnaf_pid": "GAWA_162988555"
   }
  },
  {
   "type": "Feature",
   "geometry": {
    "type": "Point",
    "coordinates": [
     120.62254802,
     -29.59626418
    ]
   },
   "properties": {
    "name": "29 RIVERINA-SNAKE HILL ROAD ULARRING 6436",
    "locID": "ChIJQ3RYd03HsysROo9gwvRDnSg",
    "tech": "SATELLITE",
    "upgrade": "UNKNOWN",
    "gnaf_pid": "GAWA_162988556"
   }
  }
 ]
}