{
 "type": "FeatureCollection",
 "generated": "2023-10-26T09:57:58.511394",
 "suburb": "WALYUNGA NATIONAL PARK",
 "features": [
  {
   "type": "Feature",
   "geometry": {
    "type": "Point",
    "coordinates": [
     116.06532121,
     -31.72253949
    ]
   },
   "properties": {
    "name": "LOT 10491 WALYUNGA ROAD WALYUNGA NATIONAL PARK 6084",
    "locID": "EjZXYWx5dW5nYSBSZCwgV2FseXVuZ2EgTmF0aW9uYWwgUGFyayBXQSA2MDg0LCBBdXN0cmFsaWEiLiosChQKEgllcb6Vj8oyKhGVJxQD-E5ORRIUChIJY6-ftOfKMioR4CXfNbXwBAU",
    "tech": "SATELLITE",
    "upgrade": "UNKNOWN",
    "gnaf_pid": "GAWA_163088649"
   }
  },
  {
   "type": "Feature",
   "geometry": {
    "type": "Point",
    "coordinates": [
     116.10058342,
     -31.70073732
    ]
   },
   "properties": {
    "name": "LOT 8439 WALYUNGA ROAD WALYUNGA NATIONAL PARK 6084",
    "locID": "EjZXYWx5dW5nYSBSZCwgV2FseXVuZ2EgTmF0aW9uYWwgUGFyayBXQSA2MDg0LCBBdXN0cmFsaWEiLiosChQKEgllcb6Vj8oyKhGVJxQD-E5ORRIUChIJY6-ftOfKMioR4CXfNbXwBAU",
    "tech": "SATELLITE",
    "upgrade": "UNKNOWN",
    "gnaf_pid": "GAWA_163088650"
   }
  },
  {
   "type": "Feature",
   "geometry": {
    "type": "Point",
    "coordinates": [
     116.05445252,
     -31.73373491
    ]
   },
   "properties": {
    "name": "LOT 8718 WALYUNGA ROAD WALYUNGA NATIONAL PARK 6084",
    "locID": "EjZXYWx5dW5nYSBSZCwgV2FseXVuZ2EgTmF0aW9uYWwgUGFyayBXQSA2MDg0LCBBdXN0cmFsaWEiLiosChQKEgllcb6Vj8oyKhGVJxQD-E5ORRIUChIJY6-ftOfKMioR4CXfNbXwBAU",
    "tech": "SATELLITE",
    "upgrade": "UNKNOWN",
    "gnaf_pid": "GAWA_163088651"
   }
  }
 ]
}