{
 "type": "FeatureCollection",
 "generated": "2024-01-23T10:00:09.151892",
 "suburb": "WILGARRUP",
 "features": [
  {
   "type": "Feature",
   "geometry": {
    "type": "Point",
    "coordinates": [
     116.23264517,
     -34.17143935
    ]
   },
   "properties": {
    "name": "LOT 2340 YARRI ROAD WILGARRUP 6258",
    "locID": "EiZZYXJyaSBSZCwgV2lsZ2FycnVwIFdBIDYyNTgsIEF1c3RyYWxpYSIuKiwKFAoSCT2oTVX2bzAqEdBUr3D51GT8EhQKEgnhDc0PNG8wKhHw8XkkOPYABA",
    "tech": "SATELLITE",
    "upgrade": "UNKNOWN",
    "gnaf_pid": "GAWA_161898083"
   }
  },
  {
   "type": "Feature",
   "geometry": {
    "type": "Point",
    "coordinates": [
     116.20464112,
     -34.13709672
    ]
   },
   "properties": {
    "name": "26538 SOUTH WESTERN HIGHWAY WILGARRUP 6258",
    "locID": "LOC000111423262",
    "tech": "SATELLITE",
    "upgrade": "NULL_NA",
    "gnaf_pid": "GAWA_163384618"
   }
  },
  {
   "type": "Feature",
   "geometry": {
    "type": "Point",
    "coordinates": [
     116.21496229,
     -34.14260328
    ]
   },
   "properties": {
    "name": "26547 SOUTH WESTERN HIGHWAY WILGARRUP 6258",
    "locID": "LOC000142443033",
    "tech": "SATELLITE",
    "upgrade": "NULL_NA",
    "gnaf_pid": "GAWA_163384619"
   }
  },
  {
   "type": "Feature",
   "geometry": {
    "type": "Point",
    "coordinates": [
     116.19556697,
     -34.14391016
    ]
   },
   "properties": {
    "name": "26582 SOUTH WESTERN HIGHWAY WILGARRUP 6258",
    "locID": "LOC000111848429",
    "tech": "SATELLITE",
    "upgrade": "NULL_NA",
    "gnaf_pid": "GAWA_163384620"
   }
  },
  {
   "type": "Feature",
   "geometry": {
    "type": "Point",
    "coordinates": [
     116.21261396,
     -34.14870995
    ]
   },
   "properties": {
    "name": "26695 SOUTH WESTERN HIGHWAY WILGARRUP 6258",
    "locID": "ChIJvV5OfplvMCoRELUqe3hi6Bo",
    "tech": "SATELLITE",
    "upgrade": "UNKNOWN",
    "gnaf_pid": "GAWA_163384621"
   }
  },
  {
   "type": "Feature",
   "geometry": {
    "type": "Point",
    "coordinates": [
     116.17625772,
     -34.1351813
    ]
   },
   "properties": {
    "name": "293 WILGARRUP ROAD WILGARRUP 6258",
    "locID": "LOC000113607012",
    "tech": "SATELLITE",
    "upgrade": "NULL_NA",
    "gnaf_pid": "GAWA_163386082"
   }
  },
  {
   "type": "Feature",
   "geometry": {
    "type": "Point",
    "coordinates": [
     116.17313934,
     -34.13919834
    ]
   },
   "properties": {
    "name": "355 WILGARRUP ROAD WILGARRUP 6258",
    "locID": "LOC000112333062",
    "tech": "SATELLITE",
    "upgrade": "NULL_NA",
    "gnaf_pid": "GAWA_163386083"
   }
  },
  {
   "type": "Feature",
   "geometry": {
    "type": "Point",
    "coordinates": [
     116.16916187,
     -34.13437324
    ]
   },
   "properties": {
    "name": "357 WILGARRUP ROAD WILGARRUP 6258",
    "locID": "LOC000110658121",
    "tech": "SATELLITE",
    "upgrade": "NULL_NA",
    "gnaf_pid": "GAWA_163386084"
   }
  },
  {
   "type": "Feature",
   "geometry": {
    "type": "Point",
    "coordinates": [
     116.22345792,
     -34.13135483
    ]
   },
   "properties": {
    "name": "33 MERSEA ROAD WILGARRUP 6258",
    "locID": "ChIJswbVm3tvMCoR3OR-HtNJFv4",
    "tech": "SATELLITE",
    "upgrade": "UNKNOWN",
    "gnaf_pid": "GAWA_721198394"
   }
  }
 ]
}