{
 "type": "FeatureCollection",
 "generated": "2024-03-02T03:03:41.204228",
 "suburb": "WILGARRUP",
 "features": [
  {
   "type": "Feature",
   "geometry": {
    "type": "Point",
    "coordinates": [
     116.20464112,
     -34.13709672
    ]
   },
   "properties": {
    "name": "26538 SOUTH WESTERN HIGHWAY WILGARRUP 6258",
    "locID": "LOC000111423262",
    "tech": "SATELLITE",
    "upgrade": "NULL_NA",
    "gnaf_pid": "GAWA_163384618"
   }
  },
  {
   "type": "Feature",
   "geometry": {
    "type": "Point",
    "coordinates": [
     116.21496229,
     -34.14260328
    ]
   },
   "properties": {
    "name": "26547 SOUTH WESTERN HIGHWAY WILGARRUP 6258",
    "locID": "LOC000142443033",
    "tech": "SATELLITE",
    "upgrade": "NULL_NA",
    "gnaf_pid": "GAWA_163384619"
   }
  },
  {
   "type": "Feature",
   "geometry": {
    "type": "Point",
    "coordinates": [
     116.19556697,
     -34.14391016
    ]
   },
   "properties": {
    "name": "26582 SOUTH WESTERN HIGHWAY WILGARRUP 6258",
    "locID": "LOC000111848429",
    "tech": "SATELLITE",
    "upgrade": "NULL_NA",
    "gnaf_pid": "GAWA_163384620"
   }
  },
  {
   "type": "Feature",
   "geometry": {
    "type": "Point",
    "coordinates": [
     116.17625772,
     -34.1351813
    ]
   },
   "properties": {
    "name": "293 WILGARRUP ROAD WILGARRUP 6258",
    "locID": "LOC000113607012",
    "tech": "SATELLITE",
    "upgrade": "NULL_NA",
    "gnaf_pid": "GAWA_163386082"
   }
  },
  {
   "type": "Feature",
   "geometry": {
    "type": "Point",
    "coordinates": [
     116.17313934,
     -34.13919834
    ]
   },
   "properties": {
    "name": "355 WILGARRUP ROAD WILGARRUP 6258",
    "locID": "LOC000112333062",
    "tech": "SATELLITE",
    "upgrade": "NULL_NA",
    "gnaf_pid": "GAWA_163386083"
   }
  },
  {
   "type": "Feature",
   "geometry": {
    "type": "Point",
    "coordinates": [
     116.16916187,
     -34.13437324
    ]
   },
   "properties": {
    "name": "357 WILGARRUP ROAD WILGARRUP 6258",
    "locID": "LOC000110658121",
    "tech": "SATELLITE",
    "upgrade": "NULL_NA",
    "gnaf_pid": "GAWA_163386084"
   }
  }
 ]
}