{
 "type": "FeatureCollection",
 "generated": "2024-09-11T11:54:38.615591",
 "suburb": "TUGGERANONG",
 "features": [
  {
   "type": "Feature",
   "geometry": {
    "type": "Point",
    "coordinates": [
     149.13384302,
     -35.56973825
    ]
   },
   "properties": {
    "name": "7860 MONARO HIGHWAY TUGGERANONG 2900",
    "locID": "LOC000111852383",
    "tech": "SATELLITE",
    "upgrade": "NULL_NA",
    "gnaf_pid": "GAACT715295959",
    "tech_change_status": "Not Planned"
   }
  },
  {
   "type": "Feature",
   "geometry": {
    "type": "Point",
    "coordinates": [
     149.14396548,
     -35.40513812
    ]
   },
   "properties": {
    "name": "1 ISABELLA DRIVE TUGGERANONG 2900",
    "locID": "LOC000110893751",
    "tech": "NULL",
    "upgrade": "NULL_NA",
    "gnaf_pid": "GAACT717122503",
    "tech_change_status": "Not Planned"
   }
  },
  {
   "type": "Feature",
   "geometry": {
    "type": "Point",
    "coordinates": [
     149.09525248,
     -35.3826563
    ]
   },
   "properties": {
    "name": "400 ATHLLON DRIVE TUGGERANONG 2900",
    "locID": "LOC000113836236",
    "tech": "FTTP",
    "upgrade": "NULL_NA",
    "gnaf_pid": "GAACT720110110"
   }
  }
 ]
}