{
 "type": "FeatureCollection",
 "generated": "2024-04-29T14:22:21.038115",
 "suburb": "BOLLARDS LAGOON",
 "features": [
  {
   "type": "Feature",
   "geometry": {
    "type": "Point",
    "coordinates": [
     140.85406787,
     -28.98624031
    ]
   },
   "properties": {
    "name": "10349 RIECKS ROAD BOLLARDS LAGOON 5731",
    "locID": "LOC000148242051",
    "tech": "SATELLITE",
    "upgrade": "NULL_NA",
    "gnaf_pid": "GASA_425630151"
   }
  }
 ]
}