{
 "type": "FeatureCollection",
 "generated": "2023-07-17T15:31:41.908720",
 "suburb": "BOLLARDS LAGOON",
 "features": [
  {
   "type": "Feature",
   "geometry": {
    "type": "Point",
    "coordinates": [
     140.85406787,
     -28.98624031
    ]
   },
   "properties": {
    "name": "10349 RIECKS ROAD BOLLARDS LAGOON 5731",
    "locID": "LOC000148242051",
    "tech": "SATELLITE",
    "upgrade": "NULL_NA",
    "gnaf_pid": "GASA_425630151"
   }
  },
  {
   "type": "Feature",
   "geometry": {
    "type": "Point",
    "coordinates": [
     140.920303,
     -28.998041
    ]
   },
   "properties": {
    "name": "11046 RIECKS ROAD BOLLARDS LAGOON 5731",
    "locID": "ChIJMb-f2S1C9GoRrUYdrm4JqJU",
    "tech": "SATELLITE",
    "upgrade": "UNKNOWN",
    "gnaf_pid": "GASA_719966671"
   }
  }
 ]
}