{
 "type": "FeatureCollection",
 "generated": "2024-10-08T17:37:58.553004",
 "suburb": "CARCUMA",
 "features": [
  {
   "type": "Feature",
   "geometry": {
    "type": "Point",
    "coordinates": [
     140.04958942,
     -35.53411888
    ]
   },
   "properties": {
    "name": "LOT 8 JABUK SOUTH ROAD CARCUMA 5301",
    "locID": "LOC000114111430",
    "tech": "SATELLITE",
    "upgrade": "NULL_NA",
    "gnaf_pid": "GASA_424309170",
    "tech_change_status": "Not Planned"
   }
  },
  {
   "type": "Feature",
   "geometry": {
    "type": "Point",
    "coordinates": [
     140.0238004,
     -35.57364727
    ]
   },
   "properties": {
    "name": "2348 TAURAGAT WELL ROAD CARCUMA 5301",
    "locID": "LOC000115058552",
    "tech": "SATELLITE",
    "upgrade": "WIRELESS",
    "gnaf_pid": "GASA_424709329",
    "tech_change_status": "Eligible to Order",
    "program_type": "Fixed Wireless and Satellite Upgrade Program",
    "target_eligibility_quarter": "Dec 2024"
   }
  },
  {
   "type": "Feature",
   "geometry": {
    "type": "Point",
    "coordinates": [
     140.04652676,
     -35.57490982
    ]
   },
   "properties": {
    "name": "2561 TAURAGAT WELL ROAD CARCUMA 5301",
    "locID": "LOC000114407886",
    "tech": "NULL",
    "upgrade": "NULL_NA",
    "gnaf_pid": "GASA_424709330",
    "tech_change_status": "Not Planned"
   }
  },
  {
   "type": "Feature",
   "geometry": {
    "type": "Point",
    "coordinates": [
     140.07500702,
     -35.5681069
    ]
   },
   "properties": {
    "name": "2836 TAURAGAT WELL ROAD CARCUMA 5301",
    "locID": "LOC000114216480",
    "tech": "NULL",
    "upgrade": "NULL_NA",
    "gnaf_pid": "GASA_424709331",
    "tech_change_status": "Not Planned"
   }
  },
  {
   "type": "Feature",
   "geometry": {
    "type": "Point",
    "coordinates": [
     140.12334734,
     -35.5439302
    ]
   },
   "properties": {
    "name": "3357 TAURAGAT WELL ROAD CARCUMA 5301",
    "locID": "LOC000114176032",
    "tech": "NULL",
    "upgrade": "NULL_NA",
    "gnaf_pid": "GASA_424709332",
    "tech_change_status": "Not Planned"
   }
  },
  {
   "type": "Feature",
   "geometry": {
    "type": "Point",
    "coordinates": [
     140.08178634,
     -35.6197093
    ]
   },
   "properties": {
    "name": "LOT 23 TAURAGAT WELL ROAD CARCUMA 5301",
    "locID": "LOC000130807831",
    "tech": "WIRELESS",
    "upgrade": "NULL_NA",
    "gnaf_pid": "GASA_425725165",
    "tech_change_status": "Not Planned",
    "program_type": "Fixed Wireless and Satellite Upgrade Program",
    "target_eligibility_quarter": "Dec 2024"
   }
  },
  {
   "type": "Feature",
   "geometry": {
    "type": "Point",
    "coordinates": [
     140.03724793,
     -35.55699448
    ]
   },
   "properties": {
    "name": "LOT 6 TAURAGAT WELL ROAD CARCUMA 5301",
    "locID": "LOC000114216480",
    "tech": "NULL",
    "upgrade": "NULL_NA",
    "gnaf_pid": "GASA_425725166",
    "tech_change_status": "Not Planned"
   }
  }
 ]
}