{
 "type": "FeatureCollection",
 "generated": "2023-07-17T19:03:21.817818",
 "suburb": "CARCUMA",
 "features": [
  {
   "type": "Feature",
   "geometry": {
    "type": "Point",
    "coordinates": [
     140.04958942,
     -35.53411888
    ]
   },
   "properties": {
    "name": "LOT 8 JABUK SOUTH ROAD CARCUMA 5301",
    "locID": "LOC000114111430",
    "tech": "SATELLITE",
    "upgrade": "NULL_NA",
    "gnaf_pid": "GASA_424309170"
   }
  },
  {
   "type": "Feature",
   "geometry": {
    "type": "Point",
    "coordinates": [
     140.07566277,
     -35.52261931
    ]
   },
   "properties": {
    "name": "1451 JABUK SOUTH ROAD CARCUMA 5301",
    "locID": "ChIJiWdVHK4myGoRgNXbs7qycx4",
    "tech": "SATELLITE",
    "upgrade": "UNKNOWN",
    "gnaf_pid": "GASA_424701470"
   }
  },
  {
   "type": "Feature",
   "geometry": {
    "type": "Point",
    "coordinates": [
     140.0238004,
     -35.57364727
    ]
   },
   "properties": {
    "name": "2348 TAURAGAT WELL ROAD CARCUMA 5301",
    "locID": "LOC000115058552",
    "tech": "SATELLITE",
    "upgrade": "NULL_NA",
    "gnaf_pid": "GASA_424709329"
   }
  },
  {
   "type": "Feature",
   "geometry": {
    "type": "Point",
    "coordinates": [
     140.04652676,
     -35.57490982
    ]
   },
   "properties": {
    "name": "2561 TAURAGAT WELL ROAD CARCUMA 5301",
    "locID": "LOC000114407886",
    "tech": "SATELLITE",
    "upgrade": "NULL_NA",
    "gnaf_pid": "GASA_424709330"
   }
  },
  {
   "type": "Feature",
   "geometry": {
    "type": "Point",
    "coordinates": [
     140.07500702,
     -35.5681069
    ]
   },
   "properties": {
    "name": "2836 TAURAGAT WELL ROAD CARCUMA 5301",
    "locID": "LOC000114216480",
    "tech": "SATELLITE",
    "upgrade": "NULL_NA",
    "gnaf_pid": "GASA_424709331"
   }
  },
  {
   "type": "Feature",
   "geometry": {
    "type": "Point",
    "coordinates": [
     140.12334734,
     -35.5439302
    ]
   },
   "properties": {
    "name": "3357 TAURAGAT WELL ROAD CARCUMA 5301",
    "locID": "LOC000114176032",
    "tech": "SATELLITE",
    "upgrade": "NULL_NA",
    "gnaf_pid": "GASA_424709332"
   }
  },
  {
   "type": "Feature",
   "geometry": {
    "type": "Point",
    "coordinates": [
     140.07232853,
     -35.54536328
    ]
   },
   "properties": {
    "name": "1703 JABUK SOUTH ROAD CARCUMA 5301",
    "locID": "ChIJl5hI0fAmyGoRLCd7UQoh11s",
    "tech": "SATELLITE",
    "upgrade": "UNKNOWN",
    "gnaf_pid": "GASA_425189842"
   }
  },
  {
   "type": "Feature",
   "geometry": {
    "type": "Point",
    "coordinates": [
     140.08178634,
     -35.6197093
    ]
   },
   "properties": {
    "name": "LOT 23 TAURAGAT WELL ROAD CARCUMA 5301",
    "locID": "LOC000130807831",
    "tech": "WIRELESS",
    "upgrade": "NULL_NA",
    "gnaf_pid": "GASA_425725165"
   }
  },
  {
   "type": "Feature",
   "geometry": {
    "type": "Point",
    "coordinates": [
     140.03724793,
     -35.55699448
    ]
   },
   "properties": {
    "name": "LOT 6 TAURAGAT WELL ROAD CARCUMA 5301",
    "locID": "LOC000114216480",
    "tech": "SATELLITE",
    "upgrade": "NULL_NA",
    "gnaf_pid": "GASA_425725166"
   }
  }
 ]
}