{
 "type": "FeatureCollection",
 "generated": "2024-09-01T06:43:15.041940",
 "suburb": "CHINBINGINA",
 "features": [
  {
   "type": "Feature",
   "geometry": {
    "type": "Point",
    "coordinates": [
     134.24085559,
     -32.17811205
    ]
   },
   "properties": {
    "name": "LOT 15 CHINBINGINA ROAD CHINBINGINA 5680",
    "locID": "LOC100071951763",
    "tech": "SATELLITE",
    "upgrade": "NULL_NA",
    "gnaf_pid": "GASA_424294400",
    "tech_change_status": "Not Planned"
   }
  },
  {
   "type": "Feature",
   "geometry": {
    "type": "Point",
    "coordinates": [
     134.22976306,
     -32.20761283
    ]
   },
   "properties": {
    "name": "LOT 17 CHINBINGINA ROAD CHINBINGINA 5680",
    "locID": "LOC100071951763",
    "tech": "SATELLITE",
    "upgrade": "NULL_NA",
    "gnaf_pid": "GASA_424294401",
    "tech_change_status": "Not Planned"
   }
  },
  {
   "type": "Feature",
   "geometry": {
    "type": "Point",
    "coordinates": [
     134.17232599,
     -32.22090593
    ]
   },
   "properties": {
    "name": "LOT 38 EYRE HIGHWAY CHINBINGINA 5680",
    "locID": "LOC000148249637",
    "tech": "SATELLITE",
    "upgrade": "NULL_NA",
    "gnaf_pid": "GASA_424300281",
    "tech_change_status": "Not Planned"
   }
  },
  {
   "type": "Feature",
   "geometry": {
    "type": "Point",
    "coordinates": [
     134.17276993,
     -32.20413449
    ]
   },
   "properties": {
    "name": "LOT 5 NUNJI ROAD CHINBINGINA 5680",
    "locID": "LOC100071951763",
    "tech": "SATELLITE",
    "upgrade": "NULL_NA",
    "gnaf_pid": "GASA_721251997",
    "tech_change_status": "Not Planned"
   }
  },
  {
   "type": "Feature",
   "geometry": {
    "type": "Point",
    "coordinates": [
     134.27261192,
     -32.21442187
    ]
   },
   "properties": {
    "name": "LOT 1 NUNJI ROAD CHINBINGINA 5680",
    "locID": "LOC100071951763",
    "tech": "SATELLITE",
    "upgrade": "NULL_NA",
    "gnaf_pid": "GASA_721253726",
    "tech_change_status": "Not Planned"
   }
  }
 ]
}