{
 "type": "FeatureCollection",
 "generated": "2024-07-22T14:44:25.113600",
 "suburb": "FARAWAY HILL",
 "features": [
  {
   "type": "Feature",
   "geometry": {
    "type": "Point",
    "coordinates": [
     139.61758722,
     -33.19008497
    ]
   },
   "properties": {
    "name": "3663 LILYDALE ROAD FARAWAY HILL 5417",
    "locID": "LOC000148249103",
    "tech": "SATELLITE",
    "upgrade": "NULL_NA",
    "gnaf_pid": "GASA_425629426",
    "tech_change_status": "Not Planned"
   }
  },
  {
   "type": "Feature",
   "geometry": {
    "type": "Point",
    "coordinates": [
     139.76300283,
     -33.10844054
    ]
   },
   "properties": {
    "name": "LOT 1 LILYDALE ROAD FARAWAY HILL 5417",
    "locID": "LOC000148249103",
    "tech": "SATELLITE",
    "upgrade": "NULL_NA",
    "gnaf_pid": "GASA_719185251",
    "tech_change_status": "Not Planned"
   }
  }
 ]
}