{
 "type": "FeatureCollection",
 "generated": "2024-04-10T19:29:31.519795",
 "suburb": "FITZGERALD BAY",
 "features": [
  {
   "type": "Feature",
   "geometry": {
    "type": "Point",
    "coordinates": [
     137.75267809,
     -32.91215833
    ]
   },
   "properties": {
    "name": "10 BLACK OAK COVE FITZGERALD BAY 5601",
    "locID": "LOC000111085623",
    "tech": "SATELLITE",
    "upgrade": "NULL_NA",
    "gnaf_pid": "GASA_424648275"
   }
  },
  {
   "type": "Feature",
   "geometry": {
    "type": "Point",
    "coordinates": [
     137.7528405,
     -32.91204483
    ]
   },
   "properties": {
    "name": "12 BLACK OAK COVE FITZGERALD BAY 5601",
    "locID": "LOC000131578973",
    "tech": "SATELLITE",
    "upgrade": "NULL_NA",
    "gnaf_pid": "GASA_424648276"
   }
  },
  {
   "type": "Feature",
   "geometry": {
    "type": "Point",
    "coordinates": [
     137.7519841,
     -32.9133546
    ]
   },
   "properties": {
    "name": "2 BLACK OAK COVE FITZGERALD BAY 5601",
    "locID": "LOC100078075115",
    "tech": "SATELLITE",
    "upgrade": "NULL_NA",
    "gnaf_pid": "GASA_424648279"
   }
  },
  {
   "type": "Feature",
   "geometry": {
    "type": "Point",
    "coordinates": [
     137.7521153,
     -32.91319438
    ]
   },
   "properties": {
    "name": "4 BLACK OAK COVE FITZGERALD BAY 5601",
    "locID": "LOC100079006717",
    "tech": "SATELLITE",
    "upgrade": "NULL_NA",
    "gnaf_pid": "GASA_424648280"
   }
  },
  {
   "type": "Feature",
   "geometry": {
    "type": "Point",
    "coordinates": [
     137.75239791,
     -32.91290016
    ]
   },
   "properties": {
    "name": "8 BLACK OAK COVE FITZGERALD BAY 5601",
    "locID": "LOC100078075073",
    "tech": "SATELLITE",
    "upgrade": "NULL_NA",
    "gnaf_pid": "GASA_424648281"
   }
  },
  {
   "type": "Feature",
   "geometry": {
    "type": "Point",
    "coordinates": [
     137.777114,
     -32.91260309
    ]
   },
   "properties": {
    "name": "10 FANFLOWER FRONTAGE FITZGERALD BAY 5601",
    "locID": "LOC000131578863",
    "tech": "SATELLITE",
    "upgrade": "NULL_NA",
    "gnaf_pid": "GASA_424649325"
   }
  },
  {
   "type": "Feature",
   "geometry": {
    "type": "Point",
    "coordinates": [
     137.74965061,
     -32.92765017
    ]
   },
   "properties": {
    "name": "12 GULF VIEW DRIVE FITZGERALD BAY 5601",
    "locID": "LOC100079108152",
    "tech": "SATELLITE",
    "upgrade": "NULL_NA",
    "gnaf_pid": "GASA_424649728"
   }
  },
  {
   "type": "Feature",
   "geometry": {
    "type": "Point",
    "coordinates": [
     137.75226145,
     -32.9130461
    ]
   },
   "properties": {
    "name": "6 BLACK OAK COVE FITZGERALD BAY 5601",
    "locID": "LOC100078075094",
    "tech": "SATELLITE",
    "upgrade": "NULL_NA",
    "gnaf_pid": "GASA_425301315"
   }
  },
  {
   "type": "Feature",
   "geometry": {
    "type": "Point",
    "coordinates": [
     137.7494947,
     -32.92485603
    ]
   },
   "properties": {
    "name": "2 ISOTOME COVE FITZGERALD BAY 5601",
    "locID": "LOC100071962335",
    "tech": "SATELLITE",
    "upgrade": "NULL_NA",
    "gnaf_pid": "GASA_425509564"
   }
  },
  {
   "type": "Feature",
   "geometry": {
    "type": "Point",
    "coordinates": [
     137.7493259,
     -32.92438613
    ]
   },
   "properties": {
    "name": "4 ISOTOME COVE FITZGERALD BAY 5601",
    "locID": "LOC100071962303",
    "tech": "SATELLITE",
    "upgrade": "NULL_NA",
    "gnaf_pid": "GASA_425509565"
   }
  },
  {
   "type": "Feature",
   "geometry": {
    "type": "Point",
    "coordinates": [
     137.75060621,
     -32.92891534
    ]
   },
   "properties": {
    "name": "2 TWINLEAF COVE FITZGERALD BAY 5601",
    "locID": "LOC100071962446",
    "tech": "SATELLITE",
    "upgrade": "NULL_NA",
    "gnaf_pid": "GASA_425511043"
   }
  },
  {
   "type": "Feature",
   "geometry": {
    "type": "Point",
    "coordinates": [
     137.75043542,
     -32.92866281
    ]
   },
   "properties": {
    "name": "4 TWINLEAF COVE FITZGERALD BAY 5601",
    "locID": "LOC100071962433",
    "tech": "SATELLITE",
    "upgrade": "NULL_NA",
    "gnaf_pid": "GASA_425511044"
   }
  }
 ]
}