{
 "type": "FeatureCollection",
 "generated": "2024-10-08T23:32:07.663595",
 "suburb": "JULANKA HOLDINGS",
 "features": [
  {
   "type": "Feature",
   "geometry": {
    "type": "Point",
    "coordinates": [
     139.54326776,
     -34.87280257
    ]
   },
   "properties": {
    "name": "2223 EAST FRONT ROAD JULANKA HOLDINGS 5238",
    "locID": "LOC000114615831",
    "tech": "WIRELESS",
    "upgrade": "NULL_NA",
    "gnaf_pid": "GASA_424699073",
    "tech_change_status": "Not Planned",
    "program_type": "Fixed Wireless and Satellite Upgrade Program",
    "target_eligibility_quarter": "NA"
   }
  }
 ]
}