{
 "type": "FeatureCollection",
 "generated": "2023-10-22T00:55:10.013575",
 "suburb": "JULANKA HOLDINGS",
 "features": [
  {
   "type": "Feature",
   "geometry": {
    "type": "Point",
    "coordinates": [
     139.54529277,
     -34.87347105
    ]
   },
   "properties": {
    "name": "LOT 3 EAST FRONT ROAD JULANKA HOLDINGS 5238",
    "locID": "ChIJF6rRbhQmuGoRdqNpxvNkZ0k",
    "tech": "WIRELESS",
    "upgrade": "UNKNOWN",
    "gnaf_pid": "GASA_424167975"
   }
  },
  {
   "type": "Feature",
   "geometry": {
    "type": "Point",
    "coordinates": [
     139.54326776,
     -34.87280257
    ]
   },
   "properties": {
    "name": "2223 EAST FRONT ROAD JULANKA HOLDINGS 5238",
    "locID": "LOC000114615831",
    "tech": "WIRELESS",
    "upgrade": "NULL_NA",
    "gnaf_pid": "GASA_424699073"
   }
  },
  {
   "type": "Feature",
   "geometry": {
    "type": "Point",
    "coordinates": [
     139.54413844,
     -34.87264147
    ]
   },
   "properties": {
    "name": "SITE 1, 2223 EAST FRONT ROAD JULANKA HOLDINGS 5238",
    "locID": "ChIJLcUJKBQmuGoRPICc-1v6iNs",
    "tech": "WIRELESS",
    "upgrade": "UNKNOWN",
    "gnaf_pid": "GASA_425581663"
   }
  },
  {
   "type": "Feature",
   "geometry": {
    "type": "Point",
    "coordinates": [
     139.54392834,
     -34.87268227
    ]
   },
   "properties": {
    "name": "SITE 2, 2223 EAST FRONT ROAD JULANKA HOLDINGS 5238",
    "locID": "ChIJLcUJKBQmuGoRPICc-1v6iNs",
    "tech": "WIRELESS",
    "upgrade": "UNKNOWN",
    "gnaf_pid": "GASA_425581664"
   }
  },
  {
   "type": "Feature",
   "geometry": {
    "type": "Point",
    "coordinates": [
     139.54370034,
     -34.87271579
    ]
   },
   "properties": {
    "name": "SITE 3, 2223 EAST FRONT ROAD JULANKA HOLDINGS 5238",
    "locID": "ChIJLcUJKBQmuGoRPICc-1v6iNs",
    "tech": "WIRELESS",
    "upgrade": "UNKNOWN",
    "gnaf_pid": "GASA_425581665"
   }
  },
  {
   "type": "Feature",
   "geometry": {
    "type": "Point",
    "coordinates": [
     139.54286782,
     -34.87287935
    ]
   },
   "properties": {
    "name": "SITE 4, 2223 EAST FRONT ROAD JULANKA HOLDINGS 5238",
    "locID": "ChIJLcUJKBQmuGoRPICc-1v6iNs",
    "tech": "WIRELESS",
    "upgrade": "UNKNOWN",
    "gnaf_pid": "GASA_425581666"
   }
  },
  {
   "type": "Feature",
   "geometry": {
    "type": "Point",
    "coordinates": [
     139.54271002,
     -34.87290956
    ]
   },
   "properties": {
    "name": "SITE 5, 2223 EAST FRONT ROAD JULANKA HOLDINGS 5238",
    "locID": "ChIJLcUJKBQmuGoRPICc-1v6iNs",
    "tech": "WIRELESS",
    "upgrade": "UNKNOWN",
    "gnaf_pid": "GASA_425581667"
   }
  },
  {
   "type": "Feature",
   "geometry": {
    "type": "Point",
    "coordinates": [
     139.54254969,
     -34.87293735
    ]
   },
   "properties": {
    "name": "SITE 6, 2223 EAST FRONT ROAD JULANKA HOLDINGS 5238",
    "locID": "ChIJLcUJKBQmuGoRPICc-1v6iNs",
    "tech": "WIRELESS",
    "upgrade": "UNKNOWN",
    "gnaf_pid": "GASA_425581668"
   }
  },
  {
   "type": "Feature",
   "geometry": {
    "type": "Point",
    "coordinates": [
     139.54239087,
     -34.87296655
    ]
   },
   "properties": {
    "name": "SITE 7, 2223 EAST FRONT ROAD JULANKA HOLDINGS 5238",
    "locID": "ChIJLcUJKBQmuGoRPICc-1v6iNs",
    "tech": "WIRELESS",
    "upgrade": "UNKNOWN",
    "gnaf_pid": "GASA_425581669"
   }
  },
  {
   "type": "Feature",
   "geometry": {
    "type": "Point",
    "coordinates": [
     139.54217417,
     -34.87301142
    ]
   },
   "properties": {
    "name": "SITE 8, 2223 EAST FRONT ROAD JULANKA HOLDINGS 5238",
    "locID": "ChIJLcUJKBQmuGoRPICc-1v6iNs",
    "tech": "WIRELESS",
    "upgrade": "UNKNOWN",
    "gnaf_pid": "GASA_425581670"
   }
  },
  {
   "type": "Feature",
   "geometry": {
    "type": "Point",
    "coordinates": [
     139.54332717,
     -34.87516777
    ]
   },
   "properties": {
    "name": "SITE 9, 2223 EAST FRONT ROAD JULANKA HOLDINGS 5238",
    "locID": "ChIJLcUJKBQmuGoRPICc-1v6iNs",
    "tech": "WIRELESS",
    "upgrade": "UNKNOWN",
    "gnaf_pid": "GASA_720849679"
   }
  }
 ]
}