{
 "type": "FeatureCollection",
 "generated": "2024-05-22T16:40:47.724158",
 "suburb": "JULANKA HOLDINGS",
 "features": [
  {
   "type": "Feature",
   "geometry": {
    "type": "Point",
    "coordinates": [
     139.54326776,
     -34.87280257
    ]
   },
   "properties": {
    "name": "2223 EAST FRONT ROAD JULANKA HOLDINGS 5238",
    "locID": "LOC000114615831",
    "tech": "WIRELESS",
    "upgrade": "NULL_NA",
    "gnaf_pid": "GASA_424699073"
   }
  }
 ]
}