{
 "type": "FeatureCollection",
 "generated": "2023-10-22T02:10:10.380708",
 "suburb": "LAKE ALEXANDRINA",
 "features": [
  {
   "type": "Feature",
   "geometry": {
    "type": "Point",
    "coordinates": [
     139.15503179,
     -35.32437714
    ]
   },
   "properties": {
    "name": "198 WEST CREEK ROAD LAKE ALEXANDRINA 5259",
    "locID": "ChIJ94Ltve4ct2oRAKBFPSJO9-c",
    "tech": "WIRELESS",
    "upgrade": "UNKNOWN",
    "gnaf_pid": "GASA_424905427"
   }
  },
  {
   "type": "Feature",
   "geometry": {
    "type": "Point",
    "coordinates": [
     139.23220962,
     -35.32056883
    ]
   },
   "properties": {
    "name": "LOT 1221 LAKE RESERVE ROAD LAKE ALEXANDRINA 5259",
    "locID": "Ei5MYWtlIFJlc2VydmUgUmQsIE11bGd1bmRhd2EgU0EgNTI1NSwgQXVzdHJhbGlhIi4qLAoUChIJL4BAK4UEt2oRBFvdx4-Jvu8SFAoSCRHdEbmhBLdqEYALj2JUNgME",
    "tech": "SATELLITE",
    "upgrade": "UNKNOWN",
    "gnaf_pid": "GASA_425509688"
   }
  },
  {
   "type": "Feature",
   "geometry": {
    "type": "Point",
    "coordinates": [
     139.18131163,
     -35.33396536
    ]
   },
   "properties": {
    "name": "LOT 1406 WEST CREEK ROAD LAKE ALEXANDRINA 5259",
    "locID": "LOC000113009891",
    "tech": "SATELLITE",
    "upgrade": "NULL_NA",
    "gnaf_pid": "GASA_720300201"
   }
  },
  {
   "type": "Feature",
   "geometry": {
    "type": "Point",
    "coordinates": [
     139.20037889,
     -35.33058053
    ]
   },
   "properties": {
    "name": "LOT 1286 WEST CREEK ROAD LAKE ALEXANDRINA 5259",
    "locID": "LOC000113009891",
    "tech": "SATELLITE",
    "upgrade": "NULL_NA",
    "gnaf_pid": "GASA_720300362"
   }
  },
  {
   "type": "Feature",
   "geometry": {
    "type": "Point",
    "coordinates": [
     139.19088879,
     -35.32374555
    ]
   },
   "properties": {
    "name": "LOT 1283 WEST CREEK ROAD LAKE ALEXANDRINA 5259",
    "locID": "LOC000113009891",
    "tech": "SATELLITE",
    "upgrade": "NULL_NA",
    "gnaf_pid": "GASA_720304189"
   }
  }
 ]
}