{
 "type": "FeatureCollection",
 "generated": "2024-06-14T12:28:13.883898",
 "suburb": "LAKE ALEXANDRINA",
 "features": [
  {
   "type": "Feature",
   "geometry": {
    "type": "Point",
    "coordinates": [
     139.18131163,
     -35.33396536
    ]
   },
   "properties": {
    "name": "LOT 1406 WEST CREEK ROAD LAKE ALEXANDRINA 5259",
    "locID": "LOC000113009891",
    "tech": "SATELLITE",
    "upgrade": "NULL_NA",
    "gnaf_pid": "GASA_720300201"
   }
  },
  {
   "type": "Feature",
   "geometry": {
    "type": "Point",
    "coordinates": [
     139.20037889,
     -35.33058053
    ]
   },
   "properties": {
    "name": "LOT 1286 WEST CREEK ROAD LAKE ALEXANDRINA 5259",
    "locID": "LOC000113009891",
    "tech": "SATELLITE",
    "upgrade": "NULL_NA",
    "gnaf_pid": "GASA_720300362"
   }
  },
  {
   "type": "Feature",
   "geometry": {
    "type": "Point",
    "coordinates": [
     139.19088879,
     -35.32374555
    ]
   },
   "properties": {
    "name": "LOT 1283 WEST CREEK ROAD LAKE ALEXANDRINA 5259",
    "locID": "LOC000113009891",
    "tech": "SATELLITE",
    "upgrade": "NULL_NA",
    "gnaf_pid": "GASA_720304189"
   }
  }
 ]
}