{
 "type": "FeatureCollection",
 "generated": "2024-09-01T14:24:26.894957",
 "suburb": "LINDLEY",
 "features": [
  {
   "type": "Feature",
   "geometry": {
    "type": "Point",
    "coordinates": [
     139.55503393,
     -33.82652726
    ]
   },
   "properties": {
    "name": "LOT 100 SAMSONS WELL ROAD LINDLEY 5320",
    "locID": "LOC000142384406",
    "tech": "SATELLITE",
    "upgrade": "NULL_NA",
    "gnaf_pid": "GASA_424429263",
    "tech_change_status": "Not Planned"
   }
  },
  {
   "type": "Feature",
   "geometry": {
    "type": "Point",
    "coordinates": [
     139.59120805,
     -33.96294348
    ]
   },
   "properties": {
    "name": "LOT 198 GOYDER HIGHWAY LINDLEY 5320",
    "locID": "LOC000116329927",
    "tech": "WIRELESS",
    "upgrade": "NULL_NA",
    "gnaf_pid": "GASA_424561004",
    "tech_change_status": "Not Planned",
    "program_type": "Fixed Wireless and Satellite Upgrade Program",
    "target_eligibility_quarter": "NA"
   }
  }
 ]
}