{
 "type": "FeatureCollection",
 "generated": "2024-08-10T19:45:38.470070",
 "suburb": "MANUNDA STATION",
 "features": [
  {
   "type": "Feature",
   "geometry": {
    "type": "Point",
    "coordinates": [
     139.821368,
     -32.807934
    ]
   },
   "properties": {
    "name": "4283 STURT VALE ROAD MANUNDA STATION 5440",
    "locID": "LOC000148249933",
    "tech": "SATELLITE",
    "upgrade": "NULL_NA",
    "gnaf_pid": "GASA_425630454",
    "tech_change_status": "Not Planned"
   }
  }
 ]
}