{
 "type": "FeatureCollection",
 "generated": "2023-10-22T03:31:21.280832",
 "suburb": "MARREE STATION",
 "features": [
  {
   "type": "Feature",
   "geometry": {
    "type": "Point",
    "coordinates": [
     138.0676721,
     -29.70611318
    ]
   },
   "properties": {
    "name": "LOT 489 THE OUTBACK HIGHWAY MARREE STATION 5733",
    "locID": "EjNUaGUgT3V0YmFjayBId3ksIEZsaW5kZXJzIFJhbmdlcyBTQSA1NDM0LCBBdXN0cmFsaWEiLiosChQKEgldqbcabTKRahFDwUSGbWlPCBIUChIJQeecKnc2lGoRo5oXpT3Mql0",
    "tech": "SATELLITE",
    "upgrade": "UNKNOWN",
    "gnaf_pid": "GASA_425725235"
   }
  },
  {
   "type": "Feature",
   "geometry": {
    "type": "Point",
    "coordinates": [
     138.19839366,
     -29.85861692
    ]
   },
   "properties": {
    "name": "LOT 547 THE OUTBACK HIGHWAY MARREE STATION 5733",
    "locID": "EipUaGUgT3V0YmFjayBId3ksIEZhcmluYSBTQSA1NzMzLCBBdXN0cmFsaWEiLiosChQKEgldqbcabTKRahFDwUSGbWlPCBIUChIJLYgCbHbQkWoRsO6OYlQ2AwQ",
    "tech": "SATELLITE",
    "upgrade": "UNKNOWN",
    "gnaf_pid": "GASA_721273850"
   }
  }
 ]
}