{
 "type": "FeatureCollection",
 "generated": "2024-04-11T03:16:07.082400",
 "suburb": "MOONAREE",
 "features": [
  {
   "type": "Feature",
   "geometry": {
    "type": "Point",
    "coordinates": [
     135.873437,
     -31.96688
    ]
   },
   "properties": {
    "name": "296 MOONAREE ROAD MOONAREE 5717",
    "locID": "LOC000190693961",
    "tech": "SATELLITE",
    "upgrade": "NULL_NA",
    "gnaf_pid": "GASA_719965118"
   }
  }
 ]
}