{
 "type": "FeatureCollection",
 "generated": "2024-09-21T06:30:34.477064",
 "suburb": "MOONAREE",
 "features": [
  {
   "type": "Feature",
   "geometry": {
    "type": "Point",
    "coordinates": [
     135.873437,
     -31.96688
    ]
   },
   "properties": {
    "name": "296 MOONAREE ROAD MOONAREE 5717",
    "locID": "LOC000190693961",
    "tech": "SATELLITE",
    "upgrade": "NULL_NA",
    "gnaf_pid": "GASA_719965118",
    "tech_change_status": "Not Planned"
   }
  }
 ]
}