{
 "type": "FeatureCollection",
 "generated": "2023-10-22T04:51:35.358292",
 "suburb": "MOONAREE",
 "features": [
  {
   "type": "Feature",
   "geometry": {
    "type": "Point",
    "coordinates": [
     135.55259118,
     -31.99566075
    ]
   },
   "properties": {
    "name": "LOT 1506 SKULL CAMP TANKS ROAD MOONAREE 5717",
    "locID": "Ei9Ta3VsbCBDYW1wIFRhbmtzIFJkLCBLb2thdGhhIFNBIDU3MTcsIEF1c3RyYWxpYSIuKiwKFAoSCc_iTkkYJqFqEfq1iN4HzjecEhQKEgkpDdPLY1mgahH8eYtAcX-8HQ",
    "tech": "SATELLITE",
    "upgrade": "UNKNOWN",
    "gnaf_pid": "GASA_425724603"
   }
  },
  {
   "type": "Feature",
   "geometry": {
    "type": "Point",
    "coordinates": [
     135.43242236,
     -32.01130741
    ]
   },
   "properties": {
    "name": "LOT 1 SKULL CAMP TANKS ROAD MOONAREE 5717",
    "locID": "Ei9Ta3VsbCBDYW1wIFRhbmtzIFJkLCBLb2thdGhhIFNBIDU3MTcsIEF1c3RyYWxpYSIuKiwKFAoSCc_iTkkYJqFqEfq1iN4HzjecEhQKEgkpDdPLY1mgahH8eYtAcX-8HQ",
    "tech": "SATELLITE",
    "upgrade": "UNKNOWN",
    "gnaf_pid": "GASA_425848507"
   }
  },
  {
   "type": "Feature",
   "geometry": {
    "type": "Point",
    "coordinates": [
     135.873437,
     -31.96688
    ]
   },
   "properties": {
    "name": "296 MOONAREE ROAD MOONAREE 5717",
    "locID": "LOC100079660398",
    "tech": "SATELLITE",
    "upgrade": "NULL_NA",
    "gnaf_pid": "GASA_719965118"
   }
  }
 ]
}