{
 "type": "FeatureCollection",
 "generated": "2024-06-14T15:52:53.783738",
 "suburb": "MOUNT BARRY",
 "features": [
  {
   "type": "Feature",
   "geometry": {
    "type": "Point",
    "coordinates": [
     134.85846047,
     -28.27299102
    ]
   },
   "properties": {
    "name": "9706 KEMPE ROAD MOUNT BARRY 5723",
    "locID": "LOC000143022424",
    "tech": "SATELLITE",
    "upgrade": "NULL_NA",
    "gnaf_pid": "GASA_425629294"
   }
  }
 ]
}