{
 "type": "FeatureCollection",
 "generated": "2024-04-30T03:59:10.369335",
 "suburb": "MUTOOROO",
 "features": [
  {
   "type": "Feature",
   "geometry": {
    "type": "Point",
    "coordinates": [
     139.969605,
     -32.958282
    ]
   },
   "properties": {
    "name": "6539 STURT VALE ROAD MUTOOROO 5440",
    "locID": "LOC000148253058",
    "tech": "SATELLITE",
    "upgrade": "NULL_NA",
    "gnaf_pid": "GASA_719651993"
   }
  }
 ]
}