{
 "type": "FeatureCollection",
 "generated": "2024-10-09T04:50:40.802541",
 "suburb": "MUTOOROO",
 "features": [
  {
   "type": "Feature",
   "geometry": {
    "type": "Point",
    "coordinates": [
     139.969605,
     -32.958282
    ]
   },
   "properties": {
    "name": "6539 STURT VALE ROAD MUTOOROO 5440",
    "locID": "LOC000148253058",
    "tech": "NULL",
    "upgrade": "NULL_NA",
    "gnaf_pid": "GASA_719651993",
    "tech_change_status": "Not Planned"
   }
  }
 ]
}