{
 "type": "FeatureCollection",
 "generated": "2023-10-22T05:39:34.150491",
 "suburb": "MUTOOROO",
 "features": [
  {
   "type": "Feature",
   "geometry": {
    "type": "Point",
    "coordinates": [
     140.92308135,
     -32.44662221
    ]
   },
   "properties": {
    "name": "4167 MUTOOROO ROAD MUTOOROO 5440",
    "locID": "ChIJFRYk8FOz62oRMuH4BmINwMo",
    "tech": "SATELLITE",
    "upgrade": "UNKNOWN",
    "gnaf_pid": "GASA_425847276"
   }
  },
  {
   "type": "Feature",
   "geometry": {
    "type": "Point",
    "coordinates": [
     140.91549,
     -32.248172
    ]
   },
   "properties": {
    "name": "1819 MUTOOROO ROAD MUTOOROO 5440",
    "locID": "ChIJw4E9D8-762oRHOW6z_CgplQ",
    "tech": "SATELLITE",
    "upgrade": "UNKNOWN",
    "gnaf_pid": "GASA_719650118"
   }
  },
  {
   "type": "Feature",
   "geometry": {
    "type": "Point",
    "coordinates": [
     139.969605,
     -32.958282
    ]
   },
   "properties": {
    "name": "6539 STURT VALE ROAD MUTOOROO 5440",
    "locID": "LOC000148253058",
    "tech": "SATELLITE",
    "upgrade": "NULL_NA",
    "gnaf_pid": "GASA_719651993"
   }
  }
 ]
}