{
 "type": "FeatureCollection",
 "generated": "2024-09-01T18:21:27.820304",
 "suburb": "NECTAR BROOK",
 "features": [
  {
   "type": "Feature",
   "geometry": {
    "type": "Point",
    "coordinates": [
     138.03885475,
     -32.64480584
    ]
   },
   "properties": {
    "name": "LOT 329 HORROCKS PASS ROAD NECTAR BROOK 5495",
    "locID": "LOC100079107799",
    "tech": "SATELLITE",
    "upgrade": "NULL_NA",
    "gnaf_pid": "GASA_425064721",
    "tech_change_status": "Not Planned"
   }
  },
  {
   "type": "Feature",
   "geometry": {
    "type": "Point",
    "coordinates": [
     138.00597791,
     -32.60961751
    ]
   },
   "properties": {
    "name": "1189 HORROCKS PASS ROAD NECTAR BROOK 5495",
    "locID": "LOC000150240609",
    "tech": "WIRELESS",
    "upgrade": "NULL_NA",
    "gnaf_pid": "GASA_425303632",
    "tech_change_status": "Not Planned",
    "program_type": "Fixed Wireless and Satellite Upgrade Program",
    "target_eligibility_quarter": "Dec 2024"
   }
  },
  {
   "type": "Feature",
   "geometry": {
    "type": "Point",
    "coordinates": [
     138.04628026,
     -32.64945061
    ]
   },
   "properties": {
    "name": "559 HORROCKS PASS ROAD NECTAR BROOK 5495",
    "locID": "LOC100079107799",
    "tech": "SATELLITE",
    "upgrade": "NULL_NA",
    "gnaf_pid": "GASA_425303633",
    "tech_change_status": "Not Planned"
   }
  },
  {
   "type": "Feature",
   "geometry": {
    "type": "Point",
    "coordinates": [
     137.99437009,
     -32.61887371
    ]
   },
   "properties": {
    "name": "1228 NECTAR BROOK ROAD NECTAR BROOK 5495",
    "locID": "LOC000150240613",
    "tech": "SATELLITE",
    "upgrade": "NULL_NA",
    "gnaf_pid": "GASA_425304539",
    "tech_change_status": "Not Planned"
   }
  },
  {
   "type": "Feature",
   "geometry": {
    "type": "Point",
    "coordinates": [
     137.95945684,
     -32.6944256
    ]
   },
   "properties": {
    "name": "172 NECTAR BROOK ROAD NECTAR BROOK 5495",
    "locID": "LOC000167864906",
    "tech": "SATELLITE",
    "upgrade": "NULL_NA",
    "gnaf_pid": "GASA_425304540",
    "tech_change_status": "Not Planned"
   }
  },
  {
   "type": "Feature",
   "geometry": {
    "type": "Point",
    "coordinates": [
     137.95013531,
     -32.69543688
    ]
   },
   "properties": {
    "name": "77 NECTAR BROOK ROAD NECTAR BROOK 5495",
    "locID": "LOC000150240621",
    "tech": "SATELLITE",
    "upgrade": "NULL_NA",
    "gnaf_pid": "GASA_425304541",
    "tech_change_status": "Not Planned"
   }
  },
  {
   "type": "Feature",
   "geometry": {
    "type": "Point",
    "coordinates": [
     138.00534355,
     -32.6218145
    ]
   },
   "properties": {
    "name": "105 SMITH ROAD NECTAR BROOK 5495",
    "locID": "LOC000150240632",
    "tech": "WIRELESS",
    "upgrade": "NULL_NA",
    "gnaf_pid": "GASA_425305441",
    "tech_change_status": "Not Planned",
    "program_type": "Fixed Wireless and Satellite Upgrade Program",
    "target_eligibility_quarter": "Dec 2024"
   }
  },
  {
   "type": "Feature",
   "geometry": {
    "type": "Point",
    "coordinates": [
     137.99987217,
     -32.62158608
    ]
   },
   "properties": {
    "name": "53 SMITH ROAD NECTAR BROOK 5495",
    "locID": "LOC000150240645",
    "tech": "SATELLITE",
    "upgrade": "NULL_NA",
    "gnaf_pid": "GASA_425305442",
    "tech_change_status": "Not Planned"
   }
  },
  {
   "type": "Feature",
   "geometry": {
    "type": "Point",
    "coordinates": [
     137.94484289,
     -32.69587572
    ]
   },
   "properties": {
    "name": "25 NECTAR BROOK ROAD NECTAR BROOK 5495",
    "locID": "LOC000150240650",
    "tech": "SATELLITE",
    "upgrade": "NULL_NA",
    "gnaf_pid": "GASA_425534188",
    "tech_change_status": "Not Planned"
   }
  },
  {
   "type": "Feature",
   "geometry": {
    "type": "Point",
    "coordinates": [
     138.03670255,
     -32.6417068
    ]
   },
   "properties": {
    "name": "LOT 199 HORROCKS PASS ROAD NECTAR BROOK 5495",
    "locID": "LOC100079107799",
    "tech": "SATELLITE",
    "upgrade": "NULL_NA",
    "gnaf_pid": "GASA_425582315",
    "tech_change_status": "Not Planned"
   }
  },
  {
   "type": "Feature",
   "geometry": {
    "type": "Point",
    "coordinates": [
     138.03103043,
     -32.63306391
    ]
   },
   "properties": {
    "name": "LOT 311 HORROCKS PASS ROAD NECTAR BROOK 5495",
    "locID": "LOC100079107799",
    "tech": "SATELLITE",
    "upgrade": "NULL_NA",
    "gnaf_pid": "GASA_425582316",
    "tech_change_status": "Not Planned"
   }
  },
  {
   "type": "Feature",
   "geometry": {
    "type": "Point",
    "coordinates": [
     137.9681457,
     -32.655887
    ]
   },
   "properties": {
    "name": "1 NECTAR BROOK ROAD NECTAR BROOK 5495",
    "locID": "LOC000167864906",
    "tech": "SATELLITE",
    "upgrade": "NULL_NA",
    "gnaf_pid": "GASA_720191642",
    "tech_change_status": "Not Planned"
   }
  }
 ]
}