{
 "type": "FeatureCollection",
 "generated": "2024-07-23T00:24:22.418306",
 "suburb": "NOTTS WELL",
 "features": [
  {
   "type": "Feature",
   "geometry": {
    "type": "Point",
    "coordinates": [
     139.75342086,
     -34.41642336
    ]
   },
   "properties": {
    "name": "LOT 2 NOTTS WELL ROAD NOTTS WELL 5357",
    "locID": "LOC000019245771",
    "tech": "SATELLITE",
    "upgrade": "NULL_NA",
    "gnaf_pid": "GASA_424398104",
    "tech_change_status": "Not Planned"
   }
  },
  {
   "type": "Feature",
   "geometry": {
    "type": "Point",
    "coordinates": [
     139.75404612,
     -34.38791341
    ]
   },
   "properties": {
    "name": "LOT 34 NOTTS WELL ROAD NOTTS WELL 5357",
    "locID": "LOC000019245771",
    "tech": "SATELLITE",
    "upgrade": "NULL_NA",
    "gnaf_pid": "GASA_424398105",
    "tech_change_status": "Not Planned"
   }
  },
  {
   "type": "Feature",
   "geometry": {
    "type": "Point",
    "coordinates": [
     139.76976925,
     -34.41569218
    ]
   },
   "properties": {
    "name": "LOT 52 NOTTS WELL ROAD NOTTS WELL 5357",
    "locID": "LOC000019245771",
    "tech": "SATELLITE",
    "upgrade": "NULL_NA",
    "gnaf_pid": "GASA_424398106",
    "tech_change_status": "Not Planned"
   }
  },
  {
   "type": "Feature",
   "geometry": {
    "type": "Point",
    "coordinates": [
     139.8079355,
     -34.41486828
    ]
   },
   "properties": {
    "name": "1803 NOTTS WELL ROAD NOTTS WELL 5357",
    "locID": "LOC000019245771",
    "tech": "SATELLITE",
    "upgrade": "NULL_NA",
    "gnaf_pid": "GASA_424523351",
    "tech_change_status": "Not Planned"
   }
  },
  {
   "type": "Feature",
   "geometry": {
    "type": "Point",
    "coordinates": [
     139.83640837,
     -34.40955342
    ]
   },
   "properties": {
    "name": "2078 NOTTS WELL ROAD NOTTS WELL 5357",
    "locID": "LOC000094541495",
    "tech": "SATELLITE",
    "upgrade": "NULL_NA",
    "gnaf_pid": "GASA_424523353",
    "tech_change_status": "Not Planned"
   }
  },
  {
   "type": "Feature",
   "geometry": {
    "type": "Point",
    "coordinates": [
     139.82721238,
     -34.44053207
    ]
   },
   "properties": {
    "name": "LOT 372 NOTTS WELL ROAD NOTTS WELL 5357",
    "locID": "LOC000023433197",
    "tech": "SATELLITE",
    "upgrade": "NULL_NA",
    "gnaf_pid": "GASA_425393181",
    "tech_change_status": "Not Planned"
   }
  },
  {
   "type": "Feature",
   "geometry": {
    "type": "Point",
    "coordinates": [
     139.75534966,
     -34.43278014
    ]
   },
   "properties": {
    "name": "LOT 500 PIONEER ROAD NOTTS WELL 5357",
    "locID": "LOC100071999020",
    "tech": "SATELLITE",
    "upgrade": "NULL_NA",
    "gnaf_pid": "GASA_425393827",
    "tech_change_status": "Not Planned"
   }
  },
  {
   "type": "Feature",
   "geometry": {
    "type": "Point",
    "coordinates": [
     139.79549734,
     -34.40311635
    ]
   },
   "properties": {
    "name": "LOT 177 PIONEER ROAD NOTTS WELL 5357",
    "locID": "LOC100071999020",
    "tech": "SATELLITE",
    "upgrade": "NULL_NA",
    "gnaf_pid": "GASA_719860622",
    "tech_change_status": "Not Planned"
   }
  },
  {
   "type": "Feature",
   "geometry": {
    "type": "Point",
    "coordinates": [
     139.80247784,
     -34.38102417
    ]
   },
   "properties": {
    "name": "LOT 176 EDSON ROAD NOTTS WELL 5357",
    "locID": "LOC100071998796",
    "tech": "SATELLITE",
    "upgrade": "NULL_NA",
    "gnaf_pid": "GASA_719860729",
    "tech_change_status": "Not Planned"
   }
  }
 ]
}