{
 "type": "FeatureCollection",
 "generated": "2023-10-22T06:43:56.190830",
 "suburb": "NOTTS WELL",
 "features": [
  {
   "type": "Feature",
   "geometry": {
    "type": "Point",
    "coordinates": [
     139.75342086,
     -34.41642336
    ]
   },
   "properties": {
    "name": "LOT 2 NOTTS WELL ROAD NOTTS WELL 5357",
    "locID": "LOC000019245771",
    "tech": "SATELLITE",
    "upgrade": "NULL_NA",
    "gnaf_pid": "GASA_424398104"
   }
  },
  {
   "type": "Feature",
   "geometry": {
    "type": "Point",
    "coordinates": [
     139.75404612,
     -34.38791341
    ]
   },
   "properties": {
    "name": "LOT 34 NOTTS WELL ROAD NOTTS WELL 5357",
    "locID": "LOC000019245771",
    "tech": "SATELLITE",
    "upgrade": "NULL_NA",
    "gnaf_pid": "GASA_424398105"
   }
  },
  {
   "type": "Feature",
   "geometry": {
    "type": "Point",
    "coordinates": [
     139.76976925,
     -34.41569218
    ]
   },
   "properties": {
    "name": "LOT 52 NOTTS WELL ROAD NOTTS WELL 5357",
    "locID": "LOC000019245771",
    "tech": "SATELLITE",
    "upgrade": "NULL_NA",
    "gnaf_pid": "GASA_424398106"
   }
  },
  {
   "type": "Feature",
   "geometry": {
    "type": "Point",
    "coordinates": [
     139.8079355,
     -34.41486828
    ]
   },
   "properties": {
    "name": "1803 NOTTS WELL ROAD NOTTS WELL 5357",
    "locID": "LOC000019245771",
    "tech": "SATELLITE",
    "upgrade": "NULL_NA",
    "gnaf_pid": "GASA_424523351"
   }
  },
  {
   "type": "Feature",
   "geometry": {
    "type": "Point",
    "coordinates": [
     139.83628441,
     -34.40947823
    ]
   },
   "properties": {
    "name": "2077 NOTTS WELL ROAD NOTTS WELL 5357",
    "locID": "ChIJXa7vgpKIuGoR5mY_FKDuD2M",
    "tech": "SATELLITE",
    "upgrade": "UNKNOWN",
    "gnaf_pid": "GASA_424523352"
   }
  },
  {
   "type": "Feature",
   "geometry": {
    "type": "Point",
    "coordinates": [
     139.83640837,
     -34.40955342
    ]
   },
   "properties": {
    "name": "2078 NOTTS WELL ROAD NOTTS WELL 5357",
    "locID": "LOC000094541495",
    "tech": "SATELLITE",
    "upgrade": "NULL_NA",
    "gnaf_pid": "GASA_424523353"
   }
  },
  {
   "type": "Feature",
   "geometry": {
    "type": "Point",
    "coordinates": [
     139.78290961,
     -34.41156183
    ]
   },
   "properties": {
    "name": "1799 PIONEER ROAD NOTTS WELL 5357",
    "locID": "ChIJR_x8AY6JuGoRHlqz2IRFeHM",
    "tech": "SATELLITE",
    "upgrade": "UNKNOWN",
    "gnaf_pid": "GASA_424523974"
   }
  },
  {
   "type": "Feature",
   "geometry": {
    "type": "Point",
    "coordinates": [
     139.78325241,
     -34.41128218
    ]
   },
   "properties": {
    "name": "1804 PIONEER ROAD NOTTS WELL 5357",
    "locID": "ChIJkxj94pGJuGoRkYf50cnwoSM",
    "tech": "SATELLITE",
    "upgrade": "UNKNOWN",
    "gnaf_pid": "GASA_424523975"
   }
  },
  {
   "type": "Feature",
   "geometry": {
    "type": "Point",
    "coordinates": [
     139.82721238,
     -34.44053207
    ]
   },
   "properties": {
    "name": "LOT 372 NOTTS WELL ROAD NOTTS WELL 5357",
    "locID": "LOC000023433197",
    "tech": "SATELLITE",
    "upgrade": "NULL_NA",
    "gnaf_pid": "GASA_425393181"
   }
  },
  {
   "type": "Feature",
   "geometry": {
    "type": "Point",
    "coordinates": [
     139.75534966,
     -34.43278014
    ]
   },
   "properties": {
    "name": "LOT 500 PIONEER ROAD NOTTS WELL 5357",
    "locID": "LOC100071999020",
    "tech": "SATELLITE",
    "upgrade": "NULL_NA",
    "gnaf_pid": "GASA_425393827"
   }
  },
  {
   "type": "Feature",
   "geometry": {
    "type": "Point",
    "coordinates": [
     139.77875993,
     -34.41637781
    ]
   },
   "properties": {
    "name": "93 NAIDIA ROAD NOTTS WELL 5357",
    "locID": "Eiw5MyBOb3R0cyBXZWxsIFJkLCBQYWlzbGV5IFNBIDUzNTcsIEF1c3RyYWxpYSIwEi4KFAoSCUXQQpKW9bhqEaxsH3jxF_YzEF0qFAoSCUdCPcN9ibhqEaYh6o5KJq4i",
    "tech": "WIRELESS",
    "upgrade": "UNKNOWN",
    "gnaf_pid": "GASA_425722899"
   }
  },
  {
   "type": "Feature",
   "geometry": {
    "type": "Point",
    "coordinates": [
     139.79549734,
     -34.40311635
    ]
   },
   "properties": {
    "name": "LOT 177 PIONEER ROAD NOTTS WELL 5357",
    "locID": "LOC100071999020",
    "tech": "SATELLITE",
    "upgrade": "NULL_NA",
    "gnaf_pid": "GASA_719860622"
   }
  },
  {
   "type": "Feature",
   "geometry": {
    "type": "Point",
    "coordinates": [
     139.80247784,
     -34.38102417
    ]
   },
   "properties": {
    "name": "LOT 176 EDSON ROAD NOTTS WELL 5357",
    "locID": "LOC100071998796",
    "tech": "SATELLITE",
    "upgrade": "NULL_NA",
    "gnaf_pid": "GASA_719860729"
   }
  }
 ]
}