{
 "type": "FeatureCollection",
 "generated": "2024-09-01T19:22:58.662850",
 "suburb": "OLD KOOMOOLOO",
 "features": [
  {
   "type": "Feature",
   "geometry": {
    "type": "Point",
    "coordinates": [
     139.70747028,
     -33.56228445
    ]
   },
   "properties": {
    "name": "2543 KOOMOOLOO ROAD OLD KOOMOOLOO 5417",
    "locID": "LOC000148247186",
    "tech": "SATELLITE",
    "upgrade": "NULL_NA",
    "gnaf_pid": "GASA_425629343",
    "tech_change_status": "Not Planned"
   }
  }
 ]
}