{
 "type": "FeatureCollection",
 "generated": "2023-11-28T04:31:02.364817",
 "suburb": "PLUMBAGO",
 "features": [
  {
   "type": "Feature",
   "geometry": {
    "type": "Point",
    "coordinates": [
     139.883912,
     -32.059339
    ]
   },
   "properties": {
    "name": "5190 PLUMBAGO ROAD PLUMBAGO 5440",
    "locID": "ChIJX3-LvtnXlGoRrB7Q0hraZ7A",
    "tech": "SATELLITE",
    "upgrade": "UNKNOWN",
    "gnaf_pid": "GASA_719966118"
   }
  }
 ]
}