{
 "type": "FeatureCollection",
 "generated": "2024-09-21T11:10:06.165577",
 "suburb": "PORTER LAGOON",
 "features": [
  {
   "type": "Feature",
   "geometry": {
    "type": "Point",
    "coordinates": [
     138.8664597,
     -33.83724583
    ]
   },
   "properties": {
    "name": "LOT 3 BARRIER HIGHWAY PORTER LAGOON 5416",
    "locID": "LOC000150766903",
    "tech": "NULL",
    "upgrade": "NULL_NA",
    "gnaf_pid": "GASA_424288636",
    "tech_change_status": "Not Planned"
   }
  },
  {
   "type": "Feature",
   "geometry": {
    "type": "Point",
    "coordinates": [
     138.86060836,
     -33.84756152
    ]
   },
   "properties": {
    "name": "LOT 504 BARRIER HIGHWAY PORTER LAGOON 5416",
    "locID": "LOC000150766903",
    "tech": "NULL",
    "upgrade": "NULL_NA",
    "gnaf_pid": "GASA_424288637",
    "tech_change_status": "Not Planned"
   }
  },
  {
   "type": "Feature",
   "geometry": {
    "type": "Point",
    "coordinates": [
     138.87047151,
     -33.82027624
    ]
   },
   "properties": {
    "name": "LOT 28 PORTER LAGOON ROAD PORTER LAGOON 5416",
    "locID": "LOC000148407874",
    "tech": "NULL",
    "upgrade": "NULL_NA",
    "gnaf_pid": "GASA_424326300",
    "tech_change_status": "Not Planned"
   }
  },
  {
   "type": "Feature",
   "geometry": {
    "type": "Point",
    "coordinates": [
     138.88712049,
     -33.806431
    ]
   },
   "properties": {
    "name": "LOT 5 PORTER LAGOON ROAD PORTER LAGOON 5416",
    "locID": "LOC000148407874",
    "tech": "NULL",
    "upgrade": "NULL_NA",
    "gnaf_pid": "GASA_424326301",
    "tech_change_status": "Not Planned"
   }
  },
  {
   "type": "Feature",
   "geometry": {
    "type": "Point",
    "coordinates": [
     138.86296329,
     -33.82672482
    ]
   },
   "properties": {
    "name": "LOT 1 BARRIER HIGHWAY PORTER LAGOON 5416",
    "locID": "LOC000150766903",
    "tech": "NULL",
    "upgrade": "NULL_NA",
    "gnaf_pid": "GASA_425060930",
    "tech_change_status": "Not Planned"
   }
  },
  {
   "type": "Feature",
   "geometry": {
    "type": "Point",
    "coordinates": [
     138.86225864,
     -33.83637653
    ]
   },
   "properties": {
    "name": "4723 BARRIER HIGHWAY PORTER LAGOON 5416",
    "locID": "LOC000150766903",
    "tech": "NULL",
    "upgrade": "NULL_NA",
    "gnaf_pid": "GASA_425302248",
    "tech_change_status": "Not Planned"
   }
  },
  {
   "type": "Feature",
   "geometry": {
    "type": "Point",
    "coordinates": [
     138.85256851,
     -33.83304229
    ]
   },
   "properties": {
    "name": "LOT 197 BARRIER HIGHWAY PORTER LAGOON 5416",
    "locID": "LOC000150766903",
    "tech": "NULL",
    "upgrade": "NULL_NA",
    "gnaf_pid": "GASA_425581038",
    "tech_change_status": "Not Planned"
   }
  },
  {
   "type": "Feature",
   "geometry": {
    "type": "Point",
    "coordinates": [
     138.89758334,
     -33.79999348
    ]
   },
   "properties": {
    "name": "LOT 25 PORTER LAGOON ROAD PORTER LAGOON 5416",
    "locID": "LOC000148407874",
    "tech": "NULL",
    "upgrade": "NULL_NA",
    "gnaf_pid": "GASA_720186839",
    "tech_change_status": "Not Planned"
   }
  },
  {
   "type": "Feature",
   "geometry": {
    "type": "Point",
    "coordinates": [
     138.87795042,
     -33.80494981
    ]
   },
   "properties": {
    "name": "LOT 15 PORTER LAGOON ROAD PORTER LAGOON 5416",
    "locID": "LOC000148407874",
    "tech": "NULL",
    "upgrade": "NULL_NA",
    "gnaf_pid": "GASA_720189632",
    "tech_change_status": "Not Planned"
   }
  }
 ]
}