{
 "type": "FeatureCollection",
 "generated": "2023-12-17T06:58:49.850759",
 "suburb": "PRELINNA",
 "features": [
  {
   "type": "Feature",
   "geometry": {
    "type": "Point",
    "coordinates": [
     138.73127707,
     -31.64549773
    ]
   },
   "properties": {
    "name": "LOT 2028 MARTINS WELL ROAD PRELINNA 5434",
    "locID": "EjEyMDI4IE1hcnRpbnMgV2VsbCBSZCwgVXBhbGlubmEgU0EgNTQzNCwgQXVzdHJhbGlhIjESLwoUChIJq8wIXVTTlWoRzgCMhm9bmSEQ7A8qFAoSCUfAyog_LpRqESOfVYfZc5mY",
    "tech": "SATELLITE",
    "upgrade": "UNKNOWN",
    "gnaf_pid": "GASA_425722468"
   }
  }
 ]
}