{
 "type": "FeatureCollection",
 "generated": "2024-09-21T12:15:47.861590",
 "suburb": "ROCKY POINT",
 "features": [
  {
   "type": "Feature",
   "geometry": {
    "type": "Point",
    "coordinates": [
     139.44880465,
     -34.84401729
    ]
   },
   "properties": {
    "name": "1 ROCKY POINT ROAD ROCKY POINT 5238",
    "locID": "LOC000114328056",
    "tech": "SATELLITE",
    "upgrade": "NULL_NA",
    "gnaf_pid": "GASA_424707653",
    "tech_change_status": "Not Planned"
   }
  },
  {
   "type": "Feature",
   "geometry": {
    "type": "Point",
    "coordinates": [
     139.44168022,
     -34.85449612
    ]
   },
   "properties": {
    "name": "LOT 621 ROCKY POINT ROAD ROCKY POINT 5238",
    "locID": "LOC100086160605",
    "tech": "WIRELESS",
    "upgrade": "NULL_NA",
    "gnaf_pid": "GASA_425394237",
    "tech_change_status": "Not Planned",
    "program_type": "Fixed Wireless and Satellite Upgrade Program",
    "target_eligibility_quarter": "NA"
   }
  }
 ]
}