{
 "type": "FeatureCollection",
 "generated": "2023-10-22T09:55:31.879170",
 "suburb": "ROCKY POINT",
 "features": [
  {
   "type": "Feature",
   "geometry": {
    "type": "Point",
    "coordinates": [
     139.44205853,
     -34.85498274
    ]
   },
   "properties": {
    "name": "LOT 673 ROCKY POINT ROAD ROCKY POINT 5238",
    "locID": "EjM2NzMgUm9ja3kgUG9pbnQgUmQsIFJvY2t5IFBvaW50IFZJQyAzMzc3LCBBdXN0cmFsaWEiMRIvChQKEgkDJJ5Zt_nRahHk8KA9miWPqBChBSoUChIJT7dMypz50WoRb27NZEzRJQU",
    "tech": "SATELLITE",
    "upgrade": "UNKNOWN",
    "gnaf_pid": "GASA_424402579"
   }
  },
  {
   "type": "Feature",
   "geometry": {
    "type": "Point",
    "coordinates": [
     139.44880465,
     -34.84401729
    ]
   },
   "properties": {
    "name": "1 ROCKY POINT ROAD ROCKY POINT 5238",
    "locID": "LOC000114328056",
    "tech": "SATELLITE",
    "upgrade": "NULL_NA",
    "gnaf_pid": "GASA_424707653"
   }
  },
  {
   "type": "Feature",
   "geometry": {
    "type": "Point",
    "coordinates": [
     139.44168022,
     -34.85449612
    ]
   },
   "properties": {
    "name": "LOT 621 ROCKY POINT ROAD ROCKY POINT 5238",
    "locID": "EjM2MjEgUm9ja3kgUG9pbnQgUmQsIFJvY2t5IFBvaW50IFZJQyAzMzc3LCBBdXN0cmFsaWEiMRIvChQKEgkDJJ5Zt_nRahHk8KA9miWPqBDtBCoUChIJT7dMypz50WoRb27NZEzRJQU",
    "tech": "SATELLITE",
    "upgrade": "UNKNOWN",
    "gnaf_pid": "GASA_425394237"
   }
  },
  {
   "type": "Feature",
   "geometry": {
    "type": "Point",
    "coordinates": [
     139.44198188,
     -34.85453172
    ]
   },
   "properties": {
    "name": "LOT 622 ROCKY POINT ROAD ROCKY POINT 5238",
    "locID": "EjM2MjIgUm9ja3kgUG9pbnQgUmQsIFJvY2t5IFBvaW50IFZJQyAzMzc3LCBBdXN0cmFsaWEiMRIvChQKEgkDJJ5Zt_nRahHk8KA9miWPqBDuBCoUChIJT7dMypz50WoRb27NZEzRJQU",
    "tech": "SATELLITE",
    "upgrade": "UNKNOWN",
    "gnaf_pid": "GASA_425394238"
   }
  },
  {
   "type": "Feature",
   "geometry": {
    "type": "Point",
    "coordinates": [
     139.44223451,
     -34.85456418
    ]
   },
   "properties": {
    "name": "LOT 623 ROCKY POINT ROAD ROCKY POINT 5238",
    "locID": "EjM2MjMgUm9ja3kgUG9pbnQgUmQsIFJvY2t5IFBvaW50IFZJQyAzMzc3LCBBdXN0cmFsaWEiMRIvChQKEgkDJJ5Zt_nRahHk8KA9miWPqBDvBCoUChIJT7dMypz50WoRb27NZEzRJQU",
    "tech": "SATELLITE",
    "upgrade": "UNKNOWN",
    "gnaf_pid": "GASA_425394239"
   }
  },
  {
   "type": "Feature",
   "geometry": {
    "type": "Point",
    "coordinates": [
     139.44277777,
     -34.85488085
    ]
   },
   "properties": {
    "name": "LOT 625 ROCKY POINT ROAD ROCKY POINT 5238",
    "locID": "EjM2MjUgUm9ja3kgUG9pbnQgUmQsIFJvY2t5IFBvaW50IFZJQyAzMzc3LCBBdXN0cmFsaWEiMRIvChQKEgkDJJ5Zt_nRahHk8KA9miWPqBDxBCoUChIJT7dMypz50WoRb27NZEzRJQU",
    "tech": "SATELLITE",
    "upgrade": "UNKNOWN",
    "gnaf_pid": "GASA_425394240"
   }
  },
  {
   "type": "Feature",
   "geometry": {
    "type": "Point",
    "coordinates": [
     139.43478718,
     -34.85574716
    ]
   },
   "properties": {
    "name": "LOT 11 ROCKY POINT ROAD ROCKY POINT 5238",
    "locID": "EjIxMSBSb2NreSBQb2ludCBSZCwgUm9ja3kgUG9pbnQgVklDIDMzNzcsIEF1c3RyYWxpYSIwEi4KFAoSCa84mdFl99FqEdwiSQkefAFGEAsqFAoSCU-3TMqc-dFqEW9uzWRM0SUF",
    "tech": "WIRELESS",
    "upgrade": "UNKNOWN",
    "gnaf_pid": "GASA_721277770"
   }
  }
 ]
}