{
 "type": "FeatureCollection",
 "generated": "2024-05-23T05:07:16.501844",
 "suburb": "ROCKY POINT",
 "features": [
  {
   "type": "Feature",
   "geometry": {
    "type": "Point",
    "coordinates": [
     139.44880465,
     -34.84401729
    ]
   },
   "properties": {
    "name": "1 ROCKY POINT ROAD ROCKY POINT 5238",
    "locID": "LOC000114328056",
    "tech": "SATELLITE",
    "upgrade": "NULL_NA",
    "gnaf_pid": "GASA_424707653"
   }
  }
 ]
}