{
 "type": "FeatureCollection",
 "generated": "2023-12-17T10:24:13.080288",
 "suburb": "SOUTH GAP",
 "features": [
  {
   "type": "Feature",
   "geometry": {
    "type": "Point",
    "coordinates": [
     137.621139,
     -31.634602
    ]
   },
   "properties": {
    "name": "952 SOUTH GAP ROAD SOUTH GAP 5713",
    "locID": "LOC000150247719",
    "tech": "SATELLITE",
    "upgrade": "NULL_NA",
    "gnaf_pid": "GASA_425630376"
   }
  }
 ]
}