{
 "type": "FeatureCollection",
 "generated": "2024-05-23T10:39:51.781859",
 "suburb": "WALLERBERDINA",
 "features": [
  {
   "type": "Feature",
   "geometry": {
    "type": "Point",
    "coordinates": [
     138.07573509,
     -32.00394804
    ]
   },
   "properties": {
    "name": "LOT 7 WARRAKIMBO ROAD WALLERBERDINA 5713",
    "locID": "LOC000173354895",
    "tech": "SATELLITE",
    "upgrade": "NULL_NA",
    "gnaf_pid": "GASA_721273900"
   }
  }
 ]
}