{
 "type": "FeatureCollection",
 "generated": "2023-10-22T15:13:08.062784",
 "suburb": "WALLERBERDINA",
 "features": [
  {
   "type": "Feature",
   "geometry": {
    "type": "Point",
    "coordinates": [
     138.0473198,
     -31.92443831
    ]
   },
   "properties": {
    "name": "LOT 11 WARRAKIMBO ROAD WALLERBERDINA 5713",
    "locID": "Ei9XYXJyYWtpbWJvIFJkLCBXYWxsZXJiZXJkaW5hIFNBIDU3MTMsIEF1c3RyYWxpYSIuKiwKFAoSCcvYBaDEc71qEfumNWtdKaQaEhQKEgn7GUln-dOXahHRgSSMsDsD5Q",
    "tech": "SATELLITE",
    "upgrade": "UNKNOWN",
    "gnaf_pid": "GASA_425395609"
   }
  },
  {
   "type": "Feature",
   "geometry": {
    "type": "Point",
    "coordinates": [
     138.00795704,
     -31.84413741
    ]
   },
   "properties": {
    "name": "LOT 15 WARRAKIMBO ROAD WALLERBERDINA 5713",
    "locID": "Ei9XYXJyYWtpbWJvIFJkLCBXYWxsZXJiZXJkaW5hIFNBIDU3MTMsIEF1c3RyYWxpYSIuKiwKFAoSCcvYBaDEc71qEfumNWtdKaQaEhQKEgn7GUln-dOXahHRgSSMsDsD5Q",
    "tech": "SATELLITE",
    "upgrade": "UNKNOWN",
    "gnaf_pid": "GASA_425395610"
   }
  },
  {
   "type": "Feature",
   "geometry": {
    "type": "Point",
    "coordinates": [
     138.01195966,
     -31.87177395
    ]
   },
   "properties": {
    "name": "LOT 19 WARRAKIMBO ROAD WALLERBERDINA 5713",
    "locID": "Ei9XYXJyYWtpbWJvIFJkLCBXYWxsZXJiZXJkaW5hIFNBIDU3MTMsIEF1c3RyYWxpYSIuKiwKFAoSCcvYBaDEc71qEfumNWtdKaQaEhQKEgn7GUln-dOXahHRgSSMsDsD5Q",
    "tech": "SATELLITE",
    "upgrade": "UNKNOWN",
    "gnaf_pid": "GASA_425395611"
   }
  },
  {
   "type": "Feature",
   "geometry": {
    "type": "Point",
    "coordinates": [
     138.02565898,
     -31.91630167
    ]
   },
   "properties": {
    "name": "LOT 72 WARRAKIMBO ROAD WALLERBERDINA 5713",
    "locID": "Ei9XYXJyYWtpbWJvIFJkLCBXYWxsZXJiZXJkaW5hIFNBIDU3MTMsIEF1c3RyYWxpYSIuKiwKFAoSCcvYBaDEc71qEfumNWtdKaQaEhQKEgn7GUln-dOXahHRgSSMsDsD5Q",
    "tech": "SATELLITE",
    "upgrade": "UNKNOWN",
    "gnaf_pid": "GASA_425395613"
   }
  },
  {
   "type": "Feature",
   "geometry": {
    "type": "Point",
    "coordinates": [
     138.02808644,
     -31.91507833
    ]
   },
   "properties": {
    "name": "LOT 73 WARRAKIMBO ROAD WALLERBERDINA 5713",
    "locID": "Ei9XYXJyYWtpbWJvIFJkLCBXYWxsZXJiZXJkaW5hIFNBIDU3MTMsIEF1c3RyYWxpYSIuKiwKFAoSCcvYBaDEc71qEfumNWtdKaQaEhQKEgn7GUln-dOXahHRgSSMsDsD5Q",
    "tech": "SATELLITE",
    "upgrade": "UNKNOWN",
    "gnaf_pid": "GASA_425395614"
   }
  },
  {
   "type": "Feature",
   "geometry": {
    "type": "Point",
    "coordinates": [
     138.02723288,
     -31.91452973
    ]
   },
   "properties": {
    "name": "LOT 94 WARRAKIMBO ROAD WALLERBERDINA 5713",
    "locID": "Ei9XYXJyYWtpbWJvIFJkLCBXYWxsZXJiZXJkaW5hIFNBIDU3MTMsIEF1c3RyYWxpYSIuKiwKFAoSCcvYBaDEc71qEfumNWtdKaQaEhQKEgn7GUln-dOXahHRgSSMsDsD5Q",
    "tech": "SATELLITE",
    "upgrade": "UNKNOWN",
    "gnaf_pid": "GASA_425395615"
   }
  },
  {
   "type": "Feature",
   "geometry": {
    "type": "Point",
    "coordinates": [
     138.02755455,
     -31.91416815
    ]
   },
   "properties": {
    "name": "LOT 95 WARRAKIMBO ROAD WALLERBERDINA 5713",
    "locID": "Ei9XYXJyYWtpbWJvIFJkLCBXYWxsZXJiZXJkaW5hIFNBIDU3MTMsIEF1c3RyYWxpYSIuKiwKFAoSCcvYBaDEc71qEfumNWtdKaQaEhQKEgn7GUln-dOXahHRgSSMsDsD5Q",
    "tech": "SATELLITE",
    "upgrade": "UNKNOWN",
    "gnaf_pid": "GASA_425395616"
   }
  },
  {
   "type": "Feature",
   "geometry": {
    "type": "Point",
    "coordinates": [
     138.07573509,
     -32.00394804
    ]
   },
   "properties": {
    "name": "LOT 7 WARRAKIMBO ROAD WALLERBERDINA 5713",
    "locID": "LOC000173354895",
    "tech": "SATELLITE",
    "upgrade": "NULL_NA",
    "gnaf_pid": "GASA_721273900"
   }
  }
 ]
}