{
 "type": "FeatureCollection",
 "generated": "2024-09-02T06:48:55.540302",
 "suburb": "WATINUMA",
 "features": [
  {
   "type": "Feature",
   "geometry": {
    "type": "Point",
    "coordinates": [
     131.88115313,
     -26.5223483
    ]
   },
   "properties": {
    "name": "1 WATINUMA ROAD WATINUMA 872",
    "locID": "LOC000174338891",
    "tech": "SATELLITE",
    "upgrade": "NULL_NA",
    "gnaf_pid": "GASA_718983143",
    "tech_change_status": "Not Planned"
   }
  },
  {
   "type": "Feature",
   "geometry": {
    "type": "Point",
    "coordinates": [
     131.88113474,
     -26.52174428
    ]
   },
   "properties": {
    "name": "3-5 WATINUMA ROAD WATINUMA 872",
    "locID": "LOC000160514949",
    "tech": "SATELLITE",
    "upgrade": "NULL_NA",
    "gnaf_pid": "GASA_718983721",
    "tech_change_status": "Not Planned"
   }
  },
  {
   "type": "Feature",
   "geometry": {
    "type": "Point",
    "coordinates": [
     131.88099576,
     -26.52121051
    ]
   },
   "properties": {
    "name": "7 WATINUMA ROAD WATINUMA 872",
    "locID": "LOC100071908614",
    "tech": "SATELLITE",
    "upgrade": "NULL_NA",
    "gnaf_pid": "GASA_718986046",
    "tech_change_status": "Not Planned"
   }
  },
  {
   "type": "Feature",
   "geometry": {
    "type": "Point",
    "coordinates": [
     131.87977785,
     -26.52153774
    ]
   },
   "properties": {
    "name": "7 UWALINYI ROAD WATINUMA 872",
    "locID": "LOC100071908614",
    "tech": "SATELLITE",
    "upgrade": "NULL_NA",
    "gnaf_pid": "GASA_719772462",
    "tech_change_status": "Not Planned"
   }
  },
  {
   "type": "Feature",
   "geometry": {
    "type": "Point",
    "coordinates": [
     131.88246549,
     -26.52180443
    ]
   },
   "properties": {
    "name": "8 KAKARARA ROAD WATINUMA 872",
    "locID": "LOC000160514688",
    "tech": "SATELLITE",
    "upgrade": "NULL_NA",
    "gnaf_pid": "GASA_719773538",
    "tech_change_status": "Not Planned"
   }
  },
  {
   "type": "Feature",
   "geometry": {
    "type": "Point",
    "coordinates": [
     131.87968504,
     -26.52185346
    ]
   },
   "properties": {
    "name": "5 UWALINYI ROAD WATINUMA 872",
    "locID": "LOC100071908622",
    "tech": "SATELLITE",
    "upgrade": "NULL_NA",
    "gnaf_pid": "GASA_719776154",
    "tech_change_status": "Not Planned"
   }
  }
 ]
}