{
 "type": "FeatureCollection",
 "generated": "2023-10-22T15:40:53.766297",
 "suburb": "WAUKARINGA",
 "features": [
  {
   "type": "Feature",
   "geometry": {
    "type": "Point",
    "coordinates": [
     139.44397315,
     -32.28170124
    ]
   },
   "properties": {
    "name": "LOT 1012 TEA TREE ROAD WAUKARINGA 5440",
    "locID": "EipUZWEgVHJlZSBSZCwgV2VydGFsb29uYSBTQSA1NzMyLCBBdXN0cmFsaWEiLiosChQKEgmJEtu0Eu6UahGoxr9TP9vIchIUChIJC90x13sLk2oRmTXW0_EL7Aw",
    "tech": "SATELLITE",
    "upgrade": "UNKNOWN",
    "gnaf_pid": "GASA_425715064"
   }
  },
  {
   "type": "Feature",
   "geometry": {
    "type": "Point",
    "coordinates": [
     139.44048883,
     -32.29210907
    ]
   },
   "properties": {
    "name": "LOT 101 TEA TREE ROAD WAUKARINGA 5440",
    "locID": "EipUZWEgVHJlZSBSZCwgV2VydGFsb29uYSBTQSA1NzMyLCBBdXN0cmFsaWEiLiosChQKEgmJEtu0Eu6UahGoxr9TP9vIchIUChIJC90x13sLk2oRmTXW0_EL7Aw",
    "tech": "SATELLITE",
    "upgrade": "UNKNOWN",
    "gnaf_pid": "GASA_425725182"
   }
  },
  {
   "type": "Feature",
   "geometry": {
    "type": "Point",
    "coordinates": [
     139.41796763,
     -32.30164582
    ]
   },
   "properties": {
    "name": "LOT 1 MELTON ROAD WAUKARINGA 5440",
    "locID": "LOC000150235984",
    "tech": "SATELLITE",
    "upgrade": "NULL_NA",
    "gnaf_pid": "GASA_719246456"
   }
  },
  {
   "type": "Feature",
   "geometry": {
    "type": "Point",
    "coordinates": [
     139.43383989,
     -32.30121336
    ]
   },
   "properties": {
    "name": "LOT 984 MELTON ROAD WAUKARINGA 5440",
    "locID": "EjA5ODQgTWVsdG9uIFJkLCBNZWx0b24gU3RhdGlvbiBTQSA1NDQwLCBBdXN0cmFsaWEiMRIvChQKEgnRmRiI6oKVahGPgwIGKsn7phDYByoUChIJ2bKqLIF3lWoRsdo8gKkhA5k",
    "tech": "SATELLITE",
    "upgrade": "UNKNOWN",
    "gnaf_pid": "GASA_719246673"
   }
  },
  {
   "type": "Feature",
   "geometry": {
    "type": "Point",
    "coordinates": [
     139.44146811,
     -32.29950097
    ]
   },
   "properties": {
    "name": "LOT 56 TEA TREE ROAD WAUKARINGA 5440",
    "locID": "EipUZWEgVHJlZSBSZCwgV2VydGFsb29uYSBTQSA1NzMyLCBBdXN0cmFsaWEiLiosChQKEgmJEtu0Eu6UahGoxr9TP9vIchIUChIJC90x13sLk2oRmTXW0_EL7Aw",
    "tech": "SATELLITE",
    "upgrade": "UNKNOWN",
    "gnaf_pid": "GASA_719247114"
   }
  },
  {
   "type": "Feature",
   "geometry": {
    "type": "Point",
    "coordinates": [
     139.41760749,
     -32.30622847
    ]
   },
   "properties": {
    "name": "LOT 982 MELTON ROAD WAUKARINGA 5440",
    "locID": "EjA5ODIgTWVsdG9uIFJkLCBNZWx0b24gU3RhdGlvbiBTQSA1NDQwLCBBdXN0cmFsaWEiMRIvChQKEgnRmRiI6oKVahGPgwIGKsn7phDWByoUChIJ2bKqLIF3lWoRsdo8gKkhA5k",
    "tech": "SATELLITE",
    "upgrade": "UNKNOWN",
    "gnaf_pid": "GASA_719250596"
   }
  }
 ]
}