{
 "type": "FeatureCollection",
 "generated": "2024-06-15T02:47:01.961179",
 "suburb": "WAUKARINGA",
 "features": [
  {
   "type": "Feature",
   "geometry": {
    "type": "Point",
    "coordinates": [
     139.42190567,
     -32.30252554
    ]
   },
   "properties": {
    "name": "LOT 1 MELTON ROAD WAUKARINGA 5440",
    "locID": "LOC000150235984",
    "tech": "SATELLITE",
    "upgrade": "NULL_NA",
    "gnaf_pid": "GASA_719246456"
   }
  }
 ]
}