{
 "type": "FeatureCollection",
 "generated": "2023-10-22T16:17:15.001861",
 "suburb": "WILLOW SPRINGS",
 "features": [
  {
   "type": "Feature",
   "geometry": {
    "type": "Point",
    "coordinates": [
     138.726952,
     -31.450042
    ]
   },
   "properties": {
    "name": "16430 FLINDERS RANGES WAY WILLOW SPRINGS 5434",
    "locID": "ChIJ82IvSvInlGoRkE8kJ8JvhU0",
    "tech": "SATELLITE",
    "upgrade": "UNKNOWN",
    "gnaf_pid": "GASA_719861891"
   }
  },
  {
   "type": "Feature",
   "geometry": {
    "type": "Point",
    "coordinates": [
     138.72438828,
     -31.45262005
    ]
   },
   "properties": {
    "name": "291 FLINDERS RANGES WAY WILLOW SPRINGS 5434",
    "locID": "ChIJY3FAKvEnlGoR2KIRhp2gNuU",
    "tech": "SATELLITE",
    "upgrade": "UNKNOWN",
    "gnaf_pid": "GASA_720091110"
   }
  },
  {
   "type": "Feature",
   "geometry": {
    "type": "Point",
    "coordinates": [
     138.72697,
     -31.450027
    ]
   },
   "properties": {
    "name": "16430A FLINDERS RANGES WAY WILLOW SPRINGS 5434",
    "locID": "ChIJ82IvSvInlGoRkE8kJ8JvhU0",
    "tech": "SATELLITE",
    "upgrade": "UNKNOWN",
    "gnaf_pid": "GASA_721254105"
   }
  }
 ]
}