{
 "type": "FeatureCollection",
 "generated": "2024-08-11T08:11:53.253231",
 "suburb": "WIRRAMINNA",
 "features": [
  {
   "type": "Feature",
   "geometry": {
    "type": "Point",
    "coordinates": [
     136.229378,
     -31.199198
    ]
   },
   "properties": {
    "name": "206 WIRRAMINNA ROAD WIRRAMINNA 5719",
    "locID": "LOC000148245886",
    "tech": "SATELLITE",
    "upgrade": "NULL_NA",
    "gnaf_pid": "GASA_425630769",
    "tech_change_status": "Not Planned"
   }
  },
  {
   "type": "Feature",
   "geometry": {
    "type": "Point",
    "coordinates": [
     136.47038035,
     -31.23097024
    ]
   },
   "properties": {
    "name": "LOT 1554 STUART HIGHWAY WIRRAMINNA 5719",
    "locID": "LOC100074171951",
    "tech": "SATELLITE",
    "upgrade": "NULL_NA",
    "gnaf_pid": "GASA_425725049",
    "tech_change_status": "Not Planned"
   }
  },
  {
   "type": "Feature",
   "geometry": {
    "type": "Point",
    "coordinates": [
     136.12992334,
     -31.15718739
    ]
   },
   "properties": {
    "name": "LOT 1 STUART HIGHWAY WIRRAMINNA 5719",
    "locID": "LOC000119002107",
    "tech": "SATELLITE",
    "upgrade": "NULL_NA",
    "gnaf_pid": "GASA_425725050",
    "tech_change_status": "Not Planned"
   }
  },
  {
   "type": "Feature",
   "geometry": {
    "type": "Point",
    "coordinates": [
     136.12731218,
     -31.16269051
    ]
   },
   "properties": {
    "name": "LOT 2 STUART HIGHWAY WIRRAMINNA 5719",
    "locID": "LOC000152492478",
    "tech": "SATELLITE",
    "upgrade": "NULL_NA",
    "gnaf_pid": "GASA_425725051",
    "tech_change_status": "Not Planned"
   }
  },
  {
   "type": "Feature",
   "geometry": {
    "type": "Point",
    "coordinates": [
     136.55422619,
     -30.95600746
    ]
   },
   "properties": {
    "name": "LOT 358 STUART HIGHWAY WIRRAMINNA 5719",
    "locID": "LOC100074171951",
    "tech": "SATELLITE",
    "upgrade": "NULL_NA",
    "gnaf_pid": "GASA_425725052",
    "tech_change_status": "Not Planned"
   }
  },
  {
   "type": "Feature",
   "geometry": {
    "type": "Point",
    "coordinates": [
     136.45630088,
     -30.95567902
    ]
   },
   "properties": {
    "name": "LOT 359 STUART HIGHWAY WIRRAMINNA 5719",
    "locID": "LOC100074171951",
    "tech": "SATELLITE",
    "upgrade": "NULL_NA",
    "gnaf_pid": "GASA_425725053",
    "tech_change_status": "Not Planned"
   }
  },
  {
   "type": "Feature",
   "geometry": {
    "type": "Point",
    "coordinates": [
     136.10168488,
     -31.15964238
    ]
   },
   "properties": {
    "name": "LOT 102 STUART HIGHWAY WIRRAMINNA 5719",
    "locID": "LOC000091318002",
    "tech": "SATELLITE",
    "upgrade": "NULL_NA",
    "gnaf_pid": "GASA_719772922",
    "tech_change_status": "Not Planned"
   }
  }
 ]
}