{
 "type": "FeatureCollection",
 "generated": "2023-10-22T16:54:25.362420",
 "suburb": "WORUMBA",
 "features": [
  {
   "type": "Feature",
   "geometry": {
    "type": "Point",
    "coordinates": [
     138.6898463,
     -31.91201809
    ]
   },
   "properties": {
    "name": "1132 WORUMBA ROAD WORUMBA 5434",
    "locID": "ChIJNX-vxc8KlmoRFO6Ydl7v8Hw",
    "tech": "SATELLITE",
    "upgrade": "UNKNOWN",
    "gnaf_pid": "GASA_425630785"
   }
  }
 ]
}