{
 "type": "FeatureCollection",
 "generated": "2023-10-22T17:32:23.970682",
 "suburb": "YOUNGHUSBAND HOLDINGS",
 "features": [
  {
   "type": "Feature",
   "geometry": {
    "type": "Point",
    "coordinates": [
     139.5490584,
     -34.87493219
    ]
   },
   "properties": {
    "name": "1 YOUNGHUSBAND HOLDINGS ROAD YOUNGHUSBAND HOLDINGS 5238",
    "locID": "LOC100020478264",
    "tech": "WIRELESS",
    "upgrade": "NULL_NA",
    "gnaf_pid": "GASA_425504978"
   }
  },
  {
   "type": "Feature",
   "geometry": {
    "type": "Point",
    "coordinates": [
     139.5492085,
     -34.87389758
    ]
   },
   "properties": {
    "name": "SITE 13, 1 YOUNGHUSBAND HOLDINGS ROAD YOUNGHUSBAND HOLDINGS 5238",
    "locID": "LOC000187233428",
    "tech": "WIRELESS",
    "upgrade": "NULL_NA",
    "gnaf_pid": "GASA_425584697"
   }
  },
  {
   "type": "Feature",
   "geometry": {
    "type": "Point",
    "coordinates": [
     139.54959409,
     -34.87426677
    ]
   },
   "properties": {
    "name": "SITE 18, 1 YOUNGHUSBAND HOLDINGS ROAD YOUNGHUSBAND HOLDINGS 5238",
    "locID": "LOC000187233428",
    "tech": "WIRELESS",
    "upgrade": "NULL_NA",
    "gnaf_pid": "GASA_425584702"
   }
  },
  {
   "type": "Feature",
   "geometry": {
    "type": "Point",
    "coordinates": [
     139.5470405,
     -34.87526977
    ]
   },
   "properties": {
    "name": "SITE 1, 1 YOUNGHUSBAND HOLDINGS ROAD YOUNGHUSBAND HOLDINGS 5238",
    "locID": "LOC000187233428",
    "tech": "WIRELESS",
    "upgrade": "NULL_NA",
    "gnaf_pid": "GASA_425584704"
   }
  },
  {
   "type": "Feature",
   "geometry": {
    "type": "Point",
    "coordinates": [
     139.54982017,
     -34.87449558
    ]
   },
   "properties": {
    "name": "SITE 21, 1 YOUNGHUSBAND HOLDINGS ROAD YOUNGHUSBAND HOLDINGS 5238",
    "locID": "LOC000175620840",
    "tech": "WIRELESS",
    "upgrade": "NULL_NA",
    "gnaf_pid": "GASA_425584706"
   }
  },
  {
   "type": "Feature",
   "geometry": {
    "type": "Point",
    "coordinates": [
     139.54826435,
     -34.87315695
    ]
   },
   "properties": {
    "name": "SITE 2, 1 YOUNGHUSBAND HOLDINGS ROAD YOUNGHUSBAND HOLDINGS 5238",
    "locID": "LOC000175620840",
    "tech": "WIRELESS",
    "upgrade": "NULL_NA",
    "gnaf_pid": "GASA_425584713"
   }
  },
  {
   "type": "Feature",
   "geometry": {
    "type": "Point",
    "coordinates": [
     139.5485308,
     -34.87334988
    ]
   },
   "properties": {
    "name": "SITE 5, 1 YOUNGHUSBAND HOLDINGS ROAD YOUNGHUSBAND HOLDINGS 5238",
    "locID": "LOC000187233428",
    "tech": "WIRELESS",
    "upgrade": "NULL_NA",
    "gnaf_pid": "GASA_425584716"
   }
  }
 ]
}