{
 "type": "FeatureCollection",
 "generated": "2024-09-02T09:25:10.616099",
 "suburb": "YOUNGHUSBAND HOLDINGS",
 "features": [
  {
   "type": "Feature",
   "geometry": {
    "type": "Point",
    "coordinates": [
     139.5490584,
     -34.87493219
    ]
   },
   "properties": {
    "name": "1 YOUNGHUSBAND HOLDINGS ROAD YOUNGHUSBAND HOLDINGS 5238",
    "locID": "LOC100020478264",
    "tech": "WIRELESS",
    "upgrade": "NULL_NA",
    "gnaf_pid": "GASA_425504978",
    "tech_change_status": "Not Planned",
    "program_type": "Fixed Wireless and Satellite Upgrade Program",
    "target_eligibility_quarter": "Dec 2024"
   }
  },
  {
   "type": "Feature",
   "geometry": {
    "type": "Point",
    "coordinates": [
     139.5492085,
     -34.87389758
    ]
   },
   "properties": {
    "name": "SITE 13, 1 YOUNGHUSBAND HOLDINGS ROAD YOUNGHUSBAND HOLDINGS 5238",
    "locID": "LOC000187233428",
    "tech": "WIRELESS",
    "upgrade": "NULL_NA",
    "gnaf_pid": "GASA_425584697",
    "tech_change_status": "Not Planned",
    "program_type": "Fixed Wireless and Satellite Upgrade Program",
    "target_eligibility_quarter": "Dec 2024"
   }
  },
  {
   "type": "Feature",
   "geometry": {
    "type": "Point",
    "coordinates": [
     139.54959409,
     -34.87426677
    ]
   },
   "properties": {
    "name": "SITE 18, 1 YOUNGHUSBAND HOLDINGS ROAD YOUNGHUSBAND HOLDINGS 5238",
    "locID": "LOC000187233428",
    "tech": "WIRELESS",
    "upgrade": "NULL_NA",
    "gnaf_pid": "GASA_425584702",
    "tech_change_status": "Not Planned",
    "program_type": "Fixed Wireless and Satellite Upgrade Program",
    "target_eligibility_quarter": "Dec 2024"
   }
  },
  {
   "type": "Feature",
   "geometry": {
    "type": "Point",
    "coordinates": [
     139.5470405,
     -34.87526977
    ]
   },
   "properties": {
    "name": "SITE 1, 1 YOUNGHUSBAND HOLDINGS ROAD YOUNGHUSBAND HOLDINGS 5238",
    "locID": "LOC000187233428",
    "tech": "WIRELESS",
    "upgrade": "NULL_NA",
    "gnaf_pid": "GASA_425584704",
    "tech_change_status": "Not Planned",
    "program_type": "Fixed Wireless and Satellite Upgrade Program",
    "target_eligibility_quarter": "Dec 2024"
   }
  },
  {
   "type": "Feature",
   "geometry": {
    "type": "Point",
    "coordinates": [
     139.54982017,
     -34.87449558
    ]
   },
   "properties": {
    "name": "SITE 21, 1 YOUNGHUSBAND HOLDINGS ROAD YOUNGHUSBAND HOLDINGS 5238",
    "locID": "LOC000175620840",
    "tech": "WIRELESS",
    "upgrade": "NULL_NA",
    "gnaf_pid": "GASA_425584706",
    "tech_change_status": "Not Planned",
    "program_type": "Fixed Wireless and Satellite Upgrade Program",
    "target_eligibility_quarter": "Dec 2024"
   }
  },
  {
   "type": "Feature",
   "geometry": {
    "type": "Point",
    "coordinates": [
     139.54826435,
     -34.87315695
    ]
   },
   "properties": {
    "name": "SITE 2, 1 YOUNGHUSBAND HOLDINGS ROAD YOUNGHUSBAND HOLDINGS 5238",
    "locID": "LOC000175620840",
    "tech": "WIRELESS",
    "upgrade": "NULL_NA",
    "gnaf_pid": "GASA_425584713",
    "tech_change_status": "Not Planned",
    "program_type": "Fixed Wireless and Satellite Upgrade Program",
    "target_eligibility_quarter": "Dec 2024"
   }
  },
  {
   "type": "Feature",
   "geometry": {
    "type": "Point",
    "coordinates": [
     139.5485308,
     -34.87334988
    ]
   },
   "properties": {
    "name": "SITE 5, 1 YOUNGHUSBAND HOLDINGS ROAD YOUNGHUSBAND HOLDINGS 5238",
    "locID": "LOC000187233428",
    "tech": "WIRELESS",
    "upgrade": "NULL_NA",
    "gnaf_pid": "GASA_425584716",
    "tech_change_status": "Not Planned",
    "program_type": "Fixed Wireless and Satellite Upgrade Program",
    "target_eligibility_quarter": "Dec 2024"
   }
  }
 ]
}