{
 "type": "FeatureCollection",
 "generated": "2024-07-12T21:30:31.588133",
 "suburb": "ANATYE",
 "features": [
  {
   "type": "Feature",
   "geometry": {
    "type": "Point",
    "coordinates": [
     136.1713013,
     -22.78375561
    ]
   },
   "properties": {
    "name": "14973 PLENTY HIGHWAY ANATYE 872",
    "locID": "LOC000119030260",
    "tech": "SATELLITE",
    "upgrade": "NULL_NA",
    "gnaf_pid": "GANT_718014065",
    "tech_change_status": "Not Planned"
   }
  },
  {
   "type": "Feature",
   "geometry": {
    "type": "Point",
    "coordinates": [
     136.80780845,
     -22.73461977
    ]
   },
   "properties": {
    "name": "20282 PLENTY HIGHWAY ANATYE 872",
    "locID": "LOC000119021713",
    "tech": "SATELLITE",
    "upgrade": "NULL_NA",
    "gnaf_pid": "GANT_718014066",
    "tech_change_status": "Not Planned"
   }
  },
  {
   "type": "Feature",
   "geometry": {
    "type": "Point",
    "coordinates": [
     136.91336623,
     -22.59437038
    ]
   },
   "properties": {
    "name": "22890 PLENTY HIGHWAY ANATYE 872",
    "locID": "LOC000119024202",
    "tech": "SATELLITE",
    "upgrade": "NULL_NA",
    "gnaf_pid": "GANT_718014067",
    "tech_change_status": "Not Planned"
   }
  },
  {
   "type": "Feature",
   "geometry": {
    "type": "Point",
    "coordinates": [
     137.51179644,
     -22.25200116
    ]
   },
   "properties": {
    "name": "32475 PLENTY HIGHWAY ANATYE 872",
    "locID": "LOC000119016879",
    "tech": "SATELLITE",
    "upgrade": "NULL_NA",
    "gnaf_pid": "GANT_718014069",
    "tech_change_status": "Not Planned"
   }
  },
  {
   "type": "Feature",
   "geometry": {
    "type": "Point",
    "coordinates": [
     137.84095912,
     -23.04247334
    ]
   },
   "properties": {
    "name": "35033 PLENTY HIGHWAY ANATYE 872",
    "locID": "LOC100074754148",
    "tech": "SATELLITE",
    "upgrade": "NULL_NA",
    "gnaf_pid": "GANT_718014070",
    "tech_change_status": "Not Planned"
   }
  }
 ]
}