{
 "type": "FeatureCollection",
 "generated": "2023-12-29T08:13:40.842747",
 "suburb": "ANATYE",
 "features": [
  {
   "type": "Feature",
   "geometry": {
    "type": "Point",
    "coordinates": [
     136.41094813,
     -22.68863618
    ]
   },
   "properties": {
    "name": "17931 PLENTY HIGHWAY ANATYE 872",
    "locID": "ChIJzabyeZflc2oRbRyxsWlIfKQ",
    "tech": "SATELLITE",
    "upgrade": "UNKNOWN",
    "gnaf_pid": "GANT_717883958"
   }
  },
  {
   "type": "Feature",
   "geometry": {
    "type": "Point",
    "coordinates": [
     136.12129298,
     -22.99698622
    ]
   },
   "properties": {
    "name": "12765 PLENTY HIGHWAY ANATYE 872",
    "locID": "ChIJ-wYq7mS2dmoRVSMM4K3BjL4",
    "tech": "SATELLITE",
    "upgrade": "UNKNOWN",
    "gnaf_pid": "GANT_718014062"
   }
  },
  {
   "type": "Feature",
   "geometry": {
    "type": "Point",
    "coordinates": [
     136.67870099,
     -23.53484693
    ]
   },
   "properties": {
    "name": "12840 PLENTY HIGHWAY ANATYE 872",
    "locID": "ChIJMeoyDucAcWoRVIftGKxZLsQ",
    "tech": "SATELLITE",
    "upgrade": "UNKNOWN",
    "gnaf_pid": "GANT_718014063"
   }
  },
  {
   "type": "Feature",
   "geometry": {
    "type": "Point",
    "coordinates": [
     136.26049775,
     -22.7771653
    ]
   },
   "properties": {
    "name": "13381 PLENTY HIGHWAY ANATYE 872",
    "locID": "ChIJJc_Pct2xdmoRgpJXgWHx1mI",
    "tech": "SATELLITE",
    "upgrade": "UNKNOWN",
    "gnaf_pid": "GANT_718014064"
   }
  },
  {
   "type": "Feature",
   "geometry": {
    "type": "Point",
    "coordinates": [
     136.1713013,
     -22.78375561
    ]
   },
   "properties": {
    "name": "14973 PLENTY HIGHWAY ANATYE 872",
    "locID": "LOC000119030260",
    "tech": "SATELLITE",
    "upgrade": "NULL_NA",
    "gnaf_pid": "GANT_718014065"
   }
  },
  {
   "type": "Feature",
   "geometry": {
    "type": "Point",
    "coordinates": [
     136.80780845,
     -22.73461977
    ]
   },
   "properties": {
    "name": "20282 PLENTY HIGHWAY ANATYE 872",
    "locID": "LOC000119021713",
    "tech": "SATELLITE",
    "upgrade": "NULL_NA",
    "gnaf_pid": "GANT_718014066"
   }
  },
  {
   "type": "Feature",
   "geometry": {
    "type": "Point",
    "coordinates": [
     136.91336623,
     -22.59437038
    ]
   },
   "properties": {
    "name": "22890 PLENTY HIGHWAY ANATYE 872",
    "locID": "LOC000119024202",
    "tech": "SATELLITE",
    "upgrade": "NULL_NA",
    "gnaf_pid": "GANT_718014067"
   }
  },
  {
   "type": "Feature",
   "geometry": {
    "type": "Point",
    "coordinates": [
     137.04711258,
     -22.48411953
    ]
   },
   "properties": {
    "name": "23763 PLENTY HIGHWAY ANATYE 872",
    "locID": "ChIJk9BGpzZZcmoRyUKpKj7T-C8",
    "tech": "SATELLITE",
    "upgrade": "UNKNOWN",
    "gnaf_pid": "GANT_718014068"
   }
  },
  {
   "type": "Feature",
   "geometry": {
    "type": "Point",
    "coordinates": [
     137.51179644,
     -22.25200116
    ]
   },
   "properties": {
    "name": "32475 PLENTY HIGHWAY ANATYE 872",
    "locID": "LOC000119016879",
    "tech": "SATELLITE",
    "upgrade": "NULL_NA",
    "gnaf_pid": "GANT_718014069"
   }
  },
  {
   "type": "Feature",
   "geometry": {
    "type": "Point",
    "coordinates": [
     137.84095912,
     -23.04247334
    ]
   },
   "properties": {
    "name": "35033 PLENTY HIGHWAY ANATYE 872",
    "locID": "LOC100074754148",
    "tech": "SATELLITE",
    "upgrade": "NULL_NA",
    "gnaf_pid": "GANT_718014070"
   }
  }
 ]
}