{
 "type": "FeatureCollection",
 "generated": "2023-11-17T14:34:32.708336",
 "suburb": "BESWICK CREEK",
 "features": [
  {
   "type": "Feature",
   "geometry": {
    "type": "Point",
    "coordinates": [
     133.14919038,
     -14.48888296
    ]
   },
   "properties": {
    "name": "7280 CENTRAL ARNHEM ROAD BESWICK CREEK 852",
    "locID": "LOC000118981774",
    "tech": "SATELLITE",
    "upgrade": "NULL_NA",
    "gnaf_pid": "GANT_717840069"
   }
  },
  {
   "type": "Feature",
   "geometry": {
    "type": "Point",
    "coordinates": [
     132.80486468,
     -14.71416445
    ]
   },
   "properties": {
    "name": "6781 STUART HIGHWAY BESWICK CREEK 852",
    "locID": "ChIJo3owL3bkrywR5Hnc--Bjs4c",
    "tech": "SATELLITE",
    "upgrade": "UNKNOWN",
    "gnaf_pid": "GANT_717938653"
   }
  },
  {
   "type": "Feature",
   "geometry": {
    "type": "Point",
    "coordinates": [
     132.7341277,
     -14.6938507
    ]
   },
   "properties": {
    "name": "7000 STUART HIGHWAY BESWICK CREEK 852",
    "locID": "ChIJCe8TjG7jrywR5Jn5LRjMGak",
    "tech": "SATELLITE",
    "upgrade": "UNKNOWN",
    "gnaf_pid": "GANT_718014113"
   }
  }
 ]
}