{
 "type": "FeatureCollection",
 "generated": "2024-06-04T00:16:40.604441",
 "suburb": "BESWICK CREEK",
 "features": [
  {
   "type": "Feature",
   "geometry": {
    "type": "Point",
    "coordinates": [
     133.14919038,
     -14.48888296
    ]
   },
   "properties": {
    "name": "7280 CENTRAL ARNHEM ROAD BESWICK CREEK 852",
    "locID": "LOC000118981774",
    "tech": "SATELLITE",
    "upgrade": "NULL_NA",
    "gnaf_pid": "GANT_717840069"
   }
  }
 ]
}