{
 "type": "FeatureCollection",
 "generated": "2024-08-23T05:16:30.485988",
 "suburb": "BUCHANAN",
 "features": [
  {
   "type": "Feature",
   "geometry": {
    "type": "Point",
    "coordinates": [
     129.22708571,
     -17.31083949
    ]
   },
   "properties": {
    "name": "14925 DUNCAN ROAD BUCHANAN 852",
    "locID": "LOC000118984377",
    "tech": "SATELLITE",
    "upgrade": "NULL_NA",
    "gnaf_pid": "GANT_717938379",
    "tech_change_status": "Not Planned"
   }
  },
  {
   "type": "Feature",
   "geometry": {
    "type": "Point",
    "coordinates": [
     129.43636035,
     -17.90901454
    ]
   },
   "properties": {
    "name": "19083 BUNTINE HIGHWAY BUCHANAN 852",
    "locID": "LOC000118988419",
    "tech": "SATELLITE",
    "upgrade": "NULL_NA",
    "gnaf_pid": "GANT_718013806",
    "tech_change_status": "Not Planned"
   }
  },
  {
   "type": "Feature",
   "geometry": {
    "type": "Point",
    "coordinates": [
     129.8066217,
     -17.20319448
    ]
   },
   "properties": {
    "name": "8540 BUNTINE HIGHWAY BUCHANAN 852",
    "locID": "LOC000118986310",
    "tech": "SATELLITE",
    "upgrade": "NULL_NA",
    "gnaf_pid": "GANT_718013810",
    "tech_change_status": "Not Planned"
   }
  }
 ]
}