{
 "type": "FeatureCollection",
 "generated": "2023-10-30T20:24:56.412428",
 "suburb": "BUCHANAN",
 "features": [
  {
   "type": "Feature",
   "geometry": {
    "type": "Point",
    "coordinates": [
     129.6923998,
     -17.78230634
    ]
   },
   "properties": {
    "name": "14566 BUNTINE HIGHWAY BUCHANAN 852",
    "locID": "ChIJi536yxIjYCsReEJ33BW9EuQ",
    "tech": "SATELLITE",
    "upgrade": "UNKNOWN",
    "gnaf_pid": "GANT_717938247"
   }
  },
  {
   "type": "Feature",
   "geometry": {
    "type": "Point",
    "coordinates": [
     129.22708571,
     -17.31083949
    ]
   },
   "properties": {
    "name": "14925 DUNCAN ROAD BUCHANAN 852",
    "locID": "LOC000118984377",
    "tech": "SATELLITE",
    "upgrade": "NULL_NA",
    "gnaf_pid": "GANT_717938379"
   }
  },
  {
   "type": "Feature",
   "geometry": {
    "type": "Point",
    "coordinates": [
     129.76351368,
     -17.90949253
    ]
   },
   "properties": {
    "name": "15055 BUNTINE HIGHWAY BUCHANAN 852",
    "locID": "ChIJMfEV3CMQYCsRp2f6l75a_UA",
    "tech": "SATELLITE",
    "upgrade": "UNKNOWN",
    "gnaf_pid": "GANT_718013804"
   }
  },
  {
   "type": "Feature",
   "geometry": {
    "type": "Point",
    "coordinates": [
     129.40140756,
     -17.69737596
    ]
   },
   "properties": {
    "name": "16702 BUNTINE HIGHWAY BUCHANAN 852",
    "locID": "ChIJdWKUuQbSnywRTZFBPMgQucQ",
    "tech": "SATELLITE",
    "upgrade": "UNKNOWN",
    "gnaf_pid": "GANT_718013805"
   }
  },
  {
   "type": "Feature",
   "geometry": {
    "type": "Point",
    "coordinates": [
     129.43636035,
     -17.90901454
    ]
   },
   "properties": {
    "name": "19083 BUNTINE HIGHWAY BUCHANAN 852",
    "locID": "LOC000118988419",
    "tech": "SATELLITE",
    "upgrade": "NULL_NA",
    "gnaf_pid": "GANT_718013806"
   }
  },
  {
   "type": "Feature",
   "geometry": {
    "type": "Point",
    "coordinates": [
     129.16151236,
     -17.79811707
    ]
   },
   "properties": {
    "name": "20520 BUNTINE HIGHWAY BUCHANAN 852",
    "locID": "ChIJOytAJMraYSsRGGIdOJcBSvo",
    "tech": "SATELLITE",
    "upgrade": "UNKNOWN",
    "gnaf_pid": "GANT_718013807"
   }
  },
  {
   "type": "Feature",
   "geometry": {
    "type": "Point",
    "coordinates": [
     130.3943764,
     -17.55848943
    ]
   },
   "properties": {
    "name": "5470 BUNTINE HIGHWAY BUCHANAN 852",
    "locID": "ChIJ57x5R4N2oCwRgwXgZG2Y3fc",
    "tech": "SATELLITE",
    "upgrade": "UNKNOWN",
    "gnaf_pid": "GANT_718013808"
   }
  },
  {
   "type": "Feature",
   "geometry": {
    "type": "Point",
    "coordinates": [
     130.20403324,
     -17.38919803
    ]
   },
   "properties": {
    "name": "7560 BUNTINE HIGHWAY BUCHANAN 852",
    "locID": "ChIJ9xMa9vIWoCwR-yuwlUUpAYo",
    "tech": "SATELLITE",
    "upgrade": "UNKNOWN",
    "gnaf_pid": "GANT_718013809"
   }
  },
  {
   "type": "Feature",
   "geometry": {
    "type": "Point",
    "coordinates": [
     129.8066217,
     -17.20319448
    ]
   },
   "properties": {
    "name": "8540 BUNTINE HIGHWAY BUCHANAN 852",
    "locID": "LOC000118986310",
    "tech": "SATELLITE",
    "upgrade": "NULL_NA",
    "gnaf_pid": "GANT_718013810"
   }
  },
  {
   "type": "Feature",
   "geometry": {
    "type": "Point",
    "coordinates": [
     130.07162148,
     -17.61313591
    ]
   },
   "properties": {
    "name": "9195 BUNTINE HIGHWAY BUCHANAN 852",
    "locID": "ChIJK9FKPa8GoCwRMaVaglVz_74",
    "tech": "SATELLITE",
    "upgrade": "UNKNOWN",
    "gnaf_pid": "GANT_718013811"
   }
  },
  {
   "type": "Feature",
   "geometry": {
    "type": "Point",
    "coordinates": [
     130.1296895,
     -17.77069544
    ]
   },
   "properties": {
    "name": "9563 BUNTINE HIGHWAY BUCHANAN 852",
    "locID": "ChIJ3eqpXqD6XysR20FG2Sjyaw0",
    "tech": "SATELLITE",
    "upgrade": "UNKNOWN",
    "gnaf_pid": "GANT_718013812"
   }
  },
  {
   "type": "Feature",
   "geometry": {
    "type": "Point",
    "coordinates": [
     129.04482203,
     -17.10739663
    ]
   },
   "properties": {
    "name": "13905 DUNCAN ROAD BUCHANAN 852",
    "locID": "ChIJkXR3XUvsniwRKDiK1V1d1qc",
    "tech": "SATELLITE",
    "upgrade": "UNKNOWN",
    "gnaf_pid": "GANT_718013919"
   }
  }
 ]
}