{
 "type": "FeatureCollection",
 "generated": "2024-09-11T18:12:36.977229",
 "suburb": "COONAWARRA",
 "features": [
  {
   "type": "Feature",
   "geometry": {
    "type": "Point",
    "coordinates": [
     130.90835754,
     -12.43440695
    ]
   },
   "properties": {
    "name": "1 JONES COURT COONAWARRA 820",
    "locID": "LOC000007370778",
    "tech": "FTTP",
    "upgrade": "NULL_NA",
    "gnaf_pid": "GANT_702936504",
    "program_type": "On-Demand N2P SDU/MDU Simple",
    "target_eligibility_quarter": "NA"
   }
  },
  {
   "type": "Feature",
   "geometry": {
    "type": "Point",
    "coordinates": [
     130.90835754,
     -12.43440695
    ]
   },
   "properties": {
    "name": "2 JONES COURT COONAWARRA 820",
    "locID": "LOC000015926869",
    "tech": "FTTN",
    "upgrade": "NULL_NA",
    "gnaf_pid": "GANT_702940556",
    "tech_change_status": "Not Planned"
   }
  },
  {
   "type": "Feature",
   "geometry": {
    "type": "Point",
    "coordinates": [
     130.90885752,
     -12.43433192
    ]
   },
   "properties": {
    "name": "620 STUART HIGHWAY COONAWARRA 820",
    "locID": "LOC000118920741",
    "tech": "FTTB",
    "upgrade": "NULL_NA",
    "gnaf_pid": "GANT_717754030"
   }
  },
  {
   "type": "Feature",
   "geometry": {
    "type": "Point",
    "coordinates": [
     130.91251537,
     -12.43088204
    ]
   },
   "properties": {
    "name": "73 MELVILLE ROAD COONAWARRA 820",
    "locID": "LOC000146792334",
    "tech": "FTTP",
    "upgrade": "NULL_NA",
    "gnaf_pid": "GANT_718345202"
   }
  }
 ]
}