{
 "type": "FeatureCollection",
 "generated": "2023-12-29T08:53:30.098987",
 "suburb": "DARWIN RIVER DAM",
 "features": [
  {
   "type": "Feature",
   "geometry": {
    "type": "Point",
    "coordinates": [
     131.09901049,
     -12.88088872
    ]
   },
   "properties": {
    "name": "4680 STUART HIGHWAY DARWIN RIVER DAM 822",
    "locID": "ChIJ4fAEcuhHvywRXYzwuJT7Xtg",
    "tech": "SATELLITE",
    "upgrade": "UNKNOWN",
    "gnaf_pid": "GANT_717884209"
   }
  },
  {
   "type": "Feature",
   "geometry": {
    "type": "Point",
    "coordinates": [
     131.13454299,
     -12.84234381
    ]
   },
   "properties": {
    "name": "4760 STUART HIGHWAY DARWIN RIVER DAM 822",
    "locID": "ChIJeynwIRhIvywR5Qh8iDlNlac",
    "tech": "SATELLITE",
    "upgrade": "UNKNOWN",
    "gnaf_pid": "GANT_717884210"
   }
  },
  {
   "type": "Feature",
   "geometry": {
    "type": "Point",
    "coordinates": [
     131.13950315,
     -12.8946993
    ]
   },
   "properties": {
    "name": "4880 STUART HIGHWAY DARWIN RIVER DAM 822",
    "locID": "ChIJj4VwYx9IvywR3SjyT_7XyHY",
    "tech": "SATELLITE",
    "upgrade": "UNKNOWN",
    "gnaf_pid": "GANT_718589952"
   }
  }
 ]
}