{
 "type": "FeatureCollection",
 "generated": "2024-08-01T05:50:44.430647",
 "suburb": "FINNISS VALLEY",
 "features": [
  {
   "type": "Feature",
   "geometry": {
    "type": "Point",
    "coordinates": [
     130.95280816,
     -13.03190113
    ]
   },
   "properties": {
    "name": "115 SCOTT ROAD FINNISS VALLEY 822",
    "locID": "LOC000118924951",
    "tech": "SATELLITE",
    "upgrade": "NULL_NA",
    "gnaf_pid": "GANT_715276896",
    "tech_change_status": "Not Planned"
   }
  },
  {
   "type": "Feature",
   "geometry": {
    "type": "Point",
    "coordinates": [
     130.94651459,
     -13.02246542
    ]
   },
   "properties": {
    "name": "785 LITCHFIELD PARK ROAD FINNISS VALLEY 822",
    "locID": "LOC000119001143",
    "tech": "SATELLITE",
    "upgrade": "NULL_NA",
    "gnaf_pid": "GANT_717181323",
    "tech_change_status": "Not Planned"
   }
  },
  {
   "type": "Feature",
   "geometry": {
    "type": "Point",
    "coordinates": [
     130.93653393,
     -13.02458146
    ]
   },
   "properties": {
    "name": "895 LITCHFIELD PARK ROAD FINNISS VALLEY 822",
    "locID": "LOC000119002531",
    "tech": "SATELLITE",
    "upgrade": "NULL_NA",
    "gnaf_pid": "GANT_717181325",
    "tech_change_status": "Not Planned"
   }
  },
  {
   "type": "Feature",
   "geometry": {
    "type": "Point",
    "coordinates": [
     130.94511057,
     -13.03188672
    ]
   },
   "properties": {
    "name": "130 SCOTT ROAD FINNISS VALLEY 822",
    "locID": "LOC000118926155",
    "tech": "SATELLITE",
    "upgrade": "NULL_NA",
    "gnaf_pid": "GANT_717488771",
    "tech_change_status": "Not Planned"
   }
  },
  {
   "type": "Feature",
   "geometry": {
    "type": "Point",
    "coordinates": [
     130.95650193,
     -13.04665578
    ]
   },
   "properties": {
    "name": "285 SCOTT ROAD FINNISS VALLEY 822",
    "locID": "LOC000118930265",
    "tech": "SATELLITE",
    "upgrade": "NULL_NA",
    "gnaf_pid": "GANT_717488772",
    "tech_change_status": "Not Planned"
   }
  },
  {
   "type": "Feature",
   "geometry": {
    "type": "Point",
    "coordinates": [
     130.94650605,
     -13.02728796
    ]
   },
   "properties": {
    "name": "74 SCOTT ROAD FINNISS VALLEY 822",
    "locID": "LOC000118999953",
    "tech": "SATELLITE",
    "upgrade": "NULL_NA",
    "gnaf_pid": "GANT_717488775",
    "tech_change_status": "Not Planned"
   }
  },
  {
   "type": "Feature",
   "geometry": {
    "type": "Point",
    "coordinates": [
     130.96569765,
     -13.07558885
    ]
   },
   "properties": {
    "name": "124 CHEENEY ROAD FINNISS VALLEY 822",
    "locID": "LOC100071883443",
    "tech": "SATELLITE",
    "upgrade": "NULL_NA",
    "gnaf_pid": "GANT_718742116",
    "tech_change_status": "Not Planned"
   }
  },
  {
   "type": "Feature",
   "geometry": {
    "type": "Point",
    "coordinates": [
     130.9657243,
     -13.08043964
    ]
   },
   "properties": {
    "name": "182 CHEENEY ROAD FINNISS VALLEY 822",
    "locID": "LOC000180866467",
    "tech": "SATELLITE",
    "upgrade": "NULL_NA",
    "gnaf_pid": "GANT_718742120",
    "tech_change_status": "Not Planned"
   }
  },
  {
   "type": "Feature",
   "geometry": {
    "type": "Point",
    "coordinates": [
     130.96569787,
     -13.08524528
    ]
   },
   "properties": {
    "name": "234 CHEENEY ROAD FINNISS VALLEY 822",
    "locID": "LOC100018388261",
    "tech": "SATELLITE",
    "upgrade": "NULL_NA",
    "gnaf_pid": "GANT_718742123",
    "tech_change_status": "Not Planned"
   }
  }
 ]
}