{
 "type": "FeatureCollection",
 "generated": "2024-08-24T05:14:23.610186",
 "suburb": "GREGORY",
 "features": [
  {
   "type": "Feature",
   "geometry": {
    "type": "Point",
    "coordinates": [
     130.32065971,
     -16.31858164
    ]
   },
   "properties": {
    "name": "1287 VICTORIA HIGHWAY GREGORY 852",
    "locID": "LOC000158439755",
    "tech": "SATELLITE",
    "upgrade": "NULL_NA",
    "gnaf_pid": "GANT_717884638",
    "tech_change_status": "Not Planned"
   }
  },
  {
   "type": "Feature",
   "geometry": {
    "type": "Point",
    "coordinates": [
     131.1285495,
     -15.61688803
    ]
   },
   "properties": {
    "name": "19405 VICTORIA HIGHWAY GREGORY 852",
    "locID": "LOC000118988457",
    "tech": "SATELLITE",
    "upgrade": "NULL_NA",
    "gnaf_pid": "GANT_717938852",
    "tech_change_status": "Not Planned"
   }
  },
  {
   "type": "Feature",
   "geometry": {
    "type": "Point",
    "coordinates": [
     130.5031439,
     -15.73720614
    ]
   },
   "properties": {
    "name": "27455 VICTORIA HIGHWAY GREGORY 852",
    "locID": "LOC000118993767",
    "tech": "SATELLITE",
    "upgrade": "NULL_NA",
    "gnaf_pid": "GANT_717938855",
    "tech_change_status": "Not Planned"
   }
  },
  {
   "type": "Feature",
   "geometry": {
    "type": "Point",
    "coordinates": [
     130.60821437,
     -15.99843369
    ]
   },
   "properties": {
    "name": "18135 BUCHANAN HIGHWAY GREGORY 852",
    "locID": "LOC000118987261",
    "tech": "SATELLITE",
    "upgrade": "NULL_NA",
    "gnaf_pid": "GANT_718013802",
    "tech_change_status": "Not Planned"
   }
  }
 ]
}