{
 "type": "FeatureCollection",
 "generated": "2023-09-22T18:35:09.341353",
 "suburb": "GREGORY",
 "features": [
  {
   "type": "Feature",
   "geometry": {
    "type": "Point",
    "coordinates": [
     130.32065971,
     -16.31858164
    ]
   },
   "properties": {
    "name": "1287 VICTORIA HIGHWAY GREGORY 852",
    "locID": "LOC000158439755",
    "tech": "SATELLITE",
    "upgrade": "NULL_NA",
    "gnaf_pid": "GANT_717884638"
   }
  },
  {
   "type": "Feature",
   "geometry": {
    "type": "Point",
    "coordinates": [
     131.18317176,
     -15.6209586
    ]
   },
   "properties": {
    "name": "18580 VICTORIA HIGHWAY GREGORY 852",
    "locID": "ChIJa0SOV-R7oywRAB8-XJetsSY",
    "tech": "SATELLITE",
    "upgrade": "UNKNOWN",
    "gnaf_pid": "GANT_717884641"
   }
  },
  {
   "type": "Feature",
   "geometry": {
    "type": "Point",
    "coordinates": [
     130.84706765,
     -15.86302885
    ]
   },
   "properties": {
    "name": "21235 VICTORIA HIGHWAY GREGORY 852",
    "locID": "ChIJAUgZ3ba5oywRruiEmVVMJ-M",
    "tech": "SATELLITE",
    "upgrade": "UNKNOWN",
    "gnaf_pid": "GANT_717884645"
   }
  },
  {
   "type": "Feature",
   "geometry": {
    "type": "Point",
    "coordinates": [
     130.70534424,
     -15.71214102
    ]
   },
   "properties": {
    "name": "24665 VICTORIA HIGHWAY GREGORY 852",
    "locID": "ChIJGxFCBfV0oywRnsN-7p8QZDk",
    "tech": "SATELLITE",
    "upgrade": "UNKNOWN",
    "gnaf_pid": "GANT_717884646"
   }
  },
  {
   "type": "Feature",
   "geometry": {
    "type": "Point",
    "coordinates": [
     130.64043893,
     -16.01273784
    ]
   },
   "properties": {
    "name": "13774 BUCHANAN HIGHWAY GREGORY 852",
    "locID": "ChIJr5HFQqnKoywRsP5aY-7tYu8",
    "tech": "SATELLITE",
    "upgrade": "UNKNOWN",
    "gnaf_pid": "GANT_717938239"
   }
  },
  {
   "type": "Feature",
   "geometry": {
    "type": "Point",
    "coordinates": [
     130.36731031,
     -15.56652564
    ]
   },
   "properties": {
    "name": "1740 VICTORIA HIGHWAY GREGORY 852",
    "locID": "ChIJhfCoAUnsoiwRYppoME93f2s",
    "tech": "SATELLITE",
    "upgrade": "UNKNOWN",
    "gnaf_pid": "GANT_717938851"
   }
  },
  {
   "type": "Feature",
   "geometry": {
    "type": "Point",
    "coordinates": [
     131.1285495,
     -15.61688803
    ]
   },
   "properties": {
    "name": "19405 VICTORIA HIGHWAY GREGORY 852",
    "locID": "LOC000118988457",
    "tech": "SATELLITE",
    "upgrade": "NULL_NA",
    "gnaf_pid": "GANT_717938852"
   }
  },
  {
   "type": "Feature",
   "geometry": {
    "type": "Point",
    "coordinates": [
     131.12743706,
     -15.62280915
    ]
   },
   "properties": {
    "name": "19445 VICTORIA HIGHWAY GREGORY 852",
    "locID": "ChIJQS0O3dGCoywRZX_pseFmsQc",
    "tech": "SATELLITE",
    "upgrade": "UNKNOWN",
    "gnaf_pid": "GANT_717938853"
   }
  },
  {
   "type": "Feature",
   "geometry": {
    "type": "Point",
    "coordinates": [
     131.12131415,
     -15.62792475
    ]
   },
   "properties": {
    "name": "19485 VICTORIA HIGHWAY GREGORY 852",
    "locID": "ChIJJ99YQtOCoywRGxN8uGGRPOQ",
    "tech": "SATELLITE",
    "upgrade": "UNKNOWN",
    "gnaf_pid": "GANT_717938854"
   }
  },
  {
   "type": "Feature",
   "geometry": {
    "type": "Point",
    "coordinates": [
     130.5031439,
     -15.73720614
    ]
   },
   "properties": {
    "name": "27455 VICTORIA HIGHWAY GREGORY 852",
    "locID": "LOC000118993767",
    "tech": "SATELLITE",
    "upgrade": "NULL_NA",
    "gnaf_pid": "GANT_717938855"
   }
  },
  {
   "type": "Feature",
   "geometry": {
    "type": "Point",
    "coordinates": [
     130.60821437,
     -15.99843369
    ]
   },
   "properties": {
    "name": "18135 BUCHANAN HIGHWAY GREGORY 852",
    "locID": "LOC000118987261",
    "tech": "SATELLITE",
    "upgrade": "NULL_NA",
    "gnaf_pid": "GANT_718013802"
   }
  }
 ]
}