{
 "type": "FeatureCollection",
 "generated": "2023-09-22T19:09:18.468273",
 "suburb": "KOOLPINYAH",
 "features": [
  {
   "type": "Feature",
   "geometry": {
    "type": "Point",
    "coordinates": [
     131.10749561,
     -12.50529572
    ]
   },
   "properties": {
    "name": "635 GIRRAWEEN ROAD KOOLPINYAH 822",
    "locID": "Ei82MzUgR2lycmF3ZWVuIFJkLCBLb29scGlueWFoIE5UIDA4MzYsIEF1c3RyYWxpYSIxEi8KFAoSCaFVYOropcAsEYXDA825EpQtEPsEKhQKEgmzP8l_-aXALBHUxUeyuaE9Hw",
    "tech": "WIRELESS",
    "upgrade": "UNKNOWN",
    "gnaf_pid": "GANT_717245370"
   }
  },
  {
   "type": "Feature",
   "geometry": {
    "type": "Point",
    "coordinates": [
     131.12628884,
     -12.51980341
    ]
   },
   "properties": {
    "name": "745 GIRRAWEEN ROAD KOOLPINYAH 822",
    "locID": "ChIJI870UEGvwCwRTsbPQR4-1AU",
    "tech": "WIRELESS",
    "upgrade": "UNKNOWN",
    "gnaf_pid": "GANT_717245371"
   }
  },
  {
   "type": "Feature",
   "geometry": {
    "type": "Point",
    "coordinates": [
     131.10382314,
     -12.52421393
    ]
   },
   "properties": {
    "name": "625 GIRRAWEEN ROAD KOOLPINYAH 822",
    "locID": "ChIJ6z6IL-mlwCwRYBLI1auJ4xE",
    "tech": "WIRELESS",
    "upgrade": "UNKNOWN",
    "gnaf_pid": "GANT_717753838"
   }
  },
  {
   "type": "Feature",
   "geometry": {
    "type": "Point",
    "coordinates": [
     131.23410892,
     -12.40169931
    ]
   },
   "properties": {
    "name": "1650 GUNN POINT ROAD KOOLPINYAH 822",
    "locID": "ChIJWRHzH52xwCwRwT-CUuk9uvU",
    "tech": "SATELLITE",
    "upgrade": "UNKNOWN",
    "gnaf_pid": "GANT_717840311"
   }
  },
  {
   "type": "Feature",
   "geometry": {
    "type": "Point",
    "coordinates": [
     131.13814083,
     -12.32252207
    ]
   },
   "properties": {
    "name": "2820 GUNN POINT ROAD KOOLPINYAH 822",
    "locID": "ChIJE_E0hem3wCwRDsp0fVPkoOc",
    "tech": "SATELLITE",
    "upgrade": "UNKNOWN",
    "gnaf_pid": "GANT_717883590"
   }
  },
  {
   "type": "Feature",
   "geometry": {
    "type": "Point",
    "coordinates": [
     131.11619322,
     -12.21574466
    ]
   },
   "properties": {
    "name": "3820 GUNN POINT ROAD KOOLPINYAH 822",
    "locID": "LOC100072121834",
    "tech": "SATELLITE",
    "upgrade": "NULL_NA",
    "gnaf_pid": "GANT_717883591"
   }
  },
  {
   "type": "Feature",
   "geometry": {
    "type": "Point",
    "coordinates": [
     131.06059233,
     -12.24485098
    ]
   },
   "properties": {
    "name": "3940 GUNN POINT ROAD KOOLPINYAH 822",
    "locID": "ChIJM09RkSPEwCwR95sQRZFC9kM",
    "tech": "SATELLITE",
    "upgrade": "UNKNOWN",
    "gnaf_pid": "GANT_717883592"
   }
  },
  {
   "type": "Feature",
   "geometry": {
    "type": "Point",
    "coordinates": [
     131.12399285,
     -12.46554232
    ]
   },
   "properties": {
    "name": "860 GUNN POINT ROAD KOOLPINYAH 822",
    "locID": "ChIJTzRwIvGvwCwRrsLF_oRoveE",
    "tech": "SATELLITE",
    "upgrade": "UNKNOWN",
    "gnaf_pid": "GANT_717883593"
   }
  },
  {
   "type": "Feature",
   "geometry": {
    "type": "Point",
    "coordinates": [
     131.10382332,
     -12.52138909
    ]
   },
   "properties": {
    "name": "47 CARRUTH ROAD KOOLPINYAH 822",
    "locID": "Ei40NyBDYXJydXRoIFJkLCBUb3JyZW5zIFBhcmsgU0EgNTA2MiwgQXVzdHJhbGlhIjASLgoUChIJ7XV7JjnOsGoRbrL0_L03rdEQLyoUChIJFdpMODnOsGoRfhNeUvOkx-Y",
    "tech": "HFC",
    "upgrade": "UNKNOWN",
    "gnaf_pid": "GANT_719398389"
   }
  },
  {
   "type": "Feature",
   "geometry": {
    "type": "Point",
    "coordinates": [
     131.14008034,
     -12.32467206
    ]
   },
   "properties": {
    "name": "4635 GUNN POINT ROAD KOOLPINYAH 822",
    "locID": "ChIJQ9rClGTDwCwRkLdhbEDhCJU",
    "tech": "SATELLITE",
    "upgrade": "UNKNOWN",
    "gnaf_pid": "GANT_720663356"
   }
  },
  {
   "type": "Feature",
   "geometry": {
    "type": "Point",
    "coordinates": [
     131.12436654,
     -12.46773972
    ]
   },
   "properties": {
    "name": "664 GUNN POINT ROAD KOOLPINYAH 822",
    "locID": "LOC100072121834",
    "tech": "SATELLITE",
    "upgrade": "NULL_NA",
    "gnaf_pid": "GANT_721192984"
   }
  }
 ]
}