{
 "type": "FeatureCollection",
 "generated": "2024-09-30T18:56:51.523260",
 "suburb": "KOOLPINYAH",
 "features": [
  {
   "type": "Feature",
   "geometry": {
    "type": "Point",
    "coordinates": [
     131.11619322,
     -12.21574466
    ]
   },
   "properties": {
    "name": "3820 GUNN POINT ROAD KOOLPINYAH 822",
    "locID": "LOC100072121834",
    "tech": "NULL",
    "upgrade": "NULL_NA",
    "gnaf_pid": "GANT_717883591",
    "tech_change_status": "Not Planned"
   }
  },
  {
   "type": "Feature",
   "geometry": {
    "type": "Point",
    "coordinates": [
     131.12436654,
     -12.46773972
    ]
   },
   "properties": {
    "name": "664 GUNN POINT ROAD KOOLPINYAH 822",
    "locID": "LOC100072121834",
    "tech": "NULL",
    "upgrade": "NULL_NA",
    "gnaf_pid": "GANT_721192984",
    "tech_change_status": "Not Planned"
   }
  }
 ]
}