{
 "type": "FeatureCollection",
 "generated": "2023-09-22T19:19:51.931336",
 "suburb": "LITCHFIELD PARK",
 "features": [
  {
   "type": "Feature",
   "geometry": {
    "type": "Point",
    "coordinates": [
     130.87379725,
     -13.37831297
    ]
   },
   "properties": {
    "name": "3800 DALY RIVER ROAD LITCHFIELD PARK 822",
    "locID": "ChIJNRG8-d3lviwR_pcRfNSIo5c",
    "tech": "SATELLITE",
    "upgrade": "UNKNOWN",
    "gnaf_pid": "GANT_717883428"
   }
  },
  {
   "type": "Feature",
   "geometry": {
    "type": "Point",
    "coordinates": [
     130.90637716,
     -13.06155345
    ]
   },
   "properties": {
    "name": "1447 LITCHFIELD PARK ROAD LITCHFIELD PARK 822",
    "locID": "ChIJXceZgBoXvywRW_Rz-bcBfpI",
    "tech": "SATELLITE",
    "upgrade": "UNKNOWN",
    "gnaf_pid": "GANT_717883760"
   }
  },
  {
   "type": "Feature",
   "geometry": {
    "type": "Point",
    "coordinates": [
     130.78080613,
     -13.15107747
    ]
   },
   "properties": {
    "name": "4995 LITCHFIELD PARK ROAD LITCHFIELD PARK 822",
    "locID": "LOC000118888518",
    "tech": "SATELLITE",
    "upgrade": "NULL_NA",
    "gnaf_pid": "GANT_717883761"
   }
  }
 ]
}