{
 "type": "FeatureCollection",
 "generated": "2024-09-30T19:08:19.331637",
 "suburb": "LITCHFIELD PARK",
 "features": [
  {
   "type": "Feature",
   "geometry": {
    "type": "Point",
    "coordinates": [
     130.78080613,
     -13.15107747
    ]
   },
   "properties": {
    "name": "4995 LITCHFIELD PARK ROAD LITCHFIELD PARK 822",
    "locID": "LOC000118888518",
    "tech": "SATELLITE",
    "upgrade": "NULL_NA",
    "gnaf_pid": "GANT_717883761",
    "tech_change_status": "Not Planned"
   }
  }
 ]
}