{
 "type": "FeatureCollection",
 "generated": "2024-06-05T06:15:06.338549",
 "suburb": "MANBULLOO",
 "features": [
  {
   "type": "Feature",
   "geometry": {
    "type": "Point",
    "coordinates": [
     132.26097497,
     -14.52230079
    ]
   },
   "properties": {
    "name": "581 VICTORIA HIGHWAY MANBULLOO 852",
    "locID": "LOC100079593795",
    "tech": "SATELLITE",
    "upgrade": "NULL_NA",
    "gnaf_pid": "GANT_717754048"
   }
  },
  {
   "type": "Feature",
   "geometry": {
    "type": "Point",
    "coordinates": [
     132.20365165,
     -14.62500316
    ]
   },
   "properties": {
    "name": "1567B VICTORIA HIGHWAY MANBULLOO 852",
    "locID": "LOC000118984591",
    "tech": "SATELLITE",
    "upgrade": "NULL_NA",
    "gnaf_pid": "GANT_717938857"
   }
  }
 ]
}