{
 "type": "FeatureCollection",
 "generated": "2024-07-14T01:37:36.782635",
 "suburb": "NEWCASTLE WATERS",
 "features": [
  {
   "type": "Feature",
   "geometry": {
    "type": "Point",
    "coordinates": [
     133.41007295,
     -17.37250762
    ]
   },
   "properties": {
    "name": "11 DROVERS DRIVE NEWCASTLE WATERS 862",
    "locID": "LOC000022335759",
    "tech": "SATELLITE",
    "upgrade": "NULL_NA",
    "gnaf_pid": "GANT_716697559",
    "tech_change_status": "Not Planned"
   }
  },
  {
   "type": "Feature",
   "geometry": {
    "type": "Point",
    "coordinates": [
     133.41079865,
     -17.37236434
    ]
   },
   "properties": {
    "name": "12 DROVERS DRIVE NEWCASTLE WATERS 862",
    "locID": "LOC000191118012",
    "tech": "SATELLITE",
    "upgrade": "NULL_NA",
    "gnaf_pid": "GANT_716697560",
    "tech_change_status": "Not Planned"
   }
  },
  {
   "type": "Feature",
   "geometry": {
    "type": "Point",
    "coordinates": [
     133.41079798,
     -17.37207275
    ]
   },
   "properties": {
    "name": "14 DROVERS DRIVE NEWCASTLE WATERS 862",
    "locID": "LOC000118983786",
    "tech": "SATELLITE",
    "upgrade": "NULL_NA",
    "gnaf_pid": "GANT_716697561",
    "tech_change_status": "Not Planned"
   }
  },
  {
   "type": "Feature",
   "geometry": {
    "type": "Point",
    "coordinates": [
     133.41077106,
     -17.37168742
    ]
   },
   "properties": {
    "name": "16 DROVERS DRIVE NEWCASTLE WATERS 862",
    "locID": "LOC000118985136",
    "tech": "SATELLITE",
    "upgrade": "NULL_NA",
    "gnaf_pid": "GANT_716697562",
    "tech_change_status": "Not Planned"
   }
  },
  {
   "type": "Feature",
   "geometry": {
    "type": "Point",
    "coordinates": [
     133.409968,
     -17.3719753
    ]
   },
   "properties": {
    "name": "17 DROVERS DRIVE NEWCASTLE WATERS 862",
    "locID": "LOC000118985311",
    "tech": "SATELLITE",
    "upgrade": "NULL_NA",
    "gnaf_pid": "GANT_716697563",
    "tech_change_status": "Not Planned"
   }
  },
  {
   "type": "Feature",
   "geometry": {
    "type": "Point",
    "coordinates": [
     133.41044592,
     -17.37146376
    ]
   },
   "properties": {
    "name": "18 DROVERS DRIVE NEWCASTLE WATERS 862",
    "locID": "LOC000118986462",
    "tech": "SATELLITE",
    "upgrade": "NULL_NA",
    "gnaf_pid": "GANT_716697564",
    "tech_change_status": "Not Planned"
   }
  },
  {
   "type": "Feature",
   "geometry": {
    "type": "Point",
    "coordinates": [
     133.4100618,
     -17.37381069
    ]
   },
   "properties": {
    "name": "1 DROVERS DRIVE NEWCASTLE WATERS 862",
    "locID": "LOC100079130985",
    "tech": "SATELLITE",
    "upgrade": "NULL_NA",
    "gnaf_pid": "GANT_716697566",
    "tech_change_status": "Not Planned"
   }
  },
  {
   "type": "Feature",
   "geometry": {
    "type": "Point",
    "coordinates": [
     133.41007086,
     -17.37351384
    ]
   },
   "properties": {
    "name": "3 DROVERS DRIVE NEWCASTLE WATERS 862",
    "locID": "LOC000186115241",
    "tech": "SATELLITE",
    "upgrade": "NULL_NA",
    "gnaf_pid": "GANT_716697579",
    "tech_change_status": "Not Planned"
   }
  },
  {
   "type": "Feature",
   "geometry": {
    "type": "Point",
    "coordinates": [
     133.41006828,
     -17.37322479
    ]
   },
   "properties": {
    "name": "5 DROVERS DRIVE NEWCASTLE WATERS 862",
    "locID": "LOC000118977393",
    "tech": "SATELLITE",
    "upgrade": "NULL_NA",
    "gnaf_pid": "GANT_716697580",
    "tech_change_status": "Not Planned"
   }
  },
  {
   "type": "Feature",
   "geometry": {
    "type": "Point",
    "coordinates": [
     133.41088687,
     -17.37314072
    ]
   },
   "properties": {
    "name": "6 DROVERS DRIVE NEWCASTLE WATERS 862",
    "locID": "LOC000118979772",
    "tech": "SATELLITE",
    "upgrade": "NULL_NA",
    "gnaf_pid": "GANT_716697581",
    "tech_change_status": "Not Planned"
   }
  },
  {
   "type": "Feature",
   "geometry": {
    "type": "Point",
    "coordinates": [
     133.41007728,
     -17.37293751
    ]
   },
   "properties": {
    "name": "7 DROVERS DRIVE NEWCASTLE WATERS 862",
    "locID": "LOC000118981109",
    "tech": "SATELLITE",
    "upgrade": "NULL_NA",
    "gnaf_pid": "GANT_716697582",
    "tech_change_status": "Not Planned"
   }
  },
  {
   "type": "Feature",
   "geometry": {
    "type": "Point",
    "coordinates": [
     133.41079666,
     -17.37287167
    ]
   },
   "properties": {
    "name": "8 DROVERS DRIVE NEWCASTLE WATERS 862",
    "locID": "LOC000118982384",
    "tech": "SATELLITE",
    "upgrade": "NULL_NA",
    "gnaf_pid": "GANT_717244095",
    "tech_change_status": "Not Planned"
   }
  }
 ]
}