{
 "type": "FeatureCollection",
 "generated": "2023-09-22T20:07:39.641699",
 "suburb": "RANKEN",
 "features": [
  {
   "type": "Feature",
   "geometry": {
    "type": "Point",
    "coordinates": [
     136.7167312,
     -19.82485363
    ]
   },
   "properties": {
    "name": "11655 BARKLY HIGHWAY RANKEN 4825",
    "locID": "ChIJ0dNHdK8cD2oRr-rMMFTZrOU",
    "tech": "SATELLITE",
    "upgrade": "UNKNOWN",
    "gnaf_pid": "GANT_717883080"
   }
  },
  {
   "type": "Feature",
   "geometry": {
    "type": "Point",
    "coordinates": [
     137.18258203,
     -20.12088949
    ]
   },
   "properties": {
    "name": "14059 BARKLY HIGHWAY RANKEN 4825",
    "locID": "ChIJa9VXzJUzDmoRAC3ZhVdCkSg",
    "tech": "SATELLITE",
    "upgrade": "UNKNOWN",
    "gnaf_pid": "GANT_717883082"
   }
  },
  {
   "type": "Feature",
   "geometry": {
    "type": "Point",
    "coordinates": [
     137.82408972,
     -19.70815024
    ]
   },
   "properties": {
    "name": "23061 BARKLY HIGHWAY RANKEN 4825",
    "locID": "ChIJ_4XROD5uEGoRHJvql5yhOJw",
    "tech": "SATELLITE",
    "upgrade": "UNKNOWN",
    "gnaf_pid": "GANT_717883091"
   }
  },
  {
   "type": "Feature",
   "geometry": {
    "type": "Point",
    "coordinates": [
     136.63774226,
     -19.98926311
    ]
   },
   "properties": {
    "name": "9530 BARKLY HIGHWAY RANKEN 4825",
    "locID": "ChIJ7UdgaQzlDmoROkNGtlJD5q8",
    "tech": "SATELLITE",
    "upgrade": "UNKNOWN",
    "gnaf_pid": "GANT_717883092"
   }
  },
  {
   "type": "Feature",
   "geometry": {
    "type": "Point",
    "coordinates": [
     136.71798439,
     -20.04962482
    ]
   },
   "properties": {
    "name": "10795 BARKLY HIGHWAY RANKEN 4825",
    "locID": "ChIJYRFoDo7wDmoRm9k1dI14RuI",
    "tech": "SATELLITE",
    "upgrade": "UNKNOWN",
    "gnaf_pid": "GANT_717938182"
   }
  },
  {
   "type": "Feature",
   "geometry": {
    "type": "Point",
    "coordinates": [
     137.01415204,
     -20.00759854
    ]
   },
   "properties": {
    "name": "14285A BARKLY HIGHWAY RANKEN 4825",
    "locID": "LOC000129519689",
    "tech": "SATELLITE",
    "upgrade": "NULL_NA",
    "gnaf_pid": "GANT_717938183"
   }
  },
  {
   "type": "Feature",
   "geometry": {
    "type": "Point",
    "coordinates": [
     137.03131736,
     -20.00353915
    ]
   },
   "properties": {
    "name": "14285B BARKLY HIGHWAY RANKEN 4825",
    "locID": "LOC000129519691",
    "tech": "SATELLITE",
    "upgrade": "NULL_NA",
    "gnaf_pid": "GANT_717938184"
   }
  },
  {
   "type": "Feature",
   "geometry": {
    "type": "Point",
    "coordinates": [
     137.48549713,
     -20.02289614
    ]
   },
   "properties": {
    "name": "19043 BARKLY HIGHWAY RANKEN 4825",
    "locID": "ChIJUU6vLpwpEGoRi-eq0PIaHOQ",
    "tech": "SATELLITE",
    "upgrade": "UNKNOWN",
    "gnaf_pid": "GANT_717938186"
   }
  },
  {
   "type": "Feature",
   "geometry": {
    "type": "Point",
    "coordinates": [
     137.48825865,
     -20.02368254
    ]
   },
   "properties": {
    "name": "19073 BARKLY HIGHWAY RANKEN 4825",
    "locID": "ChIJuam2-J0pEGoRdELWK9V2bEU",
    "tech": "SATELLITE",
    "upgrade": "UNKNOWN",
    "gnaf_pid": "GANT_717938187"
   }
  },
  {
   "type": "Feature",
   "geometry": {
    "type": "Point",
    "coordinates": [
     137.48899401,
     -20.02354468
    ]
   },
   "properties": {
    "name": "19079 BARKLY HIGHWAY RANKEN 4825",
    "locID": "LOC000129519731",
    "tech": "SATELLITE",
    "upgrade": "NULL_NA",
    "gnaf_pid": "GANT_717938188"
   }
  },
  {
   "type": "Feature",
   "geometry": {
    "type": "Point",
    "coordinates": [
     137.48803038,
     -20.02560736
    ]
   },
   "properties": {
    "name": "19120 BARKLY HIGHWAY RANKEN 4825",
    "locID": "ChIJx2YQ7iQeEGoR0lfcexPpmQo",
    "tech": "SATELLITE",
    "upgrade": "UNKNOWN",
    "gnaf_pid": "GANT_717938189"
   }
  },
  {
   "type": "Feature",
   "geometry": {
    "type": "Point",
    "coordinates": [
     137.56335658,
     -20.03049896
    ]
   },
   "properties": {
    "name": "19864 BARKLY HIGHWAY RANKEN 4825",
    "locID": "ChIJjykfw_kuEGoR1Za05cyKbEI",
    "tech": "SATELLITE",
    "upgrade": "UNKNOWN",
    "gnaf_pid": "GANT_717938190"
   }
  },
  {
   "type": "Feature",
   "geometry": {
    "type": "Point",
    "coordinates": [
     137.83269148,
     -19.96661578
    ]
   },
   "properties": {
    "name": "22854 BARKLY HIGHWAY RANKEN 4825",
    "locID": "ChIJ7Rb8rEJBEGoR8WGGUeCQuGA",
    "tech": "SATELLITE",
    "upgrade": "UNKNOWN",
    "gnaf_pid": "GANT_717938191"
   }
  }
 ]
}