{
 "type": "FeatureCollection",
 "generated": "2024-07-14T01:54:01.153362",
 "suburb": "RANKEN",
 "features": [
  {
   "type": "Feature",
   "geometry": {
    "type": "Point",
    "coordinates": [
     137.01415204,
     -20.00759854
    ]
   },
   "properties": {
    "name": "14285A BARKLY HIGHWAY RANKEN 4825",
    "locID": "LOC000129519689",
    "tech": "SATELLITE",
    "upgrade": "NULL_NA",
    "gnaf_pid": "GANT_717938183",
    "tech_change_status": "Not Planned"
   }
  },
  {
   "type": "Feature",
   "geometry": {
    "type": "Point",
    "coordinates": [
     137.03131736,
     -20.00353915
    ]
   },
   "properties": {
    "name": "14285B BARKLY HIGHWAY RANKEN 4825",
    "locID": "LOC000129519691",
    "tech": "SATELLITE",
    "upgrade": "NULL_NA",
    "gnaf_pid": "GANT_717938184",
    "tech_change_status": "Not Planned"
   }
  },
  {
   "type": "Feature",
   "geometry": {
    "type": "Point",
    "coordinates": [
     137.48899401,
     -20.02354468
    ]
   },
   "properties": {
    "name": "19079 BARKLY HIGHWAY RANKEN 4825",
    "locID": "LOC000129519731",
    "tech": "SATELLITE",
    "upgrade": "NULL_NA",
    "gnaf_pid": "GANT_717938188",
    "tech_change_status": "Not Planned"
   }
  }
 ]
}