{
 "type": "FeatureCollection",
 "generated": "2024-07-14T02:04:59.581041",
 "suburb": "TABLELANDS",
 "features": [
  {
   "type": "Feature",
   "geometry": {
    "type": "Point",
    "coordinates": [
     135.82540144,
     -19.71005017
    ]
   },
   "properties": {
    "name": "10 BARKLY HIGHWAY TABLELANDS 862",
    "locID": "LOC000119002021",
    "tech": "SATELLITE",
    "upgrade": "NULL_NA",
    "gnaf_pid": "GANT_717883093",
    "tech_change_status": "Not Planned"
   }
  },
  {
   "type": "Feature",
   "geometry": {
    "type": "Point",
    "coordinates": [
     135.82629925,
     -19.71014072
    ]
   },
   "properties": {
    "name": "2 BARKLY HIGHWAY TABLELANDS 862",
    "locID": "LOC000118987741",
    "tech": "NULL",
    "upgrade": "NULL_NA",
    "gnaf_pid": "GANT_717883097",
    "tech_change_status": "Not Planned"
   }
  },
  {
   "type": "Feature",
   "geometry": {
    "type": "Point",
    "coordinates": [
     134.0086447,
     -18.73012445
    ]
   },
   "properties": {
    "name": "13907 STUART HIGHWAY TABLELANDS 862",
    "locID": "LOC000118983701",
    "tech": "SATELLITE",
    "upgrade": "NULL_NA",
    "gnaf_pid": "GANT_717884377",
    "tech_change_status": "Not Planned"
   }
  },
  {
   "type": "Feature",
   "geometry": {
    "type": "Point",
    "coordinates": [
     135.41170359,
     -19.38373847
    ]
   },
   "properties": {
    "name": "13167 BARKLY HIGHWAY TABLELANDS 862",
    "locID": "LOC000119004815",
    "tech": "SATELLITE",
    "upgrade": "NULL_NA",
    "gnaf_pid": "GANT_717938192",
    "tech_change_status": "Not Planned"
   }
  },
  {
   "type": "Feature",
   "geometry": {
    "type": "Point",
    "coordinates": [
     135.11923084,
     -18.85969651
    ]
   },
   "properties": {
    "name": "9759 BARKLY HIGHWAY TABLELANDS 862",
    "locID": "LOC000184558713",
    "tech": "SATELLITE",
    "upgrade": "NULL_NA",
    "gnaf_pid": "GANT_717938194",
    "tech_change_status": "Not Planned"
   }
  },
  {
   "type": "Feature",
   "geometry": {
    "type": "Point",
    "coordinates": [
     135.9218204,
     -18.61064584
    ]
   },
   "properties": {
    "name": "13017 TABLELANDS HIGHWAY TABLELANDS 862",
    "locID": "LOC000186642481",
    "tech": "SATELLITE",
    "upgrade": "NULL_NA",
    "gnaf_pid": "GANT_717938812",
    "tech_change_status": "Not Planned"
   }
  },
  {
   "type": "Feature",
   "geometry": {
    "type": "Point",
    "coordinates": [
     136.00728133,
     -19.27612037
    ]
   },
   "properties": {
    "name": "5424 TABLELANDS HIGHWAY TABLELANDS 862",
    "locID": "LOC000118978560",
    "tech": "SATELLITE",
    "upgrade": "NULL_NA",
    "gnaf_pid": "GANT_717938816",
    "tech_change_status": "Not Planned"
   }
  },
  {
   "type": "Feature",
   "geometry": {
    "type": "Point",
    "coordinates": [
     134.10781039,
     -18.84059848
    ]
   },
   "properties": {
    "name": "14930 STUART HIGHWAY TABLELANDS 862",
    "locID": "LOC000118983861",
    "tech": "SATELLITE",
    "upgrade": "NULL_NA",
    "gnaf_pid": "GANT_718014177",
    "tech_change_status": "Not Planned"
   }
  }
 ]
}