{
 "type": "FeatureCollection",
 "generated": "2024-09-12T22:09:37.057938",
 "suburb": "TANAMI EAST",
 "features": [
  {
   "type": "Feature",
   "geometry": {
    "type": "Point",
    "coordinates": [
     132.56916983,
     -16.77773285
    ]
   },
   "properties": {
    "name": "9243 BUCHANAN HIGHWAY TANAMI EAST 852",
    "locID": "LOC000118965157",
    "tech": "SATELLITE",
    "upgrade": "NULL_NA",
    "gnaf_pid": "GANT_717883164",
    "tech_change_status": "Not Planned"
   }
  }
 ]
}