{
 "type": "FeatureCollection",
 "generated": "2023-09-22T20:17:40.571624",
 "suburb": "TANAMI EAST",
 "features": [
  {
   "type": "Feature",
   "geometry": {
    "type": "Point",
    "coordinates": [
     132.56916983,
     -16.77773285
    ]
   },
   "properties": {
    "name": "9243 BUCHANAN HIGHWAY TANAMI EAST 852",
    "locID": "LOC000118965157",
    "tech": "SATELLITE",
    "upgrade": "NULL_NA",
    "gnaf_pid": "GANT_717883164"
   }
  },
  {
   "type": "Feature",
   "geometry": {
    "type": "Point",
    "coordinates": [
     132.69963808,
     -17.01434165
    ]
   },
   "properties": {
    "name": "18698A STUART HIGHWAY TANAMI EAST 852",
    "locID": "ChIJR6eW2tHRVysRFG50_42w7uo",
    "tech": "SATELLITE",
    "upgrade": "UNKNOWN",
    "gnaf_pid": "GANT_717938795"
   }
  },
  {
   "type": "Feature",
   "geometry": {
    "type": "Point",
    "coordinates": [
     133.19002132,
     -17.11312217
    ]
   },
   "properties": {
    "name": "18698B STUART HIGHWAY TANAMI EAST 852",
    "locID": "ChIJad3iZkMzVisRm1r_MpbVt9Y",
    "tech": "SATELLITE",
    "upgrade": "UNKNOWN",
    "gnaf_pid": "GANT_717938796"
   }
  },
  {
   "type": "Feature",
   "geometry": {
    "type": "Point",
    "coordinates": [
     133.19002132,
     -17.11312217
    ]
   },
   "properties": {
    "name": "18698 STUART HIGHWAY TANAMI EAST 852",
    "locID": "ChIJpSkHs1wzVisRbvZZdXKnHvA",
    "tech": "SATELLITE",
    "upgrade": "UNKNOWN",
    "gnaf_pid": "GANT_720396520"
   }
  }
 ]
}