{
 "type": "FeatureCollection",
 "generated": "2024-07-05T06:06:06.745551",
 "suburb": "BAYINDEEN",
 "features": [
  {
   "type": "Feature",
   "geometry": {
    "type": "Point",
    "coordinates": [
     143.15970779,
     -37.3178679
    ]
   },
   "properties": {
    "name": "497 BUANGOR-BEN NEVIS ROAD BAYINDEEN 3375",
    "locID": "LOC000071138086",
    "tech": "SATELLITE",
    "upgrade": "NULL_NA",
    "gnaf_pid": "GAVIC410822347",
    "tech_change_status": "Not Planned"
   }
  },
  {
   "type": "Feature",
   "geometry": {
    "type": "Point",
    "coordinates": [
     143.1464453,
     -37.31576274
    ]
   },
   "properties": {
    "name": "80 VINE ROAD BAYINDEEN 3375",
    "locID": "LOC000034550623",
    "tech": "SATELLITE",
    "upgrade": "NULL_NA",
    "gnaf_pid": "GAVIC410822348",
    "tech_change_status": "Not Planned"
   }
  },
  {
   "type": "Feature",
   "geometry": {
    "type": "Point",
    "coordinates": [
     143.15714015,
     -37.29721335
    ]
   },
   "properties": {
    "name": "725 BUANGOR-BEN NEVIS ROAD BAYINDEEN 3375",
    "locID": "LOC000060459166",
    "tech": "SATELLITE",
    "upgrade": "NULL_NA",
    "gnaf_pid": "GAVIC410822349",
    "tech_change_status": "Not Planned"
   }
  },
  {
   "type": "Feature",
   "geometry": {
    "type": "Point",
    "coordinates": [
     143.1799326,
     -37.30545332
    ]
   },
   "properties": {
    "name": "239 ORDS ORCHARD ROAD BAYINDEEN 3375",
    "locID": "LOC000014696618",
    "tech": "SATELLITE",
    "upgrade": "NULL_NA",
    "gnaf_pid": "GAVIC410848641",
    "tech_change_status": "Not Planned"
   }
  },
  {
   "type": "Feature",
   "geometry": {
    "type": "Point",
    "coordinates": [
     143.15986918,
     -37.31554074
    ]
   },
   "properties": {
    "name": "522 BUANGOR-BEN NEVIS ROAD BAYINDEEN 3375",
    "locID": "LOC000142886163",
    "tech": "SATELLITE",
    "upgrade": "NULL_NA",
    "gnaf_pid": "GAVIC410848642",
    "tech_change_status": "Not Planned"
   }
  },
  {
   "type": "Feature",
   "geometry": {
    "type": "Point",
    "coordinates": [
     143.15977211,
     -37.31441872
    ]
   },
   "properties": {
    "name": "534 BUANGOR-BEN NEVIS ROAD BAYINDEEN 3375",
    "locID": "LOC000143027537",
    "tech": "SATELLITE",
    "upgrade": "NULL_NA",
    "gnaf_pid": "GAVIC421992450",
    "tech_change_status": "Not Planned"
   }
  },
  {
   "type": "Feature",
   "geometry": {
    "type": "Point",
    "coordinates": [
     143.15890989,
     -37.31477043
    ]
   },
   "properties": {
    "name": "533 BUANGOR-BEN NEVIS ROAD BAYINDEEN 3375",
    "locID": "LOC000073084376",
    "tech": "SATELLITE",
    "upgrade": "NULL_NA",
    "gnaf_pid": "GAVIC422034812",
    "tech_change_status": "Not Planned"
   }
  },
  {
   "type": "Feature",
   "geometry": {
    "type": "Point",
    "coordinates": [
     143.15890009,
     -37.30708529
    ]
   },
   "properties": {
    "name": "619 BUANGOR-BEN NEVIS ROAD BAYINDEEN 3375",
    "locID": "LOC000021897148",
    "tech": "SATELLITE",
    "upgrade": "NULL_NA",
    "gnaf_pid": "GAVIC422382931",
    "tech_change_status": "Not Planned"
   }
  },
  {
   "type": "Feature",
   "geometry": {
    "type": "Point",
    "coordinates": [
     143.16349145,
     -37.29926575
    ]
   },
   "properties": {
    "name": "43 ORDS ORCHARD ROAD BAYINDEEN 3375",
    "locID": "LOC000185301793",
    "tech": "SATELLITE",
    "upgrade": "NULL_NA",
    "gnaf_pid": "GAVIC720351068",
    "tech_change_status": "Not Planned"
   }
  }
 ]
}