{
 "type": "FeatureCollection",
 "generated": "2024-03-21T07:02:36.893075",
 "suburb": "BAYNTON EAST",
 "features": [
  {
   "type": "Feature",
   "geometry": {
    "type": "Point",
    "coordinates": [
     144.71203037,
     -37.11804382
    ]
   },
   "properties": {
    "name": "963 MISSION HILL ROAD BAYNTON EAST 3444",
    "locID": "LOC000039544472",
    "tech": "WIRELESS",
    "upgrade": "NULL_NA",
    "gnaf_pid": "GAVIC410846891"
   }
  },
  {
   "type": "Feature",
   "geometry": {
    "type": "Point",
    "coordinates": [
     144.73284843,
     -37.1336949
    ]
   },
   "properties": {
    "name": "80 SCRUBBY CAMP ROAD BAYNTON EAST 3444",
    "locID": "LOC000069125960",
    "tech": "WIRELESS",
    "upgrade": "NULL_NA",
    "gnaf_pid": "GAVIC423669170"
   }
  },
  {
   "type": "Feature",
   "geometry": {
    "type": "Point",
    "coordinates": [
     144.71643549,
     -37.111903
    ]
   },
   "properties": {
    "name": "810 TOOBORAC-BAYNTON ROAD BAYNTON EAST 3444",
    "locID": "LOC000114771217",
    "tech": "WIRELESS",
    "upgrade": "NULL_NA",
    "gnaf_pid": "GAVIC423905777"
   }
  },
  {
   "type": "Feature",
   "geometry": {
    "type": "Point",
    "coordinates": [
     144.71425,
     -37.10304691
    ]
   },
   "properties": {
    "name": "720 TOOBORAC-BAYNTON ROAD BAYNTON EAST 3444",
    "locID": "LOC000124972262",
    "tech": "SATELLITE",
    "upgrade": "NULL_NA",
    "gnaf_pid": "GAVIC424632511"
   }
  }
 ]
}