{
 "type": "FeatureCollection",
 "generated": "2023-10-23T10:00:31.714541",
 "suburb": "BAYNTON EAST",
 "features": [
  {
   "type": "Feature",
   "geometry": {
    "type": "Point",
    "coordinates": [
     144.71203037,
     -37.11804382
    ]
   },
   "properties": {
    "name": "963 MISSION HILL ROAD BAYNTON EAST 3444",
    "locID": "LOC000039544472",
    "tech": "SATELLITE",
    "upgrade": "NULL_NA",
    "gnaf_pid": "GAVIC410846891"
   }
  },
  {
   "type": "Feature",
   "geometry": {
    "type": "Point",
    "coordinates": [
     144.71566523,
     -37.11850641
    ]
   },
   "properties": {
    "name": "1008 MISSION HILL ROAD BAYNTON EAST 3444",
    "locID": "ChIJRS6Ip5N012oRltVTFXRjRVg",
    "tech": "SATELLITE",
    "upgrade": "UNKNOWN",
    "gnaf_pid": "GAVIC420261307"
   }
  },
  {
   "type": "Feature",
   "geometry": {
    "type": "Point",
    "coordinates": [
     144.73284843,
     -37.1336949
    ]
   },
   "properties": {
    "name": "80 SCRUBBY CAMP ROAD BAYNTON EAST 3444",
    "locID": "LOC000069125960",
    "tech": "SATELLITE",
    "upgrade": "NULL_NA",
    "gnaf_pid": "GAVIC423669170"
   }
  },
  {
   "type": "Feature",
   "geometry": {
    "type": "Point",
    "coordinates": [
     144.71643549,
     -37.111903
    ]
   },
   "properties": {
    "name": "810 TOOBORAC-BAYNTON ROAD BAYNTON EAST 3444",
    "locID": "LOC000114771217",
    "tech": "SATELLITE",
    "upgrade": "NULL_NA",
    "gnaf_pid": "GAVIC423905777"
   }
  },
  {
   "type": "Feature",
   "geometry": {
    "type": "Point",
    "coordinates": [
     144.71425,
     -37.10304691
    ]
   },
   "properties": {
    "name": "720 TOOBORAC-BAYNTON ROAD BAYNTON EAST 3444",
    "locID": "LOC000124972262",
    "tech": "SATELLITE",
    "upgrade": "NULL_NA",
    "gnaf_pid": "GAVIC424632511"
   }
  },
  {
   "type": "Feature",
   "geometry": {
    "type": "Point",
    "coordinates": [
     144.71218122,
     -37.12133935
    ]
   },
   "properties": {
    "name": "926 MISSION HILL ROAD BAYNTON EAST 3444",
    "locID": "ChIJG5VLPpF012oRDqA0gqbUzok",
    "tech": "SATELLITE",
    "upgrade": "UNKNOWN",
    "gnaf_pid": "GAVIC720054521"
   }
  },
  {
   "type": "Feature",
   "geometry": {
    "type": "Point",
    "coordinates": [
     144.70358147,
     -37.13177312
    ]
   },
   "properties": {
    "name": "796 MISSION HILL ROAD BAYNTON EAST 3444",
    "locID": "ChIJQZaiz6V012oRQf_EcTjVUJw",
    "tech": "SATELLITE",
    "upgrade": "UNKNOWN",
    "gnaf_pid": "GAVIC720743492"
   }
  },
  {
   "type": "Feature",
   "geometry": {
    "type": "Point",
    "coordinates": [
     144.73279156,
     -37.1335189
    ]
   },
   "properties": {
    "name": "78 SCRUBBY CAMP ROAD BAYNTON EAST 3444",
    "locID": "ChIJk5Anned012oRFltGq2Lqwu0",
    "tech": "SATELLITE",
    "upgrade": "UNKNOWN",
    "gnaf_pid": "GAVIC720822235"
   }
  }
 ]
}