{
 "type": "FeatureCollection",
 "generated": "2024-07-05T06:08:28.523346",
 "suburb": "BAYNTON EAST",
 "features": [
  {
   "type": "Feature",
   "geometry": {
    "type": "Point",
    "coordinates": [
     144.71203037,
     -37.11804382
    ]
   },
   "properties": {
    "name": "963 MISSION HILL ROAD BAYNTON EAST 3444",
    "locID": "LOC000039544472",
    "tech": "WIRELESS",
    "upgrade": "NULL_NA",
    "gnaf_pid": "GAVIC410846891",
    "tech_change_status": "Not Planned",
    "program_type": "Fixed Wireless and Satellite Upgrade Program",
    "target_eligibility_quarter": "NA"
   }
  },
  {
   "type": "Feature",
   "geometry": {
    "type": "Point",
    "coordinates": [
     144.73284843,
     -37.1336949
    ]
   },
   "properties": {
    "name": "80 SCRUBBY CAMP ROAD BAYNTON EAST 3444",
    "locID": "LOC000069125960",
    "tech": "WIRELESS",
    "upgrade": "NULL_NA",
    "gnaf_pid": "GAVIC423669170",
    "tech_change_status": "Not Planned",
    "program_type": "Fixed Wireless and Satellite Upgrade Program",
    "target_eligibility_quarter": "NA"
   }
  },
  {
   "type": "Feature",
   "geometry": {
    "type": "Point",
    "coordinates": [
     144.71643549,
     -37.111903
    ]
   },
   "properties": {
    "name": "810 TOOBORAC-BAYNTON ROAD BAYNTON EAST 3444",
    "locID": "LOC000114771217",
    "tech": "WIRELESS",
    "upgrade": "NULL_NA",
    "gnaf_pid": "GAVIC423905777",
    "tech_change_status": "Not Planned",
    "program_type": "Fixed Wireless and Satellite Upgrade Program",
    "target_eligibility_quarter": "NA"
   }
  },
  {
   "type": "Feature",
   "geometry": {
    "type": "Point",
    "coordinates": [
     144.71425,
     -37.10304691
    ]
   },
   "properties": {
    "name": "720 TOOBORAC-BAYNTON ROAD BAYNTON EAST 3444",
    "locID": "LOC000124972262",
    "tech": "SATELLITE",
    "upgrade": "NULL_NA",
    "gnaf_pid": "GAVIC424632511",
    "tech_change_status": "Not Planned"
   }
  }
 ]
}