{
 "type": "FeatureCollection",
 "generated": "2024-07-05T06:22:10.258440",
 "suburb": "BELLBIRD CREEK",
 "features": [
  {
   "type": "Feature",
   "geometry": {
    "type": "Point",
    "coordinates": [
     148.81612529,
     -37.6534358
    ]
   },
   "properties": {
    "name": "3854 PRINCES HIGHWAY BELLBIRD CREEK 3889",
    "locID": "LOC000104363279",
    "tech": "SATELLITE",
    "upgrade": "NULL_NA",
    "gnaf_pid": "GAVIC422317865",
    "tech_change_status": "Not Planned"
   }
  },
  {
   "type": "Feature",
   "geometry": {
    "type": "Point",
    "coordinates": [
     148.8172351,
     -37.6524634
    ]
   },
   "properties": {
    "name": "3872 PRINCES HIGHWAY BELLBIRD CREEK 3889",
    "locID": "LOC000084692304",
    "tech": "SATELLITE",
    "upgrade": "NULL_NA",
    "gnaf_pid": "GAVIC422317867",
    "tech_change_status": "Not Planned"
   }
  }
 ]
}