{
 "type": "FeatureCollection",
 "generated": "2024-07-24T02:56:21.499252",
 "suburb": "BOLANGUM",
 "features": [
  {
   "type": "Feature",
   "geometry": {
    "type": "Point",
    "coordinates": [
     142.96532214,
     -36.74379698
    ]
   },
   "properties": {
    "name": "869 MARNOO EAST ROAD BOLANGUM 3387",
    "locID": "LOC000048196441",
    "tech": "SATELLITE",
    "upgrade": "NULL_NA",
    "gnaf_pid": "GAVIC423362752",
    "tech_change_status": "Not Planned"
   }
  }
 ]
}