{
 "type": "FeatureCollection",
 "generated": "2024-04-12T13:33:11.609360",
 "suburb": "BRIMBOAL",
 "features": [
  {
   "type": "Feature",
   "geometry": {
    "type": "Point",
    "coordinates": [
     141.41607395,
     -37.40517969
    ]
   },
   "properties": {
    "name": "1911 CASTERTON-EDENHOPE ROAD BRIMBOAL 3312",
    "locID": "LOC000015212664",
    "tech": "SATELLITE",
    "upgrade": "NULL_NA",
    "gnaf_pid": "GAVIC422134834"
   }
  },
  {
   "type": "Feature",
   "geometry": {
    "type": "Point",
    "coordinates": [
     141.38847995,
     -37.3774247
    ]
   },
   "properties": {
    "name": "2336 CASTERTON-EDENHOPE ROAD BRIMBOAL 3312",
    "locID": "LOC000143057374",
    "tech": "SATELLITE",
    "upgrade": "NULL_NA",
    "gnaf_pid": "GAVIC422134835"
   }
  },
  {
   "type": "Feature",
   "geometry": {
    "type": "Point",
    "coordinates": [
     141.36947492,
     -37.42141013
    ]
   },
   "properties": {
    "name": "1116 WARROCK ROAD BRIMBOAL 3312",
    "locID": "LOC000115748501",
    "tech": "SATELLITE",
    "upgrade": "NULL_NA",
    "gnaf_pid": "GAVIC423125847"
   }
  },
  {
   "type": "Feature",
   "geometry": {
    "type": "Point",
    "coordinates": [
     141.40300456,
     -37.37727689
    ]
   },
   "properties": {
    "name": "103 FITZGERALDS LANE BRIMBOAL 3312",
    "locID": "LOC000093979435",
    "tech": "SATELLITE",
    "upgrade": "NULL_NA",
    "gnaf_pid": "GAVIC423140658"
   }
  }
 ]
}