{
 "type": "FeatureCollection",
 "generated": "2023-10-23T17:09:19.275665",
 "suburb": "CARALULUP",
 "features": [
  {
   "type": "Feature",
   "geometry": {
    "type": "Point",
    "coordinates": [
     143.65645719,
     -37.20776943
    ]
   },
   "properties": {
    "name": "231 QUARRY TRACK CARALULUP 3371",
    "locID": "ChIJLxkdiYwZ0WoRaltClKx8JcE",
    "tech": "SATELLITE",
    "upgrade": "UNKNOWN",
    "gnaf_pid": "GAVIC414315819"
   }
  },
  {
   "type": "Feature",
   "geometry": {
    "type": "Point",
    "coordinates": [
     143.63816809,
     -37.20256046
    ]
   },
   "properties": {
    "name": "1670 LEXTON-TALBOT ROAD CARALULUP 3371",
    "locID": "ChIJqX9rwCQa0WoRvN-uNsF4F_Q",
    "tech": "SATELLITE",
    "upgrade": "UNKNOWN",
    "gnaf_pid": "GAVIC419952473"
   }
  },
  {
   "type": "Feature",
   "geometry": {
    "type": "Point",
    "coordinates": [
     143.6657007,
     -37.18579977
    ]
   },
   "properties": {
    "name": "1890 LEXTON-TALBOT ROAD CARALULUP 3371",
    "locID": "ChIJQwfwLXcZ0WoRXgBsAp6AM7I",
    "tech": "SATELLITE",
    "upgrade": "UNKNOWN",
    "gnaf_pid": "GAVIC420267280"
   }
  },
  {
   "type": "Feature",
   "geometry": {
    "type": "Point",
    "coordinates": [
     143.64195059,
     -37.19404363
    ]
   },
   "properties": {
    "name": "15 NORBURYS ROAD CARALULUP 3371",
    "locID": "ChIJS5bkITsa0WoRXTADrETzfqA",
    "tech": "SATELLITE",
    "upgrade": "UNKNOWN",
    "gnaf_pid": "GAVIC420347773"
   }
  },
  {
   "type": "Feature",
   "geometry": {
    "type": "Point",
    "coordinates": [
     143.65026893,
     -37.19112728
    ]
   },
   "properties": {
    "name": "1735 LEXTON-TALBOT ROAD CARALULUP 3371",
    "locID": "LOC000083269756",
    "tech": "SATELLITE",
    "upgrade": "NULL_NA",
    "gnaf_pid": "GAVIC420568223"
   }
  },
  {
   "type": "Feature",
   "geometry": {
    "type": "Point",
    "coordinates": [
     143.63798635,
     -37.20060187
    ]
   },
   "properties": {
    "name": "1555 LEXTON-TALBOT ROAD CARALULUP 3371",
    "locID": "ChIJVwsMCmsa0WoRz5KUkQA_EBw",
    "tech": "SATELLITE",
    "upgrade": "UNKNOWN",
    "gnaf_pid": "GAVIC420570031"
   }
  },
  {
   "type": "Feature",
   "geometry": {
    "type": "Point",
    "coordinates": [
     143.65970168,
     -37.18723586
    ]
   },
   "properties": {
    "name": "1835 LEXTON-TALBOT ROAD CARALULUP 3371",
    "locID": "LOC000072932745",
    "tech": "SATELLITE",
    "upgrade": "NULL_NA",
    "gnaf_pid": "GAVIC420579356"
   }
  },
  {
   "type": "Feature",
   "geometry": {
    "type": "Point",
    "coordinates": [
     143.66286343,
     -37.18652409
    ]
   },
   "properties": {
    "name": "1860 LEXTON-TALBOT ROAD CARALULUP 3371",
    "locID": "ChIJ9fBf-nAZ0WoRM4DaYKBM4VU",
    "tech": "SATELLITE",
    "upgrade": "UNKNOWN",
    "gnaf_pid": "GAVIC420898150"
   }
  },
  {
   "type": "Feature",
   "geometry": {
    "type": "Point",
    "coordinates": [
     143.6373638,
     -37.20610748
    ]
   },
   "properties": {
    "name": "1515 LEXTON-TALBOT ROAD CARALULUP 3371",
    "locID": "ChIJ-zK1PxQa0WoRYN0CYk05s0w",
    "tech": "SATELLITE",
    "upgrade": "UNKNOWN",
    "gnaf_pid": "GAVIC421167654"
   }
  },
  {
   "type": "Feature",
   "geometry": {
    "type": "Point",
    "coordinates": [
     143.65900899,
     -37.18773997
    ]
   },
   "properties": {
    "name": "1845 LEXTON-TALBOT ROAD CARALULUP 3371",
    "locID": "ChIJaeIeBHwZ0WoRDrlhAAdORUM",
    "tech": "SATELLITE",
    "upgrade": "UNKNOWN",
    "gnaf_pid": "GAVIC421799545"
   }
  },
  {
   "type": "Feature",
   "geometry": {
    "type": "Point",
    "coordinates": [
     143.65212215,
     -37.19079419
    ]
   },
   "properties": {
    "name": "1754 LEXTON-TALBOT ROAD CARALULUP 3371",
    "locID": "LOC000042255639",
    "tech": "SATELLITE",
    "upgrade": "NULL_NA",
    "gnaf_pid": "GAVIC421799546"
   }
  }
 ]
}