{
 "type": "FeatureCollection",
 "generated": "2024-07-05T11:49:04.907759",
 "suburb": "CARALULUP",
 "features": [
  {
   "type": "Feature",
   "geometry": {
    "type": "Point",
    "coordinates": [
     143.65026893,
     -37.19112728
    ]
   },
   "properties": {
    "name": "1735 LEXTON-TALBOT ROAD CARALULUP 3371",
    "locID": "LOC000083269756",
    "tech": "SATELLITE",
    "upgrade": "NULL_NA",
    "gnaf_pid": "GAVIC420568223",
    "tech_change_status": "Not Planned"
   }
  },
  {
   "type": "Feature",
   "geometry": {
    "type": "Point",
    "coordinates": [
     143.65970168,
     -37.18723586
    ]
   },
   "properties": {
    "name": "1835 LEXTON-TALBOT ROAD CARALULUP 3371",
    "locID": "LOC000072932745",
    "tech": "SATELLITE",
    "upgrade": "NULL_NA",
    "gnaf_pid": "GAVIC420579356",
    "tech_change_status": "Not Planned"
   }
  },
  {
   "type": "Feature",
   "geometry": {
    "type": "Point",
    "coordinates": [
     143.65212215,
     -37.19079419
    ]
   },
   "properties": {
    "name": "1754 LEXTON-TALBOT ROAD CARALULUP 3371",
    "locID": "LOC000042255639",
    "tech": "SATELLITE",
    "upgrade": "NULL_NA",
    "gnaf_pid": "GAVIC421799546",
    "tech_change_status": "Not Planned"
   }
  }
 ]
}