{
 "type": "FeatureCollection",
 "generated": "2024-07-05T12:34:43.393710",
 "suburb": "CARRAJUNG SOUTH",
 "features": [
  {
   "type": "Feature",
   "geometry": {
    "type": "Point",
    "coordinates": [
     146.77976861,
     -38.37799095
    ]
   },
   "properties": {
    "name": "187 CARRAJUNG-WOODSIDE ROAD CARRAJUNG SOUTH 3844",
    "locID": "LOC000098753558",
    "tech": "SATELLITE",
    "upgrade": "NULL_NA",
    "gnaf_pid": "GAVIC422134501",
    "tech_change_status": "Not Planned"
   }
  },
  {
   "type": "Feature",
   "geometry": {
    "type": "Point",
    "coordinates": [
     146.7923436,
     -38.38051029
    ]
   },
   "properties": {
    "name": "312 CARRAJUNG-WOODSIDE ROAD CARRAJUNG SOUTH 3844",
    "locID": "LOC000046802812",
    "tech": "SATELLITE",
    "upgrade": "NULL_NA",
    "gnaf_pid": "GAVIC422134502",
    "tech_change_status": "Not Planned"
   }
  },
  {
   "type": "Feature",
   "geometry": {
    "type": "Point",
    "coordinates": [
     146.79597232,
     -38.38325328
    ]
   },
   "properties": {
    "name": "354 CARRAJUNG-WOODSIDE ROAD CARRAJUNG SOUTH 3844",
    "locID": "LOC000091926934",
    "tech": "SATELLITE",
    "upgrade": "NULL_NA",
    "gnaf_pid": "GAVIC422134503",
    "tech_change_status": "Not Planned"
   }
  },
  {
   "type": "Feature",
   "geometry": {
    "type": "Point",
    "coordinates": [
     146.78506599,
     -38.37886603
    ]
   },
   "properties": {
    "name": "235 CARRAJUNG-WOODSIDE ROAD CARRAJUNG SOUTH 3844",
    "locID": "LOC000080282895",
    "tech": "SATELLITE",
    "upgrade": "NULL_NA",
    "gnaf_pid": "GAVIC422282323",
    "tech_change_status": "Not Planned"
   }
  },
  {
   "type": "Feature",
   "geometry": {
    "type": "Point",
    "coordinates": [
     146.8247262,
     -38.40243591
    ]
   },
   "properties": {
    "name": "1 POGUES ROAD CARRAJUNG SOUTH 3844",
    "locID": "LOC000125733360",
    "tech": "SATELLITE",
    "upgrade": "NULL_NA",
    "gnaf_pid": "GAVIC422317377",
    "tech_change_status": "Not Planned"
   }
  },
  {
   "type": "Feature",
   "geometry": {
    "type": "Point",
    "coordinates": [
     146.76157648,
     -38.36758224
    ]
   },
   "properties": {
    "name": "140 CONNECTION ROAD CARRAJUNG SOUTH 3844",
    "locID": "LOC000100116157",
    "tech": "SATELLITE",
    "upgrade": "NULL_NA",
    "gnaf_pid": "GAVIC423065735",
    "tech_change_status": "Not Planned"
   }
  },
  {
   "type": "Feature",
   "geometry": {
    "type": "Point",
    "coordinates": [
     146.79776125,
     -38.38382725
    ]
   },
   "properties": {
    "name": "367 CARRAJUNG-WOODSIDE ROAD CARRAJUNG SOUTH 3844",
    "locID": "LOC000009779621",
    "tech": "SATELLITE",
    "upgrade": "NULL_NA",
    "gnaf_pid": "GAVIC423101886",
    "tech_change_status": "Not Planned"
   }
  },
  {
   "type": "Feature",
   "geometry": {
    "type": "Point",
    "coordinates": [
     146.79776693,
     -38.38382544
    ]
   },
   "properties": {
    "name": "367A CARRAJUNG-WOODSIDE ROAD CARRAJUNG SOUTH 3844",
    "locID": "LOC000148368173",
    "tech": "SATELLITE",
    "upgrade": "NULL_NA",
    "gnaf_pid": "GAVIC425482107",
    "tech_change_status": "Not Planned"
   }
  }
 ]
}