{
 "type": "FeatureCollection",
 "generated": "2023-10-23T17:53:01.899168",
 "suburb": "CARRAJUNG SOUTH",
 "features": [
  {
   "type": "Feature",
   "geometry": {
    "type": "Point",
    "coordinates": [
     146.77976861,
     -38.37799095
    ]
   },
   "properties": {
    "name": "187 CARRAJUNG-WOODSIDE ROAD CARRAJUNG SOUTH 3844",
    "locID": "LOC000098753558",
    "tech": "SATELLITE",
    "upgrade": "NULL_NA",
    "gnaf_pid": "GAVIC422134501"
   }
  },
  {
   "type": "Feature",
   "geometry": {
    "type": "Point",
    "coordinates": [
     146.7923436,
     -38.38051029
    ]
   },
   "properties": {
    "name": "312 CARRAJUNG-WOODSIDE ROAD CARRAJUNG SOUTH 3844",
    "locID": "LOC000046802812",
    "tech": "SATELLITE",
    "upgrade": "NULL_NA",
    "gnaf_pid": "GAVIC422134502"
   }
  },
  {
   "type": "Feature",
   "geometry": {
    "type": "Point",
    "coordinates": [
     146.79597232,
     -38.38325328
    ]
   },
   "properties": {
    "name": "354 CARRAJUNG-WOODSIDE ROAD CARRAJUNG SOUTH 3844",
    "locID": "LOC000091926934",
    "tech": "SATELLITE",
    "upgrade": "NULL_NA",
    "gnaf_pid": "GAVIC422134503"
   }
  },
  {
   "type": "Feature",
   "geometry": {
    "type": "Point",
    "coordinates": [
     146.80643475,
     -38.3901054
    ]
   },
   "properties": {
    "name": "472 CARRAJUNG-WOODSIDE ROAD CARRAJUNG SOUTH 3844",
    "locID": "ChIJw3sQsPE2KWsRFoO0yRA2sRY",
    "tech": "SATELLITE",
    "upgrade": "UNKNOWN",
    "gnaf_pid": "GAVIC422134504"
   }
  },
  {
   "type": "Feature",
   "geometry": {
    "type": "Point",
    "coordinates": [
     146.78506599,
     -38.37886603
    ]
   },
   "properties": {
    "name": "235 CARRAJUNG-WOODSIDE ROAD CARRAJUNG SOUTH 3844",
    "locID": "LOC000080282895",
    "tech": "SATELLITE",
    "upgrade": "NULL_NA",
    "gnaf_pid": "GAVIC422282323"
   }
  },
  {
   "type": "Feature",
   "geometry": {
    "type": "Point",
    "coordinates": [
     146.8247262,
     -38.40243591
    ]
   },
   "properties": {
    "name": "1 POGUES ROAD CARRAJUNG SOUTH 3844",
    "locID": "LOC000125733360",
    "tech": "SATELLITE",
    "upgrade": "NULL_NA",
    "gnaf_pid": "GAVIC422317377"
   }
  },
  {
   "type": "Feature",
   "geometry": {
    "type": "Point",
    "coordinates": [
     146.76157648,
     -38.36758224
    ]
   },
   "properties": {
    "name": "140 CONNECTION ROAD CARRAJUNG SOUTH 3844",
    "locID": "LOC000100116157",
    "tech": "SATELLITE",
    "upgrade": "NULL_NA",
    "gnaf_pid": "GAVIC423065735"
   }
  },
  {
   "type": "Feature",
   "geometry": {
    "type": "Point",
    "coordinates": [
     146.77807982,
     -38.37636308
    ]
   },
   "properties": {
    "name": "17 MACNEES ROAD CARRAJUNG SOUTH 3844",
    "locID": "ChIJDaVB2RY3KWsRGX0KWAq8VjU",
    "tech": "SATELLITE",
    "upgrade": "UNKNOWN",
    "gnaf_pid": "GAVIC423079857"
   }
  },
  {
   "type": "Feature",
   "geometry": {
    "type": "Point",
    "coordinates": [
     146.79776125,
     -38.38382725
    ]
   },
   "properties": {
    "name": "367 CARRAJUNG-WOODSIDE ROAD CARRAJUNG SOUTH 3844",
    "locID": "LOC000009779621",
    "tech": "SATELLITE",
    "upgrade": "NULL_NA",
    "gnaf_pid": "GAVIC423101886"
   }
  },
  {
   "type": "Feature",
   "geometry": {
    "type": "Point",
    "coordinates": [
     146.79776693,
     -38.38382544
    ]
   },
   "properties": {
    "name": "367A CARRAJUNG-WOODSIDE ROAD CARRAJUNG SOUTH 3844",
    "locID": "LOC000148368173",
    "tech": "SATELLITE",
    "upgrade": "NULL_NA",
    "gnaf_pid": "GAVIC425482107"
   }
  },
  {
   "type": "Feature",
   "geometry": {
    "type": "Point",
    "coordinates": [
     146.76035492,
     -38.36440893
    ]
   },
   "properties": {
    "name": "178 CONNECTION ROAD CARRAJUNG SOUTH 3844",
    "locID": "ChIJe2QLB0E3KWsRSK6cHEjSAgY",
    "tech": "SATELLITE",
    "upgrade": "UNKNOWN",
    "gnaf_pid": "GAVIC425515147"
   }
  },
  {
   "type": "Feature",
   "geometry": {
    "type": "Point",
    "coordinates": [
     146.77830273,
     -38.37464276
    ]
   },
   "properties": {
    "name": "35 MACNEES ROAD CARRAJUNG SOUTH 3844",
    "locID": "ChIJSTWa_Bg3KWsRr1WLUn71CSo",
    "tech": "SATELLITE",
    "upgrade": "UNKNOWN",
    "gnaf_pid": "GAVIC719995762"
   }
  },
  {
   "type": "Feature",
   "geometry": {
    "type": "Point",
    "coordinates": [
     146.76189558,
     -38.36206355
    ]
   },
   "properties": {
    "name": "208 CONNECTION ROAD CARRAJUNG SOUTH 3844",
    "locID": "ChIJFQ-sMEc3KWsRIbTSgd1MrYY",
    "tech": "SATELLITE",
    "upgrade": "UNKNOWN",
    "gnaf_pid": "GAVIC720452538"
   }
  }
 ]
}