{
 "type": "FeatureCollection",
 "generated": "2024-07-05T14:02:58.466029",
 "suburb": "CHIRRIP",
 "features": [
  {
   "type": "Feature",
   "geometry": {
    "type": "Point",
    "coordinates": [
     143.11007731,
     -36.14418646
    ]
   },
   "properties": {
    "name": "496 CORACK-WYCHEPROOF ROAD CHIRRIP 3525",
    "locID": "LOC000041087885",
    "tech": "WIRELESS",
    "upgrade": "NULL_NA",
    "gnaf_pid": "GAVIC421988225",
    "tech_change_status": "Not Planned",
    "program_type": "Fixed Wireless and Satellite Upgrade Program",
    "target_eligibility_quarter": "Dec 2024"
   }
  },
  {
   "type": "Feature",
   "geometry": {
    "type": "Point",
    "coordinates": [
     143.13535338,
     -36.19250233
    ]
   },
   "properties": {
    "name": "149 GILBERT ROAD CHIRRIP 3525",
    "locID": "LOC000075276960",
    "tech": "SATELLITE",
    "upgrade": "NULL_NA",
    "gnaf_pid": "GAVIC424071325",
    "tech_change_status": "Not Planned"
   }
  },
  {
   "type": "Feature",
   "geometry": {
    "type": "Point",
    "coordinates": [
     143.16008322,
     -36.16452418
    ]
   },
   "properties": {
    "name": "246 PINKS ROAD CHIRRIP 3525",
    "locID": "LOC000100282923",
    "tech": "WIRELESS",
    "upgrade": "NULL_NA",
    "gnaf_pid": "GAVIC424071957",
    "tech_change_status": "Not Planned",
    "program_type": "Fixed Wireless and Satellite Upgrade Program",
    "target_eligibility_quarter": "Dec 2024"
   }
  }
 ]
}