{
 "type": "FeatureCollection",
 "generated": "2024-07-24T13:08:43.152158",
 "suburb": "DOUBLE BRIDGES",
 "features": [
  {
   "type": "Feature",
   "geometry": {
    "type": "Point",
    "coordinates": [
     147.85922055,
     -37.63850661
    ]
   },
   "properties": {
    "name": "375 BIG CREEK ROAD DOUBLE BRIDGES 3893",
    "locID": "LOC000022841856",
    "tech": "SATELLITE",
    "upgrade": "NULL_NA",
    "gnaf_pid": "GAVIC422277857",
    "tech_change_status": "Not Planned"
   }
  },
  {
   "type": "Feature",
   "geometry": {
    "type": "Point",
    "coordinates": [
     147.89597025,
     -37.64125814
    ]
   },
   "properties": {
    "name": "850 GREAT ALPINE ROAD DOUBLE BRIDGES 3893",
    "locID": "LOC000031113493",
    "tech": "SATELLITE",
    "upgrade": "NULL_NA",
    "gnaf_pid": "GAVIC423968564",
    "tech_change_status": "Not Planned"
   }
  }
 ]
}