{
 "type": "FeatureCollection",
 "generated": "2023-10-24T00:12:26.012870",
 "suburb": "DOUBLE BRIDGES",
 "features": [
  {
   "type": "Feature",
   "geometry": {
    "type": "Point",
    "coordinates": [
     147.85922055,
     -37.63850661
    ]
   },
   "properties": {
    "name": "375 BIG CREEK ROAD DOUBLE BRIDGES 3893",
    "locID": "LOC000022841856",
    "tech": "SATELLITE",
    "upgrade": "NULL_NA",
    "gnaf_pid": "GAVIC422277857"
   }
  },
  {
   "type": "Feature",
   "geometry": {
    "type": "Point",
    "coordinates": [
     147.84567524,
     -37.63385918
    ]
   },
   "properties": {
    "name": "356 GIN CREEK ROAD DOUBLE BRIDGES 3893",
    "locID": "ChIJLWr2gxJuJWsRcUYtvk-V3U0",
    "tech": "SATELLITE",
    "upgrade": "UNKNOWN",
    "gnaf_pid": "GAVIC423922628"
   }
  },
  {
   "type": "Feature",
   "geometry": {
    "type": "Point",
    "coordinates": [
     147.89597025,
     -37.64125814
    ]
   },
   "properties": {
    "name": "850 GREAT ALPINE ROAD DOUBLE BRIDGES 3893",
    "locID": "LOC000031113493",
    "tech": "SATELLITE",
    "upgrade": "NULL_NA",
    "gnaf_pid": "GAVIC423968564"
   }
  },
  {
   "type": "Feature",
   "geometry": {
    "type": "Point",
    "coordinates": [
     147.84846689,
     -37.62954473
    ]
   },
   "properties": {
    "name": "356 BIG CREEK ROAD DOUBLE BRIDGES 3893",
    "locID": "ChIJnSX1qXRuJWsRtue6w0eHTHk",
    "tech": "SATELLITE",
    "upgrade": "UNKNOWN",
    "gnaf_pid": "GAVIC424873224"
   }
  }
 ]
}