{
 "type": "FeatureCollection",
 "generated": "2024-05-25T00:21:24.045609",
 "suburb": "EAST SALE",
 "features": [
  {
   "type": "Feature",
   "geometry": {
    "type": "Point",
    "coordinates": [
     147.11498739,
     -38.10401575
    ]
   },
   "properties": {
    "name": "415 AERODROME ROAD EAST SALE 3852",
    "locID": "LOC000089092477",
    "tech": "WIRELESS",
    "upgrade": "NULL_NA",
    "gnaf_pid": "GAVIC423055064"
   }
  },
  {
   "type": "Feature",
   "geometry": {
    "type": "Point",
    "coordinates": [
     147.11559128,
     -38.10456521
    ]
   },
   "properties": {
    "name": "422 AERODROME ROAD EAST SALE 3852",
    "locID": "LOC000080776618",
    "tech": "WIRELESS",
    "upgrade": "NULL_NA",
    "gnaf_pid": "GAVIC423055066"
   }
  },
  {
   "type": "Feature",
   "geometry": {
    "type": "Point",
    "coordinates": [
     147.11856849,
     -38.10495289
    ]
   },
   "properties": {
    "name": "450 AERODROME ROAD EAST SALE 3852",
    "locID": "LOC000075926585",
    "tech": "WIRELESS",
    "upgrade": "NULL_NA",
    "gnaf_pid": "GAVIC423055067"
   }
  },
  {
   "type": "Feature",
   "geometry": {
    "type": "Point",
    "coordinates": [
     147.12108024,
     -38.1052444
    ]
   },
   "properties": {
    "name": "472 AERODROME ROAD EAST SALE 3852",
    "locID": "LOC000079111317",
    "tech": "WIRELESS",
    "upgrade": "NULL_NA",
    "gnaf_pid": "GAVIC423055068"
   }
  },
  {
   "type": "Feature",
   "geometry": {
    "type": "Point",
    "coordinates": [
     147.12169893,
     -38.10534517
    ]
   },
   "properties": {
    "name": "476 AERODROME ROAD EAST SALE 3852",
    "locID": "LOC000102285929",
    "tech": "WIRELESS",
    "upgrade": "NULL_NA",
    "gnaf_pid": "GAVIC423055069"
   }
  },
  {
   "type": "Feature",
   "geometry": {
    "type": "Point",
    "coordinates": [
     147.12188946,
     -38.10487403
    ]
   },
   "properties": {
    "name": "477 AERODROME ROAD EAST SALE 3852",
    "locID": "LOC000085363578",
    "tech": "WIRELESS",
    "upgrade": "NULL_NA",
    "gnaf_pid": "GAVIC423055070"
   }
  },
  {
   "type": "Feature",
   "geometry": {
    "type": "Point",
    "coordinates": [
     147.12224391,
     -38.1053874
    ]
   },
   "properties": {
    "name": "482 AERODROME ROAD EAST SALE 3852",
    "locID": "LOC000084388328",
    "tech": "WIRELESS",
    "upgrade": "NULL_NA",
    "gnaf_pid": "GAVIC423055071"
   }
  },
  {
   "type": "Feature",
   "geometry": {
    "type": "Point",
    "coordinates": [
     147.12247205,
     -38.10540518
    ]
   },
   "properties": {
    "name": "484 AERODROME ROAD EAST SALE 3852",
    "locID": "LOC000072815309",
    "tech": "WIRELESS",
    "upgrade": "NULL_NA",
    "gnaf_pid": "GAVIC423055072"
   }
  },
  {
   "type": "Feature",
   "geometry": {
    "type": "Point",
    "coordinates": [
     147.12266605,
     -38.10545905
    ]
   },
   "properties": {
    "name": "486 AERODROME ROAD EAST SALE 3852",
    "locID": "LOC000039024692",
    "tech": "WIRELESS",
    "upgrade": "NULL_NA",
    "gnaf_pid": "GAVIC423055073"
   }
  },
  {
   "type": "Feature",
   "geometry": {
    "type": "Point",
    "coordinates": [
     147.15545241,
     -38.09012436
    ]
   },
   "properties": {
    "name": "90 FOSTERTON ROAD EAST SALE 3852",
    "locID": "LOC000094662673",
    "tech": "WIRELESS",
    "upgrade": "NULL_NA",
    "gnaf_pid": "GAVIC423070322"
   }
  }
 ]
}