{
 "type": "FeatureCollection",
 "generated": "2024-09-23T01:24:49.915069",
 "suburb": "EVERSLEY",
 "features": [
  {
   "type": "Feature",
   "geometry": {
    "type": "Point",
    "coordinates": [
     143.13546857,
     -37.18757936
    ]
   },
   "properties": {
    "name": "3962 PYRENEES HIGHWAY EVERSLEY 3377",
    "locID": "LOC000028443837",
    "tech": "WIRELESS",
    "upgrade": "NULL_NA",
    "gnaf_pid": "GAVIC421804235",
    "tech_change_status": "Not Planned",
    "program_type": "Fixed Wireless and Satellite Upgrade Program",
    "target_eligibility_quarter": "NA"
   }
  },
  {
   "type": "Feature",
   "geometry": {
    "type": "Point",
    "coordinates": [
     143.18978569,
     -37.21462911
    ]
   },
   "properties": {
    "name": "341 COLLIERS GAP ROAD EVERSLEY 3377",
    "locID": "LOC000096644107",
    "tech": "NULL",
    "upgrade": "NULL_NA",
    "gnaf_pid": "GAVIC422137843",
    "tech_change_status": "Not Planned"
   }
  },
  {
   "type": "Feature",
   "geometry": {
    "type": "Point",
    "coordinates": [
     143.17316514,
     -37.18857264
    ]
   },
   "properties": {
    "name": "3598 PYRENEES HIGHWAY EVERSLEY 3377",
    "locID": "LOC000062243266",
    "tech": "NULL",
    "upgrade": "NULL_NA",
    "gnaf_pid": "GAVIC422184158",
    "tech_change_status": "Not Planned"
   }
  },
  {
   "type": "Feature",
   "geometry": {
    "type": "Point",
    "coordinates": [
     143.17228228,
     -37.18908196
    ]
   },
   "properties": {
    "name": "3605 PYRENEES HIGHWAY EVERSLEY 3377",
    "locID": "LOC000043288877",
    "tech": "SATELLITE",
    "upgrade": "NULL_NA",
    "gnaf_pid": "GAVIC423107369",
    "tech_change_status": "Not Planned"
   }
  },
  {
   "type": "Feature",
   "geometry": {
    "type": "Point",
    "coordinates": [
     143.19286964,
     -37.21618906
    ]
   },
   "properties": {
    "name": "368 COLLIERS GAP ROAD EVERSLEY 3377",
    "locID": "LOC000007805878",
    "tech": "SATELLITE",
    "upgrade": "NULL_NA",
    "gnaf_pid": "GAVIC423626083",
    "tech_change_status": "Not Planned"
   }
  }
 ]
}