{
 "type": "FeatureCollection",
 "generated": "2023-10-24T02:59:45.252459",
 "suburb": "FAIRLEY",
 "features": [
  {
   "type": "Feature",
   "geometry": {
    "type": "Point",
    "coordinates": [
     143.8288305,
     -35.68666329
    ]
   },
   "properties": {
    "name": "416 FAIRLEY ROAD FAIRLEY 3579",
    "locID": "LOC000051839595",
    "tech": "WIRELESS",
    "upgrade": "NULL_NA",
    "gnaf_pid": "GAVIC411351447"
   }
  },
  {
   "type": "Feature",
   "geometry": {
    "type": "Point",
    "coordinates": [
     143.816045,
     -35.68178861
    ]
   },
   "properties": {
    "name": "546 FAIRLEY ROAD FAIRLEY 3579",
    "locID": "LOC000065696478",
    "tech": "SATELLITE",
    "upgrade": "NULL_NA",
    "gnaf_pid": "GAVIC411351448"
   }
  },
  {
   "type": "Feature",
   "geometry": {
    "type": "Point",
    "coordinates": [
     143.81500751,
     -35.6821757
    ]
   },
   "properties": {
    "name": "557 FAIRLEY ROAD FAIRLEY 3579",
    "locID": "LOC000085289609",
    "tech": "SATELLITE",
    "upgrade": "NULL_NA",
    "gnaf_pid": "GAVIC411351449"
   }
  },
  {
   "type": "Feature",
   "geometry": {
    "type": "Point",
    "coordinates": [
     143.83538018,
     -35.67343344
    ]
   },
   "properties": {
    "name": "308 MAYFIELD ROAD FAIRLEY 3579",
    "locID": "ChIJi8cteM3D22oRKIHecpWM5EY",
    "tech": "WIRELESS",
    "upgrade": "UNKNOWN",
    "gnaf_pid": "GAVIC411351454"
   }
  },
  {
   "type": "Feature",
   "geometry": {
    "type": "Point",
    "coordinates": [
     143.80129883,
     -35.6820993
    ]
   },
   "properties": {
    "name": "679 FAIRLEY ROAD FAIRLEY 3579",
    "locID": "ChIJxwKwQj_B22oRug8xtjAdD0Y",
    "tech": "WIRELESS",
    "upgrade": "UNKNOWN",
    "gnaf_pid": "GAVIC411351455"
   }
  },
  {
   "type": "Feature",
   "geometry": {
    "type": "Point",
    "coordinates": [
     143.8452298,
     -35.68721939
    ]
   },
   "properties": {
    "name": "265 FAIRLEY ROAD FAIRLEY 3579",
    "locID": "LOC000103913195",
    "tech": "WIRELESS",
    "upgrade": "NULL_NA",
    "gnaf_pid": "GAVIC411398081"
   }
  },
  {
   "type": "Feature",
   "geometry": {
    "type": "Point",
    "coordinates": [
     143.86592075,
     -35.66576201
    ]
   },
   "properties": {
    "name": "997 MURRAY VALLEY HIGHWAY FAIRLEY 3579",
    "locID": "LOC000028028266",
    "tech": "WIRELESS",
    "upgrade": "NULL_NA",
    "gnaf_pid": "GAVIC421997555"
   }
  },
  {
   "type": "Feature",
   "geometry": {
    "type": "Point",
    "coordinates": [
     143.79782781,
     -35.68256856
    ]
   },
   "properties": {
    "name": "709 FAIRLEY ROAD FAIRLEY 3579",
    "locID": "LOC000016165153",
    "tech": "WIRELESS",
    "upgrade": "NULL_NA",
    "gnaf_pid": "GAVIC422145845"
   }
  },
  {
   "type": "Feature",
   "geometry": {
    "type": "Point",
    "coordinates": [
     143.78084705,
     -35.71010588
    ]
   },
   "properties": {
    "name": "322 HALLINAN ROAD FAIRLEY 3579",
    "locID": "LOC000003502033",
    "tech": "WIRELESS",
    "upgrade": "NULL_NA",
    "gnaf_pid": "GAVIC422153071"
   }
  }
 ]
}