{
 "type": "FeatureCollection",
 "generated": "2024-09-03T23:08:33.359608",
 "suburb": "FLAMINGO BEACH",
 "features": [
  {
   "type": "Feature",
   "geometry": {
    "type": "Point",
    "coordinates": [
     147.31803748,
     -38.27392439
    ]
   },
   "properties": {
    "name": "9 SAN PAULO CRESCENT FLAMINGO BEACH 3851",
    "locID": "LOC000038828682",
    "tech": "SATELLITE",
    "upgrade": "NULL_NA",
    "gnaf_pid": "GAVIC423836418",
    "tech_change_status": "Not Planned"
   }
  },
  {
   "type": "Feature",
   "geometry": {
    "type": "Point",
    "coordinates": [
     147.32309586,
     -38.27133296
    ]
   },
   "properties": {
    "name": "6 CALAMA COURT FLAMINGO BEACH 3851",
    "locID": "LOC000026797746",
    "tech": "FTTN",
    "upgrade": "NULL_NA",
    "gnaf_pid": "GAVIC423875952",
    "tech_change_status": "Not Planned"
   }
  },
  {
   "type": "Feature",
   "geometry": {
    "type": "Point",
    "coordinates": [
     147.31649023,
     -38.27512388
    ]
   },
   "properties": {
    "name": "13 SAN DOMINGO AVENUE FLAMINGO BEACH 3851",
    "locID": "LOC100079013260",
    "tech": "SATELLITE",
    "upgrade": "NULL_NA",
    "gnaf_pid": "GAVIC423894100",
    "tech_change_status": "Not Planned"
   }
  },
  {
   "type": "Feature",
   "geometry": {
    "type": "Point",
    "coordinates": [
     147.3170612,
     -38.27565209
    ]
   },
   "properties": {
    "name": "3 SAN DOMINGO AVENUE FLAMINGO BEACH 3851",
    "locID": "LOC100079013260",
    "tech": "SATELLITE",
    "upgrade": "NULL_NA",
    "gnaf_pid": "GAVIC423894116",
    "tech_change_status": "Not Planned"
   }
  },
  {
   "type": "Feature",
   "geometry": {
    "type": "Point",
    "coordinates": [
     147.31627996,
     -38.27386101
    ]
   },
   "properties": {
    "name": "38 SAN PAULO CRESCENT FLAMINGO BEACH 3851",
    "locID": "LOC000038828682",
    "tech": "SATELLITE",
    "upgrade": "NULL_NA",
    "gnaf_pid": "GAVIC424503680",
    "tech_change_status": "Not Planned"
   }
  }
 ]
}