{
 "type": "FeatureCollection",
 "generated": "2024-09-23T02:07:27.389432",
 "suburb": "FLYNNS CREEK",
 "features": [
  {
   "type": "Feature",
   "geometry": {
    "type": "Point",
    "coordinates": [
     146.62378483,
     -38.26173838
    ]
   },
   "properties": {
    "name": "245 SCALES ROAD FLYNNS CREEK 3844",
    "locID": "LOC000079157388",
    "tech": "SATELLITE",
    "upgrade": "NULL_NA",
    "gnaf_pid": "GAVIC420988799",
    "tech_change_status": "Not Planned"
   }
  },
  {
   "type": "Feature",
   "geometry": {
    "type": "Point",
    "coordinates": [
     146.6348636,
     -38.24523549
    ]
   },
   "properties": {
    "name": "25 SCALES ROAD FLYNNS CREEK 3844",
    "locID": "LOC000056534121",
    "tech": "WIRELESS",
    "upgrade": "NULL_NA",
    "gnaf_pid": "GAVIC421771157",
    "tech_change_status": "Not Planned",
    "program_type": "Fixed Wireless and Satellite Upgrade Program",
    "target_eligibility_quarter": "NA"
   }
  },
  {
   "type": "Feature",
   "geometry": {
    "type": "Point",
    "coordinates": [
     146.65099305,
     -38.24913375
    ]
   },
   "properties": {
    "name": "19 MAXFIELDS ROAD FLYNNS CREEK 3844",
    "locID": "LOC000079190152",
    "tech": "SATELLITE",
    "upgrade": "NULL_NA",
    "gnaf_pid": "GAVIC422028200",
    "tech_change_status": "Not Planned"
   }
  },
  {
   "type": "Feature",
   "geometry": {
    "type": "Point",
    "coordinates": [
     146.64566671,
     -38.23977099
    ]
   },
   "properties": {
    "name": "975 FLYNNS CREEK ROAD FLYNNS CREEK 3844",
    "locID": "LOC000125272739",
    "tech": "WIRELESS",
    "upgrade": "NULL_NA",
    "gnaf_pid": "GAVIC422147179",
    "tech_change_status": "Not Planned"
   }
  },
  {
   "type": "Feature",
   "geometry": {
    "type": "Point",
    "coordinates": [
     146.65545141,
     -38.24977072
    ]
   },
   "properties": {
    "name": "1265 HYLAND HIGHWAY FLYNNS CREEK 3844",
    "locID": "LOC000080807324",
    "tech": "SATELLITE",
    "upgrade": "NULL_NA",
    "gnaf_pid": "GAVIC422158038",
    "tech_change_status": "Not Planned"
   }
  },
  {
   "type": "Feature",
   "geometry": {
    "type": "Point",
    "coordinates": [
     146.63179751,
     -38.27310235
    ]
   },
   "properties": {
    "name": "351 MAXFIELDS ROAD FLYNNS CREEK 3844",
    "locID": "LOC000073993908",
    "tech": "SATELLITE",
    "upgrade": "NULL_NA",
    "gnaf_pid": "GAVIC422169188",
    "tech_change_status": "Not Planned"
   }
  },
  {
   "type": "Feature",
   "geometry": {
    "type": "Point",
    "coordinates": [
     146.64728657,
     -38.25222201
    ]
   },
   "properties": {
    "name": "68 MAXFIELDS ROAD FLYNNS CREEK 3844",
    "locID": "LOC000071757205",
    "tech": "SATELLITE",
    "upgrade": "NULL_NA",
    "gnaf_pid": "GAVIC422169189",
    "tech_change_status": "Not Planned"
   }
  },
  {
   "type": "Feature",
   "geometry": {
    "type": "Point",
    "coordinates": [
     146.64277505,
     -38.25629195
    ]
   },
   "properties": {
    "name": "136 MAXFIELDS ROAD FLYNNS CREEK 3844",
    "locID": "LOC000003974035",
    "tech": "SATELLITE",
    "upgrade": "NULL_NA",
    "gnaf_pid": "GAVIC422308229",
    "tech_change_status": "Not Planned"
   }
  },
  {
   "type": "Feature",
   "geometry": {
    "type": "Point",
    "coordinates": [
     146.63808595,
     -38.26147778
    ]
   },
   "properties": {
    "name": "206 MAXFIELDS ROAD FLYNNS CREEK 3844",
    "locID": "LOC000008479820",
    "tech": "SATELLITE",
    "upgrade": "NULL_NA",
    "gnaf_pid": "GAVIC422308230",
    "tech_change_status": "Not Planned"
   }
  },
  {
   "type": "Feature",
   "geometry": {
    "type": "Point",
    "coordinates": [
     146.67397331,
     -38.24979985
    ]
   },
   "properties": {
    "name": "1691 ROSEDALE-FLYNNS CREEK ROAD FLYNNS CREEK 3844",
    "locID": "LOC000072944396",
    "tech": "SATELLITE",
    "upgrade": "NULL_NA",
    "gnaf_pid": "GAVIC423893603",
    "tech_change_status": "Not Planned"
   }
  },
  {
   "type": "Feature",
   "geometry": {
    "type": "Point",
    "coordinates": [
     146.64675118,
     -38.2376383
    ]
   },
   "properties": {
    "name": "955 FLYNNS CREEK ROAD FLYNNS CREEK 3844",
    "locID": "LOC000125272668",
    "tech": "SATELLITE",
    "upgrade": "NULL_NA",
    "gnaf_pid": "GAVIC423967728",
    "tech_change_status": "Not Planned"
   }
  },
  {
   "type": "Feature",
   "geometry": {
    "type": "Point",
    "coordinates": [
     146.6480893,
     -38.24976618
    ]
   },
   "properties": {
    "name": "38 MAXFIELDS ROAD FLYNNS CREEK 3844",
    "locID": "LOC000008479820",
    "tech": "SATELLITE",
    "upgrade": "NULL_NA",
    "gnaf_pid": "GAVIC424757714",
    "tech_change_status": "Not Planned"
   }
  }
 ]
}