{
 "type": "FeatureCollection",
 "generated": "2024-02-27T17:35:28.535038",
 "suburb": "HAWKHURST",
 "features": [
  {
   "type": "Feature",
   "geometry": {
    "type": "Point",
    "coordinates": [
     147.13834666,
     -37.4500702
    ]
   },
   "properties": {
    "name": "1443 WONNANGATTA ROAD HAWKHURST 3862",
    "locID": "LOC000088934350",
    "tech": "SATELLITE",
    "upgrade": "NULL_NA",
    "gnaf_pid": "GAVIC422204831"
   }
  },
  {
   "type": "Feature",
   "geometry": {
    "type": "Point",
    "coordinates": [
     147.11949745,
     -37.42013776
    ]
   },
   "properties": {
    "name": "2015 WONNANGATTA ROAD HAWKHURST 3862",
    "locID": "LOC000023455781",
    "tech": "SATELLITE",
    "upgrade": "NULL_NA",
    "gnaf_pid": "GAVIC422204833"
   }
  },
  {
   "type": "Feature",
   "geometry": {
    "type": "Point",
    "coordinates": [
     147.13811312,
     -37.44980002
    ]
   },
   "properties": {
    "name": "1445 WONNANGATTA ROAD HAWKHURST 3862",
    "locID": "LOC000125454998",
    "tech": "SATELLITE",
    "upgrade": "NULL_NA",
    "gnaf_pid": "GAVIC424919888"
   }
  }
 ]
}