{
 "type": "FeatureCollection",
 "generated": "2024-09-23T08:03:34.903805",
 "suburb": "INKERMAN",
 "features": [
  {
   "type": "Feature",
   "geometry": {
    "type": "Point",
    "coordinates": [
     143.67796606,
     -36.78579288
    ]
   },
   "properties": {
    "name": "1020 DUNOLLY-MOLIAGUL ROAD INKERMAN 3472",
    "locID": "LOC000080908008",
    "tech": "NULL",
    "upgrade": "NULL_NA",
    "gnaf_pid": "GAVIC411621080",
    "tech_change_status": "Not Planned"
   }
  },
  {
   "type": "Feature",
   "geometry": {
    "type": "Point",
    "coordinates": [
     143.6773075,
     -36.78207009
    ]
   },
   "properties": {
    "name": "1066 DUNOLLY-MOLIAGUL ROAD INKERMAN 3472",
    "locID": "LOC000093170039",
    "tech": "SATELLITE",
    "upgrade": "NULL_NA",
    "gnaf_pid": "GAVIC411621081",
    "tech_change_status": "Not Planned"
   }
  },
  {
   "type": "Feature",
   "geometry": {
    "type": "Point",
    "coordinates": [
     143.67783564,
     -36.7852641
    ]
   },
   "properties": {
    "name": "1038 DUNOLLY-MOLIAGUL ROAD INKERMAN 3472",
    "locID": "LOC000023841604",
    "tech": "NULL",
    "upgrade": "NULL_NA",
    "gnaf_pid": "GAVIC411621082",
    "tech_change_status": "Not Planned"
   }
  },
  {
   "type": "Feature",
   "geometry": {
    "type": "Point",
    "coordinates": [
     143.67651024,
     -36.77550694
    ]
   },
   "properties": {
    "name": "1172 DUNOLLY-MOLIAGUL ROAD INKERMAN 3472",
    "locID": "LOC000046709164",
    "tech": "NULL",
    "upgrade": "NULL_NA",
    "gnaf_pid": "GAVIC414351599",
    "tech_change_status": "Not Planned"
   }
  },
  {
   "type": "Feature",
   "geometry": {
    "type": "Point",
    "coordinates": [
     143.67765009,
     -36.78798089
    ]
   },
   "properties": {
    "name": "1015 DUNOLLY-MOLIAGUL ROAD INKERMAN 3472",
    "locID": "LOC000039590885",
    "tech": "NULL",
    "upgrade": "NULL_NA",
    "gnaf_pid": "GAVIC419655848",
    "tech_change_status": "Not Planned"
   }
  },
  {
   "type": "Feature",
   "geometry": {
    "type": "Point",
    "coordinates": [
     143.67927305,
     -36.79496263
    ]
   },
   "properties": {
    "name": "945 DUNOLLY-MOLIAGUL ROAD INKERMAN 3472",
    "locID": "LOC000007838216",
    "tech": "NULL",
    "upgrade": "NULL_NA",
    "gnaf_pid": "GAVIC421168708",
    "tech_change_status": "Not Planned"
   }
  }
 ]
}