{
 "type": "FeatureCollection",
 "generated": "2023-10-24T09:46:39.691723",
 "suburb": "INKERMAN",
 "features": [
  {
   "type": "Feature",
   "geometry": {
    "type": "Point",
    "coordinates": [
     143.67796606,
     -36.78579288
    ]
   },
   "properties": {
    "name": "1020 DUNOLLY-MOLIAGUL ROAD INKERMAN 3472",
    "locID": "LOC000080908008",
    "tech": "SATELLITE",
    "upgrade": "NULL_NA",
    "gnaf_pid": "GAVIC411621080"
   }
  },
  {
   "type": "Feature",
   "geometry": {
    "type": "Point",
    "coordinates": [
     143.6773075,
     -36.78207009
    ]
   },
   "properties": {
    "name": "1066 DUNOLLY-MOLIAGUL ROAD INKERMAN 3472",
    "locID": "LOC000093170039",
    "tech": "SATELLITE",
    "upgrade": "NULL_NA",
    "gnaf_pid": "GAVIC411621081"
   }
  },
  {
   "type": "Feature",
   "geometry": {
    "type": "Point",
    "coordinates": [
     143.67783564,
     -36.7852641
    ]
   },
   "properties": {
    "name": "1038 DUNOLLY-MOLIAGUL ROAD INKERMAN 3472",
    "locID": "LOC000023841604",
    "tech": "SATELLITE",
    "upgrade": "NULL_NA",
    "gnaf_pid": "GAVIC411621082"
   }
  },
  {
   "type": "Feature",
   "geometry": {
    "type": "Point",
    "coordinates": [
     143.67651024,
     -36.77550694
    ]
   },
   "properties": {
    "name": "1172 DUNOLLY-MOLIAGUL ROAD INKERMAN 3472",
    "locID": "LOC000046709164",
    "tech": "SATELLITE",
    "upgrade": "NULL_NA",
    "gnaf_pid": "GAVIC414351599"
   }
  },
  {
   "type": "Feature",
   "geometry": {
    "type": "Point",
    "coordinates": [
     143.67765009,
     -36.78798089
    ]
   },
   "properties": {
    "name": "1015 DUNOLLY-MOLIAGUL ROAD INKERMAN 3472",
    "locID": "LOC000039590885",
    "tech": "SATELLITE",
    "upgrade": "NULL_NA",
    "gnaf_pid": "GAVIC419655848"
   }
  },
  {
   "type": "Feature",
   "geometry": {
    "type": "Point",
    "coordinates": [
     143.67805761,
     -36.78930517
    ]
   },
   "properties": {
    "name": "1001 DUNOLLY-MOLIAGUL ROAD INKERMAN 3472",
    "locID": "ChIJX7ixgTTr0GoRgX-jPS3EVI8",
    "tech": "SATELLITE",
    "upgrade": "UNKNOWN",
    "gnaf_pid": "GAVIC420562422"
   }
  },
  {
   "type": "Feature",
   "geometry": {
    "type": "Point",
    "coordinates": [
     143.67927305,
     -36.79496263
    ]
   },
   "properties": {
    "name": "945 DUNOLLY-MOLIAGUL ROAD INKERMAN 3472",
    "locID": "LOC000007838216",
    "tech": "SATELLITE",
    "upgrade": "NULL_NA",
    "gnaf_pid": "GAVIC421168708"
   }
  },
  {
   "type": "Feature",
   "geometry": {
    "type": "Point",
    "coordinates": [
     143.67236284,
     -36.80684772
    ]
   },
   "properties": {
    "name": "707 DUNOLLY-MOLIAGUL ROAD INKERMAN 3472",
    "locID": "ChIJf6bY1hTr0GoRaAWVRZa7VwM",
    "tech": "SATELLITE",
    "upgrade": "UNKNOWN",
    "gnaf_pid": "GAVIC721100366"
   }
  }
 ]
}