{
 "type": "FeatureCollection",
 "generated": "2024-07-24T22:35:40.907695",
 "suburb": "KAMAROOKA NORTH",
 "features": [
  {
   "type": "Feature",
   "geometry": {
    "type": "Point",
    "coordinates": [
     144.30227834,
     -36.42476399
    ]
   },
   "properties": {
    "name": "40 DUNNS ROAD KAMAROOKA NORTH 3571",
    "locID": "LOC000067869175",
    "tech": "WIRELESS",
    "upgrade": "NULL_NA",
    "gnaf_pid": "GAVIC411640257",
    "tech_change_status": "Not Planned",
    "program_type": "Fixed Wireless and Satellite Upgrade Program",
    "target_eligibility_quarter": "NA"
   }
  },
  {
   "type": "Feature",
   "geometry": {
    "type": "Point",
    "coordinates": [
     144.30175259,
     -36.40058075
    ]
   },
   "properties": {
    "name": "312 DUNNS ROAD KAMAROOKA NORTH 3571",
    "locID": "LOC000091865670",
    "tech": "WIRELESS",
    "upgrade": "NULL_NA",
    "gnaf_pid": "GAVIC422143466",
    "tech_change_status": "Not Planned",
    "program_type": "Fixed Wireless and Satellite Upgrade Program",
    "target_eligibility_quarter": "NA"
   }
  },
  {
   "type": "Feature",
   "geometry": {
    "type": "Point",
    "coordinates": [
     144.30091853,
     -36.39641376
    ]
   },
   "properties": {
    "name": "371 DUNNS ROAD KAMAROOKA NORTH 3571",
    "locID": "LOC000054114751",
    "tech": "WIRELESS",
    "upgrade": "NULL_NA",
    "gnaf_pid": "GAVIC422143467",
    "tech_change_status": "Not Planned",
    "program_type": "Fixed Wireless and Satellite Upgrade Program",
    "target_eligibility_quarter": "NA"
   }
  },
  {
   "type": "Feature",
   "geometry": {
    "type": "Point",
    "coordinates": [
     144.31483468,
     -36.40764294
    ]
   },
   "properties": {
    "name": "119 PAXFORDS ROAD KAMAROOKA NORTH 3571",
    "locID": "LOC000070246297",
    "tech": "WIRELESS",
    "upgrade": "NULL_NA",
    "gnaf_pid": "GAVIC422180991",
    "tech_change_status": "Not Planned",
    "program_type": "Fixed Wireless and Satellite Upgrade Program",
    "target_eligibility_quarter": "NA"
   }
  },
  {
   "type": "Feature",
   "geometry": {
    "type": "Point",
    "coordinates": [
     144.31130917,
     -36.40848332
    ]
   },
   "properties": {
    "name": "84 PAXFORDS ROAD KAMAROOKA NORTH 3571",
    "locID": "LOC100084008750",
    "tech": "WIRELESS",
    "upgrade": "NULL_NA",
    "gnaf_pid": "GAVIC721370092",
    "tech_change_status": "Not Planned",
    "program_type": "Fixed Wireless and Satellite Upgrade Program",
    "target_eligibility_quarter": "NA"
   }
  }
 ]
}