{
 "type": "FeatureCollection",
 "generated": "2023-10-24T10:41:03.531420",
 "suburb": "KAMAROOKA NORTH",
 "features": [
  {
   "type": "Feature",
   "geometry": {
    "type": "Point",
    "coordinates": [
     144.30227834,
     -36.42476399
    ]
   },
   "properties": {
    "name": "40 DUNNS ROAD KAMAROOKA NORTH 3571",
    "locID": "LOC000067869175",
    "tech": "WIRELESS",
    "upgrade": "NULL_NA",
    "gnaf_pid": "GAVIC411640257"
   }
  },
  {
   "type": "Feature",
   "geometry": {
    "type": "Point",
    "coordinates": [
     144.30175259,
     -36.40058075
    ]
   },
   "properties": {
    "name": "312 DUNNS ROAD KAMAROOKA NORTH 3571",
    "locID": "LOC000091865670",
    "tech": "WIRELESS",
    "upgrade": "NULL_NA",
    "gnaf_pid": "GAVIC422143466"
   }
  },
  {
   "type": "Feature",
   "geometry": {
    "type": "Point",
    "coordinates": [
     144.30091853,
     -36.39641376
    ]
   },
   "properties": {
    "name": "371 DUNNS ROAD KAMAROOKA NORTH 3571",
    "locID": "LOC000054114751",
    "tech": "WIRELESS",
    "upgrade": "NULL_NA",
    "gnaf_pid": "GAVIC422143467"
   }
  },
  {
   "type": "Feature",
   "geometry": {
    "type": "Point",
    "coordinates": [
     144.31483468,
     -36.40764294
    ]
   },
   "properties": {
    "name": "119 PAXFORDS ROAD KAMAROOKA NORTH 3571",
    "locID": "LOC000070246297",
    "tech": "WIRELESS",
    "upgrade": "NULL_NA",
    "gnaf_pid": "GAVIC422180991"
   }
  },
  {
   "type": "Feature",
   "geometry": {
    "type": "Point",
    "coordinates": [
     144.31968658,
     -36.40765665
    ]
   },
   "properties": {
    "name": "165 PAXFORDS ROAD KAMAROOKA NORTH 3571",
    "locID": "ChIJDTBjsDST2WoRNROZ1gRfSlg",
    "tech": "SATELLITE",
    "upgrade": "UNKNOWN",
    "gnaf_pid": "GAVIC422180992"
   }
  }
 ]
}