{
 "type": "FeatureCollection",
 "generated": "2024-02-28T04:29:26.034024",
 "suburb": "KNOCKWOOD",
 "features": [
  {
   "type": "Feature",
   "geometry": {
    "type": "Point",
    "coordinates": [
     146.23508834,
     -37.42649889
    ]
   },
   "properties": {
    "name": "6560 MANSFIELD-WOODS POINT ROAD KNOCKWOOD 3723",
    "locID": "LOC000157753098",
    "tech": "SATELLITE",
    "upgrade": "NULL_NA",
    "gnaf_pid": "GAVIC719204296"
   }
  }
 ]
}