{
 "type": "FeatureCollection",
 "generated": "2023-10-24T12:28:11.664564",
 "suburb": "KNOCKWOOD",
 "features": [
  {
   "type": "Feature",
   "geometry": {
    "type": "Point",
    "coordinates": [
     146.2423231,
     -37.41665268
    ]
   },
   "properties": {
    "name": "6419 MANSFIELD-WOODS POINT ROAD KNOCKWOOD 3723",
    "locID": "ChIJKYZEA9qAKGsRPmQ5jy-5Tmo",
    "tech": "SATELLITE",
    "upgrade": "UNKNOWN",
    "gnaf_pid": "GAVIC424084885"
   }
  },
  {
   "type": "Feature",
   "geometry": {
    "type": "Point",
    "coordinates": [
     146.22981685,
     -37.42954238
    ]
   },
   "properties": {
    "name": "6666 MANSFIELD-WOODS POINT ROAD KNOCKWOOD 3723",
    "locID": "ChIJASae4TaHKGsREYS2FW2EMjU",
    "tech": "SATELLITE",
    "upgrade": "UNKNOWN",
    "gnaf_pid": "GAVIC424623372"
   }
  },
  {
   "type": "Feature",
   "geometry": {
    "type": "Point",
    "coordinates": [
     146.23508834,
     -37.42649889
    ]
   },
   "properties": {
    "name": "6560 MANSFIELD-WOODS POINT ROAD KNOCKWOOD 3723",
    "locID": "LOC000157753098",
    "tech": "SATELLITE",
    "upgrade": "NULL_NA",
    "gnaf_pid": "GAVIC719204296"
   }
  },
  {
   "type": "Feature",
   "geometry": {
    "type": "Point",
    "coordinates": [
     146.23906495,
     -37.42258972
    ]
   },
   "properties": {
    "name": "6481 MANSFIELD-WOODS POINT ROAD KNOCKWOOD 3723",
    "locID": "ChIJVy-1WtKAKGsREmu6xugUGvo",
    "tech": "SATELLITE",
    "upgrade": "UNKNOWN",
    "gnaf_pid": "GAVIC719317216"
   }
  },
  {
   "type": "Feature",
   "geometry": {
    "type": "Point",
    "coordinates": [
     146.23352272,
     -37.42755691
    ]
   },
   "properties": {
    "name": "6584 MANSFIELD-WOODS POINT ROAD KNOCKWOOD 3723",
    "locID": "ChIJl5MaxjOHKGsRLkGfRppV3Qc",
    "tech": "SATELLITE",
    "upgrade": "UNKNOWN",
    "gnaf_pid": "GAVIC721158318"
   }
  }
 ]
}