{
 "type": "FeatureCollection",
 "generated": "2024-03-22T12:18:17.668975",
 "suburb": "KNOCKWOOD",
 "features": [
  {
   "type": "Feature",
   "geometry": {
    "type": "Point",
    "coordinates": [
     146.23508834,
     -37.42649889
    ]
   },
   "properties": {
    "name": "6560 MANSFIELD-WOODS POINT ROAD KNOCKWOOD 3723",
    "locID": "LOC000157753098",
    "tech": "SATELLITE",
    "upgrade": "NULL_NA",
    "gnaf_pid": "GAVIC719204296"
   }
  },
  {
   "type": "Feature",
   "geometry": {
    "type": "Point",
    "coordinates": [
     146.23352272,
     -37.42755691
    ]
   },
   "properties": {
    "name": "6584 MANSFIELD-WOODS POINT ROAD KNOCKWOOD 3723",
    "locID": "LOC100085135980",
    "tech": "SATELLITE",
    "upgrade": "NULL_NA",
    "gnaf_pid": "GAVIC721158318"
   }
  }
 ]
}