{
 "type": "FeatureCollection",
 "generated": "2023-10-24T13:23:22.948077",
 "suburb": "LAKE EILDON",
 "features": [
  {
   "type": "Feature",
   "geometry": {
    "type": "Point",
    "coordinates": [
     146.04603006,
     -37.17029262
    ]
   },
   "properties": {
    "name": "179 WALSHS ROAD LAKE EILDON 3713",
    "locID": "LOC100078661495",
    "tech": "WIRELESS",
    "upgrade": "NULL_NA",
    "gnaf_pid": "GAVIC423097629"
   }
  },
  {
   "type": "Feature",
   "geometry": {
    "type": "Point",
    "coordinates": [
     146.03495973,
     -37.16827615
    ]
   },
   "properties": {
    "name": "303 WALSHS ROAD LAKE EILDON 3713",
    "locID": "LOC000031159709",
    "tech": "SATELLITE",
    "upgrade": "NULL_NA",
    "gnaf_pid": "GAVIC423097630"
   }
  },
  {
   "type": "Feature",
   "geometry": {
    "type": "Point",
    "coordinates": [
     146.03278726,
     -37.169935
    ]
   },
   "properties": {
    "name": "329 WALSHS ROAD LAKE EILDON 3713",
    "locID": "LOC000125020130",
    "tech": "SATELLITE",
    "upgrade": "NULL_NA",
    "gnaf_pid": "GAVIC423097631"
   }
  },
  {
   "type": "Feature",
   "geometry": {
    "type": "Point",
    "coordinates": [
     146.00911825,
     -37.18140813
    ]
   },
   "properties": {
    "name": "524 WALSHS ROAD LAKE EILDON 3713",
    "locID": "ChIJeSgHZxPaJ2sRkjE6LigYEGk",
    "tech": "SATELLITE",
    "upgrade": "UNKNOWN",
    "gnaf_pid": "GAVIC423760127"
   }
  },
  {
   "type": "Feature",
   "geometry": {
    "type": "Point",
    "coordinates": [
     146.04021663,
     -37.16920425
    ]
   },
   "properties": {
    "name": "247 WALSHS ROAD LAKE EILDON 3713",
    "locID": "LOC100078661476",
    "tech": "SATELLITE",
    "upgrade": "NULL_NA",
    "gnaf_pid": "GAVIC424455882"
   }
  },
  {
   "type": "Feature",
   "geometry": {
    "type": "Point",
    "coordinates": [
     146.03736995,
     -37.1683135
    ]
   },
   "properties": {
    "name": "271 WALSHS ROAD LAKE EILDON 3713",
    "locID": "LOC000107598318",
    "tech": "SATELLITE",
    "upgrade": "NULL_NA",
    "gnaf_pid": "GAVIC424455883"
   }
  }
 ]
}