{
 "type": "FeatureCollection",
 "generated": "2024-09-23T12:30:37.530517",
 "suburb": "LICOLA NORTH",
 "features": [
  {
   "type": "Feature",
   "geometry": {
    "type": "Point",
    "coordinates": [
     146.55169581,
     -37.5192553
    ]
   },
   "properties": {
    "name": "1002 GLENCAIRN ROAD LICOLA NORTH 3858",
    "locID": "LOC000125266794",
    "tech": "SATELLITE",
    "upgrade": "NULL_NA",
    "gnaf_pid": "GAVIC422149658",
    "tech_change_status": "Not Planned"
   }
  },
  {
   "type": "Feature",
   "geometry": {
    "type": "Point",
    "coordinates": [
     146.5474458,
     -37.52967695
    ]
   },
   "properties": {
    "name": "881 GLENCAIRN ROAD LICOLA NORTH 3858",
    "locID": "LOC000008576546",
    "tech": "SATELLITE",
    "upgrade": "NULL_NA",
    "gnaf_pid": "GAVIC422149659",
    "tech_change_status": "Not Planned"
   }
  },
  {
   "type": "Feature",
   "geometry": {
    "type": "Point",
    "coordinates": [
     146.55173179,
     -37.5193846
    ]
   },
   "properties": {
    "name": "998 GLENCAIRN ROAD LICOLA NORTH 3858",
    "locID": "LOC000125297916",
    "tech": "SATELLITE",
    "upgrade": "NULL_NA",
    "gnaf_pid": "GAVIC422149660",
    "tech_change_status": "Not Planned"
   }
  },
  {
   "type": "Feature",
   "geometry": {
    "type": "Point",
    "coordinates": [
     146.5507765,
     -37.52347924
    ]
   },
   "properties": {
    "name": "954 GLENCAIRN ROAD LICOLA NORTH 3858",
    "locID": "LOC000125297874",
    "tech": "SATELLITE",
    "upgrade": "NULL_NA",
    "gnaf_pid": "GAVIC422293681",
    "tech_change_status": "Not Planned"
   }
  },
  {
   "type": "Feature",
   "geometry": {
    "type": "Point",
    "coordinates": [
     146.54333671,
     -37.5141399
    ]
   },
   "properties": {
    "name": "1102 GLENCAIRN ROAD LICOLA NORTH 3858",
    "locID": "LOC000050911194",
    "tech": "NULL",
    "upgrade": "NULL_NA",
    "gnaf_pid": "GAVIC423968271",
    "tech_change_status": "Not Planned"
   }
  },
  {
   "type": "Feature",
   "geometry": {
    "type": "Point",
    "coordinates": [
     146.55173867,
     -37.51942699
    ]
   },
   "properties": {
    "name": "998B GLENCAIRN ROAD LICOLA NORTH 3858",
    "locID": "LOC000125297916",
    "tech": "SATELLITE",
    "upgrade": "NULL_NA",
    "gnaf_pid": "GAVIC424911512",
    "tech_change_status": "Not Planned"
   }
  },
  {
   "type": "Feature",
   "geometry": {
    "type": "Point",
    "coordinates": [
     146.52979131,
     -37.47790336
    ]
   },
   "properties": {
    "name": "477 BULL PLAIN ROAD LICOLA NORTH 3858",
    "locID": "LOC000148034658",
    "tech": "NULL",
    "upgrade": "NULL_NA",
    "gnaf_pid": "GAVIC425308958",
    "tech_change_status": "Not Planned"
   }
  },
  {
   "type": "Feature",
   "geometry": {
    "type": "Point",
    "coordinates": [
     146.52861109,
     -37.48313724
    ]
   },
   "properties": {
    "name": "415 BULL PLAIN ROAD LICOLA NORTH 3858",
    "locID": "LOC100072032767",
    "tech": "NULL",
    "upgrade": "NULL_NA",
    "gnaf_pid": "GAVIC719207069",
    "tech_change_status": "Not Planned"
   }
  }
 ]
}