{
 "type": "FeatureCollection",
 "generated": "2023-10-24T14:19:39.204632",
 "suburb": "LICOLA NORTH",
 "features": [
  {
   "type": "Feature",
   "geometry": {
    "type": "Point",
    "coordinates": [
     146.55169581,
     -37.5192553
    ]
   },
   "properties": {
    "name": "1002 GLENCAIRN ROAD LICOLA NORTH 3858",
    "locID": "LOC000125266794",
    "tech": "SATELLITE",
    "upgrade": "NULL_NA",
    "gnaf_pid": "GAVIC422149658"
   }
  },
  {
   "type": "Feature",
   "geometry": {
    "type": "Point",
    "coordinates": [
     146.5474458,
     -37.52967695
    ]
   },
   "properties": {
    "name": "881 GLENCAIRN ROAD LICOLA NORTH 3858",
    "locID": "LOC000008576546",
    "tech": "SATELLITE",
    "upgrade": "NULL_NA",
    "gnaf_pid": "GAVIC422149659"
   }
  },
  {
   "type": "Feature",
   "geometry": {
    "type": "Point",
    "coordinates": [
     146.55173179,
     -37.5193846
    ]
   },
   "properties": {
    "name": "998 GLENCAIRN ROAD LICOLA NORTH 3858",
    "locID": "LOC000125297916",
    "tech": "SATELLITE",
    "upgrade": "NULL_NA",
    "gnaf_pid": "GAVIC422149660"
   }
  },
  {
   "type": "Feature",
   "geometry": {
    "type": "Point",
    "coordinates": [
     146.5507765,
     -37.52347924
    ]
   },
   "properties": {
    "name": "954 GLENCAIRN ROAD LICOLA NORTH 3858",
    "locID": "LOC000125297874",
    "tech": "SATELLITE",
    "upgrade": "NULL_NA",
    "gnaf_pid": "GAVIC422293681"
   }
  },
  {
   "type": "Feature",
   "geometry": {
    "type": "Point",
    "coordinates": [
     146.54333671,
     -37.5141399
    ]
   },
   "properties": {
    "name": "1102 GLENCAIRN ROAD LICOLA NORTH 3858",
    "locID": "LOC000050911194",
    "tech": "SATELLITE",
    "upgrade": "NULL_NA",
    "gnaf_pid": "GAVIC423968271"
   }
  },
  {
   "type": "Feature",
   "geometry": {
    "type": "Point",
    "coordinates": [
     146.55173179,
     -37.5193846
    ]
   },
   "properties": {
    "name": "998A GLENCAIRN ROAD LICOLA NORTH 3858",
    "locID": "ChIJ3aCnZVefKGsRUkl__cRtPV0",
    "tech": "SATELLITE",
    "upgrade": "UNKNOWN",
    "gnaf_pid": "GAVIC424911511"
   }
  },
  {
   "type": "Feature",
   "geometry": {
    "type": "Point",
    "coordinates": [
     146.55173867,
     -37.51942699
    ]
   },
   "properties": {
    "name": "998B GLENCAIRN ROAD LICOLA NORTH 3858",
    "locID": "LOC000125297916",
    "tech": "SATELLITE",
    "upgrade": "NULL_NA",
    "gnaf_pid": "GAVIC424911512"
   }
  },
  {
   "type": "Feature",
   "geometry": {
    "type": "Point",
    "coordinates": [
     146.52810414,
     -37.48369846
    ]
   },
   "properties": {
    "name": "409 BULL PLAIN ROAD LICOLA NORTH 3858",
    "locID": "ChIJvYh3nQifKGsRUPvSinHHsXw",
    "tech": "SATELLITE",
    "upgrade": "UNKNOWN",
    "gnaf_pid": "GAVIC425308956"
   }
  },
  {
   "type": "Feature",
   "geometry": {
    "type": "Point",
    "coordinates": [
     146.52936875,
     -37.48044087
    ]
   },
   "properties": {
    "name": "445 BULL PLAIN ROAD LICOLA NORTH 3858",
    "locID": "ChIJA80X96efKGsRB0dTI1rTbXA",
    "tech": "SATELLITE",
    "upgrade": "UNKNOWN",
    "gnaf_pid": "GAVIC425308957"
   }
  },
  {
   "type": "Feature",
   "geometry": {
    "type": "Point",
    "coordinates": [
     146.52979131,
     -37.47790336
    ]
   },
   "properties": {
    "name": "477 BULL PLAIN ROAD LICOLA NORTH 3858",
    "locID": "LOC000148034658",
    "tech": "SATELLITE",
    "upgrade": "NULL_NA",
    "gnaf_pid": "GAVIC425308958"
   }
  },
  {
   "type": "Feature",
   "geometry": {
    "type": "Point",
    "coordinates": [
     146.52861109,
     -37.48313724
    ]
   },
   "properties": {
    "name": "415 BULL PLAIN ROAD LICOLA NORTH 3858",
    "locID": "LOC100072032767",
    "tech": "SATELLITE",
    "upgrade": "NULL_NA",
    "gnaf_pid": "GAVIC719207069"
   }
  }
 ]
}