{
 "type": "FeatureCollection",
 "generated": "2023-11-11T05:43:00.483665",
 "suburb": "LOCH VALLEY",
 "features": [
  {
   "type": "Feature",
   "geometry": {
    "type": "Point",
    "coordinates": [
     145.99742622,
     -37.84040226
    ]
   },
   "properties": {
    "name": "670 LOCH VALLEY ROAD LOCH VALLEY 3833",
    "locID": "ChIJg7amKApNKGsRFrGsfZ_9RSc",
    "tech": "SATELLITE",
    "upgrade": "UNKNOWN",
    "gnaf_pid": "GAVIC421487205"
   }
  }
 ]
}