{
 "type": "FeatureCollection",
 "generated": "2024-07-06T10:09:43.408997",
 "suburb": "MASSEY",
 "features": [
  {
   "type": "Feature",
   "geometry": {
    "type": "Point",
    "coordinates": [
     142.8574066,
     -36.24320786
    ]
   },
   "properties": {
    "name": "5968 SUNRAYSIA HIGHWAY MASSEY 3482",
    "locID": "LOC000047540459",
    "tech": "SATELLITE",
    "upgrade": "NULL_NA",
    "gnaf_pid": "GAVIC422025308",
    "tech_change_status": "Not Planned"
   }
  },
  {
   "type": "Feature",
   "geometry": {
    "type": "Point",
    "coordinates": [
     142.85930925,
     -36.23202918
    ]
   },
   "properties": {
    "name": "6102 SUNRAYSIA HIGHWAY MASSEY 3482",
    "locID": "LOC000035732549",
    "tech": "SATELLITE",
    "upgrade": "NULL_NA",
    "gnaf_pid": "GAVIC422030265",
    "tech_change_status": "Not Planned"
   }
  },
  {
   "type": "Feature",
   "geometry": {
    "type": "Point",
    "coordinates": [
     142.85341283,
     -36.22251924
    ]
   },
   "properties": {
    "name": "6273 SUNRAYSIA HIGHWAY MASSEY 3482",
    "locID": "LOC000079083658",
    "tech": "WIRELESS",
    "upgrade": "NULL_NA",
    "gnaf_pid": "GAVIC422030270",
    "tech_change_status": "Not Planned",
    "program_type": "Fixed Wireless and Satellite Upgrade Program",
    "target_eligibility_quarter": "Dec 2024"
   }
  },
  {
   "type": "Feature",
   "geometry": {
    "type": "Point",
    "coordinates": [
     142.85457223,
     -36.22178148
    ]
   },
   "properties": {
    "name": "6260 SUNRAYSIA HIGHWAY MASSEY 3482",
    "locID": "LOC000072065568",
    "tech": "WIRELESS",
    "upgrade": "NULL_NA",
    "gnaf_pid": "GAVIC422036291",
    "tech_change_status": "Not Planned",
    "program_type": "Fixed Wireless and Satellite Upgrade Program",
    "target_eligibility_quarter": "Dec 2024"
   }
  },
  {
   "type": "Feature",
   "geometry": {
    "type": "Point",
    "coordinates": [
     142.81247583,
     -36.20202725
    ]
   },
   "properties": {
    "name": "1053 MASSEY-BANGERANG ROAD MASSEY 3482",
    "locID": "LOC000124939258",
    "tech": "WIRELESS",
    "upgrade": "NULL_NA",
    "gnaf_pid": "GAVIC422168887",
    "tech_change_status": "Not Planned",
    "program_type": "Fixed Wireless and Satellite Upgrade Program",
    "target_eligibility_quarter": "Dec 2024"
   }
  },
  {
   "type": "Feature",
   "geometry": {
    "type": "Point",
    "coordinates": [
     142.7961666,
     -36.20087594
    ]
   },
   "properties": {
    "name": "908 MASSEY-BANGERANG ROAD MASSEY 3482",
    "locID": "LOC000088464462",
    "tech": "SATELLITE",
    "upgrade": "NULL_NA",
    "gnaf_pid": "GAVIC422168888",
    "tech_change_status": "Not Planned"
   }
  },
  {
   "type": "Feature",
   "geometry": {
    "type": "Point",
    "coordinates": [
     142.8554692,
     -36.24279764
    ]
   },
   "properties": {
    "name": "5979 SUNRAYSIA HIGHWAY MASSEY 3482",
    "locID": "LOC000008499609",
    "tech": "SATELLITE",
    "upgrade": "NULL_NA",
    "gnaf_pid": "GAVIC422193914",
    "tech_change_status": "Not Planned"
   }
  },
  {
   "type": "Feature",
   "geometry": {
    "type": "Point",
    "coordinates": [
     142.81945513,
     -36.2229336
    ]
   },
   "properties": {
    "name": "500 VOGELS ROAD MASSEY 3482",
    "locID": "LOC000108940011",
    "tech": "SATELLITE",
    "upgrade": "NULL_NA",
    "gnaf_pid": "GAVIC422199932",
    "tech_change_status": "Not Planned"
   }
  }
 ]
}