{
 "type": "FeatureCollection",
 "generated": "2024-09-23T15:11:07.946523",
 "suburb": "MEATIAN",
 "features": [
  {
   "type": "Feature",
   "geometry": {
    "type": "Point",
    "coordinates": [
     143.34127786,
     -35.57516184
    ]
   },
   "properties": {
    "name": "5 MEATIAN WEST ROAD MEATIAN 3585",
    "locID": "LOC000024791354",
    "tech": "SATELLITE",
    "upgrade": "NULL_NA",
    "gnaf_pid": "GAVIC411806459",
    "tech_change_status": "Not Planned"
   }
  },
  {
   "type": "Feature",
   "geometry": {
    "type": "Point",
    "coordinates": [
     143.35629224,
     -35.57534105
    ]
   },
   "properties": {
    "name": "339 MEATIAN EAST ROAD MEATIAN 3585",
    "locID": "LOC000061836058",
    "tech": "NULL",
    "upgrade": "NULL_NA",
    "gnaf_pid": "GAVIC411806462",
    "tech_change_status": "Not Planned"
   }
  },
  {
   "type": "Feature",
   "geometry": {
    "type": "Point",
    "coordinates": [
     143.34223,
     -35.56754511
    ]
   },
   "properties": {
    "name": "82 MEATIAN NORTH ROAD MEATIAN 3585",
    "locID": "LOC000019511278",
    "tech": "NULL",
    "upgrade": "NULL_NA",
    "gnaf_pid": "GAVIC411806463",
    "tech_change_status": "Not Planned"
   }
  },
  {
   "type": "Feature",
   "geometry": {
    "type": "Point",
    "coordinates": [
     143.32405859,
     -35.57477474
    ]
   },
   "properties": {
    "name": "162 MEATIAN WEST ROAD MEATIAN 3585",
    "locID": "LOC000075549120",
    "tech": "NULL",
    "upgrade": "NULL_NA",
    "gnaf_pid": "GAVIC411806464",
    "tech_change_status": "Not Planned"
   }
  },
  {
   "type": "Feature",
   "geometry": {
    "type": "Point",
    "coordinates": [
     143.33953885,
     -35.5747817
    ]
   },
   "properties": {
    "name": "22 MEATIAN WEST ROAD MEATIAN 3585",
    "locID": "LOC000092985312",
    "tech": "SATELLITE",
    "upgrade": "NULL_NA",
    "gnaf_pid": "GAVIC411806466",
    "tech_change_status": "Not Planned"
   }
  },
  {
   "type": "Feature",
   "geometry": {
    "type": "Point",
    "coordinates": [
     143.3416018,
     -35.57325428
    ]
   },
   "properties": {
    "name": "15 MEATIAN NORTH ROAD MEATIAN 3585",
    "locID": "LOC000008535767",
    "tech": "NULL",
    "upgrade": "NULL_NA",
    "gnaf_pid": "GAVIC421997938",
    "tech_change_status": "Not Planned"
   }
  },
  {
   "type": "Feature",
   "geometry": {
    "type": "Point",
    "coordinates": [
     143.34158765,
     -35.5723892
    ]
   },
   "properties": {
    "name": "27 MEATIAN NORTH ROAD MEATIAN 3585",
    "locID": "LOC000124889170",
    "tech": "NULL",
    "upgrade": "NULL_NA",
    "gnaf_pid": "GAVIC422170446",
    "tech_change_status": "Not Planned"
   }
  },
  {
   "type": "Feature",
   "geometry": {
    "type": "Point",
    "coordinates": [
     143.40943116,
     -35.56911388
    ]
   },
   "properties": {
    "name": "129 MYSTIC PARK-MEATIAN ROAD MEATIAN 3585",
    "locID": "LOC000103058778",
    "tech": "NULL",
    "upgrade": "NULL_NA",
    "gnaf_pid": "GAVIC422175555",
    "tech_change_status": "Not Planned"
   }
  }
 ]
}