{
 "type": "FeatureCollection",
 "generated": "2023-10-24T16:41:42.715144",
 "suburb": "MEATIAN",
 "features": [
  {
   "type": "Feature",
   "geometry": {
    "type": "Point",
    "coordinates": [
     143.34127786,
     -35.57516184
    ]
   },
   "properties": {
    "name": "5 MEATIAN WEST ROAD MEATIAN 3585",
    "locID": "LOC000024791354",
    "tech": "SATELLITE",
    "upgrade": "NULL_NA",
    "gnaf_pid": "GAVIC411806459"
   }
  },
  {
   "type": "Feature",
   "geometry": {
    "type": "Point",
    "coordinates": [
     143.35629224,
     -35.57534105
    ]
   },
   "properties": {
    "name": "339 MEATIAN EAST ROAD MEATIAN 3585",
    "locID": "LOC000061836058",
    "tech": "SATELLITE",
    "upgrade": "NULL_NA",
    "gnaf_pid": "GAVIC411806462"
   }
  },
  {
   "type": "Feature",
   "geometry": {
    "type": "Point",
    "coordinates": [
     143.34223,
     -35.56754511
    ]
   },
   "properties": {
    "name": "82 MEATIAN NORTH ROAD MEATIAN 3585",
    "locID": "LOC000019511278",
    "tech": "SATELLITE",
    "upgrade": "NULL_NA",
    "gnaf_pid": "GAVIC411806463"
   }
  },
  {
   "type": "Feature",
   "geometry": {
    "type": "Point",
    "coordinates": [
     143.32405859,
     -35.57477474
    ]
   },
   "properties": {
    "name": "162 MEATIAN WEST ROAD MEATIAN 3585",
    "locID": "LOC000075549120",
    "tech": "SATELLITE",
    "upgrade": "NULL_NA",
    "gnaf_pid": "GAVIC411806464"
   }
  },
  {
   "type": "Feature",
   "geometry": {
    "type": "Point",
    "coordinates": [
     143.33953885,
     -35.5747817
    ]
   },
   "properties": {
    "name": "22 MEATIAN WEST ROAD MEATIAN 3585",
    "locID": "LOC000092985312",
    "tech": "SATELLITE",
    "upgrade": "NULL_NA",
    "gnaf_pid": "GAVIC411806466"
   }
  },
  {
   "type": "Feature",
   "geometry": {
    "type": "Point",
    "coordinates": [
     143.34079942,
     -35.57479726
    ]
   },
   "properties": {
    "name": "10 MEATIAN WEST ROAD MEATIAN 3585",
    "locID": "ChIJ4dDqfQIJ22oRl9nuq9uLMpw",
    "tech": "SATELLITE",
    "upgrade": "UNKNOWN",
    "gnaf_pid": "GAVIC420975029"
   }
  },
  {
   "type": "Feature",
   "geometry": {
    "type": "Point",
    "coordinates": [
     143.3416018,
     -35.57325428
    ]
   },
   "properties": {
    "name": "15 MEATIAN NORTH ROAD MEATIAN 3585",
    "locID": "LOC000008535767",
    "tech": "SATELLITE",
    "upgrade": "NULL_NA",
    "gnaf_pid": "GAVIC421997938"
   }
  },
  {
   "type": "Feature",
   "geometry": {
    "type": "Point",
    "coordinates": [
     143.34158765,
     -35.5723892
    ]
   },
   "properties": {
    "name": "27 MEATIAN NORTH ROAD MEATIAN 3585",
    "locID": "LOC000124889170",
    "tech": "SATELLITE",
    "upgrade": "NULL_NA",
    "gnaf_pid": "GAVIC422170446"
   }
  },
  {
   "type": "Feature",
   "geometry": {
    "type": "Point",
    "coordinates": [
     143.40943116,
     -35.56911388
    ]
   },
   "properties": {
    "name": "129 MYSTIC PARK-MEATIAN ROAD MEATIAN 3585",
    "locID": "LOC000103058778",
    "tech": "SATELLITE",
    "upgrade": "NULL_NA",
    "gnaf_pid": "GAVIC422175555"
   }
  },
  {
   "type": "Feature",
   "geometry": {
    "type": "Point",
    "coordinates": [
     143.34113938,
     -35.57480469
    ]
   },
   "properties": {
    "name": "6 MEATIAN WEST ROAD MEATIAN 3585",
    "locID": "ChIJZfK1eBoJ22oRuUOuwnN3xtA",
    "tech": "SATELLITE",
    "upgrade": "UNKNOWN",
    "gnaf_pid": "GAVIC422309058"
   }
  },
  {
   "type": "Feature",
   "geometry": {
    "type": "Point",
    "coordinates": [
     143.33968441,
     -35.57315762
    ]
   },
   "properties": {
    "name": "28 GILMORE LANE MEATIAN 3585",
    "locID": "ChIJXQ3UZgIJ22oROQ-iLajSi3U",
    "tech": "SATELLITE",
    "upgrade": "UNKNOWN",
    "gnaf_pid": "GAVIC719616184"
   }
  }
 ]
}