{
 "type": "FeatureCollection",
 "generated": "2023-10-24T19:59:37.966574",
 "suburb": "MOUNT DRYDEN",
 "features": [
  {
   "type": "Feature",
   "geometry": {
    "type": "Point",
    "coordinates": [
     142.54368958,
     -37.05947341
    ]
   },
   "properties": {
    "name": "59 PINES ROAD MOUNT DRYDEN 3381",
    "locID": "ChIJOZJ9FBAazmoRMynsPBlzV50",
    "tech": "SATELLITE",
    "upgrade": "UNKNOWN",
    "gnaf_pid": "GAVIC421997285"
   }
  },
  {
   "type": "Feature",
   "geometry": {
    "type": "Point",
    "coordinates": [
     142.581824,
     -37.06467595
    ]
   },
   "properties": {
    "name": "701 FYANS CREEK ROAD MOUNT DRYDEN 3381",
    "locID": "ChIJzVzNMNYbzmoRUeMUKRpzLjU",
    "tech": "SATELLITE",
    "upgrade": "UNKNOWN",
    "gnaf_pid": "GAVIC422148223"
   }
  },
  {
   "type": "Feature",
   "geometry": {
    "type": "Point",
    "coordinates": [
     142.53748038,
     -37.0509732
    ]
   },
   "properties": {
    "name": "174 HEATHERLIE TRACK MOUNT DRYDEN 3381",
    "locID": "ChIJjY-mTv4ZzmoR5LBl0BDJMA8",
    "tech": "SATELLITE",
    "upgrade": "UNKNOWN",
    "gnaf_pid": "GAVIC422154699"
   }
  },
  {
   "type": "Feature",
   "geometry": {
    "type": "Point",
    "coordinates": [
     142.54776214,
     -37.05660167
    ]
   },
   "properties": {
    "name": "71 HEATHERLIE TRACK MOUNT DRYDEN 3381",
    "locID": "LOC000124578282",
    "tech": "SATELLITE",
    "upgrade": "NULL_NA",
    "gnaf_pid": "GAVIC422154700"
   }
  },
  {
   "type": "Feature",
   "geometry": {
    "type": "Point",
    "coordinates": [
     142.56275906,
     -37.03816761
    ]
   },
   "properties": {
    "name": "239 SCARSIS ROAD MOUNT DRYDEN 3381",
    "locID": "LOC000091059283",
    "tech": "SATELLITE",
    "upgrade": "NULL_NA",
    "gnaf_pid": "GAVIC422188554"
   }
  },
  {
   "type": "Feature",
   "geometry": {
    "type": "Point",
    "coordinates": [
     142.5626797,
     -37.0382862
    ]
   },
   "properties": {
    "name": "237 SCARSIS ROAD MOUNT DRYDEN 3381",
    "locID": "LOC000067751522",
    "tech": "SATELLITE",
    "upgrade": "NULL_NA",
    "gnaf_pid": "GAVIC422321637"
   }
  },
  {
   "type": "Feature",
   "geometry": {
    "type": "Point",
    "coordinates": [
     142.51574581,
     -37.06032703
    ]
   },
   "properties": {
    "name": "554 PINES ROAD MOUNT DRYDEN 3381",
    "locID": "ChIJcblDKJQQzmoRo4ZU5_Sl1nE",
    "tech": "SATELLITE",
    "upgrade": "UNKNOWN",
    "gnaf_pid": "GAVIC425167017"
   }
  }
 ]
}