{
 "type": "FeatureCollection",
 "generated": "2024-07-06T13:32:38.675839",
 "suburb": "MOUNT DRYDEN",
 "features": [
  {
   "type": "Feature",
   "geometry": {
    "type": "Point",
    "coordinates": [
     142.54776214,
     -37.05660167
    ]
   },
   "properties": {
    "name": "71 HEATHERLIE TRACK MOUNT DRYDEN 3381",
    "locID": "LOC000124578282",
    "tech": "SATELLITE",
    "upgrade": "NULL_NA",
    "gnaf_pid": "GAVIC422154700",
    "tech_change_status": "Not Planned"
   }
  },
  {
   "type": "Feature",
   "geometry": {
    "type": "Point",
    "coordinates": [
     142.56275906,
     -37.03816761
    ]
   },
   "properties": {
    "name": "239 SCARSIS ROAD MOUNT DRYDEN 3381",
    "locID": "LOC000091059283",
    "tech": "SATELLITE",
    "upgrade": "NULL_NA",
    "gnaf_pid": "GAVIC422188554",
    "tech_change_status": "Not Planned"
   }
  },
  {
   "type": "Feature",
   "geometry": {
    "type": "Point",
    "coordinates": [
     142.5626797,
     -37.0382862
    ]
   },
   "properties": {
    "name": "237 SCARSIS ROAD MOUNT DRYDEN 3381",
    "locID": "LOC000067751522",
    "tech": "SATELLITE",
    "upgrade": "NULL_NA",
    "gnaf_pid": "GAVIC422321637",
    "tech_change_status": "Not Planned"
   }
  }
 ]
}