{
 "type": "FeatureCollection",
 "generated": "2024-09-23T19:30:44.558836",
 "suburb": "MOYREISK",
 "features": [
  {
   "type": "Feature",
   "geometry": {
    "type": "Point",
    "coordinates": [
     143.37590786,
     -36.89356804
    ]
   },
   "properties": {
    "name": "3764 MARYBOROUGH-ST ARNAUD ROAD MOYREISK 3477",
    "locID": "LOC000041484676",
    "tech": "NULL",
    "upgrade": "NULL_NA",
    "gnaf_pid": "GAVIC422168750",
    "tech_change_status": "Not Planned"
   }
  },
  {
   "type": "Feature",
   "geometry": {
    "type": "Point",
    "coordinates": [
     143.36840398,
     -36.89329811
    ]
   },
   "properties": {
    "name": "3832 MARYBOROUGH-ST ARNAUD ROAD MOYREISK 3477",
    "locID": "LOC000036035964",
    "tech": "NULL",
    "upgrade": "NULL_NA",
    "gnaf_pid": "GAVIC422168751",
    "tech_change_status": "Not Planned"
   }
  },
  {
   "type": "Feature",
   "geometry": {
    "type": "Point",
    "coordinates": [
     143.33237834,
     -36.85802033
    ]
   },
   "properties": {
    "name": "3134 SUNRAYSIA HIGHWAY MOYREISK 3477",
    "locID": "LOC000083972034",
    "tech": "SATELLITE",
    "upgrade": "NULL_NA",
    "gnaf_pid": "GAVIC422193916",
    "tech_change_status": "Not Planned"
   }
  },
  {
   "type": "Feature",
   "geometry": {
    "type": "Point",
    "coordinates": [
     143.33194762,
     -36.85550372
    ]
   },
   "properties": {
    "name": "3164 SUNRAYSIA HIGHWAY MOYREISK 3477",
    "locID": "LOC000045245864",
    "tech": "SATELLITE",
    "upgrade": "NULL_NA",
    "gnaf_pid": "GAVIC422193917",
    "tech_change_status": "Not Planned"
   }
  },
  {
   "type": "Feature",
   "geometry": {
    "type": "Point",
    "coordinates": [
     143.33321594,
     -36.85210427
    ]
   },
   "properties": {
    "name": "15 MOYREISK NORTH ROAD MOYREISK 3477",
    "locID": "LOC000059868758",
    "tech": "SATELLITE",
    "upgrade": "NULL_NA",
    "gnaf_pid": "GAVIC423227223",
    "tech_change_status": "Not Planned"
   }
  },
  {
   "type": "Feature",
   "geometry": {
    "type": "Point",
    "coordinates": [
     143.3400406,
     -36.86069719
    ]
   },
   "properties": {
    "name": "46 VOSS ROAD MOYREISK 3477",
    "locID": "LOC000067246954",
    "tech": "NULL",
    "upgrade": "NULL_NA",
    "gnaf_pid": "GAVIC423239312",
    "tech_change_status": "Not Planned"
   }
  },
  {
   "type": "Feature",
   "geometry": {
    "type": "Point",
    "coordinates": [
     143.34019554,
     -36.85708233
    ]
   },
   "properties": {
    "name": "6 VOSS ROAD MOYREISK 3477",
    "locID": "LOC000048478206",
    "tech": "SATELLITE",
    "upgrade": "NULL_NA",
    "gnaf_pid": "GAVIC423239313",
    "tech_change_status": "Not Planned"
   }
  },
  {
   "type": "Feature",
   "geometry": {
    "type": "Point",
    "coordinates": [
     143.34081076,
     -36.85722336
    ]
   },
   "properties": {
    "name": "7 VOSS ROAD MOYREISK 3477",
    "locID": "LOC000124805068",
    "tech": "SATELLITE",
    "upgrade": "NULL_NA",
    "gnaf_pid": "GAVIC423239314",
    "tech_change_status": "Not Planned"
   }
  },
  {
   "type": "Feature",
   "geometry": {
    "type": "Point",
    "coordinates": [
     143.37851385,
     -36.90412163
    ]
   },
   "properties": {
    "name": "105 SMITH ROAD MOYREISK 3477",
    "locID": "LOC000013542852",
    "tech": "NULL",
    "upgrade": "NULL_NA",
    "gnaf_pid": "GAVIC423488284",
    "tech_change_status": "Not Planned"
   }
  },
  {
   "type": "Feature",
   "geometry": {
    "type": "Point",
    "coordinates": [
     143.33582296,
     -36.86693369
    ]
   },
   "properties": {
    "name": "3022 SUNRAYSIA HIGHWAY MOYREISK 3477",
    "locID": "LOC000021042438",
    "tech": "NULL",
    "upgrade": "NULL_NA",
    "gnaf_pid": "GAVIC423838344",
    "tech_change_status": "Not Planned"
   }
  },
  {
   "type": "Feature",
   "geometry": {
    "type": "Point",
    "coordinates": [
     143.36786878,
     -36.91166623
    ]
   },
   "properties": {
    "name": "347 GRANTS ROAD MOYREISK 3477",
    "locID": "LOC000037177832",
    "tech": "SATELLITE",
    "upgrade": "NULL_NA",
    "gnaf_pid": "GAVIC423882619",
    "tech_change_status": "Not Planned"
   }
  },
  {
   "type": "Feature",
   "geometry": {
    "type": "Point",
    "coordinates": [
     143.34050095,
     -36.87145443
    ]
   },
   "properties": {
    "name": "2956 SUNRAYSIA HIGHWAY MOYREISK 3477",
    "locID": "LOC000148367804",
    "tech": "NULL",
    "upgrade": "NULL_NA",
    "gnaf_pid": "GAVIC425423368",
    "tech_change_status": "Not Planned"
   }
  },
  {
   "type": "Feature",
   "geometry": {
    "type": "Point",
    "coordinates": [
     143.339871,
     -36.8592639
    ]
   },
   "properties": {
    "name": "30 VOSS ROAD MOYREISK 3477",
    "locID": "LOC000148368615",
    "tech": "SATELLITE",
    "upgrade": "NULL_NA",
    "gnaf_pid": "GAVIC425529985",
    "tech_change_status": "Not Planned"
   }
  }
 ]
}