{
 "type": "FeatureCollection",
 "generated": "2024-09-23T20:35:02.608251",
 "suburb": "NARRUNG",
 "features": [
  {
   "type": "Feature",
   "geometry": {
    "type": "Point",
    "coordinates": [
     143.21088033,
     -34.7640453
    ]
   },
   "properties": {
    "name": "8045 MURRAY VALLEY HIGHWAY NARRUNG 3597",
    "locID": "LOC000060587309",
    "tech": "NULL",
    "upgrade": "NULL_NA",
    "gnaf_pid": "GAVIC411986235",
    "tech_change_status": "Not Planned"
   }
  },
  {
   "type": "Feature",
   "geometry": {
    "type": "Point",
    "coordinates": [
     143.23626209,
     -34.78565125
    ]
   },
   "properties": {
    "name": "103 HEYWOOD LAKE ROAD NARRUNG 3597",
    "locID": "LOC000092068221",
    "tech": "SATELLITE",
    "upgrade": "NULL_NA",
    "gnaf_pid": "GAVIC422155356",
    "tech_change_status": "Not Planned"
   }
  },
  {
   "type": "Feature",
   "geometry": {
    "type": "Point",
    "coordinates": [
     143.24411615,
     -34.78297555
    ]
   },
   "properties": {
    "name": "33 HEYWOOD LAKE ROAD NARRUNG 3597",
    "locID": "LOC000124901349",
    "tech": "NULL",
    "upgrade": "NULL_NA",
    "gnaf_pid": "GAVIC422155357",
    "tech_change_status": "Not Planned"
   }
  },
  {
   "type": "Feature",
   "geometry": {
    "type": "Point",
    "coordinates": [
     143.24045844,
     -34.78412612
    ]
   },
   "properties": {
    "name": "99 HEYWOOD LAKE ROAD NARRUNG 3597",
    "locID": "LOC000095957450",
    "tech": "NULL",
    "upgrade": "NULL_NA",
    "gnaf_pid": "GAVIC422155358",
    "tech_change_status": "Not Planned"
   }
  },
  {
   "type": "Feature",
   "geometry": {
    "type": "Point",
    "coordinates": [
     143.247488,
     -34.79464006
    ]
   },
   "properties": {
    "name": "7413 MURRAY VALLEY HIGHWAY NARRUNG 3597",
    "locID": "LOC000016147257",
    "tech": "NULL",
    "upgrade": "NULL_NA",
    "gnaf_pid": "GAVIC422174823",
    "tech_change_status": "Not Planned"
   }
  },
  {
   "type": "Feature",
   "geometry": {
    "type": "Point",
    "coordinates": [
     143.24753441,
     -34.7808416
    ]
   },
   "properties": {
    "name": "7566 MURRAY VALLEY HIGHWAY NARRUNG 3597",
    "locID": "LOC000087596917",
    "tech": "NULL",
    "upgrade": "NULL_NA",
    "gnaf_pid": "GAVIC422174824",
    "tech_change_status": "Not Planned"
   }
  },
  {
   "type": "Feature",
   "geometry": {
    "type": "Point",
    "coordinates": [
     143.24668101,
     -34.77657921
    ]
   },
   "properties": {
    "name": "7616 MURRAY VALLEY HIGHWAY NARRUNG 3597",
    "locID": "LOC000007761369",
    "tech": "NULL",
    "upgrade": "NULL_NA",
    "gnaf_pid": "GAVIC422174825",
    "tech_change_status": "Not Planned"
   }
  },
  {
   "type": "Feature",
   "geometry": {
    "type": "Point",
    "coordinates": [
     143.24888795,
     -34.77998778
    ]
   },
   "properties": {
    "name": "19 FISHER ROAD NARRUNG 3597",
    "locID": "LOC000124901331",
    "tech": "NULL",
    "upgrade": "NULL_NA",
    "gnaf_pid": "GAVIC424250789",
    "tech_change_status": "Not Planned"
   }
  },
  {
   "type": "Feature",
   "geometry": {
    "type": "Point",
    "coordinates": [
     143.24888795,
     -34.77998778
    ]
   },
   "properties": {
    "name": "39 FISHER ROAD NARRUNG 3597",
    "locID": "LOC000124901331",
    "tech": "NULL",
    "upgrade": "NULL_NA",
    "gnaf_pid": "GAVIC424250790",
    "tech_change_status": "Not Planned"
   }
  },
  {
   "type": "Feature",
   "geometry": {
    "type": "Point",
    "coordinates": [
     143.25614588,
     -34.78003609
    ]
   },
   "properties": {
    "name": "50A FISHER ROAD NARRUNG 3597",
    "locID": "LOC000059553435",
    "tech": "SATELLITE",
    "upgrade": "NULL_NA",
    "gnaf_pid": "GAVIC424250792",
    "tech_change_status": "Not Planned"
   }
  },
  {
   "type": "Feature",
   "geometry": {
    "type": "Point",
    "coordinates": [
     143.24888795,
     -34.77998778
    ]
   },
   "properties": {
    "name": "19-39 FISHER ROAD NARRUNG 3597",
    "locID": "LOC000124901331",
    "tech": "NULL",
    "upgrade": "NULL_NA",
    "gnaf_pid": "GAVIC424263563",
    "tech_change_status": "Not Planned"
   }
  },
  {
   "type": "Feature",
   "geometry": {
    "type": "Point",
    "coordinates": [
     143.25223131,
     -34.78003086
    ]
   },
   "properties": {
    "name": "49A FISHER ROAD NARRUNG 3597",
    "locID": "LOC000113063576",
    "tech": "SATELLITE",
    "upgrade": "NULL_NA",
    "gnaf_pid": "GAVIC424263564",
    "tech_change_status": "Not Planned"
   }
  },
  {
   "type": "Feature",
   "geometry": {
    "type": "Point",
    "coordinates": [
     143.25216954,
     -34.78001439
    ]
   },
   "properties": {
    "name": "49 FISHER ROAD NARRUNG 3597",
    "locID": "LOC000113063576",
    "tech": "SATELLITE",
    "upgrade": "NULL_NA",
    "gnaf_pid": "GAVIC719212217",
    "tech_change_status": "Not Planned"
   }
  }
 ]
}