{
 "type": "FeatureCollection",
 "generated": "2024-09-23T21:14:19.055831",
 "suburb": "NINYEUNOOK",
 "features": [
  {
   "type": "Feature",
   "geometry": {
    "type": "Point",
    "coordinates": [
     143.45786111,
     -35.9729204
    ]
   },
   "properties": {
    "name": "587 HOLMES BRIDGE ROAD NINYEUNOOK 3527",
    "locID": "LOC000053017459",
    "tech": "SATELLITE",
    "upgrade": "NULL_NA",
    "gnaf_pid": "GAVIC412003358",
    "tech_change_status": "Not Planned"
   }
  },
  {
   "type": "Feature",
   "geometry": {
    "type": "Point",
    "coordinates": [
     143.43349708,
     -35.95050923
    ]
   },
   "properties": {
    "name": "1515 NINYEUNOOK ROAD NINYEUNOOK 3527",
    "locID": "LOC000060199674",
    "tech": "SATELLITE",
    "upgrade": "NULL_NA",
    "gnaf_pid": "GAVIC421991466",
    "tech_change_status": "Not Planned"
   }
  },
  {
   "type": "Feature",
   "geometry": {
    "type": "Point",
    "coordinates": [
     143.45219614,
     -35.93709814
    ]
   },
   "properties": {
    "name": "1290 NINYEUNOOK ROAD NINYEUNOOK 3527",
    "locID": "LOC000021121570",
    "tech": "NULL",
    "upgrade": "NULL_NA",
    "gnaf_pid": "GAVIC422177387",
    "tech_change_status": "Not Planned"
   }
  },
  {
   "type": "Feature",
   "geometry": {
    "type": "Point",
    "coordinates": [
     143.4170237,
     -35.96961735
    ]
   },
   "properties": {
    "name": "1777 NINYEUNOOK ROAD NINYEUNOOK 3527",
    "locID": "LOC000101578872",
    "tech": "SATELLITE",
    "upgrade": "NULL_NA",
    "gnaf_pid": "GAVIC423106518",
    "tech_change_status": "Not Planned"
   }
  },
  {
   "type": "Feature",
   "geometry": {
    "type": "Point",
    "coordinates": [
     143.42085074,
     -35.96443307
    ]
   },
   "properties": {
    "name": "LOT 48 NINYEUNOOK ROAD NINYEUNOOK 3527",
    "locID": "LOC000101578872",
    "tech": "SATELLITE",
    "upgrade": "NULL_NA",
    "gnaf_pid": "GAVIC423404637",
    "tech_change_status": "Not Planned"
   }
  }
 ]
}