{
 "type": "FeatureCollection",
 "generated": "2023-10-24T22:11:11.803901",
 "suburb": "NINYEUNOOK",
 "features": [
  {
   "type": "Feature",
   "geometry": {
    "type": "Point",
    "coordinates": [
     143.45786111,
     -35.9729204
    ]
   },
   "properties": {
    "name": "587 HOLMES BRIDGE ROAD NINYEUNOOK 3527",
    "locID": "LOC000053017459",
    "tech": "SATELLITE",
    "upgrade": "NULL_NA",
    "gnaf_pid": "GAVIC412003358"
   }
  },
  {
   "type": "Feature",
   "geometry": {
    "type": "Point",
    "coordinates": [
     143.43349708,
     -35.95050923
    ]
   },
   "properties": {
    "name": "1515 NINYEUNOOK ROAD NINYEUNOOK 3527",
    "locID": "LOC000060199674",
    "tech": "SATELLITE",
    "upgrade": "NULL_NA",
    "gnaf_pid": "GAVIC421991466"
   }
  },
  {
   "type": "Feature",
   "geometry": {
    "type": "Point",
    "coordinates": [
     143.45535557,
     -35.93380846
    ]
   },
   "properties": {
    "name": "1232 NINYEUNOOK ROAD NINYEUNOOK 3527",
    "locID": "ChIJoehWTRZX2moRAgjwLgmVFD0",
    "tech": "SATELLITE",
    "upgrade": "UNKNOWN",
    "gnaf_pid": "GAVIC422177386"
   }
  },
  {
   "type": "Feature",
   "geometry": {
    "type": "Point",
    "coordinates": [
     143.45219614,
     -35.93709814
    ]
   },
   "properties": {
    "name": "1290 NINYEUNOOK ROAD NINYEUNOOK 3527",
    "locID": "LOC000021121570",
    "tech": "SATELLITE",
    "upgrade": "NULL_NA",
    "gnaf_pid": "GAVIC422177387"
   }
  },
  {
   "type": "Feature",
   "geometry": {
    "type": "Point",
    "coordinates": [
     143.40164417,
     -36.00232161
    ]
   },
   "properties": {
    "name": "2172 NINYEUNOOK ROAD NINYEUNOOK 3527",
    "locID": "ChIJuW-MbqpY2moRLaSnrYt3BYM",
    "tech": "SATELLITE",
    "upgrade": "UNKNOWN",
    "gnaf_pid": "GAVIC422177388"
   }
  },
  {
   "type": "Feature",
   "geometry": {
    "type": "Point",
    "coordinates": [
     143.4170237,
     -35.96961735
    ]
   },
   "properties": {
    "name": "1777 NINYEUNOOK ROAD NINYEUNOOK 3527",
    "locID": "LOC000101578872",
    "tech": "SATELLITE",
    "upgrade": "NULL_NA",
    "gnaf_pid": "GAVIC423106518"
   }
  },
  {
   "type": "Feature",
   "geometry": {
    "type": "Point",
    "coordinates": [
     143.42085074,
     -35.96443307
    ]
   },
   "properties": {
    "name": "LOT 48 NINYEUNOOK ROAD NINYEUNOOK 3527",
    "locID": "LOC000101578872",
    "tech": "SATELLITE",
    "upgrade": "NULL_NA",
    "gnaf_pid": "GAVIC423404637"
   }
  }
 ]
}