{
 "type": "FeatureCollection",
 "generated": "2023-11-30T19:56:40.064870",
 "suburb": "OCEAN GRANGE",
 "features": [
  {
   "type": "Feature",
   "geometry": {
    "type": "Point",
    "coordinates": [
     147.61592188,
     -38.04626407
    ]
   },
   "properties": {
    "name": "LOT 2 STOCKYARD HILL CAUSEWAY OCEAN GRANGE 3880",
    "locID": "EjdTdG9ja3lhcmQgSGlsbCBDYXVzZXdheSwgTG9jaCBTcG9ydCBWSUMgMzg1MSwgQXVzdHJhbGlhIi4qLAoUChIJ1dt5OaR1L2sRzfQ8IlcpdnYSFAoSCY0Z9Zu6Cy9rEeBioDCkeQUE",
    "tech": "SATELLITE",
    "upgrade": "UNKNOWN",
    "gnaf_pid": "GAVIC425035091"
   }
  }
 ]
}