{
 "type": "FeatureCollection",
 "generated": "2023-10-25T01:15:28.912250",
 "suburb": "PIRA",
 "features": [
  {
   "type": "Feature",
   "geometry": {
    "type": "Point",
    "coordinates": [
     143.36245308,
     -35.24278312
    ]
   },
   "properties": {
    "name": "612 PIRA ROAD PIRA 3585",
    "locID": "LOC000040586222",
    "tech": "SATELLITE",
    "upgrade": "NULL_NA",
    "gnaf_pid": "GAVIC412104812"
   }
  },
  {
   "type": "Feature",
   "geometry": {
    "type": "Point",
    "coordinates": [
     143.36373846,
     -35.24224018
    ]
   },
   "properties": {
    "name": "603 PIRA ROAD PIRA 3585",
    "locID": "LOC000104330149",
    "tech": "SATELLITE",
    "upgrade": "NULL_NA",
    "gnaf_pid": "GAVIC412104813"
   }
  },
  {
   "type": "Feature",
   "geometry": {
    "type": "Point",
    "coordinates": [
     143.34664143,
     -35.25732032
    ]
   },
   "properties": {
    "name": "1514 CHILLINGOLLAH ROAD PIRA 3585",
    "locID": "LOC000032833920",
    "tech": "SATELLITE",
    "upgrade": "NULL_NA",
    "gnaf_pid": "GAVIC412104814"
   }
  },
  {
   "type": "Feature",
   "geometry": {
    "type": "Point",
    "coordinates": [
     143.36692005,
     -35.25569321
    ]
   },
   "properties": {
    "name": "765 PIRA ROAD PIRA 3585",
    "locID": "LOC000047493995",
    "tech": "SATELLITE",
    "upgrade": "NULL_NA",
    "gnaf_pid": "GAVIC412104815"
   }
  },
  {
   "type": "Feature",
   "geometry": {
    "type": "Point",
    "coordinates": [
     143.38728254,
     -35.28246465
    ]
   },
   "properties": {
    "name": "482 BARRY ROAD PIRA 3585",
    "locID": "LOC000012685654",
    "tech": "SATELLITE",
    "upgrade": "NULL_NA",
    "gnaf_pid": "GAVIC420869780"
   }
  },
  {
   "type": "Feature",
   "geometry": {
    "type": "Point",
    "coordinates": [
     143.37323889,
     -35.25636866
    ]
   },
   "properties": {
    "name": "1312 CHILLINGOLLAH ROAD PIRA 3585",
    "locID": "LOC000030260447",
    "tech": "SATELLITE",
    "upgrade": "NULL_NA",
    "gnaf_pid": "GAVIC422136247"
   }
  },
  {
   "type": "Feature",
   "geometry": {
    "type": "Point",
    "coordinates": [
     143.36392625,
     -35.2577865
    ]
   },
   "properties": {
    "name": "1357 CHILLINGOLLAH ROAD PIRA 3585",
    "locID": "LOC000017749316",
    "tech": "SATELLITE",
    "upgrade": "NULL_NA",
    "gnaf_pid": "GAVIC422136248"
   }
  },
  {
   "type": "Feature",
   "geometry": {
    "type": "Point",
    "coordinates": [
     143.38319465,
     -35.21696045
    ]
   },
   "properties": {
    "name": "189 WILLOUGHBY ROAD PIRA 3585",
    "locID": "LOC000049195107",
    "tech": "SATELLITE",
    "upgrade": "NULL_NA",
    "gnaf_pid": "GAVIC422435780"
   }
  },
  {
   "type": "Feature",
   "geometry": {
    "type": "Point",
    "coordinates": [
     143.36580465,
     -35.25538503
    ]
   },
   "properties": {
    "name": "1324 CHILLINGOLLAH ROAD PIRA 3585",
    "locID": "ChIJmTJa0sZ422oReO8xyYY8Ao4",
    "tech": "SATELLITE",
    "upgrade": "UNKNOWN",
    "gnaf_pid": "GAVIC423445349"
   }
  },
  {
   "type": "Feature",
   "geometry": {
    "type": "Point",
    "coordinates": [
     143.35715229,
     -35.2573239
    ]
   },
   "properties": {
    "name": "1412 CHILLINGOLLAH ROAD PIRA 3585",
    "locID": "LOC000023899155",
    "tech": "SATELLITE",
    "upgrade": "NULL_NA",
    "gnaf_pid": "GAVIC423846917"
   }
  },
  {
   "type": "Feature",
   "geometry": {
    "type": "Point",
    "coordinates": [
     143.35562785,
     -35.25764774
    ]
   },
   "properties": {
    "name": "1413 CHILLINGOLLAH ROAD PIRA 3585",
    "locID": "ChIJ2bhMnud422oR_2CsgxhaHj8",
    "tech": "SATELLITE",
    "upgrade": "UNKNOWN",
    "gnaf_pid": "GAVIC425462930"
   }
  },
  {
   "type": "Feature",
   "geometry": {
    "type": "Point",
    "coordinates": [
     143.3766106,
     -35.257327
    ]
   },
   "properties": {
    "name": "1306 CHILLINGOLLAH ROAD PIRA 3585",
    "locID": "ChIJdcsLr7t422oRrZtijBUryK8",
    "tech": "SATELLITE",
    "upgrade": "UNKNOWN",
    "gnaf_pid": "GAVIC720053322"
   }
  }
 ]
}