{
 "type": "FeatureCollection",
 "generated": "2023-10-25T01:44:29.262748",
 "suburb": "POLISBET",
 "features": [
  {
   "type": "Feature",
   "geometry": {
    "type": "Point",
    "coordinates": [
     143.14788852,
     -35.30079179
    ]
   },
   "properties": {
    "name": "496 POLISBET ROAD POLISBET 3585",
    "locID": "LOC000102169316",
    "tech": "SATELLITE",
    "upgrade": "NULL_NA",
    "gnaf_pid": "GAVIC412132595"
   }
  },
  {
   "type": "Feature",
   "geometry": {
    "type": "Point",
    "coordinates": [
     143.12732687,
     -35.29121993
    ]
   },
   "properties": {
    "name": "142 WAITCHIE TANK ROAD POLISBET 3585",
    "locID": "LOC000109746781",
    "tech": "SATELLITE",
    "upgrade": "NULL_NA",
    "gnaf_pid": "GAVIC421185213"
   }
  },
  {
   "type": "Feature",
   "geometry": {
    "type": "Point",
    "coordinates": [
     143.19782299,
     -35.30069402
    ]
   },
   "properties": {
    "name": "268 POLISBET ROAD POLISBET 3585",
    "locID": "LOC000030246677",
    "tech": "SATELLITE",
    "upgrade": "NULL_NA",
    "gnaf_pid": "GAVIC421439380"
   }
  },
  {
   "type": "Feature",
   "geometry": {
    "type": "Point",
    "coordinates": [
     143.125557,
     -35.28962425
    ]
   },
   "properties": {
    "name": "163 WAITCHIE TANK ROAD POLISBET 3585",
    "locID": "LOC000096781779",
    "tech": "SATELLITE",
    "upgrade": "NULL_NA",
    "gnaf_pid": "GAVIC421995923"
   }
  },
  {
   "type": "Feature",
   "geometry": {
    "type": "Point",
    "coordinates": [
     143.1712347,
     -35.25807204
    ]
   },
   "properties": {
    "name": "3105 CHILLINGOLLAH ROAD POLISBET 3585",
    "locID": "LOC000083296697",
    "tech": "SATELLITE",
    "upgrade": "NULL_NA",
    "gnaf_pid": "GAVIC421995956"
   }
  },
  {
   "type": "Feature",
   "geometry": {
    "type": "Point",
    "coordinates": [
     143.10645856,
     -35.30065924
    ]
   },
   "properties": {
    "name": "1104 POLISBET ROAD POLISBET 3585",
    "locID": "ChIJwfbN0mRp22oRcOCotq_SUfo",
    "tech": "SATELLITE",
    "upgrade": "UNKNOWN",
    "gnaf_pid": "GAVIC422027070"
   }
  },
  {
   "type": "Feature",
   "geometry": {
    "type": "Point",
    "coordinates": [
     143.12556414,
     -35.28959041
    ]
   },
   "properties": {
    "name": "193 WAITCHIE TANK ROAD POLISBET 3585",
    "locID": "ChIJJ8bF0UNp22oR0YrC3jUdKXM",
    "tech": "SATELLITE",
    "upgrade": "UNKNOWN",
    "gnaf_pid": "GAVIC422200102"
   }
  }
 ]
}