{
 "type": "FeatureCollection",
 "generated": "2024-07-25T13:13:22.853655",
 "suburb": "POLISBET",
 "features": [
  {
   "type": "Feature",
   "geometry": {
    "type": "Point",
    "coordinates": [
     143.14788852,
     -35.30079179
    ]
   },
   "properties": {
    "name": "496 POLISBET ROAD POLISBET 3585",
    "locID": "LOC000102169316",
    "tech": "SATELLITE",
    "upgrade": "NULL_NA",
    "gnaf_pid": "GAVIC412132595",
    "tech_change_status": "Not Planned"
   }
  },
  {
   "type": "Feature",
   "geometry": {
    "type": "Point",
    "coordinates": [
     143.12732687,
     -35.29121993
    ]
   },
   "properties": {
    "name": "142 WAITCHIE TANK ROAD POLISBET 3585",
    "locID": "LOC000109746781",
    "tech": "SATELLITE",
    "upgrade": "NULL_NA",
    "gnaf_pid": "GAVIC421185213",
    "tech_change_status": "Not Planned"
   }
  },
  {
   "type": "Feature",
   "geometry": {
    "type": "Point",
    "coordinates": [
     143.19782299,
     -35.30069402
    ]
   },
   "properties": {
    "name": "268 POLISBET ROAD POLISBET 3585",
    "locID": "LOC000030246677",
    "tech": "SATELLITE",
    "upgrade": "NULL_NA",
    "gnaf_pid": "GAVIC421439380",
    "tech_change_status": "Not Planned"
   }
  },
  {
   "type": "Feature",
   "geometry": {
    "type": "Point",
    "coordinates": [
     143.125557,
     -35.28962425
    ]
   },
   "properties": {
    "name": "163 WAITCHIE TANK ROAD POLISBET 3585",
    "locID": "LOC000096781779",
    "tech": "SATELLITE",
    "upgrade": "NULL_NA",
    "gnaf_pid": "GAVIC421995923",
    "tech_change_status": "Not Planned"
   }
  },
  {
   "type": "Feature",
   "geometry": {
    "type": "Point",
    "coordinates": [
     143.1712347,
     -35.25807204
    ]
   },
   "properties": {
    "name": "3105 CHILLINGOLLAH ROAD POLISBET 3585",
    "locID": "LOC000083296697",
    "tech": "SATELLITE",
    "upgrade": "NULL_NA",
    "gnaf_pid": "GAVIC421995956",
    "tech_change_status": "Not Planned"
   }
  }
 ]
}