{
 "type": "FeatureCollection",
 "generated": "2024-08-17T10:52:27.516235",
 "suburb": "RICH AVON",
 "features": [
  {
   "type": "Feature",
   "geometry": {
    "type": "Point",
    "coordinates": [
     142.8902296,
     -36.42067659
    ]
   },
   "properties": {
    "name": "174 LAEN-COPE COPE ROAD RICH AVON 3480",
    "locID": "LOC000124957133",
    "tech": "WIRELESS",
    "upgrade": "NULL_NA",
    "gnaf_pid": "GAVIC422162565",
    "tech_change_status": "Not Planned",
    "program_type": "Fixed Wireless and Satellite Upgrade Program",
    "target_eligibility_quarter": "Dec 2024"
   }
  },
  {
   "type": "Feature",
   "geometry": {
    "type": "Point",
    "coordinates": [
     142.88540854,
     -36.45652891
    ]
   },
   "properties": {
    "name": "327 LAINGS ROAD RICH AVON 3480",
    "locID": "LOC000017881940",
    "tech": "WIRELESS",
    "upgrade": "NULL_NA",
    "gnaf_pid": "GAVIC422162608",
    "tech_change_status": "Not Planned",
    "program_type": "Fixed Wireless and Satellite Upgrade Program",
    "target_eligibility_quarter": "Dec 2024"
   }
  },
  {
   "type": "Feature",
   "geometry": {
    "type": "Point",
    "coordinates": [
     142.88132615,
     -36.44949711
    ]
   },
   "properties": {
    "name": "139 MIDDLE SETTLEMENT ROAD RICH AVON 3480",
    "locID": "LOC000036017525",
    "tech": "WIRELESS",
    "upgrade": "NULL_NA",
    "gnaf_pid": "GAVIC422171142",
    "tech_change_status": "Not Planned",
    "program_type": "Fixed Wireless and Satellite Upgrade Program",
    "target_eligibility_quarter": "Dec 2024"
   }
  },
  {
   "type": "Feature",
   "geometry": {
    "type": "Point",
    "coordinates": [
     142.89526546,
     -36.45057453
    ]
   },
   "properties": {
    "name": "265 MIDDLE SETTLEMENT ROAD RICH AVON 3480",
    "locID": "LOC000059966105",
    "tech": "WIRELESS",
    "upgrade": "NULL_NA",
    "gnaf_pid": "GAVIC422171143",
    "tech_change_status": "Not Planned",
    "program_type": "Fixed Wireless and Satellite Upgrade Program",
    "target_eligibility_quarter": "Dec 2024"
   }
  },
  {
   "type": "Feature",
   "geometry": {
    "type": "Point",
    "coordinates": [
     142.89771922,
     -36.45170922
    ]
   },
   "properties": {
    "name": "286 MIDDLE SETTLEMENT ROAD RICH AVON 3480",
    "locID": "LOC000089959354",
    "tech": "WIRELESS",
    "upgrade": "NULL_NA",
    "gnaf_pid": "GAVIC422171144",
    "tech_change_status": "Not Planned",
    "program_type": "Fixed Wireless and Satellite Upgrade Program",
    "target_eligibility_quarter": "Dec 2024"
   }
  },
  {
   "type": "Feature",
   "geometry": {
    "type": "Point",
    "coordinates": [
     142.86356663,
     -36.44652405
    ]
   },
   "properties": {
    "name": "377 SUMMERHAYES ROAD RICH AVON 3480",
    "locID": "LOC000073152567",
    "tech": "WIRELESS",
    "upgrade": "NULL_NA",
    "gnaf_pid": "GAVIC422193697",
    "tech_change_status": "Not Planned",
    "program_type": "Fixed Wireless and Satellite Upgrade Program",
    "target_eligibility_quarter": "Dec 2024"
   }
  }
 ]
}