{
 "type": "FeatureCollection",
 "generated": "2024-07-25T15:04:44.997454",
 "suburb": "RICHMOND PLAINS",
 "features": [
  {
   "type": "Feature",
   "geometry": {
    "type": "Point",
    "coordinates": [
     143.50939156,
     -36.38747474
    ]
   },
   "properties": {
    "name": "978 RICHMOND PLAINS-WEDDERBURN ROAD RICHMOND PLAINS 3518",
    "locID": "LOC000124794550",
    "tech": "SATELLITE",
    "upgrade": "NULL_NA",
    "gnaf_pid": "GAVIC412202733",
    "tech_change_status": "Not Planned"
   }
  },
  {
   "type": "Feature",
   "geometry": {
    "type": "Point",
    "coordinates": [
     143.52901331,
     -36.38506863
    ]
   },
   "properties": {
    "name": "269 TURNBULLS ROAD RICHMOND PLAINS 3518",
    "locID": "LOC000100401992",
    "tech": "SATELLITE",
    "upgrade": "NULL_NA",
    "gnaf_pid": "GAVIC412202735",
    "tech_change_status": "Not Planned"
   }
  },
  {
   "type": "Feature",
   "geometry": {
    "type": "Point",
    "coordinates": [
     143.49173828,
     -36.38348496
    ]
   },
   "properties": {
    "name": "430 NINE MILE-WOOSANG ROAD RICHMOND PLAINS 3518",
    "locID": "LOC000019527013",
    "tech": "SATELLITE",
    "upgrade": "NULL_NA",
    "gnaf_pid": "GAVIC422177370",
    "tech_change_status": "Not Planned"
   }
  },
  {
   "type": "Feature",
   "geometry": {
    "type": "Point",
    "coordinates": [
     143.44192191,
     -36.3913721
    ]
   },
   "properties": {
    "name": "222 PARRYS ROAD RICHMOND PLAINS 3518",
    "locID": "LOC000115782243",
    "tech": "SATELLITE",
    "upgrade": "NULL_NA",
    "gnaf_pid": "GAVIC424501450",
    "tech_change_status": "Not Planned"
   }
  }
 ]
}