{
 "type": "FeatureCollection",
 "generated": "2023-10-25T04:36:15.740960",
 "suburb": "ROSES GAP",
 "features": [
  {
   "type": "Feature",
   "geometry": {
    "type": "Point",
    "coordinates": [
     142.45175461,
     -36.96310108
    ]
   },
   "properties": {
    "name": "1008 ROSES GAP ROAD ROSES GAP 3385",
    "locID": "LOC000062179470",
    "tech": "SATELLITE",
    "upgrade": "NULL_NA",
    "gnaf_pid": "GAVIC422320706"
   }
  },
  {
   "type": "Feature",
   "geometry": {
    "type": "Point",
    "coordinates": [
     142.45111233,
     -36.96298721
    ]
   },
   "properties": {
    "name": "1014 ROSES GAP ROAD ROSES GAP 3385",
    "locID": "LOC000124591089",
    "tech": "SATELLITE",
    "upgrade": "NULL_NA",
    "gnaf_pid": "GAVIC422320707"
   }
  },
  {
   "type": "Feature",
   "geometry": {
    "type": "Point",
    "coordinates": [
     142.45067705,
     -36.96285868
    ]
   },
   "properties": {
    "name": "1020 ROSES GAP ROAD ROSES GAP 3385",
    "locID": "LOC000018403662",
    "tech": "SATELLITE",
    "upgrade": "NULL_NA",
    "gnaf_pid": "GAVIC422320708"
   }
  },
  {
   "type": "Feature",
   "geometry": {
    "type": "Point",
    "coordinates": [
     142.4498556,
     -36.96286181
    ]
   },
   "properties": {
    "name": "1028 ROSES GAP ROAD ROSES GAP 3385",
    "locID": "LOC000124591091",
    "tech": "SATELLITE",
    "upgrade": "NULL_NA",
    "gnaf_pid": "GAVIC422320709"
   }
  },
  {
   "type": "Feature",
   "geometry": {
    "type": "Point",
    "coordinates": [
     142.44826502,
     -36.96270439
    ]
   },
   "properties": {
    "name": "1040 ROSES GAP ROAD ROSES GAP 3385",
    "locID": "ChIJIV6ozXUWzmoRZx5aE4Zmj0o",
    "tech": "SATELLITE",
    "upgrade": "UNKNOWN",
    "gnaf_pid": "GAVIC422320710"
   }
  },
  {
   "type": "Feature",
   "geometry": {
    "type": "Point",
    "coordinates": [
     142.44931751,
     -36.96282983
    ]
   },
   "properties": {
    "name": "1030 ROSES GAP ROAD ROSES GAP 3385",
    "locID": "ChIJQdTaRXQWzmoRSib277yNulU",
    "tech": "SATELLITE",
    "upgrade": "UNKNOWN",
    "gnaf_pid": "GAVIC423155210"
   }
  },
  {
   "type": "Feature",
   "geometry": {
    "type": "Point",
    "coordinates": [
     142.45199107,
     -36.96324542
    ]
   },
   "properties": {
    "name": "1006 ROSES GAP ROAD ROSES GAP 3385",
    "locID": "LOC000038771894",
    "tech": "SATELLITE",
    "upgrade": "NULL_NA",
    "gnaf_pid": "GAVIC423806887"
   }
  }
 ]
}