{
 "type": "FeatureCollection",
 "generated": "2024-07-06T21:48:44.288597",
 "suburb": "ROSES GAP",
 "features": [
  {
   "type": "Feature",
   "geometry": {
    "type": "Point",
    "coordinates": [
     142.45175461,
     -36.96310108
    ]
   },
   "properties": {
    "name": "1008 ROSES GAP ROAD ROSES GAP 3385",
    "locID": "LOC000062179470",
    "tech": "SATELLITE",
    "upgrade": "NULL_NA",
    "gnaf_pid": "GAVIC422320706",
    "tech_change_status": "Not Planned"
   }
  },
  {
   "type": "Feature",
   "geometry": {
    "type": "Point",
    "coordinates": [
     142.45111233,
     -36.96298721
    ]
   },
   "properties": {
    "name": "1014 ROSES GAP ROAD ROSES GAP 3385",
    "locID": "LOC000124591089",
    "tech": "SATELLITE",
    "upgrade": "NULL_NA",
    "gnaf_pid": "GAVIC422320707",
    "tech_change_status": "Not Planned"
   }
  },
  {
   "type": "Feature",
   "geometry": {
    "type": "Point",
    "coordinates": [
     142.45067705,
     -36.96285868
    ]
   },
   "properties": {
    "name": "1020 ROSES GAP ROAD ROSES GAP 3385",
    "locID": "LOC000018403662",
    "tech": "SATELLITE",
    "upgrade": "NULL_NA",
    "gnaf_pid": "GAVIC422320708",
    "tech_change_status": "Not Planned"
   }
  },
  {
   "type": "Feature",
   "geometry": {
    "type": "Point",
    "coordinates": [
     142.4498556,
     -36.96286181
    ]
   },
   "properties": {
    "name": "1028 ROSES GAP ROAD ROSES GAP 3385",
    "locID": "LOC000124591091",
    "tech": "SATELLITE",
    "upgrade": "NULL_NA",
    "gnaf_pid": "GAVIC422320709",
    "tech_change_status": "Not Planned"
   }
  },
  {
   "type": "Feature",
   "geometry": {
    "type": "Point",
    "coordinates": [
     142.45199107,
     -36.96324542
    ]
   },
   "properties": {
    "name": "1006 ROSES GAP ROAD ROSES GAP 3385",
    "locID": "LOC000038771894",
    "tech": "SATELLITE",
    "upgrade": "NULL_NA",
    "gnaf_pid": "GAVIC423806887",
    "tech_change_status": "Not Planned"
   }
  }
 ]
}