{
 "type": "FeatureCollection",
 "generated": "2023-10-25T04:50:31.396250",
 "suburb": "SANDHILL LAKE",
 "features": [
  {
   "type": "Feature",
   "geometry": {
    "type": "Point",
    "coordinates": [
     143.71222915,
     -35.7673195
    ]
   },
   "properties": {
    "name": "1772 KERANG-QUAMBATOOK ROAD SANDHILL LAKE 3579",
    "locID": "LOC000031915477",
    "tech": "SATELLITE",
    "upgrade": "NULL_NA",
    "gnaf_pid": "GAVIC412253832"
   }
  },
  {
   "type": "Feature",
   "geometry": {
    "type": "Point",
    "coordinates": [
     143.68754635,
     -35.77618453
    ]
   },
   "properties": {
    "name": "2016 KERANG-QUAMBATOOK ROAD SANDHILL LAKE 3579",
    "locID": "LOC000004321169",
    "tech": "SATELLITE",
    "upgrade": "NULL_NA",
    "gnaf_pid": "GAVIC422160811"
   }
  },
  {
   "type": "Feature",
   "geometry": {
    "type": "Point",
    "coordinates": [
     143.65603291,
     -35.71938544
    ]
   },
   "properties": {
    "name": "1410 LAKE CHARM-QUAMBATOOK ROAD SANDHILL LAKE 3579",
    "locID": "LOC000098258991",
    "tech": "SATELLITE",
    "upgrade": "NULL_NA",
    "gnaf_pid": "GAVIC422162646"
   }
  },
  {
   "type": "Feature",
   "geometry": {
    "type": "Point",
    "coordinates": [
     143.65809246,
     -35.71823586
    ]
   },
   "properties": {
    "name": "1433 LAKE CHARM-QUAMBATOOK ROAD SANDHILL LAKE 3579",
    "locID": "ChIJib_9He6522oRo4MlJXh92JI",
    "tech": "SATELLITE",
    "upgrade": "UNKNOWN",
    "gnaf_pid": "GAVIC422162647"
   }
  },
  {
   "type": "Feature",
   "geometry": {
    "type": "Point",
    "coordinates": [
     143.68763336,
     -35.7357342
    ]
   },
   "properties": {
    "name": "1085 LALBERT-KERANG ROAD SANDHILL LAKE 3579",
    "locID": "ChIJXYTBrnG322oRyLcK-hcD0jU",
    "tech": "SATELLITE",
    "upgrade": "UNKNOWN",
    "gnaf_pid": "GAVIC422162831"
   }
  },
  {
   "type": "Feature",
   "geometry": {
    "type": "Point",
    "coordinates": [
     143.6876024,
     -35.73461594
    ]
   },
   "properties": {
    "name": "1086 LALBERT-KERANG ROAD SANDHILL LAKE 3579",
    "locID": "LOC000102084516",
    "tech": "SATELLITE",
    "upgrade": "NULL_NA",
    "gnaf_pid": "GAVIC422162832"
   }
  },
  {
   "type": "Feature",
   "geometry": {
    "type": "Point",
    "coordinates": [
     143.66293975,
     -35.73287534
    ]
   },
   "properties": {
    "name": "1319 LALBERT-KERANG ROAD SANDHILL LAKE 3579",
    "locID": "LOC000075983176",
    "tech": "SATELLITE",
    "upgrade": "NULL_NA",
    "gnaf_pid": "GAVIC422162833"
   }
  },
  {
   "type": "Feature",
   "geometry": {
    "type": "Point",
    "coordinates": [
     143.73515698,
     -35.73635904
    ]
   },
   "properties": {
    "name": "657 LALBERT-KERANG ROAD SANDHILL LAKE 3579",
    "locID": "LOC000142438246",
    "tech": "SATELLITE",
    "upgrade": "NULL_NA",
    "gnaf_pid": "GAVIC422162834"
   }
  },
  {
   "type": "Feature",
   "geometry": {
    "type": "Point",
    "coordinates": [
     143.70195033,
     -35.76405135
    ]
   },
   "properties": {
    "name": "5 BRADY LANE SANDHILL LAKE 3579",
    "locID": "ChIJexyCAKe322oRYf3MKlWKO-E",
    "tech": "SATELLITE",
    "upgrade": "UNKNOWN",
    "gnaf_pid": "GAVIC423788028"
   }
  },
  {
   "type": "Feature",
   "geometry": {
    "type": "Point",
    "coordinates": [
     143.67624749,
     -35.73099417
    ]
   },
   "properties": {
    "name": "1200 LALBERT-KERANG ROAD SANDHILL LAKE 3579",
    "locID": "ChIJUxz062G322oRB6CmZjDC2JE",
    "tech": "SATELLITE",
    "upgrade": "UNKNOWN",
    "gnaf_pid": "GAVIC424882616"
   }
  }
 ]
}