{
 "type": "FeatureCollection",
 "generated": "2024-08-17T12:07:29.464137",
 "suburb": "SANDHILL LAKE",
 "features": [
  {
   "type": "Feature",
   "geometry": {
    "type": "Point",
    "coordinates": [
     143.71222915,
     -35.7673195
    ]
   },
   "properties": {
    "name": "1772 KERANG-QUAMBATOOK ROAD SANDHILL LAKE 3579",
    "locID": "LOC000031915477",
    "tech": "SATELLITE",
    "upgrade": "NULL_NA",
    "gnaf_pid": "GAVIC412253832",
    "tech_change_status": "Not Planned"
   }
  },
  {
   "type": "Feature",
   "geometry": {
    "type": "Point",
    "coordinates": [
     143.68754635,
     -35.77618453
    ]
   },
   "properties": {
    "name": "2016 KERANG-QUAMBATOOK ROAD SANDHILL LAKE 3579",
    "locID": "LOC000004321169",
    "tech": "SATELLITE",
    "upgrade": "NULL_NA",
    "gnaf_pid": "GAVIC422160811",
    "tech_change_status": "Not Planned"
   }
  },
  {
   "type": "Feature",
   "geometry": {
    "type": "Point",
    "coordinates": [
     143.65603291,
     -35.71938544
    ]
   },
   "properties": {
    "name": "1410 LAKE CHARM-QUAMBATOOK ROAD SANDHILL LAKE 3579",
    "locID": "LOC000098258991",
    "tech": "SATELLITE",
    "upgrade": "NULL_NA",
    "gnaf_pid": "GAVIC422162646",
    "tech_change_status": "Not Planned"
   }
  },
  {
   "type": "Feature",
   "geometry": {
    "type": "Point",
    "coordinates": [
     143.6876024,
     -35.73461594
    ]
   },
   "properties": {
    "name": "1086 LALBERT-KERANG ROAD SANDHILL LAKE 3579",
    "locID": "LOC000102084516",
    "tech": "SATELLITE",
    "upgrade": "NULL_NA",
    "gnaf_pid": "GAVIC422162832",
    "tech_change_status": "Not Planned"
   }
  },
  {
   "type": "Feature",
   "geometry": {
    "type": "Point",
    "coordinates": [
     143.66293975,
     -35.73287534
    ]
   },
   "properties": {
    "name": "1319 LALBERT-KERANG ROAD SANDHILL LAKE 3579",
    "locID": "LOC000075983176",
    "tech": "SATELLITE",
    "upgrade": "NULL_NA",
    "gnaf_pid": "GAVIC422162833",
    "tech_change_status": "Not Planned"
   }
  },
  {
   "type": "Feature",
   "geometry": {
    "type": "Point",
    "coordinates": [
     143.73515698,
     -35.73635904
    ]
   },
   "properties": {
    "name": "657 LALBERT-KERANG ROAD SANDHILL LAKE 3579",
    "locID": "LOC000142438246",
    "tech": "SATELLITE",
    "upgrade": "NULL_NA",
    "gnaf_pid": "GAVIC422162834",
    "tech_change_status": "Not Planned"
   }
  }
 ]
}