{
 "type": "FeatureCollection",
 "generated": "2024-09-24T04:34:28.693883",
 "suburb": "SHAYS FLAT",
 "features": [
  {
   "type": "Feature",
   "geometry": {
    "type": "Point",
    "coordinates": [
     143.10164356,
     -37.05572761
    ]
   },
   "properties": {
    "name": "19 SHAYS FLAT-MALAKOFF ROAD SHAYS FLAT 3377",
    "locID": "LOC100079012585",
    "tech": "NULL",
    "upgrade": "NULL_NA",
    "gnaf_pid": "GAVIC419969577",
    "tech_change_status": "Not Planned"
   }
  },
  {
   "type": "Feature",
   "geometry": {
    "type": "Point",
    "coordinates": [
     143.102927,
     -37.048918
    ]
   },
   "properties": {
    "name": "1785 ARARAT-ST ARNAUD ROAD SHAYS FLAT 3377",
    "locID": "LOC000047384558",
    "tech": "NULL",
    "upgrade": "NULL_NA",
    "gnaf_pid": "GAVIC419969585",
    "tech_change_status": "Not Planned"
   }
  },
  {
   "type": "Feature",
   "geometry": {
    "type": "Point",
    "coordinates": [
     143.1028289,
     -37.04991393
    ]
   },
   "properties": {
    "name": "1777 ARARAT-ST ARNAUD ROAD SHAYS FLAT 3377",
    "locID": "LOC000086534438",
    "tech": "NULL",
    "upgrade": "NULL_NA",
    "gnaf_pid": "GAVIC420271281",
    "tech_change_status": "Not Planned"
   }
  },
  {
   "type": "Feature",
   "geometry": {
    "type": "Point",
    "coordinates": [
     143.09874628,
     -37.07778148
    ]
   },
   "properties": {
    "name": "1447 ARARAT-ST ARNAUD ROAD SHAYS FLAT 3377",
    "locID": "LOC000060821893",
    "tech": "NULL",
    "upgrade": "NULL_NA",
    "gnaf_pid": "GAVIC422123844",
    "tech_change_status": "Not Planned"
   }
  },
  {
   "type": "Feature",
   "geometry": {
    "type": "Point",
    "coordinates": [
     143.09485571,
     -37.06110271
    ]
   },
   "properties": {
    "name": "1639 ARARAT-ST ARNAUD ROAD SHAYS FLAT 3377",
    "locID": "LOC000107543705",
    "tech": "SATELLITE",
    "upgrade": "NULL_NA",
    "gnaf_pid": "GAVIC422123845",
    "tech_change_status": "Not Planned"
   }
  },
  {
   "type": "Feature",
   "geometry": {
    "type": "Point",
    "coordinates": [
     143.0992915,
     -37.05455145
    ]
   },
   "properties": {
    "name": "1721 ARARAT-ST ARNAUD ROAD SHAYS FLAT 3377",
    "locID": "LOC000083179775",
    "tech": "NULL",
    "upgrade": "NULL_NA",
    "gnaf_pid": "GAVIC422123846",
    "tech_change_status": "Not Planned"
   }
  },
  {
   "type": "Feature",
   "geometry": {
    "type": "Point",
    "coordinates": [
     143.09981992,
     -37.05382671
    ]
   },
   "properties": {
    "name": "1731 ARARAT-ST ARNAUD ROAD SHAYS FLAT 3377",
    "locID": "LOC000115787670",
    "tech": "NULL",
    "upgrade": "NULL_NA",
    "gnaf_pid": "GAVIC422123847",
    "tech_change_status": "Not Planned"
   }
  }
 ]
}