{
 "type": "FeatureCollection",
 "generated": "2023-10-25T05:55:22.258755",
 "suburb": "SHAYS FLAT",
 "features": [
  {
   "type": "Feature",
   "geometry": {
    "type": "Point",
    "coordinates": [
     143.10164356,
     -37.05572761
    ]
   },
   "properties": {
    "name": "19 SHAYS FLAT-MALAKOFF ROAD SHAYS FLAT 3377",
    "locID": "LOC100079012585",
    "tech": "SATELLITE",
    "upgrade": "NULL_NA",
    "gnaf_pid": "GAVIC419969577"
   }
  },
  {
   "type": "Feature",
   "geometry": {
    "type": "Point",
    "coordinates": [
     143.102927,
     -37.048918
    ]
   },
   "properties": {
    "name": "1785 ARARAT-ST ARNAUD ROAD SHAYS FLAT 3377",
    "locID": "LOC000047384558",
    "tech": "SATELLITE",
    "upgrade": "NULL_NA",
    "gnaf_pid": "GAVIC419969585"
   }
  },
  {
   "type": "Feature",
   "geometry": {
    "type": "Point",
    "coordinates": [
     143.1028289,
     -37.04991393
    ]
   },
   "properties": {
    "name": "1777 ARARAT-ST ARNAUD ROAD SHAYS FLAT 3377",
    "locID": "LOC000086534438",
    "tech": "SATELLITE",
    "upgrade": "NULL_NA",
    "gnaf_pid": "GAVIC420271281"
   }
  },
  {
   "type": "Feature",
   "geometry": {
    "type": "Point",
    "coordinates": [
     143.09874628,
     -37.07778148
    ]
   },
   "properties": {
    "name": "1447 ARARAT-ST ARNAUD ROAD SHAYS FLAT 3377",
    "locID": "LOC000060821893",
    "tech": "SATELLITE",
    "upgrade": "NULL_NA",
    "gnaf_pid": "GAVIC422123844"
   }
  },
  {
   "type": "Feature",
   "geometry": {
    "type": "Point",
    "coordinates": [
     143.09485571,
     -37.06110271
    ]
   },
   "properties": {
    "name": "1639 ARARAT-ST ARNAUD ROAD SHAYS FLAT 3377",
    "locID": "LOC000107543705",
    "tech": "SATELLITE",
    "upgrade": "NULL_NA",
    "gnaf_pid": "GAVIC422123845"
   }
  },
  {
   "type": "Feature",
   "geometry": {
    "type": "Point",
    "coordinates": [
     143.0992915,
     -37.05455145
    ]
   },
   "properties": {
    "name": "1721 ARARAT-ST ARNAUD ROAD SHAYS FLAT 3377",
    "locID": "LOC000083179775",
    "tech": "SATELLITE",
    "upgrade": "NULL_NA",
    "gnaf_pid": "GAVIC422123846"
   }
  },
  {
   "type": "Feature",
   "geometry": {
    "type": "Point",
    "coordinates": [
     143.09981992,
     -37.05382671
    ]
   },
   "properties": {
    "name": "1731 ARARAT-ST ARNAUD ROAD SHAYS FLAT 3377",
    "locID": "LOC000115787670",
    "tech": "SATELLITE",
    "upgrade": "NULL_NA",
    "gnaf_pid": "GAVIC422123847"
   }
  },
  {
   "type": "Feature",
   "geometry": {
    "type": "Point",
    "coordinates": [
     143.10188921,
     -37.05607277
    ]
   },
   "properties": {
    "name": "20 SHAYS FLAT-MALAKOFF ROAD SHAYS FLAT 3377",
    "locID": "ChIJWyiiFK-50WoRLMVtWkDteKw",
    "tech": "SATELLITE",
    "upgrade": "UNKNOWN",
    "gnaf_pid": "GAVIC721024329"
   }
  },
  {
   "type": "Feature",
   "geometry": {
    "type": "Point",
    "coordinates": [
     143.09567684,
     -37.06120278
    ]
   },
   "properties": {
    "name": "1634 ARARAT-ST ARNAUD ROAD SHAYS FLAT 3377",
    "locID": "EjgxNjM0IEFyYXJhdC1zdCBBcm5hdWQgUmQsIFNoYXlzIEZsYXQgVklDIDMzNzcsIEF1c3RyYWxpYSIxEi8KFAoSCRU8U4gXudFqEX_UrMWFbQucEOIMKhQKEgnBfcCBNLnRahHhOf_94OATEw",
    "tech": "SATELLITE",
    "upgrade": "UNKNOWN",
    "gnaf_pid": "GAVIC721099403"
   }
  },
  {
   "type": "Feature",
   "geometry": {
    "type": "Point",
    "coordinates": [
     143.06986147,
     -37.07174145
    ]
   },
   "properties": {
    "name": "142 SHAYS FLAT ROAD SHAYS FLAT 3377",
    "locID": "ChIJFVPDBuu40WoR68IKQU2l15A",
    "tech": "SATELLITE",
    "upgrade": "UNKNOWN",
    "gnaf_pid": "GAVIC721292571"
   }
  }
 ]
}