{
 "type": "FeatureCollection",
 "generated": "2023-10-25T06:27:48.397889",
 "suburb": "SKINNERS FLAT",
 "features": [
  {
   "type": "Feature",
   "geometry": {
    "type": "Point",
    "coordinates": [
     143.58962819,
     -36.35618693
    ]
   },
   "properties": {
    "name": "118 GIBSON ROAD SKINNERS FLAT 3518",
    "locID": "LOC000100288799",
    "tech": "SATELLITE",
    "upgrade": "NULL_NA",
    "gnaf_pid": "GAVIC420985136"
   }
  },
  {
   "type": "Feature",
   "geometry": {
    "type": "Point",
    "coordinates": [
     143.6030176,
     -36.35237585
    ]
   },
   "properties": {
    "name": "289 WEDDERBURN-WYCHITELLA ROAD SKINNERS FLAT 3518",
    "locID": "LOC000054035503",
    "tech": "WIRELESS",
    "upgrade": "NULL_NA",
    "gnaf_pid": "GAVIC422025491"
   }
  },
  {
   "type": "Feature",
   "geometry": {
    "type": "Point",
    "coordinates": [
     143.60156624,
     -36.36803118
    ]
   },
   "properties": {
    "name": "123 WEDDERBURN-WYCHITELLA ROAD SKINNERS FLAT 3518",
    "locID": "LOC000033899479",
    "tech": "WIRELESS",
    "upgrade": "NULL_NA",
    "gnaf_pid": "GAVIC422201985"
   }
  },
  {
   "type": "Feature",
   "geometry": {
    "type": "Point",
    "coordinates": [
     143.60184499,
     -36.36392343
    ]
   },
   "properties": {
    "name": "169 WEDDERBURN-WYCHITELLA ROAD SKINNERS FLAT 3518",
    "locID": "LOC000067069410",
    "tech": "WIRELESS",
    "upgrade": "NULL_NA",
    "gnaf_pid": "GAVIC422201986"
   }
  },
  {
   "type": "Feature",
   "geometry": {
    "type": "Point",
    "coordinates": [
     143.60229674,
     -36.34420329
    ]
   },
   "properties": {
    "name": "381 WEDDERBURN-WYCHITELLA ROAD SKINNERS FLAT 3518",
    "locID": "LOC000007799900",
    "tech": "SATELLITE",
    "upgrade": "NULL_NA",
    "gnaf_pid": "GAVIC422201987"
   }
  },
  {
   "type": "Feature",
   "geometry": {
    "type": "Point",
    "coordinates": [
     143.59816257,
     -36.35773985
    ]
   },
   "properties": {
    "name": "41 GIBSON ROAD SKINNERS FLAT 3518",
    "locID": "LOC000084447667",
    "tech": "WIRELESS",
    "upgrade": "NULL_NA",
    "gnaf_pid": "GAVIC423071034"
   }
  },
  {
   "type": "Feature",
   "geometry": {
    "type": "Point",
    "coordinates": [
     143.59628316,
     -36.35695793
    ]
   },
   "properties": {
    "name": "56 GIBSON ROAD SKINNERS FLAT 3518",
    "locID": "LOC000114302658",
    "tech": "WIRELESS",
    "upgrade": "NULL_NA",
    "gnaf_pid": "GAVIC423071035"
   }
  },
  {
   "type": "Feature",
   "geometry": {
    "type": "Point",
    "coordinates": [
     143.59370423,
     -36.35723398
    ]
   },
   "properties": {
    "name": "79 GIBSON ROAD SKINNERS FLAT 3518",
    "locID": "ChIJbdOW2O5w2moRMGvlU8hieEw",
    "tech": "SATELLITE",
    "upgrade": "UNKNOWN",
    "gnaf_pid": "GAVIC423071036"
   }
  },
  {
   "type": "Feature",
   "geometry": {
    "type": "Point",
    "coordinates": [
     143.59220799,
     -36.36887136
    ]
   },
   "properties": {
    "name": "39 SMITH ROAD SKINNERS FLAT 3518",
    "locID": "LOC000057816755",
    "tech": "WIRELESS",
    "upgrade": "NULL_NA",
    "gnaf_pid": "GAVIC423156319"
   }
  },
  {
   "type": "Feature",
   "geometry": {
    "type": "Point",
    "coordinates": [
     143.59248822,
     -36.36878404
    ]
   },
   "properties": {
    "name": "41 SMITH ROAD SKINNERS FLAT 3518",
    "locID": "LOC000046661792",
    "tech": "WIRELESS",
    "upgrade": "NULL_NA",
    "gnaf_pid": "GAVIC423156320"
   }
  },
  {
   "type": "Feature",
   "geometry": {
    "type": "Point",
    "coordinates": [
     143.58153835,
     -36.36289104
    ]
   },
   "properties": {
    "name": "155 MOUNT KERANG ROAD SKINNERS FLAT 3518",
    "locID": "ChIJjZKZ-7tw2moR4SLAOaGt-2k",
    "tech": "WIRELESS",
    "upgrade": "UNKNOWN",
    "gnaf_pid": "GAVIC424085600"
   }
  },
  {
   "type": "Feature",
   "geometry": {
    "type": "Point",
    "coordinates": [
     143.58968228,
     -36.37318298
    ]
   },
   "properties": {
    "name": "15 MOUNT KERANG ROAD SKINNERS FLAT 3518",
    "locID": "LOC100079491309",
    "tech": "SATELLITE",
    "upgrade": "NULL_NA",
    "gnaf_pid": "GAVIC424085601"
   }
  },
  {
   "type": "Feature",
   "geometry": {
    "type": "Point",
    "coordinates": [
     143.58182239,
     -36.36331261
    ]
   },
   "properties": {
    "name": "153 MOUNT KERANG ROAD SKINNERS FLAT 3518",
    "locID": "ChIJ1YtTKLlw2moRtpFsVqFCZq0",
    "tech": "WIRELESS",
    "upgrade": "UNKNOWN",
    "gnaf_pid": "GAVIC424555100"
   }
  },
  {
   "type": "Feature",
   "geometry": {
    "type": "Point",
    "coordinates": [
     143.60199925,
     -36.36219866
    ]
   },
   "properties": {
    "name": "187 WEDDERBURN-WYCHITELLA ROAD SKINNERS FLAT 3518",
    "locID": "ChIJUyk46uZw2moR1G0AsRL7XYY",
    "tech": "WIRELESS",
    "upgrade": "UNKNOWN",
    "gnaf_pid": "GAVIC721169589"
   }
  }
 ]
}