{
 "type": "FeatureCollection",
 "generated": "2023-10-25T08:25:53.448507",
 "suburb": "SYLVATERRE",
 "features": [
  {
   "type": "Feature",
   "geometry": {
    "type": "Point",
    "coordinates": [
     144.21699468,
     -36.05925955
    ]
   },
   "properties": {
    "name": "522 RITCHIES ROAD SYLVATERRE 3575",
    "locID": "LOC000014407894",
    "tech": "SATELLITE",
    "upgrade": "NULL_NA",
    "gnaf_pid": "GAVIC421989070"
   }
  },
  {
   "type": "Feature",
   "geometry": {
    "type": "Point",
    "coordinates": [
     144.23131372,
     -36.07635372
    ]
   },
   "properties": {
    "name": "223 JUNGABURRA ROAD SYLVATERRE 3575",
    "locID": "LOC000086015361",
    "tech": "SATELLITE",
    "upgrade": "NULL_NA",
    "gnaf_pid": "GAVIC422027528"
   }
  },
  {
   "type": "Feature",
   "geometry": {
    "type": "Point",
    "coordinates": [
     144.23653091,
     -36.08737565
    ]
   },
   "properties": {
    "name": "1126 SYLVATERRE-TIMMS LAKE ROAD SYLVATERRE 3575",
    "locID": "LOC000095305851",
    "tech": "WIRELESS",
    "upgrade": "NULL_NA",
    "gnaf_pid": "GAVIC423115621"
   }
  },
  {
   "type": "Feature",
   "geometry": {
    "type": "Point",
    "coordinates": [
     144.23613882,
     -36.08408598
    ]
   },
   "properties": {
    "name": "1162 SYLVATERRE-TIMMS LAKE ROAD SYLVATERRE 3575",
    "locID": "LOC000069587065",
    "tech": "SATELLITE",
    "upgrade": "NULL_NA",
    "gnaf_pid": "GAVIC423115622"
   }
  },
  {
   "type": "Feature",
   "geometry": {
    "type": "Point",
    "coordinates": [
     144.23622518,
     -36.0784608
    ]
   },
   "properties": {
    "name": "1224 SYLVATERRE-TIMMS LAKE ROAD SYLVATERRE 3575",
    "locID": "LOC000094932262",
    "tech": "SATELLITE",
    "upgrade": "NULL_NA",
    "gnaf_pid": "GAVIC423115623"
   }
  },
  {
   "type": "Feature",
   "geometry": {
    "type": "Point",
    "coordinates": [
     144.2370639,
     -36.06698705
    ]
   },
   "properties": {
    "name": "1354 SYLVATERRE-TIMMS LAKE ROAD SYLVATERRE 3575",
    "locID": "LOC000061833216",
    "tech": "SATELLITE",
    "upgrade": "NULL_NA",
    "gnaf_pid": "GAVIC423115624"
   }
  },
  {
   "type": "Feature",
   "geometry": {
    "type": "Point",
    "coordinates": [
     144.23686442,
     -36.06554687
    ]
   },
   "properties": {
    "name": "1371 SYLVATERRE-TIMMS LAKE ROAD SYLVATERRE 3575",
    "locID": "LOC000023474828",
    "tech": "SATELLITE",
    "upgrade": "NULL_NA",
    "gnaf_pid": "GAVIC423115625"
   }
  }
 ]
}