{
 "type": "FeatureCollection",
 "generated": "2024-07-07T01:56:46.433247",
 "suburb": "TANWOOD",
 "features": [
  {
   "type": "Feature",
   "geometry": {
    "type": "Point",
    "coordinates": [
     143.40318076,
     -37.00397644
    ]
   },
   "properties": {
    "name": "145 WILLIAMS ROAD TANWOOD 3478",
    "locID": "LOC000011134967",
    "tech": "SATELLITE",
    "upgrade": "NULL_NA",
    "gnaf_pid": "GAVIC421270914",
    "tech_change_status": "Not Planned"
   }
  },
  {
   "type": "Feature",
   "geometry": {
    "type": "Point",
    "coordinates": [
     143.38638125,
     -37.00036341
    ]
   },
   "properties": {
    "name": "1312 SUNRAYSIA HIGHWAY TANWOOD 3478",
    "locID": "LOC000092816785",
    "tech": "SATELLITE",
    "upgrade": "NULL_NA",
    "gnaf_pid": "GAVIC421459220",
    "tech_change_status": "Not Planned"
   }
  },
  {
   "type": "Feature",
   "geometry": {
    "type": "Point",
    "coordinates": [
     143.39407469,
     -37.00957893
    ]
   },
   "properties": {
    "name": "1182 SUNRAYSIA HIGHWAY TANWOOD 3478",
    "locID": "LOC000007743579",
    "tech": "SATELLITE",
    "upgrade": "NULL_NA",
    "gnaf_pid": "GAVIC421574707",
    "tech_change_status": "Not Planned"
   }
  },
  {
   "type": "Feature",
   "geometry": {
    "type": "Point",
    "coordinates": [
     143.40111194,
     -37.00372722
    ]
   },
   "properties": {
    "name": "125 WILLIAMS ROAD TANWOOD 3478",
    "locID": "LOC000124784572",
    "tech": "SATELLITE",
    "upgrade": "NULL_NA",
    "gnaf_pid": "GAVIC421857241",
    "tech_change_status": "Not Planned"
   }
  },
  {
   "type": "Feature",
   "geometry": {
    "type": "Point",
    "coordinates": [
     143.38084929,
     -37.00243854
    ]
   },
   "properties": {
    "name": "6609 STAWELL-AVOCA ROAD TANWOOD 3478",
    "locID": "LOC000094760754",
    "tech": "SATELLITE",
    "upgrade": "NULL_NA",
    "gnaf_pid": "GAVIC423164670",
    "tech_change_status": "Not Planned"
   }
  },
  {
   "type": "Feature",
   "geometry": {
    "type": "Point",
    "coordinates": [
     143.37558755,
     -37.00732208
    ]
   },
   "properties": {
    "name": "128 TANWOOD ROAD TANWOOD 3478",
    "locID": "LOC000021006483",
    "tech": "SATELLITE",
    "upgrade": "NULL_NA",
    "gnaf_pid": "GAVIC423164698",
    "tech_change_status": "Not Planned"
   }
  },
  {
   "type": "Feature",
   "geometry": {
    "type": "Point",
    "coordinates": [
     143.3743793,
     -37.0110356
    ]
   },
   "properties": {
    "name": "170 TANWOOD ROAD TANWOOD 3478",
    "locID": "LOC000104852006",
    "tech": "SATELLITE",
    "upgrade": "NULL_NA",
    "gnaf_pid": "GAVIC423164699",
    "tech_change_status": "Not Planned"
   }
  },
  {
   "type": "Feature",
   "geometry": {
    "type": "Point",
    "coordinates": [
     143.36548363,
     -37.02172373
    ]
   },
   "properties": {
    "name": "93 CASTLEMANS ROAD TANWOOD 3478",
    "locID": "LOC000066052193",
    "tech": "SATELLITE",
    "upgrade": "NULL_NA",
    "gnaf_pid": "GAVIC423846862",
    "tech_change_status": "Not Planned"
   }
  },
  {
   "type": "Feature",
   "geometry": {
    "type": "Point",
    "coordinates": [
     143.37390291,
     -37.01504557
    ]
   },
   "properties": {
    "name": "323 PUNTON ROAD TANWOOD 3478",
    "locID": "LOC000002006893",
    "tech": "SATELLITE",
    "upgrade": "NULL_NA",
    "gnaf_pid": "GAVIC424244937",
    "tech_change_status": "Not Planned"
   }
  },
  {
   "type": "Feature",
   "geometry": {
    "type": "Point",
    "coordinates": [
     143.37019091,
     -37.01461041
    ]
   },
   "properties": {
    "name": "357 PUNTON ROAD TANWOOD 3478",
    "locID": "LOC000056256422",
    "tech": "SATELLITE",
    "upgrade": "NULL_NA",
    "gnaf_pid": "GAVIC424244938",
    "tech_change_status": "Not Planned"
   }
  },
  {
   "type": "Feature",
   "geometry": {
    "type": "Point",
    "coordinates": [
     143.36093581,
     -37.0135537
    ]
   },
   "properties": {
    "name": "441 PUNTON ROAD TANWOOD 3478",
    "locID": "LOC000104570487",
    "tech": "SATELLITE",
    "upgrade": "NULL_NA",
    "gnaf_pid": "GAVIC424244939",
    "tech_change_status": "Not Planned"
   }
  },
  {
   "type": "Feature",
   "geometry": {
    "type": "Point",
    "coordinates": [
     143.36009439,
     -37.01341963
    ]
   },
   "properties": {
    "name": "457 PUNTON ROAD TANWOOD 3478",
    "locID": "LOC000081117644",
    "tech": "SATELLITE",
    "upgrade": "NULL_NA",
    "gnaf_pid": "GAVIC424244940",
    "tech_change_status": "Not Planned"
   }
  },
  {
   "type": "Feature",
   "geometry": {
    "type": "Point",
    "coordinates": [
     143.37824804,
     -37.00527855
    ]
   },
   "properties": {
    "name": "93 TANWOOD ROAD TANWOOD 3478",
    "locID": "LOC000066052193",
    "tech": "SATELLITE",
    "upgrade": "NULL_NA",
    "gnaf_pid": "GAVIC424284617",
    "tech_change_status": "Not Planned"
   }
  }
 ]
}