{
 "type": "FeatureCollection",
 "generated": "2023-10-25T09:24:54.635804",
 "suburb": "THALLOO",
 "features": [
  {
   "type": "Feature",
   "geometry": {
    "type": "Point",
    "coordinates": [
     146.30399003,
     -38.08458871
    ]
   },
   "properties": {
    "name": "104 THALLOO ROAD THALLOO 3825",
    "locID": "LOC000035979457",
    "tech": "SATELLITE",
    "upgrade": "NULL_NA",
    "gnaf_pid": "GAVIC423800492"
   }
  },
  {
   "type": "Feature",
   "geometry": {
    "type": "Point",
    "coordinates": [
     146.30379354,
     -38.08486695
    ]
   },
   "properties": {
    "name": "105 THALLOO ROAD THALLOO 3825",
    "locID": "LOC000084877653",
    "tech": "SATELLITE",
    "upgrade": "NULL_NA",
    "gnaf_pid": "GAVIC423800493"
   }
  },
  {
   "type": "Feature",
   "geometry": {
    "type": "Point",
    "coordinates": [
     146.30372795,
     -38.08456915
    ]
   },
   "properties": {
    "name": "106 THALLOO ROAD THALLOO 3825",
    "locID": "LOC000178365759",
    "tech": "SATELLITE",
    "upgrade": "NULL_NA",
    "gnaf_pid": "GAVIC423800494"
   }
  },
  {
   "type": "Feature",
   "geometry": {
    "type": "Point",
    "coordinates": [
     146.3095548,
     -38.09024836
    ]
   },
   "properties": {
    "name": "12 THALLOO ROAD THALLOO 3825",
    "locID": "LOC000108813449",
    "tech": "WIRELESS",
    "upgrade": "NULL_NA",
    "gnaf_pid": "GAVIC423800495"
   }
  },
  {
   "type": "Feature",
   "geometry": {
    "type": "Point",
    "coordinates": [
     146.30877755,
     -38.08951023
    ]
   },
   "properties": {
    "name": "25 THALLOO ROAD THALLOO 3825",
    "locID": "ChIJWzh4SzMEKWsRgHquQFY5guU",
    "tech": "SATELLITE",
    "upgrade": "UNKNOWN",
    "gnaf_pid": "GAVIC423800496"
   }
  },
  {
   "type": "Feature",
   "geometry": {
    "type": "Point",
    "coordinates": [
     146.30901184,
     -38.08905695
    ]
   },
   "properties": {
    "name": "34 THALLOO ROAD THALLOO 3825",
    "locID": "LOC000070431204",
    "tech": "SATELLITE",
    "upgrade": "NULL_NA",
    "gnaf_pid": "GAVIC423800497"
   }
  },
  {
   "type": "Feature",
   "geometry": {
    "type": "Point",
    "coordinates": [
     146.30840921,
     -38.08876059
    ]
   },
   "properties": {
    "name": "35 THALLOO ROAD THALLOO 3825",
    "locID": "LOC000092116150",
    "tech": "WIRELESS",
    "upgrade": "NULL_NA",
    "gnaf_pid": "GAVIC423800498"
   }
  },
  {
   "type": "Feature",
   "geometry": {
    "type": "Point",
    "coordinates": [
     146.30828436,
     -38.08748908
    ]
   },
   "properties": {
    "name": "50 THALLOO ROAD THALLOO 3825",
    "locID": "LOC000172935331",
    "tech": "WIRELESS",
    "upgrade": "NULL_NA",
    "gnaf_pid": "GAVIC423800499"
   }
  },
  {
   "type": "Feature",
   "geometry": {
    "type": "Point",
    "coordinates": [
     146.30746669,
     -38.08713278
    ]
   },
   "properties": {
    "name": "55 THALLOO ROAD THALLOO 3825",
    "locID": "LOC000056790878",
    "tech": "WIRELESS",
    "upgrade": "NULL_NA",
    "gnaf_pid": "GAVIC423800500"
   }
  },
  {
   "type": "Feature",
   "geometry": {
    "type": "Point",
    "coordinates": [
     146.30712914,
     -38.08544544
    ]
   },
   "properties": {
    "name": "74 THALLOO ROAD THALLOO 3825",
    "locID": "LOC000007603095",
    "tech": "SATELLITE",
    "upgrade": "NULL_NA",
    "gnaf_pid": "GAVIC423800501"
   }
  },
  {
   "type": "Feature",
   "geometry": {
    "type": "Point",
    "coordinates": [
     146.30845519,
     -38.09114019
    ]
   },
   "properties": {
    "name": "7 THALLOO ROAD THALLOO 3825",
    "locID": "LOC000007692480",
    "tech": "WIRELESS",
    "upgrade": "NULL_NA",
    "gnaf_pid": "GAVIC423800502"
   }
  },
  {
   "type": "Feature",
   "geometry": {
    "type": "Point",
    "coordinates": [
     146.30484178,
     -38.08495426
    ]
   },
   "properties": {
    "name": "97 THALLOO ROAD THALLOO 3825",
    "locID": "LOC000027852098",
    "tech": "WIRELESS",
    "upgrade": "NULL_NA",
    "gnaf_pid": "GAVIC423800503"
   }
  },
  {
   "type": "Feature",
   "geometry": {
    "type": "Point",
    "coordinates": [
     146.31365365,
     -38.09010715
    ]
   },
   "properties": {
    "name": "1145 MOE-RAWSON ROAD THALLOO 3825",
    "locID": "LOC000048150394",
    "tech": "SATELLITE",
    "upgrade": "NULL_NA",
    "gnaf_pid": "GAVIC424066263"
   }
  },
  {
   "type": "Feature",
   "geometry": {
    "type": "Point",
    "coordinates": [
     146.31432971,
     -38.0897596
    ]
   },
   "properties": {
    "name": "1151 MOE-RAWSON ROAD THALLOO 3825",
    "locID": "LOC000088562059",
    "tech": "WIRELESS",
    "upgrade": "NULL_NA",
    "gnaf_pid": "GAVIC424066264"
   }
  }
 ]
}