{
 "type": "FeatureCollection",
 "generated": "2024-09-24T07:34:48.772108",
 "suburb": "THALIA",
 "features": [
  {
   "type": "Feature",
   "geometry": {
    "type": "Point",
    "coordinates": [
     143.13277835,
     -36.09300623
    ]
   },
   "properties": {
    "name": "247 DOWNES ROAD THALIA 3527",
    "locID": "LOC000067703809",
    "tech": "WIRELESS",
    "upgrade": "NULL_NA",
    "gnaf_pid": "GAVIC422025299",
    "tech_change_status": "Not Planned",
    "program_type": "Fixed Wireless and Satellite Upgrade Program",
    "target_eligibility_quarter": "Dec 2024"
   }
  },
  {
   "type": "Feature",
   "geometry": {
    "type": "Point",
    "coordinates": [
     143.09941533,
     -36.10510646
    ]
   },
   "properties": {
    "name": "343 CHARLTON-THALIA ROAD THALIA 3527",
    "locID": "LOC000100104341",
    "tech": "WIRELESS",
    "upgrade": "NULL_NA",
    "gnaf_pid": "GAVIC422135887",
    "tech_change_status": "Not Planned",
    "program_type": "Fixed Wireless and Satellite Upgrade Program",
    "target_eligibility_quarter": "Dec 2024"
   }
  },
  {
   "type": "Feature",
   "geometry": {
    "type": "Point",
    "coordinates": [
     143.12259164,
     -36.13127887
    ]
   },
   "properties": {
    "name": "571 NICHOLLS ROAD THALIA 3527",
    "locID": "LOC000026638537",
    "tech": "WIRELESS",
    "upgrade": "NULL_NA",
    "gnaf_pid": "GAVIC423796947",
    "tech_change_status": "Not Planned",
    "program_type": "Fixed Wireless and Satellite Upgrade Program",
    "target_eligibility_quarter": "Dec 2024"
   }
  },
  {
   "type": "Feature",
   "geometry": {
    "type": "Point",
    "coordinates": [
     143.08071655,
     -36.14293536
    ]
   },
   "properties": {
    "name": "230 CORACK-WYCHEPROOF ROAD THALIA 3527",
    "locID": "LOC000058012794",
    "tech": "NULL",
    "upgrade": "NULL_NA",
    "gnaf_pid": "GAVIC424061293",
    "tech_change_status": "Not Planned"
   }
  },
  {
   "type": "Feature",
   "geometry": {
    "type": "Point",
    "coordinates": [
     143.0876863,
     -36.14328616
    ]
   },
   "properties": {
    "name": "291 CORACK-WYCHEPROOF ROAD THALIA 3527",
    "locID": "LOC000142440856",
    "tech": "SATELLITE",
    "upgrade": "NULL_NA",
    "gnaf_pid": "GAVIC424061294",
    "tech_change_status": "Not Planned"
   }
  }
 ]
}