{
 "type": "FeatureCollection",
 "generated": "2024-09-05T16:23:11.703335",
 "suburb": "TIDAL RIVER",
 "features": [
  {
   "type": "Feature",
   "geometry": {
    "type": "Point",
    "coordinates": [
     146.31779314,
     -39.03303582
    ]
   },
   "properties": {
    "name": "14 WILSONS PROMONTORY ROAD TIDAL RIVER 3960",
    "locID": "LOC000055028157",
    "tech": "SATELLITE",
    "upgrade": "NULL_NA",
    "gnaf_pid": "GAVIC424092773",
    "tech_change_status": "Not Planned"
   }
  },
  {
   "type": "Feature",
   "geometry": {
    "type": "Point",
    "coordinates": [
     146.31779314,
     -39.03303582
    ]
   },
   "properties": {
    "name": "11 WILSONS PROMONTORY ROAD TIDAL RIVER 3960",
    "locID": "LOC000012051620",
    "tech": "SATELLITE",
    "upgrade": "NULL_NA",
    "gnaf_pid": "GAVIC424275016",
    "tech_change_status": "Not Planned"
   }
  },
  {
   "type": "Feature",
   "geometry": {
    "type": "Point",
    "coordinates": [
     146.31779314,
     -39.03303582
    ]
   },
   "properties": {
    "name": "15 WILSONS PROMONTORY ROAD TIDAL RIVER 3960",
    "locID": "LOC000079764299",
    "tech": "SATELLITE",
    "upgrade": "NULL_NA",
    "gnaf_pid": "GAVIC424275018",
    "tech_change_status": "Not Planned"
   }
  },
  {
   "type": "Feature",
   "geometry": {
    "type": "Point",
    "coordinates": [
     146.3266679,
     -39.03060909
    ]
   },
   "properties": {
    "name": "1 WILSONS PROMONTORY ROAD TIDAL RIVER 3960",
    "locID": "LOC000055028157",
    "tech": "SATELLITE",
    "upgrade": "NULL_NA",
    "gnaf_pid": "GAVIC424275019",
    "tech_change_status": "Not Planned"
   }
  },
  {
   "type": "Feature",
   "geometry": {
    "type": "Point",
    "coordinates": [
     146.3266679,
     -39.03060909
    ]
   },
   "properties": {
    "name": "3 WILSONS PROMONTORY ROAD TIDAL RIVER 3960",
    "locID": "LOC000070846303",
    "tech": "SATELLITE",
    "upgrade": "NULL_NA",
    "gnaf_pid": "GAVIC424275021",
    "tech_change_status": "Not Planned"
   }
  },
  {
   "type": "Feature",
   "geometry": {
    "type": "Point",
    "coordinates": [
     146.31779314,
     -39.03303582
    ]
   },
   "properties": {
    "name": "7 WILSONS PROMONTORY ROAD TIDAL RIVER 3960",
    "locID": "LOC000070846303",
    "tech": "SATELLITE",
    "upgrade": "NULL_NA",
    "gnaf_pid": "GAVIC721033774",
    "tech_change_status": "Not Planned"
   }
  }
 ]
}