{
 "type": "FeatureCollection",
 "generated": "2023-10-25T11:37:04.562477",
 "suburb": "TURRIFF EAST",
 "features": [
  {
   "type": "Feature",
   "geometry": {
    "type": "Point",
    "coordinates": [
     142.5802635,
     -35.45643069
    ]
   },
   "properties": {
    "name": "135 MOTTS ROAD TURRIFF EAST 3488",
    "locID": "LOC000124773608",
    "tech": "SATELLITE",
    "upgrade": "NULL_NA",
    "gnaf_pid": "GAVIC422025565"
   }
  },
  {
   "type": "Feature",
   "geometry": {
    "type": "Point",
    "coordinates": [
     142.54997904,
     -35.44297529
    ]
   },
   "properties": {
    "name": "59 NINDA-TURRIFF ROAD TURRIFF EAST 3488",
    "locID": "LOC000048880282",
    "tech": "SATELLITE",
    "upgrade": "NULL_NA",
    "gnaf_pid": "GAVIC422026345"
   }
  },
  {
   "type": "Feature",
   "geometry": {
    "type": "Point",
    "coordinates": [
     142.5655435,
     -35.44340554
    ]
   },
   "properties": {
    "name": "203 NINDA-TURRIFF ROAD TURRIFF EAST 3488",
    "locID": "LOC000066898898",
    "tech": "SATELLITE",
    "upgrade": "NULL_NA",
    "gnaf_pid": "GAVIC422177358"
   }
  },
  {
   "type": "Feature",
   "geometry": {
    "type": "Point",
    "coordinates": [
     142.54486125,
     -35.45997234
    ]
   },
   "properties": {
    "name": "175 CARTERS AND EMONSONS ROAD TURRIFF EAST 3488",
    "locID": "LOC000030236702",
    "tech": "SATELLITE",
    "upgrade": "NULL_NA",
    "gnaf_pid": "GAVIC423876628"
   }
  },
  {
   "type": "Feature",
   "geometry": {
    "type": "Point",
    "coordinates": [
     142.5452584,
     -35.42041785
    ]
   },
   "properties": {
    "name": "260 SHEARING SHED ROAD TURRIFF EAST 3488",
    "locID": "LOC000115794324",
    "tech": "SATELLITE",
    "upgrade": "NULL_NA",
    "gnaf_pid": "GAVIC424678471"
   }
  }
 ]
}