{
 "type": "FeatureCollection",
 "generated": "2024-07-25T22:22:07.522700",
 "suburb": "TYRRELL",
 "features": [
  {
   "type": "Feature",
   "geometry": {
    "type": "Point",
    "coordinates": [
     142.94805955,
     -35.44626844
    ]
   },
   "properties": {
    "name": "505 SCHODDES ROAD TYRRELL 3533",
    "locID": "LOC000095295523",
    "tech": "SATELLITE",
    "upgrade": "NULL_NA",
    "gnaf_pid": "GAVIC422025983",
    "tech_change_status": "Not Planned"
   }
  },
  {
   "type": "Feature",
   "geometry": {
    "type": "Point",
    "coordinates": [
     142.96229185,
     -35.45892036
    ]
   },
   "properties": {
    "name": "198 GORMANS ROAD TYRRELL 3533",
    "locID": "LOC000142814109",
    "tech": "SATELLITE",
    "upgrade": "NULL_NA",
    "gnaf_pid": "GAVIC422150781",
    "tech_change_status": "Not Planned"
   }
  },
  {
   "type": "Feature",
   "geometry": {
    "type": "Point",
    "coordinates": [
     142.9368273,
     -35.44618895
    ]
   },
   "properties": {
    "name": "405 SCHODDES ROAD TYRRELL 3533",
    "locID": "LOC000026875918",
    "tech": "SATELLITE",
    "upgrade": "NULL_NA",
    "gnaf_pid": "GAVIC423669148",
    "tech_change_status": "Not Planned"
   }
  },
  {
   "type": "Feature",
   "geometry": {
    "type": "Point",
    "coordinates": [
     143.01524571,
     -35.43910784
    ]
   },
   "properties": {
    "name": "354 DUSTY ROAD TYRRELL 3533",
    "locID": "LOC000124807383",
    "tech": "SATELLITE",
    "upgrade": "NULL_NA",
    "gnaf_pid": "GAVIC423824938",
    "tech_change_status": "Not Planned"
   }
  },
  {
   "type": "Feature",
   "geometry": {
    "type": "Point",
    "coordinates": [
     143.01452816,
     -35.42814647
    ]
   },
   "properties": {
    "name": "458 DUSTY ROAD TYRRELL 3533",
    "locID": "LOC000124807464",
    "tech": "SATELLITE",
    "upgrade": "NULL_NA",
    "gnaf_pid": "GAVIC424080429",
    "tech_change_status": "Not Planned"
   }
  },
  {
   "type": "Feature",
   "geometry": {
    "type": "Point",
    "coordinates": [
     142.96764088,
     -35.40226501
    ]
   },
   "properties": {
    "name": "55 LLOYDS ROAD TYRRELL 3533",
    "locID": "LOC000009291085",
    "tech": "SATELLITE",
    "upgrade": "NULL_NA",
    "gnaf_pid": "GAVIC424360354",
    "tech_change_status": "Not Planned"
   }
  }
 ]
}