{
 "type": "FeatureCollection",
 "generated": "2024-07-25T22:24:10.711687",
 "suburb": "ULUPNA",
 "features": [
  {
   "type": "Feature",
   "geometry": {
    "type": "Point",
    "coordinates": [
     145.45708574,
     -35.84649119
    ]
   },
   "properties": {
    "name": "311 ULUPNA BRIDGE ROAD ULUPNA 3641",
    "locID": "LOC000010645197",
    "tech": "SATELLITE",
    "upgrade": "NULL_NA",
    "gnaf_pid": "GAVIC422198768",
    "tech_change_status": "Not Planned"
   }
  },
  {
   "type": "Feature",
   "geometry": {
    "type": "Point",
    "coordinates": [
     145.45636901,
     -35.8426723
    ]
   },
   "properties": {
    "name": "353 ULUPNA BRIDGE ROAD ULUPNA 3641",
    "locID": "LOC000096746814",
    "tech": "SATELLITE",
    "upgrade": "NULL_NA",
    "gnaf_pid": "GAVIC422198769",
    "tech_change_status": "Not Planned"
   }
  },
  {
   "type": "Feature",
   "geometry": {
    "type": "Point",
    "coordinates": [
     145.45664745,
     -35.84201774
    ]
   },
   "properties": {
    "name": "359 ULUPNA BRIDGE ROAD ULUPNA 3641",
    "locID": "LOC000151816797",
    "tech": "SATELLITE",
    "upgrade": "NULL_NA",
    "gnaf_pid": "GAVIC422198770",
    "tech_change_status": "Not Planned"
   }
  },
  {
   "type": "Feature",
   "geometry": {
    "type": "Point",
    "coordinates": [
     145.45722691,
     -35.83439795
    ]
   },
   "properties": {
    "name": "445 ULUPNA BRIDGE ROAD ULUPNA 3641",
    "locID": "LOC000006922704",
    "tech": "SATELLITE",
    "upgrade": "NULL_NA",
    "gnaf_pid": "GAVIC422198771",
    "tech_change_status": "Not Planned"
   }
  },
  {
   "type": "Feature",
   "geometry": {
    "type": "Point",
    "coordinates": [
     145.45718034,
     -35.83108859
    ]
   },
   "properties": {
    "name": "481 ULUPNA BRIDGE ROAD ULUPNA 3641",
    "locID": "LOC000072115594",
    "tech": "SATELLITE",
    "upgrade": "NULL_NA",
    "gnaf_pid": "GAVIC422198772",
    "tech_change_status": "Not Planned"
   }
  },
  {
   "type": "Feature",
   "geometry": {
    "type": "Point",
    "coordinates": [
     145.46333895,
     -35.82685426
    ]
   },
   "properties": {
    "name": "557 ULUPNA BRIDGE ROAD ULUPNA 3641",
    "locID": "LOC000075856447",
    "tech": "SATELLITE",
    "upgrade": "NULL_NA",
    "gnaf_pid": "GAVIC422198774",
    "tech_change_status": "Not Planned"
   }
  },
  {
   "type": "Feature",
   "geometry": {
    "type": "Point",
    "coordinates": [
     145.4653004,
     -35.8250222
    ]
   },
   "properties": {
    "name": "580 ULUPNA BRIDGE ROAD ULUPNA 3641",
    "locID": "LOC000052092629",
    "tech": "SATELLITE",
    "upgrade": "NULL_NA",
    "gnaf_pid": "GAVIC422198775",
    "tech_change_status": "Not Planned"
   }
  },
  {
   "type": "Feature",
   "geometry": {
    "type": "Point",
    "coordinates": [
     145.46609473,
     -35.82343665
    ]
   },
   "properties": {
    "name": "600 ULUPNA BRIDGE ROAD ULUPNA 3641",
    "locID": "LOC000093937006",
    "tech": "SATELLITE",
    "upgrade": "NULL_NA",
    "gnaf_pid": "GAVIC422198776",
    "tech_change_status": "Not Planned"
   }
  },
  {
   "type": "Feature",
   "geometry": {
    "type": "Point",
    "coordinates": [
     145.46676164,
     -35.82276364
    ]
   },
   "properties": {
    "name": "610 ULUPNA BRIDGE ROAD ULUPNA 3641",
    "locID": "LOC000078980496",
    "tech": "SATELLITE",
    "upgrade": "NULL_NA",
    "gnaf_pid": "GAVIC422198777",
    "tech_change_status": "Not Planned"
   }
  },
  {
   "type": "Feature",
   "geometry": {
    "type": "Point",
    "coordinates": [
     145.48952561,
     -35.81547904
    ]
   },
   "properties": {
    "name": "884 ULUPNA BRIDGE ROAD ULUPNA 3641",
    "locID": "LOC000039709416",
    "tech": "SATELLITE",
    "upgrade": "NULL_NA",
    "gnaf_pid": "GAVIC422198778",
    "tech_change_status": "Not Planned"
   }
  }
 ]
}