{
 "type": "FeatureCollection",
 "generated": "2023-12-01T09:57:21.515011",
 "suburb": "WENTWORTH",
 "features": [
  {
   "type": "Feature",
   "geometry": {
    "type": "Point",
    "coordinates": [
     147.52901982,
     -37.32397535
    ]
   },
   "properties": {
    "name": "37 MOUNT DELUSION ROAD WENTWORTH 3875",
    "locID": "ChIJ-c_-XrilJWsR4llDU5xMwzY",
    "tech": "SATELLITE",
    "upgrade": "UNKNOWN",
    "gnaf_pid": "GAVIC423721990"
   }
  },
  {
   "type": "Feature",
   "geometry": {
    "type": "Point",
    "coordinates": [
     147.47344447,
     -37.26199713
    ]
   },
   "properties": {
    "name": "662 UPPER LIVINGSTONE CREEK TRACK WENTWORTH 3875",
    "locID": "ChIJU_675eevJWsR0Yj23WB3gF0",
    "tech": "SATELLITE",
    "upgrade": "UNKNOWN",
    "gnaf_pid": "GAVIC720133223"
   }
  }
 ]
}