{
 "type": "FeatureCollection",
 "generated": "2023-10-25T15:52:48.699046",
 "suburb": "WYCHITELLA NORTH",
 "features": [
  {
   "type": "Feature",
   "geometry": {
    "type": "Point",
    "coordinates": [
     143.59789828,
     -36.21754384
    ]
   },
   "properties": {
    "name": "1261 OLD CHARLTON-BOORT ROAD WYCHITELLA NORTH 3525",
    "locID": "LOC000114019124",
    "tech": "SATELLITE",
    "upgrade": "NULL_NA",
    "gnaf_pid": "GAVIC412650037"
   }
  },
  {
   "type": "Feature",
   "geometry": {
    "type": "Point",
    "coordinates": [
     143.65805613,
     -36.22366894
    ]
   },
   "properties": {
    "name": "690 OLD CHARLTON-BOORT ROAD WYCHITELLA NORTH 3525",
    "locID": "LOC000056075152",
    "tech": "WIRELESS",
    "upgrade": "NULL_NA",
    "gnaf_pid": "GAVIC412650041"
   }
  },
  {
   "type": "Feature",
   "geometry": {
    "type": "Point",
    "coordinates": [
     143.63919615,
     -36.19221075
    ]
   },
   "properties": {
    "name": "1250 WYCHITELLA BUS ROUTE ROAD WYCHITELLA NORTH 3525",
    "locID": "ChIJEQ0CWZJp2moRU_wihCKvX2U",
    "tech": "SATELLITE",
    "upgrade": "UNKNOWN",
    "gnaf_pid": "GAVIC422025992"
   }
  },
  {
   "type": "Feature",
   "geometry": {
    "type": "Point",
    "coordinates": [
     143.62028579,
     -36.19880964
    ]
   },
   "properties": {
    "name": "185 JAMES ROAD WYCHITELLA NORTH 3525",
    "locID": "LOC000084495604",
    "tech": "SATELLITE",
    "upgrade": "NULL_NA",
    "gnaf_pid": "GAVIC422158829"
   }
  },
  {
   "type": "Feature",
   "geometry": {
    "type": "Point",
    "coordinates": [
     143.61917666,
     -36.20944158
    ]
   },
   "properties": {
    "name": "71 JAMES ROAD WYCHITELLA NORTH 3525",
    "locID": "LOC000040505017",
    "tech": "SATELLITE",
    "upgrade": "NULL_NA",
    "gnaf_pid": "GAVIC422158830"
   }
  },
  {
   "type": "Feature",
   "geometry": {
    "type": "Point",
    "coordinates": [
     143.61948801,
     -36.1552298
    ]
   },
   "properties": {
    "name": "2204 WYCHITELLA BUS ROUTE ROAD WYCHITELLA NORTH 3525",
    "locID": "ChIJP_x3s3dC2moRpE-2CiNMd2Y",
    "tech": "SATELLITE",
    "upgrade": "UNKNOWN",
    "gnaf_pid": "GAVIC422205333"
   }
  },
  {
   "type": "Feature",
   "geometry": {
    "type": "Point",
    "coordinates": [
     143.62890198,
     -36.21518892
    ]
   },
   "properties": {
    "name": "984 OLD CHARLTON-BOORT ROAD WYCHITELLA NORTH 3525",
    "locID": "ChIJ6REQo3Jp2moR2TXsPb_TLYM",
    "tech": "SATELLITE",
    "upgrade": "UNKNOWN",
    "gnaf_pid": "GAVIC424500910"
   }
  },
  {
   "type": "Feature",
   "geometry": {
    "type": "Point",
    "coordinates": [
     143.61525188,
     -36.21628235
    ]
   },
   "properties": {
    "name": "1105 OLD CHARLTON-BOORT ROAD WYCHITELLA NORTH 3525",
    "locID": "ChIJdwu7UBhp2moRVaM4I2AdWuo",
    "tech": "SATELLITE",
    "upgrade": "UNKNOWN",
    "gnaf_pid": "GAVIC424676372"
   }
  }
 ]
}