{
 "type": "FeatureCollection",
 "generated": "2024-09-24T13:32:03.901712",
 "suburb": "WYCHITELLA NORTH",
 "features": [
  {
   "type": "Feature",
   "geometry": {
    "type": "Point",
    "coordinates": [
     143.59789828,
     -36.21754384
    ]
   },
   "properties": {
    "name": "1261 OLD CHARLTON-BOORT ROAD WYCHITELLA NORTH 3525",
    "locID": "LOC000114019124",
    "tech": "SATELLITE",
    "upgrade": "NULL_NA",
    "gnaf_pid": "GAVIC412650037",
    "tech_change_status": "Not Planned"
   }
  },
  {
   "type": "Feature",
   "geometry": {
    "type": "Point",
    "coordinates": [
     143.65805613,
     -36.22366894
    ]
   },
   "properties": {
    "name": "690 OLD CHARLTON-BOORT ROAD WYCHITELLA NORTH 3525",
    "locID": "LOC000056075152",
    "tech": "WIRELESS",
    "upgrade": "NULL_NA",
    "gnaf_pid": "GAVIC412650041",
    "tech_change_status": "Not Planned",
    "program_type": "Fixed Wireless and Satellite Upgrade Program",
    "target_eligibility_quarter": "Dec 2024"
   }
  },
  {
   "type": "Feature",
   "geometry": {
    "type": "Point",
    "coordinates": [
     143.62028579,
     -36.19880964
    ]
   },
   "properties": {
    "name": "185 JAMES ROAD WYCHITELLA NORTH 3525",
    "locID": "LOC000084495604",
    "tech": "SATELLITE",
    "upgrade": "NULL_NA",
    "gnaf_pid": "GAVIC422158829",
    "tech_change_status": "Not Planned"
   }
  },
  {
   "type": "Feature",
   "geometry": {
    "type": "Point",
    "coordinates": [
     143.61917666,
     -36.20944158
    ]
   },
   "properties": {
    "name": "71 JAMES ROAD WYCHITELLA NORTH 3525",
    "locID": "LOC000040505017",
    "tech": "NULL",
    "upgrade": "NULL_NA",
    "gnaf_pid": "GAVIC422158830",
    "tech_change_status": "Not Planned"
   }
  }
 ]
}