{
 "type": "FeatureCollection",
 "generated": "2024-06-18T04:44:24.148084",
 "suburb": "YATCHAW",
 "features": [
  {
   "type": "Feature",
   "geometry": {
    "type": "Point",
    "coordinates": [
     142.16367285,
     -37.87288611
    ]
   },
   "properties": {
    "name": "254 BURGERS ROAD YATCHAW 3301",
    "locID": "LOC000016077103",
    "tech": "SATELLITE",
    "upgrade": "NULL_NA",
    "gnaf_pid": "GAVIC420980785"
   }
  },
  {
   "type": "Feature",
   "geometry": {
    "type": "Point",
    "coordinates": [
     142.16842083,
     -37.87331679
    ]
   },
   "properties": {
    "name": "213 BURGERS ROAD YATCHAW 3301",
    "locID": "LOC000086534192",
    "tech": "SATELLITE",
    "upgrade": "NULL_NA",
    "gnaf_pid": "GAVIC422280537"
   }
  },
  {
   "type": "Feature",
   "geometry": {
    "type": "Point",
    "coordinates": [
     142.14690055,
     -37.80892553
    ]
   },
   "properties": {
    "name": "104 GELLERTS ROAD YATCHAW 3301",
    "locID": "LOC000044728032",
    "tech": "WIRELESS",
    "upgrade": "NULL_NA",
    "gnaf_pid": "GAVIC422292981"
   }
  },
  {
   "type": "Feature",
   "geometry": {
    "type": "Point",
    "coordinates": [
     142.1445005,
     -37.80872351
    ]
   },
   "properties": {
    "name": "83 GELLERTS ROAD YATCHAW 3301",
    "locID": "LOC000093465092",
    "tech": "WIRELESS",
    "upgrade": "NULL_NA",
    "gnaf_pid": "GAVIC422292982"
   }
  },
  {
   "type": "Feature",
   "geometry": {
    "type": "Point",
    "coordinates": [
     142.11889853,
     -37.81645896
    ]
   },
   "properties": {
    "name": "115 MEADOWLANDS ROAD YATCHAW 3301",
    "locID": "LOC000124638868",
    "tech": "WIRELESS",
    "upgrade": "NULL_NA",
    "gnaf_pid": "GAVIC422309052"
   }
  },
  {
   "type": "Feature",
   "geometry": {
    "type": "Point",
    "coordinates": [
     142.18646944,
     -37.8707841
    ]
   },
   "properties": {
    "name": "29 MIRTSCHINS ROAD YATCHAW 3301",
    "locID": "LOC000042448041",
    "tech": "WIRELESS",
    "upgrade": "NULL_NA",
    "gnaf_pid": "GAVIC422310199"
   }
  },
  {
   "type": "Feature",
   "geometry": {
    "type": "Point",
    "coordinates": [
     142.13012474,
     -37.80910563
    ]
   },
   "properties": {
    "name": "188 TWOMEYS BRIDGE ROAD YATCHAW 3301",
    "locID": "LOC000080051165",
    "tech": "WIRELESS",
    "upgrade": "NULL_NA",
    "gnaf_pid": "GAVIC422330158"
   }
  },
  {
   "type": "Feature",
   "geometry": {
    "type": "Point",
    "coordinates": [
     142.15290365,
     -37.84940595
    ]
   },
   "properties": {
    "name": "730 TWOMEYS BRIDGE ROAD YATCHAW 3301",
    "locID": "LOC000092776008",
    "tech": "WIRELESS",
    "upgrade": "NULL_NA",
    "gnaf_pid": "GAVIC422330159"
   }
  },
  {
   "type": "Feature",
   "geometry": {
    "type": "Point",
    "coordinates": [
     142.15293053,
     -37.85858312
    ]
   },
   "properties": {
    "name": "830 TWOMEYS BRIDGE ROAD YATCHAW 3301",
    "locID": "LOC000103033514",
    "tech": "WIRELESS",
    "upgrade": "NULL_NA",
    "gnaf_pid": "GAVIC422330160"
   }
  },
  {
   "type": "Feature",
   "geometry": {
    "type": "Point",
    "coordinates": [
     142.15257714,
     -37.87311498
    ]
   },
   "properties": {
    "name": "992 TWOMEYS BRIDGE ROAD YATCHAW 3301",
    "locID": "LOC000019549706",
    "tech": "WIRELESS",
    "upgrade": "NULL_NA",
    "gnaf_pid": "GAVIC422330161"
   }
  },
  {
   "type": "Feature",
   "geometry": {
    "type": "Point",
    "coordinates": [
     142.1095342,
     -37.80579791
    ]
   },
   "properties": {
    "name": "595 YATCHAW ROAD YATCHAW 3301",
    "locID": "LOC000093697972",
    "tech": "WIRELESS",
    "upgrade": "NULL_NA",
    "gnaf_pid": "GAVIC422335439"
   }
  },
  {
   "type": "Feature",
   "geometry": {
    "type": "Point",
    "coordinates": [
     142.10866415,
     -37.8099069
    ]
   },
   "properties": {
    "name": "647 YATCHAW ROAD YATCHAW 3301",
    "locID": "LOC000002041960",
    "tech": "WIRELESS",
    "upgrade": "NULL_NA",
    "gnaf_pid": "GAVIC423590180"
   }
  },
  {
   "type": "Feature",
   "geometry": {
    "type": "Point",
    "coordinates": [
     142.18688538,
     -37.87347706
    ]
   },
   "properties": {
    "name": "49 BURGERS ROAD YATCHAW 3301",
    "locID": "LOC000124643683",
    "tech": "WIRELESS",
    "upgrade": "NULL_NA",
    "gnaf_pid": "GAVIC424874089"
   }
  }
 ]
}