{
 "type": "FeatureCollection",
 "generated": "2024-04-20T02:10:04.993121",
 "suburb": "APPLETREE FLAT",
 "features": [
  {
   "type": "Feature",
   "geometry": {
    "type": "Point",
    "coordinates": [
     150.86343812,
     -32.5142847
    ]
   },
   "properties": {
    "name": "109 APPLE TREE FLAT ROAD APPLETREE FLAT 2330",
    "locID": "LOC000020594419",
    "tech": "SATELLITE",
    "upgrade": "NULL_NA",
    "gnaf_pid": "GANSW703920999"
   }
  },
  {
   "type": "Feature",
   "geometry": {
    "type": "Point",
    "coordinates": [
     150.85029551,
     -32.51972399
    ]
   },
   "properties": {
    "name": "264 APPLE TREE FLAT ROAD APPLETREE FLAT 2330",
    "locID": "LOC000142559360",
    "tech": "WIRELESS",
    "upgrade": "NULL_NA",
    "gnaf_pid": "GANSW703921000"
   }
  },
  {
   "type": "Feature",
   "geometry": {
    "type": "Point",
    "coordinates": [
     150.86206931,
     -32.51393752
    ]
   },
   "properties": {
    "name": "83 APPLE TREE FLAT ROAD APPLETREE FLAT 2330",
    "locID": "LOC100063827054",
    "tech": "SATELLITE",
    "upgrade": "NULL_NA",
    "gnaf_pid": "GANSW703921001"
   }
  },
  {
   "type": "Feature",
   "geometry": {
    "type": "Point",
    "coordinates": [
     150.86414925,
     -32.51129952
    ]
   },
   "properties": {
    "name": "92 APPLE TREE FLAT ROAD APPLETREE FLAT 2330",
    "locID": "LOC000029135851",
    "tech": "SATELLITE",
    "upgrade": "NULL_NA",
    "gnaf_pid": "GANSW703921002"
   }
  },
  {
   "type": "Feature",
   "geometry": {
    "type": "Point",
    "coordinates": [
     150.86924032,
     -32.5029898
    ]
   },
   "properties": {
    "name": "428 JONES RESERVE ROAD APPLETREE FLAT 2330",
    "locID": "LOC000090821455",
    "tech": "WIRELESS",
    "upgrade": "NULL_NA",
    "gnaf_pid": "GANSW703921005"
   }
  },
  {
   "type": "Feature",
   "geometry": {
    "type": "Point",
    "coordinates": [
     150.83869053,
     -32.50225997
    ]
   },
   "properties": {
    "name": "671 JONES RESERVE ROAD APPLETREE FLAT 2330",
    "locID": "LOC000009157901",
    "tech": "WIRELESS",
    "upgrade": "SAT_CT",
    "gnaf_pid": "GANSW703921007",
    "tech_change_status": "Eligible To Order"
   }
  },
  {
   "type": "Feature",
   "geometry": {
    "type": "Point",
    "coordinates": [
     150.86661448,
     -32.49689152
    ]
   },
   "properties": {
    "name": "488 JONES RESERVE ROAD APPLETREE FLAT 2330",
    "locID": "LOC000015100739",
    "tech": "SATELLITE",
    "upgrade": "NULL_NA",
    "gnaf_pid": "GANSW708466405"
   }
  },
  {
   "type": "Feature",
   "geometry": {
    "type": "Point",
    "coordinates": [
     150.85095711,
     -32.50541366
    ]
   },
   "properties": {
    "name": "541 JONES RESERVE ROAD APPLETREE FLAT 2330",
    "locID": "LOC000009705088",
    "tech": "WIRELESS",
    "upgrade": "NULL_NA",
    "gnaf_pid": "GANSW716735044"
   }
  },
  {
   "type": "Feature",
   "geometry": {
    "type": "Point",
    "coordinates": [
     150.84210153,
     -32.49793408
    ]
   },
   "properties": {
    "name": "734 JONES RESERVE ROAD APPLETREE FLAT 2330",
    "locID": "LOC000100384233",
    "tech": "WIRELESS",
    "upgrade": "NULL_NA",
    "gnaf_pid": "GANSW718054184"
   }
  },
  {
   "type": "Feature",
   "geometry": {
    "type": "Point",
    "coordinates": [
     150.85979306,
     -32.51797874
    ]
   },
   "properties": {
    "name": "165 APPLE TREE FLAT ROAD APPLETREE FLAT 2330",
    "locID": "LOC100078069338",
    "tech": "SATELLITE",
    "upgrade": "NULL_NA",
    "gnaf_pid": "GANSW720082430"
   }
  },
  {
   "type": "Feature",
   "geometry": {
    "type": "Point",
    "coordinates": [
     150.85684652,
     -32.5142153
    ]
   },
   "properties": {
    "name": "188 APPLE TREE FLAT ROAD APPLETREE FLAT 2330",
    "locID": "LOC100078069291",
    "tech": "SATELLITE",
    "upgrade": "NULL_NA",
    "gnaf_pid": "GANSW720087113"
   }
  },
  {
   "type": "Feature",
   "geometry": {
    "type": "Point",
    "coordinates": [
     150.86120472,
     -32.51800859
    ]
   },
   "properties": {
    "name": "163 APPLE TREE FLAT ROAD APPLETREE FLAT 2330",
    "locID": "LOC100078069340",
    "tech": "SATELLITE",
    "upgrade": "NULL_NA",
    "gnaf_pid": "GANSW720088127"
   }
  }
 ]
}