{
 "type": "FeatureCollection",
 "generated": "2024-07-28T22:46:10.334107",
 "suburb": "ARABLE",
 "features": [
  {
   "type": "Feature",
   "geometry": {
    "type": "Point",
    "coordinates": [
     148.98000384,
     -36.33164587
    ]
   },
   "properties": {
    "name": "411 ARABLE ROAD ARABLE 2630",
    "locID": "LOC000077880315",
    "tech": "WIRELESS",
    "upgrade": "NULL_NA",
    "gnaf_pid": "GANSW716912967",
    "tech_change_status": "Not Planned",
    "program_type": "Fixed Wireless and Satellite Upgrade Program",
    "target_eligibility_quarter": "NA"
   }
  },
  {
   "type": "Feature",
   "geometry": {
    "type": "Point",
    "coordinates": [
     149.02317971,
     -36.41204381
    ]
   },
   "properties": {
    "name": "164 COTTAGE CREEK ROAD ARABLE 2630",
    "locID": "LOC000054784544",
    "tech": "WIRELESS",
    "upgrade": "NULL_NA",
    "gnaf_pid": "GANSW716918222",
    "tech_change_status": "Not Planned",
    "program_type": "Fixed Wireless and Satellite Upgrade Program",
    "target_eligibility_quarter": "NA"
   }
  },
  {
   "type": "Feature",
   "geometry": {
    "type": "Point",
    "coordinates": [
     148.97753676,
     -36.43102257
    ]
   },
   "properties": {
    "name": "692 COTTAGE CREEK ROAD ARABLE 2630",
    "locID": "LOC000081805207",
    "tech": "SATELLITE",
    "upgrade": "NULL_NA",
    "gnaf_pid": "GANSW717096548",
    "tech_change_status": "Not Planned"
   }
  },
  {
   "type": "Feature",
   "geometry": {
    "type": "Point",
    "coordinates": [
     149.01492045,
     -36.38367653
    ]
   },
   "properties": {
    "name": "1834 MAFFRA ROAD ARABLE 2630",
    "locID": "LOC000152764706",
    "tech": "WIRELESS",
    "upgrade": "NULL_NA",
    "gnaf_pid": "GANSW717104029",
    "tech_change_status": "Not Planned",
    "program_type": "Fixed Wireless and Satellite Upgrade Program",
    "target_eligibility_quarter": "NA"
   }
  },
  {
   "type": "Feature",
   "geometry": {
    "type": "Point",
    "coordinates": [
     148.9638847,
     -36.37564054
    ]
   },
   "properties": {
    "name": "871 ARABLE ROAD ARABLE 2630",
    "locID": "LOC000022324298",
    "tech": "SATELLITE",
    "upgrade": "NULL_NA",
    "gnaf_pid": "GANSW717547971",
    "tech_change_status": "Not Planned"
   }
  },
  {
   "type": "Feature",
   "geometry": {
    "type": "Point",
    "coordinates": [
     149.017091,
     -36.3817454
    ]
   },
   "properties": {
    "name": "1832 MAFFRA ROAD ARABLE 2630",
    "locID": "LOC000148067600",
    "tech": "SATELLITE",
    "upgrade": "NULL_NA",
    "gnaf_pid": "GANSW718646305",
    "tech_change_status": "Not Planned"
   }
  },
  {
   "type": "Feature",
   "geometry": {
    "type": "Point",
    "coordinates": [
     149.00570544,
     -36.37325482
    ]
   },
   "properties": {
    "name": "1836 MAFFRA ROAD ARABLE 2630",
    "locID": "LOC000148067637",
    "tech": "WIRELESS",
    "upgrade": "NULL_NA",
    "gnaf_pid": "GANSW718646306",
    "tech_change_status": "Not Planned",
    "program_type": "Fixed Wireless and Satellite Upgrade Program",
    "target_eligibility_quarter": "NA"
   }
  },
  {
   "type": "Feature",
   "geometry": {
    "type": "Point",
    "coordinates": [
     148.92269957,
     -36.38311406
    ]
   },
   "properties": {
    "name": "1096 ARABLE ROAD ARABLE 2630",
    "locID": "LOC100079392288",
    "tech": "WIRELESS",
    "upgrade": "NULL_NA",
    "gnaf_pid": "GANSW719156486",
    "tech_change_status": "Not Planned",
    "program_type": "Fixed Wireless and Satellite Upgrade Program",
    "target_eligibility_quarter": "NA"
   }
  },
  {
   "type": "Feature",
   "geometry": {
    "type": "Point",
    "coordinates": [
     149.05109838,
     -36.38154703
    ]
   },
   "properties": {
    "name": "1825 MAFFRA ROAD ARABLE 2630",
    "locID": "LOC000102849849",
    "tech": "SATELLITE",
    "upgrade": "NULL_NA",
    "gnaf_pid": "GANSW720086649",
    "tech_change_status": "Not Planned"
   }
  }
 ]
}