{
 "type": "FeatureCollection",
 "generated": "2024-07-29T09:15:12.523272",
 "suburb": "BABINDA",
 "features": [
  {
   "type": "Feature",
   "geometry": {
    "type": "Point",
    "coordinates": [
     146.43414741,
     -31.84145246
    ]
   },
   "properties": {
    "name": "820 SARONA DOWNS ROAD BABINDA 2825",
    "locID": "LOC000122097793",
    "tech": "SATELLITE",
    "upgrade": "NULL_NA",
    "gnaf_pid": "GANSW718106209",
    "tech_change_status": "Not Planned"
   }
  },
  {
   "type": "Feature",
   "geometry": {
    "type": "Point",
    "coordinates": [
     146.47003082,
     -31.8725157
    ]
   },
   "properties": {
    "name": "386 SARONA DOWNS ROAD BABINDA 2825",
    "locID": "LOC000142529158",
    "tech": "SATELLITE",
    "upgrade": "NULL_NA",
    "gnaf_pid": "GANSW720625749",
    "tech_change_status": "Not Planned"
   }
  },
  {
   "type": "Feature",
   "geometry": {
    "type": "Point",
    "coordinates": [
     146.55351006,
     -31.89092502
    ]
   },
   "properties": {
    "name": "3823 HERMIDALE NYMAGEE ROAD BABINDA 2825",
    "locID": "LOC000172725540",
    "tech": "SATELLITE",
    "upgrade": "NULL_NA",
    "gnaf_pid": "GANSW720626066",
    "tech_change_status": "Not Planned"
   }
  },
  {
   "type": "Feature",
   "geometry": {
    "type": "Point",
    "coordinates": [
     146.55547554,
     -31.99771308
    ]
   },
   "properties": {
    "name": "7678 PEISLEY ROAD BABINDA 2825",
    "locID": "LOC100079660435",
    "tech": "SATELLITE",
    "upgrade": "NULL_NA",
    "gnaf_pid": "GANSW720626348",
    "tech_change_status": "Not Planned"
   }
  },
  {
   "type": "Feature",
   "geometry": {
    "type": "Point",
    "coordinates": [
     146.62223352,
     -31.98669579
    ]
   },
   "properties": {
    "name": "5596 PEISLEY ROAD BABINDA 2825",
    "locID": "LOC100080511779",
    "tech": "SATELLITE",
    "upgrade": "NULL_NA",
    "gnaf_pid": "GANSW720681252",
    "tech_change_status": "Not Planned"
   }
  },
  {
   "type": "Feature",
   "geometry": {
    "type": "Point",
    "coordinates": [
     146.4714638,
     -31.96128055
    ]
   },
   "properties": {
    "name": "5287 HERMIDALE NYMAGEE ROAD BABINDA 2825",
    "locID": "LOC000172725540",
    "tech": "SATELLITE",
    "upgrade": "NULL_NA",
    "gnaf_pid": "GANSW720681590",
    "tech_change_status": "Not Planned"
   }
  }
 ]
}