{
 "type": "FeatureCollection",
 "generated": "2024-07-12T09:24:25.605534",
 "suburb": "BENGALLA",
 "features": [
  {
   "type": "Feature",
   "geometry": {
    "type": "Point",
    "coordinates": [
     150.79357224,
     -32.30109021
    ]
   },
   "properties": {
    "name": "UNIT 3, 690 BENGALLA ROAD BENGALLA 2333",
    "locID": "LOC000086421820",
    "tech": "WIRELESS",
    "upgrade": "NULL_NA",
    "gnaf_pid": "GANSW707840358",
    "tech_change_status": "Not Planned",
    "program_type": "Fixed Wireless and Satellite Upgrade Program",
    "target_eligibility_quarter": "NA"
   }
  },
  {
   "type": "Feature",
   "geometry": {
    "type": "Point",
    "coordinates": [
     150.79357224,
     -32.30109021
    ]
   },
   "properties": {
    "name": "UNIT 1, 690 BENGALLA ROAD BENGALLA 2333",
    "locID": "LOC000086183698",
    "tech": "WIRELESS",
    "upgrade": "NULL_NA",
    "gnaf_pid": "GANSW707841241",
    "tech_change_status": "Not Planned",
    "program_type": "Fixed Wireless and Satellite Upgrade Program",
    "target_eligibility_quarter": "NA"
   }
  },
  {
   "type": "Feature",
   "geometry": {
    "type": "Point",
    "coordinates": [
     150.79357224,
     -32.30109021
    ]
   },
   "properties": {
    "name": "UNIT 2, 690 BENGALLA ROAD BENGALLA 2333",
    "locID": "LOC000086421820",
    "tech": "WIRELESS",
    "upgrade": "NULL_NA",
    "gnaf_pid": "GANSW707841242",
    "tech_change_status": "Not Planned",
    "program_type": "Fixed Wireless and Satellite Upgrade Program",
    "target_eligibility_quarter": "NA"
   }
  },
  {
   "type": "Feature",
   "geometry": {
    "type": "Point",
    "coordinates": [
     150.79357224,
     -32.30109021
    ]
   },
   "properties": {
    "name": "690 BENGALLA ROAD BENGALLA 2333",
    "locID": "LOC000086421820",
    "tech": "WIRELESS",
    "upgrade": "NULL_NA",
    "gnaf_pid": "GANSW708591242",
    "tech_change_status": "Not Planned",
    "program_type": "Fixed Wireless and Satellite Upgrade Program",
    "target_eligibility_quarter": "NA"
   }
  }
 ]
}