{
 "type": "FeatureCollection",
 "generated": "2024-03-07T20:39:43.013187",
 "suburb": "BENGALLA",
 "features": [
  {
   "type": "Feature",
   "geometry": {
    "type": "Point",
    "coordinates": [
     150.79357224,
     -32.30109021
    ]
   },
   "properties": {
    "name": "UNIT 3, 690 BENGALLA ROAD BENGALLA 2333",
    "locID": "LOC000086421820",
    "tech": "WIRELESS",
    "upgrade": "NULL_NA",
    "gnaf_pid": "GANSW707840358"
   }
  },
  {
   "type": "Feature",
   "geometry": {
    "type": "Point",
    "coordinates": [
     150.79357224,
     -32.30109021
    ]
   },
   "properties": {
    "name": "UNIT 1, 690 BENGALLA ROAD BENGALLA 2333",
    "locID": "LOC000086183698",
    "tech": "WIRELESS",
    "upgrade": "NULL_NA",
    "gnaf_pid": "GANSW707841241"
   }
  },
  {
   "type": "Feature",
   "geometry": {
    "type": "Point",
    "coordinates": [
     150.79357224,
     -32.30109021
    ]
   },
   "properties": {
    "name": "UNIT 2, 690 BENGALLA ROAD BENGALLA 2333",
    "locID": "LOC000086421820",
    "tech": "WIRELESS",
    "upgrade": "NULL_NA",
    "gnaf_pid": "GANSW707841242"
   }
  },
  {
   "type": "Feature",
   "geometry": {
    "type": "Point",
    "coordinates": [
     150.79357224,
     -32.30109021
    ]
   },
   "properties": {
    "name": "690 BENGALLA ROAD BENGALLA 2333",
    "locID": "LOC000086421820",
    "tech": "WIRELESS",
    "upgrade": "NULL_NA",
    "gnaf_pid": "GANSW708591242"
   }
  },
  {
   "type": "Feature",
   "geometry": {
    "type": "Point",
    "coordinates": [
     150.80607953,
     -32.30926579
    ]
   },
   "properties": {
    "name": "774 BENGALLA ROAD BENGALLA 2333",
    "locID": "LOC000101168193",
    "tech": "WIRELESS",
    "upgrade": "NULL_NA",
    "gnaf_pid": "GANSW708591243"
   }
  }
 ]
}