{
 "type": "FeatureCollection",
 "generated": "2023-10-30T08:45:42.011988",
 "suburb": "BENGALLA",
 "features": [
  {
   "type": "Feature",
   "geometry": {
    "type": "Point",
    "coordinates": [
     150.79357224,
     -32.30109021
    ]
   },
   "properties": {
    "name": "UNIT 3, 690 BENGALLA ROAD BENGALLA 2333",
    "locID": "LOC000086421820",
    "tech": "WIRELESS",
    "upgrade": "NULL_NA",
    "gnaf_pid": "GANSW707840358"
   }
  },
  {
   "type": "Feature",
   "geometry": {
    "type": "Point",
    "coordinates": [
     150.79357224,
     -32.30109021
    ]
   },
   "properties": {
    "name": "UNIT 1, 690 BENGALLA ROAD BENGALLA 2333",
    "locID": "LOC000086183698",
    "tech": "WIRELESS",
    "upgrade": "NULL_NA",
    "gnaf_pid": "GANSW707841241"
   }
  },
  {
   "type": "Feature",
   "geometry": {
    "type": "Point",
    "coordinates": [
     150.79357224,
     -32.30109021
    ]
   },
   "properties": {
    "name": "UNIT 2, 690 BENGALLA ROAD BENGALLA 2333",
    "locID": "LOC000086421820",
    "tech": "WIRELESS",
    "upgrade": "NULL_NA",
    "gnaf_pid": "GANSW707841242"
   }
  },
  {
   "type": "Feature",
   "geometry": {
    "type": "Point",
    "coordinates": [
     150.79357224,
     -32.30109021
    ]
   },
   "properties": {
    "name": "690 BENGALLA ROAD BENGALLA 2333",
    "locID": "LOC000086421820",
    "tech": "WIRELESS",
    "upgrade": "NULL_NA",
    "gnaf_pid": "GANSW708591242"
   }
  },
  {
   "type": "Feature",
   "geometry": {
    "type": "Point",
    "coordinates": [
     150.80607953,
     -32.30926579
    ]
   },
   "properties": {
    "name": "774 BENGALLA ROAD BENGALLA 2333",
    "locID": "LOC000101168193",
    "tech": "WIRELESS",
    "upgrade": "NULL_NA",
    "gnaf_pid": "GANSW708591243"
   }
  },
  {
   "type": "Feature",
   "geometry": {
    "type": "Point",
    "coordinates": [
     150.82527952,
     -32.29358052
    ]
   },
   "properties": {
    "name": "550 BENGALLA ROAD BENGALLA 2333",
    "locID": "ChIJ-XlwCGZiC2sRn_5mPgD7nQI",
    "tech": "SATELLITE",
    "upgrade": "UNKNOWN",
    "gnaf_pid": "GANSW708591244"
   }
  },
  {
   "type": "Feature",
   "geometry": {
    "type": "Point",
    "coordinates": [
     150.85157603,
     -32.26584568
    ]
   },
   "properties": {
    "name": "3 OVERTON ROAD BENGALLA 2333",
    "locID": "ChIJLYzgWtBjC2sRhuHW0orW_18",
    "tech": "WIRELESS",
    "upgrade": "UNKNOWN",
    "gnaf_pid": "GANSW708592750"
   }
  },
  {
   "type": "Feature",
   "geometry": {
    "type": "Point",
    "coordinates": [
     150.82527952,
     -32.29358052
    ]
   },
   "properties": {
    "name": "772 BENGALLA ROAD BENGALLA 2333",
    "locID": "ChIJ-XlwCGZiC2sRHKIGbFX7FLQ",
    "tech": "SATELLITE",
    "upgrade": "UNKNOWN",
    "gnaf_pid": "GANSW708592754"
   }
  },
  {
   "type": "Feature",
   "geometry": {
    "type": "Point",
    "coordinates": [
     150.83247426,
     -32.29339962
    ]
   },
   "properties": {
    "name": "413 BENGALLA ROAD BENGALLA 2333",
    "locID": "ChIJVxGV0GtiC2sR2Nesf2r8V98",
    "tech": "SATELLITE",
    "upgrade": "UNKNOWN",
    "gnaf_pid": "GANSW717154736"
   }
  },
  {
   "type": "Feature",
   "geometry": {
    "type": "Point",
    "coordinates": [
     150.82527952,
     -32.29358052
    ]
   },
   "properties": {
    "name": "519 BENGALLA ROAD BENGALLA 2333",
    "locID": "ChIJ-XlwCGZiC2sRRP8dcVXoYe0",
    "tech": "SATELLITE",
    "upgrade": "UNKNOWN",
    "gnaf_pid": "GANSW717154737"
   }
  },
  {
   "type": "Feature",
   "geometry": {
    "type": "Point",
    "coordinates": [
     150.85384757,
     -32.27027854
    ]
   },
   "properties": {
    "name": "79 OVERTON ROAD BENGALLA 2333",
    "locID": "ChIJT7M2ZtFjC2sRvBpApdiJ614",
    "tech": "WIRELESS",
    "upgrade": "UNKNOWN",
    "gnaf_pid": "GANSW719575124"
   }
  }
 ]
}