{
 "type": "FeatureCollection",
 "generated": "2023-12-28T03:19:18.261904",
 "suburb": "BILLILINGRA",
 "features": [
  {
   "type": "Feature",
   "geometry": {
    "type": "Point",
    "coordinates": [
     149.09931859,
     -36.01254885
    ]
   },
   "properties": {
    "name": "398 BILLILINGRA ROAD BILLILINGRA 2630",
    "locID": "ChIJk6_ND3B1PWsRYgb5SGS60jM",
    "tech": "WIRELESS",
    "upgrade": "UNKNOWN",
    "gnaf_pid": "GANSW704125415"
   }
  },
  {
   "type": "Feature",
   "geometry": {
    "type": "Point",
    "coordinates": [
     149.10447849,
     -36.03572472
    ]
   },
   "properties": {
    "name": "399 BILLILINGRA ROAD BILLILINGRA 2630",
    "locID": "LOC000006401612",
    "tech": "SATELLITE",
    "upgrade": "NULL_NA",
    "gnaf_pid": "GANSW704125416"
   }
  },
  {
   "type": "Feature",
   "geometry": {
    "type": "Point",
    "coordinates": [
     149.14433067,
     -36.02171687
    ]
   },
   "properties": {
    "name": "2653 MONARO HIGHWAY BILLILINGRA 2630",
    "locID": "ChIJn10bn1SePWsRrvuMjLzx818",
    "tech": "WIRELESS",
    "upgrade": "UNKNOWN",
    "gnaf_pid": "GANSW716737776"
   }
  },
  {
   "type": "Feature",
   "geometry": {
    "type": "Point",
    "coordinates": [
     149.16459529,
     -36.01451283
    ]
   },
   "properties": {
    "name": "2760 MONARO HIGHWAY BILLILINGRA 2630",
    "locID": "ChIJ5_Mcg-6ePWsRRWvZKD4mcwI",
    "tech": "SATELLITE",
    "upgrade": "UNKNOWN",
    "gnaf_pid": "GANSW716737777"
   }
  },
  {
   "type": "Feature",
   "geometry": {
    "type": "Point",
    "coordinates": [
     149.13190426,
     -36.03298677
    ]
   },
   "properties": {
    "name": "223 BILLILINGRA ROAD BILLILINGRA 2630",
    "locID": "LOC100072019631",
    "tech": "WIRELESS",
    "upgrade": "NULL_NA",
    "gnaf_pid": "GANSW716869808"
   }
  },
  {
   "type": "Feature",
   "geometry": {
    "type": "Point",
    "coordinates": [
     149.14417259,
     -36.01175962
    ]
   },
   "properties": {
    "name": "2761 MONARO HIGHWAY BILLILINGRA 2630",
    "locID": "LOC000048455725",
    "tech": "SATELLITE",
    "upgrade": "NULL_NA",
    "gnaf_pid": "GANSW716880562"
   }
  },
  {
   "type": "Feature",
   "geometry": {
    "type": "Point",
    "coordinates": [
     149.12836167,
     -36.01947705
    ]
   },
   "properties": {
    "name": "226 BILLILINGRA ROAD BILLILINGRA 2630",
    "locID": "LOC000106867497",
    "tech": "WIRELESS",
    "upgrade": "NULL_NA",
    "gnaf_pid": "GANSW717125370"
   }
  },
  {
   "type": "Feature",
   "geometry": {
    "type": "Point",
    "coordinates": [
     149.07328709,
     -36.0346864
    ]
   },
   "properties": {
    "name": "190 NIGHTINGALE ROAD BILLILINGRA 2630",
    "locID": "LOC000079853606",
    "tech": "SATELLITE",
    "upgrade": "NULL_NA",
    "gnaf_pid": "GANSW717271888"
   }
  },
  {
   "type": "Feature",
   "geometry": {
    "type": "Point",
    "coordinates": [
     149.16505053,
     -36.03453575
    ]
   },
   "properties": {
    "name": "2438 MONARO HIGHWAY BILLILINGRA 2630",
    "locID": "ChIJ1wa7ZxyfPWsRLXxSUw7aNPw",
    "tech": "SATELLITE",
    "upgrade": "UNKNOWN",
    "gnaf_pid": "GANSW717480535"
   }
  },
  {
   "type": "Feature",
   "geometry": {
    "type": "Point",
    "coordinates": [
     149.14743074,
     -36.0145249
    ]
   },
   "properties": {
    "name": "LOT 58 MONARO HIGHWAY BILLILINGRA 2630",
    "locID": "LOC000109046021",
    "tech": "SATELLITE",
    "upgrade": "NULL_NA",
    "gnaf_pid": "GANSW718045489"
   }
  },
  {
   "type": "Feature",
   "geometry": {
    "type": "Point",
    "coordinates": [
     149.07702709,
     -35.99456196
    ]
   },
   "properties": {
    "name": "802 NIGHTINGALE ROAD BILLILINGRA 2630",
    "locID": "ChIJM6mQ6rx1PWsR34GXoajHdE8",
    "tech": "SATELLITE",
    "upgrade": "UNKNOWN",
    "gnaf_pid": "GANSW718267151"
   }
  },
  {
   "type": "Feature",
   "geometry": {
    "type": "Point",
    "coordinates": [
     149.10770978,
     -36.03655893
    ]
   },
   "properties": {
    "name": "397 BILLILINGRA ROAD BILLILINGRA 2630",
    "locID": "ChIJg0JF_eCfPWsRnysnh3cJw-A",
    "tech": "SATELLITE",
    "upgrade": "UNKNOWN",
    "gnaf_pid": "GANSW718581125"
   }
  }
 ]
}