{
 "type": "FeatureCollection",
 "generated": "2024-09-10T17:32:36.741981",
 "suburb": "BILLILINGRA",
 "features": [
  {
   "type": "Feature",
   "geometry": {
    "type": "Point",
    "coordinates": [
     149.10447849,
     -36.03572472
    ]
   },
   "properties": {
    "name": "399 BILLILINGRA ROAD BILLILINGRA 2630",
    "locID": "LOC000006401612",
    "tech": "SATELLITE",
    "upgrade": "NULL_NA",
    "gnaf_pid": "GANSW704125416",
    "tech_change_status": "Not Planned"
   }
  },
  {
   "type": "Feature",
   "geometry": {
    "type": "Point",
    "coordinates": [
     149.13190426,
     -36.03298677
    ]
   },
   "properties": {
    "name": "223 BILLILINGRA ROAD BILLILINGRA 2630",
    "locID": "LOC100072019631",
    "tech": "WIRELESS",
    "upgrade": "NULL_NA",
    "gnaf_pid": "GANSW716869808",
    "tech_change_status": "Not Planned",
    "program_type": "Fixed Wireless and Satellite Upgrade Program",
    "target_eligibility_quarter": "NA"
   }
  },
  {
   "type": "Feature",
   "geometry": {
    "type": "Point",
    "coordinates": [
     149.14417259,
     -36.01175962
    ]
   },
   "properties": {
    "name": "2761 MONARO HIGHWAY BILLILINGRA 2630",
    "locID": "LOC000048455725",
    "tech": "SATELLITE",
    "upgrade": "NULL_NA",
    "gnaf_pid": "GANSW716880562",
    "tech_change_status": "Not Planned"
   }
  },
  {
   "type": "Feature",
   "geometry": {
    "type": "Point",
    "coordinates": [
     149.12836167,
     -36.01947705
    ]
   },
   "properties": {
    "name": "226 BILLILINGRA ROAD BILLILINGRA 2630",
    "locID": "LOC000106867497",
    "tech": "WIRELESS",
    "upgrade": "NULL_NA",
    "gnaf_pid": "GANSW717125370",
    "tech_change_status": "Not Planned",
    "program_type": "Fixed Wireless and Satellite Upgrade Program",
    "target_eligibility_quarter": "NA"
   }
  },
  {
   "type": "Feature",
   "geometry": {
    "type": "Point",
    "coordinates": [
     149.07328709,
     -36.0346864
    ]
   },
   "properties": {
    "name": "190 NIGHTINGALE ROAD BILLILINGRA 2630",
    "locID": "LOC000079853606",
    "tech": "SATELLITE",
    "upgrade": "NULL_NA",
    "gnaf_pid": "GANSW717271888",
    "tech_change_status": "Not Planned"
   }
  },
  {
   "type": "Feature",
   "geometry": {
    "type": "Point",
    "coordinates": [
     149.14743074,
     -36.0145249
    ]
   },
   "properties": {
    "name": "LOT 58 MONARO HIGHWAY BILLILINGRA 2630",
    "locID": "LOC000109046021",
    "tech": "SATELLITE",
    "upgrade": "NULL_NA",
    "gnaf_pid": "GANSW718045489",
    "tech_change_status": "Not Planned"
   }
  }
 ]
}