{
 "type": "FeatureCollection",
 "generated": "2023-12-06T04:37:15.528167",
 "suburb": "BOCO",
 "features": [
  {
   "type": "Feature",
   "geometry": {
    "type": "Point",
    "coordinates": [
     149.12725747,
     -36.6043836
    ]
   },
   "properties": {
    "name": "330 BOCO ROAD BOCO 2631",
    "locID": "LOC000086861665",
    "tech": "SATELLITE",
    "upgrade": "NULL_NA",
    "gnaf_pid": "GANSW717977705"
   }
  },
  {
   "type": "Feature",
   "geometry": {
    "type": "Point",
    "coordinates": [
     149.12652742,
     -36.60413137
    ]
   },
   "properties": {
    "name": "569 BOCO ROAD BOCO 2631",
    "locID": "ChIJRZ3m_LVYPGsRUBWB7tuYNTs",
    "tech": "SATELLITE",
    "upgrade": "UNKNOWN",
    "gnaf_pid": "GANSW717977706"
   }
  },
  {
   "type": "Feature",
   "geometry": {
    "type": "Point",
    "coordinates": [
     149.16501409,
     -36.58032017
    ]
   },
   "properties": {
    "name": "HOUSE 2, 451 BOCO ROAD BOCO 2631",
    "locID": "LOC000176818911",
    "tech": "SATELLITE",
    "upgrade": "NULL_NA",
    "gnaf_pid": "GANSW718574762"
   }
  },
  {
   "type": "Feature",
   "geometry": {
    "type": "Point",
    "coordinates": [
     149.16501409,
     -36.58032017
    ]
   },
   "properties": {
    "name": "451 BOCO ROAD BOCO 2631",
    "locID": "LOC000154126611",
    "tech": "SATELLITE",
    "upgrade": "NULL_NA",
    "gnaf_pid": "GANSW718574763"
   }
  },
  {
   "type": "Feature",
   "geometry": {
    "type": "Point",
    "coordinates": [
     149.1083923,
     -36.61886511
    ]
   },
   "properties": {
    "name": "2220 THE SNOWY RIVER WAY BOCO 2631",
    "locID": "LOC000184384742",
    "tech": "SATELLITE",
    "upgrade": "NULL_NA",
    "gnaf_pid": "GANSW719665383"
   }
  },
  {
   "type": "Feature",
   "geometry": {
    "type": "Point",
    "coordinates": [
     149.12339207,
     -36.64849525
    ]
   },
   "properties": {
    "name": "1746 THE SNOWY RIVER WAY BOCO 2631",
    "locID": "LOC000168203983",
    "tech": "SATELLITE",
    "upgrade": "NULL_NA",
    "gnaf_pid": "GANSW720274409"
   }
  }
 ]
}