{
 "type": "FeatureCollection",
 "generated": "2023-12-05T10:54:31.877986",
 "suburb": "BOGONG PEAKS WILDERNESS",
 "features": [
  {
   "type": "Feature",
   "geometry": {
    "type": "Point",
    "coordinates": [
     148.41953642,
     -35.65837892
    ]
   },
   "properties": {
    "name": "5772 SNOWY MOUNTAINS HIGHWAY BOGONG PEAKS WILDERNESS 2720",
    "locID": "EjY1NzcyIFNub3d5IE1vdW50YWlucyBId3ksIFRhbGJpbmdvIE5TVyAyNzIwLCBBdXN0cmFsaWEiMRIvChQKEglHKLMSpKsiaxEoOsqiYbgd3BCMLSoUChIJMZDjlNBRPWsRFv2uXXjulu0",
    "tech": "SATELLITE",
    "upgrade": "UNKNOWN",
    "gnaf_pid": "GANSW721171293"
   }
  }
 ]
}