{
 "type": "FeatureCollection",
 "generated": "2024-05-07T10:35:56.652000",
 "suburb": "BORAMBIL",
 "features": [
  {
   "type": "Feature",
   "geometry": {
    "type": "Point",
    "coordinates": [
     150.64716712,
     -31.50652167
    ]
   },
   "properties": {
    "name": "100 BORAMBIL ROAD BORAMBIL 2343",
    "locID": "LOC000120880548",
    "tech": "WIRELESS",
    "upgrade": "NULL_NA",
    "gnaf_pid": "GANSW717324217"
   }
  },
  {
   "type": "Feature",
   "geometry": {
    "type": "Point",
    "coordinates": [
     150.64548124,
     -31.50566133
    ]
   },
   "properties": {
    "name": "116 BORAMBIL ROAD BORAMBIL 2343",
    "locID": "LOC000120842762",
    "tech": "WIRELESS",
    "upgrade": "NULL_NA",
    "gnaf_pid": "GANSW717324218"
   }
  },
  {
   "type": "Feature",
   "geometry": {
    "type": "Point",
    "coordinates": [
     150.64086074,
     -31.50554996
    ]
   },
   "properties": {
    "name": "160 BORAMBIL ROAD BORAMBIL 2343",
    "locID": "LOC000171691764",
    "tech": "WIRELESS",
    "upgrade": "NULL_NA",
    "gnaf_pid": "GANSW717324219"
   }
  },
  {
   "type": "Feature",
   "geometry": {
    "type": "Point",
    "coordinates": [
     150.6386288,
     -31.50504314
    ]
   },
   "properties": {
    "name": "179 BORAMBIL ROAD BORAMBIL 2343",
    "locID": "LOC000120850694",
    "tech": "WIRELESS",
    "upgrade": "NULL_NA",
    "gnaf_pid": "GANSW717324220"
   }
  },
  {
   "type": "Feature",
   "geometry": {
    "type": "Point",
    "coordinates": [
     150.63700761,
     -31.50314302
    ]
   },
   "properties": {
    "name": "207 BORAMBIL ROAD BORAMBIL 2343",
    "locID": "LOC000120854568",
    "tech": "WIRELESS",
    "upgrade": "NULL_NA",
    "gnaf_pid": "GANSW717324221"
   }
  },
  {
   "type": "Feature",
   "geometry": {
    "type": "Point",
    "coordinates": [
     150.63700951,
     -31.50212575
    ]
   },
   "properties": {
    "name": "216 BORAMBIL ROAD BORAMBIL 2343",
    "locID": "LOC000088033621",
    "tech": "WIRELESS",
    "upgrade": "NULL_NA",
    "gnaf_pid": "GANSW717324222"
   }
  },
  {
   "type": "Feature",
   "geometry": {
    "type": "Point",
    "coordinates": [
     150.63269119,
     -31.49959619
    ]
   },
   "properties": {
    "name": "265 BORAMBIL ROAD BORAMBIL 2343",
    "locID": "LOC000120858804",
    "tech": "WIRELESS",
    "upgrade": "NULL_NA",
    "gnaf_pid": "GANSW717324223"
   }
  },
  {
   "type": "Feature",
   "geometry": {
    "type": "Point",
    "coordinates": [
     150.627768,
     -31.49877151
    ]
   },
   "properties": {
    "name": "323 BORAMBIL ROAD BORAMBIL 2343",
    "locID": "LOC000120863241",
    "tech": "WIRELESS",
    "upgrade": "NULL_NA",
    "gnaf_pid": "GANSW717324224"
   }
  },
  {
   "type": "Feature",
   "geometry": {
    "type": "Point",
    "coordinates": [
     150.62881737,
     -31.49429245
    ]
   },
   "properties": {
    "name": "330 BORAMBIL ROAD BORAMBIL 2343",
    "locID": "LOC000120863304",
    "tech": "WIRELESS",
    "upgrade": "NULL_NA",
    "gnaf_pid": "GANSW717324225"
   }
  },
  {
   "type": "Feature",
   "geometry": {
    "type": "Point",
    "coordinates": [
     150.64724348,
     -31.50871513
    ]
   },
   "properties": {
    "name": "84 BORAMBIL ROAD BORAMBIL 2343",
    "locID": "LOC000115416765",
    "tech": "WIRELESS",
    "upgrade": "NULL_NA",
    "gnaf_pid": "GANSW717324227"
   }
  },
  {
   "type": "Feature",
   "geometry": {
    "type": "Point",
    "coordinates": [
     150.63956067,
     -31.51555598
    ]
   },
   "properties": {
    "name": "37 LINDEMANS LANE BORAMBIL 2343",
    "locID": "LOC000120863447",
    "tech": "WIRELESS",
    "upgrade": "NULL_NA",
    "gnaf_pid": "GANSW717337668"
   }
  },
  {
   "type": "Feature",
   "geometry": {
    "type": "Point",
    "coordinates": [
     150.63741997,
     -31.51568566
    ]
   },
   "properties": {
    "name": "75 LINDEMANS LANE BORAMBIL 2343",
    "locID": "LOC000120878060",
    "tech": "WIRELESS",
    "upgrade": "NULL_NA",
    "gnaf_pid": "GANSW717337669"
   }
  },
  {
   "type": "Feature",
   "geometry": {
    "type": "Point",
    "coordinates": [
     150.62797413,
     -31.49754283
    ]
   },
   "properties": {
    "name": "333 BORAMBIL ROAD BORAMBIL 2343",
    "locID": "LOC100077363284",
    "tech": "WIRELESS",
    "upgrade": "NULL_NA",
    "gnaf_pid": "GANSW717904616"
   }
  }
 ]
}