{
 "type": "FeatureCollection",
 "generated": "2024-07-11T17:49:40.799373",
 "suburb": "BOWMANS CREEK",
 "features": [
  {
   "type": "Feature",
   "geometry": {
    "type": "Point",
    "coordinates": [
     151.1510802,
     -32.28058886
    ]
   },
   "properties": {
    "name": "522 BOWMANS CREEK ROAD BOWMANS CREEK 2330",
    "locID": "LOC000047076990",
    "tech": "SATELLITE",
    "upgrade": "NULL_NA",
    "gnaf_pid": "GANSW704218053",
    "tech_change_status": "Not Planned"
   }
  },
  {
   "type": "Feature",
   "geometry": {
    "type": "Point",
    "coordinates": [
     151.14615883,
     -32.2682264
    ]
   },
   "properties": {
    "name": "551 BOWMANS CREEK ROAD BOWMANS CREEK 2330",
    "locID": "LOC000031371403",
    "tech": "SATELLITE",
    "upgrade": "NULL_NA",
    "gnaf_pid": "GANSW704218054",
    "tech_change_status": "Not Planned"
   }
  },
  {
   "type": "Feature",
   "geometry": {
    "type": "Point",
    "coordinates": [
     151.13658408,
     -32.27481409
    ]
   },
   "properties": {
    "name": "608 BOWMANS CREEK ROAD BOWMANS CREEK 2330",
    "locID": "LOC000046991847",
    "tech": "SATELLITE",
    "upgrade": "NULL_NA",
    "gnaf_pid": "GANSW704218055",
    "tech_change_status": "Not Planned"
   }
  },
  {
   "type": "Feature",
   "geometry": {
    "type": "Point",
    "coordinates": [
     151.1425753,
     -32.27202783
    ]
   },
   "properties": {
    "name": "472 BOWMANS CREEK ROAD BOWMANS CREEK 2330",
    "locID": "LOC000034023857",
    "tech": "SATELLITE",
    "upgrade": "NULL_NA",
    "gnaf_pid": "GANSW708710644",
    "tech_change_status": "Not Planned"
   }
  },
  {
   "type": "Feature",
   "geometry": {
    "type": "Point",
    "coordinates": [
     151.10694418,
     -32.25916537
    ]
   },
   "properties": {
    "name": "1100 ALBANO ROAD BOWMANS CREEK 2330",
    "locID": "LOC000071047364",
    "tech": "SATELLITE",
    "upgrade": "NULL_NA",
    "gnaf_pid": "GANSW717153469",
    "tech_change_status": "Not Planned"
   }
  },
  {
   "type": "Feature",
   "geometry": {
    "type": "Point",
    "coordinates": [
     151.07708398,
     -32.24700791
    ]
   },
   "properties": {
    "name": "1104 ALBANO ROAD BOWMANS CREEK 2330",
    "locID": "LOC100079107618",
    "tech": "SATELLITE",
    "upgrade": "NULL_NA",
    "gnaf_pid": "GANSW717153471",
    "tech_change_status": "Not Planned"
   }
  },
  {
   "type": "Feature",
   "geometry": {
    "type": "Point",
    "coordinates": [
     151.0919301,
     -32.25948606
    ]
   },
   "properties": {
    "name": "850 ALBANO ROAD BOWMANS CREEK 2330",
    "locID": "LOC000071047364",
    "tech": "SATELLITE",
    "upgrade": "NULL_NA",
    "gnaf_pid": "GANSW717153475",
    "tech_change_status": "Not Planned"
   }
  },
  {
   "type": "Feature",
   "geometry": {
    "type": "Point",
    "coordinates": [
     151.16052247,
     -32.25724333
    ]
   },
   "properties": {
    "name": "164 MARSHALLS ROAD BOWMANS CREEK 2330",
    "locID": "LOC000047434546",
    "tech": "SATELLITE",
    "upgrade": "NULL_NA",
    "gnaf_pid": "GANSW717996622",
    "tech_change_status": "Not Planned"
   }
  },
  {
   "type": "Feature",
   "geometry": {
    "type": "Point",
    "coordinates": [
     151.15167316,
     -32.25077735
    ]
   },
   "properties": {
    "name": "260 MARSHALLS ROAD BOWMANS CREEK 2330",
    "locID": "LOC000052739947",
    "tech": "SATELLITE",
    "upgrade": "NULL_NA",
    "gnaf_pid": "GANSW717996624",
    "tech_change_status": "Not Planned"
   }
  },
  {
   "type": "Feature",
   "geometry": {
    "type": "Point",
    "coordinates": [
     151.15033736,
     -32.26910526
    ]
   },
   "properties": {
    "name": "484 BOWMANS CREEK ROAD BOWMANS CREEK 2330",
    "locID": "LOC000142566991",
    "tech": "SATELLITE",
    "upgrade": "NULL_NA",
    "gnaf_pid": "GANSW719079579",
    "tech_change_status": "Not Planned"
   }
  }
 ]
}