{
 "type": "FeatureCollection",
 "generated": "2024-07-29T00:12:41.897151",
 "suburb": "BRINERVILLE",
 "features": [
  {
   "type": "Feature",
   "geometry": {
    "type": "Point",
    "coordinates": [
     152.54432998,
     -30.46801977
    ]
   },
   "properties": {
    "name": "3712 DARKWOOD ROAD BRINERVILLE 2454",
    "locID": "LOC000043441782",
    "tech": "SATELLITE",
    "upgrade": "NULL_NA",
    "gnaf_pid": "GANSW704231088",
    "tech_change_status": "Not Planned"
   }
  }
 ]
}