{
 "type": "FeatureCollection",
 "generated": "2023-12-26T01:22:30.977683",
 "suburb": "BRINERVILLE",
 "features": [
  {
   "type": "Feature",
   "geometry": {
    "type": "Point",
    "coordinates": [
     152.52624667,
     -30.45135857
    ]
   },
   "properties": {
    "name": "3716 DARKWOOD ROAD BRINERVILLE 2454",
    "locID": "ChIJqTp33PWTnmsRBOl286GMnio",
    "tech": "SATELLITE",
    "upgrade": "UNKNOWN",
    "gnaf_pid": "GANSW704220144"
   }
  },
  {
   "type": "Feature",
   "geometry": {
    "type": "Point",
    "coordinates": [
     152.54432998,
     -30.46801977
    ]
   },
   "properties": {
    "name": "3712 DARKWOOD ROAD BRINERVILLE 2454",
    "locID": "LOC000043441782",
    "tech": "SATELLITE",
    "upgrade": "NULL_NA",
    "gnaf_pid": "GANSW704231088"
   }
  },
  {
   "type": "Feature",
   "geometry": {
    "type": "Point",
    "coordinates": [
     152.53893125,
     -30.46636982
    ]
   },
   "properties": {
    "name": "3714 DARKWOOD ROAD BRINERVILLE 2454",
    "locID": "ChIJQZpVnuOTnmsRsq4CTRpU19A",
    "tech": "SATELLITE",
    "upgrade": "UNKNOWN",
    "gnaf_pid": "GANSW704231089"
   }
  },
  {
   "type": "Feature",
   "geometry": {
    "type": "Point",
    "coordinates": [
     152.52502262,
     -30.47475806
    ]
   },
   "properties": {
    "name": "3943 DARKWOOD ROAD BRINERVILLE 2454",
    "locID": "ChIJA2o5PsGTnmsROEpWOexUm0M",
    "tech": "SATELLITE",
    "upgrade": "UNKNOWN",
    "gnaf_pid": "GANSW720156283"
   }
  },
  {
   "type": "Feature",
   "geometry": {
    "type": "Point",
    "coordinates": [
     152.5682897,
     -30.46698637
    ]
   },
   "properties": {
    "name": "3353 DARKWOOD ROAD BRINERVILLE 2454",
    "locID": "ChIJ32EULDaRnmsRC4Ujx1CVL-4",
    "tech": "SATELLITE",
    "upgrade": "UNKNOWN",
    "gnaf_pid": "GANSW720160688"
   }
  }
 ]
}