{
 "type": "FeatureCollection",
 "generated": "2024-09-29T11:55:27.046396",
 "suburb": "BRUNGLE CREEK",
 "features": [
  {
   "type": "Feature",
   "geometry": {
    "type": "Point",
    "coordinates": [
     148.27846444,
     -35.14058568
    ]
   },
   "properties": {
    "name": "1171 BRUNGLE CREEK ROAD BRUNGLE CREEK 2722",
    "locID": "LOC000078372804",
    "tech": "SATELLITE",
    "upgrade": "NULL_NA",
    "gnaf_pid": "GANSW704245980",
    "tech_change_status": "Not Planned"
   }
  },
  {
   "type": "Feature",
   "geometry": {
    "type": "Point",
    "coordinates": [
     148.31798352,
     -35.19029043
    ]
   },
   "properties": {
    "name": "273 BRUNGLE CREEK ROAD BRUNGLE CREEK 2722",
    "locID": "LOC000089592722",
    "tech": "SATELLITE",
    "upgrade": "NULL_NA",
    "gnaf_pid": "GANSW704245983",
    "tech_change_status": "Not Planned"
   }
  },
  {
   "type": "Feature",
   "geometry": {
    "type": "Point",
    "coordinates": [
     148.32527458,
     -35.18566545
    ]
   },
   "properties": {
    "name": "328 BRUNGLE CREEK ROAD BRUNGLE CREEK 2722",
    "locID": "LOC000101980446",
    "tech": "SATELLITE",
    "upgrade": "NULL_NA",
    "gnaf_pid": "GANSW704245984",
    "tech_change_status": "Not Planned"
   }
  },
  {
   "type": "Feature",
   "geometry": {
    "type": "Point",
    "coordinates": [
     148.29390805,
     -35.13927871
    ]
   },
   "properties": {
    "name": "995 BRUNGLE CREEK ROAD BRUNGLE CREEK 2722",
    "locID": "LOC000006474455",
    "tech": "NULL",
    "upgrade": "NULL_NA",
    "gnaf_pid": "GANSW704245990",
    "tech_change_status": "Not Planned"
   }
  },
  {
   "type": "Feature",
   "geometry": {
    "type": "Point",
    "coordinates": [
     148.28219704,
     -35.14216438
    ]
   },
   "properties": {
    "name": "1298 BRUNGLE CREEK ROAD BRUNGLE CREEK 2722",
    "locID": "LOC000035639987",
    "tech": "SATELLITE",
    "upgrade": "NULL_NA",
    "gnaf_pid": "GANSW715360333",
    "tech_change_status": "Not Planned"
   }
  },
  {
   "type": "Feature",
   "geometry": {
    "type": "Point",
    "coordinates": [
     148.32022192,
     -35.17600826
    ]
   },
   "properties": {
    "name": "431 BRUNGLE CREEK ROAD BRUNGLE CREEK 2722",
    "locID": "LOC000104043074",
    "tech": "NULL",
    "upgrade": "NULL_NA",
    "gnaf_pid": "GANSW716728754",
    "tech_change_status": "Not Planned"
   }
  },
  {
   "type": "Feature",
   "geometry": {
    "type": "Point",
    "coordinates": [
     148.28219704,
     -35.14216438
    ]
   },
   "properties": {
    "name": "1132 BRUNGLE CREEK ROAD BRUNGLE CREEK 2722",
    "locID": "LOC000055592560",
    "tech": "SATELLITE",
    "upgrade": "NULL_NA",
    "gnaf_pid": "GANSW717294540",
    "tech_change_status": "Not Planned"
   }
  },
  {
   "type": "Feature",
   "geometry": {
    "type": "Point",
    "coordinates": [
     148.28547726,
     -35.143441
    ]
   },
   "properties": {
    "name": "1452 BRUNGLE CREEK ROAD BRUNGLE CREEK 2722",
    "locID": "LOC000061761168",
    "tech": "SATELLITE",
    "upgrade": "NULL_NA",
    "gnaf_pid": "GANSW717294542",
    "tech_change_status": "Not Planned"
   }
  },
  {
   "type": "Feature",
   "geometry": {
    "type": "Point",
    "coordinates": [
     148.26078377,
     -35.13429285
    ]
   },
   "properties": {
    "name": "1344 BRUNGLE CREEK ROAD BRUNGLE CREEK 2722",
    "locID": "LOC000122075612",
    "tech": "SATELLITE",
    "upgrade": "NULL_NA",
    "gnaf_pid": "GANSW718129541",
    "tech_change_status": "Not Planned"
   }
  }
 ]
}