{
 "type": "FeatureCollection",
 "generated": "2024-03-04T06:55:53.474890",
 "suburb": "CADGEE",
 "features": [
  {
   "type": "Feature",
   "geometry": {
    "type": "Point",
    "coordinates": [
     149.8978669,
     -36.14356962
    ]
   },
   "properties": {
    "name": "166 CADGEE ROAD CADGEE 2545",
    "locID": "LOC000074237730",
    "tech": "SATELLITE",
    "upgrade": "NULL_NA",
    "gnaf_pid": "GANSW704283109"
   }
  },
  {
   "type": "Feature",
   "geometry": {
    "type": "Point",
    "coordinates": [
     149.93139058,
     -36.15587557
    ]
   },
   "properties": {
    "name": "2288 EUROBODALLA ROAD CADGEE 2545",
    "locID": "LOC000031487029",
    "tech": "SATELLITE",
    "upgrade": "NULL_NA",
    "gnaf_pid": "GANSW704283110"
   }
  },
  {
   "type": "Feature",
   "geometry": {
    "type": "Point",
    "coordinates": [
     149.93380271,
     -36.15297146
    ]
   },
   "properties": {
    "name": "2311 EUROBODALLA ROAD CADGEE 2545",
    "locID": "LOC000030439709",
    "tech": "SATELLITE",
    "upgrade": "NULL_NA",
    "gnaf_pid": "GANSW704283111"
   }
  },
  {
   "type": "Feature",
   "geometry": {
    "type": "Point",
    "coordinates": [
     149.93894177,
     -36.15029881
    ]
   },
   "properties": {
    "name": "2315 EUROBODALLA ROAD CADGEE 2545",
    "locID": "LOC000037558112",
    "tech": "SATELLITE",
    "upgrade": "NULL_NA",
    "gnaf_pid": "GANSW704283113"
   }
  },
  {
   "type": "Feature",
   "geometry": {
    "type": "Point",
    "coordinates": [
     149.94045511,
     -36.15078422
    ]
   },
   "properties": {
    "name": "2317 EUROBODALLA ROAD CADGEE 2545",
    "locID": "LOC000014726347",
    "tech": "SATELLITE",
    "upgrade": "NULL_NA",
    "gnaf_pid": "GANSW704283114"
   }
  },
  {
   "type": "Feature",
   "geometry": {
    "type": "Point",
    "coordinates": [
     149.94848958,
     -36.15204481
    ]
   },
   "properties": {
    "name": "2321 EUROBODALLA ROAD CADGEE 2545",
    "locID": "LOC000037281420",
    "tech": "SATELLITE",
    "upgrade": "NULL_NA",
    "gnaf_pid": "GANSW704283116"
   }
  },
  {
   "type": "Feature",
   "geometry": {
    "type": "Point",
    "coordinates": [
     149.92087833,
     -36.14501093
    ]
   },
   "properties": {
    "name": "2479 EUROBODALLA ROAD CADGEE 2545",
    "locID": "LOC000049652256",
    "tech": "SATELLITE",
    "upgrade": "NULL_NA",
    "gnaf_pid": "GANSW704283118"
   }
  },
  {
   "type": "Feature",
   "geometry": {
    "type": "Point",
    "coordinates": [
     149.92051456,
     -36.14307392
    ]
   },
   "properties": {
    "name": "2491 EUROBODALLA ROAD CADGEE 2545",
    "locID": "LOC000098481255",
    "tech": "SATELLITE",
    "upgrade": "NULL_NA",
    "gnaf_pid": "GANSW704283119"
   }
  },
  {
   "type": "Feature",
   "geometry": {
    "type": "Point",
    "coordinates": [
     149.91291627,
     -36.16802583
    ]
   },
   "properties": {
    "name": "440 WATTLEGROVE ROAD CADGEE 2545",
    "locID": "LOC000025989892",
    "tech": "SATELLITE",
    "upgrade": "NULL_NA",
    "gnaf_pid": "GANSW704283760"
   }
  },
  {
   "type": "Feature",
   "geometry": {
    "type": "Point",
    "coordinates": [
     149.91129566,
     -36.15655851
    ]
   },
   "properties": {
    "name": "20 WATTLEGROVE ROAD CADGEE 2545",
    "locID": "LOC000031819306",
    "tech": "SATELLITE",
    "upgrade": "NULL_NA",
    "gnaf_pid": "GANSW717091083"
   }
  },
  {
   "type": "Feature",
   "geometry": {
    "type": "Point",
    "coordinates": [
     149.92346024,
     -36.14360365
    ]
   },
   "properties": {
    "name": "2424 EUROBODALLA ROAD CADGEE 2545",
    "locID": "LOC000095911014",
    "tech": "SATELLITE",
    "upgrade": "NULL_NA",
    "gnaf_pid": "GANSW717139700"
   }
  },
  {
   "type": "Feature",
   "geometry": {
    "type": "Point",
    "coordinates": [
     149.92280933,
     -36.15131687
    ]
   },
   "properties": {
    "name": "2472 EUROBODALLA ROAD CADGEE 2545",
    "locID": "LOC000121212453",
    "tech": "SATELLITE",
    "upgrade": "NULL_NA",
    "gnaf_pid": "GANSW718353362"
   }
  }
 ]
}