{
 "type": "FeatureCollection",
 "generated": "2023-11-14T17:22:21.809856",
 "suburb": "CATARACT",
 "features": [
  {
   "type": "Feature",
   "geometry": {
    "type": "Point",
    "coordinates": [
     150.80612323,
     -34.24308908
    ]
   },
   "properties": {
    "name": "6 CATARACT DAM ROAD CATARACT 2560",
    "locID": "ChIJb8POXfriEmsR-g2O5XavTSU",
    "tech": "SATELLITE",
    "upgrade": "UNKNOWN",
    "gnaf_pid": "GANSW718809607"
   }
  },
  {
   "type": "Feature",
   "geometry": {
    "type": "Point",
    "coordinates": [
     150.82222434,
     -34.25076809
    ]
   },
   "properties": {
    "name": "3 BADEN POWELL DRIVE CATARACT 2560",
    "locID": "ChIJR474TlriEmsRntRB9kCY01Q",
    "tech": "SATELLITE",
    "upgrade": "UNKNOWN",
    "gnaf_pid": "GANSW720545284"
   }
  },
  {
   "type": "Feature",
   "geometry": {
    "type": "Point",
    "coordinates": [
     150.82222434,
     -34.25076809
    ]
   },
   "properties": {
    "name": "4 BADEN POWELL DRIVE CATARACT 2560",
    "locID": "ChIJR474TlriEmsRZ4Kk96LU5KY",
    "tech": "SATELLITE",
    "upgrade": "UNKNOWN",
    "gnaf_pid": "GANSW720546537"
   }
  },
  {
   "type": "Feature",
   "geometry": {
    "type": "Point",
    "coordinates": [
     150.82222434,
     -34.25076809
    ]
   },
   "properties": {
    "name": "5 BADEN POWELL DRIVE CATARACT 2560",
    "locID": "Eiw1IEJhZGVuIFBvd2VsbCBEciwgQXBwaW4gTlNXIDI1NjAsIEF1c3RyYWxpYSIwEi4KFAoSCTcTKS1a4hJrERInwkGgxSXJEAUqFAoSCXnNikFa4hJrEcswzefLxFkX",
    "tech": "SATELLITE",
    "upgrade": "UNKNOWN",
    "gnaf_pid": "GANSW720547046"
   }
  },
  {
   "type": "Feature",
   "geometry": {
    "type": "Point",
    "coordinates": [
     150.82222434,
     -34.25076809
    ]
   },
   "properties": {
    "name": "6 BADEN POWELL DRIVE CATARACT 2560",
    "locID": "LOC000108603882",
    "tech": "SATELLITE",
    "upgrade": "NULL_NA",
    "gnaf_pid": "GANSW720547600"
   }
  }
 ]
}