{
 "type": "FeatureCollection",
 "generated": "2024-04-17T09:19:18.315320",
 "suburb": "CATARACT",
 "features": [
  {
   "type": "Feature",
   "geometry": {
    "type": "Point",
    "coordinates": [
     150.82222434,
     -34.25076809
    ]
   },
   "properties": {
    "name": "6 BADEN POWELL DRIVE CATARACT 2560",
    "locID": "LOC000108603882",
    "tech": "SATELLITE",
    "upgrade": "NULL_NA",
    "gnaf_pid": "GANSW720547600"
   }
  }
 ]
}