{
 "type": "FeatureCollection",
 "generated": "2024-05-27T22:55:16.086177",
 "suburb": "CHINNOCK",
 "features": [
  {
   "type": "Feature",
   "geometry": {
    "type": "Point",
    "coordinates": [
     149.9467759,
     -36.69892628
    ]
   },
   "properties": {
    "name": "298 VIMY RIDGE ROAD CHINNOCK 2550",
    "locID": "LOC000042114702",
    "tech": "WIRELESS",
    "upgrade": "NULL_NA",
    "gnaf_pid": "GANSW704402551"
   }
  },
  {
   "type": "Feature",
   "geometry": {
    "type": "Point",
    "coordinates": [
     149.9433081,
     -36.70195073
    ]
   },
   "properties": {
    "name": "280 VIMY RIDGE ROAD CHINNOCK 2550",
    "locID": "LOC000077692132",
    "tech": "WIRELESS",
    "upgrade": "NULL_NA",
    "gnaf_pid": "GANSW706498289"
   }
  },
  {
   "type": "Feature",
   "geometry": {
    "type": "Point",
    "coordinates": [
     149.92943986,
     -36.71406254
    ]
   },
   "properties": {
    "name": "114 VIMY RIDGE ROAD CHINNOCK 2550",
    "locID": "LOC000080883593",
    "tech": "WIRELESS",
    "upgrade": "NULL_NA",
    "gnaf_pid": "GANSW706498291"
   }
  },
  {
   "type": "Feature",
   "geometry": {
    "type": "Point",
    "coordinates": [
     149.96166857,
     -36.69301435
    ]
   },
   "properties": {
    "name": "89 GOATS KNOB ROAD CHINNOCK 2550",
    "locID": "LOC000121498150",
    "tech": "WIRELESS",
    "upgrade": "NULL_NA",
    "gnaf_pid": "GANSW717952347"
   }
  },
  {
   "type": "Feature",
   "geometry": {
    "type": "Point",
    "coordinates": [
     149.96325757,
     -36.69469142
    ]
   },
   "properties": {
    "name": "91 GOATS KNOB ROAD CHINNOCK 2550",
    "locID": "LOC000121500450",
    "tech": "WIRELESS",
    "upgrade": "NULL_NA",
    "gnaf_pid": "GANSW717952348"
   }
  },
  {
   "type": "Feature",
   "geometry": {
    "type": "Point",
    "coordinates": [
     149.9428815,
     -36.71370261
    ]
   },
   "properties": {
    "name": "170 VIMY RIDGE ROAD CHINNOCK 2550",
    "locID": "LOC100078142011",
    "tech": "WIRELESS",
    "upgrade": "NULL_NA",
    "gnaf_pid": "GANSW718271132"
   }
  },
  {
   "type": "Feature",
   "geometry": {
    "type": "Point",
    "coordinates": [
     149.94617621,
     -36.70111469
    ]
   },
   "properties": {
    "name": "282 VIMY RIDGE ROAD CHINNOCK 2550",
    "locID": "LOC000121478055",
    "tech": "WIRELESS",
    "upgrade": "NULL_NA",
    "gnaf_pid": "GANSW718271133"
   }
  },
  {
   "type": "Feature",
   "geometry": {
    "type": "Point",
    "coordinates": [
     149.95408106,
     -36.7024811
    ]
   },
   "properties": {
    "name": "284 VIMY RIDGE ROAD CHINNOCK 2550",
    "locID": "LOC000121478064",
    "tech": "WIRELESS",
    "upgrade": "NULL_NA",
    "gnaf_pid": "GANSW718321305"
   }
  },
  {
   "type": "Feature",
   "geometry": {
    "type": "Point",
    "coordinates": [
     149.93187498,
     -36.69879925
    ]
   },
   "properties": {
    "name": "866 VIMY RIDGE ROAD CHINNOCK 2550",
    "locID": "LOC100072024938",
    "tech": "WIRELESS",
    "upgrade": "NULL_NA",
    "gnaf_pid": "GANSW719026605"
   }
  },
  {
   "type": "Feature",
   "geometry": {
    "type": "Point",
    "coordinates": [
     149.9190245,
     -36.69030043
    ]
   },
   "properties": {
    "name": "LOT 155 REEDY SWAMP ROAD CHINNOCK 2550",
    "locID": "LOC000186866249",
    "tech": "SATELLITE",
    "upgrade": "NULL_NA",
    "gnaf_pid": "GANSW720091885"
   }
  },
  {
   "type": "Feature",
   "geometry": {
    "type": "Point",
    "coordinates": [
     149.94010441,
     -36.68992598
    ]
   },
   "properties": {
    "name": "177 GOATS KNOB ROAD CHINNOCK 2550",
    "locID": "LOC000187202563",
    "tech": "WIRELESS",
    "upgrade": "NULL_NA",
    "gnaf_pid": "GANSW721006069"
   }
  }
 ]
}