{
 "type": "FeatureCollection",
 "generated": "2024-01-26T19:57:32.031413",
 "suburb": "COGGAN",
 "features": [
  {
   "type": "Feature",
   "geometry": {
    "type": "Point",
    "coordinates": [
     150.08730356,
     -32.34681691
    ]
   },
   "properties": {
    "name": "5567 WOLLAR ROAD COGGAN 2849",
    "locID": "LOC000013942203",
    "tech": "SATELLITE",
    "upgrade": "NULL_NA",
    "gnaf_pid": "GANSW706568169"
   }
  },
  {
   "type": "Feature",
   "geometry": {
    "type": "Point",
    "coordinates": [
     150.10941093,
     -32.35888452
    ]
   },
   "properties": {
    "name": "5745 WOLLAR ROAD COGGAN 2849",
    "locID": "ChIJb7Lee1sRDGsRJxIyFP-vJAs",
    "tech": "SATELLITE",
    "upgrade": "UNKNOWN",
    "gnaf_pid": "GANSW706578194"
   }
  },
  {
   "type": "Feature",
   "geometry": {
    "type": "Point",
    "coordinates": [
     150.09607888,
     -32.35490522
    ]
   },
   "properties": {
    "name": "5682 WOLLAR ROAD COGGAN 2849",
    "locID": "LOC000122476210",
    "tech": "SATELLITE",
    "upgrade": "NULL_NA",
    "gnaf_pid": "GANSW706588580"
   }
  },
  {
   "type": "Feature",
   "geometry": {
    "type": "Point",
    "coordinates": [
     150.10114032,
     -32.34456604
    ]
   },
   "properties": {
    "name": "5657 WOLLAR ROAD COGGAN 2849",
    "locID": "LOC000037497062",
    "tech": "SATELLITE",
    "upgrade": "NULL_NA",
    "gnaf_pid": "GANSW715412277"
   }
  },
  {
   "type": "Feature",
   "geometry": {
    "type": "Point",
    "coordinates": [
     150.09713987,
     -32.3581165
    ]
   },
   "properties": {
    "name": "5706 WOLLAR ROAD COGGAN 2849",
    "locID": "LOC000013897556",
    "tech": "SATELLITE",
    "upgrade": "NULL_NA",
    "gnaf_pid": "GANSW715412278"
   }
  },
  {
   "type": "Feature",
   "geometry": {
    "type": "Point",
    "coordinates": [
     150.10599859,
     -32.36585299
    ]
   },
   "properties": {
    "name": "5830 WOLLAR ROAD COGGAN 2849",
    "locID": "LOC000023301472",
    "tech": "SATELLITE",
    "upgrade": "NULL_NA",
    "gnaf_pid": "GANSW717911593"
   }
  },
  {
   "type": "Feature",
   "geometry": {
    "type": "Point",
    "coordinates": [
     150.11364095,
     -32.36127156
    ]
   },
   "properties": {
    "name": "5907 WOLLAR ROAD COGGAN 2849",
    "locID": "ChIJxSYuaVkRDGsRfXYukuynT8g",
    "tech": "SATELLITE",
    "upgrade": "UNKNOWN",
    "gnaf_pid": "GANSW718429229"
   }
  },
  {
   "type": "Feature",
   "geometry": {
    "type": "Point",
    "coordinates": [
     150.09208211,
     -32.38000343
    ]
   },
   "properties": {
    "name": "5569 WOLLAR ROAD COGGAN 2849",
    "locID": "ChIJe_JXKcYWDGsRnnAbsiEopMI",
    "tech": "SATELLITE",
    "upgrade": "UNKNOWN",
    "gnaf_pid": "GANSW718608291"
   }
  }
 ]
}