{
 "type": "FeatureCollection",
 "generated": "2024-08-20T21:18:33.590080",
 "suburb": "COGGAN",
 "features": [
  {
   "type": "Feature",
   "geometry": {
    "type": "Point",
    "coordinates": [
     150.08730356,
     -32.34681691
    ]
   },
   "properties": {
    "name": "5567 WOLLAR ROAD COGGAN 2849",
    "locID": "LOC000013942203",
    "tech": "SATELLITE",
    "upgrade": "NULL_NA",
    "gnaf_pid": "GANSW706568169",
    "tech_change_status": "Not Planned"
   }
  },
  {
   "type": "Feature",
   "geometry": {
    "type": "Point",
    "coordinates": [
     150.09607888,
     -32.35490522
    ]
   },
   "properties": {
    "name": "5682 WOLLAR ROAD COGGAN 2849",
    "locID": "LOC000122476210",
    "tech": "SATELLITE",
    "upgrade": "NULL_NA",
    "gnaf_pid": "GANSW706588580",
    "tech_change_status": "Not Planned"
   }
  },
  {
   "type": "Feature",
   "geometry": {
    "type": "Point",
    "coordinates": [
     150.10114032,
     -32.34456604
    ]
   },
   "properties": {
    "name": "5657 WOLLAR ROAD COGGAN 2849",
    "locID": "LOC000037497062",
    "tech": "SATELLITE",
    "upgrade": "NULL_NA",
    "gnaf_pid": "GANSW715412277",
    "tech_change_status": "Not Planned"
   }
  },
  {
   "type": "Feature",
   "geometry": {
    "type": "Point",
    "coordinates": [
     150.09713987,
     -32.3581165
    ]
   },
   "properties": {
    "name": "5706 WOLLAR ROAD COGGAN 2849",
    "locID": "LOC000013897556",
    "tech": "SATELLITE",
    "upgrade": "NULL_NA",
    "gnaf_pid": "GANSW715412278",
    "tech_change_status": "Not Planned"
   }
  },
  {
   "type": "Feature",
   "geometry": {
    "type": "Point",
    "coordinates": [
     150.10599859,
     -32.36585299
    ]
   },
   "properties": {
    "name": "5830 WOLLAR ROAD COGGAN 2849",
    "locID": "LOC000023301472",
    "tech": "SATELLITE",
    "upgrade": "NULL_NA",
    "gnaf_pid": "GANSW717911593",
    "tech_change_status": "Not Planned"
   }
  }
 ]
}