{
 "type": "FeatureCollection",
 "generated": "2024-07-30T12:51:39.789830",
 "suburb": "CONEAC",
 "features": [
  {
   "type": "Feature",
   "geometry": {
    "type": "Point",
    "coordinates": [
     151.81379644,
     -31.84607969
    ]
   },
   "properties": {
    "name": "777 CURRICABARK ROAD CONEAC 2422",
    "locID": "LOC000032015236",
    "tech": "SATELLITE",
    "upgrade": "NULL_NA",
    "gnaf_pid": "GANSW706442835",
    "tech_change_status": "Not Planned"
   }
  },
  {
   "type": "Feature",
   "geometry": {
    "type": "Point",
    "coordinates": [
     151.82015529,
     -31.8496535
    ]
   },
   "properties": {
    "name": "714 CURRICABARK ROAD CONEAC 2422",
    "locID": "LOC000075913088",
    "tech": "SATELLITE",
    "upgrade": "NULL_NA",
    "gnaf_pid": "GANSW706442853",
    "tech_change_status": "Not Planned"
   }
  },
  {
   "type": "Feature",
   "geometry": {
    "type": "Point",
    "coordinates": [
     151.82756047,
     -31.86150613
    ]
   },
   "properties": {
    "name": "517 CURRICABARK ROAD CONEAC 2422",
    "locID": "LOC000054489335",
    "tech": "SATELLITE",
    "upgrade": "NULL_NA",
    "gnaf_pid": "GANSW706603127",
    "tech_change_status": "Not Planned"
   }
  },
  {
   "type": "Feature",
   "geometry": {
    "type": "Point",
    "coordinates": [
     151.80643574,
     -31.81528575
    ]
   },
   "properties": {
    "name": "1149 CURRICABARK ROAD CONEAC 2422",
    "locID": "LOC000097031514",
    "tech": "SATELLITE",
    "upgrade": "NULL_NA",
    "gnaf_pid": "GANSW712117889",
    "tech_change_status": "Not Planned"
   }
  },
  {
   "type": "Feature",
   "geometry": {
    "type": "Point",
    "coordinates": [
     151.84442678,
     -31.87633987
    ]
   },
   "properties": {
    "name": "291 CURRICABARK ROAD CONEAC 2422",
    "locID": "LOC000089406667",
    "tech": "SATELLITE",
    "upgrade": "NULL_NA",
    "gnaf_pid": "GANSW715821291",
    "tech_change_status": "Not Planned"
   }
  },
  {
   "type": "Feature",
   "geometry": {
    "type": "Point",
    "coordinates": [
     151.80876631,
     -31.81811565
    ]
   },
   "properties": {
    "name": "1130 CURRICABARK ROAD CONEAC 2422",
    "locID": "LOC000012176068",
    "tech": "SATELLITE",
    "upgrade": "NULL_NA",
    "gnaf_pid": "GANSW716541958",
    "tech_change_status": "Not Planned"
   }
  },
  {
   "type": "Feature",
   "geometry": {
    "type": "Point",
    "coordinates": [
     151.80907521,
     -31.83711606
    ]
   },
   "properties": {
    "name": "889 CURRICABARK ROAD CONEAC 2422",
    "locID": "LOC000005652051",
    "tech": "SATELLITE",
    "upgrade": "NULL_NA",
    "gnaf_pid": "GANSW716605667",
    "tech_change_status": "Not Planned"
   }
  },
  {
   "type": "Feature",
   "geometry": {
    "type": "Point",
    "coordinates": [
     151.83024985,
     -31.86351737
    ]
   },
   "properties": {
    "name": "497 CURRICABARK ROAD CONEAC 2422",
    "locID": "LOC000148051608",
    "tech": "SATELLITE",
    "upgrade": "NULL_NA",
    "gnaf_pid": "GANSW716605668",
    "tech_change_status": "Not Planned"
   }
  },
  {
   "type": "Feature",
   "geometry": {
    "type": "Point",
    "coordinates": [
     151.84548564,
     -31.87386225
    ]
   },
   "properties": {
    "name": "308 CURRICABARK ROAD CONEAC 2422",
    "locID": "LOC000101247021",
    "tech": "SATELLITE",
    "upgrade": "NULL_NA",
    "gnaf_pid": "GANSW716872965",
    "tech_change_status": "Not Planned"
   }
  },
  {
   "type": "Feature",
   "geometry": {
    "type": "Point",
    "coordinates": [
     151.83653044,
     -31.86481893
    ]
   },
   "properties": {
    "name": "438 CURRICABARK ROAD CONEAC 2422",
    "locID": "LOC000056921931",
    "tech": "SATELLITE",
    "upgrade": "NULL_NA",
    "gnaf_pid": "GANSW717126812",
    "tech_change_status": "Not Planned"
   }
  },
  {
   "type": "Feature",
   "geometry": {
    "type": "Point",
    "coordinates": [
     151.81807405,
     -31.83141731
    ]
   },
   "properties": {
    "name": "1058 CURRICABARK ROAD CONEAC 2422",
    "locID": "LOC000029530948",
    "tech": "SATELLITE",
    "upgrade": "NULL_NA",
    "gnaf_pid": "GANSW717594347",
    "tech_change_status": "Not Planned"
   }
  },
  {
   "type": "Feature",
   "geometry": {
    "type": "Point",
    "coordinates": [
     151.83024985,
     -31.86351737
    ]
   },
   "properties": {
    "name": "HOUSE 2, 497 CURRICABARK ROAD CONEAC 2422",
    "locID": "LOC000142292437",
    "tech": "SATELLITE",
    "upgrade": "NULL_NA",
    "gnaf_pid": "GANSW718323841",
    "tech_change_status": "Not Planned"
   }
  },
  {
   "type": "Feature",
   "geometry": {
    "type": "Point",
    "coordinates": [
     151.81938763,
     -31.84907518
    ]
   },
   "properties": {
    "name": "LOT 2 CURRICABARK ROAD CONEAC 2422",
    "locID": "LOC000032015236",
    "tech": "SATELLITE",
    "upgrade": "NULL_NA",
    "gnaf_pid": "GANSW719063644",
    "tech_change_status": "Not Planned"
   }
  }
 ]
}