{
 "type": "FeatureCollection",
 "generated": "2024-07-30T20:01:55.839744",
 "suburb": "COOMOO COOMOO",
 "features": [
  {
   "type": "Feature",
   "geometry": {
    "type": "Point",
    "coordinates": [
     150.12900951,
     -31.55908115
    ]
   },
   "properties": {
    "name": "5609 BUNDELLA ROAD COOMOO COOMOO 2343",
    "locID": "LOC000037012159",
    "tech": "SATELLITE",
    "upgrade": "NULL_NA",
    "gnaf_pid": "GANSW717325217",
    "tech_change_status": "Not Planned"
   }
  },
  {
   "type": "Feature",
   "geometry": {
    "type": "Point",
    "coordinates": [
     150.05281647,
     -31.57040125
    ]
   },
   "properties": {
    "name": "6467 BUNDELLA ROAD COOMOO COOMOO 2343",
    "locID": "LOC000074489838",
    "tech": "SATELLITE",
    "upgrade": "NULL_NA",
    "gnaf_pid": "GANSW717325219",
    "tech_change_status": "Not Planned"
   }
  },
  {
   "type": "Feature",
   "geometry": {
    "type": "Point",
    "coordinates": [
     150.13155979,
     -31.57452855
    ]
   },
   "properties": {
    "name": "129 COOMOO COOMOO CREEK ROAD COOMOO COOMOO 2343",
    "locID": "LOC000064739460",
    "tech": "SATELLITE",
    "upgrade": "NULL_NA",
    "gnaf_pid": "GANSW717327898",
    "tech_change_status": "Not Planned"
   }
  },
  {
   "type": "Feature",
   "geometry": {
    "type": "Point",
    "coordinates": [
     150.11307852,
     -31.60149298
    ]
   },
   "properties": {
    "name": "494 COOMOO COOMOO CREEK ROAD COOMOO COOMOO 2343",
    "locID": "LOC000086653833",
    "tech": "SATELLITE",
    "upgrade": "NULL_NA",
    "gnaf_pid": "GANSW717327899",
    "tech_change_status": "Not Planned"
   }
  },
  {
   "type": "Feature",
   "geometry": {
    "type": "Point",
    "coordinates": [
     150.112536,
     -31.61026205
    ]
   },
   "properties": {
    "name": "572 COOMOO COOMOO CREEK ROAD COOMOO COOMOO 2343",
    "locID": "LOC000020753584",
    "tech": "SATELLITE",
    "upgrade": "NULL_NA",
    "gnaf_pid": "GANSW717327900",
    "tech_change_status": "Not Planned"
   }
  },
  {
   "type": "Feature",
   "geometry": {
    "type": "Point",
    "coordinates": [
     150.11119047,
     -31.63143813
    ]
   },
   "properties": {
    "name": "791 COOMOO COOMOO CREEK ROAD COOMOO COOMOO 2343",
    "locID": "LOC000076520739",
    "tech": "SATELLITE",
    "upgrade": "NULL_NA",
    "gnaf_pid": "GANSW717327901",
    "tech_change_status": "Not Planned"
   }
  },
  {
   "type": "Feature",
   "geometry": {
    "type": "Point",
    "coordinates": [
     150.18524283,
     -31.53351428
    ]
   },
   "properties": {
    "name": "1572 WILMOTTS ROAD COOMOO COOMOO 2343",
    "locID": "LOC100086158840",
    "tech": "SATELLITE",
    "upgrade": "NULL_NA",
    "gnaf_pid": "GANSW721437243",
    "tech_change_status": "Not Planned"
   }
  }
 ]
}