{
 "type": "FeatureCollection",
 "generated": "2024-09-27T23:59:39.500044",
 "suburb": "CRAVEN PLATEAU",
 "features": [
  {
   "type": "Feature",
   "geometry": {
    "type": "Point",
    "coordinates": [
     151.76522488,
     -31.86848136
    ]
   },
   "properties": {
    "name": "893 CRAVEN PLATEAU ROAD CRAVEN PLATEAU 2422",
    "locID": "LOC000041914621",
    "tech": "SATELLITE",
    "upgrade": "NULL_NA",
    "gnaf_pid": "GANSW706619304",
    "tech_change_status": "Not Planned"
   }
  },
  {
   "type": "Feature",
   "geometry": {
    "type": "Point",
    "coordinates": [
     151.7768462,
     -31.88465679
    ]
   },
   "properties": {
    "name": "611 CRAVEN PLATEAU ROAD CRAVEN PLATEAU 2422",
    "locID": "LOC000044473813",
    "tech": "SATELLITE",
    "upgrade": "NULL_NA",
    "gnaf_pid": "GANSW706619306",
    "tech_change_status": "Not Planned"
   }
  },
  {
   "type": "Feature",
   "geometry": {
    "type": "Point",
    "coordinates": [
     151.77903311,
     -31.88527558
    ]
   },
   "properties": {
    "name": "608 CRAVEN PLATEAU ROAD CRAVEN PLATEAU 2422",
    "locID": "LOC000005107031",
    "tech": "NULL",
    "upgrade": "NULL_NA",
    "gnaf_pid": "GANSW706619307",
    "tech_change_status": "Not Planned"
   }
  },
  {
   "type": "Feature",
   "geometry": {
    "type": "Point",
    "coordinates": [
     151.78339768,
     -31.86523775
    ]
   },
   "properties": {
    "name": "886 CRAVEN PLATEAU ROAD CRAVEN PLATEAU 2422",
    "locID": "LOC100078060938",
    "tech": "NULL",
    "upgrade": "NULL_NA",
    "gnaf_pid": "GANSW712179454",
    "tech_change_status": "Not Planned"
   }
  },
  {
   "type": "Feature",
   "geometry": {
    "type": "Point",
    "coordinates": [
     151.77048774,
     -31.86870942
    ]
   },
   "properties": {
    "name": "833 CRAVEN PLATEAU ROAD CRAVEN PLATEAU 2422",
    "locID": "LOC000024810270",
    "tech": "NULL",
    "upgrade": "NULL_NA",
    "gnaf_pid": "GANSW716605558",
    "tech_change_status": "Not Planned"
   }
  },
  {
   "type": "Feature",
   "geometry": {
    "type": "Point",
    "coordinates": [
     151.76311501,
     -31.85948504
    ]
   },
   "properties": {
    "name": "991 CRAVEN PLATEAU ROAD CRAVEN PLATEAU 2422",
    "locID": "LOC000024006259",
    "tech": "SATELLITE",
    "upgrade": "NULL_NA",
    "gnaf_pid": "GANSW718042612",
    "tech_change_status": "Not Planned"
   }
  },
  {
   "type": "Feature",
   "geometry": {
    "type": "Point",
    "coordinates": [
     151.76205595,
     -31.85725052
    ]
   },
   "properties": {
    "name": "1012 CRAVEN PLATEAU ROAD CRAVEN PLATEAU 2422",
    "locID": "LOC000152489008",
    "tech": "SATELLITE",
    "upgrade": "NULL_NA",
    "gnaf_pid": "GANSW719180359",
    "tech_change_status": "Not Planned"
   }
  }
 ]
}