{
 "type": "FeatureCollection",
 "generated": "2024-09-26T16:29:47.863373",
 "suburb": "CURRICABARK",
 "features": [
  {
   "type": "Feature",
   "geometry": {
    "type": "Point",
    "coordinates": [
     151.63539688,
     -31.74386686
    ]
   },
   "properties": {
    "name": "3436 CURRICABARK ROAD CURRICABARK 2422",
    "locID": "LOC000018257836",
    "tech": "SATELLITE",
    "upgrade": "NULL_NA",
    "gnaf_pid": "GANSW704554673",
    "tech_change_status": "Not Planned"
   }
  },
  {
   "type": "Feature",
   "geometry": {
    "type": "Point",
    "coordinates": [
     151.66780721,
     -31.73878608
    ]
   },
   "properties": {
    "name": "2796 CURRICABARK ROAD CURRICABARK 2422",
    "locID": "LOC000064573837",
    "tech": "SATELLITE",
    "upgrade": "NULL_NA",
    "gnaf_pid": "GANSW712179457",
    "tech_change_status": "Not Planned"
   }
  },
  {
   "type": "Feature",
   "geometry": {
    "type": "Point",
    "coordinates": [
     151.69205622,
     -31.74494305
    ]
   },
   "properties": {
    "name": "2814 CURRICABARK ROAD CURRICABARK 2422",
    "locID": "LOC000142485826",
    "tech": "SATELLITE",
    "upgrade": "NULL_NA",
    "gnaf_pid": "GANSW712179458",
    "tech_change_status": "Not Planned"
   }
  },
  {
   "type": "Feature",
   "geometry": {
    "type": "Point",
    "coordinates": [
     151.66780721,
     -31.73878608
    ]
   },
   "properties": {
    "name": "3421 CURRICABARK ROAD CURRICABARK 2422",
    "locID": "LOC000024029528",
    "tech": "SATELLITE",
    "upgrade": "NULL_NA",
    "gnaf_pid": "GANSW712179459",
    "tech_change_status": "Not Planned"
   }
  },
  {
   "type": "Feature",
   "geometry": {
    "type": "Point",
    "coordinates": [
     151.66780721,
     -31.73878608
    ]
   },
   "properties": {
    "name": "3470 CURRICABARK ROAD CURRICABARK 2422",
    "locID": "LOC000022385920",
    "tech": "SATELLITE",
    "upgrade": "NULL_NA",
    "gnaf_pid": "GANSW712179461",
    "tech_change_status": "Not Planned"
   }
  }
 ]
}