{
 "type": "FeatureCollection",
 "generated": "2023-12-24T13:03:08.114236",
 "suburb": "CURRICABARK",
 "features": [
  {
   "type": "Feature",
   "geometry": {
    "type": "Point",
    "coordinates": [
     151.68407229,
     -31.7074567
    ]
   },
   "properties": {
    "name": "586 BLOXOMS ROAD CURRICABARK 2422",
    "locID": "ChIJkQGrO6IidWsRa638qZm4Eko",
    "tech": "SATELLITE",
    "upgrade": "UNKNOWN",
    "gnaf_pid": "GANSW704544504"
   }
  },
  {
   "type": "Feature",
   "geometry": {
    "type": "Point",
    "coordinates": [
     151.63539688,
     -31.74386686
    ]
   },
   "properties": {
    "name": "3436 CURRICABARK ROAD CURRICABARK 2422",
    "locID": "LOC000018257836",
    "tech": "SATELLITE",
    "upgrade": "NULL_NA",
    "gnaf_pid": "GANSW704554673"
   }
  },
  {
   "type": "Feature",
   "geometry": {
    "type": "Point",
    "coordinates": [
     151.66780721,
     -31.73878608
    ]
   },
   "properties": {
    "name": "2796 CURRICABARK ROAD CURRICABARK 2422",
    "locID": "LOC000064573837",
    "tech": "SATELLITE",
    "upgrade": "NULL_NA",
    "gnaf_pid": "GANSW712179457"
   }
  },
  {
   "type": "Feature",
   "geometry": {
    "type": "Point",
    "coordinates": [
     151.69205622,
     -31.74494305
    ]
   },
   "properties": {
    "name": "2814 CURRICABARK ROAD CURRICABARK 2422",
    "locID": "LOC000142485826",
    "tech": "SATELLITE",
    "upgrade": "NULL_NA",
    "gnaf_pid": "GANSW712179458"
   }
  },
  {
   "type": "Feature",
   "geometry": {
    "type": "Point",
    "coordinates": [
     151.66780721,
     -31.73878608
    ]
   },
   "properties": {
    "name": "3421 CURRICABARK ROAD CURRICABARK 2422",
    "locID": "LOC000024029528",
    "tech": "SATELLITE",
    "upgrade": "NULL_NA",
    "gnaf_pid": "GANSW712179459"
   }
  },
  {
   "type": "Feature",
   "geometry": {
    "type": "Point",
    "coordinates": [
     151.66780721,
     -31.73878608
    ]
   },
   "properties": {
    "name": "3470 CURRICABARK ROAD CURRICABARK 2422",
    "locID": "LOC000022385920",
    "tech": "SATELLITE",
    "upgrade": "NULL_NA",
    "gnaf_pid": "GANSW712179461"
   }
  },
  {
   "type": "Feature",
   "geometry": {
    "type": "Point",
    "coordinates": [
     151.62213813,
     -31.75305998
    ]
   },
   "properties": {
    "name": "3627 CURRICABARK ROAD CURRICABARK 2422",
    "locID": "ChIJ8ZyV6OQjdWsRSrb8ZVx07gg",
    "tech": "SATELLITE",
    "upgrade": "UNKNOWN",
    "gnaf_pid": "GANSW712179462"
   }
  },
  {
   "type": "Feature",
   "geometry": {
    "type": "Point",
    "coordinates": [
     151.66780721,
     -31.73878608
    ]
   },
   "properties": {
    "name": "3628 CURRICABARK ROAD CURRICABARK 2422",
    "locID": "ChIJ-SVFqEUidWsRXpC9nfjz30w",
    "tech": "SATELLITE",
    "upgrade": "UNKNOWN",
    "gnaf_pid": "GANSW712179463"
   }
  }
 ]
}