{
 "type": "FeatureCollection",
 "generated": "2024-09-10T01:41:08.056409",
 "suburb": "DAVIS CREEK",
 "features": [
  {
   "type": "Feature",
   "geometry": {
    "type": "Point",
    "coordinates": [
     151.15403052,
     -32.15798443
    ]
   },
   "properties": {
    "name": "59 STUDLEIGH ROAD DAVIS CREEK 2336",
    "locID": "LOC000025892844",
    "tech": "SATELLITE",
    "upgrade": "NULL_NA",
    "gnaf_pid": "GANSW712029069",
    "tech_change_status": "Not Planned"
   }
  },
  {
   "type": "Feature",
   "geometry": {
    "type": "Point",
    "coordinates": [
     151.15813015,
     -32.1629956
    ]
   },
   "properties": {
    "name": "110 STUDLEIGH ROAD DAVIS CREEK 2336",
    "locID": "LOC000006806359",
    "tech": "SATELLITE",
    "upgrade": "NULL_NA",
    "gnaf_pid": "GANSW712029070",
    "tech_change_status": "Not Planned"
   }
  },
  {
   "type": "Feature",
   "geometry": {
    "type": "Point",
    "coordinates": [
     151.16939939,
     -32.1676766
    ]
   },
   "properties": {
    "name": "154 STUDLEIGH ROAD DAVIS CREEK 2336",
    "locID": "LOC000019774455",
    "tech": "SATELLITE",
    "upgrade": "NULL_NA",
    "gnaf_pid": "GANSW712029071",
    "tech_change_status": "Not Planned"
   }
  },
  {
   "type": "Feature",
   "geometry": {
    "type": "Point",
    "coordinates": [
     151.11123399,
     -32.14340617
    ]
   },
   "properties": {
    "name": "358 DAVIS CREEK ROAD DAVIS CREEK 2336",
    "locID": "LOC000120940602",
    "tech": "SATELLITE",
    "upgrade": "NULL_NA",
    "gnaf_pid": "GANSW717329035",
    "tech_change_status": "Not Planned"
   }
  },
  {
   "type": "Feature",
   "geometry": {
    "type": "Point",
    "coordinates": [
     151.15965409,
     -32.17011809
    ]
   },
   "properties": {
    "name": "150 STUDLEIGH ROAD DAVIS CREEK 2336",
    "locID": "LOC000120931330",
    "tech": "SATELLITE",
    "upgrade": "NULL_NA",
    "gnaf_pid": "GANSW718319814",
    "tech_change_status": "Not Planned"
   }
  },
  {
   "type": "Feature",
   "geometry": {
    "type": "Point",
    "coordinates": [
     151.12859257,
     -32.16658485
    ]
   },
   "properties": {
    "name": "694 DAVIS CREEK ROAD DAVIS CREEK 2336",
    "locID": "LOC000141393285",
    "tech": "SATELLITE",
    "upgrade": "NULL_NA",
    "gnaf_pid": "GANSW718431211",
    "tech_change_status": "Not Planned"
   }
  },
  {
   "type": "Feature",
   "geometry": {
    "type": "Point",
    "coordinates": [
     151.14905713,
     -32.15198266
    ]
   },
   "properties": {
    "name": "47 STUDLEIGH ROAD DAVIS CREEK 2336",
    "locID": "LOC000171084893",
    "tech": "SATELLITE",
    "upgrade": "NULL_NA",
    "gnaf_pid": "GANSW718540640",
    "tech_change_status": "Not Planned"
   }
  },
  {
   "type": "Feature",
   "geometry": {
    "type": "Point",
    "coordinates": [
     151.26709333,
     -32.18529262
    ]
   },
   "properties": {
    "name": "921 CASSELS ROAD DAVIS CREEK 2336",
    "locID": "LOC000047383499",
    "tech": "NULL",
    "upgrade": "NULL_NA",
    "gnaf_pid": "GANSW721172810",
    "tech_change_status": "Not Planned"
   }
  },
  {
   "type": "Feature",
   "geometry": {
    "type": "Point",
    "coordinates": [
     151.28146534,
     -32.17150595
    ]
   },
   "properties": {
    "name": "1195 CASSELS ROAD DAVIS CREEK 2336",
    "locID": "LOC000047383499",
    "tech": "NULL",
    "upgrade": "NULL_NA",
    "gnaf_pid": "GANSW721173336",
    "tech_change_status": "Not Planned"
   }
  }
 ]
}