{
 "type": "FeatureCollection",
 "generated": "2023-12-27T01:48:04.707858",
 "suburb": "DAVIS CREEK",
 "features": [
  {
   "type": "Feature",
   "geometry": {
    "type": "Point",
    "coordinates": [
     151.15403052,
     -32.15798443
    ]
   },
   "properties": {
    "name": "59 STUDLEIGH ROAD DAVIS CREEK 2336",
    "locID": "LOC000025892844",
    "tech": "SATELLITE",
    "upgrade": "NULL_NA",
    "gnaf_pid": "GANSW712029069"
   }
  },
  {
   "type": "Feature",
   "geometry": {
    "type": "Point",
    "coordinates": [
     151.15811076,
     -32.16258135
    ]
   },
   "properties": {
    "name": "110 STUDLEIGH ROAD DAVIS CREEK 2336",
    "locID": "LOC000006806359",
    "tech": "SATELLITE",
    "upgrade": "NULL_NA",
    "gnaf_pid": "GANSW712029070"
   }
  },
  {
   "type": "Feature",
   "geometry": {
    "type": "Point",
    "coordinates": [
     151.16939939,
     -32.1676766
    ]
   },
   "properties": {
    "name": "154 STUDLEIGH ROAD DAVIS CREEK 2336",
    "locID": "LOC000019774455",
    "tech": "SATELLITE",
    "upgrade": "NULL_NA",
    "gnaf_pid": "GANSW712029071"
   }
  },
  {
   "type": "Feature",
   "geometry": {
    "type": "Point",
    "coordinates": [
     151.11123399,
     -32.14340617
    ]
   },
   "properties": {
    "name": "358 DAVIS CREEK ROAD DAVIS CREEK 2336",
    "locID": "LOC000120940602",
    "tech": "SATELLITE",
    "upgrade": "NULL_NA",
    "gnaf_pid": "GANSW717329035"
   }
  },
  {
   "type": "Feature",
   "geometry": {
    "type": "Point",
    "coordinates": [
     151.15965409,
     -32.17011809
    ]
   },
   "properties": {
    "name": "150 STUDLEIGH ROAD DAVIS CREEK 2336",
    "locID": "LOC000120931330",
    "tech": "SATELLITE",
    "upgrade": "NULL_NA",
    "gnaf_pid": "GANSW718319814"
   }
  },
  {
   "type": "Feature",
   "geometry": {
    "type": "Point",
    "coordinates": [
     151.12859257,
     -32.16658485
    ]
   },
   "properties": {
    "name": "694 DAVIS CREEK ROAD DAVIS CREEK 2336",
    "locID": "LOC000141393285",
    "tech": "SATELLITE",
    "upgrade": "NULL_NA",
    "gnaf_pid": "GANSW718431211"
   }
  },
  {
   "type": "Feature",
   "geometry": {
    "type": "Point",
    "coordinates": [
     151.14905713,
     -32.15198266
    ]
   },
   "properties": {
    "name": "47 STUDLEIGH ROAD DAVIS CREEK 2336",
    "locID": "LOC000171084893",
    "tech": "SATELLITE",
    "upgrade": "NULL_NA",
    "gnaf_pid": "GANSW718540640"
   }
  },
  {
   "type": "Feature",
   "geometry": {
    "type": "Point",
    "coordinates": [
     151.11876754,
     -32.14613916
    ]
   },
   "properties": {
    "name": "436 DAVIS CREEK ROAD DAVIS CREEK 2336",
    "locID": "ChIJpYTfSOhFC2sR6Ld1U5xbqV8",
    "tech": "SATELLITE",
    "upgrade": "UNKNOWN",
    "gnaf_pid": "GANSW719891708"
   }
  },
  {
   "type": "Feature",
   "geometry": {
    "type": "Point",
    "coordinates": [
     151.24896124,
     -32.18424987
    ]
   },
   "properties": {
    "name": "110 CEDAR ROAD DAVIS CREEK 2336",
    "locID": "ChIJXddLWBZMC2sR06IsH-YSqzo",
    "tech": "SATELLITE",
    "upgrade": "UNKNOWN",
    "gnaf_pid": "GANSW720689015"
   }
  },
  {
   "type": "Feature",
   "geometry": {
    "type": "Point",
    "coordinates": [
     151.25192523,
     -32.18064903
    ]
   },
   "properties": {
    "name": "108 CEDAR ROAD DAVIS CREEK 2336",
    "locID": "ChIJLz96wxNMC2sRmz4DtJkp0fs",
    "tech": "SATELLITE",
    "upgrade": "UNKNOWN",
    "gnaf_pid": "GANSW720777284"
   }
  },
  {
   "type": "Feature",
   "geometry": {
    "type": "Point",
    "coordinates": [
     151.26709333,
     -32.18529262
    ]
   },
   "properties": {
    "name": "921 CASSELS ROAD DAVIS CREEK 2336",
    "locID": "LOC000047383499",
    "tech": "SATELLITE",
    "upgrade": "NULL_NA",
    "gnaf_pid": "GANSW721172810"
   }
  },
  {
   "type": "Feature",
   "geometry": {
    "type": "Point",
    "coordinates": [
     151.28146534,
     -32.17150595
    ]
   },
   "properties": {
    "name": "1195 CASSELS ROAD DAVIS CREEK 2336",
    "locID": "LOC000047383499",
    "tech": "SATELLITE",
    "upgrade": "NULL_NA",
    "gnaf_pid": "GANSW721173336"
   }
  },
  {
   "type": "Feature",
   "geometry": {
    "type": "Point",
    "coordinates": [
     151.23494734,
     -32.20469494
    ]
   },
   "properties": {
    "name": "69 CASSELS ROAD DAVIS CREEK 2336",
    "locID": "Ei42OSBDYXNzZWxzIFJkLCBNb3VudCBSb3lhbCBOU1cgMjMzMCwgQXVzdHJhbGlhIjASLgoUChIJe1gom4JNC2sRWPcz06WvUm0QRSoUChIJ_5BgH_BMC2sRukn7NKD0Vc4",
    "tech": "SATELLITE",
    "upgrade": "UNKNOWN",
    "gnaf_pid": "GANSW721315219"
   }
  }
 ]
}