{
 "type": "FeatureCollection",
 "generated": "2024-07-10T14:53:05.676009",
 "suburb": "DIEHARD",
 "features": [
  {
   "type": "Feature",
   "geometry": {
    "type": "Point",
    "coordinates": [
     152.13300507,
     -29.70211216
    ]
   },
   "properties": {
    "name": "11648 OLD GRAFTON ROAD DIEHARD 2370",
    "locID": "LOC100080864634",
    "tech": "SATELLITE",
    "upgrade": "NULL_NA",
    "gnaf_pid": "GANSW708999930",
    "tech_change_status": "Not Planned"
   }
  },
  {
   "type": "Feature",
   "geometry": {
    "type": "Point",
    "coordinates": [
     152.10961487,
     -29.69266657
    ]
   },
   "properties": {
    "name": "11674 OLD GRAFTON ROAD DIEHARD 2370",
    "locID": "LOC000019877784",
    "tech": "SATELLITE",
    "upgrade": "NULL_NA",
    "gnaf_pid": "GANSW708999932",
    "tech_change_status": "Not Planned"
   }
  },
  {
   "type": "Feature",
   "geometry": {
    "type": "Point",
    "coordinates": [
     152.13300507,
     -29.70211216
    ]
   },
   "properties": {
    "name": "11648B OLD GRAFTON ROAD DIEHARD 2370",
    "locID": "LOC000059642866",
    "tech": "SATELLITE",
    "upgrade": "NULL_NA",
    "gnaf_pid": "GANSW717727485",
    "tech_change_status": "Not Planned"
   }
  },
  {
   "type": "Feature",
   "geometry": {
    "type": "Point",
    "coordinates": [
     152.10094155,
     -29.68800673
    ]
   },
   "properties": {
    "name": "11286 OLD GRAFTON ROAD DIEHARD 2370",
    "locID": "LOC000142810590",
    "tech": "SATELLITE",
    "upgrade": "NULL_NA",
    "gnaf_pid": "GANSW718577755",
    "tech_change_status": "Not Planned"
   }
  },
  {
   "type": "Feature",
   "geometry": {
    "type": "Point",
    "coordinates": [
     152.10094155,
     -29.68800673
    ]
   },
   "properties": {
    "name": "11444 OLD GRAFTON ROAD DIEHARD 2370",
    "locID": "LOC000178664100",
    "tech": "SATELLITE",
    "upgrade": "NULL_NA",
    "gnaf_pid": "GANSW718611489",
    "tech_change_status": "Not Planned"
   }
  },
  {
   "type": "Feature",
   "geometry": {
    "type": "Point",
    "coordinates": [
     152.10094155,
     -29.68800673
    ]
   },
   "properties": {
    "name": "11020 OLD GRAFTON ROAD DIEHARD 2370",
    "locID": "LOC000155036651",
    "tech": "SATELLITE",
    "upgrade": "NULL_NA",
    "gnaf_pid": "GANSW719585408",
    "tech_change_status": "Not Planned"
   }
  },
  {
   "type": "Feature",
   "geometry": {
    "type": "Point",
    "coordinates": [
     152.10094155,
     -29.68800673
    ]
   },
   "properties": {
    "name": "10996 OLD GRAFTON ROAD DIEHARD 2370",
    "locID": "LOC000167674637",
    "tech": "SATELLITE",
    "upgrade": "NULL_NA",
    "gnaf_pid": "GANSW719841149",
    "tech_change_status": "Not Planned"
   }
  },
  {
   "type": "Feature",
   "geometry": {
    "type": "Point",
    "coordinates": [
     152.10094155,
     -29.68800673
    ]
   },
   "properties": {
    "name": "11450 OLD GRAFTON ROAD DIEHARD 2370",
    "locID": "LOC000142496998",
    "tech": "SATELLITE",
    "upgrade": "NULL_NA",
    "gnaf_pid": "GANSW719841555",
    "tech_change_status": "Not Planned"
   }
  },
  {
   "type": "Feature",
   "geometry": {
    "type": "Point",
    "coordinates": [
     152.10094155,
     -29.68800673
    ]
   },
   "properties": {
    "name": "11560 OLD GRAFTON ROAD DIEHARD 2370",
    "locID": "LOC000152391782",
    "tech": "SATELLITE",
    "upgrade": "NULL_NA",
    "gnaf_pid": "GANSW719842436",
    "tech_change_status": "Not Planned"
   }
  },
  {
   "type": "Feature",
   "geometry": {
    "type": "Point",
    "coordinates": [
     152.10094155,
     -29.68800673
    ]
   },
   "properties": {
    "name": "10790 OLD GRAFTON ROAD DIEHARD 2370",
    "locID": "LOC000142537725",
    "tech": "SATELLITE",
    "upgrade": "NULL_NA",
    "gnaf_pid": "GANSW719845314",
    "tech_change_status": "Not Planned"
   }
  },
  {
   "type": "Feature",
   "geometry": {
    "type": "Point",
    "coordinates": [
     152.10094155,
     -29.68800673
    ]
   },
   "properties": {
    "name": "10892 OLD GRAFTON ROAD DIEHARD 2370",
    "locID": "LOC000142868381",
    "tech": "SATELLITE",
    "upgrade": "NULL_NA",
    "gnaf_pid": "GANSW719845575",
    "tech_change_status": "Not Planned"
   }
  },
  {
   "type": "Feature",
   "geometry": {
    "type": "Point",
    "coordinates": [
     152.11036686,
     -29.69161449
    ]
   },
   "properties": {
    "name": "11664 OLD GRAFTON ROAD DIEHARD 2370",
    "locID": "LOC000181453287",
    "tech": "SATELLITE",
    "upgrade": "NULL_NA",
    "gnaf_pid": "GANSW720677805",
    "tech_change_status": "Not Planned"
   }
  }
 ]
}