{
 "type": "FeatureCollection",
 "generated": "2023-10-27T23:34:58.716395",
 "suburb": "EIGHTEEN MILE",
 "features": [
  {
   "type": "Feature",
   "geometry": {
    "type": "Point",
    "coordinates": [
     152.54574331,
     -29.24993804
    ]
   },
   "properties": {
    "name": "886 EIGHTEEN MILE ROAD EIGHTEEN MILE 2460",
    "locID": "LOC000018741546",
    "tech": "SATELLITE",
    "upgrade": "NULL_NA",
    "gnaf_pid": "GANSW706418275"
   }
  },
  {
   "type": "Feature",
   "geometry": {
    "type": "Point",
    "coordinates": [
     152.59592823,
     -29.25634256
    ]
   },
   "properties": {
    "name": "430 EIGHTEEN MILE ROAD EIGHTEEN MILE 2460",
    "locID": "ChIJK3OXc3GbmWsRKNlBvdTHhv8",
    "tech": "SATELLITE",
    "upgrade": "UNKNOWN",
    "gnaf_pid": "GANSW706418279"
   }
  },
  {
   "type": "Feature",
   "geometry": {
    "type": "Point",
    "coordinates": [
     152.61775012,
     -29.24275213
    ]
   },
   "properties": {
    "name": "6840 CLARENCE WAY EIGHTEEN MILE 2460",
    "locID": "LOC000142529094",
    "tech": "SATELLITE",
    "upgrade": "NULL_NA",
    "gnaf_pid": "GANSW706442190"
   }
  },
  {
   "type": "Feature",
   "geometry": {
    "type": "Point",
    "coordinates": [
     152.61758403,
     -29.24371786
    ]
   },
   "properties": {
    "name": "6822 CLARENCE WAY EIGHTEEN MILE 2460",
    "locID": "LOC000121188567",
    "tech": "SATELLITE",
    "upgrade": "NULL_NA",
    "gnaf_pid": "GANSW706442191"
   }
  },
  {
   "type": "Feature",
   "geometry": {
    "type": "Point",
    "coordinates": [
     152.57774751,
     -29.28616635
    ]
   },
   "properties": {
    "name": "487 EIGHTEEN MILE ROAD EIGHTEEN MILE 2460",
    "locID": "LOC000033012250",
    "tech": "SATELLITE",
    "upgrade": "NULL_NA",
    "gnaf_pid": "GANSW716522060"
   }
  },
  {
   "type": "Feature",
   "geometry": {
    "type": "Point",
    "coordinates": [
     152.60738193,
     -29.24462191
    ]
   },
   "properties": {
    "name": "6819 CLARENCE WAY EIGHTEEN MILE 2460",
    "locID": "ChIJ4ZqFexGbmWsRJ03casVbI0E",
    "tech": "SATELLITE",
    "upgrade": "UNKNOWN",
    "gnaf_pid": "GANSW716605206"
   }
  },
  {
   "type": "Feature",
   "geometry": {
    "type": "Point",
    "coordinates": [
     152.56031655,
     -29.28450072
    ]
   },
   "properties": {
    "name": "516 EIGHTEEN MILE ROAD EIGHTEEN MILE 2460",
    "locID": "LOC000093017815",
    "tech": "SATELLITE",
    "upgrade": "NULL_NA",
    "gnaf_pid": "GANSW716606214"
   }
  },
  {
   "type": "Feature",
   "geometry": {
    "type": "Point",
    "coordinates": [
     152.63122279,
     -29.27758484
    ]
   },
   "properties": {
    "name": "6372 CLARENCE WAY EIGHTEEN MILE 2460",
    "locID": "ChIJ1-dIHlabmWsRiMTHxKsgNUk",
    "tech": "SATELLITE",
    "upgrade": "UNKNOWN",
    "gnaf_pid": "GANSW720537751"
   }
  }
 ]
}