{
 "type": "FeatureCollection",
 "generated": "2024-07-09T18:38:53.970795",
 "suburb": "EIGHTEEN MILE",
 "features": [
  {
   "type": "Feature",
   "geometry": {
    "type": "Point",
    "coordinates": [
     152.54574331,
     -29.24993804
    ]
   },
   "properties": {
    "name": "886 EIGHTEEN MILE ROAD EIGHTEEN MILE 2460",
    "locID": "LOC000018741546",
    "tech": "SATELLITE",
    "upgrade": "NULL_NA",
    "gnaf_pid": "GANSW706418275",
    "tech_change_status": "Not Planned"
   }
  },
  {
   "type": "Feature",
   "geometry": {
    "type": "Point",
    "coordinates": [
     152.61775012,
     -29.24275213
    ]
   },
   "properties": {
    "name": "6840 CLARENCE WAY EIGHTEEN MILE 2460",
    "locID": "LOC000142529094",
    "tech": "SATELLITE",
    "upgrade": "NULL_NA",
    "gnaf_pid": "GANSW706442190",
    "tech_change_status": "Not Planned"
   }
  },
  {
   "type": "Feature",
   "geometry": {
    "type": "Point",
    "coordinates": [
     152.61758403,
     -29.24371786
    ]
   },
   "properties": {
    "name": "6822 CLARENCE WAY EIGHTEEN MILE 2460",
    "locID": "LOC000121188567",
    "tech": "SATELLITE",
    "upgrade": "NULL_NA",
    "gnaf_pid": "GANSW706442191",
    "tech_change_status": "Not Planned"
   }
  },
  {
   "type": "Feature",
   "geometry": {
    "type": "Point",
    "coordinates": [
     152.57774751,
     -29.28616635
    ]
   },
   "properties": {
    "name": "487 EIGHTEEN MILE ROAD EIGHTEEN MILE 2460",
    "locID": "LOC000033012250",
    "tech": "SATELLITE",
    "upgrade": "NULL_NA",
    "gnaf_pid": "GANSW716522060",
    "tech_change_status": "Not Planned"
   }
  },
  {
   "type": "Feature",
   "geometry": {
    "type": "Point",
    "coordinates": [
     152.56296484,
     -29.28565672
    ]
   },
   "properties": {
    "name": "516 EIGHTEEN MILE ROAD EIGHTEEN MILE 2460",
    "locID": "LOC000093017815",
    "tech": "SATELLITE",
    "upgrade": "NULL_NA",
    "gnaf_pid": "GANSW716606214",
    "tech_change_status": "Not Planned"
   }
  }
 ]
}