{
 "type": "FeatureCollection",
 "generated": "2024-06-19T06:22:20.322192",
 "suburb": "FARRINGDON",
 "features": [
  {
   "type": "Feature",
   "geometry": {
    "type": "Point",
    "coordinates": [
     149.66599164,
     -35.49864341
    ]
   },
   "properties": {
    "name": "1000 FARRINGDON ROAD FARRINGDON 2622",
    "locID": "LOC000048529095",
    "tech": "WIRELESS",
    "upgrade": "NULL_NA",
    "gnaf_pid": "GANSW716753164"
   }
  },
  {
   "type": "Feature",
   "geometry": {
    "type": "Point",
    "coordinates": [
     149.674435,
     -35.50456167
    ]
   },
   "properties": {
    "name": "1025 FARRINGDON ROAD FARRINGDON 2622",
    "locID": "LOC000023077181",
    "tech": "WIRELESS",
    "upgrade": "NULL_NA",
    "gnaf_pid": "GANSW716753165"
   }
  },
  {
   "type": "Feature",
   "geometry": {
    "type": "Point",
    "coordinates": [
     149.65405676,
     -35.50926533
    ]
   },
   "properties": {
    "name": "1109 FARRINGDON ROAD FARRINGDON 2622",
    "locID": "LOC000037455597",
    "tech": "SATELLITE",
    "upgrade": "NULL_NA",
    "gnaf_pid": "GANSW716753166"
   }
  },
  {
   "type": "Feature",
   "geometry": {
    "type": "Point",
    "coordinates": [
     149.66253424,
     -35.49188576
    ]
   },
   "properties": {
    "name": "908 FARRINGDON ROAD FARRINGDON 2622",
    "locID": "LOC000031253959",
    "tech": "SATELLITE",
    "upgrade": "NULL_NA",
    "gnaf_pid": "GANSW716753167"
   }
  },
  {
   "type": "Feature",
   "geometry": {
    "type": "Point",
    "coordinates": [
     149.6499021,
     -35.51780092
    ]
   },
   "properties": {
    "name": "159 MOUNT ELRINGTON ROAD FARRINGDON 2622",
    "locID": "LOC000014891964",
    "tech": "SATELLITE",
    "upgrade": "NULL_NA",
    "gnaf_pid": "GANSW716758204"
   }
  },
  {
   "type": "Feature",
   "geometry": {
    "type": "Point",
    "coordinates": [
     149.64823547,
     -35.5306009
    ]
   },
   "properties": {
    "name": "299 MOUNT ELRINGTON ROAD FARRINGDON 2622",
    "locID": "LOC000099060744",
    "tech": "SATELLITE",
    "upgrade": "NULL_NA",
    "gnaf_pid": "GANSW716758205"
   }
  },
  {
   "type": "Feature",
   "geometry": {
    "type": "Point",
    "coordinates": [
     149.64115627,
     -35.52944391
    ]
   },
   "properties": {
    "name": "312 MOUNT ELRINGTON ROAD FARRINGDON 2622",
    "locID": "LOC000053167648",
    "tech": "SATELLITE",
    "upgrade": "NULL_NA",
    "gnaf_pid": "GANSW716758206"
   }
  },
  {
   "type": "Feature",
   "geometry": {
    "type": "Point",
    "coordinates": [
     149.66552529,
     -35.50106021
    ]
   },
   "properties": {
    "name": "1002 FARRINGDON ROAD FARRINGDON 2622",
    "locID": "LOC000033800170",
    "tech": "WIRELESS",
    "upgrade": "NULL_NA",
    "gnaf_pid": "GANSW717951055"
   }
  },
  {
   "type": "Feature",
   "geometry": {
    "type": "Point",
    "coordinates": [
     149.65237404,
     -35.50113636
    ]
   },
   "properties": {
    "name": "1070 FARRINGDON ROAD FARRINGDON 2622",
    "locID": "LOC100078129146",
    "tech": "WIRELESS",
    "upgrade": "NULL_NA",
    "gnaf_pid": "GANSW717951056"
   }
  },
  {
   "type": "Feature",
   "geometry": {
    "type": "Point",
    "coordinates": [
     149.66971786,
     -35.49359953
    ]
   },
   "properties": {
    "name": "940 FARRINGDON ROAD FARRINGDON 2622",
    "locID": "LOC000025449184",
    "tech": "WIRELESS",
    "upgrade": "NULL_NA",
    "gnaf_pid": "GANSW717951058"
   }
  },
  {
   "type": "Feature",
   "geometry": {
    "type": "Point",
    "coordinates": [
     149.66710332,
     -35.51956428
    ]
   },
   "properties": {
    "name": "67 MOUNT ELRINGTON ROAD FARRINGDON 2622",
    "locID": "LOC000020908570",
    "tech": "SATELLITE",
    "upgrade": "NULL_NA",
    "gnaf_pid": "GANSW718009927"
   }
  },
  {
   "type": "Feature",
   "geometry": {
    "type": "Point",
    "coordinates": [
     149.66363152,
     -35.49523291
    ]
   },
   "properties": {
    "name": "954 FARRINGDON ROAD FARRINGDON 2622",
    "locID": "LOC000148386820",
    "tech": "WIRELESS",
    "upgrade": "NULL_NA",
    "gnaf_pid": "GANSW718599658"
   }
  },
  {
   "type": "Feature",
   "geometry": {
    "type": "Point",
    "coordinates": [
     149.64076555,
     -35.5273281
    ]
   },
   "properties": {
    "name": "296 MOUNT ELRINGTON ROAD FARRINGDON 2622",
    "locID": "LOC000148387956",
    "tech": "SATELLITE",
    "upgrade": "NULL_NA",
    "gnaf_pid": "GANSW718603842"
   }
  }
 ]
}