{
 "type": "FeatureCollection",
 "generated": "2024-07-09T23:46:25.752384",
 "suburb": "GALA VALE",
 "features": [
  {
   "type": "Feature",
   "geometry": {
    "type": "Point",
    "coordinates": [
     145.82278371,
     -34.96261774
    ]
   },
   "properties": {
    "name": "1578 CADELL ROAD GALA VALE 2716",
    "locID": "LOC000121823324",
    "tech": "SATELLITE",
    "upgrade": "NULL_NA",
    "gnaf_pid": "GANSW718065862",
    "tech_change_status": "Not Planned"
   }
  },
  {
   "type": "Feature",
   "geometry": {
    "type": "Point",
    "coordinates": [
     145.79504591,
     -34.98477423
    ]
   },
   "properties": {
    "name": "884 CADELL ROAD GALA VALE 2716",
    "locID": "LOC000121819509",
    "tech": "SATELLITE",
    "upgrade": "NULL_NA",
    "gnaf_pid": "GANSW718065863",
    "tech_change_status": "Not Planned"
   }
  },
  {
   "type": "Feature",
   "geometry": {
    "type": "Point",
    "coordinates": [
     145.75722304,
     -34.96693491
    ]
   },
   "properties": {
    "name": "231 GALA VALE ROAD GALA VALE 2716",
    "locID": "LOC000121830479",
    "tech": "SATELLITE",
    "upgrade": "NULL_NA",
    "gnaf_pid": "GANSW718068329",
    "tech_change_status": "Not Planned"
   }
  },
  {
   "type": "Feature",
   "geometry": {
    "type": "Point",
    "coordinates": [
     145.7923526,
     -34.94745455
    ]
   },
   "properties": {
    "name": "1307 CADELL ROAD GALA VALE 2716",
    "locID": "LOC000121821305",
    "tech": "SATELLITE",
    "upgrade": "NULL_NA",
    "gnaf_pid": "GANSW718259088",
    "tech_change_status": "Not Planned"
   }
  },
  {
   "type": "Feature",
   "geometry": {
    "type": "Point",
    "coordinates": [
     145.77388225,
     -34.95057703
    ]
   },
   "properties": {
    "name": "1189 CADELL ROAD GALA VALE 2716",
    "locID": "LOC000121817011",
    "tech": "SATELLITE",
    "upgrade": "NULL_NA",
    "gnaf_pid": "GANSW718351204",
    "tech_change_status": "Not Planned"
   }
  },
  {
   "type": "Feature",
   "geometry": {
    "type": "Point",
    "coordinates": [
     145.72358352,
     -34.94699635
    ]
   },
   "properties": {
    "name": "629 STUD PARK NORTH ROAD GALA VALE 2716",
    "locID": "LOC100081172041",
    "tech": "SATELLITE",
    "upgrade": "NULL_NA",
    "gnaf_pid": "GANSW718649579",
    "tech_change_status": "Not Planned"
   }
  },
  {
   "type": "Feature",
   "geometry": {
    "type": "Point",
    "coordinates": [
     145.77201237,
     -34.98452965
    ]
   },
   "properties": {
    "name": "1 CADELL ROAD GALA VALE 2716",
    "locID": "LOC100076632192",
    "tech": "SATELLITE",
    "upgrade": "NULL_NA",
    "gnaf_pid": "GANSW720089082",
    "tech_change_status": "Not Planned"
   }
  }
 ]
}