{
 "type": "FeatureCollection",
 "generated": "2023-11-14T17:51:29.728833",
 "suburb": "GALA VALE",
 "features": [
  {
   "type": "Feature",
   "geometry": {
    "type": "Point",
    "coordinates": [
     145.79149729,
     -34.94327588
    ]
   },
   "properties": {
    "name": "1308 CADELL ROAD GALA VALE 2716",
    "locID": "ChIJRf-VzfoWIGsRubpbFGHCXlU",
    "tech": "SATELLITE",
    "upgrade": "UNKNOWN",
    "gnaf_pid": "GANSW718065861"
   }
  },
  {
   "type": "Feature",
   "geometry": {
    "type": "Point",
    "coordinates": [
     145.82278371,
     -34.96261774
    ]
   },
   "properties": {
    "name": "1578 CADELL ROAD GALA VALE 2716",
    "locID": "LOC000121823324",
    "tech": "SATELLITE",
    "upgrade": "NULL_NA",
    "gnaf_pid": "GANSW718065862"
   }
  },
  {
   "type": "Feature",
   "geometry": {
    "type": "Point",
    "coordinates": [
     145.79504591,
     -34.98477423
    ]
   },
   "properties": {
    "name": "884 CADELL ROAD GALA VALE 2716",
    "locID": "LOC000121819509",
    "tech": "SATELLITE",
    "upgrade": "NULL_NA",
    "gnaf_pid": "GANSW718065863"
   }
  },
  {
   "type": "Feature",
   "geometry": {
    "type": "Point",
    "coordinates": [
     145.75722304,
     -34.96693491
    ]
   },
   "properties": {
    "name": "231 GALA VALE ROAD GALA VALE 2716",
    "locID": "LOC000121830479",
    "tech": "SATELLITE",
    "upgrade": "NULL_NA",
    "gnaf_pid": "GANSW718068329"
   }
  },
  {
   "type": "Feature",
   "geometry": {
    "type": "Point",
    "coordinates": [
     145.7923526,
     -34.94745455
    ]
   },
   "properties": {
    "name": "1307 CADELL ROAD GALA VALE 2716",
    "locID": "LOC000121821305",
    "tech": "SATELLITE",
    "upgrade": "NULL_NA",
    "gnaf_pid": "GANSW718259088"
   }
  },
  {
   "type": "Feature",
   "geometry": {
    "type": "Point",
    "coordinates": [
     145.77388225,
     -34.95057703
    ]
   },
   "properties": {
    "name": "1189 CADELL ROAD GALA VALE 2716",
    "locID": "LOC000121817011",
    "tech": "SATELLITE",
    "upgrade": "NULL_NA",
    "gnaf_pid": "GANSW718351204"
   }
  },
  {
   "type": "Feature",
   "geometry": {
    "type": "Point",
    "coordinates": [
     145.72358352,
     -34.94699635
    ]
   },
   "properties": {
    "name": "629 STUD PARK NORTH ROAD GALA VALE 2716",
    "locID": "ChIJCS-6RHsRIGsRjsYE4AC6Cm4",
    "tech": "SATELLITE",
    "upgrade": "UNKNOWN",
    "gnaf_pid": "GANSW718649579"
   }
  },
  {
   "type": "Feature",
   "geometry": {
    "type": "Point",
    "coordinates": [
     145.77201237,
     -34.98452965
    ]
   },
   "properties": {
    "name": "1 CADELL ROAD GALA VALE 2716",
    "locID": "LOC100076632192",
    "tech": "SATELLITE",
    "upgrade": "NULL_NA",
    "gnaf_pid": "GANSW720089082"
   }
  }
 ]
}