{
 "type": "FeatureCollection",
 "generated": "2024-07-31T01:31:36.190676",
 "suburb": "GINGHI",
 "features": [
  {
   "type": "Feature",
   "geometry": {
    "type": "Point",
    "coordinates": [
     150.08783546,
     -32.59007927
    ]
   },
   "properties": {
    "name": "5468 BYLONG VALLEY WAY GINGHI 2849",
    "locID": "LOC000142356043",
    "tech": "SATELLITE",
    "upgrade": "NULL_NA",
    "gnaf_pid": "GANSW709195170",
    "tech_change_status": "Not Planned"
   }
  },
  {
   "type": "Feature",
   "geometry": {
    "type": "Point",
    "coordinates": [
     150.07303793,
     -32.57760215
    ]
   },
   "properties": {
    "name": "188 GINGHI ROAD GINGHI 2849",
    "locID": "LOC100078070007",
    "tech": "SATELLITE",
    "upgrade": "NULL_NA",
    "gnaf_pid": "GANSW716511793",
    "tech_change_status": "Not Planned"
   }
  },
  {
   "type": "Feature",
   "geometry": {
    "type": "Point",
    "coordinates": [
     150.07533576,
     -32.59988529
    ]
   },
   "properties": {
    "name": "5243 BYLONG VALLEY WAY GINGHI 2849",
    "locID": "LOC000094134703",
    "tech": "SATELLITE",
    "upgrade": "NULL_NA",
    "gnaf_pid": "GANSW717618096",
    "tech_change_status": "Not Planned"
   }
  },
  {
   "type": "Feature",
   "geometry": {
    "type": "Point",
    "coordinates": [
     150.08188766,
     -32.58005205
    ]
   },
   "properties": {
    "name": "109 GINGHI ROAD GINGHI 2849",
    "locID": "LOC000122475398",
    "tech": "SATELLITE",
    "upgrade": "NULL_NA",
    "gnaf_pid": "GANSW717618860",
    "tech_change_status": "Not Planned"
   }
  },
  {
   "type": "Feature",
   "geometry": {
    "type": "Point",
    "coordinates": [
     150.04831039,
     -32.58603822
    ]
   },
   "properties": {
    "name": "488 GINGHI ROAD GINGHI 2849",
    "locID": "LOC000122463756",
    "tech": "SATELLITE",
    "upgrade": "NULL_NA",
    "gnaf_pid": "GANSW717701204",
    "tech_change_status": "Not Planned"
   }
  },
  {
   "type": "Feature",
   "geometry": {
    "type": "Point",
    "coordinates": [
     150.02306289,
     -32.59330329
    ]
   },
   "properties": {
    "name": "726 GINGHI ROAD GINGHI 2849",
    "locID": "LOC000122452608",
    "tech": "SATELLITE",
    "upgrade": "NULL_NA",
    "gnaf_pid": "GANSW717952214",
    "tech_change_status": "Not Planned"
   }
  },
  {
   "type": "Feature",
   "geometry": {
    "type": "Point",
    "coordinates": [
     150.06013786,
     -32.58609274
    ]
   },
   "properties": {
    "name": "7425 GINGHI ROAD GINGHI 2849",
    "locID": "LOC000174110225",
    "tech": "SATELLITE",
    "upgrade": "NULL_NA",
    "gnaf_pid": "GANSW719906223",
    "tech_change_status": "Not Planned"
   }
  },
  {
   "type": "Feature",
   "geometry": {
    "type": "Point",
    "coordinates": [
     150.06135419,
     -32.57842641
    ]
   },
   "properties": {
    "name": "284 GINGHI ROAD GINGHI 2849",
    "locID": "LOC000174110225",
    "tech": "SATELLITE",
    "upgrade": "NULL_NA",
    "gnaf_pid": "GANSW720809712",
    "tech_change_status": "Not Planned"
   }
  }
 ]
}