{
 "type": "FeatureCollection",
 "generated": "2024-01-30T01:59:34.402678",
 "suburb": "GOOANDRA",
 "features": [
  {
   "type": "Feature",
   "geometry": {
    "type": "Point",
    "coordinates": [
     148.49638253,
     -35.81401073
    ]
   },
   "properties": {
    "name": "9650 SNOWY MOUNTAINS HIGHWAY GOOANDRA 2629",
    "locID": "Ejc5NjUwIFNub3d5IE1vdW50YWlucyBId3ksIEFkYW1pbmFieSBOU1cgMjYyOSwgQXVzdHJhbGlhIjESLwoUChIJ_56weqY_PWsR4xAtsSsxkJMQsksqFAoSCTGQ45TQUT1rERb9rl147pbt",
    "tech": "SATELLITE",
    "upgrade": "UNKNOWN",
    "gnaf_pid": "GANSW721238427"
   }
  },
  {
   "type": "Feature",
   "geometry": {
    "type": "Point",
    "coordinates": [
     148.49962012,
     -35.79632658
    ]
   },
   "properties": {
    "name": "9851 SNOWY MOUNTAINS HIGHWAY GOOANDRA 2629",
    "locID": "Ejc5ODUxIFNub3d5IE1vdW50YWlucyBId3ksIEFkYW1pbmFieSBOU1cgMjYyOSwgQXVzdHJhbGlhIjESLwoUChIJ_56weqY_PWsR4xAtsSsxkJMQ-0wqFAoSCTGQ45TQUT1rERb9rl147pbt",
    "tech": "SATELLITE",
    "upgrade": "UNKNOWN",
    "gnaf_pid": "GANSW721244206"
   }
  },
  {
   "type": "Feature",
   "geometry": {
    "type": "Point",
    "coordinates": [
     148.65809443,
     -35.7981483
    ]
   },
   "properties": {
    "name": "1703 TANTANGARA ROAD GOOANDRA 2629",
    "locID": "EitUYW50YW5nYXJhIFJkLCBHb29hbmRyYSBOU1cgMjYyNywgQXVzdHJhbGlhIi4qLAoUChIJAR7npcpGPWsRpOo6R2aPms0SFAoSCevkeYgbRj1rEcpW4fb2f66G",
    "tech": "SATELLITE",
    "upgrade": "UNKNOWN",
    "gnaf_pid": "GANSW721249278"
   }
  }
 ]
}