{
 "type": "FeatureCollection",
 "generated": "2024-07-29T08:41:43.702465",
 "suburb": "GOSTWYCK",
 "features": [
  {
   "type": "Feature",
   "geometry": {
    "type": "Point",
    "coordinates": [
     151.63570235,
     -30.68437774
    ]
   },
   "properties": {
    "name": "183 GOSTWYCK WAR SERVICE ROAD GOSTWYCK 2358",
    "locID": "LOC000054830342",
    "tech": "WIRELESS",
    "upgrade": "NULL_NA",
    "gnaf_pid": "GANSW712107792",
    "tech_change_status": "Not Planned",
    "program_type": "Fixed Wireless and Satellite Upgrade Program",
    "target_eligibility_quarter": "Dec 2024"
   }
  },
  {
   "type": "Feature",
   "geometry": {
    "type": "Point",
    "coordinates": [
     151.64447671,
     -30.6813151
    ]
   },
   "properties": {
    "name": "310 GOSTWYCK WAR SERVICE ROAD GOSTWYCK 2358",
    "locID": "LOC000016270583",
    "tech": "SATELLITE",
    "upgrade": "NULL_NA",
    "gnaf_pid": "GANSW712107793",
    "tech_change_status": "Not Planned"
   }
  },
  {
   "type": "Feature",
   "geometry": {
    "type": "Point",
    "coordinates": [
     151.58739548,
     -30.69487819
    ]
   },
   "properties": {
    "name": "1081 GOSTWYCK ROAD GOSTWYCK 2358",
    "locID": "LOC000120829855",
    "tech": "SATELLITE",
    "upgrade": "NULL_NA",
    "gnaf_pid": "GANSW715877654",
    "tech_change_status": "Not Planned"
   }
  },
  {
   "type": "Feature",
   "geometry": {
    "type": "Point",
    "coordinates": [
     151.58697022,
     -30.69030298
    ]
   },
   "properties": {
    "name": "979 GOSTWYCK ROAD GOSTWYCK 2358",
    "locID": "LOC000120838531",
    "tech": "SATELLITE",
    "upgrade": "NULL_NA",
    "gnaf_pid": "GANSW715877656",
    "tech_change_status": "Not Planned"
   }
  },
  {
   "type": "Feature",
   "geometry": {
    "type": "Point",
    "coordinates": [
     151.63246874,
     -30.69956384
    ]
   },
   "properties": {
    "name": "1499 GOSTWYCK ROAD GOSTWYCK 2358",
    "locID": "LOC000046706871",
    "tech": "SATELLITE",
    "upgrade": "NULL_NA",
    "gnaf_pid": "GANSW716608114",
    "tech_change_status": "Not Planned"
   }
  },
  {
   "type": "Feature",
   "geometry": {
    "type": "Point",
    "coordinates": [
     151.59584491,
     -30.69742932
    ]
   },
   "properties": {
    "name": "1170 GOSTWYCK ROAD GOSTWYCK 2358",
    "locID": "LOC000120829893",
    "tech": "SATELLITE",
    "upgrade": "NULL_NA",
    "gnaf_pid": "GANSW718099470",
    "tech_change_status": "Not Planned"
   }
  }
 ]
}