{
 "type": "FeatureCollection",
 "generated": "2024-01-27T09:08:49.024949",
 "suburb": "GOSTWYCK",
 "features": [
  {
   "type": "Feature",
   "geometry": {
    "type": "Point",
    "coordinates": [
     151.63570235,
     -30.68437774
    ]
   },
   "properties": {
    "name": "183 GOSTWYCK WAR SERVICE ROAD GOSTWYCK 2358",
    "locID": "LOC000054830342",
    "tech": "WIRELESS",
    "upgrade": "NULL_NA",
    "gnaf_pid": "GANSW712107792"
   }
  },
  {
   "type": "Feature",
   "geometry": {
    "type": "Point",
    "coordinates": [
     151.64447671,
     -30.6813151
    ]
   },
   "properties": {
    "name": "310 GOSTWYCK WAR SERVICE ROAD GOSTWYCK 2358",
    "locID": "LOC000016270583",
    "tech": "SATELLITE",
    "upgrade": "NULL_NA",
    "gnaf_pid": "GANSW712107793"
   }
  },
  {
   "type": "Feature",
   "geometry": {
    "type": "Point",
    "coordinates": [
     151.58739548,
     -30.69487819
    ]
   },
   "properties": {
    "name": "1081 GOSTWYCK ROAD GOSTWYCK 2358",
    "locID": "LOC000120829855",
    "tech": "SATELLITE",
    "upgrade": "NULL_NA",
    "gnaf_pid": "GANSW715877654"
   }
  },
  {
   "type": "Feature",
   "geometry": {
    "type": "Point",
    "coordinates": [
     151.58697022,
     -30.69030298
    ]
   },
   "properties": {
    "name": "979 GOSTWYCK ROAD GOSTWYCK 2358",
    "locID": "LOC000120838531",
    "tech": "SATELLITE",
    "upgrade": "NULL_NA",
    "gnaf_pid": "GANSW715877656"
   }
  },
  {
   "type": "Feature",
   "geometry": {
    "type": "Point",
    "coordinates": [
     151.66420272,
     -30.68444995
    ]
   },
   "properties": {
    "name": "60 MIHI ROAD GOSTWYCK 2358",
    "locID": "ChIJw7GW2YSXn2sR-gVeFVR-ZFE",
    "tech": "SATELLITE",
    "upgrade": "UNKNOWN",
    "gnaf_pid": "GANSW716238212"
   }
  },
  {
   "type": "Feature",
   "geometry": {
    "type": "Point",
    "coordinates": [
     151.63246874,
     -30.69956384
    ]
   },
   "properties": {
    "name": "1499 GOSTWYCK ROAD GOSTWYCK 2358",
    "locID": "LOC000046706871",
    "tech": "SATELLITE",
    "upgrade": "NULL_NA",
    "gnaf_pid": "GANSW716608114"
   }
  },
  {
   "type": "Feature",
   "geometry": {
    "type": "Point",
    "coordinates": [
     151.59584491,
     -30.69742932
    ]
   },
   "properties": {
    "name": "1170 GOSTWYCK ROAD GOSTWYCK 2358",
    "locID": "LOC000120829893",
    "tech": "SATELLITE",
    "upgrade": "NULL_NA",
    "gnaf_pid": "GANSW718099470"
   }
  },
  {
   "type": "Feature",
   "geometry": {
    "type": "Point",
    "coordinates": [
     151.62821312,
     -30.75147472
    ]
   },
   "properties": {
    "name": "2290 HILLVIEW ROAD GOSTWYCK 2358",
    "locID": "ChIJ3yeJrx-Un2sRV6YhTFItR8o",
    "tech": "SATELLITE",
    "upgrade": "UNKNOWN",
    "gnaf_pid": "GANSW719461461"
   }
  }
 ]
}