{
 "type": "FeatureCollection",
 "generated": "2024-07-09T08:26:53.606422",
 "suburb": "GRAGIN",
 "features": [
  {
   "type": "Feature",
   "geometry": {
    "type": "Point",
    "coordinates": [
     150.78490339,
     -29.54494046
    ]
   },
   "properties": {
    "name": "178 GRAGIN BOUNDARY ROAD GRAGIN 2403",
    "locID": "LOC000002228865",
    "tech": "SATELLITE",
    "upgrade": "NULL_NA",
    "gnaf_pid": "GANSW717065240",
    "tech_change_status": "Not Planned"
   }
  },
  {
   "type": "Feature",
   "geometry": {
    "type": "Point",
    "coordinates": [
     150.76817027,
     -29.5562016
    ]
   },
   "properties": {
    "name": "24 GRAGIN BOUNDARY ROAD GRAGIN 2403",
    "locID": "LOC000094013428",
    "tech": "SATELLITE",
    "upgrade": "NULL_NA",
    "gnaf_pid": "GANSW717065241",
    "tech_change_status": "Not Planned"
   }
  },
  {
   "type": "Feature",
   "geometry": {
    "type": "Point",
    "coordinates": [
     150.79659679,
     -29.56005893
    ]
   },
   "properties": {
    "name": "730 LECOIN ROAD GRAGIN 2403",
    "locID": "LOC000120886073",
    "tech": "SATELLITE",
    "upgrade": "NULL_NA",
    "gnaf_pid": "GANSW717067092",
    "tech_change_status": "Not Planned"
   }
  },
  {
   "type": "Feature",
   "geometry": {
    "type": "Point",
    "coordinates": [
     150.77648689,
     -29.56269715
    ]
   },
   "properties": {
    "name": "907 LECOIN ROAD GRAGIN 2403",
    "locID": "LOC000120888671",
    "tech": "SATELLITE",
    "upgrade": "NULL_NA",
    "gnaf_pid": "GANSW717067093",
    "tech_change_status": "Not Planned"
   }
  },
  {
   "type": "Feature",
   "geometry": {
    "type": "Point",
    "coordinates": [
     150.80353522,
     -29.53011844
    ]
   },
   "properties": {
    "name": "86 GRAGIN BOUNDARY ROAD GRAGIN 2403",
    "locID": "LOC000076504141",
    "tech": "SATELLITE",
    "upgrade": "NULL_NA",
    "gnaf_pid": "GANSW717080595",
    "tech_change_status": "Not Planned"
   }
  },
  {
   "type": "Feature",
   "geometry": {
    "type": "Point",
    "coordinates": [
     150.83056041,
     -29.52159324
    ]
   },
   "properties": {
    "name": "730 GRAGIN BOUNDARY ROAD GRAGIN 2403",
    "locID": "LOC000025334814",
    "tech": "SATELLITE",
    "upgrade": "NULL_NA",
    "gnaf_pid": "GANSW717726344",
    "tech_change_status": "Not Planned"
   }
  }
 ]
}