{
 "type": "FeatureCollection",
 "generated": "2024-01-25T06:37:26.294398",
 "suburb": "HACKS FERRY",
 "features": [
  {
   "type": "Feature",
   "geometry": {
    "type": "Point",
    "coordinates": [
     152.8377263,
     -31.32624413
    ]
   },
   "properties": {
    "name": "552 HACKS FERRY ROAD HACKS FERRY 2441",
    "locID": "LOC000055761488",
    "tech": "WIRELESS",
    "upgrade": "NULL_NA",
    "gnaf_pid": "GANSW709343043"
   }
  },
  {
   "type": "Feature",
   "geometry": {
    "type": "Point",
    "coordinates": [
     152.8209527,
     -31.31949775
    ]
   },
   "properties": {
    "name": "502 HACKS FERRY ROAD HACKS FERRY 2441",
    "locID": "ChIJL-h_e4EHnmsRh0GgZZ-995I",
    "tech": "WIRELESS",
    "upgrade": "UNKNOWN",
    "gnaf_pid": "GANSW709343044"
   }
  },
  {
   "type": "Feature",
   "geometry": {
    "type": "Point",
    "coordinates": [
     152.83786568,
     -31.32622414
    ]
   },
   "properties": {
    "name": "540 HACKS FERRY ROAD HACKS FERRY 2441",
    "locID": "ChIJTet6cYL9nWsRQuYQo91icN4",
    "tech": "SATELLITE",
    "upgrade": "UNKNOWN",
    "gnaf_pid": "GANSW716876077"
   }
  },
  {
   "type": "Feature",
   "geometry": {
    "type": "Point",
    "coordinates": [
     152.80488469,
     -31.32756742
    ]
   },
   "properties": {
    "name": "100 HACKS FERRY ROAD HACKS FERRY 2441",
    "locID": "LOC000018765577",
    "tech": "WIRELESS",
    "upgrade": "NULL_NA",
    "gnaf_pid": "GANSW716923425"
   }
  },
  {
   "type": "Feature",
   "geometry": {
    "type": "Point",
    "coordinates": [
     152.80557415,
     -31.32475044
    ]
   },
   "properties": {
    "name": "94 HACKS FERRY ROAD HACKS FERRY 2441",
    "locID": "EjI5NCBIYWNrcyBGZXJyeSBSZCwgSGFja3MgRmVycnkgTlNXIDI0NDEsIEF1c3RyYWxpYSIwEi4KFAoSCYsHzbN3B55rET1d6vVgD1gXEF4qFAoSCbfuM4B4B55rEbu4lHoBRAmb",
    "tech": "WIRELESS",
    "upgrade": "UNKNOWN",
    "gnaf_pid": "GANSW716923426"
   }
  },
  {
   "type": "Feature",
   "geometry": {
    "type": "Point",
    "coordinates": [
     152.8092608,
     -31.3243988
    ]
   },
   "properties": {
    "name": "130 HACKS FERRY ROAD HACKS FERRY 2441",
    "locID": "LOC000035691431",
    "tech": "WIRELESS",
    "upgrade": "NULL_NA",
    "gnaf_pid": "GANSW717141198"
   }
  },
  {
   "type": "Feature",
   "geometry": {
    "type": "Point",
    "coordinates": [
     152.81513867,
     -31.32316029
    ]
   },
   "properties": {
    "name": "195 HACKS FERRY ROAD HACKS FERRY 2441",
    "locID": "LOC100077363162",
    "tech": "WIRELESS",
    "upgrade": "NULL_NA",
    "gnaf_pid": "GANSW717141199"
   }
  },
  {
   "type": "Feature",
   "geometry": {
    "type": "Point",
    "coordinates": [
     152.8043344,
     -31.32855509
    ]
   },
   "properties": {
    "name": "16 HACKS FERRY ROAD HACKS FERRY 2441",
    "locID": "LOC000052564905",
    "tech": "WIRELESS",
    "upgrade": "NULL_NA",
    "gnaf_pid": "GANSW717874325"
   }
  },
  {
   "type": "Feature",
   "geometry": {
    "type": "Point",
    "coordinates": [
     152.82082261,
     -31.31966248
    ]
   },
   "properties": {
    "name": "256 HACKS FERRY ROAD HACKS FERRY 2441",
    "locID": "LOC100077363158",
    "tech": "WIRELESS",
    "upgrade": "NULL_NA",
    "gnaf_pid": "GANSW718725696"
   }
  },
  {
   "type": "Feature",
   "geometry": {
    "type": "Point",
    "coordinates": [
     152.84047874,
     -31.31973395
    ]
   },
   "properties": {
    "name": "414 HACKS FERRY ROAD HACKS FERRY 2441",
    "locID": "LOC000150116825",
    "tech": "SATELLITE",
    "upgrade": "NULL_NA",
    "gnaf_pid": "GANSW718844119"
   }
  },
  {
   "type": "Feature",
   "geometry": {
    "type": "Point",
    "coordinates": [
     152.83800464,
     -31.32695593
    ]
   },
   "properties": {
    "name": "534 HACKS FERRY ROAD HACKS FERRY 2441",
    "locID": "LOC000150116839",
    "tech": "WIRELESS",
    "upgrade": "NULL_NA",
    "gnaf_pid": "GANSW718844120"
   }
  },
  {
   "type": "Feature",
   "geometry": {
    "type": "Point",
    "coordinates": [
     152.8209527,
     -31.31949775
    ]
   },
   "properties": {
    "name": "164 HACKS FERRY ROAD HACKS FERRY 2441",
    "locID": "ChIJL-h_e4EHnmsRtIqQ20wdxZg",
    "tech": "WIRELESS",
    "upgrade": "UNKNOWN",
    "gnaf_pid": "GANSW720395828"
   }
  }
 ]
}