{
 "type": "FeatureCollection",
 "generated": "2024-07-28T01:07:55.423772",
 "suburb": "HACKS FERRY",
 "features": [
  {
   "type": "Feature",
   "geometry": {
    "type": "Point",
    "coordinates": [
     152.8377263,
     -31.32624413
    ]
   },
   "properties": {
    "name": "552 HACKS FERRY ROAD HACKS FERRY 2441",
    "locID": "LOC000055761488",
    "tech": "WIRELESS",
    "upgrade": "NULL_NA",
    "gnaf_pid": "GANSW709343043",
    "tech_change_status": "Not Planned",
    "program_type": "Fixed Wireless and Satellite Upgrade Program",
    "target_eligibility_quarter": "Dec 2024"
   }
  },
  {
   "type": "Feature",
   "geometry": {
    "type": "Point",
    "coordinates": [
     152.80488469,
     -31.32756742
    ]
   },
   "properties": {
    "name": "100 HACKS FERRY ROAD HACKS FERRY 2441",
    "locID": "LOC000018765577",
    "tech": "WIRELESS",
    "upgrade": "NULL_NA",
    "gnaf_pid": "GANSW716923425",
    "tech_change_status": "Not Planned",
    "program_type": "Fixed Wireless and Satellite Upgrade Program",
    "target_eligibility_quarter": "Dec 2024"
   }
  },
  {
   "type": "Feature",
   "geometry": {
    "type": "Point",
    "coordinates": [
     152.8092608,
     -31.3243988
    ]
   },
   "properties": {
    "name": "130 HACKS FERRY ROAD HACKS FERRY 2441",
    "locID": "LOC000035691431",
    "tech": "WIRELESS",
    "upgrade": "NULL_NA",
    "gnaf_pid": "GANSW717141198",
    "tech_change_status": "Not Planned",
    "program_type": "Fixed Wireless and Satellite Upgrade Program",
    "target_eligibility_quarter": "Dec 2024"
   }
  },
  {
   "type": "Feature",
   "geometry": {
    "type": "Point",
    "coordinates": [
     152.81513867,
     -31.32316029
    ]
   },
   "properties": {
    "name": "195 HACKS FERRY ROAD HACKS FERRY 2441",
    "locID": "LOC100077363162",
    "tech": "WIRELESS",
    "upgrade": "NULL_NA",
    "gnaf_pid": "GANSW717141199",
    "tech_change_status": "Not Planned",
    "program_type": "Fixed Wireless and Satellite Upgrade Program",
    "target_eligibility_quarter": "Dec 2024"
   }
  },
  {
   "type": "Feature",
   "geometry": {
    "type": "Point",
    "coordinates": [
     152.8043344,
     -31.32855509
    ]
   },
   "properties": {
    "name": "16 HACKS FERRY ROAD HACKS FERRY 2441",
    "locID": "LOC000052564905",
    "tech": "WIRELESS",
    "upgrade": "NULL_NA",
    "gnaf_pid": "GANSW717874325",
    "tech_change_status": "Not Planned",
    "program_type": "Fixed Wireless and Satellite Upgrade Program",
    "target_eligibility_quarter": "Dec 2024"
   }
  },
  {
   "type": "Feature",
   "geometry": {
    "type": "Point",
    "coordinates": [
     152.82082261,
     -31.31966248
    ]
   },
   "properties": {
    "name": "256 HACKS FERRY ROAD HACKS FERRY 2441",
    "locID": "LOC100077363158",
    "tech": "WIRELESS",
    "upgrade": "NULL_NA",
    "gnaf_pid": "GANSW718725696",
    "tech_change_status": "Not Planned",
    "program_type": "Fixed Wireless and Satellite Upgrade Program",
    "target_eligibility_quarter": "Dec 2024"
   }
  },
  {
   "type": "Feature",
   "geometry": {
    "type": "Point",
    "coordinates": [
     152.84047874,
     -31.31973395
    ]
   },
   "properties": {
    "name": "414 HACKS FERRY ROAD HACKS FERRY 2441",
    "locID": "LOC000150116825",
    "tech": "WIRELESS",
    "upgrade": "NULL_NA",
    "gnaf_pid": "GANSW718844119",
    "tech_change_status": "Not Planned",
    "program_type": "Fixed Wireless and Satellite Upgrade Program",
    "target_eligibility_quarter": "Dec 2024"
   }
  },
  {
   "type": "Feature",
   "geometry": {
    "type": "Point",
    "coordinates": [
     152.83800464,
     -31.32695593
    ]
   },
   "properties": {
    "name": "534 HACKS FERRY ROAD HACKS FERRY 2441",
    "locID": "LOC000150116839",
    "tech": "WIRELESS",
    "upgrade": "NULL_NA",
    "gnaf_pid": "GANSW718844120",
    "tech_change_status": "Not Planned",
    "program_type": "Fixed Wireless and Satellite Upgrade Program",
    "target_eligibility_quarter": "Dec 2024"
   }
  },
  {
   "type": "Feature",
   "geometry": {
    "type": "Point",
    "coordinates": [
     152.8209527,
     -31.31949775
    ]
   },
   "properties": {
    "name": "164 HACKS FERRY ROAD HACKS FERRY 2441",
    "locID": "LOC100082815356",
    "tech": "SATELLITE",
    "upgrade": "NULL_NA",
    "gnaf_pid": "GANSW720395828",
    "tech_change_status": "Not Planned"
   }
  },
  {
   "type": "Feature",
   "geometry": {
    "type": "Point",
    "coordinates": [
     152.82438231,
     -31.33753298
    ]
   },
   "properties": {
    "name": "552 THE HATCH ROAD HACKS FERRY 2441",
    "locID": "LOC100077291903",
    "tech": "WIRELESS",
    "upgrade": "NULL_NA",
    "gnaf_pid": "GANSW721447091",
    "tech_change_status": "Not Planned",
    "program_type": "Fixed Wireless and Satellite Upgrade Program",
    "target_eligibility_quarter": "Dec 2024"
   }
  }
 ]
}