{
 "type": "FeatureCollection",
 "generated": "2024-07-09T10:36:22.213313",
 "suburb": "HEIFER STATION",
 "features": [
  {
   "type": "Feature",
   "geometry": {
    "type": "Point",
    "coordinates": [
     152.646926,
     -29.4763285
    ]
   },
   "properties": {
    "name": "1020 GORGE ROAD HEIFER STATION 2460",
    "locID": "LOC000108561582",
    "tech": "SATELLITE",
    "upgrade": "NULL_NA",
    "gnaf_pid": "GANSW716733172",
    "tech_change_status": "Not Planned"
   }
  },
  {
   "type": "Feature",
   "geometry": {
    "type": "Point",
    "coordinates": [
     152.5657994,
     -29.42088354
    ]
   },
   "properties": {
    "name": "2567 GORGE ROAD HEIFER STATION 2460",
    "locID": "LOC000064670136",
    "tech": "SATELLITE",
    "upgrade": "NULL_NA",
    "gnaf_pid": "GANSW716733175",
    "tech_change_status": "Not Planned"
   }
  },
  {
   "type": "Feature",
   "geometry": {
    "type": "Point",
    "coordinates": [
     152.58182343,
     -29.40847909
    ]
   },
   "properties": {
    "name": "2568 GORGE ROAD HEIFER STATION 2460",
    "locID": "LOC000061848462",
    "tech": "SATELLITE",
    "upgrade": "NULL_NA",
    "gnaf_pid": "GANSW716733176",
    "tech_change_status": "Not Planned"
   }
  },
  {
   "type": "Feature",
   "geometry": {
    "type": "Point",
    "coordinates": [
     152.54498372,
     -29.37784394
    ]
   },
   "properties": {
    "name": "2570 GORGE ROAD HEIFER STATION 2460",
    "locID": "LOC000121208281",
    "tech": "SATELLITE",
    "upgrade": "NULL_NA",
    "gnaf_pid": "GANSW716733177",
    "tech_change_status": "Not Planned"
   }
  },
  {
   "type": "Feature",
   "geometry": {
    "type": "Point",
    "coordinates": [
     152.62177738,
     -29.4460312
    ]
   },
   "properties": {
    "name": "1044 GORGE ROAD HEIFER STATION 2460",
    "locID": "LOC000064670136",
    "tech": "SATELLITE",
    "upgrade": "NULL_NA",
    "gnaf_pid": "GANSW716754024",
    "tech_change_status": "Not Planned"
   }
  },
  {
   "type": "Feature",
   "geometry": {
    "type": "Point",
    "coordinates": [
     152.63843454,
     -29.47626596
    ]
   },
   "properties": {
    "name": "1080 GORGE ROAD HEIFER STATION 2460",
    "locID": "LOC000078070928",
    "tech": "SATELLITE",
    "upgrade": "NULL_NA",
    "gnaf_pid": "GANSW716754025",
    "tech_change_status": "Not Planned"
   }
  }
 ]
}