{
 "type": "FeatureCollection",
 "generated": "2023-11-14T05:43:45.403706",
 "suburb": "HEIFER STATION",
 "features": [
  {
   "type": "Feature",
   "geometry": {
    "type": "Point",
    "coordinates": [
     152.646926,
     -29.4763285
    ]
   },
   "properties": {
    "name": "1020 GORGE ROAD HEIFER STATION 2460",
    "locID": "LOC000108561582",
    "tech": "SATELLITE",
    "upgrade": "NULL_NA",
    "gnaf_pid": "GANSW716733172"
   }
  },
  {
   "type": "Feature",
   "geometry": {
    "type": "Point",
    "coordinates": [
     152.61184597,
     -29.48003635
    ]
   },
   "properties": {
    "name": "1440 GORGE ROAD HEIFER STATION 2460",
    "locID": "ChIJabU70PZwmWsRmNjXtQ1qQbk",
    "tech": "SATELLITE",
    "upgrade": "UNKNOWN",
    "gnaf_pid": "GANSW716733173"
   }
  },
  {
   "type": "Feature",
   "geometry": {
    "type": "Point",
    "coordinates": [
     152.5657994,
     -29.42088354
    ]
   },
   "properties": {
    "name": "2567 GORGE ROAD HEIFER STATION 2460",
    "locID": "LOC000064670136",
    "tech": "SATELLITE",
    "upgrade": "NULL_NA",
    "gnaf_pid": "GANSW716733175"
   }
  },
  {
   "type": "Feature",
   "geometry": {
    "type": "Point",
    "coordinates": [
     152.57245012,
     -29.38975117
    ]
   },
   "properties": {
    "name": "2568 GORGE ROAD HEIFER STATION 2460",
    "locID": "LOC000061848462",
    "tech": "SATELLITE",
    "upgrade": "NULL_NA",
    "gnaf_pid": "GANSW716733176"
   }
  },
  {
   "type": "Feature",
   "geometry": {
    "type": "Point",
    "coordinates": [
     152.54498372,
     -29.37784394
    ]
   },
   "properties": {
    "name": "2570 GORGE ROAD HEIFER STATION 2460",
    "locID": "ChIJM7jRnXd2mWsRNTSrDnMFMaA",
    "tech": "SATELLITE",
    "upgrade": "UNKNOWN",
    "gnaf_pid": "GANSW716733177"
   }
  },
  {
   "type": "Feature",
   "geometry": {
    "type": "Point",
    "coordinates": [
     152.63600877,
     -29.47620439
    ]
   },
   "properties": {
    "name": "743 GORGE ROAD HEIFER STATION 2460",
    "locID": "ChIJ6drTbZ5wmWsRgQsOhlX6OZo",
    "tech": "SATELLITE",
    "upgrade": "UNKNOWN",
    "gnaf_pid": "GANSW716733178"
   }
  },
  {
   "type": "Feature",
   "geometry": {
    "type": "Point",
    "coordinates": [
     152.62177738,
     -29.4460312
    ]
   },
   "properties": {
    "name": "1044 GORGE ROAD HEIFER STATION 2460",
    "locID": "LOC000064670136",
    "tech": "SATELLITE",
    "upgrade": "NULL_NA",
    "gnaf_pid": "GANSW716754024"
   }
  },
  {
   "type": "Feature",
   "geometry": {
    "type": "Point",
    "coordinates": [
     152.63843454,
     -29.47626596
    ]
   },
   "properties": {
    "name": "1080 GORGE ROAD HEIFER STATION 2460",
    "locID": "LOC000078070928",
    "tech": "SATELLITE",
    "upgrade": "NULL_NA",
    "gnaf_pid": "GANSW716754025"
   }
  },
  {
   "type": "Feature",
   "geometry": {
    "type": "Point",
    "coordinates": [
     152.62177738,
     -29.4460312
    ]
   },
   "properties": {
    "name": "2590 GORGE ROAD HEIFER STATION 2460",
    "locID": "ChIJaYf6u0x3mWsR2qxAA528gwc",
    "tech": "SATELLITE",
    "upgrade": "UNKNOWN",
    "gnaf_pid": "GANSW716754026"
   }
  }
 ]
}