{
 "type": "FeatureCollection",
 "generated": "2024-08-21T22:29:03.939523",
 "suburb": "JACKSONS FLAT",
 "features": [
  {
   "type": "Feature",
   "geometry": {
    "type": "Point",
    "coordinates": [
     152.55503946,
     -28.84623834
    ]
   },
   "properties": {
    "name": "239 JACKSONS FLAT ROAD JACKSONS FLAT 2469",
    "locID": "LOC000010091400",
    "tech": "WIRELESS",
    "upgrade": "NULL_NA",
    "gnaf_pid": "GANSW706532557",
    "tech_change_status": "Not Planned",
    "program_type": "Fixed Wireless and Satellite Upgrade Program",
    "target_eligibility_quarter": "NA"
   }
  },
  {
   "type": "Feature",
   "geometry": {
    "type": "Point",
    "coordinates": [
     152.5598975,
     -28.84909676
    ]
   },
   "properties": {
    "name": "296 JACKSONS FLAT ROAD JACKSONS FLAT 2469",
    "locID": "LOC000038088272",
    "tech": "WIRELESS",
    "upgrade": "NULL_NA",
    "gnaf_pid": "GANSW709417907",
    "tech_change_status": "Not Planned",
    "program_type": "Fixed Wireless and Satellite Upgrade Program",
    "target_eligibility_quarter": "NA"
   }
  },
  {
   "type": "Feature",
   "geometry": {
    "type": "Point",
    "coordinates": [
     152.56710812,
     -28.85438994
    ]
   },
   "properties": {
    "name": "1192 TABULAM ROAD JACKSONS FLAT 2469",
    "locID": "LOC000038901519",
    "tech": "WIRELESS",
    "upgrade": "NULL_NA",
    "gnaf_pid": "GANSW709417909",
    "tech_change_status": "Not Planned",
    "program_type": "Fixed Wireless and Satellite Upgrade Program",
    "target_eligibility_quarter": "NA"
   }
  },
  {
   "type": "Feature",
   "geometry": {
    "type": "Point",
    "coordinates": [
     152.54511855,
     -28.8423282
    ]
   },
   "properties": {
    "name": "160 JACKSONS FLAT ROAD JACKSONS FLAT 2469",
    "locID": "LOC100076050355",
    "tech": "WIRELESS",
    "upgrade": "NULL_NA",
    "gnaf_pid": "GANSW716667323",
    "tech_change_status": "Not Planned",
    "program_type": "Fixed Wireless and Satellite Upgrade Program",
    "target_eligibility_quarter": "NA"
   }
  },
  {
   "type": "Feature",
   "geometry": {
    "type": "Point",
    "coordinates": [
     152.57158024,
     -28.86040511
    ]
   },
   "properties": {
    "name": "1252 TABULAM ROAD JACKSONS FLAT 2469",
    "locID": "LOC000071192311",
    "tech": "WIRELESS",
    "upgrade": "NULL_NA",
    "gnaf_pid": "GANSW716690070",
    "tech_change_status": "Not Planned",
    "program_type": "Fixed Wireless and Satellite Upgrade Program",
    "target_eligibility_quarter": "NA"
   }
  },
  {
   "type": "Feature",
   "geometry": {
    "type": "Point",
    "coordinates": [
     152.56543743,
     -28.84801724
    ]
   },
   "properties": {
    "name": "968 TABULAM ROAD JACKSONS FLAT 2469",
    "locID": "LOC000097979853",
    "tech": "WIRELESS",
    "upgrade": "NULL_NA",
    "gnaf_pid": "GANSW716690071",
    "tech_change_status": "Not Planned",
    "program_type": "Fixed Wireless and Satellite Upgrade Program",
    "target_eligibility_quarter": "NA"
   }
  },
  {
   "type": "Feature",
   "geometry": {
    "type": "Point",
    "coordinates": [
     152.56118884,
     -28.82945924
    ]
   },
   "properties": {
    "name": "970 TABULAM ROAD JACKSONS FLAT 2469",
    "locID": "LOC000087543161",
    "tech": "WIRELESS",
    "upgrade": "NULL_NA",
    "gnaf_pid": "GANSW716690072",
    "tech_change_status": "Eligible to Order",
    "program_type": "Fixed Wireless and Satellite Upgrade Program",
    "target_eligibility_quarter": "NA"
   }
  },
  {
   "type": "Feature",
   "geometry": {
    "type": "Point",
    "coordinates": [
     152.54511855,
     -28.8423282
    ]
   },
   "properties": {
    "name": "166 JACKSONS FLAT ROAD JACKSONS FLAT 2469",
    "locID": "LOC000033989603",
    "tech": "WIRELESS",
    "upgrade": "NULL_NA",
    "gnaf_pid": "GANSW720528233",
    "tech_change_status": "Not Planned",
    "program_type": "Fixed Wireless and Satellite Upgrade Program",
    "target_eligibility_quarter": "NA"
   }
  },
  {
   "type": "Feature",
   "geometry": {
    "type": "Point",
    "coordinates": [
     152.56090465,
     -28.83411772
    ]
   },
   "properties": {
    "name": "16 JACKSONS FLAT ROAD JACKSONS FLAT 2469",
    "locID": "LOC100076050355",
    "tech": "WIRELESS",
    "upgrade": "NULL_NA",
    "gnaf_pid": "GANSW720531458",
    "tech_change_status": "Not Planned",
    "program_type": "Fixed Wireless and Satellite Upgrade Program",
    "target_eligibility_quarter": "NA"
   }
  },
  {
   "type": "Feature",
   "geometry": {
    "type": "Point",
    "coordinates": [
     152.55594961,
     -28.84771972
    ]
   },
   "properties": {
    "name": "1 JACKSONS FLAT ROAD JACKSONS FLAT 2469",
    "locID": "LOC000179514903",
    "tech": "WIRELESS",
    "upgrade": "NULL_NA",
    "gnaf_pid": "GANSW721237728",
    "tech_change_status": "Not Planned",
    "program_type": "Fixed Wireless and Satellite Upgrade Program",
    "target_eligibility_quarter": "NA"
   }
  }
 ]
}