{
 "type": "FeatureCollection",
 "generated": "2024-03-07T18:16:59.018882",
 "suburb": "KHATAMBUHL",
 "features": [
  {
   "type": "Feature",
   "geometry": {
    "type": "Point",
    "coordinates": [
     152.00105773,
     -31.79622522
    ]
   },
   "properties": {
    "name": "151 KHATAMBUHL CREEK ROAD KHATAMBUHL 2429",
    "locID": "LOC000104115107",
    "tech": "SATELLITE",
    "upgrade": "NULL_NA",
    "gnaf_pid": "GANSW715929361"
   }
  },
  {
   "type": "Feature",
   "geometry": {
    "type": "Point",
    "coordinates": [
     152.02119166,
     -31.81746097
    ]
   },
   "properties": {
    "name": "219 KHATAMBUHL CREEK ROAD KHATAMBUHL 2429",
    "locID": "LOC100078060098",
    "tech": "SATELLITE",
    "upgrade": "NULL_NA",
    "gnaf_pid": "GANSW717598859"
   }
  },
  {
   "type": "Feature",
   "geometry": {
    "type": "Point",
    "coordinates": [
     152.01308396,
     -31.79880416
    ]
   },
   "properties": {
    "name": "319 KHATAMBUHL CREEK ROAD KHATAMBUHL 2429",
    "locID": "LOC000104115107",
    "tech": "SATELLITE",
    "upgrade": "NULL_NA",
    "gnaf_pid": "GANSW717598862"
   }
  },
  {
   "type": "Feature",
   "geometry": {
    "type": "Point",
    "coordinates": [
     152.01308396,
     -31.79880416
    ]
   },
   "properties": {
    "name": "918 KHATAMBUHL CREEK ROAD KHATAMBUHL 2429",
    "locID": "LOC000142318224",
    "tech": "SATELLITE",
    "upgrade": "NULL_NA",
    "gnaf_pid": "GANSW717598874"
   }
  }
 ]
}