{
 "type": "FeatureCollection",
 "generated": "2024-07-26T22:33:14.420772",
 "suburb": "KULWIN",
 "features": [
  {
   "type": "Feature",
   "geometry": {
    "type": "Point",
    "coordinates": [
     144.77176338,
     -32.22668163
    ]
   },
   "properties": {
    "name": "11408 THE WOOL TRACK KULWIN 2835",
    "locID": "LOC000122366560",
    "tech": "SATELLITE",
    "upgrade": "NULL_NA",
    "gnaf_pid": "GANSW718320791",
    "tech_change_status": "Not Planned"
   }
  },
  {
   "type": "Feature",
   "geometry": {
    "type": "Point",
    "coordinates": [
     145.13733994,
     -32.47394255
    ]
   },
   "properties": {
    "name": "3891 MOOLAH ROAD KULWIN 2835",
    "locID": "LOC000148085737",
    "tech": "SATELLITE",
    "upgrade": "NULL_NA",
    "gnaf_pid": "GANSW718498143",
    "tech_change_status": "Not Planned"
   }
  },
  {
   "type": "Feature",
   "geometry": {
    "type": "Point",
    "coordinates": [
     144.98155723,
     -32.15235402
    ]
   },
   "properties": {
    "name": "10816 THE WOOL TRACK KULWIN 2835",
    "locID": "LOC000148054460",
    "tech": "SATELLITE",
    "upgrade": "NULL_NA",
    "gnaf_pid": "GANSW718501402",
    "tech_change_status": "Not Planned"
   }
  },
  {
   "type": "Feature",
   "geometry": {
    "type": "Point",
    "coordinates": [
     144.81904214,
     -32.4267439
    ]
   },
   "properties": {
    "name": "14597 THE WOOL TRACK KULWIN 2835",
    "locID": "LOC000148061777",
    "tech": "SATELLITE",
    "upgrade": "NULL_NA",
    "gnaf_pid": "GANSW718501403",
    "tech_change_status": "Not Planned"
   }
  },
  {
   "type": "Feature",
   "geometry": {
    "type": "Point",
    "coordinates": [
     144.7451349,
     -32.38835645
    ]
   },
   "properties": {
    "name": "14600 THE WOOL TRACK KULWIN 2835",
    "locID": "LOC000148061852",
    "tech": "SATELLITE",
    "upgrade": "NULL_NA",
    "gnaf_pid": "GANSW718501404",
    "tech_change_status": "Not Planned"
   }
  },
  {
   "type": "Feature",
   "geometry": {
    "type": "Point",
    "coordinates": [
     145.00404157,
     -32.06601102
    ]
   },
   "properties": {
    "name": "9739 THE WOOL TRACK KULWIN 2835",
    "locID": "LOC000148106647",
    "tech": "SATELLITE",
    "upgrade": "NULL_NA",
    "gnaf_pid": "GANSW718501405",
    "tech_change_status": "Not Planned"
   }
  },
  {
   "type": "Feature",
   "geometry": {
    "type": "Point",
    "coordinates": [
     144.9871324,
     -32.65515054
    ]
   },
   "properties": {
    "name": "6433 MOOLAH ROAD KULWIN 2835",
    "locID": "LOC000148097256",
    "tech": "SATELLITE",
    "upgrade": "NULL_NA",
    "gnaf_pid": "GANSW718563488",
    "tech_change_status": "Not Planned"
   }
  },
  {
   "type": "Feature",
   "geometry": {
    "type": "Point",
    "coordinates": [
     145.07769418,
     -32.24717639
    ]
   },
   "properties": {
    "name": "1540 MOOLAH ROAD KULWIN 2835",
    "locID": "LOC000148063115",
    "tech": "SATELLITE",
    "upgrade": "NULL_NA",
    "gnaf_pid": "GANSW718690865",
    "tech_change_status": "Not Planned"
   }
  },
  {
   "type": "Feature",
   "geometry": {
    "type": "Point",
    "coordinates": [
     144.92986627,
     -32.33549404
    ]
   },
   "properties": {
    "name": "13097 THE WOOL TRACK KULWIN 2835",
    "locID": "LOC000148059294",
    "tech": "SATELLITE",
    "upgrade": "NULL_NA",
    "gnaf_pid": "GANSW718693895",
    "tech_change_status": "Not Planned"
   }
  }
 ]
}