{
 "type": "FeatureCollection",
 "generated": "2024-08-21T01:48:34.523156",
 "suburb": "LOWER ACACIA CREEK",
 "features": [
  {
   "type": "Feature",
   "geometry": {
    "type": "Point",
    "coordinates": [
     152.23140476,
     -28.45561705
    ]
   },
   "properties": {
    "name": "8196 MOUNT LINDESAY ROAD LOWER ACACIA CREEK 2476",
    "locID": "LOC000055371063",
    "tech": "SATELLITE",
    "upgrade": "NULL_NA",
    "gnaf_pid": "GANSW717652145",
    "tech_change_status": "Not Planned"
   }
  },
  {
   "type": "Feature",
   "geometry": {
    "type": "Point",
    "coordinates": [
     152.23959434,
     -28.43938577
    ]
   },
   "properties": {
    "name": "8439 MOUNT LINDESAY ROAD LOWER ACACIA CREEK 2476",
    "locID": "LOC000081745103",
    "tech": "SATELLITE",
    "upgrade": "NULL_NA",
    "gnaf_pid": "GANSW717652147",
    "tech_change_status": "Not Planned"
   }
  },
  {
   "type": "Feature",
   "geometry": {
    "type": "Point",
    "coordinates": [
     152.21925885,
     -28.45323368
    ]
   },
   "properties": {
    "name": "8249 MOUNT LINDESAY ROAD LOWER ACACIA CREEK 2476",
    "locID": "LOC100078033331",
    "tech": "SATELLITE",
    "upgrade": "NULL_NA",
    "gnaf_pid": "GANSW717683621",
    "tech_change_status": "Not Planned"
   }
  },
  {
   "type": "Feature",
   "geometry": {
    "type": "Point",
    "coordinates": [
     152.24558294,
     -28.42990991
    ]
   },
   "properties": {
    "name": "24 BARLOWS GATE ROAD LOWER ACACIA CREEK 2476",
    "locID": "LOC000043923995",
    "tech": "SATELLITE",
    "upgrade": "NULL_NA",
    "gnaf_pid": "GANSW717759680",
    "tech_change_status": "Not Planned"
   }
  },
  {
   "type": "Feature",
   "geometry": {
    "type": "Point",
    "coordinates": [
     152.244558,
     -28.43204035
    ]
   },
   "properties": {
    "name": "1 BARLOWS GATE ROAD LOWER ACACIA CREEK 2476",
    "locID": "LOC000153103608",
    "tech": "SATELLITE",
    "upgrade": "NULL_NA",
    "gnaf_pid": "GANSW718048778",
    "tech_change_status": "Not Planned"
   }
  },
  {
   "type": "Feature",
   "geometry": {
    "type": "Point",
    "coordinates": [
     152.24465262,
     -28.42914701
    ]
   },
   "properties": {
    "name": "33 BARLOWS GATE ROAD LOWER ACACIA CREEK 2476",
    "locID": "LOC000053638260",
    "tech": "SATELLITE",
    "upgrade": "NULL_NA",
    "gnaf_pid": "GANSW718048780",
    "tech_change_status": "Not Planned"
   }
  },
  {
   "type": "Feature",
   "geometry": {
    "type": "Point",
    "coordinates": [
     152.24467774,
     -28.43173119
    ]
   },
   "properties": {
    "name": "3 BARLOWS GATE ROAD LOWER ACACIA CREEK 2476",
    "locID": "LOC000040103043",
    "tech": "SATELLITE",
    "upgrade": "NULL_NA",
    "gnaf_pid": "GANSW718048781",
    "tech_change_status": "Not Planned"
   }
  },
  {
   "type": "Feature",
   "geometry": {
    "type": "Point",
    "coordinates": [
     152.25204333,
     -28.44260523
    ]
   },
   "properties": {
    "name": "65 VINEGAR HILL ROAD LOWER ACACIA CREEK 2476",
    "locID": "LOC000072148126",
    "tech": "SATELLITE",
    "upgrade": "NULL_NA",
    "gnaf_pid": "GANSW718060702",
    "tech_change_status": "Not Planned"
   }
  },
  {
   "type": "Feature",
   "geometry": {
    "type": "Point",
    "coordinates": [
     152.24606436,
     -28.42892429
    ]
   },
   "properties": {
    "name": "14 LOWER ACACIA CREEK ROAD LOWER ACACIA CREEK 2476",
    "locID": "LOC000148382248",
    "tech": "SATELLITE",
    "upgrade": "NULL_NA",
    "gnaf_pid": "GANSW718532211",
    "tech_change_status": "Not Planned"
   }
  },
  {
   "type": "Feature",
   "geometry": {
    "type": "Point",
    "coordinates": [
     152.24743152,
     -28.43227112
    ]
   },
   "properties": {
    "name": "LOT 148 LOWER ACACIA CHURCH ROAD LOWER ACACIA CREEK 2476",
    "locID": "LOC000189945944",
    "tech": "SATELLITE",
    "upgrade": "NULL_NA",
    "gnaf_pid": "GANSW718540087",
    "tech_change_status": "Not Planned"
   }
  },
  {
   "type": "Feature",
   "geometry": {
    "type": "Point",
    "coordinates": [
     152.22373878,
     -28.45681037
    ]
   },
   "properties": {
    "name": "66 VINEGAR HILL ROAD LOWER ACACIA CREEK 2476",
    "locID": "LOC000072148126",
    "tech": "SATELLITE",
    "upgrade": "NULL_NA",
    "gnaf_pid": "GANSW721323813",
    "tech_change_status": "Not Planned"
   }
  }
 ]
}