{
 "type": "FeatureCollection",
 "generated": "2024-07-30T19:28:35.381023",
 "suburb": "LOWER PEACOCK",
 "features": [
  {
   "type": "Feature",
   "geometry": {
    "type": "Point",
    "coordinates": [
     152.59946846,
     -28.77496221
    ]
   },
   "properties": {
    "name": "529 FARM ROAD LOWER PEACOCK 2469",
    "locID": "LOC000053612107",
    "tech": "WIRELESS",
    "upgrade": "NULL_NA",
    "gnaf_pid": "GANSW709633271",
    "tech_change_status": "Not Planned",
    "program_type": "Fixed Wireless and Satellite Upgrade Program",
    "target_eligibility_quarter": "NA"
   }
  },
  {
   "type": "Feature",
   "geometry": {
    "type": "Point",
    "coordinates": [
     152.60720393,
     -28.75159048
    ]
   },
   "properties": {
    "name": "244 FARM ROAD LOWER PEACOCK 2469",
    "locID": "LOC000088017033",
    "tech": "WIRELESS",
    "upgrade": "NULL_NA",
    "gnaf_pid": "GANSW709633272",
    "tech_change_status": "Not Planned",
    "program_type": "Fixed Wireless and Satellite Upgrade Program",
    "target_eligibility_quarter": "NA"
   }
  },
  {
   "type": "Feature",
   "geometry": {
    "type": "Point",
    "coordinates": [
     152.59794851,
     -28.76450595
    ]
   },
   "properties": {
    "name": "408 FARM ROAD LOWER PEACOCK 2469",
    "locID": "LOC000084064515",
    "tech": "WIRELESS",
    "upgrade": "NULL_NA",
    "gnaf_pid": "GANSW715369915",
    "tech_change_status": "Not Planned",
    "program_type": "Fixed Wireless and Satellite Upgrade Program",
    "target_eligibility_quarter": "NA"
   }
  },
  {
   "type": "Feature",
   "geometry": {
    "type": "Point",
    "coordinates": [
     152.57043742,
     -28.75594988
    ]
   },
   "properties": {
    "name": "408A FARM ROAD LOWER PEACOCK 2469",
    "locID": "LOC000084064515",
    "tech": "WIRELESS",
    "upgrade": "NULL_NA",
    "gnaf_pid": "GANSW720680896",
    "tech_change_status": "Not Planned",
    "program_type": "Fixed Wireless and Satellite Upgrade Program",
    "target_eligibility_quarter": "NA"
   }
  }
 ]
}