{
 "type": "FeatureCollection",
 "generated": "2024-01-29T16:19:22.891629",
 "suburb": "LOWER PEACOCK",
 "features": [
  {
   "type": "Feature",
   "geometry": {
    "type": "Point",
    "coordinates": [
     152.59946846,
     -28.77496221
    ]
   },
   "properties": {
    "name": "529 FARM ROAD LOWER PEACOCK 2469",
    "locID": "LOC000053612107",
    "tech": "WIRELESS",
    "upgrade": "NULL_NA",
    "gnaf_pid": "GANSW709633271"
   }
  },
  {
   "type": "Feature",
   "geometry": {
    "type": "Point",
    "coordinates": [
     152.60720393,
     -28.75159048
    ]
   },
   "properties": {
    "name": "244 FARM ROAD LOWER PEACOCK 2469",
    "locID": "LOC000088017033",
    "tech": "WIRELESS",
    "upgrade": "NULL_NA",
    "gnaf_pid": "GANSW709633272"
   }
  },
  {
   "type": "Feature",
   "geometry": {
    "type": "Point",
    "coordinates": [
     152.60269444,
     -28.76138541
    ]
   },
   "properties": {
    "name": "240 FARM ROAD LOWER PEACOCK 2469",
    "locID": "ChIJy3h6VoPkmWsRxXAR8EYg0Qo",
    "tech": "WIRELESS",
    "upgrade": "UNKNOWN",
    "gnaf_pid": "GANSW715369914"
   }
  },
  {
   "type": "Feature",
   "geometry": {
    "type": "Point",
    "coordinates": [
     152.59794851,
     -28.76450595
    ]
   },
   "properties": {
    "name": "408 FARM ROAD LOWER PEACOCK 2469",
    "locID": "LOC000084064515",
    "tech": "WIRELESS",
    "upgrade": "NULL_NA",
    "gnaf_pid": "GANSW715369915"
   }
  },
  {
   "type": "Feature",
   "geometry": {
    "type": "Point",
    "coordinates": [
     152.58892876,
     -28.75397358
    ]
   },
   "properties": {
    "name": "276 FARM ROAD LOWER PEACOCK 2469",
    "locID": "ChIJ-ZKbnn_kmWsRJXQjxuyjpN8",
    "tech": "WIRELESS",
    "upgrade": "UNKNOWN",
    "gnaf_pid": "GANSW717330961"
   }
  },
  {
   "type": "Feature",
   "geometry": {
    "type": "Point",
    "coordinates": [
     152.57043742,
     -28.75594988
    ]
   },
   "properties": {
    "name": "408A FARM ROAD LOWER PEACOCK 2469",
    "locID": "LOC000084064515",
    "tech": "WIRELESS",
    "upgrade": "NULL_NA",
    "gnaf_pid": "GANSW720680896"
   }
  }
 ]
}