{
 "type": "FeatureCollection",
 "generated": "2023-12-03T13:58:42.466673",
 "suburb": "LUCAS HEIGHTS",
 "features": [
  {
   "type": "Feature",
   "geometry": {
    "type": "Point",
    "coordinates": [
     150.97672205,
     -34.05106759
    ]
   },
   "properties": {
    "name": "178 NEW ILLAWARRA ROAD LUCAS HEIGHTS 2234",
    "locID": "LOC000036927606",
    "tech": "SATELLITE",
    "upgrade": "NULL_NA",
    "gnaf_pid": "GANSW718010107"
   }
  },
  {
   "type": "Feature",
   "geometry": {
    "type": "Point",
    "coordinates": [
     150.96825762,
     -34.03234831
    ]
   },
   "properties": {
    "name": "2280 HEATHCOTE ROAD LUCAS HEIGHTS 2234",
    "locID": "ChIJ86b4KdrBEmsRCwJcW-AkowQ",
    "tech": "SATELLITE",
    "upgrade": "UNKNOWN",
    "gnaf_pid": "GANSW718195949"
   }
  },
  {
   "type": "Feature",
   "geometry": {
    "type": "Point",
    "coordinates": [
     150.96623296,
     -34.03997139
    ]
   },
   "properties": {
    "name": "6781 HEATHCOTE ROAD LUCAS HEIGHTS 2234",
    "locID": "ChIJDSWF3M_BEmsRfAAeP6wvt44",
    "tech": "SATELLITE",
    "upgrade": "UNKNOWN",
    "gnaf_pid": "GANSW718195950"
   }
  },
  {
   "type": "Feature",
   "geometry": {
    "type": "Point",
    "coordinates": [
     150.96869918,
     -34.02702089
    ]
   },
   "properties": {
    "name": "9339 HEATHCOTE ROAD LUCAS HEIGHTS 2234",
    "locID": "ChIJS_CngTHAEmsR1_-vzv3KkO4",
    "tech": "SATELLITE",
    "upgrade": "UNKNOWN",
    "gnaf_pid": "GANSW718195951"
   }
  },
  {
   "type": "Feature",
   "geometry": {
    "type": "Point",
    "coordinates": [
     150.98569198,
     -34.03411368
    ]
   },
   "properties": {
    "name": "1961 LITTLE FOREST ROAD LUCAS HEIGHTS 2234",
    "locID": "EjNMaXR0bGUgRm9yZXN0IFJkLCBMdWNhcyBIZWlnaHRzIE5TVyAyMjM0LCBBdXN0cmFsaWEiLiosChQKEgllCPMTyMESaxHQXqQ7DD0NqhIUChIJd_xvGbbBEmsRIL8yFmh9AQU",
    "tech": "SATELLITE",
    "upgrade": "UNKNOWN",
    "gnaf_pid": "GANSW718198895"
   }
  },
  {
   "type": "Feature",
   "geometry": {
    "type": "Point",
    "coordinates": [
     150.97475215,
     -34.04785942
    ]
   },
   "properties": {
    "name": "19 LITTLE FOREST ROAD LUCAS HEIGHTS 2234",
    "locID": "ChIJ0xCfLcHBEmsRRaGZR5DsQGo",
    "tech": "SATELLITE",
    "upgrade": "UNKNOWN",
    "gnaf_pid": "GANSW718198897"
   }
  },
  {
   "type": "Feature",
   "geometry": {
    "type": "Point",
    "coordinates": [
     150.97421902,
     -34.029802
    ]
   },
   "properties": {
    "name": "2449 LITTLE FOREST ROAD LUCAS HEIGHTS 2234",
    "locID": "ChIJn7AMSzTAEmsRTj-WIsRNBG0",
    "tech": "SATELLITE",
    "upgrade": "UNKNOWN",
    "gnaf_pid": "GANSW718198898"
   }
  },
  {
   "type": "Feature",
   "geometry": {
    "type": "Point",
    "coordinates": [
     150.98340107,
     -34.04530819
    ]
   },
   "properties": {
    "name": "175 NEW ILLAWARRA ROAD LUCAS HEIGHTS 2234",
    "locID": "LOC000120632339",
    "tech": "SATELLITE",
    "upgrade": "NULL_NA",
    "gnaf_pid": "GANSW718201476"
   }
  },
  {
   "type": "Feature",
   "geometry": {
    "type": "Point",
    "coordinates": [
     150.97131497,
     -34.04602769
    ]
   },
   "properties": {
    "name": "55 NEW ILLAWARRA ROAD LUCAS HEIGHTS 2234",
    "locID": "LOC000120630674",
    "tech": "SATELLITE",
    "upgrade": "NULL_NA",
    "gnaf_pid": "GANSW718201477"
   }
  },
  {
   "type": "Feature",
   "geometry": {
    "type": "Point",
    "coordinates": [
     150.97605908,
     -34.0336186
    ]
   },
   "properties": {
    "name": "1839 LITTLE FOREST ROAD LUCAS HEIGHTS 2234",
    "locID": "ChIJVZuPwsrBEmsRZETM1uqawTs",
    "tech": "SATELLITE",
    "upgrade": "UNKNOWN",
    "gnaf_pid": "GANSW718602765"
   }
  },
  {
   "type": "Feature",
   "geometry": {
    "type": "Point",
    "coordinates": [
     150.97329854,
     -34.03219156
    ]
   },
   "properties": {
    "name": "2280A HEATHCOTE ROAD LUCAS HEIGHTS 2234",
    "locID": "ChIJxan-wzTAEmsR0y9vEIKTkvc",
    "tech": "SATELLITE",
    "upgrade": "UNKNOWN",
    "gnaf_pid": "GANSW720151467"
   }
  }
 ]
}