{
 "type": "FeatureCollection",
 "generated": "2024-08-20T00:54:45.862474",
 "suburb": "LUCAS HEIGHTS",
 "features": [
  {
   "type": "Feature",
   "geometry": {
    "type": "Point",
    "coordinates": [
     150.97672205,
     -34.05106759
    ]
   },
   "properties": {
    "name": "178 NEW ILLAWARRA ROAD LUCAS HEIGHTS 2234",
    "locID": "LOC000036927606",
    "tech": "NULL",
    "upgrade": "NULL_NA",
    "gnaf_pid": "GANSW718010107",
    "tech_change_status": "Not Planned"
   }
  },
  {
   "type": "Feature",
   "geometry": {
    "type": "Point",
    "coordinates": [
     150.98340107,
     -34.04530819
    ]
   },
   "properties": {
    "name": "175 NEW ILLAWARRA ROAD LUCAS HEIGHTS 2234",
    "locID": "LOC000120632339",
    "tech": "SATELLITE",
    "upgrade": "NULL_NA",
    "gnaf_pid": "GANSW718201476",
    "tech_change_status": "Not Planned"
   }
  },
  {
   "type": "Feature",
   "geometry": {
    "type": "Point",
    "coordinates": [
     150.97131497,
     -34.04602769
    ]
   },
   "properties": {
    "name": "55 NEW ILLAWARRA ROAD LUCAS HEIGHTS 2234",
    "locID": "LOC000120630674",
    "tech": "SATELLITE",
    "upgrade": "NULL_NA",
    "gnaf_pid": "GANSW718201477",
    "tech_change_status": "Not Planned"
   }
  }
 ]
}