{
 "type": "FeatureCollection",
 "generated": "2024-03-04T16:27:23.685236",
 "suburb": "MIAMLEY",
 "features": [
  {
   "type": "Feature",
   "geometry": {
    "type": "Point",
    "coordinates": [
     146.92825913,
     -32.41589414
    ]
   },
   "properties": {
    "name": "2664 NYNGAN ROAD MIAMLEY 2873",
    "locID": "LOC100080386747",
    "tech": "SATELLITE",
    "upgrade": "NULL_NA",
    "gnaf_pid": "GANSW719804009"
   }
  },
  {
   "type": "Feature",
   "geometry": {
    "type": "Point",
    "coordinates": [
     146.86432235,
     -32.46784256
    ]
   },
   "properties": {
    "name": "1871 NYNGAN ROAD MIAMLEY 2873",
    "locID": "LOC100071955418",
    "tech": "SATELLITE",
    "upgrade": "NULL_NA",
    "gnaf_pid": "GANSW719804088"
   }
  },
  {
   "type": "Feature",
   "geometry": {
    "type": "Point",
    "coordinates": [
     146.87598656,
     -32.41897187
    ]
   },
   "properties": {
    "name": "2213 NYNGAN ROAD MIAMLEY 2873",
    "locID": "LOC000185954876",
    "tech": "SATELLITE",
    "upgrade": "NULL_NA",
    "gnaf_pid": "GANSW719805404"
   }
  },
  {
   "type": "Feature",
   "geometry": {
    "type": "Point",
    "coordinates": [
     146.89286558,
     -32.3865194
    ]
   },
   "properties": {
    "name": "2551 NYNGAN ROAD MIAMLEY 2873",
    "locID": "LOC100079006124",
    "tech": "SATELLITE",
    "upgrade": "NULL_NA",
    "gnaf_pid": "GANSW719806564"
   }
  },
  {
   "type": "Feature",
   "geometry": {
    "type": "Point",
    "coordinates": [
     146.90232247,
     -32.34641655
    ]
   },
   "properties": {
    "name": "3159 NYNGAN ROAD MIAMLEY 2873",
    "locID": "LOC100078066867",
    "tech": "SATELLITE",
    "upgrade": "NULL_NA",
    "gnaf_pid": "GANSW719809605"
   }
  },
  {
   "type": "Feature",
   "geometry": {
    "type": "Point",
    "coordinates": [
     146.97349242,
     -32.35335887
    ]
   },
   "properties": {
    "name": "3646 NYNGAN ROAD MIAMLEY 2873",
    "locID": "LOC100071954194",
    "tech": "SATELLITE",
    "upgrade": "NULL_NA",
    "gnaf_pid": "GANSW719895825"
   }
  },
  {
   "type": "Feature",
   "geometry": {
    "type": "Point",
    "coordinates": [
     146.98456104,
     -32.47513953
    ]
   },
   "properties": {
    "name": "1463 MYAMLEY ROAD MIAMLEY 2873",
    "locID": "LOC100071955707",
    "tech": "SATELLITE",
    "upgrade": "NULL_NA",
    "gnaf_pid": "GANSW720006900"
   }
  },
  {
   "type": "Feature",
   "geometry": {
    "type": "Point",
    "coordinates": [
     146.91109275,
     -32.45362572
    ]
   },
   "properties": {
    "name": "2066 NYNGAN ROAD MIAMLEY 2873",
    "locID": "LOC100071955418",
    "tech": "SATELLITE",
    "upgrade": "NULL_NA",
    "gnaf_pid": "GANSW720016198"
   }
  }
 ]
}