{
 "type": "FeatureCollection",
 "generated": "2023-10-29T18:02:29.435516",
 "suburb": "MOOLPA",
 "features": [
  {
   "type": "Feature",
   "geometry": {
    "type": "Point",
    "coordinates": [
     143.66968185,
     -35.00038151
    ]
   },
   "properties": {
    "name": "2066 KYALITE ROAD MOOLPA 2734",
    "locID": "LOC000018808043",
    "tech": "SATELLITE",
    "upgrade": "NULL_NA",
    "gnaf_pid": "GANSW717706346"
   }
  },
  {
   "type": "Feature",
   "geometry": {
    "type": "Point",
    "coordinates": [
     143.70393216,
     -35.00615621
    ]
   },
   "properties": {
    "name": "2504 KYALITE ROAD MOOLPA 2734",
    "locID": "LOC000109963465",
    "tech": "SATELLITE",
    "upgrade": "NULL_NA",
    "gnaf_pid": "GANSW717706347"
   }
  },
  {
   "type": "Feature",
   "geometry": {
    "type": "Point",
    "coordinates": [
     143.86317788,
     -34.87004608
    ]
   },
   "properties": {
    "name": "2204 KERI KERI ROAD MOOLPA 2734",
    "locID": "ChIJO4m8LwU63GoRU55tvdDIHXs",
    "tech": "SATELLITE",
    "upgrade": "UNKNOWN",
    "gnaf_pid": "GANSW717774713"
   }
  },
  {
   "type": "Feature",
   "geometry": {
    "type": "Point",
    "coordinates": [
     143.79937445,
     -35.00987294
    ]
   },
   "properties": {
    "name": "2371 BALRANALD ROAD MOOLPA 2734",
    "locID": "LOC000122039545",
    "tech": "SATELLITE",
    "upgrade": "NULL_NA",
    "gnaf_pid": "GANSW718257369"
   }
  },
  {
   "type": "Feature",
   "geometry": {
    "type": "Point",
    "coordinates": [
     143.69358847,
     -34.85286571
    ]
   },
   "properties": {
    "name": "4538 BALRANALD ROAD MOOLPA 2734",
    "locID": "Ei00NTM4IEJhbHJhbmFsZCBSZCwgTW9vbHBhIE5TVyAyNzE1LCBBdXN0cmFsaWEiMRIvChQKEgnPt8jGtlrcahH6CgvlU0W6XBC6IyoUChIJFb7ZS9U-3GoRipGPcXHjRsg",
    "tech": "SATELLITE",
    "upgrade": "UNKNOWN",
    "gnaf_pid": "GANSW718257370"
   }
  },
  {
   "type": "Feature",
   "geometry": {
    "type": "Point",
    "coordinates": [
     143.86317788,
     -34.87004608
    ]
   },
   "properties": {
    "name": "1651 KERI KERI ROAD MOOLPA 2734",
    "locID": "ChIJbfK2QoYw3GoRznvZLYD4xDs",
    "tech": "SATELLITE",
    "upgrade": "UNKNOWN",
    "gnaf_pid": "GANSW720938945"
   }
  }
 ]
}