{
 "type": "FeatureCollection",
 "generated": "2024-07-11T17:49:45.383989",
 "suburb": "MOOLPA",
 "features": [
  {
   "type": "Feature",
   "geometry": {
    "type": "Point",
    "coordinates": [
     143.66968185,
     -35.00038151
    ]
   },
   "properties": {
    "name": "2066 KYALITE ROAD MOOLPA 2734",
    "locID": "LOC000018808043",
    "tech": "SATELLITE",
    "upgrade": "NULL_NA",
    "gnaf_pid": "GANSW717706346",
    "tech_change_status": "Not Planned"
   }
  },
  {
   "type": "Feature",
   "geometry": {
    "type": "Point",
    "coordinates": [
     143.70393216,
     -35.00615621
    ]
   },
   "properties": {
    "name": "2504 KYALITE ROAD MOOLPA 2734",
    "locID": "LOC000109963465",
    "tech": "SATELLITE",
    "upgrade": "NULL_NA",
    "gnaf_pid": "GANSW717706347",
    "tech_change_status": "Not Planned"
   }
  },
  {
   "type": "Feature",
   "geometry": {
    "type": "Point",
    "coordinates": [
     143.79937445,
     -35.00987294
    ]
   },
   "properties": {
    "name": "2371 BALRANALD ROAD MOOLPA 2734",
    "locID": "LOC000122039545",
    "tech": "SATELLITE",
    "upgrade": "NULL_NA",
    "gnaf_pid": "GANSW718257369",
    "tech_change_status": "Not Planned"
   }
  }
 ]
}