{
 "type": "FeatureCollection",
 "generated": "2023-12-26T08:16:20.861087",
 "suburb": "MOORARA",
 "features": [
  {
   "type": "Feature",
   "geometry": {
    "type": "Point",
    "coordinates": [
     142.63884551,
     -33.12303178
    ]
   },
   "properties": {
    "name": "4107 KARPA KORA ROAD MOORARA 2648",
    "locID": "ChIJz5dc3nEo5moRdOYvvlnHoWo",
    "tech": "SATELLITE",
    "upgrade": "UNKNOWN",
    "gnaf_pid": "GANSW718154933"
   }
  },
  {
   "type": "Feature",
   "geometry": {
    "type": "Point",
    "coordinates": [
     142.71024948,
     -32.99590953
    ]
   },
   "properties": {
    "name": "2288 KARPA KORA ROAD MOORARA 2648",
    "locID": "ChIJHddiajt86GoRj8jyPpN_9cM",
    "tech": "SATELLITE",
    "upgrade": "UNKNOWN",
    "gnaf_pid": "GANSW718197689"
   }
  },
  {
   "type": "Feature",
   "geometry": {
    "type": "Point",
    "coordinates": [
     142.83951529,
     -32.96074519
    ]
   },
   "properties": {
    "name": "3725 KARPA KORA ROAD MOORARA 2648",
    "locID": "LOC000121879868",
    "tech": "SATELLITE",
    "upgrade": "NULL_NA",
    "gnaf_pid": "GANSW718197690"
   }
  },
  {
   "type": "Feature",
   "geometry": {
    "type": "Point",
    "coordinates": [
     142.72709371,
     -32.98746964
    ]
   },
   "properties": {
    "name": "4174 KARPA KORA ROAD MOORARA 2648",
    "locID": "LOC000121882794",
    "tech": "SATELLITE",
    "upgrade": "NULL_NA",
    "gnaf_pid": "GANSW718197691"
   }
  },
  {
   "type": "Feature",
   "geometry": {
    "type": "Point",
    "coordinates": [
     142.37632459,
     -33.10522513
    ]
   },
   "properties": {
    "name": "15365 POONCARIE ROAD MOORARA 2648",
    "locID": "LOC000121854365",
    "tech": "SATELLITE",
    "upgrade": "NULL_NA",
    "gnaf_pid": "GANSW718286881"
   }
  },
  {
   "type": "Feature",
   "geometry": {
    "type": "Point",
    "coordinates": [
     142.39206192,
     -33.06727038
    ]
   },
   "properties": {
    "name": "16095 POONCARIE ROAD MOORARA 2648",
    "locID": "ChIJl-F3wDpn6GoRbw4FndP1NRg",
    "tech": "SATELLITE",
    "upgrade": "UNKNOWN",
    "gnaf_pid": "GANSW718286882"
   }
  },
  {
   "type": "Feature",
   "geometry": {
    "type": "Point",
    "coordinates": [
     142.71024948,
     -32.99590953
    ]
   },
   "properties": {
    "name": "4150 KARPA KORA ROAD MOORARA 2648",
    "locID": "ChIJI-XlAucp5moRYPhdT-ou1nA",
    "tech": "SATELLITE",
    "upgrade": "UNKNOWN",
    "gnaf_pid": "GANSW718438894"
   }
  },
  {
   "type": "Feature",
   "geometry": {
    "type": "Point",
    "coordinates": [
     142.71024948,
     -32.99590953
    ]
   },
   "properties": {
    "name": "5140 KARPA KORA ROAD MOORARA 2648",
    "locID": "ChIJI-XlAucp5moRI9jt3Pekf7E",
    "tech": "SATELLITE",
    "upgrade": "UNKNOWN",
    "gnaf_pid": "GANSW718438895"
   }
  }
 ]
}