{
 "type": "FeatureCollection",
 "generated": "2024-09-27T16:41:45.063466",
 "suburb": "MOORARA",
 "features": [
  {
   "type": "Feature",
   "geometry": {
    "type": "Point",
    "coordinates": [
     142.83951529,
     -32.96074519
    ]
   },
   "properties": {
    "name": "3725 KARPA KORA ROAD MOORARA 2648",
    "locID": "LOC000121879868",
    "tech": "NULL",
    "upgrade": "NULL_NA",
    "gnaf_pid": "GANSW718197690",
    "tech_change_status": "Not Planned"
   }
  },
  {
   "type": "Feature",
   "geometry": {
    "type": "Point",
    "coordinates": [
     142.72709371,
     -32.98746964
    ]
   },
   "properties": {
    "name": "4174 KARPA KORA ROAD MOORARA 2648",
    "locID": "LOC000121882794",
    "tech": "NULL",
    "upgrade": "NULL_NA",
    "gnaf_pid": "GANSW718197691",
    "tech_change_status": "Not Planned"
   }
  },
  {
   "type": "Feature",
   "geometry": {
    "type": "Point",
    "coordinates": [
     142.37632459,
     -33.10522513
    ]
   },
   "properties": {
    "name": "15365 POONCARIE ROAD MOORARA 2648",
    "locID": "LOC000121854365",
    "tech": "SATELLITE",
    "upgrade": "NULL_NA",
    "gnaf_pid": "GANSW718286881",
    "tech_change_status": "Not Planned"
   }
  }
 ]
}