{
 "type": "FeatureCollection",
 "generated": "2024-09-26T20:45:43.959436",
 "suburb": "MOUNT MARSH",
 "features": [
  {
   "type": "Feature",
   "geometry": {
    "type": "Point",
    "coordinates": [
     152.92014824,
     -29.26099841
    ]
   },
   "properties": {
    "name": "350 CAMIRA CREEK ROAD MOUNT MARSH 2469",
    "locID": "LOC000052380216",
    "tech": "SATELLITE",
    "upgrade": "NULL_NA",
    "gnaf_pid": "GANSW705446691",
    "tech_change_status": "Not Planned"
   }
  },
  {
   "type": "Feature",
   "geometry": {
    "type": "Point",
    "coordinates": [
     152.88820041,
     -29.30159904
    ]
   },
   "properties": {
    "name": "1159 MOUNT MARSH ROAD MOUNT MARSH 2469",
    "locID": "LOC000010508300",
    "tech": "NULL",
    "upgrade": "NULL_NA",
    "gnaf_pid": "GANSW706384898",
    "tech_change_status": "Not Planned"
   }
  },
  {
   "type": "Feature",
   "geometry": {
    "type": "Point",
    "coordinates": [
     152.902765,
     -29.23048505
    ]
   },
   "properties": {
    "name": "837 OLD TENTERFIELD ROAD MOUNT MARSH 2469",
    "locID": "LOC000115482727",
    "tech": "SATELLITE",
    "upgrade": "NULL_NA",
    "gnaf_pid": "GANSW715254428",
    "tech_change_status": "Not Planned"
   }
  },
  {
   "type": "Feature",
   "geometry": {
    "type": "Point",
    "coordinates": [
     152.8878374,
     -29.29607438
    ]
   },
   "properties": {
    "name": "1208 MOUNT MARSH ROAD MOUNT MARSH 2469",
    "locID": "LOC000009188097",
    "tech": "NULL",
    "upgrade": "NULL_NA",
    "gnaf_pid": "GANSW716610644",
    "tech_change_status": "Not Planned"
   }
  },
  {
   "type": "Feature",
   "geometry": {
    "type": "Point",
    "coordinates": [
     152.85583319,
     -29.30316373
    ]
   },
   "properties": {
    "name": "1338 MOUNT MARSH ROAD MOUNT MARSH 2469",
    "locID": "LOC000066753060",
    "tech": "NULL",
    "upgrade": "NULL_NA",
    "gnaf_pid": "GANSW716610646",
    "tech_change_status": "Not Planned"
   }
  }
 ]
}