{
 "type": "FeatureCollection",
 "generated": "2024-01-25T19:49:22.100347",
 "suburb": "MOUNT MARSH",
 "features": [
  {
   "type": "Feature",
   "geometry": {
    "type": "Point",
    "coordinates": [
     152.87550608,
     -29.2593504
    ]
   },
   "properties": {
    "name": "316 CAMIRA CREEK ROAD MOUNT MARSH 2469",
    "locID": "ChIJoQ2ErGAommsRfbVDgvfAkPs",
    "tech": "SATELLITE",
    "upgrade": "UNKNOWN",
    "gnaf_pid": "GANSW705446690"
   }
  },
  {
   "type": "Feature",
   "geometry": {
    "type": "Point",
    "coordinates": [
     152.92014824,
     -29.26099841
    ]
   },
   "properties": {
    "name": "350 CAMIRA CREEK ROAD MOUNT MARSH 2469",
    "locID": "LOC000052380216",
    "tech": "SATELLITE",
    "upgrade": "NULL_NA",
    "gnaf_pid": "GANSW705446691"
   }
  },
  {
   "type": "Feature",
   "geometry": {
    "type": "Point",
    "coordinates": [
     152.92122912,
     -29.30642347
    ]
   },
   "properties": {
    "name": "449 LYONS ROAD MOUNT MARSH 2469",
    "locID": "ChIJ_9tPWtIummsRnLu05uHZ4tg",
    "tech": "SATELLITE",
    "upgrade": "UNKNOWN",
    "gnaf_pid": "GANSW705446692"
   }
  },
  {
   "type": "Feature",
   "geometry": {
    "type": "Point",
    "coordinates": [
     152.88820041,
     -29.30159904
    ]
   },
   "properties": {
    "name": "1159 MOUNT MARSH ROAD MOUNT MARSH 2469",
    "locID": "LOC000010508300",
    "tech": "SATELLITE",
    "upgrade": "NULL_NA",
    "gnaf_pid": "GANSW706384898"
   }
  },
  {
   "type": "Feature",
   "geometry": {
    "type": "Point",
    "coordinates": [
     152.89886212,
     -29.29500231
    ]
   },
   "properties": {
    "name": "1085 MOUNT MARSH ROAD MOUNT MARSH 2469",
    "locID": "ChIJjdyOQSApmmsRc2ki68PEkUU",
    "tech": "SATELLITE",
    "upgrade": "UNKNOWN",
    "gnaf_pid": "GANSW706426148"
   }
  },
  {
   "type": "Feature",
   "geometry": {
    "type": "Point",
    "coordinates": [
     152.88250436,
     -29.23488913
    ]
   },
   "properties": {
    "name": "839 OLD TENTERFIELD ROAD MOUNT MARSH 2469",
    "locID": "ChIJJ07PSjAmmmsRXptRWQQGZpE",
    "tech": "SATELLITE",
    "upgrade": "UNKNOWN",
    "gnaf_pid": "GANSW715254427"
   }
  },
  {
   "type": "Feature",
   "geometry": {
    "type": "Point",
    "coordinates": [
     152.902765,
     -29.23048505
    ]
   },
   "properties": {
    "name": "837 OLD TENTERFIELD ROAD MOUNT MARSH 2469",
    "locID": "LOC000115482727",
    "tech": "SATELLITE",
    "upgrade": "NULL_NA",
    "gnaf_pid": "GANSW715254428"
   }
  },
  {
   "type": "Feature",
   "geometry": {
    "type": "Point",
    "coordinates": [
     152.8878374,
     -29.29607438
    ]
   },
   "properties": {
    "name": "1208 MOUNT MARSH ROAD MOUNT MARSH 2469",
    "locID": "LOC000009188097",
    "tech": "SATELLITE",
    "upgrade": "NULL_NA",
    "gnaf_pid": "GANSW716610644"
   }
  },
  {
   "type": "Feature",
   "geometry": {
    "type": "Point",
    "coordinates": [
     152.89155947,
     -29.31074887
    ]
   },
   "properties": {
    "name": "1101 MOUNT MARSH ROAD MOUNT MARSH 2469",
    "locID": "ChIJzyS7QhIpmmsRgDLKFesisBQ",
    "tech": "SATELLITE",
    "upgrade": "UNKNOWN",
    "gnaf_pid": "GANSW716610645"
   }
  },
  {
   "type": "Feature",
   "geometry": {
    "type": "Point",
    "coordinates": [
     152.85583319,
     -29.30316373
    ]
   },
   "properties": {
    "name": "1338 MOUNT MARSH ROAD MOUNT MARSH 2469",
    "locID": "LOC000066753060",
    "tech": "SATELLITE",
    "upgrade": "NULL_NA",
    "gnaf_pid": "GANSW716610646"
   }
  },
  {
   "type": "Feature",
   "geometry": {
    "type": "Point",
    "coordinates": [
     152.8995537,
     -29.30886096
    ]
   },
   "properties": {
    "name": "1101 LYONS ROAD MOUNT MARSH 2469",
    "locID": "ChIJf9sryj0pmmsRlhiw6UDRPDA",
    "tech": "SATELLITE",
    "upgrade": "UNKNOWN",
    "gnaf_pid": "GANSW718199256"
   }
  },
  {
   "type": "Feature",
   "geometry": {
    "type": "Point",
    "coordinates": [
     152.75434429,
     -29.24852245
    ]
   },
   "properties": {
    "name": "1061 UPPER FINE FLOWER ROAD MOUNT MARSH 2469",
    "locID": "ChIJR4Mq6kKGmWsR6CRijwU-BWI",
    "tech": "SATELLITE",
    "upgrade": "UNKNOWN",
    "gnaf_pid": "GANSW718607559"
   }
  },
  {
   "type": "Feature",
   "geometry": {
    "type": "Point",
    "coordinates": [
     152.88681109,
     -29.30896016
    ]
   },
   "properties": {
    "name": "1105 MOUNT MARSH ROAD MOUNT MARSH 2469",
    "locID": "ChIJc_O8QhIpmmsRcbE8x5gICA0",
    "tech": "SATELLITE",
    "upgrade": "UNKNOWN",
    "gnaf_pid": "GANSW720323119"
   }
  },
  {
   "type": "Feature",
   "geometry": {
    "type": "Point",
    "coordinates": [
     152.8995537,
     -29.30886096
    ]
   },
   "properties": {
    "name": "140 LYONS ROAD MOUNT MARSH 2469",
    "locID": "ChIJYaO-zj0pmmsRGRDba5tWyis",
    "tech": "SATELLITE",
    "upgrade": "UNKNOWN",
    "gnaf_pid": "GANSW720385394"
   }
  }
 ]
}