{
 "type": "FeatureCollection",
 "generated": "2024-07-28T23:40:25.318219",
 "suburb": "MOUNT TENANDRA",
 "features": [
  {
   "type": "Feature",
   "geometry": {
    "type": "Point",
    "coordinates": [
     148.7908872,
     -31.2477023
    ]
   },
   "properties": {
    "name": "191 MENA ROAD MOUNT TENANDRA 2828",
    "locID": "LOC000036806254",
    "tech": "SATELLITE",
    "upgrade": "NULL_NA",
    "gnaf_pid": "GANSW717480342",
    "tech_change_status": "Not Planned"
   }
  },
  {
   "type": "Feature",
   "geometry": {
    "type": "Point",
    "coordinates": [
     148.69848745,
     -31.16496692
    ]
   },
   "properties": {
    "name": "4494 TOORAWEENAH ROAD MOUNT TENANDRA 2828",
    "locID": "LOC000122101092",
    "tech": "SATELLITE",
    "upgrade": "NULL_NA",
    "gnaf_pid": "GANSW717485151",
    "tech_change_status": "Not Planned"
   }
  },
  {
   "type": "Feature",
   "geometry": {
    "type": "Point",
    "coordinates": [
     148.73908468,
     -31.1937904
    ]
   },
   "properties": {
    "name": "4656 TOORAWEENAH ROAD MOUNT TENANDRA 2828",
    "locID": "LOC000122101125",
    "tech": "SATELLITE",
    "upgrade": "NULL_NA",
    "gnaf_pid": "GANSW717485152",
    "tech_change_status": "Not Planned"
   }
  },
  {
   "type": "Feature",
   "geometry": {
    "type": "Point",
    "coordinates": [
     148.75719267,
     -31.22045095
    ]
   },
   "properties": {
    "name": "4948 TOORAWEENAH ROAD MOUNT TENANDRA 2828",
    "locID": "LOC000122103910",
    "tech": "SATELLITE",
    "upgrade": "NULL_NA",
    "gnaf_pid": "GANSW717485154",
    "tech_change_status": "Not Planned"
   }
  },
  {
   "type": "Feature",
   "geometry": {
    "type": "Point",
    "coordinates": [
     148.78171325,
     -31.23005227
    ]
   },
   "properties": {
    "name": "5128 TOORAWEENAH ROAD MOUNT TENANDRA 2828",
    "locID": "LOC000122104008",
    "tech": "SATELLITE",
    "upgrade": "NULL_NA",
    "gnaf_pid": "GANSW717485155",
    "tech_change_status": "Not Planned"
   }
  },
  {
   "type": "Feature",
   "geometry": {
    "type": "Point",
    "coordinates": [
     148.79929083,
     -31.22552441
    ]
   },
   "properties": {
    "name": "5353 TOORAWEENAH ROAD MOUNT TENANDRA 2828",
    "locID": "LOC000122104054",
    "tech": "SATELLITE",
    "upgrade": "NULL_NA",
    "gnaf_pid": "GANSW717485156",
    "tech_change_status": "Not Planned"
   }
  },
  {
   "type": "Feature",
   "geometry": {
    "type": "Point",
    "coordinates": [
     148.78172532,
     -31.23004578
    ]
   },
   "properties": {
    "name": "3199 BOX RIDGE ROAD MOUNT TENANDRA 2828",
    "locID": "LOC000143031509",
    "tech": "SATELLITE",
    "upgrade": "NULL_NA",
    "gnaf_pid": "GANSW717692473",
    "tech_change_status": "Not Planned"
   }
  },
  {
   "type": "Feature",
   "geometry": {
    "type": "Point",
    "coordinates": [
     148.77669077,
     -31.22162101
    ]
   },
   "properties": {
    "name": "5132 TOORAWEENAH ROAD MOUNT TENANDRA 2828",
    "locID": "LOC000122104012",
    "tech": "SATELLITE",
    "upgrade": "NULL_NA",
    "gnaf_pid": "GANSW717720596",
    "tech_change_status": "Not Planned"
   }
  },
  {
   "type": "Feature",
   "geometry": {
    "type": "Point",
    "coordinates": [
     148.76832387,
     -31.17238775
    ]
   },
   "properties": {
    "name": "291 GOORIANAWA ROAD MOUNT TENANDRA 2828",
    "locID": "LOC000099817982",
    "tech": "SATELLITE",
    "upgrade": "NULL_NA",
    "gnaf_pid": "GANSW717891155",
    "tech_change_status": "Not Planned"
   }
  },
  {
   "type": "Feature",
   "geometry": {
    "type": "Point",
    "coordinates": [
     148.82500452,
     -31.16934104
    ]
   },
   "properties": {
    "name": "916 GOORIANAWA ROAD MOUNT TENANDRA 2828",
    "locID": "LOC000077465453",
    "tech": "SATELLITE",
    "upgrade": "NULL_NA",
    "gnaf_pid": "GANSW717891157",
    "tech_change_status": "Not Planned"
   }
  },
  {
   "type": "Feature",
   "geometry": {
    "type": "Point",
    "coordinates": [
     148.72852348,
     -31.21460158
    ]
   },
   "properties": {
    "name": "4926 TOORAWEENAH ROAD MOUNT TENANDRA 2828",
    "locID": "LOC100071942435",
    "tech": "SATELLITE",
    "upgrade": "NULL_NA",
    "gnaf_pid": "GANSW720016744",
    "tech_change_status": "Not Planned"
   }
  },
  {
   "type": "Feature",
   "geometry": {
    "type": "Point",
    "coordinates": [
     148.69702045,
     -31.16222367
    ]
   },
   "properties": {
    "name": "4378 TOORAWEENAH ROAD MOUNT TENANDRA 2828",
    "locID": "LOC100071942194",
    "tech": "SATELLITE",
    "upgrade": "NULL_NA",
    "gnaf_pid": "GANSW720022427",
    "tech_change_status": "Not Planned"
   }
  }
 ]
}