{
 "type": "FeatureCollection",
 "generated": "2024-01-25T05:41:15.936254",
 "suburb": "OBAN",
 "features": [
  {
   "type": "Feature",
   "geometry": {
    "type": "Point",
    "coordinates": [
     151.87629919,
     -30.08512664
    ]
   },
   "properties": {
    "name": "605 MOUNT MITCHELL ROAD OBAN 2365",
    "locID": "LOC000009852002",
    "tech": "SATELLITE",
    "upgrade": "NULL_NA",
    "gnaf_pid": "GANSW705622224"
   }
  },
  {
   "type": "Feature",
   "geometry": {
    "type": "Point",
    "coordinates": [
     151.88265908,
     -30.13493067
    ]
   },
   "properties": {
    "name": "2201 WARDS MISTAKE ROAD OBAN 2365",
    "locID": "LOC000098630012",
    "tech": "SATELLITE",
    "upgrade": "NULL_NA",
    "gnaf_pid": "GANSW705622225"
   }
  },
  {
   "type": "Feature",
   "geometry": {
    "type": "Point",
    "coordinates": [
     151.90909577,
     -30.14363519
    ]
   },
   "properties": {
    "name": "2465 WARDS MISTAKE ROAD OBAN 2365",
    "locID": "LOC000055744396",
    "tech": "SATELLITE",
    "upgrade": "NULL_NA",
    "gnaf_pid": "GANSW705622226"
   }
  },
  {
   "type": "Feature",
   "geometry": {
    "type": "Point",
    "coordinates": [
     151.92440549,
     -30.10662822
    ]
   },
   "properties": {
    "name": "263 DEANS ROAD OBAN 2365",
    "locID": "ChIJQQm1hu8kn2sRsxSN_Ydpjh4",
    "tech": "SATELLITE",
    "upgrade": "UNKNOWN",
    "gnaf_pid": "GANSW705625453"
   }
  },
  {
   "type": "Feature",
   "geometry": {
    "type": "Point",
    "coordinates": [
     151.84075978,
     -30.09770513
    ]
   },
   "properties": {
    "name": "279 MOUNT MITCHELL ROAD OBAN 2365",
    "locID": "ChIJw7mv3xQ7n2sRzFJ2FB8TKbw",
    "tech": "SATELLITE",
    "upgrade": "UNKNOWN",
    "gnaf_pid": "GANSW705625454"
   }
  },
  {
   "type": "Feature",
   "geometry": {
    "type": "Point",
    "coordinates": [
     151.86389674,
     -30.10899232
    ]
   },
   "properties": {
    "name": "286 MOUNT MITCHELL ROAD OBAN 2365",
    "locID": "LOC000033890409",
    "tech": "SATELLITE",
    "upgrade": "NULL_NA",
    "gnaf_pid": "GANSW705625455"
   }
  },
  {
   "type": "Feature",
   "geometry": {
    "type": "Point",
    "coordinates": [
     151.8658529,
     -30.10041195
    ]
   },
   "properties": {
    "name": "385 MOUNT MITCHELL ROAD OBAN 2365",
    "locID": "LOC000056471836",
    "tech": "SATELLITE",
    "upgrade": "NULL_NA",
    "gnaf_pid": "GANSW705625456"
   }
  },
  {
   "type": "Feature",
   "geometry": {
    "type": "Point",
    "coordinates": [
     151.86622103,
     -30.10193912
    ]
   },
   "properties": {
    "name": "771 MOUNT MITCHELL ROAD OBAN 2365",
    "locID": "ChIJRcmTdj47n2sRCsUmDBzdgZE",
    "tech": "SATELLITE",
    "upgrade": "UNKNOWN",
    "gnaf_pid": "GANSW709889842"
   }
  },
  {
   "type": "Feature",
   "geometry": {
    "type": "Point",
    "coordinates": [
     151.86622103,
     -30.10193912
    ]
   },
   "properties": {
    "name": "1497 MOUNT MITCHELL ROAD OBAN 2365",
    "locID": "ChIJRcmTdj47n2sRbXPjNip09Wg",
    "tech": "SATELLITE",
    "upgrade": "UNKNOWN",
    "gnaf_pid": "GANSW716636761"
   }
  },
  {
   "type": "Feature",
   "geometry": {
    "type": "Point",
    "coordinates": [
     151.86796716,
     -30.09751984
    ]
   },
   "properties": {
    "name": "437 MOUNT MITCHELL ROAD OBAN 2365",
    "locID": "LOC000081745064",
    "tech": "SATELLITE",
    "upgrade": "NULL_NA",
    "gnaf_pid": "GANSW717466960"
   }
  },
  {
   "type": "Feature",
   "geometry": {
    "type": "Point",
    "coordinates": [
     151.83789221,
     -30.11318906
    ]
   },
   "properties": {
    "name": "1779 WARDS MISTAKE ROAD OBAN 2365",
    "locID": "ChIJeRZ6eYI7n2sRd4z2LPv-gRw",
    "tech": "SATELLITE",
    "upgrade": "UNKNOWN",
    "gnaf_pid": "GANSW718568373"
   }
  },
  {
   "type": "Feature",
   "geometry": {
    "type": "Point",
    "coordinates": [
     151.8587139,
     -30.12045656
    ]
   },
   "properties": {
    "name": "59 KERSLAKES ROAD OBAN 2365",
    "locID": "LOC000148095188",
    "tech": "SATELLITE",
    "upgrade": "NULL_NA",
    "gnaf_pid": "GANSW718689388"
   }
  },
  {
   "type": "Feature",
   "geometry": {
    "type": "Point",
    "coordinates": [
     151.82699891,
     -30.07882316
    ]
   },
   "properties": {
    "name": "387 MOUNT MITCHELL ROAD OBAN 2365",
    "locID": "ChIJq4GD-rI7n2sRcXgJUGeaVFU",
    "tech": "SATELLITE",
    "upgrade": "UNKNOWN",
    "gnaf_pid": "GANSW720778294"
   }
  }
 ]
}