{
 "type": "FeatureCollection",
 "generated": "2024-09-26T12:18:51.776476",
 "suburb": "OBAN",
 "features": [
  {
   "type": "Feature",
   "geometry": {
    "type": "Point",
    "coordinates": [
     151.87629919,
     -30.08512664
    ]
   },
   "properties": {
    "name": "605 MOUNT MITCHELL ROAD OBAN 2365",
    "locID": "LOC000009852002",
    "tech": "SATELLITE",
    "upgrade": "NULL_NA",
    "gnaf_pid": "GANSW705622224",
    "tech_change_status": "Not Planned"
   }
  },
  {
   "type": "Feature",
   "geometry": {
    "type": "Point",
    "coordinates": [
     151.88265908,
     -30.13493067
    ]
   },
   "properties": {
    "name": "2201 WARDS MISTAKE ROAD OBAN 2365",
    "locID": "LOC000098630012",
    "tech": "SATELLITE",
    "upgrade": "NULL_NA",
    "gnaf_pid": "GANSW705622225",
    "tech_change_status": "Not Planned"
   }
  },
  {
   "type": "Feature",
   "geometry": {
    "type": "Point",
    "coordinates": [
     151.90909577,
     -30.14363519
    ]
   },
   "properties": {
    "name": "2465 WARDS MISTAKE ROAD OBAN 2365",
    "locID": "LOC000055744396",
    "tech": "NULL",
    "upgrade": "NULL_NA",
    "gnaf_pid": "GANSW705622226",
    "tech_change_status": "Not Planned"
   }
  },
  {
   "type": "Feature",
   "geometry": {
    "type": "Point",
    "coordinates": [
     151.86389674,
     -30.10899232
    ]
   },
   "properties": {
    "name": "286 MOUNT MITCHELL ROAD OBAN 2365",
    "locID": "LOC000033890409",
    "tech": "SATELLITE",
    "upgrade": "NULL_NA",
    "gnaf_pid": "GANSW705625455",
    "tech_change_status": "Not Planned"
   }
  },
  {
   "type": "Feature",
   "geometry": {
    "type": "Point",
    "coordinates": [
     151.8658529,
     -30.10041195
    ]
   },
   "properties": {
    "name": "385 MOUNT MITCHELL ROAD OBAN 2365",
    "locID": "LOC000056471836",
    "tech": "NULL",
    "upgrade": "NULL_NA",
    "gnaf_pid": "GANSW705625456",
    "tech_change_status": "Not Planned"
   }
  },
  {
   "type": "Feature",
   "geometry": {
    "type": "Point",
    "coordinates": [
     151.86796716,
     -30.09751984
    ]
   },
   "properties": {
    "name": "437 MOUNT MITCHELL ROAD OBAN 2365",
    "locID": "LOC000081745064",
    "tech": "SATELLITE",
    "upgrade": "NULL_NA",
    "gnaf_pid": "GANSW717466960",
    "tech_change_status": "Not Planned"
   }
  },
  {
   "type": "Feature",
   "geometry": {
    "type": "Point",
    "coordinates": [
     151.8587139,
     -30.12045656
    ]
   },
   "properties": {
    "name": "59 KERSLAKES ROAD OBAN 2365",
    "locID": "LOC000148095188",
    "tech": "NULL",
    "upgrade": "NULL_NA",
    "gnaf_pid": "GANSW718689388",
    "tech_change_status": "Not Planned"
   }
  }
 ]
}