{
 "type": "FeatureCollection",
 "generated": "2024-07-10T07:23:03.262950",
 "suburb": "OMADALE",
 "features": [
  {
   "type": "Feature",
   "geometry": {
    "type": "Point",
    "coordinates": [
     151.30406431,
     -31.87670493
    ]
   },
   "properties": {
    "name": "224 OMADALE BROOK ROAD OMADALE 2337",
    "locID": "LOC000106154053",
    "tech": "SATELLITE",
    "upgrade": "NULL_NA",
    "gnaf_pid": "GANSW716513685",
    "tech_change_status": "Not Planned"
   }
  },
  {
   "type": "Feature",
   "geometry": {
    "type": "Point",
    "coordinates": [
     151.30163515,
     -31.8762207
    ]
   },
   "properties": {
    "name": "148 OMADALE BROOK ROAD OMADALE 2337",
    "locID": "LOC000058988909",
    "tech": "SATELLITE",
    "upgrade": "NULL_NA",
    "gnaf_pid": "GANSW716534015",
    "tech_change_status": "Not Planned"
   }
  },
  {
   "type": "Feature",
   "geometry": {
    "type": "Point",
    "coordinates": [
     151.28846089,
     -31.86714324
    ]
   },
   "properties": {
    "name": "6261 HUNTER ROAD OMADALE 2337",
    "locID": "LOC000182914567",
    "tech": "SATELLITE",
    "upgrade": "NULL_NA",
    "gnaf_pid": "GANSW720251538",
    "tech_change_status": "Not Planned"
   }
  },
  {
   "type": "Feature",
   "geometry": {
    "type": "Point",
    "coordinates": [
     151.28766139,
     -31.86795225
    ]
   },
   "properties": {
    "name": "6241 HUNTER ROAD OMADALE 2337",
    "locID": "LOC000183354545",
    "tech": "SATELLITE",
    "upgrade": "NULL_NA",
    "gnaf_pid": "GANSW720257413",
    "tech_change_status": "Not Planned"
   }
  },
  {
   "type": "Feature",
   "geometry": {
    "type": "Point",
    "coordinates": [
     151.33800306,
     -31.87997887
    ]
   },
   "properties": {
    "name": "840 TOMALLA ROAD OMADALE 2337",
    "locID": "LOC100078061107",
    "tech": "SATELLITE",
    "upgrade": "NULL_NA",
    "gnaf_pid": "GANSW720324931",
    "tech_change_status": "Not Planned"
   }
  }
 ]
}