{
 "type": "FeatureCollection",
 "generated": "2023-12-04T05:47:59.221226",
 "suburb": "OMADALE",
 "features": [
  {
   "type": "Feature",
   "geometry": {
    "type": "Point",
    "coordinates": [
     151.30266704,
     -31.87666046
    ]
   },
   "properties": {
    "name": "180 OMADALE BROOK ROAD OMADALE 2337",
    "locID": "ChIJY-Q8D-gsC2sRgZqNZk57a_0",
    "tech": "SATELLITE",
    "upgrade": "UNKNOWN",
    "gnaf_pid": "GANSW712009090"
   }
  },
  {
   "type": "Feature",
   "geometry": {
    "type": "Point",
    "coordinates": [
     151.29987021,
     -31.87473055
    ]
   },
   "properties": {
    "name": "181 OMADALE BROOK ROAD OMADALE 2337",
    "locID": "ChIJ0xAC7ugsC2sRj9A6PUN4CTw",
    "tech": "SATELLITE",
    "upgrade": "UNKNOWN",
    "gnaf_pid": "GANSW712009091"
   }
  },
  {
   "type": "Feature",
   "geometry": {
    "type": "Point",
    "coordinates": [
     151.30406431,
     -31.87670493
    ]
   },
   "properties": {
    "name": "224 OMADALE BROOK ROAD OMADALE 2337",
    "locID": "LOC000106154053",
    "tech": "SATELLITE",
    "upgrade": "NULL_NA",
    "gnaf_pid": "GANSW716513685"
   }
  },
  {
   "type": "Feature",
   "geometry": {
    "type": "Point",
    "coordinates": [
     151.30163515,
     -31.8762207
    ]
   },
   "properties": {
    "name": "148 OMADALE BROOK ROAD OMADALE 2337",
    "locID": "LOC000058988909",
    "tech": "SATELLITE",
    "upgrade": "NULL_NA",
    "gnaf_pid": "GANSW716534015"
   }
  },
  {
   "type": "Feature",
   "geometry": {
    "type": "Point",
    "coordinates": [
     151.29157339,
     -31.86591902
    ]
   },
   "properties": {
    "name": "31 HUNTER ROAD OMADALE 2337",
    "locID": "ChIJEbFHg_IsC2sR0ADgTU4rmhs",
    "tech": "SATELLITE",
    "upgrade": "UNKNOWN",
    "gnaf_pid": "GANSW717704384"
   }
  },
  {
   "type": "Feature",
   "geometry": {
    "type": "Point",
    "coordinates": [
     151.28846089,
     -31.86714324
    ]
   },
   "properties": {
    "name": "6261 HUNTER ROAD OMADALE 2337",
    "locID": "LOC000182914567",
    "tech": "SATELLITE",
    "upgrade": "NULL_NA",
    "gnaf_pid": "GANSW720251538"
   }
  },
  {
   "type": "Feature",
   "geometry": {
    "type": "Point",
    "coordinates": [
     151.28766139,
     -31.86795225
    ]
   },
   "properties": {
    "name": "6241 HUNTER ROAD OMADALE 2337",
    "locID": "LOC000183354545",
    "tech": "SATELLITE",
    "upgrade": "NULL_NA",
    "gnaf_pid": "GANSW720257413"
   }
  },
  {
   "type": "Feature",
   "geometry": {
    "type": "Point",
    "coordinates": [
     151.29206559,
     -31.8745679
    ]
   },
   "properties": {
    "name": "5241 HUNTER ROAD OMADALE 2337",
    "locID": "ChIJB_SjVeUsC2sRjnhR_1Ams1o",
    "tech": "SATELLITE",
    "upgrade": "UNKNOWN",
    "gnaf_pid": "GANSW720258104"
   }
  },
  {
   "type": "Feature",
   "geometry": {
    "type": "Point",
    "coordinates": [
     151.33800306,
     -31.87997887
    ]
   },
   "properties": {
    "name": "840 TOMALLA ROAD OMADALE 2337",
    "locID": "LOC100078061107",
    "tech": "SATELLITE",
    "upgrade": "NULL_NA",
    "gnaf_pid": "GANSW720324931"
   }
  }
 ]
}