{
 "type": "FeatureCollection",
 "generated": "2024-07-10T03:35:29.004697",
 "suburb": "PAGES CREEK",
 "features": [
  {
   "type": "Feature",
   "geometry": {
    "type": "Point",
    "coordinates": [
     151.21312325,
     -31.70699104
    ]
   },
   "properties": {
    "name": "2011 PAGES CREEK ROAD PAGES CREEK 2337",
    "locID": "LOC000077807698",
    "tech": "SATELLITE",
    "upgrade": "NULL_NA",
    "gnaf_pid": "GANSW716537776",
    "tech_change_status": "Not Planned"
   }
  },
  {
   "type": "Feature",
   "geometry": {
    "type": "Point",
    "coordinates": [
     151.21186603,
     -31.71354218
    ]
   },
   "properties": {
    "name": "1951 PAGES CREEK ROAD PAGES CREEK 2337",
    "locID": "LOC000105515394",
    "tech": "SATELLITE",
    "upgrade": "NULL_NA",
    "gnaf_pid": "GANSW716863415",
    "tech_change_status": "Not Planned"
   }
  },
  {
   "type": "Feature",
   "geometry": {
    "type": "Point",
    "coordinates": [
     151.24538192,
     -31.69693979
    ]
   },
   "properties": {
    "name": "2660 PAGES CREEK ROAD PAGES CREEK 2337",
    "locID": "LOC100078058576",
    "tech": "SATELLITE",
    "upgrade": "NULL_NA",
    "gnaf_pid": "GANSW717853804",
    "tech_change_status": "Not Planned"
   }
  },
  {
   "type": "Feature",
   "geometry": {
    "type": "Point",
    "coordinates": [
     151.21312325,
     -31.70699104
    ]
   },
   "properties": {
    "name": "COTTAGE 1, 2011 PAGES CREEK ROAD PAGES CREEK 2337",
    "locID": "LOC000120866895",
    "tech": "SATELLITE",
    "upgrade": "NULL_NA",
    "gnaf_pid": "GANSW718278749",
    "tech_change_status": "Not Planned"
   }
  },
  {
   "type": "Feature",
   "geometry": {
    "type": "Point",
    "coordinates": [
     151.19186943,
     -31.66832825
    ]
   },
   "properties": {
    "name": "2260 PAGES CREEK ROAD PAGES CREEK 2337",
    "locID": "LOC000035920920",
    "tech": "SATELLITE",
    "upgrade": "NULL_NA",
    "gnaf_pid": "GANSW718361452",
    "tech_change_status": "Not Planned"
   }
  }
 ]
}