{
 "type": "FeatureCollection",
 "generated": "2023-10-28T07:41:47.111117",
 "suburb": "PAGES CREEK",
 "features": [
  {
   "type": "Feature",
   "geometry": {
    "type": "Point",
    "coordinates": [
     151.21424626,
     -31.70505529
    ]
   },
   "properties": {
    "name": "2661 PAGES CREEK ROAD PAGES CREEK 2337",
    "locID": "ChIJ49hXwWbWCmsRK_94bqGmNo4",
    "tech": "SATELLITE",
    "upgrade": "UNKNOWN",
    "gnaf_pid": "GANSW712009105"
   }
  },
  {
   "type": "Feature",
   "geometry": {
    "type": "Point",
    "coordinates": [
     151.21312325,
     -31.70699104
    ]
   },
   "properties": {
    "name": "2011 PAGES CREEK ROAD PAGES CREEK 2337",
    "locID": "LOC000077807698",
    "tech": "SATELLITE",
    "upgrade": "NULL_NA",
    "gnaf_pid": "GANSW716537776"
   }
  },
  {
   "type": "Feature",
   "geometry": {
    "type": "Point",
    "coordinates": [
     151.19193982,
     -31.72583837
    ]
   },
   "properties": {
    "name": "1609 PAGES CREEK ROAD PAGES CREEK 2337",
    "locID": "ChIJURtHwy3WCmsRK3cjlCgbJpA",
    "tech": "SATELLITE",
    "upgrade": "UNKNOWN",
    "gnaf_pid": "GANSW716611684"
   }
  },
  {
   "type": "Feature",
   "geometry": {
    "type": "Point",
    "coordinates": [
     151.21186603,
     -31.71354218
    ]
   },
   "properties": {
    "name": "1951 PAGES CREEK ROAD PAGES CREEK 2337",
    "locID": "LOC000105515394",
    "tech": "SATELLITE",
    "upgrade": "NULL_NA",
    "gnaf_pid": "GANSW716863415"
   }
  },
  {
   "type": "Feature",
   "geometry": {
    "type": "Point",
    "coordinates": [
     151.24561581,
     -31.66977746
    ]
   },
   "properties": {
    "name": "2660 PAGES CREEK ROAD PAGES CREEK 2337",
    "locID": "LOC100078058576",
    "tech": "SATELLITE",
    "upgrade": "NULL_NA",
    "gnaf_pid": "GANSW717853804"
   }
  },
  {
   "type": "Feature",
   "geometry": {
    "type": "Point",
    "coordinates": [
     151.21312325,
     -31.70699104
    ]
   },
   "properties": {
    "name": "COTTAGE 1, 2011 PAGES CREEK ROAD PAGES CREEK 2337",
    "locID": "LOC000120866895",
    "tech": "SATELLITE",
    "upgrade": "NULL_NA",
    "gnaf_pid": "GANSW718278749"
   }
  },
  {
   "type": "Feature",
   "geometry": {
    "type": "Point",
    "coordinates": [
     151.19186943,
     -31.66832825
    ]
   },
   "properties": {
    "name": "2260 PAGES CREEK ROAD PAGES CREEK 2337",
    "locID": "LOC000035920920",
    "tech": "SATELLITE",
    "upgrade": "NULL_NA",
    "gnaf_pid": "GANSW718361452"
   }
  },
  {
   "type": "Feature",
   "geometry": {
    "type": "Point",
    "coordinates": [
     151.24538191,
     -31.69693979
    ]
   },
   "properties": {
    "name": "1982 PAGES CREEK ROAD PAGES CREEK 2337",
    "locID": "ChIJk4PLHTDUCmsRcbxcY4iDFDM",
    "tech": "SATELLITE",
    "upgrade": "UNKNOWN",
    "gnaf_pid": "GANSW719161766"
   }
  },
  {
   "type": "Feature",
   "geometry": {
    "type": "Point",
    "coordinates": [
     151.24394474,
     -31.72107623
    ]
   },
   "properties": {
    "name": "1460 PAGES CREEK ROAD PAGES CREEK 2337",
    "locID": "ChIJ7bgnQ9vVCmsR-ps80nfJI-s",
    "tech": "SATELLITE",
    "upgrade": "UNKNOWN",
    "gnaf_pid": "GANSW720149961"
   }
  }
 ]
}