{
 "type": "FeatureCollection",
 "generated": "2024-07-09T09:16:00.145838",
 "suburb": "PARA",
 "features": [
  {
   "type": "Feature",
   "geometry": {
    "type": "Point",
    "coordinates": [
     142.26892676,
     -33.74177877
    ]
   },
   "properties": {
    "name": "5634 HIGH DARLING ROAD PARA 2648",
    "locID": "LOC000121852635",
    "tech": "SATELLITE",
    "upgrade": "NULL_NA",
    "gnaf_pid": "GANSW718196190",
    "tech_change_status": "Not Planned"
   }
  },
  {
   "type": "Feature",
   "geometry": {
    "type": "Point",
    "coordinates": [
     142.1680858,
     -33.78321126
    ]
   },
   "properties": {
    "name": "3748C LOW DARLING ROAD PARA 2648",
    "locID": "LOC000121879899",
    "tech": "SATELLITE",
    "upgrade": "NULL_NA",
    "gnaf_pid": "GANSW718199185",
    "tech_change_status": "Not Planned"
   }
  },
  {
   "type": "Feature",
   "geometry": {
    "type": "Point",
    "coordinates": [
     142.03117523,
     -33.63353467
    ]
   },
   "properties": {
    "name": "1240 NOB ROAD PARA 2648",
    "locID": "LOC000121891260",
    "tech": "SATELLITE",
    "upgrade": "NULL_NA",
    "gnaf_pid": "GANSW718201644",
    "tech_change_status": "Not Planned"
   }
  }
 ]
}