{
 "type": "FeatureCollection",
 "generated": "2023-10-27T15:10:12.232086",
 "suburb": "PARA",
 "features": [
  {
   "type": "Feature",
   "geometry": {
    "type": "Point",
    "coordinates": [
     142.13541834,
     -33.79227715
    ]
   },
   "properties": {
    "name": "3748B LOW DARLING ROAD PARA 2648",
    "locID": "ChIJY64kZcKMwmoRd8ive_Ujqsw",
    "tech": "SATELLITE",
    "upgrade": "UNKNOWN",
    "gnaf_pid": "GANSW718155892"
   }
  },
  {
   "type": "Feature",
   "geometry": {
    "type": "Point",
    "coordinates": [
     142.26892676,
     -33.74177877
    ]
   },
   "properties": {
    "name": "5634 HIGH DARLING ROAD PARA 2648",
    "locID": "LOC000121852635",
    "tech": "SATELLITE",
    "upgrade": "NULL_NA",
    "gnaf_pid": "GANSW718196190"
   }
  },
  {
   "type": "Feature",
   "geometry": {
    "type": "Point",
    "coordinates": [
     142.1680858,
     -33.78321126
    ]
   },
   "properties": {
    "name": "3748C LOW DARLING ROAD PARA 2648",
    "locID": "LOC000121879899",
    "tech": "SATELLITE",
    "upgrade": "NULL_NA",
    "gnaf_pid": "GANSW718199185"
   }
  },
  {
   "type": "Feature",
   "geometry": {
    "type": "Point",
    "coordinates": [
     142.03117523,
     -33.63353467
    ]
   },
   "properties": {
    "name": "1240 NOB ROAD PARA 2648",
    "locID": "LOC000121891260",
    "tech": "SATELLITE",
    "upgrade": "NULL_NA",
    "gnaf_pid": "GANSW718201644"
   }
  },
  {
   "type": "Feature",
   "geometry": {
    "type": "Point",
    "coordinates": [
     142.13541834,
     -33.79227715
    ]
   },
   "properties": {
    "name": "3748A LOW DARLING ROAD PARA 2648",
    "locID": "ChIJnUpu7-aMwmoRistJiUxemTk",
    "tech": "SATELLITE",
    "upgrade": "UNKNOWN",
    "gnaf_pid": "GANSW718439597"
   }
  }
 ]
}