{
 "type": "FeatureCollection",
 "generated": "2024-09-27T16:30:10.256843",
 "suburb": "PEBBLY BEACH",
 "features": [
  {
   "type": "Feature",
   "geometry": {
    "type": "Point",
    "coordinates": [
     150.32199078,
     -35.60484912
    ]
   },
   "properties": {
    "name": "LOT 114 PEBBLY BEACH ROAD PEBBLY BEACH 2536",
    "locID": "LOC000109602975",
    "tech": "SATELLITE",
    "upgrade": "NULL_NA",
    "gnaf_pid": "GANSW716039426",
    "tech_change_status": "Not Planned"
   }
  },
  {
   "type": "Feature",
   "geometry": {
    "type": "Point",
    "coordinates": [
     150.32199078,
     -35.60484912
    ]
   },
   "properties": {
    "name": "LOT 115 PEBBLY BEACH ROAD PEBBLY BEACH 2536",
    "locID": "LOC000107627999",
    "tech": "SATELLITE",
    "upgrade": "NULL_NA",
    "gnaf_pid": "GANSW716039427",
    "tech_change_status": "Not Planned"
   }
  },
  {
   "type": "Feature",
   "geometry": {
    "type": "Point",
    "coordinates": [
     150.32951051,
     -35.60672666
    ]
   },
   "properties": {
    "name": "UNIT 3, 60 PEBBLY BEACH ACCESS ROAD PEBBLY BEACH 2536",
    "locID": "LOC100086074636",
    "tech": "NULL",
    "upgrade": "NULL_NA",
    "gnaf_pid": "GANSW720148416",
    "tech_change_status": "Not Planned"
   }
  },
  {
   "type": "Feature",
   "geometry": {
    "type": "Point",
    "coordinates": [
     150.32879903,
     -35.60715299
    ]
   },
   "properties": {
    "name": "60 PEBBLY BEACH ACCESS ROAD PEBBLY BEACH 2536",
    "locID": "LOC100086074636",
    "tech": "NULL",
    "upgrade": "NULL_NA",
    "gnaf_pid": "GANSW720152591",
    "tech_change_status": "Not Planned"
   }
  },
  {
   "type": "Feature",
   "geometry": {
    "type": "Point",
    "coordinates": [
     150.3296421,
     -35.60708778
    ]
   },
   "properties": {
    "name": "UNIT 1, 60 PEBBLY BEACH ACCESS ROAD PEBBLY BEACH 2536",
    "locID": "LOC100086135512",
    "tech": "NULL",
    "upgrade": "NULL_NA",
    "gnaf_pid": "GANSW720157378",
    "tech_change_status": "Not Planned"
   }
  },
  {
   "type": "Feature",
   "geometry": {
    "type": "Point",
    "coordinates": [
     150.32933913,
     -35.60659201
    ]
   },
   "properties": {
    "name": "UNIT 2, 60 PEBBLY BEACH ACCESS ROAD PEBBLY BEACH 2536",
    "locID": "LOC100086074636",
    "tech": "NULL",
    "upgrade": "NULL_NA",
    "gnaf_pid": "GANSW720161765",
    "tech_change_status": "Not Planned"
   }
  },
  {
   "type": "Feature",
   "geometry": {
    "type": "Point",
    "coordinates": [
     150.3286475,
     -35.60724386
    ]
   },
   "properties": {
    "name": "UNIT 4, 60 PEBBLY BEACH ACCESS ROAD PEBBLY BEACH 2536",
    "locID": "LOC100086040494",
    "tech": "NULL",
    "upgrade": "NULL_NA",
    "gnaf_pid": "GANSW720163130",
    "tech_change_status": "Not Planned"
   }
  }
 ]
}