{
 "type": "FeatureCollection",
 "generated": "2024-01-27T02:44:31.778129",
 "suburb": "PEBBLY BEACH",
 "features": [
  {
   "type": "Feature",
   "geometry": {
    "type": "Point",
    "coordinates": [
     150.32199078,
     -35.60484912
    ]
   },
   "properties": {
    "name": "LOT 114 PEBBLY BEACH ROAD PEBBLY BEACH 2536",
    "locID": "LOC000109602975",
    "tech": "SATELLITE",
    "upgrade": "NULL_NA",
    "gnaf_pid": "GANSW716039426"
   }
  },
  {
   "type": "Feature",
   "geometry": {
    "type": "Point",
    "coordinates": [
     150.32199078,
     -35.60484912
    ]
   },
   "properties": {
    "name": "LOT 115 PEBBLY BEACH ROAD PEBBLY BEACH 2536",
    "locID": "LOC000107627999",
    "tech": "SATELLITE",
    "upgrade": "NULL_NA",
    "gnaf_pid": "GANSW716039427"
   }
  },
  {
   "type": "Feature",
   "geometry": {
    "type": "Point",
    "coordinates": [
     150.32199078,
     -35.60484912
    ]
   },
   "properties": {
    "name": "LOT 104 PEBBLY BEACH ROAD PEBBLY BEACH 2536",
    "locID": "EjhQZWJibHkgQmVhY2ggQWNjZXNzIFJkLCBQZWJibHkgQmVhY2ggTlNXIDI1MzYsIEF1c3RyYWxpYSIuKiwKFAoSCdVr9mUSuhVrESwYoJtRQdtFEhQKEgmTB47A2LkVaxEgDkSQtAkGBA",
    "tech": "SATELLITE",
    "upgrade": "UNKNOWN",
    "gnaf_pid": "GANSW717796669"
   }
  },
  {
   "type": "Feature",
   "geometry": {
    "type": "Point",
    "coordinates": [
     150.32951051,
     -35.60672666
    ]
   },
   "properties": {
    "name": "UNIT 3, 60 PEBBLY BEACH ACCESS ROAD PEBBLY BEACH 2536",
    "locID": "ChIJc8bQ6HK6FWsRhyRKBWisDMU",
    "tech": "SATELLITE",
    "upgrade": "UNKNOWN",
    "gnaf_pid": "GANSW720148416"
   }
  },
  {
   "type": "Feature",
   "geometry": {
    "type": "Point",
    "coordinates": [
     150.32879903,
     -35.60715299
    ]
   },
   "properties": {
    "name": "60 PEBBLY BEACH ACCESS ROAD PEBBLY BEACH 2536",
    "locID": "ChIJc8bQ6HK6FWsRhyRKBWisDMU",
    "tech": "SATELLITE",
    "upgrade": "UNKNOWN",
    "gnaf_pid": "GANSW720152591"
   }
  },
  {
   "type": "Feature",
   "geometry": {
    "type": "Point",
    "coordinates": [
     150.3296421,
     -35.60708778
    ]
   },
   "properties": {
    "name": "UNIT 1, 60 PEBBLY BEACH ACCESS ROAD PEBBLY BEACH 2536",
    "locID": "ChIJc8bQ6HK6FWsRhyRKBWisDMU",
    "tech": "SATELLITE",
    "upgrade": "UNKNOWN",
    "gnaf_pid": "GANSW720157378"
   }
  },
  {
   "type": "Feature",
   "geometry": {
    "type": "Point",
    "coordinates": [
     150.32862154,
     -35.60650348
    ]
   },
   "properties": {
    "name": "UNIT 5, 60 PEBBLY BEACH ACCESS ROAD PEBBLY BEACH 2536",
    "locID": "ChIJc8bQ6HK6FWsRhyRKBWisDMU",
    "tech": "SATELLITE",
    "upgrade": "UNKNOWN",
    "gnaf_pid": "GANSW720157742"
   }
  },
  {
   "type": "Feature",
   "geometry": {
    "type": "Point",
    "coordinates": [
     150.32933913,
     -35.60659201
    ]
   },
   "properties": {
    "name": "UNIT 2, 60 PEBBLY BEACH ACCESS ROAD PEBBLY BEACH 2536",
    "locID": "ChIJc8bQ6HK6FWsRhyRKBWisDMU",
    "tech": "SATELLITE",
    "upgrade": "UNKNOWN",
    "gnaf_pid": "GANSW720161765"
   }
  },
  {
   "type": "Feature",
   "geometry": {
    "type": "Point",
    "coordinates": [
     150.3286475,
     -35.60724386
    ]
   },
   "properties": {
    "name": "UNIT 4, 60 PEBBLY BEACH ACCESS ROAD PEBBLY BEACH 2536",
    "locID": "ChIJc8bQ6HK6FWsRhyRKBWisDMU",
    "tech": "SATELLITE",
    "upgrade": "UNKNOWN",
    "gnaf_pid": "GANSW720163130"
   }
  }
 ]
}