{
 "type": "FeatureCollection",
 "generated": "2024-06-01T15:16:59.806239",
 "suburb": "PEBBLY BEACH",
 "features": [
  {
   "type": "Feature",
   "geometry": {
    "type": "Point",
    "coordinates": [
     150.32199078,
     -35.60484912
    ]
   },
   "properties": {
    "name": "LOT 114 PEBBLY BEACH ROAD PEBBLY BEACH 2536",
    "locID": "LOC000109602975",
    "tech": "SATELLITE",
    "upgrade": "NULL_NA",
    "gnaf_pid": "GANSW716039426"
   }
  },
  {
   "type": "Feature",
   "geometry": {
    "type": "Point",
    "coordinates": [
     150.32199078,
     -35.60484912
    ]
   },
   "properties": {
    "name": "LOT 115 PEBBLY BEACH ROAD PEBBLY BEACH 2536",
    "locID": "LOC000107627999",
    "tech": "SATELLITE",
    "upgrade": "NULL_NA",
    "gnaf_pid": "GANSW716039427"
   }
  }
 ]
}