{
 "type": "FeatureCollection",
 "generated": "2024-07-11T04:10:44.123915",
 "suburb": "PIGEONBAH",
 "features": [
  {
   "type": "Feature",
   "geometry": {
    "type": "Point",
    "coordinates": [
     148.1678934,
     -31.54722411
    ]
   },
   "properties": {
    "name": "1475 PIGEONBAH ROAD PIGEONBAH 2824",
    "locID": "LOC000004228824",
    "tech": "SATELLITE",
    "upgrade": "NULL_NA",
    "gnaf_pid": "GANSW717715019",
    "tech_change_status": "Not Planned"
   }
  },
  {
   "type": "Feature",
   "geometry": {
    "type": "Point",
    "coordinates": [
     148.01221363,
     -31.55369646
    ]
   },
   "properties": {
    "name": "533 PIGEONBAH ROAD PIGEONBAH 2824",
    "locID": "LOC000028620453",
    "tech": "SATELLITE",
    "upgrade": "NULL_NA",
    "gnaf_pid": "GANSW717715021",
    "tech_change_status": "Not Planned"
   }
  },
  {
   "type": "Feature",
   "geometry": {
    "type": "Point",
    "coordinates": [
     148.05568037,
     -31.56516596
    ]
   },
   "properties": {
    "name": "987 PIGEONBAH ROAD PIGEONBAH 2824",
    "locID": "LOC000089809785",
    "tech": "SATELLITE",
    "upgrade": "NULL_NA",
    "gnaf_pid": "GANSW717715022",
    "tech_change_status": "Not Planned"
   }
  },
  {
   "type": "Feature",
   "geometry": {
    "type": "Point",
    "coordinates": [
     148.16783815,
     -31.59457171
    ]
   },
   "properties": {
    "name": "1036 PLEASANT VIEW LANE PIGEONBAH 2824",
    "locID": "LOC000122117262",
    "tech": "SATELLITE",
    "upgrade": "NULL_NA",
    "gnaf_pid": "GANSW717715298",
    "tech_change_status": "Not Planned"
   }
  },
  {
   "type": "Feature",
   "geometry": {
    "type": "Point",
    "coordinates": [
     148.11915177,
     -31.59429601
    ]
   },
   "properties": {
    "name": "1190 PLEASANT VIEW LANE PIGEONBAH 2824",
    "locID": "LOC000115059912",
    "tech": "SATELLITE",
    "upgrade": "NULL_NA",
    "gnaf_pid": "GANSW717715299",
    "tech_change_status": "Not Planned"
   }
  },
  {
   "type": "Feature",
   "geometry": {
    "type": "Point",
    "coordinates": [
     148.05795869,
     -31.49285527
    ]
   },
   "properties": {
    "name": "5705 WARREN ROAD PIGEONBAH 2824",
    "locID": "LOC100086173728",
    "tech": "SATELLITE",
    "upgrade": "NULL_NA",
    "gnaf_pid": "GANSW721438935",
    "tech_change_status": "Not Planned"
   }
  }
 ]
}