{
 "type": "FeatureCollection",
 "generated": "2023-11-15T20:45:17.387873",
 "suburb": "PIGEONBAH",
 "features": [
  {
   "type": "Feature",
   "geometry": {
    "type": "Point",
    "coordinates": [
     147.96771026,
     -31.56472999
    ]
   },
   "properties": {
    "name": "120 PIGEONBAH ROAD PIGEONBAH 2824",
    "locID": "ChIJHYIk9ZvfBWsRXeNFMRe0KGM",
    "tech": "SATELLITE",
    "upgrade": "UNKNOWN",
    "gnaf_pid": "GANSW717715018"
   }
  },
  {
   "type": "Feature",
   "geometry": {
    "type": "Point",
    "coordinates": [
     148.1678934,
     -31.54722411
    ]
   },
   "properties": {
    "name": "1475 PIGEONBAH ROAD PIGEONBAH 2824",
    "locID": "LOC000004228824",
    "tech": "SATELLITE",
    "upgrade": "NULL_NA",
    "gnaf_pid": "GANSW717715019"
   }
  },
  {
   "type": "Feature",
   "geometry": {
    "type": "Point",
    "coordinates": [
     148.12551549,
     -31.50081805
    ]
   },
   "properties": {
    "name": "1476 PIGEONBAH ROAD PIGEONBAH 2824",
    "locID": "ChIJOw1Ba8YOBmsRxqsJPvpsnjE",
    "tech": "SATELLITE",
    "upgrade": "UNKNOWN",
    "gnaf_pid": "GANSW717715020"
   }
  },
  {
   "type": "Feature",
   "geometry": {
    "type": "Point",
    "coordinates": [
     148.01221363,
     -31.55369646
    ]
   },
   "properties": {
    "name": "533 PIGEONBAH ROAD PIGEONBAH 2824",
    "locID": "LOC000028620453",
    "tech": "SATELLITE",
    "upgrade": "NULL_NA",
    "gnaf_pid": "GANSW717715021"
   }
  },
  {
   "type": "Feature",
   "geometry": {
    "type": "Point",
    "coordinates": [
     148.05568037,
     -31.56516596
    ]
   },
   "properties": {
    "name": "987 PIGEONBAH ROAD PIGEONBAH 2824",
    "locID": "LOC000089809785",
    "tech": "SATELLITE",
    "upgrade": "NULL_NA",
    "gnaf_pid": "GANSW717715022"
   }
  },
  {
   "type": "Feature",
   "geometry": {
    "type": "Point",
    "coordinates": [
     148.16783815,
     -31.59457171
    ]
   },
   "properties": {
    "name": "1036 PLEASANT VIEW LANE PIGEONBAH 2824",
    "locID": "LOC000122117262",
    "tech": "SATELLITE",
    "upgrade": "NULL_NA",
    "gnaf_pid": "GANSW717715298"
   }
  },
  {
   "type": "Feature",
   "geometry": {
    "type": "Point",
    "coordinates": [
     148.11915177,
     -31.59429601
    ]
   },
   "properties": {
    "name": "1190 PLEASANT VIEW LANE PIGEONBAH 2824",
    "locID": "LOC000115059912",
    "tech": "SATELLITE",
    "upgrade": "NULL_NA",
    "gnaf_pid": "GANSW717715299"
   }
  },
  {
   "type": "Feature",
   "geometry": {
    "type": "Point",
    "coordinates": [
     147.97198685,
     -31.56684343
    ]
   },
   "properties": {
    "name": "199 WONBOBBIE ROAD PIGEONBAH 2824",
    "locID": "ChIJYR_reqffBWsRZFJcW-2t7Ao",
    "tech": "SATELLITE",
    "upgrade": "UNKNOWN",
    "gnaf_pid": "GANSW717724347"
   }
  },
  {
   "type": "Feature",
   "geometry": {
    "type": "Point",
    "coordinates": [
     148.09434889,
     -31.59135327
    ]
   },
   "properties": {
    "name": "1023 WONBOBBIE ROAD PIGEONBAH 2824",
    "locID": "ChIJifGBtv7hBWsRqIEGCRdD3NY",
    "tech": "SATELLITE",
    "upgrade": "UNKNOWN",
    "gnaf_pid": "GANSW717999380"
   }
  },
  {
   "type": "Feature",
   "geometry": {
    "type": "Point",
    "coordinates": [
     148.0636377,
     -31.56885656
    ]
   },
   "properties": {
    "name": "822 PIGEONBAH ROAD PIGEONBAH 2824",
    "locID": "ChIJh4e5hHoKBmsRH91mIeaK1lk",
    "tech": "SATELLITE",
    "upgrade": "UNKNOWN",
    "gnaf_pid": "GANSW718135855"
   }
  }
 ]
}