{
 "type": "FeatureCollection",
 "generated": "2024-09-10T04:24:32.191186",
 "suburb": "PROVIDENCE PORTAL",
 "features": [
  {
   "type": "Feature",
   "geometry": {
    "type": "Point",
    "coordinates": [
     148.62720636,
     -35.94207923
    ]
   },
   "properties": {
    "name": "46 PROVIDENCE ROAD PROVIDENCE PORTAL 2629",
    "locID": "LOC000037847450",
    "tech": "SATELLITE",
    "upgrade": "NULL_NA",
    "gnaf_pid": "GANSW717002746",
    "tech_change_status": "Not Planned"
   }
  },
  {
   "type": "Feature",
   "geometry": {
    "type": "Point",
    "coordinates": [
     148.62975714,
     -35.94313095
    ]
   },
   "properties": {
    "name": "68 PROVIDENCE ROAD PROVIDENCE PORTAL 2629",
    "locID": "LOC000064000353",
    "tech": "SATELLITE",
    "upgrade": "NULL_NA",
    "gnaf_pid": "GANSW717002747",
    "tech_change_status": "Not Planned"
   }
  }
 ]
}