{
 "type": "FeatureCollection",
 "generated": "2024-07-27T00:50:45.109157",
 "suburb": "RAVENSWORTH",
 "features": [
  {
   "type": "Feature",
   "geometry": {
    "type": "Point",
    "coordinates": [
     151.06343139,
     -32.42711652
    ]
   },
   "properties": {
    "name": "220 HEBDEN ROAD RAVENSWORTH 2330",
    "locID": "LOC000020697564",
    "tech": "SATELLITE",
    "upgrade": "NULL_NA",
    "gnaf_pid": "GANSW705803270",
    "tech_change_status": "Not Planned"
   }
  },
  {
   "type": "Feature",
   "geometry": {
    "type": "Point",
    "coordinates": [
     151.06258699,
     -32.42476138
    ]
   },
   "properties": {
    "name": "246 HEBDEN ROAD RAVENSWORTH 2330",
    "locID": "LOC000011368734",
    "tech": "WIRELESS",
    "upgrade": "NULL_NA",
    "gnaf_pid": "GANSW705803271",
    "tech_change_status": "Not Planned",
    "program_type": "Fixed Wireless and Satellite Upgrade Program",
    "target_eligibility_quarter": "NA"
   }
  },
  {
   "type": "Feature",
   "geometry": {
    "type": "Point",
    "coordinates": [
     151.05597511,
     -32.40189829
    ]
   },
   "properties": {
    "name": "463 HEBDEN ROAD RAVENSWORTH 2330",
    "locID": "LOC000090145502",
    "tech": "SATELLITE",
    "upgrade": "NULL_NA",
    "gnaf_pid": "GANSW705803274",
    "tech_change_status": "Not Planned"
   }
  },
  {
   "type": "Feature",
   "geometry": {
    "type": "Point",
    "coordinates": [
     151.09042389,
     -32.39290347
    ]
   },
   "properties": {
    "name": "642 HEBDEN ROAD RAVENSWORTH 2330",
    "locID": "LOC000052452338",
    "tech": "SATELLITE",
    "upgrade": "NULL_NA",
    "gnaf_pid": "GANSW705803275",
    "tech_change_status": "Not Planned"
   }
  },
  {
   "type": "Feature",
   "geometry": {
    "type": "Point",
    "coordinates": [
     151.06470156,
     -32.38634111
    ]
   },
   "properties": {
    "name": "691 HEBDEN ROAD RAVENSWORTH 2330",
    "locID": "LOC000080144091",
    "tech": "SATELLITE",
    "upgrade": "NULL_NA",
    "gnaf_pid": "GANSW705803276",
    "tech_change_status": "Not Planned"
   }
  },
  {
   "type": "Feature",
   "geometry": {
    "type": "Point",
    "coordinates": [
     151.05600489,
     -32.44055843
    ]
   },
   "properties": {
    "name": "7 HEBDEN ROAD RAVENSWORTH 2330",
    "locID": "LOC000041847398",
    "tech": "WIRELESS",
    "upgrade": "NULL_NA",
    "gnaf_pid": "GANSW705803278",
    "tech_change_status": "Not Planned",
    "program_type": "Fixed Wireless and Satellite Upgrade Program",
    "target_eligibility_quarter": "NA"
   }
  },
  {
   "type": "Feature",
   "geometry": {
    "type": "Point",
    "coordinates": [
     151.05583497,
     -32.43796244
    ]
   },
   "properties": {
    "name": "6474 NEW ENGLAND HIGHWAY RAVENSWORTH 2330",
    "locID": "LOC000018433608",
    "tech": "WIRELESS",
    "upgrade": "NULL_NA",
    "gnaf_pid": "GANSW705803281",
    "tech_change_status": "Not Planned",
    "program_type": "Fixed Wireless and Satellite Upgrade Program",
    "target_eligibility_quarter": "NA"
   }
  },
  {
   "type": "Feature",
   "geometry": {
    "type": "Point",
    "coordinates": [
     151.05556079,
     -32.43780436
    ]
   },
   "properties": {
    "name": "6496 NEW ENGLAND HIGHWAY RAVENSWORTH 2330",
    "locID": "LOC000064376805",
    "tech": "SATELLITE",
    "upgrade": "NULL_NA",
    "gnaf_pid": "GANSW705803282",
    "tech_change_status": "Not Planned"
   }
  },
  {
   "type": "Feature",
   "geometry": {
    "type": "Point",
    "coordinates": [
     151.06100417,
     -32.41349959
    ]
   },
   "properties": {
    "name": "4 HEBDEN ROAD RAVENSWORTH 2330",
    "locID": "LOC000090145502",
    "tech": "SATELLITE",
    "upgrade": "NULL_NA",
    "gnaf_pid": "GANSW715895901",
    "tech_change_status": "Not Planned"
   }
  },
  {
   "type": "Feature",
   "geometry": {
    "type": "Point",
    "coordinates": [
     151.06100417,
     -32.41349959
    ]
   },
   "properties": {
    "name": "2 HEBDEN ROAD RAVENSWORTH 2330",
    "locID": "LOC000090145502",
    "tech": "SATELLITE",
    "upgrade": "NULL_NA",
    "gnaf_pid": "GANSW716400974",
    "tech_change_status": "Not Planned"
   }
  },
  {
   "type": "Feature",
   "geometry": {
    "type": "Point",
    "coordinates": [
     151.07451986,
     -32.40462026
    ]
   },
   "properties": {
    "name": "484 HEBDEN ROAD RAVENSWORTH 2330",
    "locID": "LOC000095463900",
    "tech": "WIRELESS",
    "upgrade": "NULL_NA",
    "gnaf_pid": "GANSW717619072",
    "tech_change_status": "Not Planned",
    "program_type": "Fixed Wireless and Satellite Upgrade Program",
    "target_eligibility_quarter": "NA"
   }
  }
 ]
}