{
 "type": "FeatureCollection",
 "generated": "2024-08-23T03:08:03.967715",
 "suburb": "ROUCHEL BROOK",
 "features": [
  {
   "type": "Feature",
   "geometry": {
    "type": "Point",
    "coordinates": [
     151.0761447,
     -32.14218481
    ]
   },
   "properties": {
    "name": "25 STONEY CREEK ROAD ROUCHEL BROOK 2336",
    "locID": "LOC000074532289",
    "tech": "SATELLITE",
    "upgrade": "NULL_NA",
    "gnaf_pid": "GANSW712073994",
    "tech_change_status": "Not Planned"
   }
  },
  {
   "type": "Feature",
   "geometry": {
    "type": "Point",
    "coordinates": [
     151.09624528,
     -32.16042248
    ]
   },
   "properties": {
    "name": "180 STONEY CREEK ROAD ROUCHEL BROOK 2336",
    "locID": "LOC000072635017",
    "tech": "SATELLITE",
    "upgrade": "NULL_NA",
    "gnaf_pid": "GANSW712073995",
    "tech_change_status": "Not Planned"
   }
  },
  {
   "type": "Feature",
   "geometry": {
    "type": "Point",
    "coordinates": [
     151.10345044,
     -32.16514334
    ]
   },
   "properties": {
    "name": "411 STONEY CREEK ROAD ROUCHEL BROOK 2336",
    "locID": "LOC000022318971",
    "tech": "SATELLITE",
    "upgrade": "NULL_NA",
    "gnaf_pid": "GANSW712073996",
    "tech_change_status": "Not Planned"
   }
  },
  {
   "type": "Feature",
   "geometry": {
    "type": "Point",
    "coordinates": [
     151.10645201,
     -32.17162036
    ]
   },
   "properties": {
    "name": "460 STONEY CREEK ROAD ROUCHEL BROOK 2336",
    "locID": "LOC000142557861",
    "tech": "SATELLITE",
    "upgrade": "NULL_NA",
    "gnaf_pid": "GANSW712073997",
    "tech_change_status": "Not Planned"
   }
  },
  {
   "type": "Feature",
   "geometry": {
    "type": "Point",
    "coordinates": [
     151.11938807,
     -32.18086086
    ]
   },
   "properties": {
    "name": "660 STONEY CREEK ROAD ROUCHEL BROOK 2336",
    "locID": "LOC000009000395",
    "tech": "SATELLITE",
    "upgrade": "NULL_NA",
    "gnaf_pid": "GANSW712073998",
    "tech_change_status": "Not Planned"
   }
  },
  {
   "type": "Feature",
   "geometry": {
    "type": "Point",
    "coordinates": [
     151.09093173,
     -32.22854501
    ]
   },
   "properties": {
    "name": "226 ALBANO ROAD ROUCHEL BROOK 2336",
    "locID": "LOC000120949877",
    "tech": "SATELLITE",
    "upgrade": "NULL_NA",
    "gnaf_pid": "GANSW715713843",
    "tech_change_status": "Not Planned"
   }
  },
  {
   "type": "Feature",
   "geometry": {
    "type": "Point",
    "coordinates": [
     151.09624528,
     -32.16042248
    ]
   },
   "properties": {
    "name": "LOT 1 STONEY CREEK ROAD ROUCHEL BROOK 2336",
    "locID": "LOC000072635017",
    "tech": "SATELLITE",
    "upgrade": "NULL_NA",
    "gnaf_pid": "GANSW716539205",
    "tech_change_status": "Not Planned"
   }
  },
  {
   "type": "Feature",
   "geometry": {
    "type": "Point",
    "coordinates": [
     151.07210074,
     -32.14225299
    ]
   },
   "properties": {
    "name": "11 ARMSTRONG ROAD ROUCHEL BROOK 2336",
    "locID": "LOC000090110646",
    "tech": "SATELLITE",
    "upgrade": "NULL_NA",
    "gnaf_pid": "GANSW716645265",
    "tech_change_status": "Not Planned"
   }
  },
  {
   "type": "Feature",
   "geometry": {
    "type": "Point",
    "coordinates": [
     151.07038995,
     -32.14439158
    ]
   },
   "properties": {
    "name": "45 ARMSTRONG ROAD ROUCHEL BROOK 2336",
    "locID": "LOC000043778348",
    "tech": "SATELLITE",
    "upgrade": "NULL_NA",
    "gnaf_pid": "GANSW716645266",
    "tech_change_status": "Not Planned"
   }
  },
  {
   "type": "Feature",
   "geometry": {
    "type": "Point",
    "coordinates": [
     151.07646646,
     -32.13596341
    ]
   },
   "properties": {
    "name": "2173 ROUCHEL ROAD ROUCHEL BROOK 2336",
    "locID": "LOC000050175685",
    "tech": "SATELLITE",
    "upgrade": "NULL_NA",
    "gnaf_pid": "GANSW716762536",
    "tech_change_status": "Not Planned"
   }
  },
  {
   "type": "Feature",
   "geometry": {
    "type": "Point",
    "coordinates": [
     151.07479698,
     -32.13778757
    ]
   },
   "properties": {
    "name": "2209 ROUCHEL ROAD ROUCHEL BROOK 2336",
    "locID": "LOC000051578383",
    "tech": "SATELLITE",
    "upgrade": "NULL_NA",
    "gnaf_pid": "GANSW716762537",
    "tech_change_status": "Not Planned"
   }
  },
  {
   "type": "Feature",
   "geometry": {
    "type": "Point",
    "coordinates": [
     151.07162702,
     -32.1404109
    ]
   },
   "properties": {
    "name": "2171 ROUCHEL ROAD ROUCHEL BROOK 2336",
    "locID": "LOC100078064323",
    "tech": "SATELLITE",
    "upgrade": "NULL_NA",
    "gnaf_pid": "GANSW720255599",
    "tech_change_status": "Not Planned"
   }
  }
 ]
}