{
 "type": "FeatureCollection",
 "generated": "2024-03-05T18:55:30.676333",
 "suburb": "ROUND SWAMP",
 "features": [
  {
   "type": "Feature",
   "geometry": {
    "type": "Point",
    "coordinates": [
     149.94104109,
     -33.07814362
    ]
   },
   "properties": {
    "name": "5249 CASTLEREAGH HIGHWAY ROUND SWAMP 2846",
    "locID": "LOC000075731743",
    "tech": "SATELLITE",
    "upgrade": "NULL_NA",
    "gnaf_pid": "GANSW706480889"
   }
  },
  {
   "type": "Feature",
   "geometry": {
    "type": "Point",
    "coordinates": [
     149.94439483,
     -33.08472948
    ]
   },
   "properties": {
    "name": "5162 CASTLEREAGH HIGHWAY ROUND SWAMP 2846",
    "locID": "LOC000099899690",
    "tech": "SATELLITE",
    "upgrade": "NULL_NA",
    "gnaf_pid": "GANSW706604892"
   }
  },
  {
   "type": "Feature",
   "geometry": {
    "type": "Point",
    "coordinates": [
     149.94834458,
     -33.0892831
    ]
   },
   "properties": {
    "name": "5066 CASTLEREAGH HIGHWAY ROUND SWAMP 2846",
    "locID": "LOC000044160621",
    "tech": "SATELLITE",
    "upgrade": "NULL_NA",
    "gnaf_pid": "GANSW706604893"
   }
  },
  {
   "type": "Feature",
   "geometry": {
    "type": "Point",
    "coordinates": [
     149.9514253,
     -33.09505441
    ]
   },
   "properties": {
    "name": "5016 CASTLEREAGH HIGHWAY ROUND SWAMP 2846",
    "locID": "LOC000063282566",
    "tech": "SATELLITE",
    "upgrade": "NULL_NA",
    "gnaf_pid": "GANSW706604895"
   }
  },
  {
   "type": "Feature",
   "geometry": {
    "type": "Point",
    "coordinates": [
     149.94734254,
     -33.09543026
    ]
   },
   "properties": {
    "name": "5053 CASTLEREAGH HIGHWAY ROUND SWAMP 2846",
    "locID": "LOC000084025161",
    "tech": "SATELLITE",
    "upgrade": "NULL_NA",
    "gnaf_pid": "GANSW716604929"
   }
  },
  {
   "type": "Feature",
   "geometry": {
    "type": "Point",
    "coordinates": [
     149.93816527,
     -33.0619363
    ]
   },
   "properties": {
    "name": "5424 CASTLEREAGH HIGHWAY ROUND SWAMP 2846",
    "locID": "LOC000076122178",
    "tech": "SATELLITE",
    "upgrade": "NULL_NA",
    "gnaf_pid": "GANSW717062730"
   }
  },
  {
   "type": "Feature",
   "geometry": {
    "type": "Point",
    "coordinates": [
     149.95254032,
     -33.07934218
    ]
   },
   "properties": {
    "name": "220 EXCELSIOR ROAD ROUND SWAMP 2846",
    "locID": "LOC000043760450",
    "tech": "SATELLITE",
    "upgrade": "NULL_NA",
    "gnaf_pid": "GANSW717973105"
   }
  },
  {
   "type": "Feature",
   "geometry": {
    "type": "Point",
    "coordinates": [
     149.93256674,
     -33.08456217
    ]
   },
   "properties": {
    "name": "5269 CASTLEREAGH HIGHWAY ROUND SWAMP 2846",
    "locID": "LOC000150143320",
    "tech": "SATELLITE",
    "upgrade": "NULL_NA",
    "gnaf_pid": "GANSW718597381"
   }
  },
  {
   "type": "Feature",
   "geometry": {
    "type": "Point",
    "coordinates": [
     149.93238848,
     -33.07246876
    ]
   },
   "properties": {
    "name": "5329 CASTLEREAGH HIGHWAY ROUND SWAMP 2846",
    "locID": "LOC100078077773",
    "tech": "SATELLITE",
    "upgrade": "NULL_NA",
    "gnaf_pid": "GANSW718597382"
   }
  },
  {
   "type": "Feature",
   "geometry": {
    "type": "Point",
    "coordinates": [
     149.93377506,
     -33.06969632
    ]
   },
   "properties": {
    "name": "5383 CASTLEREAGH HIGHWAY ROUND SWAMP 2846",
    "locID": "LOC000150143349",
    "tech": "SATELLITE",
    "upgrade": "NULL_NA",
    "gnaf_pid": "GANSW718597384"
   }
  },
  {
   "type": "Feature",
   "geometry": {
    "type": "Point",
    "coordinates": [
     149.93818573,
     -33.09252529
    ]
   },
   "properties": {
    "name": "5095 CASTLEREAGH HIGHWAY ROUND SWAMP 2846",
    "locID": "LOC100077216038",
    "tech": "SATELLITE",
    "upgrade": "NULL_NA",
    "gnaf_pid": "GANSW719661166"
   }
  },
  {
   "type": "Feature",
   "geometry": {
    "type": "Point",
    "coordinates": [
     149.94231717,
     -33.08632631
    ]
   },
   "properties": {
    "name": "5135 CASTLEREAGH HIGHWAY ROUND SWAMP 2846",
    "locID": "LOC100071965521",
    "tech": "SATELLITE",
    "upgrade": "NULL_NA",
    "gnaf_pid": "GANSW719661167"
   }
  },
  {
   "type": "Feature",
   "geometry": {
    "type": "Point",
    "coordinates": [
     149.9387341,
     -33.08752324
    ]
   },
   "properties": {
    "name": "5133 CASTLEREAGH HIGHWAY ROUND SWAMP 2846",
    "locID": "LOC100071965578",
    "tech": "SATELLITE",
    "upgrade": "NULL_NA",
    "gnaf_pid": "GANSW719662544"
   }
  }
 ]
}