{
 "type": "FeatureCollection",
 "generated": "2024-09-11T03:31:51.448864",
 "suburb": "SINGLETON MILITARY AREA",
 "features": [
  {
   "type": "Feature",
   "geometry": {
    "type": "Point",
    "coordinates": [
     151.12636147,
     -32.74004007
    ]
   },
   "properties": {
    "name": "267 CESSNOCK ROAD SINGLETON MILITARY AREA 2331",
    "locID": "LOC000120961804",
    "tech": "NULL",
    "upgrade": "NULL_NA",
    "gnaf_pid": "GANSW715790119",
    "tech_change_status": "Not Planned"
   }
  },
  {
   "type": "Feature",
   "geometry": {
    "type": "Point",
    "coordinates": [
     151.15912699,
     -32.7462483
    ]
   },
   "properties": {
    "name": "319 OAKLEY LANE SINGLETON MILITARY AREA 2331",
    "locID": "LOC000054463970",
    "tech": "WIRELESS",
    "upgrade": "NULL_NA",
    "gnaf_pid": "GANSW716414031",
    "tech_change_status": "Not Planned",
    "program_type": "Fixed Wireless and Satellite Upgrade Program",
    "target_eligibility_quarter": "Dec 2024"
   }
  }
 ]
}