{
 "type": "FeatureCollection",
 "generated": "2024-07-11T03:26:43.328723",
 "suburb": "SNOWY PLAIN",
 "features": [
  {
   "type": "Feature",
   "geometry": {
    "type": "Point",
    "coordinates": [
     148.53524633,
     -36.12058169
    ]
   },
   "properties": {
    "name": "1 HAPPY JACKS ROAD SNOWY PLAIN 2628",
    "locID": "LOC100086093924",
    "tech": "SATELLITE",
    "upgrade": "NULL_NA",
    "gnaf_pid": "GANSW720391491",
    "tech_change_status": "Not Planned"
   }
  },
  {
   "type": "Feature",
   "geometry": {
    "type": "Point",
    "coordinates": [
     148.53709906,
     -36.10669046
    ]
   },
   "properties": {
    "name": "1429 HAPPY JACKS ROAD SNOWY PLAIN 2628",
    "locID": "LOC100086093924",
    "tech": "SATELLITE",
    "upgrade": "NULL_NA",
    "gnaf_pid": "GANSW721042093",
    "tech_change_status": "Not Planned"
   }
  }
 ]
}