{
 "type": "FeatureCollection",
 "generated": "2023-12-05T01:01:31.602625",
 "suburb": "SNOWY PLAIN",
 "features": [
  {
   "type": "Feature",
   "geometry": {
    "type": "Point",
    "coordinates": [
     148.55807074,
     -36.15291343
    ]
   },
   "properties": {
    "name": "745 HAPPY JACKS ROAD SNOWY PLAIN 2628",
    "locID": "ChIJ2bIXpSEmPWsRhG7mdFxfBmM",
    "tech": "SATELLITE",
    "upgrade": "UNKNOWN",
    "gnaf_pid": "GANSW720250022"
   }
  },
  {
   "type": "Feature",
   "geometry": {
    "type": "Point",
    "coordinates": [
     148.53524633,
     -36.12058169
    ]
   },
   "properties": {
    "name": "1 HAPPY JACKS ROAD SNOWY PLAIN 2628",
    "locID": "ChIJXWkExUsvPWsRbNEByQfVmSQ",
    "tech": "SATELLITE",
    "upgrade": "UNKNOWN",
    "gnaf_pid": "GANSW720391491"
   }
  },
  {
   "type": "Feature",
   "geometry": {
    "type": "Point",
    "coordinates": [
     148.53709906,
     -36.10669046
    ]
   },
   "properties": {
    "name": "1429 HAPPY JACKS ROAD SNOWY PLAIN 2628",
    "locID": "ChIJaUy39UEvPWsRXqGhVlIhcnk",
    "tech": "SATELLITE",
    "upgrade": "UNKNOWN",
    "gnaf_pid": "GANSW721042093"
   }
  }
 ]
}