{
 "type": "FeatureCollection",
 "generated": "2024-07-30T16:28:50.607098",
 "suburb": "SWANBROOK",
 "features": [
  {
   "type": "Feature",
   "geometry": {
    "type": "Point",
    "coordinates": [
     151.21919512,
     -29.72122869
    ]
   },
   "properties": {
    "name": "1219 KINGS PLAINS ROAD SWANBROOK 2360",
    "locID": "LOC000069262997",
    "tech": "SATELLITE",
    "upgrade": "NULL_NA",
    "gnaf_pid": "GANSW716404926",
    "tech_change_status": "Not Planned"
   }
  },
  {
   "type": "Feature",
   "geometry": {
    "type": "Point",
    "coordinates": [
     151.2215352,
     -29.71848077
    ]
   },
   "properties": {
    "name": "1252 KINGS PLAINS ROAD SWANBROOK 2360",
    "locID": "LOC000037395757",
    "tech": "SATELLITE",
    "upgrade": "NULL_NA",
    "gnaf_pid": "GANSW716481934",
    "tech_change_status": "Not Planned"
   }
  },
  {
   "type": "Feature",
   "geometry": {
    "type": "Point",
    "coordinates": [
     151.22002721,
     -29.71783638
    ]
   },
   "properties": {
    "name": "1253 KINGS PLAINS ROAD SWANBROOK 2360",
    "locID": "LOC000033318856",
    "tech": "WIRELESS",
    "upgrade": "NULL_NA",
    "gnaf_pid": "GANSW716481935",
    "tech_change_status": "Not Planned",
    "program_type": "Fixed Wireless and Satellite Upgrade Program",
    "target_eligibility_quarter": "NA"
   }
  },
  {
   "type": "Feature",
   "geometry": {
    "type": "Point",
    "coordinates": [
     151.23355241,
     -29.69319474
    ]
   },
   "properties": {
    "name": "1493 KINGS PLAINS ROAD SWANBROOK 2360",
    "locID": "LOC000070992196",
    "tech": "WIRELESS",
    "upgrade": "NULL_NA",
    "gnaf_pid": "GANSW716481936",
    "tech_change_status": "Not Planned",
    "program_type": "Fixed Wireless and Satellite Upgrade Program",
    "target_eligibility_quarter": "NA"
   }
  },
  {
   "type": "Feature",
   "geometry": {
    "type": "Point",
    "coordinates": [
     151.20381107,
     -29.73596417
    ]
   },
   "properties": {
    "name": "961 KINGS PLAINS ROAD SWANBROOK 2360",
    "locID": "LOC000058515601",
    "tech": "WIRELESS",
    "upgrade": "NULL_NA",
    "gnaf_pid": "GANSW716481937",
    "tech_change_status": "Not Planned",
    "program_type": "Fixed Wireless and Satellite Upgrade Program",
    "target_eligibility_quarter": "NA"
   }
  },
  {
   "type": "Feature",
   "geometry": {
    "type": "Point",
    "coordinates": [
     151.21488348,
     -29.70812238
    ]
   },
   "properties": {
    "name": "66 HEATHER BRAE LANE SWANBROOK 2360",
    "locID": "LOC000015435126",
    "tech": "SATELLITE",
    "upgrade": "NULL_NA",
    "gnaf_pid": "GANSW717065702",
    "tech_change_status": "Not Planned"
   }
  },
  {
   "type": "Feature",
   "geometry": {
    "type": "Point",
    "coordinates": [
     151.24121685,
     -29.73446257
    ]
   },
   "properties": {
    "name": "199 INVERELL ESTATE ROAD SWANBROOK 2360",
    "locID": "LOC000115470493",
    "tech": "SATELLITE",
    "upgrade": "NULL_NA",
    "gnaf_pid": "GANSW718227645",
    "tech_change_status": "Not Planned"
   }
  },
  {
   "type": "Feature",
   "geometry": {
    "type": "Point",
    "coordinates": [
     151.24786376,
     -29.73280739
    ]
   },
   "properties": {
    "name": "223 INVERELL ESTATE ROAD SWANBROOK 2360",
    "locID": "LOC000115454538",
    "tech": "WIRELESS",
    "upgrade": "NULL_NA",
    "gnaf_pid": "GANSW718227646",
    "tech_change_status": "Not Planned",
    "program_type": "Fixed Wireless and Satellite Upgrade Program",
    "target_eligibility_quarter": "NA"
   }
  },
  {
   "type": "Feature",
   "geometry": {
    "type": "Point",
    "coordinates": [
     151.24740987,
     -29.73488412
    ]
   },
   "properties": {
    "name": "224 INVERELL ESTATE ROAD SWANBROOK 2360",
    "locID": "LOC000115454540",
    "tech": "SATELLITE",
    "upgrade": "NULL_NA",
    "gnaf_pid": "GANSW718227647",
    "tech_change_status": "Not Planned"
   }
  }
 ]
}