{
 "type": "FeatureCollection",
 "generated": "2024-07-31T04:13:28.478819",
 "suburb": "THE FRESHWATER",
 "features": [
  {
   "type": "Feature",
   "geometry": {
    "type": "Point",
    "coordinates": [
     153.32815518,
     -29.35713374
    ]
   },
   "properties": {
    "name": "878 ILUKA ROAD THE FRESHWATER 2466",
    "locID": "LOC000078052010",
    "tech": "SATELLITE",
    "upgrade": "NULL_NA",
    "gnaf_pid": "GANSW706539501",
    "tech_change_status": "Not Planned"
   }
  },
  {
   "type": "Feature",
   "geometry": {
    "type": "Point",
    "coordinates": [
     153.32623231,
     -29.35651152
    ]
   },
   "properties": {
    "name": "860 ILUKA ROAD THE FRESHWATER 2466",
    "locID": "LOC000094602980",
    "tech": "SATELLITE",
    "upgrade": "NULL_NA",
    "gnaf_pid": "GANSW717954844",
    "tech_change_status": "Not Planned"
   }
  },
  {
   "type": "Feature",
   "geometry": {
    "type": "Point",
    "coordinates": [
     153.32759124,
     -29.35748353
    ]
   },
   "properties": {
    "name": "870 ILUKA ROAD THE FRESHWATER 2466",
    "locID": "LOC000064809209",
    "tech": "SATELLITE",
    "upgrade": "NULL_NA",
    "gnaf_pid": "GANSW717954845",
    "tech_change_status": "Not Planned"
   }
  }
 ]
}