{
 "type": "FeatureCollection",
 "generated": "2023-12-06T16:49:14.620385",
 "suburb": "THE FRESHWATER",
 "features": [
  {
   "type": "Feature",
   "geometry": {
    "type": "Point",
    "coordinates": [
     153.32815518,
     -29.35713374
    ]
   },
   "properties": {
    "name": "878 ILUKA ROAD THE FRESHWATER 2466",
    "locID": "LOC000078052010",
    "tech": "SATELLITE",
    "upgrade": "NULL_NA",
    "gnaf_pid": "GANSW706539501"
   }
  },
  {
   "type": "Feature",
   "geometry": {
    "type": "Point",
    "coordinates": [
     153.32623231,
     -29.35651152
    ]
   },
   "properties": {
    "name": "860 ILUKA ROAD THE FRESHWATER 2466",
    "locID": "LOC000094602980",
    "tech": "SATELLITE",
    "upgrade": "NULL_NA",
    "gnaf_pid": "GANSW717954844"
   }
  },
  {
   "type": "Feature",
   "geometry": {
    "type": "Point",
    "coordinates": [
     153.32759124,
     -29.35748353
    ]
   },
   "properties": {
    "name": "870 ILUKA ROAD THE FRESHWATER 2466",
    "locID": "LOC000064809209",
    "tech": "SATELLITE",
    "upgrade": "NULL_NA",
    "gnaf_pid": "GANSW717954845"
   }
  },
  {
   "type": "Feature",
   "geometry": {
    "type": "Point",
    "coordinates": [
     153.33928902,
     -29.3580081
    ]
   },
   "properties": {
    "name": "LOT 3 ILUKA ROAD THE FRESHWATER 2466",
    "locID": "EixJbHVrYSBSZCwgVGhlIEZyZXNod2F0ZXIgTlNXIDI0NjksIEF1c3RyYWxpYSIuKiwKFAoSCTVyxycpT5prESBOglC6yBPxEhQKEgnXD7Jy-EWaaxEgHUSQtAkGBA",
    "tech": "FTTC",
    "upgrade": "UNKNOWN",
    "gnaf_pid": "GANSW720168391"
   }
  },
  {
   "type": "Feature",
   "geometry": {
    "type": "Point",
    "coordinates": [
     153.34340085,
     -29.37569579
    ]
   },
   "properties": {
    "name": "1402 ILUKA ROAD THE FRESHWATER 2466",
    "locID": "ChIJmZXBRVJPmmsRCBtYW8gzYoQ",
    "tech": "WIRELESS",
    "upgrade": "UNKNOWN",
    "gnaf_pid": "GANSW720317618"
   }
  },
  {
   "type": "Feature",
   "geometry": {
    "type": "Point",
    "coordinates": [
     153.34326211,
     -29.37612435
    ]
   },
   "properties": {
    "name": "1400 ILUKA ROAD THE FRESHWATER 2466",
    "locID": "ChIJ2TSIyglPmmsRAScXV8EWGPY",
    "tech": "WIRELESS",
    "upgrade": "UNKNOWN",
    "gnaf_pid": "GANSW720318033"
   }
  }
 ]
}