{
 "type": "FeatureCollection",
 "generated": "2024-07-12T08:00:40.959893",
 "suburb": "THE MEADOWS",
 "features": [
  {
   "type": "Feature",
   "geometry": {
    "type": "Point",
    "coordinates": [
     149.92202962,
     -33.63805569
    ]
   },
   "properties": {
    "name": "313 MEADOWS ROAD THE MEADOWS 2787",
    "locID": "LOC000057656569",
    "tech": "WIRELESS",
    "upgrade": "NULL_NA",
    "gnaf_pid": "GANSW716880081",
    "tech_change_status": "Not Planned",
    "program_type": "Fixed Wireless and Satellite Upgrade Program",
    "target_eligibility_quarter": "NA"
   }
  },
  {
   "type": "Feature",
   "geometry": {
    "type": "Point",
    "coordinates": [
     149.92603978,
     -33.63589887
    ]
   },
   "properties": {
    "name": "349 MEADOWS ROAD THE MEADOWS 2787",
    "locID": "LOC000098310249",
    "tech": "WIRELESS",
    "upgrade": "NULL_NA",
    "gnaf_pid": "GANSW716880082",
    "tech_change_status": "Not Planned",
    "program_type": "Fixed Wireless and Satellite Upgrade Program",
    "target_eligibility_quarter": "NA"
   }
  },
  {
   "type": "Feature",
   "geometry": {
    "type": "Point",
    "coordinates": [
     149.927346,
     -33.63596119
    ]
   },
   "properties": {
    "name": "359 MEADOWS ROAD THE MEADOWS 2787",
    "locID": "LOC000103904988",
    "tech": "WIRELESS",
    "upgrade": "NULL_NA",
    "gnaf_pid": "GANSW716880083",
    "tech_change_status": "Not Planned",
    "program_type": "Fixed Wireless and Satellite Upgrade Program",
    "target_eligibility_quarter": "NA"
   }
  },
  {
   "type": "Feature",
   "geometry": {
    "type": "Point",
    "coordinates": [
     149.93089681,
     -33.63639758
    ]
   },
   "properties": {
    "name": "399 MEADOWS ROAD THE MEADOWS 2787",
    "locID": "LOC000007369808",
    "tech": "WIRELESS",
    "upgrade": "NULL_NA",
    "gnaf_pid": "GANSW716880084",
    "tech_change_status": "Not Planned",
    "program_type": "Fixed Wireless and Satellite Upgrade Program",
    "target_eligibility_quarter": "NA"
   }
  },
  {
   "type": "Feature",
   "geometry": {
    "type": "Point",
    "coordinates": [
     149.92319009,
     -33.63850978
    ]
   },
   "properties": {
    "name": "314 MEADOWS ROAD THE MEADOWS 2787",
    "locID": "LOC000010324891",
    "tech": "WIRELESS",
    "upgrade": "NULL_NA",
    "gnaf_pid": "GANSW716928261",
    "tech_change_status": "Not Planned",
    "program_type": "Fixed Wireless and Satellite Upgrade Program",
    "target_eligibility_quarter": "NA"
   }
  },
  {
   "type": "Feature",
   "geometry": {
    "type": "Point",
    "coordinates": [
     149.92947449,
     -33.63695629
    ]
   },
   "properties": {
    "name": "489 MEADOWS ROAD THE MEADOWS 2787",
    "locID": "LOC000044003034",
    "tech": "WIRELESS",
    "upgrade": "NULL_NA",
    "gnaf_pid": "GANSW716928262",
    "tech_change_status": "Not Planned",
    "program_type": "Fixed Wireless and Satellite Upgrade Program",
    "target_eligibility_quarter": "NA"
   }
  },
  {
   "type": "Feature",
   "geometry": {
    "type": "Point",
    "coordinates": [
     149.92053964,
     -33.64090169
    ]
   },
   "properties": {
    "name": "263 MEADOWS ROAD THE MEADOWS 2787",
    "locID": "LOC000099578372",
    "tech": "WIRELESS",
    "upgrade": "NULL_NA",
    "gnaf_pid": "GANSW717852154",
    "tech_change_status": "Not Planned",
    "program_type": "Fixed Wireless and Satellite Upgrade Program",
    "target_eligibility_quarter": "NA"
   }
  },
  {
   "type": "Feature",
   "geometry": {
    "type": "Point",
    "coordinates": [
     149.92756173,
     -33.64016196
    ]
   },
   "properties": {
    "name": "370 MEADOWS ROAD THE MEADOWS 2787",
    "locID": "LOC000183163591",
    "tech": "SATELLITE",
    "upgrade": "NULL_NA",
    "gnaf_pid": "GANSW717852155",
    "tech_change_status": "Not Planned"
   }
  },
  {
   "type": "Feature",
   "geometry": {
    "type": "Point",
    "coordinates": [
     149.9496538,
     -33.64637509
    ]
   },
   "properties": {
    "name": "484 MEADOWS ROAD THE MEADOWS 2787",
    "locID": "LOC000008921623",
    "tech": "SATELLITE",
    "upgrade": "NULL_NA",
    "gnaf_pid": "GANSW717959131",
    "tech_change_status": "Not Planned"
   }
  },
  {
   "type": "Feature",
   "geometry": {
    "type": "Point",
    "coordinates": [
     149.92465483,
     -33.63518046
    ]
   },
   "properties": {
    "name": "353 MEADOWS ROAD THE MEADOWS 2787",
    "locID": "LOC000183567903",
    "tech": "WIRELESS",
    "upgrade": "NULL_NA",
    "gnaf_pid": "GANSW719473196",
    "tech_change_status": "Not Planned",
    "program_type": "Fixed Wireless and Satellite Upgrade Program",
    "target_eligibility_quarter": "NA"
   }
  }
 ]
}