{
 "type": "FeatureCollection",
 "generated": "2024-07-10T14:19:13.922609",
 "suburb": "TOOLOOM",
 "features": [
  {
   "type": "Feature",
   "geometry": {
    "type": "Point",
    "coordinates": [
     152.46860601,
     -28.54422184
    ]
   },
   "properties": {
    "name": "327 NEEDHAMS ROAD TOOLOOM 2475",
    "locID": "LOC000054745124",
    "tech": "SATELLITE",
    "upgrade": "NULL_NA",
    "gnaf_pid": "GANSW715390452",
    "tech_change_status": "Not Planned"
   }
  },
  {
   "type": "Feature",
   "geometry": {
    "type": "Point",
    "coordinates": [
     152.4594356,
     -28.56334523
    ]
   },
   "properties": {
    "name": "570 NEEDHAMS ROAD TOOLOOM 2475",
    "locID": "LOC000041110383",
    "tech": "SATELLITE",
    "upgrade": "NULL_NA",
    "gnaf_pid": "GANSW715390453",
    "tech_change_status": "Not Planned"
   }
  },
  {
   "type": "Feature",
   "geometry": {
    "type": "Point",
    "coordinates": [
     152.41380843,
     -28.62368191
    ]
   },
   "properties": {
    "name": "4243 PADDYS FLAT ROAD TOOLOOM 2475",
    "locID": "LOC000045690359",
    "tech": "SATELLITE",
    "upgrade": "NULL_NA",
    "gnaf_pid": "GANSW715394340",
    "tech_change_status": "Not Planned"
   }
  },
  {
   "type": "Feature",
   "geometry": {
    "type": "Point",
    "coordinates": [
     152.4705519,
     -28.52169899
    ]
   },
   "properties": {
    "name": "47 NEEDHAMS ROAD TOOLOOM 2475",
    "locID": "LOC000022332408",
    "tech": "SATELLITE",
    "upgrade": "NULL_NA",
    "gnaf_pid": "GANSW717130794",
    "tech_change_status": "Not Planned"
   }
  },
  {
   "type": "Feature",
   "geometry": {
    "type": "Point",
    "coordinates": [
     152.47730731,
     -28.53058439
    ]
   },
   "properties": {
    "name": "145 JASPER IVERSON ROAD TOOLOOM 2475",
    "locID": "LOC000069574428",
    "tech": "SATELLITE",
    "upgrade": "NULL_NA",
    "gnaf_pid": "GANSW717335479",
    "tech_change_status": "Not Planned"
   }
  },
  {
   "type": "Feature",
   "geometry": {
    "type": "Point",
    "coordinates": [
     152.47493778,
     -28.52338722
    ]
   },
   "properties": {
    "name": "59 JASPER IVERSON ROAD TOOLOOM 2475",
    "locID": "LOC000087884728",
    "tech": "SATELLITE",
    "upgrade": "NULL_NA",
    "gnaf_pid": "GANSW717335480",
    "tech_change_status": "Not Planned"
   }
  },
  {
   "type": "Feature",
   "geometry": {
    "type": "Point",
    "coordinates": [
     152.49529847,
     -28.54381605
    ]
   },
   "properties": {
    "name": "205 JASPER IVERSON ROAD TOOLOOM 2475",
    "locID": "LOC000039932696",
    "tech": "SATELLITE",
    "upgrade": "NULL_NA",
    "gnaf_pid": "GANSW717357517",
    "tech_change_status": "Not Planned"
   }
  },
  {
   "type": "Feature",
   "geometry": {
    "type": "Point",
    "coordinates": [
     152.4720903,
     -28.52088565
    ]
   },
   "properties": {
    "name": "7 JASPER IVERSON ROAD TOOLOOM 2475",
    "locID": "LOC000073500593",
    "tech": "SATELLITE",
    "upgrade": "NULL_NA",
    "gnaf_pid": "GANSW717357518",
    "tech_change_status": "Not Planned"
   }
  },
  {
   "type": "Feature",
   "geometry": {
    "type": "Point",
    "coordinates": [
     152.42048318,
     -28.63305447
    ]
   },
   "properties": {
    "name": "4185 PADDYS FLAT ROAD TOOLOOM 2475",
    "locID": "LOC000005874170",
    "tech": "SATELLITE",
    "upgrade": "NULL_NA",
    "gnaf_pid": "GANSW717538212",
    "tech_change_status": "Not Planned"
   }
  },
  {
   "type": "Feature",
   "geometry": {
    "type": "Point",
    "coordinates": [
     152.41564956,
     -28.64193019
    ]
   },
   "properties": {
    "name": "4073 PADDYS FLAT ROAD TOOLOOM 2475",
    "locID": "LOC000176027933",
    "tech": "SATELLITE",
    "upgrade": "NULL_NA",
    "gnaf_pid": "GANSW719688955",
    "tech_change_status": "Not Planned"
   }
  },
  {
   "type": "Feature",
   "geometry": {
    "type": "Point",
    "coordinates": [
     152.44602907,
     -28.62376671
    ]
   },
   "properties": {
    "name": "131 PADDYS FLAT ROAD TOOLOOM 2475",
    "locID": "LOC000045690359",
    "tech": "SATELLITE",
    "upgrade": "NULL_NA",
    "gnaf_pid": "GANSW721121123",
    "tech_change_status": "Not Planned"
   }
  },
  {
   "type": "Feature",
   "geometry": {
    "type": "Point",
    "coordinates": [
     152.42588958,
     -28.64033919
    ]
   },
   "properties": {
    "name": "LOT 120 PADDYS FLAT ROAD TOOLOOM 2475",
    "locID": "LOC000190596870",
    "tech": "SATELLITE",
    "upgrade": "NULL_NA",
    "gnaf_pid": "GANSW721131428",
    "tech_change_status": "Not Planned"
   }
  }
 ]
}