{
 "type": "FeatureCollection",
 "generated": "2024-09-09T07:05:31.243268",
 "suburb": "TUMORRAMA",
 "features": [
  {
   "type": "Feature",
   "geometry": {
    "type": "Point",
    "coordinates": [
     148.46364793,
     -35.17185023
    ]
   },
   "properties": {
    "name": "314 FAIRVIEW ROAD TUMORRAMA 2720",
    "locID": "LOC000022529957",
    "tech": "NULL",
    "upgrade": "NULL_NA",
    "gnaf_pid": "GANSW706105131",
    "tech_change_status": "Not Planned"
   }
  },
  {
   "type": "Feature",
   "geometry": {
    "type": "Point",
    "coordinates": [
     148.47009828,
     -35.20311964
    ]
   },
   "properties": {
    "name": "485 LEE ARCHERS ROAD TUMORRAMA 2720",
    "locID": "LOC000101490007",
    "tech": "SATELLITE",
    "upgrade": "NULL_NA",
    "gnaf_pid": "GANSW706105132",
    "tech_change_status": "Not Planned"
   }
  },
  {
   "type": "Feature",
   "geometry": {
    "type": "Point",
    "coordinates": [
     148.41610844,
     -35.18743739
    ]
   },
   "properties": {
    "name": "2686 WEE JASPER ROAD TUMORRAMA 2720",
    "locID": "LOC000086376513",
    "tech": "NULL",
    "upgrade": "NULL_NA",
    "gnaf_pid": "GANSW706105133",
    "tech_change_status": "Not Planned"
   }
  },
  {
   "type": "Feature",
   "geometry": {
    "type": "Point",
    "coordinates": [
     148.41576167,
     -35.16439799
    ]
   },
   "properties": {
    "name": "2947 WEE JASPER ROAD TUMORRAMA 2720",
    "locID": "LOC000061071331",
    "tech": "SATELLITE",
    "upgrade": "NULL_NA",
    "gnaf_pid": "GANSW706105134",
    "tech_change_status": "Not Planned"
   }
  },
  {
   "type": "Feature",
   "geometry": {
    "type": "Point",
    "coordinates": [
     148.42039104,
     -35.16460387
    ]
   },
   "properties": {
    "name": "2977 WEE JASPER ROAD TUMORRAMA 2720",
    "locID": "LOC000034432296",
    "tech": "SATELLITE",
    "upgrade": "NULL_NA",
    "gnaf_pid": "GANSW706105135",
    "tech_change_status": "Not Planned"
   }
  },
  {
   "type": "Feature",
   "geometry": {
    "type": "Point",
    "coordinates": [
     148.46830669,
     -35.14981594
    ]
   },
   "properties": {
    "name": "345 FAIRVIEW ROAD TUMORRAMA 2720",
    "locID": "LOC000060723129",
    "tech": "NULL",
    "upgrade": "NULL_NA",
    "gnaf_pid": "GANSW712795686",
    "tech_change_status": "Not Planned"
   }
  },
  {
   "type": "Feature",
   "geometry": {
    "type": "Point",
    "coordinates": [
     148.51753608,
     -35.16272698
    ]
   },
   "properties": {
    "name": "887 FAIRVIEW ROAD TUMORRAMA 2720",
    "locID": "LOC000142539915",
    "tech": "SATELLITE",
    "upgrade": "NULL_NA",
    "gnaf_pid": "GANSW712795687",
    "tech_change_status": "Not Planned"
   }
  },
  {
   "type": "Feature",
   "geometry": {
    "type": "Point",
    "coordinates": [
     148.55624415,
     -35.16959836
    ]
   },
   "properties": {
    "name": "1222 FAIRVIEW ROAD TUMORRAMA 2720",
    "locID": "LOC100078123785",
    "tech": "NULL",
    "upgrade": "NULL_NA",
    "gnaf_pid": "GANSW712795689",
    "tech_change_status": "Not Planned"
   }
  },
  {
   "type": "Feature",
   "geometry": {
    "type": "Point",
    "coordinates": [
     148.51391834,
     -35.16716632
    ]
   },
   "properties": {
    "name": "1254 FAIRVIEW ROAD TUMORRAMA 2720",
    "locID": "LOC000065903430",
    "tech": "SATELLITE",
    "upgrade": "NULL_NA",
    "gnaf_pid": "GANSW712795690",
    "tech_change_status": "Not Planned"
   }
  }
 ]
}