{
 "type": "FeatureCollection",
 "generated": "2024-01-26T15:24:26.617942",
 "suburb": "TUMORRAMA",
 "features": [
  {
   "type": "Feature",
   "geometry": {
    "type": "Point",
    "coordinates": [
     148.46364793,
     -35.17185023
    ]
   },
   "properties": {
    "name": "314 FAIRVIEW ROAD TUMORRAMA 2720",
    "locID": "LOC000022529957",
    "tech": "SATELLITE",
    "upgrade": "NULL_NA",
    "gnaf_pid": "GANSW706105131"
   }
  },
  {
   "type": "Feature",
   "geometry": {
    "type": "Point",
    "coordinates": [
     148.47009828,
     -35.20311964
    ]
   },
   "properties": {
    "name": "485 LEE ARCHERS ROAD TUMORRAMA 2720",
    "locID": "LOC000101490007",
    "tech": "SATELLITE",
    "upgrade": "NULL_NA",
    "gnaf_pid": "GANSW706105132"
   }
  },
  {
   "type": "Feature",
   "geometry": {
    "type": "Point",
    "coordinates": [
     148.41610844,
     -35.18743739
    ]
   },
   "properties": {
    "name": "2686 WEE JASPER ROAD TUMORRAMA 2720",
    "locID": "LOC000086376513",
    "tech": "SATELLITE",
    "upgrade": "NULL_NA",
    "gnaf_pid": "GANSW706105133"
   }
  },
  {
   "type": "Feature",
   "geometry": {
    "type": "Point",
    "coordinates": [
     148.41576167,
     -35.16439799
    ]
   },
   "properties": {
    "name": "2947 WEE JASPER ROAD TUMORRAMA 2720",
    "locID": "LOC000061071331",
    "tech": "SATELLITE",
    "upgrade": "NULL_NA",
    "gnaf_pid": "GANSW706105134"
   }
  },
  {
   "type": "Feature",
   "geometry": {
    "type": "Point",
    "coordinates": [
     148.42039104,
     -35.16460387
    ]
   },
   "properties": {
    "name": "2977 WEE JASPER ROAD TUMORRAMA 2720",
    "locID": "LOC000034432296",
    "tech": "SATELLITE",
    "upgrade": "NULL_NA",
    "gnaf_pid": "GANSW706105135"
   }
  },
  {
   "type": "Feature",
   "geometry": {
    "type": "Point",
    "coordinates": [
     148.47521899,
     -35.12435149
    ]
   },
   "properties": {
    "name": "2980 WEE JASPER ROAD TUMORRAMA 2720",
    "locID": "ChIJZ2NAztmOF2sR0QdchcJhlMc",
    "tech": "SATELLITE",
    "upgrade": "UNKNOWN",
    "gnaf_pid": "GANSW712744143"
   }
  },
  {
   "type": "Feature",
   "geometry": {
    "type": "Point",
    "coordinates": [
     148.46830669,
     -35.14981594
    ]
   },
   "properties": {
    "name": "345 FAIRVIEW ROAD TUMORRAMA 2720",
    "locID": "LOC000060723129",
    "tech": "SATELLITE",
    "upgrade": "NULL_NA",
    "gnaf_pid": "GANSW712795686"
   }
  },
  {
   "type": "Feature",
   "geometry": {
    "type": "Point",
    "coordinates": [
     148.51753608,
     -35.16272698
    ]
   },
   "properties": {
    "name": "887 FAIRVIEW ROAD TUMORRAMA 2720",
    "locID": "LOC000142539915",
    "tech": "SATELLITE",
    "upgrade": "NULL_NA",
    "gnaf_pid": "GANSW712795687"
   }
  },
  {
   "type": "Feature",
   "geometry": {
    "type": "Point",
    "coordinates": [
     148.51391834,
     -35.16716632
    ]
   },
   "properties": {
    "name": "1206 FAIRVIEW ROAD TUMORRAMA 2720",
    "locID": "ChIJcfezA3yOF2sRBQVOHvE0l2M",
    "tech": "SATELLITE",
    "upgrade": "UNKNOWN",
    "gnaf_pid": "GANSW712795688"
   }
  },
  {
   "type": "Feature",
   "geometry": {
    "type": "Point",
    "coordinates": [
     148.55624415,
     -35.16959836
    ]
   },
   "properties": {
    "name": "1222 FAIRVIEW ROAD TUMORRAMA 2720",
    "locID": "LOC100078123785",
    "tech": "SATELLITE",
    "upgrade": "NULL_NA",
    "gnaf_pid": "GANSW712795689"
   }
  },
  {
   "type": "Feature",
   "geometry": {
    "type": "Point",
    "coordinates": [
     148.51391834,
     -35.16716632
    ]
   },
   "properties": {
    "name": "1254 FAIRVIEW ROAD TUMORRAMA 2720",
    "locID": "LOC000065903430",
    "tech": "SATELLITE",
    "upgrade": "NULL_NA",
    "gnaf_pid": "GANSW712795690"
   }
  },
  {
   "type": "Feature",
   "geometry": {
    "type": "Point",
    "coordinates": [
     148.47521899,
     -35.12435149
    ]
   },
   "properties": {
    "name": "3708 WEE JASPER ROAD TUMORRAMA 2720",
    "locID": "ChIJZ2NAztmOF2sR2rJQqpMtcLA",
    "tech": "SATELLITE",
    "upgrade": "UNKNOWN",
    "gnaf_pid": "GANSW716172486"
   }
  },
  {
   "type": "Feature",
   "geometry": {
    "type": "Point",
    "coordinates": [
     148.47432761,
     -35.25290134
    ]
   },
   "properties": {
    "name": "1 BRINDABELLA ROAD TUMORRAMA 2720",
    "locID": "ChIJwWPCLFvzF2sRzedl47rS4ek",
    "tech": "SATELLITE",
    "upgrade": "UNKNOWN",
    "gnaf_pid": "GANSW719587997"
   }
  }
 ]
}