{
 "type": "FeatureCollection",
 "generated": "2023-11-14T18:31:44.524781",
 "suburb": "UNUMGAR",
 "features": [
  {
   "type": "Feature",
   "geometry": {
    "type": "Point",
    "coordinates": [
     152.75483478,
     -28.42428024
    ]
   },
   "properties": {
    "name": "4032 SUMMERLAND WAY UNUMGAR 2474",
    "locID": "LOC000142560266",
    "tech": "SATELLITE",
    "upgrade": "NULL_NA",
    "gnaf_pid": "GANSW718425824"
   }
  },
  {
   "type": "Feature",
   "geometry": {
    "type": "Point",
    "coordinates": [
     152.74946465,
     -28.42364067
    ]
   },
   "properties": {
    "name": "4083 SUMMERLAND WAY UNUMGAR 2474",
    "locID": "LOC000142559840",
    "tech": "SATELLITE",
    "upgrade": "NULL_NA",
    "gnaf_pid": "GANSW718425825"
   }
  },
  {
   "type": "Feature",
   "geometry": {
    "type": "Point",
    "coordinates": [
     152.75032489,
     -28.42331844
    ]
   },
   "properties": {
    "name": "4086 SUMMERLAND WAY UNUMGAR 2474",
    "locID": "LOC000142547716",
    "tech": "SATELLITE",
    "upgrade": "NULL_NA",
    "gnaf_pid": "GANSW718425826"
   }
  },
  {
   "type": "Feature",
   "geometry": {
    "type": "Point",
    "coordinates": [
     152.7477835,
     -28.42094412
    ]
   },
   "properties": {
    "name": "4135 SUMMERLAND WAY UNUMGAR 2474",
    "locID": "LOC000148377302",
    "tech": "SATELLITE",
    "upgrade": "NULL_NA",
    "gnaf_pid": "GANSW718425827"
   }
  },
  {
   "type": "Feature",
   "geometry": {
    "type": "Point",
    "coordinates": [
     152.74914534,
     -28.41333145
    ]
   },
   "properties": {
    "name": "4182 SUMMERLAND WAY UNUMGAR 2474",
    "locID": "LOC000142534163",
    "tech": "SATELLITE",
    "upgrade": "NULL_NA",
    "gnaf_pid": "GANSW718425828"
   }
  },
  {
   "type": "Feature",
   "geometry": {
    "type": "Point",
    "coordinates": [
     152.74153954,
     -28.41030849
    ]
   },
   "properties": {
    "name": "4257 SUMMERLAND WAY UNUMGAR 2474",
    "locID": "LOC000148087765",
    "tech": "SATELLITE",
    "upgrade": "NULL_NA",
    "gnaf_pid": "GANSW718425829"
   }
  },
  {
   "type": "Feature",
   "geometry": {
    "type": "Point",
    "coordinates": [
     152.74191347,
     -28.40261483
    ]
   },
   "properties": {
    "name": "4272 SUMMERLAND WAY UNUMGAR 2474",
    "locID": "ChIJn4uESNJLl2sR2f0wubLxMD8",
    "tech": "SATELLITE",
    "upgrade": "UNKNOWN",
    "gnaf_pid": "GANSW718425830"
   }
  },
  {
   "type": "Feature",
   "geometry": {
    "type": "Point",
    "coordinates": [
     152.73923094,
     -28.40781557
    ]
   },
   "properties": {
    "name": "4294 SUMMERLAND WAY UNUMGAR 2474",
    "locID": "LOC000148377325",
    "tech": "SATELLITE",
    "upgrade": "NULL_NA",
    "gnaf_pid": "GANSW718425831"
   }
  },
  {
   "type": "Feature",
   "geometry": {
    "type": "Point",
    "coordinates": [
     152.74894658,
     -28.43328162
    ]
   },
   "properties": {
    "name": "4483 SUMMERLAND WAY UNUMGAR 2474",
    "locID": "ChIJ5bPtaexLl2sRSZSi_Hdq-mQ",
    "tech": "SATELLITE",
    "upgrade": "UNKNOWN",
    "gnaf_pid": "GANSW718425832"
   }
  },
  {
   "type": "Feature",
   "geometry": {
    "type": "Point",
    "coordinates": [
     152.74069049,
     -28.40914578
    ]
   },
   "properties": {
    "name": "4287 SUMMERLAND WAY UNUMGAR 2474",
    "locID": "ChIJI1qsg9BLl2sRhtjouXlgby0",
    "tech": "SATELLITE",
    "upgrade": "UNKNOWN",
    "gnaf_pid": "GANSW718434594"
   }
  },
  {
   "type": "Feature",
   "geometry": {
    "type": "Point",
    "coordinates": [
     152.74139762,
     -28.40913833
    ]
   },
   "properties": {
    "name": "4339 SUMMERLAND WAY UNUMGAR 2474",
    "locID": "LOC000142558544",
    "tech": "SATELLITE",
    "upgrade": "NULL_NA",
    "gnaf_pid": "GANSW718434595"
   }
  },
  {
   "type": "Feature",
   "geometry": {
    "type": "Point",
    "coordinates": [
     152.74139762,
     -28.40913833
    ]
   },
   "properties": {
    "name": "4431 SUMMERLAND WAY UNUMGAR 2474",
    "locID": "LOC000142492954",
    "tech": "SATELLITE",
    "upgrade": "NULL_NA",
    "gnaf_pid": "GANSW718434596"
   }
  },
  {
   "type": "Feature",
   "geometry": {
    "type": "Point",
    "coordinates": [
     152.74893469,
     -28.43329947
    ]
   },
   "properties": {
    "name": "4007 SUMMERLAND WAY UNUMGAR 2474",
    "locID": "ChIJo0wB5vFLl2sRbCIPsWbifUo",
    "tech": "SATELLITE",
    "upgrade": "UNKNOWN",
    "gnaf_pid": "GANSW718442761"
   }
  },
  {
   "type": "Feature",
   "geometry": {
    "type": "Point",
    "coordinates": [
     152.74082541,
     -28.40525906
    ]
   },
   "properties": {
    "name": "4274 SUMMERLAND WAY UNUMGAR 2474",
    "locID": "EjA0Mjc0IFN1bW1lcmxhbmQgV2F5LCBVbnVtZ2FyIE5TVyAyNDc0LCBBdXN0cmFsaWEiMRIvChQKEgmpnZ6v0EuXaxGXHlZKKK2VMxCyISoUChIJYRe6mMAfmmsR1ggkcuBKdvk",
    "tech": "SATELLITE",
    "upgrade": "UNKNOWN",
    "gnaf_pid": "GANSW718818552"
   }
  }
 ]
}