{
 "type": "FeatureCollection",
 "generated": "2024-07-28T13:02:32.929504",
 "suburb": "UNUMGAR",
 "features": [
  {
   "type": "Feature",
   "geometry": {
    "type": "Point",
    "coordinates": [
     152.75483478,
     -28.42428024
    ]
   },
   "properties": {
    "name": "4032 SUMMERLAND WAY UNUMGAR 2474",
    "locID": "LOC000142560266",
    "tech": "SATELLITE",
    "upgrade": "NULL_NA",
    "gnaf_pid": "GANSW718425824",
    "tech_change_status": "Not Planned"
   }
  },
  {
   "type": "Feature",
   "geometry": {
    "type": "Point",
    "coordinates": [
     152.74946465,
     -28.42364067
    ]
   },
   "properties": {
    "name": "4083 SUMMERLAND WAY UNUMGAR 2474",
    "locID": "LOC000142559840",
    "tech": "SATELLITE",
    "upgrade": "NULL_NA",
    "gnaf_pid": "GANSW718425825",
    "tech_change_status": "Not Planned"
   }
  },
  {
   "type": "Feature",
   "geometry": {
    "type": "Point",
    "coordinates": [
     152.75032489,
     -28.42331844
    ]
   },
   "properties": {
    "name": "4086 SUMMERLAND WAY UNUMGAR 2474",
    "locID": "LOC000142547716",
    "tech": "SATELLITE",
    "upgrade": "NULL_NA",
    "gnaf_pid": "GANSW718425826",
    "tech_change_status": "Not Planned"
   }
  },
  {
   "type": "Feature",
   "geometry": {
    "type": "Point",
    "coordinates": [
     152.7477835,
     -28.42094412
    ]
   },
   "properties": {
    "name": "4135 SUMMERLAND WAY UNUMGAR 2474",
    "locID": "LOC000148377302",
    "tech": "SATELLITE",
    "upgrade": "NULL_NA",
    "gnaf_pid": "GANSW718425827",
    "tech_change_status": "Not Planned"
   }
  },
  {
   "type": "Feature",
   "geometry": {
    "type": "Point",
    "coordinates": [
     152.74914534,
     -28.41333145
    ]
   },
   "properties": {
    "name": "4182 SUMMERLAND WAY UNUMGAR 2474",
    "locID": "LOC000142534163",
    "tech": "SATELLITE",
    "upgrade": "NULL_NA",
    "gnaf_pid": "GANSW718425828",
    "tech_change_status": "Not Planned"
   }
  },
  {
   "type": "Feature",
   "geometry": {
    "type": "Point",
    "coordinates": [
     152.74153954,
     -28.41030849
    ]
   },
   "properties": {
    "name": "4257 SUMMERLAND WAY UNUMGAR 2474",
    "locID": "LOC000148087765",
    "tech": "SATELLITE",
    "upgrade": "NULL_NA",
    "gnaf_pid": "GANSW718425829",
    "tech_change_status": "Not Planned"
   }
  },
  {
   "type": "Feature",
   "geometry": {
    "type": "Point",
    "coordinates": [
     152.73923094,
     -28.40781557
    ]
   },
   "properties": {
    "name": "4294 SUMMERLAND WAY UNUMGAR 2474",
    "locID": "LOC000148377325",
    "tech": "SATELLITE",
    "upgrade": "NULL_NA",
    "gnaf_pid": "GANSW718425831",
    "tech_change_status": "Not Planned"
   }
  },
  {
   "type": "Feature",
   "geometry": {
    "type": "Point",
    "coordinates": [
     152.74139762,
     -28.40913833
    ]
   },
   "properties": {
    "name": "4339 SUMMERLAND WAY UNUMGAR 2474",
    "locID": "LOC000142558544",
    "tech": "SATELLITE",
    "upgrade": "NULL_NA",
    "gnaf_pid": "GANSW718434595",
    "tech_change_status": "Not Planned"
   }
  },
  {
   "type": "Feature",
   "geometry": {
    "type": "Point",
    "coordinates": [
     152.74139762,
     -28.40913833
    ]
   },
   "properties": {
    "name": "4431 SUMMERLAND WAY UNUMGAR 2474",
    "locID": "LOC000142492954",
    "tech": "SATELLITE",
    "upgrade": "NULL_NA",
    "gnaf_pid": "GANSW718434596",
    "tech_change_status": "Not Planned"
   }
  }
 ]
}