{
 "type": "FeatureCollection",
 "generated": "2024-09-10T17:10:32.419534",
 "suburb": "UPPER GROWEE",
 "features": [
  {
   "type": "Feature",
   "geometry": {
    "type": "Point",
    "coordinates": [
     150.02483614,
     -32.65607346
    ]
   },
   "properties": {
    "name": "4242 BYLONG VALLEY WAY UPPER GROWEE 2849",
    "locID": "LOC000122474685",
    "tech": "NULL",
    "upgrade": "NULL_NA",
    "gnaf_pid": "GANSW706425418",
    "tech_change_status": "Not Planned"
   }
  },
  {
   "type": "Feature",
   "geometry": {
    "type": "Point",
    "coordinates": [
     150.01669396,
     -32.65787314
    ]
   },
   "properties": {
    "name": "4222 BYLONG VALLEY WAY UPPER GROWEE 2849",
    "locID": "LOC000091748638",
    "tech": "SATELLITE",
    "upgrade": "NULL_NA",
    "gnaf_pid": "GANSW706425419",
    "tech_change_status": "Not Planned"
   }
  },
  {
   "type": "Feature",
   "geometry": {
    "type": "Point",
    "coordinates": [
     150.01905027,
     -32.64979007
    ]
   },
   "properties": {
    "name": "4345 BYLONG VALLEY WAY UPPER GROWEE 2849",
    "locID": "LOC000098665319",
    "tech": "SATELLITE",
    "upgrade": "NULL_NA",
    "gnaf_pid": "GANSW715427991",
    "tech_change_status": "Not Planned"
   }
  },
  {
   "type": "Feature",
   "geometry": {
    "type": "Point",
    "coordinates": [
     150.03180893,
     -32.63435668
    ]
   },
   "properties": {
    "name": "4541 BYLONG VALLEY WAY UPPER GROWEE 2849",
    "locID": "LOC000009001897",
    "tech": "NULL",
    "upgrade": "NULL_NA",
    "gnaf_pid": "GANSW717542390",
    "tech_change_status": "Not Planned"
   }
  },
  {
   "type": "Feature",
   "geometry": {
    "type": "Point",
    "coordinates": [
     150.01263909,
     -32.65572342
    ]
   },
   "properties": {
    "name": "4255 BYLONG VALLEY WAY UPPER GROWEE 2849",
    "locID": "LOC100078071393",
    "tech": "NULL",
    "upgrade": "NULL_NA",
    "gnaf_pid": "GANSW718259069",
    "tech_change_status": "Not Planned"
   }
  },
  {
   "type": "Feature",
   "geometry": {
    "type": "Point",
    "coordinates": [
     150.01445778,
     -32.64173521
    ]
   },
   "properties": {
    "name": "4407 BYLONG VALLEY WAY UPPER GROWEE 2849",
    "locID": "LOC000148088482",
    "tech": "NULL",
    "upgrade": "NULL_NA",
    "gnaf_pid": "GANSW718609092",
    "tech_change_status": "Not Planned"
   }
  },
  {
   "type": "Feature",
   "geometry": {
    "type": "Point",
    "coordinates": [
     150.01544381,
     -32.62908634
    ]
   },
   "properties": {
    "name": "198 JIMMY JIMMY ROAD UPPER GROWEE 2849",
    "locID": "LOC100078070568",
    "tech": "NULL",
    "upgrade": "NULL_NA",
    "gnaf_pid": "GANSW719388275",
    "tech_change_status": "Not Planned"
   }
  },
  {
   "type": "Feature",
   "geometry": {
    "type": "Point",
    "coordinates": [
     150.01718043,
     -32.63555847
    ]
   },
   "properties": {
    "name": "135 JIMMY JIMMY ROAD UPPER GROWEE 2849",
    "locID": "LOC100071958189",
    "tech": "NULL",
    "upgrade": "NULL_NA",
    "gnaf_pid": "GANSW719390996",
    "tech_change_status": "Not Planned"
   }
  },
  {
   "type": "Feature",
   "geometry": {
    "type": "Point",
    "coordinates": [
     150.02561029,
     -32.62977209
    ]
   },
   "properties": {
    "name": "166 JIMMY JIMMY ROAD UPPER GROWEE 2849",
    "locID": "LOC000192126641",
    "tech": "SATELLITE",
    "upgrade": "NULL_NA",
    "gnaf_pid": "GANSW720423584",
    "tech_change_status": "Not Planned"
   }
  }
 ]
}