{
 "type": "FeatureCollection",
 "generated": "2024-01-28T17:25:00.183999",
 "suburb": "WARRABAH",
 "features": [
  {
   "type": "Feature",
   "geometry": {
    "type": "Point",
    "coordinates": [
     150.98075881,
     -30.48518374
    ]
   },
   "properties": {
    "name": "1560 WARRABAH ROAD WARRABAH 2346",
    "locID": "ChIJa12x5b43oGsRjl0LGR0FhK8",
    "tech": "SATELLITE",
    "upgrade": "UNKNOWN",
    "gnaf_pid": "GANSW717737097"
   }
  },
  {
   "type": "Feature",
   "geometry": {
    "type": "Point",
    "coordinates": [
     150.98075881,
     -30.48518374
    ]
   },
   "properties": {
    "name": "1947 WARRABAH ROAD WARRABAH 2346",
    "locID": "LOC000078772240",
    "tech": "SATELLITE",
    "upgrade": "NULL_NA",
    "gnaf_pid": "GANSW717737098"
   }
  },
  {
   "type": "Feature",
   "geometry": {
    "type": "Point",
    "coordinates": [
     150.98075881,
     -30.48518374
    ]
   },
   "properties": {
    "name": "1959 WARRABAH ROAD WARRABAH 2346",
    "locID": "ChIJa12x5b43oGsRSPdF4W_M-Dk",
    "tech": "SATELLITE",
    "upgrade": "UNKNOWN",
    "gnaf_pid": "GANSW717737099"
   }
  },
  {
   "type": "Feature",
   "geometry": {
    "type": "Point",
    "coordinates": [
     150.98075881,
     -30.48518374
    ]
   },
   "properties": {
    "name": "2013 WARRABAH ROAD WARRABAH 2346",
    "locID": "LOC000086196014",
    "tech": "SATELLITE",
    "upgrade": "NULL_NA",
    "gnaf_pid": "GANSW717737100"
   }
  },
  {
   "type": "Feature",
   "geometry": {
    "type": "Point",
    "coordinates": [
     150.90188965,
     -30.48881774
    ]
   },
   "properties": {
    "name": "2317 WARRABAH ROAD WARRABAH 2346",
    "locID": "ChIJZ8YTiYFIoGsRyyzhfjnA2TA",
    "tech": "SATELLITE",
    "upgrade": "UNKNOWN",
    "gnaf_pid": "GANSW717737101"
   }
  },
  {
   "type": "Feature",
   "geometry": {
    "type": "Point",
    "coordinates": [
     150.98075881,
     -30.48518374
    ]
   },
   "properties": {
    "name": "685 WARRABAH ROAD WARRABAH 2346",
    "locID": "ChIJa12x5b43oGsR47XYX6ZgeFg",
    "tech": "SATELLITE",
    "upgrade": "UNKNOWN",
    "gnaf_pid": "GANSW717737102"
   }
  },
  {
   "type": "Feature",
   "geometry": {
    "type": "Point",
    "coordinates": [
     151.00461884,
     -30.56478585
    ]
   },
   "properties": {
    "name": "784 STONE HUT ROAD WARRABAH 2346",
    "locID": "ChIJLwPCvAM5oGsRw_gVIjP3bKQ",
    "tech": "SATELLITE",
    "upgrade": "UNKNOWN",
    "gnaf_pid": "GANSW719687464"
   }
  },
  {
   "type": "Feature",
   "geometry": {
    "type": "Point",
    "coordinates": [
     150.95306129,
     -30.45434479
    ]
   },
   "properties": {
    "name": "1 WARRABAH ROAD WARRABAH 2346",
    "locID": "LOC000142494246",
    "tech": "SATELLITE",
    "upgrade": "NULL_NA",
    "gnaf_pid": "GANSW720321535"
   }
  }
 ]
}