{
 "type": "FeatureCollection",
 "generated": "2024-09-10T17:09:21.459684",
 "suburb": "WARRABAH",
 "features": [
  {
   "type": "Feature",
   "geometry": {
    "type": "Point",
    "coordinates": [
     150.98075881,
     -30.48518374
    ]
   },
   "properties": {
    "name": "1947 WARRABAH ROAD WARRABAH 2346",
    "locID": "LOC000078772240",
    "tech": "SATELLITE",
    "upgrade": "NULL_NA",
    "gnaf_pid": "GANSW717737098",
    "tech_change_status": "Not Planned"
   }
  },
  {
   "type": "Feature",
   "geometry": {
    "type": "Point",
    "coordinates": [
     150.98075881,
     -30.48518374
    ]
   },
   "properties": {
    "name": "2013 WARRABAH ROAD WARRABAH 2346",
    "locID": "LOC000086196014",
    "tech": "SATELLITE",
    "upgrade": "NULL_NA",
    "gnaf_pid": "GANSW717737100",
    "tech_change_status": "Not Planned"
   }
  },
  {
   "type": "Feature",
   "geometry": {
    "type": "Point",
    "coordinates": [
     150.95306129,
     -30.45434479
    ]
   },
   "properties": {
    "name": "1 WARRABAH ROAD WARRABAH 2346",
    "locID": "LOC000142494246",
    "tech": "SATELLITE",
    "upgrade": "NULL_NA",
    "gnaf_pid": "GANSW720321535",
    "tech_change_status": "Not Planned"
   }
  }
 ]
}