{
 "type": "FeatureCollection",
 "generated": "2024-08-21T12:13:29.474437",
 "suburb": "WILBETREE",
 "features": [
  {
   "type": "Feature",
   "geometry": {
    "type": "Point",
    "coordinates": [
     149.57246649,
     -32.51058698
    ]
   },
   "properties": {
    "name": "744 WILBETREE ROAD WILBETREE 2850",
    "locID": "LOC000023917638",
    "tech": "SATELLITE",
    "upgrade": "NULL_NA",
    "gnaf_pid": "GANSW706293970",
    "tech_change_status": "Not Planned"
   }
  },
  {
   "type": "Feature",
   "geometry": {
    "type": "Point",
    "coordinates": [
     149.59466992,
     -32.43770785
    ]
   },
   "properties": {
    "name": "1594 WILBETREE ROAD WILBETREE 2850",
    "locID": "LOC000183522059",
    "tech": "WIRELESS",
    "upgrade": "NULL_NA",
    "gnaf_pid": "GANSW707666597",
    "tech_change_status": "Not Planned",
    "program_type": "Fixed Wireless and Satellite Upgrade Program",
    "target_eligibility_quarter": "NA"
   }
  },
  {
   "type": "Feature",
   "geometry": {
    "type": "Point",
    "coordinates": [
     149.58146064,
     -32.48693306
    ]
   },
   "properties": {
    "name": "1050 WILBETREE ROAD WILBETREE 2850",
    "locID": "LOC000122473007",
    "tech": "WIRELESS",
    "upgrade": "NULL_NA",
    "gnaf_pid": "GANSW716178776",
    "tech_change_status": "Not Planned",
    "program_type": "Fixed Wireless and Satellite Upgrade Program",
    "target_eligibility_quarter": "NA"
   }
  },
  {
   "type": "Feature",
   "geometry": {
    "type": "Point",
    "coordinates": [
     149.56983697,
     -32.49474998
    ]
   },
   "properties": {
    "name": "875 WILBETREE ROAD WILBETREE 2850",
    "locID": "LOC000067318397",
    "tech": "WIRELESS",
    "upgrade": "NULL_NA",
    "gnaf_pid": "GANSW716178779",
    "tech_change_status": "Not Planned",
    "program_type": "Fixed Wireless and Satellite Upgrade Program",
    "target_eligibility_quarter": "NA"
   }
  },
  {
   "type": "Feature",
   "geometry": {
    "type": "Point",
    "coordinates": [
     149.59173502,
     -32.46883512
    ]
   },
   "properties": {
    "name": "1393 WILBETREE ROAD WILBETREE 2850",
    "locID": "LOC000047607967",
    "tech": "WIRELESS",
    "upgrade": "NULL_NA",
    "gnaf_pid": "GANSW717029434",
    "tech_change_status": "Not Planned",
    "program_type": "Fixed Wireless and Satellite Upgrade Program",
    "target_eligibility_quarter": "NA"
   }
  },
  {
   "type": "Feature",
   "geometry": {
    "type": "Point",
    "coordinates": [
     149.57790682,
     -32.50208353
    ]
   },
   "properties": {
    "name": "409 SNAKES CREEK ROAD WILBETREE 2850",
    "locID": "LOC000053617924",
    "tech": "SATELLITE",
    "upgrade": "NULL_NA",
    "gnaf_pid": "GANSW717224810",
    "tech_change_status": "Not Planned"
   }
  },
  {
   "type": "Feature",
   "geometry": {
    "type": "Point",
    "coordinates": [
     149.59575515,
     -32.49941854
    ]
   },
   "properties": {
    "name": "177 SNAKES CREEK ROAD WILBETREE 2850",
    "locID": "LOC000122468190",
    "tech": "SATELLITE",
    "upgrade": "NULL_NA",
    "gnaf_pid": "GANSW718269760",
    "tech_change_status": "Not Planned"
   }
  },
  {
   "type": "Feature",
   "geometry": {
    "type": "Point",
    "coordinates": [
     149.57019496,
     -32.50825833
    ]
   },
   "properties": {
    "name": "767 WILBETREE ROAD WILBETREE 2850",
    "locID": "LOC000150155512",
    "tech": "SATELLITE",
    "upgrade": "NULL_NA",
    "gnaf_pid": "GANSW718510614",
    "tech_change_status": "Not Planned"
   }
  },
  {
   "type": "Feature",
   "geometry": {
    "type": "Point",
    "coordinates": [
     149.55751124,
     -32.49503657
    ]
   },
   "properties": {
    "name": "145 GOOREE LANE WILBETREE 2850",
    "locID": "LOC100080415856",
    "tech": "SATELLITE",
    "upgrade": "NULL_NA",
    "gnaf_pid": "GANSW719355449",
    "tech_change_status": "Not Planned"
   }
  },
  {
   "type": "Feature",
   "geometry": {
    "type": "Point",
    "coordinates": [
     149.56531107,
     -32.50238483
    ]
   },
   "properties": {
    "name": "153 GOOREE LANE WILBETREE 2850",
    "locID": "LOC100055419177",
    "tech": "SATELLITE",
    "upgrade": "WIRELESS",
    "gnaf_pid": "GANSW719387050",
    "tech_change_status": "Eligible to Order",
    "program_type": "Fixed Wireless and Satellite Upgrade Program",
    "target_eligibility_quarter": "NA"
   }
  },
  {
   "type": "Feature",
   "geometry": {
    "type": "Point",
    "coordinates": [
     149.56531107,
     -32.50238483
    ]
   },
   "properties": {
    "name": "159 GOOREE LANE WILBETREE 2850",
    "locID": "LOC100055419183",
    "tech": "SATELLITE",
    "upgrade": "NULL_NA",
    "gnaf_pid": "GANSW719389803",
    "tech_change_status": "Not Planned"
   }
  }
 ]
}