{
 "type": "FeatureCollection",
 "generated": "2024-07-12T21:13:20.103486",
 "suburb": "WILLURAH",
 "features": [
  {
   "type": "Feature",
   "geometry": {
    "type": "Point",
    "coordinates": [
     145.09131475,
     -34.99653451
    ]
   },
   "properties": {
    "name": "3365 WILLURAH ROAD WILLURAH 2710",
    "locID": "LOC000047346826",
    "tech": "SATELLITE",
    "upgrade": "NULL_NA",
    "gnaf_pid": "GANSW717228281",
    "tech_change_status": "Not Planned"
   }
  }
 ]
}