{
 "type": "FeatureCollection",
 "generated": "2024-09-28T12:46:18.822331",
 "suburb": "WILPINJONG",
 "features": [
  {
   "type": "Feature",
   "geometry": {
    "type": "Point",
    "coordinates": [
     149.84714783,
     -32.31603369
    ]
   },
   "properties": {
    "name": "981 ULAN-WOLLAR ROAD WILPINJONG 2850",
    "locID": "LOC000100867946",
    "tech": "NULL",
    "upgrade": "NULL_NA",
    "gnaf_pid": "GANSW717901938",
    "tech_change_status": "Not Planned"
   }
  },
  {
   "type": "Feature",
   "geometry": {
    "type": "Point",
    "coordinates": [
     149.86130949,
     -32.32151734
    ]
   },
   "properties": {
    "name": "1206 ULAN-WOLLAR ROAD WILPINJONG 2850",
    "locID": "LOC000062670982",
    "tech": "NULL",
    "upgrade": "NULL_NA",
    "gnaf_pid": "GANSW717931094",
    "tech_change_status": "Not Planned"
   }
  },
  {
   "type": "Feature",
   "geometry": {
    "type": "Point",
    "coordinates": [
     149.89823796,
     -32.35156737
    ]
   },
   "properties": {
    "name": "130 WILPINJONG ROAD WILPINJONG 2850",
    "locID": "LOC000148059111",
    "tech": "NULL",
    "upgrade": "NULL_NA",
    "gnaf_pid": "GANSW718429043",
    "tech_change_status": "Not Planned"
   }
  },
  {
   "type": "Feature",
   "geometry": {
    "type": "Point",
    "coordinates": [
     149.86457516,
     -32.31592367
    ]
   },
   "properties": {
    "name": "1239 ULAN-WOLLAR ROAD WILPINJONG 2850",
    "locID": "LOC100078066441",
    "tech": "NULL",
    "upgrade": "NULL_NA",
    "gnaf_pid": "GANSW718694246",
    "tech_change_status": "Not Planned"
   }
  },
  {
   "type": "Feature",
   "geometry": {
    "type": "Point",
    "coordinates": [
     149.84521308,
     -32.34783199
    ]
   },
   "properties": {
    "name": "2769 WOLLAR ROAD WILPINJONG 2850",
    "locID": "LOC100071954125",
    "tech": "NULL",
    "upgrade": "NULL_NA",
    "gnaf_pid": "GANSW719893380",
    "tech_change_status": "Not Planned"
   }
  }
 ]
}