{
 "type": "FeatureCollection",
 "generated": "2023-12-27T16:40:13.366998",
 "suburb": "WILPINJONG",
 "features": [
  {
   "type": "Feature",
   "geometry": {
    "type": "Point",
    "coordinates": [
     149.85768737,
     -32.32098062
    ]
   },
   "properties": {
    "name": "789 BUNGULLA ROAD WILPINJONG 2850",
    "locID": "ChIJM-y1ghEeDGsRdBpjlRw_50k",
    "tech": "SATELLITE",
    "upgrade": "UNKNOWN",
    "gnaf_pid": "GANSW715673980"
   }
  },
  {
   "type": "Feature",
   "geometry": {
    "type": "Point",
    "coordinates": [
     149.85363237,
     -32.30787953
    ]
   },
   "properties": {
    "name": "31 TRGO CLOSE WILPINJONG 2850",
    "locID": "ChIJeWOCaggeDGsRPo303Qt-k60",
    "tech": "SATELLITE",
    "upgrade": "UNKNOWN",
    "gnaf_pid": "GANSW716131986"
   }
  },
  {
   "type": "Feature",
   "geometry": {
    "type": "Point",
    "coordinates": [
     149.84714783,
     -32.31603369
    ]
   },
   "properties": {
    "name": "981 ULAN-WOLLAR ROAD WILPINJONG 2850",
    "locID": "LOC000100867946",
    "tech": "SATELLITE",
    "upgrade": "NULL_NA",
    "gnaf_pid": "GANSW717901938"
   }
  },
  {
   "type": "Feature",
   "geometry": {
    "type": "Point",
    "coordinates": [
     149.86130949,
     -32.32151734
    ]
   },
   "properties": {
    "name": "1206 ULAN-WOLLAR ROAD WILPINJONG 2850",
    "locID": "LOC000062670982",
    "tech": "SATELLITE",
    "upgrade": "NULL_NA",
    "gnaf_pid": "GANSW717931094"
   }
  },
  {
   "type": "Feature",
   "geometry": {
    "type": "Point",
    "coordinates": [
     149.84522497,
     -32.34783308
    ]
   },
   "properties": {
    "name": "2767 WOLLAR ROAD WILPINJONG 2850",
    "locID": "ChIJOyoAx9MfDGsRcxKhtT-90_A",
    "tech": "SATELLITE",
    "upgrade": "UNKNOWN",
    "gnaf_pid": "GANSW718271841"
   }
  },
  {
   "type": "Feature",
   "geometry": {
    "type": "Point",
    "coordinates": [
     149.91820264,
     -32.33591401
    ]
   },
   "properties": {
    "name": "1780 ULAN-WOLLAR ROAD WILPINJONG 2850",
    "locID": "ChIJmwQ5F7seDGsR6nLp3tmCfEA",
    "tech": "SATELLITE",
    "upgrade": "UNKNOWN",
    "gnaf_pid": "GANSW718364297"
   }
  },
  {
   "type": "Feature",
   "geometry": {
    "type": "Point",
    "coordinates": [
     149.84099311,
     -32.34116518
    ]
   },
   "properties": {
    "name": "294 BUNGULLA ROAD WILPINJONG 2850",
    "locID": "ChIJEY3o34GgDmsRFnUzsn-fDBI",
    "tech": "SATELLITE",
    "upgrade": "UNKNOWN",
    "gnaf_pid": "GANSW718402812"
   }
  },
  {
   "type": "Feature",
   "geometry": {
    "type": "Point",
    "coordinates": [
     149.89823796,
     -32.35156737
    ]
   },
   "properties": {
    "name": "130 WILPINJONG ROAD WILPINJONG 2850",
    "locID": "LOC000148059111",
    "tech": "SATELLITE",
    "upgrade": "NULL_NA",
    "gnaf_pid": "GANSW718429043"
   }
  },
  {
   "type": "Feature",
   "geometry": {
    "type": "Point",
    "coordinates": [
     149.86457516,
     -32.31592367
    ]
   },
   "properties": {
    "name": "1239 ULAN-WOLLAR ROAD WILPINJONG 2850",
    "locID": "LOC100078066441",
    "tech": "SATELLITE",
    "upgrade": "NULL_NA",
    "gnaf_pid": "GANSW718694246"
   }
  },
  {
   "type": "Feature",
   "geometry": {
    "type": "Point",
    "coordinates": [
     149.91948712,
     -32.32114214
    ]
   },
   "properties": {
    "name": "1616 ULAN-WOLLAR ROAD WILPINJONG 2850",
    "locID": "ChIJuzmY8BwcDGsReLSVMGieD3Y",
    "tech": "SATELLITE",
    "upgrade": "UNKNOWN",
    "gnaf_pid": "GANSW718694247"
   }
  },
  {
   "type": "Feature",
   "geometry": {
    "type": "Point",
    "coordinates": [
     149.9182278,
     -32.31343381
    ]
   },
   "properties": {
    "name": "1620 ULAN-WOLLAR ROAD WILPINJONG 2850",
    "locID": "ChIJafdemxAcDGsR_ihRP8RfEW8",
    "tech": "SATELLITE",
    "upgrade": "UNKNOWN",
    "gnaf_pid": "GANSW719357427"
   }
  },
  {
   "type": "Feature",
   "geometry": {
    "type": "Point",
    "coordinates": [
     149.84521308,
     -32.34783199
    ]
   },
   "properties": {
    "name": "2769 WOLLAR ROAD WILPINJONG 2850",
    "locID": "LOC100071954125",
    "tech": "SATELLITE",
    "upgrade": "NULL_NA",
    "gnaf_pid": "GANSW719893380"
   }
  },
  {
   "type": "Feature",
   "geometry": {
    "type": "Point",
    "coordinates": [
     149.91234802,
     -32.33786415
    ]
   },
   "properties": {
    "name": "1676 ULAN-WOLLAR ROAD WILPINJONG 2850",
    "locID": "ChIJryn22L0eDGsRrVJpOq1p3Fg",
    "tech": "SATELLITE",
    "upgrade": "UNKNOWN",
    "gnaf_pid": "GANSW720610374"
   }
  }
 ]
}