{
 "type": "FeatureCollection",
 "generated": "2024-09-25T16:45:02.252535",
 "suburb": "WINDY",
 "features": [
  {
   "type": "Feature",
   "geometry": {
    "type": "Point",
    "coordinates": [
     150.38173634,
     -31.6005289
    ]
   },
   "properties": {
    "name": "1020 WINDY ROAD WINDY 2343",
    "locID": "LOC100078057752",
    "tech": "NULL",
    "upgrade": "NULL_NA",
    "gnaf_pid": "GANSW720538507",
    "tech_change_status": "Not Planned"
   }
  }
 ]
}