{
 "type": "FeatureCollection",
 "generated": "2024-04-15T21:50:26.411685",
 "suburb": "WINDY",
 "features": [
  {
   "type": "Feature",
   "geometry": {
    "type": "Point",
    "coordinates": [
     150.38173634,
     -31.6005289
    ]
   },
   "properties": {
    "name": "1020 WINDY ROAD WINDY 2343",
    "locID": "LOC100078057752",
    "tech": "SATELLITE",
    "upgrade": "NULL_NA",
    "gnaf_pid": "GANSW720538507"
   }
  }
 ]
}