{
 "type": "FeatureCollection",
 "generated": "2023-12-02T14:53:06.713890",
 "suburb": "WINDY",
 "features": [
  {
   "type": "Feature",
   "geometry": {
    "type": "Point",
    "coordinates": [
     150.39159324,
     -31.57709187
    ]
   },
   "properties": {
    "name": "1019 WINDY ROAD WINDY 2343",
    "locID": "EiVXaW5keSBSZCwgQnVycmFnYSBOU1cgMjc5NSwgQXVzdHJhbGlhIi4qLAoUChIJ1eDq49ShEWsRh2bDk5TGwLESFAoSCUmBwI4BnxFrEaBdQ5C0CQYE",
    "tech": "SATELLITE",
    "upgrade": "UNKNOWN",
    "gnaf_pid": "GANSW716474681"
   }
  },
  {
   "type": "Feature",
   "geometry": {
    "type": "Point",
    "coordinates": [
     150.45005487,
     -31.61581097
    ]
   },
   "properties": {
    "name": "1520 CATTLE LANE WINDY 2343",
    "locID": "EjAxNTIwIENhdHRsZSBMbiwgV2FycmFoIFJpZGdlIE5TVyAyMzQzLCBBdXN0cmFsaWEiMRIvChQKEgk3EI6shKwLaxGXqHb6X-Vh1RDwCyoUChIJrxMqHXisC2sR_sJF_NzNzYM",
    "tech": "SATELLITE",
    "upgrade": "UNKNOWN",
    "gnaf_pid": "GANSW718840436"
   }
  },
  {
   "type": "Feature",
   "geometry": {
    "type": "Point",
    "coordinates": [
     150.38173634,
     -31.6005289
    ]
   },
   "properties": {
    "name": "1020 WINDY ROAD WINDY 2343",
    "locID": "LOC100078057752",
    "tech": "SATELLITE",
    "upgrade": "NULL_NA",
    "gnaf_pid": "GANSW720538507"
   }
  }
 ]
}