{
 "type": "FeatureCollection",
 "generated": "2024-07-10T05:18:12.487972",
 "suburb": "WOMBAT CREEK",
 "features": [
  {
   "type": "Feature",
   "geometry": {
    "type": "Point",
    "coordinates": [
     152.76644973,
     -29.51701939
    ]
   },
   "properties": {
    "name": "409 WOMBAT CREEK ROAD WOMBAT CREEK 2460",
    "locID": "LOC000017240632",
    "tech": "SATELLITE",
    "upgrade": "NULL_NA",
    "gnaf_pid": "GANSW706312027",
    "tech_change_status": "Not Planned"
   }
  },
  {
   "type": "Feature",
   "geometry": {
    "type": "Point",
    "coordinates": [
     152.76219125,
     -29.51426429
    ]
   },
   "properties": {
    "name": "451 WOMBAT CREEK ROAD WOMBAT CREEK 2460",
    "locID": "LOC000042240356",
    "tech": "SATELLITE",
    "upgrade": "NULL_NA",
    "gnaf_pid": "GANSW706312028",
    "tech_change_status": "Not Planned"
   }
  },
  {
   "type": "Feature",
   "geometry": {
    "type": "Point",
    "coordinates": [
     152.76565439,
     -29.51299226
    ]
   },
   "properties": {
    "name": "482 WOMBAT CREEK ROAD WOMBAT CREEK 2460",
    "locID": "LOC000038816251",
    "tech": "SATELLITE",
    "upgrade": "NULL_NA",
    "gnaf_pid": "GANSW706312029",
    "tech_change_status": "Not Planned"
   }
  }
 ]
}