{
 "type": "FeatureCollection",
 "generated": "2023-12-04T03:48:12.221438",
 "suburb": "WOMBAT CREEK",
 "features": [
  {
   "type": "Feature",
   "geometry": {
    "type": "Point",
    "coordinates": [
     152.76644973,
     -29.51701939
    ]
   },
   "properties": {
    "name": "409 WOMBAT CREEK ROAD WOMBAT CREEK 2460",
    "locID": "LOC000017240632",
    "tech": "SATELLITE",
    "upgrade": "NULL_NA",
    "gnaf_pid": "GANSW706312027"
   }
  },
  {
   "type": "Feature",
   "geometry": {
    "type": "Point",
    "coordinates": [
     152.76219125,
     -29.51426429
    ]
   },
   "properties": {
    "name": "451 WOMBAT CREEK ROAD WOMBAT CREEK 2460",
    "locID": "LOC000042240356",
    "tech": "SATELLITE",
    "upgrade": "NULL_NA",
    "gnaf_pid": "GANSW706312028"
   }
  },
  {
   "type": "Feature",
   "geometry": {
    "type": "Point",
    "coordinates": [
     152.76565439,
     -29.51299226
    ]
   },
   "properties": {
    "name": "482 WOMBAT CREEK ROAD WOMBAT CREEK 2460",
    "locID": "LOC000038816251",
    "tech": "SATELLITE",
    "upgrade": "NULL_NA",
    "gnaf_pid": "GANSW706312029"
   }
  },
  {
   "type": "Feature",
   "geometry": {
    "type": "Point",
    "coordinates": [
     152.76014982,
     -29.52571876
    ]
   },
   "properties": {
    "name": "164 WOMBAT CREEK ROAD WOMBAT CREEK 2460",
    "locID": "ChIJ7Z5qk_F8mWsROUFvKw3GuHo",
    "tech": "SATELLITE",
    "upgrade": "UNKNOWN",
    "gnaf_pid": "GANSW707674034"
   }
  },
  {
   "type": "Feature",
   "geometry": {
    "type": "Point",
    "coordinates": [
     152.74796129,
     -29.52847319
    ]
   },
   "properties": {
    "name": "268 SMITHS CREEK ROAD WOMBAT CREEK 2460",
    "locID": "ChIJc_l77I18mWsRVZueGS06NSM",
    "tech": "SATELLITE",
    "upgrade": "UNKNOWN",
    "gnaf_pid": "GANSW716236908"
   }
  },
  {
   "type": "Feature",
   "geometry": {
    "type": "Point",
    "coordinates": [
     152.76692348,
     -29.51430199
    ]
   },
   "properties": {
    "name": "480 WOMBAT CREEK ROAD WOMBAT CREEK 2460",
    "locID": "ChIJW8xMe1p8mWsR8G_ZOW4DjcY",
    "tech": "SATELLITE",
    "upgrade": "UNKNOWN",
    "gnaf_pid": "GANSW717486459"
   }
  }
 ]
}