{
 "type": "FeatureCollection",
 "generated": "2024-03-05T01:50:39.530310",
 "suburb": "WOODHOUSELEE",
 "features": [
  {
   "type": "Feature",
   "geometry": {
    "type": "Point",
    "coordinates": [
     149.60490013,
     -34.57033329
    ]
   },
   "properties": {
    "name": "689 WOODHOUSELEE ROAD WOODHOUSELEE 2580",
    "locID": "LOC000115525199",
    "tech": "SATELLITE",
    "upgrade": "NULL_NA",
    "gnaf_pid": "GANSW716906841"
   }
  },
  {
   "type": "Feature",
   "geometry": {
    "type": "Point",
    "coordinates": [
     149.6316413,
     -34.56797118
    ]
   },
   "properties": {
    "name": "674 WOODHOUSELEE ROAD WOODHOUSELEE 2580",
    "locID": "LOC000121460676",
    "tech": "SATELLITE",
    "upgrade": "NULL_NA",
    "gnaf_pid": "GANSW716906842"
   }
  },
  {
   "type": "Feature",
   "geometry": {
    "type": "Point",
    "coordinates": [
     149.63092831,
     -34.56616987
    ]
   },
   "properties": {
    "name": "692 WOODHOUSELEE ROAD WOODHOUSELEE 2580",
    "locID": "LOC000176830050",
    "tech": "SATELLITE",
    "upgrade": "NULL_NA",
    "gnaf_pid": "GANSW718271917"
   }
  },
  {
   "type": "Feature",
   "geometry": {
    "type": "Point",
    "coordinates": [
     149.65677849,
     -34.59037176
    ]
   },
   "properties": {
    "name": "249 ANNIES LANE WOODHOUSELEE 2580",
    "locID": "LOC000121471373",
    "tech": "SATELLITE",
    "upgrade": "NULL_NA",
    "gnaf_pid": "GANSW718348860"
   }
  },
  {
   "type": "Feature",
   "geometry": {
    "type": "Point",
    "coordinates": [
     149.63060172,
     -34.56493904
    ]
   },
   "properties": {
    "name": "708 WOODHOUSELEE ROAD WOODHOUSELEE 2580",
    "locID": "LOC000121466435",
    "tech": "SATELLITE",
    "upgrade": "NULL_NA",
    "gnaf_pid": "GANSW718365161"
   }
  },
  {
   "type": "Feature",
   "geometry": {
    "type": "Point",
    "coordinates": [
     149.65523609,
     -34.59624813
    ]
   },
   "properties": {
    "name": "208 ANNIES LANE WOODHOUSELEE 2580",
    "locID": "LOC100072002120",
    "tech": "SATELLITE",
    "upgrade": "NULL_NA",
    "gnaf_pid": "GANSW718399096"
   }
  },
  {
   "type": "Feature",
   "geometry": {
    "type": "Point",
    "coordinates": [
     149.63281771,
     -34.57387034
    ]
   },
   "properties": {
    "name": "614 WOODHOUSELEE ROAD WOODHOUSELEE 2580",
    "locID": "LOC000154278854",
    "tech": "SATELLITE",
    "upgrade": "NULL_NA",
    "gnaf_pid": "GANSW718429340"
   }
  },
  {
   "type": "Feature",
   "geometry": {
    "type": "Point",
    "coordinates": [
     149.63215146,
     -34.57041536
    ]
   },
   "properties": {
    "name": "650 WOODHOUSELEE ROAD WOODHOUSELEE 2580",
    "locID": "LOC000150156843",
    "tech": "SATELLITE",
    "upgrade": "NULL_NA",
    "gnaf_pid": "GANSW718429341"
   }
  },
  {
   "type": "Feature",
   "geometry": {
    "type": "Point",
    "coordinates": [
     149.66313626,
     -34.59462729
    ]
   },
   "properties": {
    "name": "286 ANNIES LANE WOODHOUSELEE 2580",
    "locID": "LOC100078108995",
    "tech": "SATELLITE",
    "upgrade": "NULL_NA",
    "gnaf_pid": "GANSW718454092"
   }
  },
  {
   "type": "Feature",
   "geometry": {
    "type": "Point",
    "coordinates": [
     149.65541243,
     -34.59175697
    ]
   },
   "properties": {
    "name": "247 ANNIES LANE WOODHOUSELEE 2580",
    "locID": "LOC000156306439",
    "tech": "SATELLITE",
    "upgrade": "NULL_NA",
    "gnaf_pid": "GANSW718641602"
   }
  },
  {
   "type": "Feature",
   "geometry": {
    "type": "Point",
    "coordinates": [
     149.65662292,
     -34.59249238
    ]
   },
   "properties": {
    "name": "288 ANNIES LANE WOODHOUSELEE 2580",
    "locID": "LOC000191518311",
    "tech": "SATELLITE",
    "upgrade": "NULL_NA",
    "gnaf_pid": "GANSW720024949"
   }
  },
  {
   "type": "Feature",
   "geometry": {
    "type": "Point",
    "coordinates": [
     149.63066966,
     -34.5661041
    ]
   },
   "properties": {
    "name": "24 WOODHOUSELEE ROAD WOODHOUSELEE 2580",
    "locID": "LOC000176830050",
    "tech": "SATELLITE",
    "upgrade": "NULL_NA",
    "gnaf_pid": "GANSW720796601"
   }
  }
 ]
}