{
 "type": "FeatureCollection",
 "generated": "2024-09-29T07:50:37.591080",
 "suburb": "WORLDS END",
 "features": [
  {
   "type": "Feature",
   "geometry": {
    "type": "Point",
    "coordinates": [
     149.35287754,
     -32.67851077
    ]
   },
   "properties": {
    "name": "245 WORLDS END ROAD WORLDS END 2850",
    "locID": "LOC000122454962",
    "tech": "SATELLITE",
    "upgrade": "NULL_NA",
    "gnaf_pid": "GANSW717541332",
    "tech_change_status": "Not Planned"
   }
  },
  {
   "type": "Feature",
   "geometry": {
    "type": "Point",
    "coordinates": [
     149.37709702,
     -32.67094925
    ]
   },
   "properties": {
    "name": "1018 WORLDS END ROAD WORLDS END 2850",
    "locID": "LOC000122470235",
    "tech": "SATELLITE",
    "upgrade": "NULL_NA",
    "gnaf_pid": "GANSW718109269",
    "tech_change_status": "Not Planned"
   }
  },
  {
   "type": "Feature",
   "geometry": {
    "type": "Point",
    "coordinates": [
     149.37729621,
     -32.66174248
    ]
   },
   "properties": {
    "name": "1019 WORLDS END ROAD WORLDS END 2850",
    "locID": "LOC000122470274",
    "tech": "SATELLITE",
    "upgrade": "NULL_NA",
    "gnaf_pid": "GANSW718271944",
    "tech_change_status": "Not Planned"
   }
  },
  {
   "type": "Feature",
   "geometry": {
    "type": "Point",
    "coordinates": [
     149.36214844,
     -32.66436355
    ]
   },
   "properties": {
    "name": "826 WORLDS END ROAD WORLDS END 2850",
    "locID": "LOC000122461432",
    "tech": "SATELLITE",
    "upgrade": "NULL_NA",
    "gnaf_pid": "GANSW718271947",
    "tech_change_status": "Not Planned"
   }
  },
  {
   "type": "Feature",
   "geometry": {
    "type": "Point",
    "coordinates": [
     149.36217928,
     -32.67018345
    ]
   },
   "properties": {
    "name": "862 WORLDS END ROAD WORLDS END 2850",
    "locID": "LOC000114964240",
    "tech": "SATELLITE",
    "upgrade": "NULL_NA",
    "gnaf_pid": "GANSW718271950",
    "tech_change_status": "Not Planned"
   }
  },
  {
   "type": "Feature",
   "geometry": {
    "type": "Point",
    "coordinates": [
     149.36845198,
     -32.66422168
    ]
   },
   "properties": {
    "name": "926 WORLDS END ROAD WORLDS END 2850",
    "locID": "LOC000122471256",
    "tech": "NULL",
    "upgrade": "NULL_NA",
    "gnaf_pid": "GANSW718271951",
    "tech_change_status": "Not Planned"
   }
  },
  {
   "type": "Feature",
   "geometry": {
    "type": "Point",
    "coordinates": [
     149.36724401,
     -32.66315347
    ]
   },
   "properties": {
    "name": "931 WORLDS END ROAD WORLDS END 2850",
    "locID": "LOC000122471315",
    "tech": "SATELLITE",
    "upgrade": "NULL_NA",
    "gnaf_pid": "GANSW718271952",
    "tech_change_status": "Not Planned"
   }
  },
  {
   "type": "Feature",
   "geometry": {
    "type": "Point",
    "coordinates": [
     149.35590904,
     -32.66580349
    ]
   },
   "properties": {
    "name": "786 WORLDS END ROAD WORLDS END 2850",
    "locID": "LOC000150157784",
    "tech": "SATELLITE",
    "upgrade": "NULL_NA",
    "gnaf_pid": "GANSW718608346",
    "tech_change_status": "Not Planned"
   }
  },
  {
   "type": "Feature",
   "geometry": {
    "type": "Point",
    "coordinates": [
     149.39796213,
     -32.68526989
    ]
   },
   "properties": {
    "name": "682 GRATTAI CREEK ROAD WORLDS END 2850",
    "locID": "LOC100078071669",
    "tech": "NULL",
    "upgrade": "NULL_NA",
    "gnaf_pid": "GANSW718843994",
    "tech_change_status": "Not Planned"
   }
  }
 ]
}