{
 "type": "FeatureCollection",
 "generated": "2024-01-25T22:41:22.279378",
 "suburb": "YARROW",
 "features": [
  {
   "type": "Feature",
   "geometry": {
    "type": "Point",
    "coordinates": [
     149.31507104,
     -35.4055851
    ]
   },
   "properties": {
    "name": "517 WANNA WANNA ROAD YARROW 2620",
    "locID": "ChIJNwPvheFFFmsRt44pV5AoaCU",
    "tech": "SATELLITE",
    "upgrade": "UNKNOWN",
    "gnaf_pid": "GANSW706383673"
   }
  },
  {
   "type": "Feature",
   "geometry": {
    "type": "Point",
    "coordinates": [
     149.31914642,
     -35.41889279
    ]
   },
   "properties": {
    "name": "519 WANNA WANNA ROAD YARROW 2620",
    "locID": "ChIJASoeJEdGFmsRffvfN3ZHcEM",
    "tech": "SATELLITE",
    "upgrade": "UNKNOWN",
    "gnaf_pid": "GANSW706383674"
   }
  },
  {
   "type": "Feature",
   "geometry": {
    "type": "Point",
    "coordinates": [
     149.3015171,
     -35.45977915
    ]
   },
   "properties": {
    "name": "521 WANNA WANNA ROAD YARROW 2620",
    "locID": "ChIJ6dURw-hHFmsRRKtVkLUJYyI",
    "tech": "SATELLITE",
    "upgrade": "UNKNOWN",
    "gnaf_pid": "GANSW706383675"
   }
  },
  {
   "type": "Feature",
   "geometry": {
    "type": "Point",
    "coordinates": [
     149.31507104,
     -35.4055851
    ]
   },
   "properties": {
    "name": "7715 WANNA WANNA ROAD YARROW 2620",
    "locID": "ChIJZcqQjXNGFmsRI6HheDGSWxo",
    "tech": "SATELLITE",
    "upgrade": "UNKNOWN",
    "gnaf_pid": "GANSW706383676"
   }
  },
  {
   "type": "Feature",
   "geometry": {
    "type": "Point",
    "coordinates": [
     149.34097884,
     -35.46717038
    ]
   },
   "properties": {
    "name": "525 WOOLCARA LANE YARROW 2620",
    "locID": "LOC000102540763",
    "tech": "SATELLITE",
    "upgrade": "NULL_NA",
    "gnaf_pid": "GANSW706383677"
   }
  },
  {
   "type": "Feature",
   "geometry": {
    "type": "Point",
    "coordinates": [
     149.31967633,
     -35.40321352
    ]
   },
   "properties": {
    "name": "518 WANNA WANNA ROAD YARROW 2620",
    "locID": "ChIJue64Mn9GFmsRQyk-fv6FfTc",
    "tech": "SATELLITE",
    "upgrade": "UNKNOWN",
    "gnaf_pid": "GANSW718364636"
   }
  },
  {
   "type": "Feature",
   "geometry": {
    "type": "Point",
    "coordinates": [
     149.30774567,
     -35.44735143
    ]
   },
   "properties": {
    "name": "523 WANNA WANNA ROAD YARROW 2620",
    "locID": "EjA1MjMgV2FubmEgV2FubmEgUmQsIENhcndvb2xhIE5TVyAyNjIwLCBBdXN0cmFsaWEiMRIvChQKEgl_jDxAWE8WaxGaP3yNe762ChCLBCoUChIJxw-xfBBGFmsRcTYlnPaaDfs",
    "tech": "SATELLITE",
    "upgrade": "UNKNOWN",
    "gnaf_pid": "GANSW719362277"
   }
  },
  {
   "type": "Feature",
   "geometry": {
    "type": "Point",
    "coordinates": [
     149.30353546,
     -35.4013636
    ]
   },
   "properties": {
    "name": "516 WANNA WANNA ROAD YARROW 2620",
    "locID": "ChIJLSjGQVhPFmsRGkrZwJEJ5a0",
    "tech": "SATELLITE",
    "upgrade": "UNKNOWN",
    "gnaf_pid": "GANSW720636193"
   }
  }
 ]
}