{
 "type": "FeatureCollection",
 "generated": "2024-04-17T07:01:19.073347",
 "suburb": "YARROW",
 "features": [
  {
   "type": "Feature",
   "geometry": {
    "type": "Point",
    "coordinates": [
     149.34097884,
     -35.46717038
    ]
   },
   "properties": {
    "name": "525 WOOLCARA LANE YARROW 2620",
    "locID": "LOC000102540763",
    "tech": "SATELLITE",
    "upgrade": "NULL_NA",
    "gnaf_pid": "GANSW706383677"
   }
  }
 ]
}