{
 "type": "FeatureCollection",
 "generated": "2024-08-11T09:54:58.774538",
 "suburb": "BOOBYALLA",
 "features": [
  {
   "type": "Feature",
   "geometry": {
    "type": "Point",
    "coordinates": [
     147.84618837,
     -40.94540854
    ]
   },
   "properties": {
    "name": "4428 WATERHOUSE ROAD BOOBYALLA 7264",
    "locID": "LOC000091808249",
    "tech": "SATELLITE",
    "upgrade": "NULL_NA",
    "gnaf_pid": "GATAS702398743",
    "tech_change_status": "Not Planned"
   }
  },
  {
   "type": "Feature",
   "geometry": {
    "type": "Point",
    "coordinates": [
     147.88910631,
     -40.88377773
    ]
   },
   "properties": {
    "name": "590 BOOBYALLA ROAD BOOBYALLA 7264",
    "locID": "LOC000048709985",
    "tech": "SATELLITE",
    "upgrade": "NULL_NA",
    "gnaf_pid": "GATAS702398744",
    "tech_change_status": "Not Planned"
   }
  }
 ]
}