{
 "type": "FeatureCollection",
 "generated": "2023-10-22T18:37:21.963759",
 "suburb": "BOOBYALLA",
 "features": [
  {
   "type": "Feature",
   "geometry": {
    "type": "Point",
    "coordinates": [
     147.84618837,
     -40.94540854
    ]
   },
   "properties": {
    "name": "4428 WATERHOUSE ROAD BOOBYALLA 7264",
    "locID": "LOC000091808249",
    "tech": "SATELLITE",
    "upgrade": "NULL_NA",
    "gnaf_pid": "GATAS702398743"
   }
  },
  {
   "type": "Feature",
   "geometry": {
    "type": "Point",
    "coordinates": [
     147.88910631,
     -40.88377773
    ]
   },
   "properties": {
    "name": "590 BOOBYALLA ROAD BOOBYALLA 7264",
    "locID": "LOC000048709985",
    "tech": "SATELLITE",
    "upgrade": "NULL_NA",
    "gnaf_pid": "GATAS702398744"
   }
  },
  {
   "type": "Feature",
   "geometry": {
    "type": "Point",
    "coordinates": [
     147.87407486,
     -40.92136048
    ]
   },
   "properties": {
    "name": "5462 WATERHOUSE ROAD BOOBYALLA 7264",
    "locID": "ChIJt5buaFB5d6oREzFJGiMESZQ",
    "tech": "SATELLITE",
    "upgrade": "UNKNOWN",
    "gnaf_pid": "GATAS716241848"
   }
  },
  {
   "type": "Feature",
   "geometry": {
    "type": "Point",
    "coordinates": [
     147.88425243,
     -40.88172754
    ]
   },
   "properties": {
    "name": "592 BOOBYALLA ROAD BOOBYALLA 7264",
    "locID": "ChIJCz5lFDx_d6oR3xIjS_Jlpo4",
    "tech": "SATELLITE",
    "upgrade": "UNKNOWN",
    "gnaf_pid": "GATAS720484875"
   }
  }
 ]
}