{
 "type": "FeatureCollection",
 "generated": "2024-08-11T10:21:57.388840",
 "suburb": "CAPE PORTLAND",
 "features": [
  {
   "type": "Feature",
   "geometry": {
    "type": "Point",
    "coordinates": [
     148.0236033,
     -40.77847775
    ]
   },
   "properties": {
    "name": "2205 CAPE PORTLAND ROAD CAPE PORTLAND 7264",
    "locID": "LOC100072630826",
    "tech": "SATELLITE",
    "upgrade": "NULL_NA",
    "gnaf_pid": "GATAS702221717",
    "tech_change_status": "Not Planned"
   }
  },
  {
   "type": "Feature",
   "geometry": {
    "type": "Point",
    "coordinates": [
     148.0364037,
     -40.76095548
    ]
   },
   "properties": {
    "name": "558 LITTLE MUSSELROE ROAD CAPE PORTLAND 7264",
    "locID": "LOC000023487403",
    "tech": "SATELLITE",
    "upgrade": "NULL_NA",
    "gnaf_pid": "GATAS702409119",
    "tech_change_status": "Not Planned"
   }
  },
  {
   "type": "Feature",
   "geometry": {
    "type": "Point",
    "coordinates": [
     147.9985461,
     -40.79137866
    ]
   },
   "properties": {
    "name": "2098 CAPE PORTLAND ROAD CAPE PORTLAND 7264",
    "locID": "LOC000034938943",
    "tech": "SATELLITE",
    "upgrade": "NULL_NA",
    "gnaf_pid": "GATAS716713231",
    "tech_change_status": "Not Planned"
   }
  },
  {
   "type": "Feature",
   "geometry": {
    "type": "Point",
    "coordinates": [
     148.03459459,
     -40.76156374
    ]
   },
   "properties": {
    "name": "536 LITTLE MUSSELROE ROAD CAPE PORTLAND 7264",
    "locID": "LOC100072049835",
    "tech": "SATELLITE",
    "upgrade": "NULL_NA",
    "gnaf_pid": "GATAS719066380",
    "tech_change_status": "Not Planned"
   }
  },
  {
   "type": "Feature",
   "geometry": {
    "type": "Point",
    "coordinates": [
     148.03435149,
     -40.7621585
    ]
   },
   "properties": {
    "name": "530 LITTLE MUSSELROE ROAD CAPE PORTLAND 7264",
    "locID": "LOC100078870941",
    "tech": "SATELLITE",
    "upgrade": "NULL_NA",
    "gnaf_pid": "GATAS720275044",
    "tech_change_status": "Not Planned"
   }
  }
 ]
}