{
 "type": "FeatureCollection",
 "generated": "2023-10-22T18:56:17.101488",
 "suburb": "CAPE PORTLAND",
 "features": [
  {
   "type": "Feature",
   "geometry": {
    "type": "Point",
    "coordinates": [
     148.0236033,
     -40.77847775
    ]
   },
   "properties": {
    "name": "2205 CAPE PORTLAND ROAD CAPE PORTLAND 7264",
    "locID": "LOC100072630826",
    "tech": "SATELLITE",
    "upgrade": "NULL_NA",
    "gnaf_pid": "GATAS702221717"
   }
  },
  {
   "type": "Feature",
   "geometry": {
    "type": "Point",
    "coordinates": [
     148.0364037,
     -40.76095548
    ]
   },
   "properties": {
    "name": "558 LITTLE MUSSELROE ROAD CAPE PORTLAND 7264",
    "locID": "LOC000023487403",
    "tech": "SATELLITE",
    "upgrade": "NULL_NA",
    "gnaf_pid": "GATAS702409119"
   }
  },
  {
   "type": "Feature",
   "geometry": {
    "type": "Point",
    "coordinates": [
     147.9985461,
     -40.79137866
    ]
   },
   "properties": {
    "name": "2019 CAPE PORTLAND ROAD CAPE PORTLAND 7264",
    "locID": "ChIJzfHzPpKGd6oRNP40Q6RGNSg",
    "tech": "SATELLITE",
    "upgrade": "UNKNOWN",
    "gnaf_pid": "GATAS702409120"
   }
  },
  {
   "type": "Feature",
   "geometry": {
    "type": "Point",
    "coordinates": [
     147.9985461,
     -40.79137866
    ]
   },
   "properties": {
    "name": "2098 CAPE PORTLAND ROAD CAPE PORTLAND 7264",
    "locID": "ChIJzfHzPpKGd6oRJ07Gdc4vcqU",
    "tech": "SATELLITE",
    "upgrade": "UNKNOWN",
    "gnaf_pid": "GATAS716713231"
   }
  },
  {
   "type": "Feature",
   "geometry": {
    "type": "Point",
    "coordinates": [
     148.03459459,
     -40.76156374
    ]
   },
   "properties": {
    "name": "536 LITTLE MUSSELROE ROAD CAPE PORTLAND 7264",
    "locID": "LOC100072049835",
    "tech": "SATELLITE",
    "upgrade": "NULL_NA",
    "gnaf_pid": "GATAS719066380"
   }
  },
  {
   "type": "Feature",
   "geometry": {
    "type": "Point",
    "coordinates": [
     148.03435149,
     -40.7621585
    ]
   },
   "properties": {
    "name": "530 LITTLE MUSSELROE ROAD CAPE PORTLAND 7264",
    "locID": "LOC100078870941",
    "tech": "SATELLITE",
    "upgrade": "NULL_NA",
    "gnaf_pid": "GATAS720275044"
   }
  },
  {
   "type": "Feature",
   "geometry": {
    "type": "Point",
    "coordinates": [
     148.0325093,
     -40.76956126
    ]
   },
   "properties": {
    "name": "490 LITTLE MUSSELROE ROAD CAPE PORTLAND 7264",
    "locID": "ChIJeaOzTxKGd6oRr4aBMvYzQRE",
    "tech": "SATELLITE",
    "upgrade": "UNKNOWN",
    "gnaf_pid": "GATAS720713215"
   }
  }
 ]
}