{
 "type": "FeatureCollection",
 "generated": "2024-07-04T17:31:24.575679",
 "suburb": "FORESTER",
 "features": [
  {
   "type": "Feature",
   "geometry": {
    "type": "Point",
    "coordinates": [
     147.67633722,
     -41.08156534
    ]
   },
   "properties": {
    "name": "10 BASE ROAD FORESTER 7260",
    "locID": "LOC000028374241",
    "tech": "SATELLITE",
    "upgrade": "NULL_NA",
    "gnaf_pid": "GATAS702193960",
    "tech_change_status": "Not Planned"
   }
  },
  {
   "type": "Feature",
   "geometry": {
    "type": "Point",
    "coordinates": [
     147.64734956,
     -41.08493574
    ]
   },
   "properties": {
    "name": "1152 FORESTER ROAD FORESTER 7260",
    "locID": "LOC000096492640",
    "tech": "SATELLITE",
    "upgrade": "NULL_NA",
    "gnaf_pid": "GATAS702238785",
    "tech_change_status": "Not Planned"
   }
  },
  {
   "type": "Feature",
   "geometry": {
    "type": "Point",
    "coordinates": [
     147.69085661,
     -41.09713595
    ]
   },
   "properties": {
    "name": "585 FORESTER ROAD FORESTER 7260",
    "locID": "LOC000102852112",
    "tech": "SATELLITE",
    "upgrade": "NULL_NA",
    "gnaf_pid": "GATAS702249561",
    "tech_change_status": "Not Planned"
   }
  },
  {
   "type": "Feature",
   "geometry": {
    "type": "Point",
    "coordinates": [
     147.68302083,
     -41.0951332
    ]
   },
   "properties": {
    "name": "587 FORESTER ROAD FORESTER 7260",
    "locID": "LOC000010170552",
    "tech": "SATELLITE",
    "upgrade": "NULL_NA",
    "gnaf_pid": "GATAS702249564",
    "tech_change_status": "Not Planned"
   }
  },
  {
   "type": "Feature",
   "geometry": {
    "type": "Point",
    "coordinates": [
     147.64734956,
     -41.08493574
    ]
   },
   "properties": {
    "name": "UNIT HO2, 1152 FORESTER ROAD FORESTER 7260",
    "locID": "LOC000096492640",
    "tech": "SATELLITE",
    "upgrade": "NULL_NA",
    "gnaf_pid": "GATAS721085580",
    "tech_change_status": "Not Planned"
   }
  }
 ]
}