{
 "type": "FeatureCollection",
 "generated": "2023-10-22T20:38:42.148348",
 "suburb": "FORESTER",
 "features": [
  {
   "type": "Feature",
   "geometry": {
    "type": "Point",
    "coordinates": [
     147.67633722,
     -41.08156534
    ]
   },
   "properties": {
    "name": "10 BASE ROAD FORESTER 7260",
    "locID": "LOC000028374241",
    "tech": "SATELLITE",
    "upgrade": "NULL_NA",
    "gnaf_pid": "GATAS702193960"
   }
  },
  {
   "type": "Feature",
   "geometry": {
    "type": "Point",
    "coordinates": [
     147.64734956,
     -41.08493574
    ]
   },
   "properties": {
    "name": "1152 FORESTER ROAD FORESTER 7260",
    "locID": "LOC000096492640",
    "tech": "SATELLITE",
    "upgrade": "NULL_NA",
    "gnaf_pid": "GATAS702238785"
   }
  },
  {
   "type": "Feature",
   "geometry": {
    "type": "Point",
    "coordinates": [
     147.67450697,
     -41.08490038
    ]
   },
   "properties": {
    "name": "803 FORESTER ROAD FORESTER 7260",
    "locID": "ChIJVYA8d1tnd6oR467KZk_g_0Q",
    "tech": "SATELLITE",
    "upgrade": "UNKNOWN",
    "gnaf_pid": "GATAS702248735"
   }
  },
  {
   "type": "Feature",
   "geometry": {
    "type": "Point",
    "coordinates": [
     147.69085661,
     -41.09713595
    ]
   },
   "properties": {
    "name": "585 FORESTER ROAD FORESTER 7260",
    "locID": "LOC000102852112",
    "tech": "SATELLITE",
    "upgrade": "NULL_NA",
    "gnaf_pid": "GATAS702249561"
   }
  },
  {
   "type": "Feature",
   "geometry": {
    "type": "Point",
    "coordinates": [
     147.68302083,
     -41.0951332
    ]
   },
   "properties": {
    "name": "587 FORESTER ROAD FORESTER 7260",
    "locID": "LOC000010170552",
    "tech": "SATELLITE",
    "upgrade": "NULL_NA",
    "gnaf_pid": "GATAS702249564"
   }
  },
  {
   "type": "Feature",
   "geometry": {
    "type": "Point",
    "coordinates": [
     147.64734956,
     -41.08493574
    ]
   },
   "properties": {
    "name": "UNIT HO2, 1152 FORESTER ROAD FORESTER 7260",
    "locID": "LOC000096492640",
    "tech": "SATELLITE",
    "upgrade": "NULL_NA",
    "gnaf_pid": "GATAS721085580"
   }
  }
 ]
}