{
 "type": "FeatureCollection",
 "generated": "2023-12-17T21:31:14.318160",
 "suburb": "FORTESCUE",
 "features": [
  {
   "type": "Feature",
   "geometry": {
    "type": "Point",
    "coordinates": [
     147.92018074,
     -43.11830997
    ]
   },
   "properties": {
    "name": "1200 FORTESCUE BAY ROAD FORTESCUE 7182",
    "locID": "ChIJU2lLv4ukbaoRUkDX0R653Ak",
    "tech": "SATELLITE",
    "upgrade": "UNKNOWN",
    "gnaf_pid": "GATAS720883182"
   }
  }
 ]
}