{
 "type": "FeatureCollection",
 "generated": "2023-10-22T20:41:10.663399",
 "suburb": "FREYCINET",
 "features": [
  {
   "type": "Feature",
   "geometry": {
    "type": "Point",
    "coordinates": [
     148.29759345,
     -42.12448474
    ]
   },
   "properties": {
    "name": "140 FREYCINET DRIVE FREYCINET 7215",
    "locID": "ChIJ972Z3_99caoRVK3rllbCJxU",
    "tech": "WIRELESS",
    "upgrade": "UNKNOWN",
    "gnaf_pid": "GATAS720639704"
   }
  },
  {
   "type": "Feature",
   "geometry": {
    "type": "Point",
    "coordinates": [
     148.29908241,
     -42.12295412
    ]
   },
   "properties": {
    "name": "119 FREYCINET DRIVE FREYCINET 7215",
    "locID": "ChIJ1UYUpP99caoRKrJybjKl4N4",
    "tech": "WIRELESS",
    "upgrade": "UNKNOWN",
    "gnaf_pid": "GATAS720639910"
   }
  },
  {
   "type": "Feature",
   "geometry": {
    "type": "Point",
    "coordinates": [
     148.29903323,
     -42.12335576
    ]
   },
   "properties": {
    "name": "117 FREYCINET DRIVE FREYCINET 7215",
    "locID": "ChIJt_qhvf99caoRU5xEVsWcqnY",
    "tech": "WIRELESS",
    "upgrade": "UNKNOWN",
    "gnaf_pid": "GATAS720640037"
   }
  },
  {
   "type": "Feature",
   "geometry": {
    "type": "Point",
    "coordinates": [
     148.2978437,
     -42.1249242
    ]
   },
   "properties": {
    "name": "138 FREYCINET DRIVE FREYCINET 7215",
    "locID": "ChIJRb_IDgB-caoRkxH82Z1XSPM",
    "tech": "WIRELESS",
    "upgrade": "UNKNOWN",
    "gnaf_pid": "GATAS720640744"
   }
  },
  {
   "type": "Feature",
   "geometry": {
    "type": "Point",
    "coordinates": [
     148.29830033,
     -42.12397884
    ]
   },
   "properties": {
    "name": "113 FREYCINET DRIVE FREYCINET 7215",
    "locID": "ChIJpX6rKvDVc6oRuxKMmTLoLcQ",
    "tech": "WIRELESS",
    "upgrade": "UNKNOWN",
    "gnaf_pid": "GATAS720640830"
   }
  },
  {
   "type": "Feature",
   "geometry": {
    "type": "Point",
    "coordinates": [
     148.29930662,
     -42.12412705
    ]
   },
   "properties": {
    "name": "115 FREYCINET DRIVE FREYCINET 7215",
    "locID": "ChIJpX6rKvDVc6oRk3CCs9NK7gE",
    "tech": "WIRELESS",
    "upgrade": "UNKNOWN",
    "gnaf_pid": "GATAS720640971"
   }
  }
 ]
}