{
 "type": "FeatureCollection",
 "generated": "2023-10-22T22:06:46.234464",
 "suburb": "KAMONA",
 "features": [
  {
   "type": "Feature",
   "geometry": {
    "type": "Point",
    "coordinates": [
     147.65221778,
     -41.15911959
    ]
   },
   "properties": {
    "name": "113 KAMONA VALLEY ROAD KAMONA 7260",
    "locID": "LOC000045660976",
    "tech": "WIRELESS",
    "upgrade": "NULL_NA",
    "gnaf_pid": "GATAS702274443"
   }
  },
  {
   "type": "Feature",
   "geometry": {
    "type": "Point",
    "coordinates": [
     147.67182966,
     -41.11373332
    ]
   },
   "properties": {
    "name": "786 KAMONA VALLEY ROAD KAMONA 7260",
    "locID": "LOC000085450419",
    "tech": "SATELLITE",
    "upgrade": "NULL_NA",
    "gnaf_pid": "GATAS702277273"
   }
  },
  {
   "type": "Feature",
   "geometry": {
    "type": "Point",
    "coordinates": [
     147.66780043,
     -41.15229106
    ]
   },
   "properties": {
    "name": "244 KAMONA VALLEY ROAD KAMONA 7260",
    "locID": "LOC000062405723",
    "tech": "WIRELESS",
    "upgrade": "NULL_NA",
    "gnaf_pid": "GATAS702277274"
   }
  },
  {
   "type": "Feature",
   "geometry": {
    "type": "Point",
    "coordinates": [
     147.65631389,
     -41.15454948
    ]
   },
   "properties": {
    "name": "155 KAMONA VALLEY ROAD KAMONA 7260",
    "locID": "LOC000041369486",
    "tech": "WIRELESS",
    "upgrade": "NULL_NA",
    "gnaf_pid": "GATAS702278807"
   }
  },
  {
   "type": "Feature",
   "geometry": {
    "type": "Point",
    "coordinates": [
     147.6610515,
     -41.15310387
    ]
   },
   "properties": {
    "name": "186 KAMONA VALLEY ROAD KAMONA 7260",
    "locID": "LOC000088599435",
    "tech": "WIRELESS",
    "upgrade": "NULL_NA",
    "gnaf_pid": "GATAS702456912"
   }
  },
  {
   "type": "Feature",
   "geometry": {
    "type": "Point",
    "coordinates": [
     147.66086613,
     -41.16212302
    ]
   },
   "properties": {
    "name": "156 KAMONA VALLEY ROAD KAMONA 7260",
    "locID": "LOC000093549101",
    "tech": "WIRELESS",
    "upgrade": "NULL_NA",
    "gnaf_pid": "GATAS702470633"
   }
  },
  {
   "type": "Feature",
   "geometry": {
    "type": "Point",
    "coordinates": [
     147.65876075,
     -41.15097638
    ]
   },
   "properties": {
    "name": "229 KAMONA VALLEY ROAD KAMONA 7260",
    "locID": "ChIJM5ML4pZcd6oReielt27dTdk",
    "tech": "WIRELESS",
    "upgrade": "UNKNOWN",
    "gnaf_pid": "GATAS720484805"
   }
  },
  {
   "type": "Feature",
   "geometry": {
    "type": "Point",
    "coordinates": [
     147.65195032,
     -41.15713099
    ]
   },
   "properties": {
    "name": "115 KAMONA VALLEY ROAD KAMONA 7260",
    "locID": "EjAxMTUgS2Ftb25hIFZhbGxleSBSZCwgS2Ftb25hIFRBUyA3MjYwLCBBdXN0cmFsaWEiMBIuChQKEglRJVjPoVx3qhFuBtUGvJxb9BBzKhQKEgnRtOet8Fx3qhE26XDTBhXlng",
    "tech": "WIRELESS",
    "upgrade": "UNKNOWN",
    "gnaf_pid": "GATAS720485253"
   }
  }
 ]
}