{
 "type": "FeatureCollection",
 "generated": "2024-07-04T18:53:58.653618",
 "suburb": "KAMONA",
 "features": [
  {
   "type": "Feature",
   "geometry": {
    "type": "Point",
    "coordinates": [
     147.65221778,
     -41.15911959
    ]
   },
   "properties": {
    "name": "113 KAMONA VALLEY ROAD KAMONA 7260",
    "locID": "LOC000045660976",
    "tech": "WIRELESS",
    "upgrade": "NULL_NA",
    "gnaf_pid": "GATAS702274443",
    "tech_change_status": "Not Planned",
    "program_type": "Fixed Wireless and Satellite Upgrade Program",
    "target_eligibility_quarter": "Dec 2024"
   }
  },
  {
   "type": "Feature",
   "geometry": {
    "type": "Point",
    "coordinates": [
     147.67182966,
     -41.11373332
    ]
   },
   "properties": {
    "name": "786 KAMONA VALLEY ROAD KAMONA 7260",
    "locID": "LOC000085450419",
    "tech": "SATELLITE",
    "upgrade": "NULL_NA",
    "gnaf_pid": "GATAS702277273",
    "tech_change_status": "Not Planned"
   }
  },
  {
   "type": "Feature",
   "geometry": {
    "type": "Point",
    "coordinates": [
     147.66780043,
     -41.15229106
    ]
   },
   "properties": {
    "name": "244 KAMONA VALLEY ROAD KAMONA 7260",
    "locID": "LOC000062405723",
    "tech": "WIRELESS",
    "upgrade": "NULL_NA",
    "gnaf_pid": "GATAS702277274",
    "tech_change_status": "Not Planned",
    "program_type": "Fixed Wireless and Satellite Upgrade Program",
    "target_eligibility_quarter": "Dec 2024"
   }
  },
  {
   "type": "Feature",
   "geometry": {
    "type": "Point",
    "coordinates": [
     147.65631389,
     -41.15454948
    ]
   },
   "properties": {
    "name": "155 KAMONA VALLEY ROAD KAMONA 7260",
    "locID": "LOC000041369486",
    "tech": "WIRELESS",
    "upgrade": "NULL_NA",
    "gnaf_pid": "GATAS702278807",
    "tech_change_status": "Not Planned",
    "program_type": "Fixed Wireless and Satellite Upgrade Program",
    "target_eligibility_quarter": "Dec 2024"
   }
  },
  {
   "type": "Feature",
   "geometry": {
    "type": "Point",
    "coordinates": [
     147.6610515,
     -41.15310387
    ]
   },
   "properties": {
    "name": "186 KAMONA VALLEY ROAD KAMONA 7260",
    "locID": "LOC000088599435",
    "tech": "WIRELESS",
    "upgrade": "NULL_NA",
    "gnaf_pid": "GATAS702456912",
    "tech_change_status": "Not Planned",
    "program_type": "Fixed Wireless and Satellite Upgrade Program",
    "target_eligibility_quarter": "Dec 2024"
   }
  },
  {
   "type": "Feature",
   "geometry": {
    "type": "Point",
    "coordinates": [
     147.66086613,
     -41.16212302
    ]
   },
   "properties": {
    "name": "156 KAMONA VALLEY ROAD KAMONA 7260",
    "locID": "LOC000093549101",
    "tech": "WIRELESS",
    "upgrade": "NULL_NA",
    "gnaf_pid": "GATAS702470633",
    "tech_change_status": "Not Planned",
    "program_type": "Fixed Wireless and Satellite Upgrade Program",
    "target_eligibility_quarter": "Dec 2024"
   }
  }
 ]
}