{
 "type": "FeatureCollection",
 "generated": "2023-10-22T22:15:47.357207",
 "suburb": "KILLORA",
 "features": [
  {
   "type": "Feature",
   "geometry": {
    "type": "Point",
    "coordinates": [
     147.32297198,
     -43.09577365
    ]
   },
   "properties": {
    "name": "471 KILLORA ROAD KILLORA 7150",
    "locID": "LOC000072348475",
    "tech": "WIRELESS",
    "upgrade": "NULL_NA",
    "gnaf_pid": "GATAS702275917"
   }
  },
  {
   "type": "Feature",
   "geometry": {
    "type": "Point",
    "coordinates": [
     147.32296697,
     -43.09481914
    ]
   },
   "properties": {
    "name": "459 KILLORA ROAD KILLORA 7150",
    "locID": "LOC000103826829",
    "tech": "WIRELESS",
    "upgrade": "NULL_NA",
    "gnaf_pid": "GATAS702275918"
   }
  },
  {
   "type": "Feature",
   "geometry": {
    "type": "Point",
    "coordinates": [
     147.32298332,
     -43.09559352
    ]
   },
   "properties": {
    "name": "469 KILLORA ROAD KILLORA 7150",
    "locID": "LOC000035065483",
    "tech": "WIRELESS",
    "upgrade": "NULL_NA",
    "gnaf_pid": "GATAS702275919"
   }
  },
  {
   "type": "Feature",
   "geometry": {
    "type": "Point",
    "coordinates": [
     147.32279404,
     -43.09464853
    ]
   },
   "properties": {
    "name": "457 KILLORA ROAD KILLORA 7150",
    "locID": "LOC000096380057",
    "tech": "WIRELESS",
    "upgrade": "NULL_NA",
    "gnaf_pid": "GATAS702275920"
   }
  },
  {
   "type": "Feature",
   "geometry": {
    "type": "Point",
    "coordinates": [
     147.32301815,
     -43.09520621
    ]
   },
   "properties": {
    "name": "461 KILLORA ROAD KILLORA 7150",
    "locID": "ChIJqbMxvW3SbaoRXJcZELBu_No",
    "tech": "WIRELESS",
    "upgrade": "UNKNOWN",
    "gnaf_pid": "GATAS702275921"
   }
  },
  {
   "type": "Feature",
   "geometry": {
    "type": "Point",
    "coordinates": [
     147.32328472,
     -43.09682634
    ]
   },
   "properties": {
    "name": "481 KILLORA ROAD KILLORA 7150",
    "locID": "LOC000047091531",
    "tech": "WIRELESS",
    "upgrade": "NULL_NA",
    "gnaf_pid": "GATAS702275922"
   }
  },
  {
   "type": "Feature",
   "geometry": {
    "type": "Point",
    "coordinates": [
     147.32301982,
     -43.09615244
    ]
   },
   "properties": {
    "name": "475 KILLORA ROAD KILLORA 7150",
    "locID": "LOC000095026773",
    "tech": "WIRELESS",
    "upgrade": "NULL_NA",
    "gnaf_pid": "GATAS717937780"
   }
  },
  {
   "type": "Feature",
   "geometry": {
    "type": "Point",
    "coordinates": [
     147.32505626,
     -43.09189634
    ]
   },
   "properties": {
    "name": "418 NEBRASKA ROAD KILLORA 7150",
    "locID": "ChIJ9Y78JxPSbaoR2AxS8SDQcUw",
    "tech": "WIRELESS",
    "upgrade": "UNKNOWN",
    "gnaf_pid": "GATAS718482021"
   }
  },
  {
   "type": "Feature",
   "geometry": {
    "type": "Point",
    "coordinates": [
     147.32432308,
     -43.09192512
    ]
   },
   "properties": {
    "name": "420 NEBRASKA ROAD KILLORA 7150",
    "locID": "ChIJsbeNLhPSbaoRLLtXTDcHgIE",
    "tech": "WIRELESS",
    "upgrade": "UNKNOWN",
    "gnaf_pid": "GATAS718482022"
   }
  },
  {
   "type": "Feature",
   "geometry": {
    "type": "Point",
    "coordinates": [
     147.32365857,
     -43.09180643
    ]
   },
   "properties": {
    "name": "422 NEBRASKA ROAD KILLORA 7150",
    "locID": "ChIJXzH6MxPSbaoR20wGAgY7quo",
    "tech": "WIRELESS",
    "upgrade": "UNKNOWN",
    "gnaf_pid": "GATAS718482023"
   }
  },
  {
   "type": "Feature",
   "geometry": {
    "type": "Point",
    "coordinates": [
     147.32300417,
     -43.09273232
    ]
   },
   "properties": {
    "name": "424 NEBRASKA ROAD KILLORA 7150",
    "locID": "ChIJ8-FJ22zSbaoR3Qzx4Lxhixo",
    "tech": "WIRELESS",
    "upgrade": "UNKNOWN",
    "gnaf_pid": "GATAS718482024"
   }
  },
  {
   "type": "Feature",
   "geometry": {
    "type": "Point",
    "coordinates": [
     147.32351269,
     -43.09449558
    ]
   },
   "properties": {
    "name": "451 NEBRASKA ROAD KILLORA 7150",
    "locID": "LOC100079394301",
    "tech": "WIRELESS",
    "upgrade": "NULL_NA",
    "gnaf_pid": "GATAS718482025"
   }
  },
  {
   "type": "Feature",
   "geometry": {
    "type": "Point",
    "coordinates": [
     147.32581453,
     -43.09192871
    ]
   },
   "properties": {
    "name": "414 NEBRASKA ROAD KILLORA 7150",
    "locID": "ChIJKe-i2xLSbaoRjS91pchUcI0",
    "tech": "WIRELESS",
    "upgrade": "UNKNOWN",
    "gnaf_pid": "GATAS721208166"
   }
  }
 ]
}