{
 "type": "FeatureCollection",
 "generated": "2024-07-04T19:03:03.653053",
 "suburb": "KILLORA",
 "features": [
  {
   "type": "Feature",
   "geometry": {
    "type": "Point",
    "coordinates": [
     147.32297198,
     -43.09577365
    ]
   },
   "properties": {
    "name": "471 KILLORA ROAD KILLORA 7150",
    "locID": "LOC000072348475",
    "tech": "WIRELESS",
    "upgrade": "NULL_NA",
    "gnaf_pid": "GATAS702275917",
    "tech_change_status": "Not Planned",
    "program_type": "Fixed Wireless and Satellite Upgrade Program",
    "target_eligibility_quarter": "Dec 2024"
   }
  },
  {
   "type": "Feature",
   "geometry": {
    "type": "Point",
    "coordinates": [
     147.32296697,
     -43.09481914
    ]
   },
   "properties": {
    "name": "459 KILLORA ROAD KILLORA 7150",
    "locID": "LOC000103826829",
    "tech": "WIRELESS",
    "upgrade": "NULL_NA",
    "gnaf_pid": "GATAS702275918",
    "tech_change_status": "Not Planned",
    "program_type": "Fixed Wireless and Satellite Upgrade Program",
    "target_eligibility_quarter": "Dec 2024"
   }
  },
  {
   "type": "Feature",
   "geometry": {
    "type": "Point",
    "coordinates": [
     147.32298332,
     -43.09559352
    ]
   },
   "properties": {
    "name": "469 KILLORA ROAD KILLORA 7150",
    "locID": "LOC000035065483",
    "tech": "WIRELESS",
    "upgrade": "NULL_NA",
    "gnaf_pid": "GATAS702275919",
    "tech_change_status": "Not Planned",
    "program_type": "Fixed Wireless and Satellite Upgrade Program",
    "target_eligibility_quarter": "Dec 2024"
   }
  },
  {
   "type": "Feature",
   "geometry": {
    "type": "Point",
    "coordinates": [
     147.32279404,
     -43.09464853
    ]
   },
   "properties": {
    "name": "457 KILLORA ROAD KILLORA 7150",
    "locID": "LOC000096380057",
    "tech": "WIRELESS",
    "upgrade": "NULL_NA",
    "gnaf_pid": "GATAS702275920",
    "tech_change_status": "Not Planned",
    "program_type": "Fixed Wireless and Satellite Upgrade Program",
    "target_eligibility_quarter": "Dec 2024"
   }
  },
  {
   "type": "Feature",
   "geometry": {
    "type": "Point",
    "coordinates": [
     147.32328472,
     -43.09682634
    ]
   },
   "properties": {
    "name": "481 KILLORA ROAD KILLORA 7150",
    "locID": "LOC000047091531",
    "tech": "WIRELESS",
    "upgrade": "NULL_NA",
    "gnaf_pid": "GATAS702275922",
    "tech_change_status": "Not Planned",
    "program_type": "Fixed Wireless and Satellite Upgrade Program",
    "target_eligibility_quarter": "Dec 2024"
   }
  },
  {
   "type": "Feature",
   "geometry": {
    "type": "Point",
    "coordinates": [
     147.32301982,
     -43.09615244
    ]
   },
   "properties": {
    "name": "475 KILLORA ROAD KILLORA 7150",
    "locID": "LOC000095026773",
    "tech": "WIRELESS",
    "upgrade": "NULL_NA",
    "gnaf_pid": "GATAS717937780",
    "tech_change_status": "Not Planned",
    "program_type": "Fixed Wireless and Satellite Upgrade Program",
    "target_eligibility_quarter": "Dec 2024"
   }
  },
  {
   "type": "Feature",
   "geometry": {
    "type": "Point",
    "coordinates": [
     147.32351269,
     -43.09449558
    ]
   },
   "properties": {
    "name": "451 NEBRASKA ROAD KILLORA 7150",
    "locID": "LOC100079394301",
    "tech": "WIRELESS",
    "upgrade": "NULL_NA",
    "gnaf_pid": "GATAS718482025",
    "tech_change_status": "Not Planned",
    "program_type": "Fixed Wireless and Satellite Upgrade Program",
    "target_eligibility_quarter": "Dec 2024"
   }
  }
 ]
}