{
 "type": "FeatureCollection",
 "generated": "2024-07-04T22:16:07.887239",
 "suburb": "POWRANNA",
 "features": [
  {
   "type": "Feature",
   "geometry": {
    "type": "Point",
    "coordinates": [
     147.25794387,
     -41.66809113
    ]
   },
   "properties": {
    "name": "14743 MIDLAND HIGHWAY POWRANNA 7300",
    "locID": "LOC000085863164",
    "tech": "SATELLITE",
    "upgrade": "NULL_NA",
    "gnaf_pid": "GATAS702300346",
    "tech_change_status": "Not Planned"
   }
  },
  {
   "type": "Feature",
   "geometry": {
    "type": "Point",
    "coordinates": [
     147.2761362,
     -41.68488156
    ]
   },
   "properties": {
    "name": "14718 MIDLAND HIGHWAY POWRANNA 7300",
    "locID": "LOC000079688319",
    "tech": "WIRELESS",
    "upgrade": "NULL_NA",
    "gnaf_pid": "GATAS702303940",
    "tech_change_status": "Not Planned",
    "program_type": "Fixed Wireless and Satellite Upgrade Program",
    "target_eligibility_quarter": "NA"
   }
  },
  {
   "type": "Feature",
   "geometry": {
    "type": "Point",
    "coordinates": [
     147.28209301,
     -41.67907379
    ]
   },
   "properties": {
    "name": "14532 MIDLAND HIGHWAY POWRANNA 7300",
    "locID": "LOC000084916955",
    "tech": "WIRELESS",
    "upgrade": "NULL_NA",
    "gnaf_pid": "GATAS702305910",
    "tech_change_status": "Not Planned",
    "program_type": "Fixed Wireless and Satellite Upgrade Program",
    "target_eligibility_quarter": "NA"
   }
  },
  {
   "type": "Feature",
   "geometry": {
    "type": "Point",
    "coordinates": [
     147.26575106,
     -41.6760202
    ]
   },
   "properties": {
    "name": "18 POWRANNA ROAD POWRANNA 7300",
    "locID": "LOC000102929242",
    "tech": "WIRELESS",
    "upgrade": "NULL_NA",
    "gnaf_pid": "GATAS702309496",
    "tech_change_status": "Not Planned",
    "program_type": "Fixed Wireless and Satellite Upgrade Program",
    "target_eligibility_quarter": "NA"
   }
  },
  {
   "type": "Feature",
   "geometry": {
    "type": "Point",
    "coordinates": [
     147.2761362,
     -41.68488156
    ]
   },
   "properties": {
    "name": "14535 MIDLAND HIGHWAY POWRANNA 7300",
    "locID": "LOC000003491729",
    "tech": "SATELLITE",
    "upgrade": "NULL_NA",
    "gnaf_pid": "GATAS702543130",
    "tech_change_status": "Not Planned"
   }
  },
  {
   "type": "Feature",
   "geometry": {
    "type": "Point",
    "coordinates": [
     147.27210503,
     -41.67731921
    ]
   },
   "properties": {
    "name": "14638 MIDLAND HIGHWAY POWRANNA 7300",
    "locID": "LOC000057219454",
    "tech": "WIRELESS",
    "upgrade": "NULL_NA",
    "gnaf_pid": "GATAS702544050",
    "tech_change_status": "Not Planned",
    "program_type": "Fixed Wireless and Satellite Upgrade Program",
    "target_eligibility_quarter": "NA"
   }
  },
  {
   "type": "Feature",
   "geometry": {
    "type": "Point",
    "coordinates": [
     147.2637461,
     -41.68468217
    ]
   },
   "properties": {
    "name": "73 POWRANNA ROAD POWRANNA 7300",
    "locID": "LOC000037216703",
    "tech": "SATELLITE",
    "upgrade": "NULL_NA",
    "gnaf_pid": "GATAS702799843",
    "tech_change_status": "Not Planned"
   }
  },
  {
   "type": "Feature",
   "geometry": {
    "type": "Point",
    "coordinates": [
     147.2467374,
     -41.67732146
    ]
   },
   "properties": {
    "name": "118 POWRANNA ROAD POWRANNA 7300",
    "locID": "LOC000133837506",
    "tech": "SATELLITE",
    "upgrade": "NULL_NA",
    "gnaf_pid": "GATAS717413440",
    "tech_change_status": "Not Planned"
   }
  },
  {
   "type": "Feature",
   "geometry": {
    "type": "Point",
    "coordinates": [
     147.26278847,
     -41.6782198
    ]
   },
   "properties": {
    "name": "24 POWRANNA ROAD POWRANNA 7300",
    "locID": "LOC000148016920",
    "tech": "WIRELESS",
    "upgrade": "NULL_NA",
    "gnaf_pid": "GATAS718479902",
    "tech_change_status": "Not Planned",
    "program_type": "Fixed Wireless and Satellite Upgrade Program",
    "target_eligibility_quarter": "NA"
   }
  }
 ]
}