{
 "type": "FeatureCollection",
 "generated": "2024-07-05T00:41:43.753920",
 "suburb": "TIBERIAS",
 "features": [
  {
   "type": "Feature",
   "geometry": {
    "type": "Point",
    "coordinates": [
     147.35998074,
     -42.44359314
    ]
   },
   "properties": {
    "name": "158 TIBERIAS ROAD TIBERIAS 7120",
    "locID": "LOC000026251868",
    "tech": "SATELLITE",
    "upgrade": "NULL_NA",
    "gnaf_pid": "GATAS702354839",
    "tech_change_status": "Not Planned"
   }
  },
  {
   "type": "Feature",
   "geometry": {
    "type": "Point",
    "coordinates": [
     147.3642008,
     -42.45324491
    ]
   },
   "properties": {
    "name": "127 TIBERIAS ROAD TIBERIAS 7120",
    "locID": "LOC000001893409",
    "tech": "WIRELESS",
    "upgrade": "NULL_NA",
    "gnaf_pid": "GATAS702356725",
    "tech_change_status": "Not Planned",
    "program_type": "Fixed Wireless and Satellite Upgrade Program",
    "target_eligibility_quarter": "Dec 2024"
   }
  },
  {
   "type": "Feature",
   "geometry": {
    "type": "Point",
    "coordinates": [
     147.37868327,
     -42.43932135
    ]
   },
   "properties": {
    "name": "128 TIBERIAS ROAD TIBERIAS 7120",
    "locID": "LOC000060828784",
    "tech": "SATELLITE",
    "upgrade": "NULL_NA",
    "gnaf_pid": "GATAS716462583",
    "tech_change_status": "Not Planned"
   }
  }
 ]
}