{
 "type": "FeatureCollection",
 "generated": "2023-09-22T22:25:49.112644",
 "suburb": "ARCHER RIVER",
 "features": [
  {
   "type": "Feature",
   "geometry": {
    "type": "Point",
    "coordinates": [
     143.00374285,
     -13.54242615
    ]
   },
   "properties": {
    "name": "LOT 2 PENINSULA DEVELOPMENTAL ROAD ARCHER RIVER 4892",
    "locID": "LOC000142386695",
    "tech": "SATELLITE",
    "upgrade": "NULL_NA",
    "gnaf_pid": "GAQLD161764816"
   }
  },
  {
   "type": "Feature",
   "geometry": {
    "type": "Point",
    "coordinates": [
     142.34519219,
     -13.07025503
    ]
   },
   "properties": {
    "name": "LOT 3 PENINSULA DEVELOPMENTAL ROAD ARCHER RIVER 4892",
    "locID": "LOC000178032130",
    "tech": "SATELLITE",
    "upgrade": "NULL_NA",
    "gnaf_pid": "GAQLD161764817"
   }
  },
  {
   "type": "Feature",
   "geometry": {
    "type": "Point",
    "coordinates": [
     142.8112542,
     -13.20520182
    ]
   },
   "properties": {
    "name": "LOT 1 TELEGRAPH ROAD ARCHER RIVER 4892",
    "locID": "LOC000129794612",
    "tech": "SATELLITE",
    "upgrade": "NULL_NA",
    "gnaf_pid": "GAQLD161770554"
   }
  },
  {
   "type": "Feature",
   "geometry": {
    "type": "Point",
    "coordinates": [
     142.93243726,
     -13.43414831
    ]
   },
   "properties": {
    "name": "LOT 1 PENINSULA DEVELOPMENTAL ROAD ARCHER RIVER 4892",
    "locID": "LOC000142855066",
    "tech": "SATELLITE",
    "upgrade": "NULL_NA",
    "gnaf_pid": "GAQLD163018053"
   }
  }
 ]
}