{
 "type": "FeatureCollection",
 "generated": "2024-08-24T09:11:33.762021",
 "suburb": "ARGYLL",
 "features": [
  {
   "type": "Feature",
   "geometry": {
    "type": "Point",
    "coordinates": [
     147.6048885,
     -23.20897367
    ]
   },
   "properties": {
    "name": "LOT 1 CLERMONT RUBYVALE ROAD ARGYLL 4721",
    "locID": "LOC000129244581",
    "tech": "SATELLITE",
    "upgrade": "NULL_NA",
    "gnaf_pid": "GAQLD161104565",
    "tech_change_status": "Not Planned"
   }
  },
  {
   "type": "Feature",
   "geometry": {
    "type": "Point",
    "coordinates": [
     147.5741476,
     -23.24065931
    ]
   },
   "properties": {
    "name": "LOT 2 CLERMONT RUBYVALE ROAD ARGYLL 4721",
    "locID": "LOC000129244683",
    "tech": "SATELLITE",
    "upgrade": "NULL_NA",
    "gnaf_pid": "GAQLD161104566",
    "tech_change_status": "Not Planned"
   }
  },
  {
   "type": "Feature",
   "geometry": {
    "type": "Point",
    "coordinates": [
     147.64968675,
     -23.26322672
    ]
   },
   "properties": {
    "name": "LOT 3 CLERMONT RUBYVALE ROAD ARGYLL 4721",
    "locID": "LOC000129244683",
    "tech": "SATELLITE",
    "upgrade": "NULL_NA",
    "gnaf_pid": "GAQLD161104567",
    "tech_change_status": "Not Planned"
   }
  },
  {
   "type": "Feature",
   "geometry": {
    "type": "Point",
    "coordinates": [
     147.6821975,
     -23.30586164
    ]
   },
   "properties": {
    "name": "LOT 5 CLERMONT RUBYVALE ROAD ARGYLL 4721",
    "locID": "LOC000129244683",
    "tech": "SATELLITE",
    "upgrade": "NULL_NA",
    "gnaf_pid": "GAQLD161104568",
    "tech_change_status": "Not Planned"
   }
  },
  {
   "type": "Feature",
   "geometry": {
    "type": "Point",
    "coordinates": [
     147.48592431,
     -23.25071166
    ]
   },
   "properties": {
    "name": "22 REKLAW ROAD ARGYLL 4721",
    "locID": "LOC000003357301",
    "tech": "SATELLITE",
    "upgrade": "NULL_NA",
    "gnaf_pid": "GAQLD162189066",
    "tech_change_status": "Not Planned"
   }
  },
  {
   "type": "Feature",
   "geometry": {
    "type": "Point",
    "coordinates": [
     147.48792335,
     -23.32969213
    ]
   },
   "properties": {
    "name": "588 REKLAW ROAD ARGYLL 4721",
    "locID": "LOC000015312367",
    "tech": "SATELLITE",
    "upgrade": "NULL_NA",
    "gnaf_pid": "GAQLD162386534",
    "tech_change_status": "Not Planned"
   }
  },
  {
   "type": "Feature",
   "geometry": {
    "type": "Point",
    "coordinates": [
     147.40392481,
     -23.39305852
    ]
   },
   "properties": {
    "name": "LOT 4 REKLAW ROAD ARGYLL 4721",
    "locID": "LOC000003357301",
    "tech": "SATELLITE",
    "upgrade": "NULL_NA",
    "gnaf_pid": "GAQLD162963428",
    "tech_change_status": "Not Planned"
   }
  },
  {
   "type": "Feature",
   "geometry": {
    "type": "Point",
    "coordinates": [
     147.67527713,
     -23.33911042
    ]
   },
   "properties": {
    "name": "LOT 8 CLERMONT RUBYVALE ROAD ARGYLL 4721",
    "locID": "LOC000129244683",
    "tech": "SATELLITE",
    "upgrade": "NULL_NA",
    "gnaf_pid": "GAQLD424933099",
    "tech_change_status": "Not Planned"
   }
  }
 ]
}