{
 "type": "FeatureCollection",
 "generated": "2023-09-22T22:28:20.263422",
 "suburb": "ARGYLL",
 "features": [
  {
   "type": "Feature",
   "geometry": {
    "type": "Point",
    "coordinates": [
     147.6048885,
     -23.20897367
    ]
   },
   "properties": {
    "name": "LOT 1 CLERMONT RUBYVALE ROAD ARGYLL 4721",
    "locID": "LOC000129244581",
    "tech": "SATELLITE",
    "upgrade": "NULL_NA",
    "gnaf_pid": "GAQLD161104565"
   }
  },
  {
   "type": "Feature",
   "geometry": {
    "type": "Point",
    "coordinates": [
     147.5741476,
     -23.24065931
    ]
   },
   "properties": {
    "name": "LOT 2 CLERMONT RUBYVALE ROAD ARGYLL 4721",
    "locID": "LOC000129244683",
    "tech": "SATELLITE",
    "upgrade": "NULL_NA",
    "gnaf_pid": "GAQLD161104566"
   }
  },
  {
   "type": "Feature",
   "geometry": {
    "type": "Point",
    "coordinates": [
     147.64968675,
     -23.26322672
    ]
   },
   "properties": {
    "name": "LOT 3 CLERMONT RUBYVALE ROAD ARGYLL 4721",
    "locID": "LOC000129244683",
    "tech": "SATELLITE",
    "upgrade": "NULL_NA",
    "gnaf_pid": "GAQLD161104567"
   }
  },
  {
   "type": "Feature",
   "geometry": {
    "type": "Point",
    "coordinates": [
     147.6821975,
     -23.30586164
    ]
   },
   "properties": {
    "name": "LOT 5 CLERMONT RUBYVALE ROAD ARGYLL 4721",
    "locID": "LOC000129244683",
    "tech": "SATELLITE",
    "upgrade": "NULL_NA",
    "gnaf_pid": "GAQLD161104568"
   }
  },
  {
   "type": "Feature",
   "geometry": {
    "type": "Point",
    "coordinates": [
     147.61690613,
     -23.3068486
    ]
   },
   "properties": {
    "name": "7082 CLERMONT RUBYVALE ROAD ARGYLL 4721",
    "locID": "ChIJA-VnarTXzmsRG6iTH_POA5k",
    "tech": "SATELLITE",
    "upgrade": "UNKNOWN",
    "gnaf_pid": "GAQLD162132272"
   }
  },
  {
   "type": "Feature",
   "geometry": {
    "type": "Point",
    "coordinates": [
     147.47925252,
     -23.3544866
    ]
   },
   "properties": {
    "name": "LOT 1 REKLAW ROAD ARGYLL 4721",
    "locID": "EicxIFJla2xhdyBSZCwgQXJneWxsIFFMRCA0NzIxLCBBdXN0cmFsaWEiMBIuChQKEglHBZ0ZK9HOaxGhUAB58e4AExABKhQKEgmv9ZgjK9HOaxF6DUbO0JAU7g",
    "tech": "SATELLITE",
    "upgrade": "UNKNOWN",
    "gnaf_pid": "GAQLD162189065"
   }
  },
  {
   "type": "Feature",
   "geometry": {
    "type": "Point",
    "coordinates": [
     147.48592431,
     -23.25071166
    ]
   },
   "properties": {
    "name": "22 REKLAW ROAD ARGYLL 4721",
    "locID": "LOC000003357301",
    "tech": "SATELLITE",
    "upgrade": "NULL_NA",
    "gnaf_pid": "GAQLD162189066"
   }
  },
  {
   "type": "Feature",
   "geometry": {
    "type": "Point",
    "coordinates": [
     147.52359563,
     -23.22299665
    ]
   },
   "properties": {
    "name": "5144 CLERMONT RUBYVALE ROAD ARGYLL 4721",
    "locID": "ChIJ5XmXykPazmsRXbk9vxnK23o",
    "tech": "SATELLITE",
    "upgrade": "UNKNOWN",
    "gnaf_pid": "GAQLD162381897"
   }
  },
  {
   "type": "Feature",
   "geometry": {
    "type": "Point",
    "coordinates": [
     147.61600596,
     -23.29059501
    ]
   },
   "properties": {
    "name": "6973 CLERMONT RUBYVALE ROAD ARGYLL 4721",
    "locID": "ChIJU2y1DL7XzmsRJ16k3JdZ4mw",
    "tech": "SATELLITE",
    "upgrade": "UNKNOWN",
    "gnaf_pid": "GAQLD162381898"
   }
  },
  {
   "type": "Feature",
   "geometry": {
    "type": "Point",
    "coordinates": [
     147.48792335,
     -23.32969213
    ]
   },
   "properties": {
    "name": "588 REKLAW ROAD ARGYLL 4721",
    "locID": "LOC000015312367",
    "tech": "SATELLITE",
    "upgrade": "NULL_NA",
    "gnaf_pid": "GAQLD162386534"
   }
  },
  {
   "type": "Feature",
   "geometry": {
    "type": "Point",
    "coordinates": [
     147.40392481,
     -23.39305852
    ]
   },
   "properties": {
    "name": "LOT 4 REKLAW ROAD ARGYLL 4721",
    "locID": "LOC000003357301",
    "tech": "SATELLITE",
    "upgrade": "NULL_NA",
    "gnaf_pid": "GAQLD162963428"
   }
  },
  {
   "type": "Feature",
   "geometry": {
    "type": "Point",
    "coordinates": [
     147.67527713,
     -23.33911042
    ]
   },
   "properties": {
    "name": "LOT 8 CLERMONT RUBYVALE ROAD ARGYLL 4721",
    "locID": "LOC000129244683",
    "tech": "SATELLITE",
    "upgrade": "NULL_NA",
    "gnaf_pid": "GAQLD424933099"
   }
  },
  {
   "type": "Feature",
   "geometry": {
    "type": "Point",
    "coordinates": [
     147.44440598,
     -23.36282423
    ]
   },
   "properties": {
    "name": "LOT 19 REKLAW ROAD ARGYLL 4721",
    "locID": "EigxOSBSZWtsYXcgUmQsIEFyZ3lsbCBRTEQgNDcyMSwgQXVzdHJhbGlhIjASLgoUChIJRwWdGSvRzmsRoVAAefHuABMQEyoUChIJr_WYIyvRzmsReg1GztCQFO4",
    "tech": "SATELLITE",
    "upgrade": "UNKNOWN",
    "gnaf_pid": "GAQLD425215656"
   }
  },
  {
   "type": "Feature",
   "geometry": {
    "type": "Point",
    "coordinates": [
     147.49732856,
     -23.15386767
    ]
   },
   "properties": {
    "name": "4428 CLERMONT RUBYVALE ROAD ARGYLL 4721",
    "locID": "ChIJq_dw14LczmsRxz5ZHShaKcI",
    "tech": "SATELLITE",
    "upgrade": "UNKNOWN",
    "gnaf_pid": "GAQLD720976635"
   }
  }
 ]
}