{
 "type": "FeatureCollection",
 "generated": "2024-07-14T05:43:17.327920",
 "suburb": "BARKLY",
 "features": [
  {
   "type": "Feature",
   "geometry": {
    "type": "Point",
    "coordinates": [
     138.30159447,
     -20.31432126
    ]
   },
   "properties": {
    "name": "LOT 2 BARKLY HIGHWAY BARKLY 4825",
    "locID": "LOC000045578979",
    "tech": "FTTN",
    "upgrade": "NULL_NA",
    "gnaf_pid": "GAQLD155593672",
    "tech_change_status": "Not Planned"
   }
  },
  {
   "type": "Feature",
   "geometry": {
    "type": "Point",
    "coordinates": [
     138.11424255,
     -20.87524864
    ]
   },
   "properties": {
    "name": "LOT 3 BARKLY HIGHWAY BARKLY 4825",
    "locID": "LOC000073333819",
    "tech": "FTTN",
    "upgrade": "NULL_NA",
    "gnaf_pid": "GAQLD161058904",
    "tech_change_status": "Not Planned"
   }
  },
  {
   "type": "Feature",
   "geometry": {
    "type": "Point",
    "coordinates": [
     138.00013405,
     -20.79946019
    ]
   },
   "properties": {
    "name": "LOT 6 BARKLY HIGHWAY BARKLY 4825",
    "locID": "LOC000020215473",
    "tech": "FTTN",
    "upgrade": "NULL_NA",
    "gnaf_pid": "GAQLD161058906",
    "tech_change_status": "Not Planned"
   }
  },
  {
   "type": "Feature",
   "geometry": {
    "type": "Point",
    "coordinates": [
     138.55931398,
     -20.00413327
    ]
   },
   "properties": {
    "name": "LOT 8 BARKLY HIGHWAY BARKLY 4825",
    "locID": "LOC000028953073",
    "tech": "FTTN",
    "upgrade": "NULL_NA",
    "gnaf_pid": "GAQLD161058907",
    "tech_change_status": "Not Planned"
   }
  },
  {
   "type": "Feature",
   "geometry": {
    "type": "Point",
    "coordinates": [
     138.11894032,
     -20.41237591
    ]
   },
   "properties": {
    "name": "6835 CAMOOWEAL URANDANGI ROAD BARKLY 4825",
    "locID": "LOC000154841786",
    "tech": "SATELLITE",
    "upgrade": "NULL_NA",
    "gnaf_pid": "GAQLD425261287",
    "tech_change_status": "Not Planned"
   }
  },
  {
   "type": "Feature",
   "geometry": {
    "type": "Point",
    "coordinates": [
     138.65599918,
     -20.02549221
    ]
   },
   "properties": {
    "name": "LOT 42 BARKLY HIGHWAY BARKLY 4825",
    "locID": "LOC000129511638",
    "tech": "FTTN",
    "upgrade": "FTTP_NA",
    "gnaf_pid": "GAQLD425809110",
    "tech_change_status": "Committed",
    "program_type": "On-Demand N2P SDU/MDU Simple",
    "target_eligibility_quarter": "Dec 2024"
   }
  },
  {
   "type": "Feature",
   "geometry": {
    "type": "Point",
    "coordinates": [
     138.00068767,
     -20.38036405
    ]
   },
   "properties": {
    "name": "LOT 1 CAMOOWEAL URANDANGI ROAD BARKLY 4825",
    "locID": "LOC000154841786",
    "tech": "SATELLITE",
    "upgrade": "NULL_NA",
    "gnaf_pid": "GAQLD721146382",
    "tech_change_status": "Not Planned"
   }
  },
  {
   "type": "Feature",
   "geometry": {
    "type": "Point",
    "coordinates": [
     138.00033194,
     -20.59901073
    ]
   },
   "properties": {
    "name": "LOT 2 CAMOOWEAL URANDANGI ROAD BARKLY 4825",
    "locID": "LOC000154841786",
    "tech": "SATELLITE",
    "upgrade": "NULL_NA",
    "gnaf_pid": "GAQLD721151178",
    "tech_change_status": "Not Planned"
   }
  }
 ]
}