{
 "type": "FeatureCollection",
 "generated": "2024-10-01T00:01:56.642941",
 "suburb": "BARRINGUN",
 "features": [
  {
   "type": "Feature",
   "geometry": {
    "type": "Point",
    "coordinates": [
     145.72987274,
     -28.98164951
    ]
   },
   "properties": {
    "name": "LOT 10 MITCHELL HIGHWAY BARRINGUN 4490",
    "locID": "LOC000128098985",
    "tech": "NULL",
    "upgrade": "NULL_NA",
    "gnaf_pid": "GAQLD161239453",
    "tech_change_status": "Not Planned"
   }
  },
  {
   "type": "Feature",
   "geometry": {
    "type": "Point",
    "coordinates": [
     145.96825648,
     -28.95212626
    ]
   },
   "properties": {
    "name": "LOT 1 MITCHELL HIGHWAY BARRINGUN 4490",
    "locID": "LOC000128098985",
    "tech": "NULL",
    "upgrade": "NULL_NA",
    "gnaf_pid": "GAQLD161239455",
    "tech_change_status": "Not Planned"
   }
  },
  {
   "type": "Feature",
   "geometry": {
    "type": "Point",
    "coordinates": [
     145.72101384,
     -28.94568974
    ]
   },
   "properties": {
    "name": "LOT 5 MITCHELL HIGHWAY BARRINGUN 4490",
    "locID": "LOC000128103132",
    "tech": "NULL",
    "upgrade": "NULL_NA",
    "gnaf_pid": "GAQLD161239456",
    "tech_change_status": "Not Planned"
   }
  },
  {
   "type": "Feature",
   "geometry": {
    "type": "Point",
    "coordinates": [
     145.72465445,
     -28.74228438
    ]
   },
   "properties": {
    "name": "3022 BARRINGUN ROAD BARRINGUN 4490",
    "locID": "LOC000072183686",
    "tech": "SATELLITE",
    "upgrade": "NULL_NA",
    "gnaf_pid": "GAQLD162240071",
    "tech_change_status": "Not Planned"
   }
  },
  {
   "type": "Feature",
   "geometry": {
    "type": "Point",
    "coordinates": [
     145.68189076,
     -28.86664829
    ]
   },
   "properties": {
    "name": "1077 BARRINGUN ROAD BARRINGUN 4490",
    "locID": "LOC000043651944",
    "tech": "NULL",
    "upgrade": "NULL_NA",
    "gnaf_pid": "GAQLD162240072",
    "tech_change_status": "Not Planned"
   }
  },
  {
   "type": "Feature",
   "geometry": {
    "type": "Point",
    "coordinates": [
     145.80223661,
     -28.97882152
    ]
   },
   "properties": {
    "name": "318 BARRINGUN ROAD BARRINGUN 4490",
    "locID": "LOC000101806490",
    "tech": "SATELLITE",
    "upgrade": "NULL_NA",
    "gnaf_pid": "GAQLD162240073",
    "tech_change_status": "Not Planned"
   }
  },
  {
   "type": "Feature",
   "geometry": {
    "type": "Point",
    "coordinates": [
     145.79281502,
     -28.80571996
    ]
   },
   "properties": {
    "name": "1193 BLUEGRASS ROAD BARRINGUN 4490",
    "locID": "LOC000026584283",
    "tech": "SATELLITE",
    "upgrade": "NULL_NA",
    "gnaf_pid": "GAQLD163252678",
    "tech_change_status": "Not Planned"
   }
  },
  {
   "type": "Feature",
   "geometry": {
    "type": "Point",
    "coordinates": [
     145.69774076,
     -28.8430633
    ]
   },
   "properties": {
    "name": "LOT 3 BARRINGUN ROAD BARRINGUN 4490",
    "locID": "LOC000072183686",
    "tech": "SATELLITE",
    "upgrade": "NULL_NA",
    "gnaf_pid": "GAQLD720989743",
    "tech_change_status": "Not Planned"
   }
  }
 ]
}