{
 "type": "FeatureCollection",
 "generated": "2023-09-23T01:58:57.948486",
 "suburb": "BOLWARRA",
 "features": [
  {
   "type": "Feature",
   "geometry": {
    "type": "Point",
    "coordinates": [
     144.01511241,
     -17.49249279
    ]
   },
   "properties": {
    "name": "LOT 2 BOLWARRA ROAD BOLWARRA 4871",
    "locID": "LOC000013914422",
    "tech": "FTTN",
    "upgrade": "NULL_NA",
    "gnaf_pid": "GAQLD425172707"
   }
  }
 ]
}