{
 "type": "FeatureCollection",
 "generated": "2024-07-14T07:45:10.151642",
 "suburb": "BOLWARRA",
 "features": [
  {
   "type": "Feature",
   "geometry": {
    "type": "Point",
    "coordinates": [
     144.01511241,
     -17.49249279
    ]
   },
   "properties": {
    "name": "LOT 2 BOLWARRA ROAD BOLWARRA 4871",
    "locID": "LOC000013914422",
    "tech": "FTTN",
    "upgrade": "FTTP_NA",
    "gnaf_pid": "GAQLD425172707",
    "tech_change_status": "In Design",
    "program_type": "On-Demand N2P SDU/MDU Simple",
    "target_eligibility_quarter": "Sep 2025"
   }
  }
 ]
}