{
 "type": "FeatureCollection",
 "generated": "2024-03-10T05:52:50.484093",
 "suburb": "CAMERON CORNER",
 "features": [
  {
   "type": "Feature",
   "geometry": {
    "type": "Point",
    "coordinates": [
     141.41904473,
     -28.07357396
    ]
   },
   "properties": {
    "name": "8765 ORIENTOS ROAD CAMERON CORNER 4492",
    "locID": "LOC000164264539",
    "tech": "SATELLITE",
    "upgrade": "NULL_NA",
    "gnaf_pid": "GAQLD425804988"
   }
  },
  {
   "type": "Feature",
   "geometry": {
    "type": "Point",
    "coordinates": [
     141.26240078,
     -28.39103489
    ]
   },
   "properties": {
    "name": "3430 MOOMBA ROAD CAMERON CORNER 4492",
    "locID": "LOC000155810895",
    "tech": "SATELLITE",
    "upgrade": "NULL_NA",
    "gnaf_pid": "GAQLD719637735"
   }
  },
  {
   "type": "Feature",
   "geometry": {
    "type": "Point",
    "coordinates": [
     141.2848337,
     -28.87840793
    ]
   },
   "properties": {
    "name": "LOT 1 TOONA GATE ROAD CAMERON CORNER 4492",
    "locID": "LOC000142539576",
    "tech": "SATELLITE",
    "upgrade": "NULL_NA",
    "gnaf_pid": "GAQLD721114201"
   }
  },
  {
   "type": "Feature",
   "geometry": {
    "type": "Point",
    "coordinates": [
     141.29507904,
     -28.87396307
    ]
   },
   "properties": {
    "name": "LOT 2 TOONA GATE ROAD CAMERON CORNER 4492",
    "locID": "LOC000142539576",
    "tech": "SATELLITE",
    "upgrade": "NULL_NA",
    "gnaf_pid": "GAQLD721114791"
   }
  },
  {
   "type": "Feature",
   "geometry": {
    "type": "Point",
    "coordinates": [
     141.514612,
     -28.34645355
    ]
   },
   "properties": {
    "name": "LOT 2 ORIENTOS ROAD CAMERON CORNER 4492",
    "locID": "LOC000164264539",
    "tech": "SATELLITE",
    "upgrade": "NULL_NA",
    "gnaf_pid": "GAQLD721115542"
   }
  }
 ]
}