{
 "type": "FeatureCollection",
 "generated": "2024-07-14T11:07:57.085250",
 "suburb": "CARDSTONE",
 "features": [
  {
   "type": "Feature",
   "geometry": {
    "type": "Point",
    "coordinates": [
     145.76558407,
     -17.87111508
    ]
   },
   "properties": {
    "name": "2925 TULLY GORGE ROAD CARDSTONE 4854",
    "locID": "LOC000142913851",
    "tech": "SATELLITE",
    "upgrade": "NULL_NA",
    "gnaf_pid": "GAQLD162366893",
    "tech_change_status": "Not Planned"
   }
  },
  {
   "type": "Feature",
   "geometry": {
    "type": "Point",
    "coordinates": [
     145.75709205,
     -17.86998418
    ]
   },
   "properties": {
    "name": "LOT 31 TULLY GORGE ROAD CARDSTONE 4854",
    "locID": "LOC000142913851",
    "tech": "SATELLITE",
    "upgrade": "NULL_NA",
    "gnaf_pid": "GAQLD425334634",
    "tech_change_status": "Not Planned"
   }
  },
  {
   "type": "Feature",
   "geometry": {
    "type": "Point",
    "coordinates": [
     145.6135607,
     -17.74975174
    ]
   },
   "properties": {
    "name": "LOT 32 TULLY GORGE ROAD CARDSTONE 4854",
    "locID": "LOC000142913851",
    "tech": "SATELLITE",
    "upgrade": "NULL_NA",
    "gnaf_pid": "GAQLD425334635",
    "tech_change_status": "Not Planned"
   }
  },
  {
   "type": "Feature",
   "geometry": {
    "type": "Point",
    "coordinates": [
     145.67066061,
     -17.78191195
    ]
   },
   "properties": {
    "name": "LOT 34 TULLY GORGE ROAD CARDSTONE 4854",
    "locID": "LOC000089383345",
    "tech": "FTTN",
    "upgrade": "NULL_NA",
    "gnaf_pid": "GAQLD425334637",
    "tech_change_status": "Not Planned"
   }
  },
  {
   "type": "Feature",
   "geometry": {
    "type": "Point",
    "coordinates": [
     145.67324761,
     -17.78557889
    ]
   },
   "properties": {
    "name": "LOT 35 TULLY GORGE ROAD CARDSTONE 4854",
    "locID": "LOC000019046561",
    "tech": "FTTN",
    "upgrade": "FTTP_NA",
    "gnaf_pid": "GAQLD425334638",
    "tech_change_status": "In Design",
    "program_type": "On-Demand N2P SDU/MDU Simple",
    "target_eligibility_quarter": "Jun 2025"
   }
  },
  {
   "type": "Feature",
   "geometry": {
    "type": "Point",
    "coordinates": [
     145.690092,
     -17.80894998
    ]
   },
   "properties": {
    "name": "LOT 60 TULLY GORGE ROAD CARDSTONE 4854",
    "locID": "LOC000142913851",
    "tech": "SATELLITE",
    "upgrade": "NULL_NA",
    "gnaf_pid": "GAQLD425351855",
    "tech_change_status": "Not Planned"
   }
  }
 ]
}