{
 "type": "FeatureCollection",
 "generated": "2024-10-01T05:28:11.509702",
 "suburb": "CARPENTARIA",
 "features": [
  {
   "type": "Feature",
   "geometry": {
    "type": "Point",
    "coordinates": [
     140.340393,
     -18.1227
    ]
   },
   "properties": {
    "name": "LOT 2 BURKETOWN NORMANTON ROAD CARPENTARIA 4823",
    "locID": "LOC000176204591",
    "tech": "SATELLITE",
    "upgrade": "NULL_NA",
    "gnaf_pid": "GAQLD720667733",
    "tech_change_status": "Not Planned"
   }
  }
 ]
}