{
 "type": "FeatureCollection",
 "generated": "2023-07-13T08:23:17.897380",
 "suburb": "COOEEIMBARDI",
 "features": [
  {
   "type": "Feature",
   "geometry": {
    "type": "Point",
    "coordinates": [
     152.49202693,
     -27.10503639
    ]
   },
   "properties": {
    "name": "428 COOEEIMBARDI ROAD COOEEIMBARDI 4313",
    "locID": "LOC000091165429",
    "tech": "WIRELESS",
    "upgrade": "NULL_NA",
    "gnaf_pid": "GAQLD160946345"
   }
  },
  {
   "type": "Feature",
   "geometry": {
    "type": "Point",
    "coordinates": [
     152.49809773,
     -27.1302765
    ]
   },
   "properties": {
    "name": "LOT 1 COOEEIMBARDI ROAD COOEEIMBARDI 4313",
    "locID": "LOC000021654535",
    "tech": "WIRELESS",
    "upgrade": "NULL_NA",
    "gnaf_pid": "GAQLD161108887"
   }
  },
  {
   "type": "Feature",
   "geometry": {
    "type": "Point",
    "coordinates": [
     152.51133361,
     -27.12545831
    ]
   },
   "properties": {
    "name": "LOT 222 COOEEIMBARDI ROAD COOEEIMBARDI 4313",
    "locID": "EjUyMjIgQ29vZWVpbWJhcmRpIFJkLCBDb29lZWltYmFyZGkgUUxEIDQzMTMsIEF1c3RyYWxpYSIxEi8KFAoSCSsR6HSyGZRrEed268WYEIcFEN4BKhQKEgmPNEK1JRiUaxHc6mFx6BXjXw",
    "tech": "SATELLITE",
    "upgrade": "UNKNOWN",
    "gnaf_pid": "GAQLD161108888"
   }
  },
  {
   "type": "Feature",
   "geometry": {
    "type": "Point",
    "coordinates": [
     152.48424753,
     -27.10528648
    ]
   },
   "properties": {
    "name": "LOT 2 COOEEIMBARDI ROAD COOEEIMBARDI 4313",
    "locID": "LOC000091165429",
    "tech": "WIRELESS",
    "upgrade": "NULL_NA",
    "gnaf_pid": "GAQLD161108892"
   }
  },
  {
   "type": "Feature",
   "geometry": {
    "type": "Point",
    "coordinates": [
     152.5193075,
     -27.09305926
    ]
   },
   "properties": {
    "name": "LOT 47 COOEEIMBARDI ROAD COOEEIMBARDI 4313",
    "locID": "LOC000190133327",
    "tech": "WIRELESS",
    "upgrade": "NULL_NA",
    "gnaf_pid": "GAQLD161108893"
   }
  },
  {
   "type": "Feature",
   "geometry": {
    "type": "Point",
    "coordinates": [
     152.50261219,
     -27.12485313
    ]
   },
   "properties": {
    "name": "LOT 8 COOEEIMBARDI ROAD COOEEIMBARDI 4313",
    "locID": "LOC000054722706",
    "tech": "SATELLITE",
    "upgrade": "NULL_NA",
    "gnaf_pid": "GAQLD161108895"
   }
  },
  {
   "type": "Feature",
   "geometry": {
    "type": "Point",
    "coordinates": [
     152.50227806,
     -27.1193611
    ]
   },
   "properties": {
    "name": "229-262 COOEEIMBARDI ROAD COOEEIMBARDI 4313",
    "locID": "ChIJJ1pCPLQZlGsROIk5L-BFgfI",
    "tech": "SATELLITE",
    "upgrade": "UNKNOWN",
    "gnaf_pid": "GAQLD162019344"
   }
  },
  {
   "type": "Feature",
   "geometry": {
    "type": "Point",
    "coordinates": [
     152.47918002,
     -27.11671665
    ]
   },
   "properties": {
    "name": "427 COOEEIMBARDI ROAD COOEEIMBARDI 4313",
    "locID": "LOC000021654535",
    "tech": "WIRELESS",
    "upgrade": "NULL_NA",
    "gnaf_pid": "GAQLD162019345"
   }
  },
  {
   "type": "Feature",
   "geometry": {
    "type": "Point",
    "coordinates": [
     152.50227806,
     -27.1193611
    ]
   },
   "properties": {
    "name": "229 COOEEIMBARDI ROAD COOEEIMBARDI 4313",
    "locID": "LOC000076494597",
    "tech": "SATELLITE",
    "upgrade": "NULL_NA",
    "gnaf_pid": "GAQLD162083157"
   }
  },
  {
   "type": "Feature",
   "geometry": {
    "type": "Point",
    "coordinates": [
     152.49265843,
     -27.11820036
    ]
   },
   "properties": {
    "name": "262 COOEEIMBARDI ROAD COOEEIMBARDI 4313",
    "locID": "ChIJWYfjrVMYlGsR1P6ddD21s14",
    "tech": "SATELLITE",
    "upgrade": "UNKNOWN",
    "gnaf_pid": "GAQLD162083158"
   }
  },
  {
   "type": "Feature",
   "geometry": {
    "type": "Point",
    "coordinates": [
     152.50227806,
     -27.1193611
    ]
   },
   "properties": {
    "name": "261 COOEEIMBARDI ROAD COOEEIMBARDI 4313",
    "locID": "ChIJWYfjrVMYlGsR5NJqbl66fns",
    "tech": "SATELLITE",
    "upgrade": "UNKNOWN",
    "gnaf_pid": "GAQLD162671970"
   }
  },
  {
   "type": "Feature",
   "geometry": {
    "type": "Point",
    "coordinates": [
     152.49741244,
     -27.11417751
    ]
   },
   "properties": {
    "name": "339 COOEEIMBARDI ROAD COOEEIMBARDI 4313",
    "locID": "ChIJY9yprMoZlGsRa_nAWjeK9mY",
    "tech": "SATELLITE",
    "upgrade": "UNKNOWN",
    "gnaf_pid": "GAQLD425644767"
   }
  },
  {
   "type": "Feature",
   "geometry": {
    "type": "Point",
    "coordinates": [
     152.50069048,
     -27.12645969
    ]
   },
   "properties": {
    "name": "213 COOEEIMBARDI ROAD COOEEIMBARDI 4313",
    "locID": "LOC000189872655",
    "tech": "WIRELESS",
    "upgrade": "NULL_NA",
    "gnaf_pid": "GAQLD719961504"
   }
  }
 ]
}