{
 "type": "FeatureCollection",
 "generated": "2024-10-01T07:37:22.849376",
 "suburb": "COOEEIMBARDI",
 "features": [
  {
   "type": "Feature",
   "geometry": {
    "type": "Point",
    "coordinates": [
     152.49202693,
     -27.10503639
    ]
   },
   "properties": {
    "name": "428 COOEEIMBARDI ROAD COOEEIMBARDI 4313",
    "locID": "LOC000091165429",
    "tech": "WIRELESS",
    "upgrade": "NULL_NA",
    "gnaf_pid": "GAQLD160946345",
    "tech_change_status": "Not Planned",
    "program_type": "Fixed Wireless and Satellite Upgrade Program",
    "target_eligibility_quarter": "NA"
   }
  },
  {
   "type": "Feature",
   "geometry": {
    "type": "Point",
    "coordinates": [
     152.49809773,
     -27.1302765
    ]
   },
   "properties": {
    "name": "LOT 1 COOEEIMBARDI ROAD COOEEIMBARDI 4313",
    "locID": "LOC000021654535",
    "tech": "WIRELESS",
    "upgrade": "NULL_NA",
    "gnaf_pid": "GAQLD161108887",
    "tech_change_status": "Not Planned",
    "program_type": "Fixed Wireless and Satellite Upgrade Program",
    "target_eligibility_quarter": "NA"
   }
  },
  {
   "type": "Feature",
   "geometry": {
    "type": "Point",
    "coordinates": [
     152.48424753,
     -27.10528648
    ]
   },
   "properties": {
    "name": "LOT 2 COOEEIMBARDI ROAD COOEEIMBARDI 4313",
    "locID": "LOC000091165429",
    "tech": "WIRELESS",
    "upgrade": "NULL_NA",
    "gnaf_pid": "GAQLD161108892",
    "tech_change_status": "Not Planned",
    "program_type": "Fixed Wireless and Satellite Upgrade Program",
    "target_eligibility_quarter": "NA"
   }
  },
  {
   "type": "Feature",
   "geometry": {
    "type": "Point",
    "coordinates": [
     152.5193075,
     -27.09305926
    ]
   },
   "properties": {
    "name": "LOT 47 COOEEIMBARDI ROAD COOEEIMBARDI 4313",
    "locID": "LOC000190133327",
    "tech": "WIRELESS",
    "upgrade": "NULL_NA",
    "gnaf_pid": "GAQLD161108893",
    "tech_change_status": "Not Planned",
    "program_type": "Fixed Wireless and Satellite Upgrade Program",
    "target_eligibility_quarter": "NA"
   }
  },
  {
   "type": "Feature",
   "geometry": {
    "type": "Point",
    "coordinates": [
     152.50261219,
     -27.12485313
    ]
   },
   "properties": {
    "name": "LOT 8 COOEEIMBARDI ROAD COOEEIMBARDI 4313",
    "locID": "LOC000054722706",
    "tech": "WIRELESS",
    "upgrade": "NULL_NA",
    "gnaf_pid": "GAQLD161108895",
    "tech_change_status": "Not Planned"
   }
  },
  {
   "type": "Feature",
   "geometry": {
    "type": "Point",
    "coordinates": [
     152.47918002,
     -27.11671665
    ]
   },
   "properties": {
    "name": "427 COOEEIMBARDI ROAD COOEEIMBARDI 4313",
    "locID": "LOC000021654535",
    "tech": "WIRELESS",
    "upgrade": "NULL_NA",
    "gnaf_pid": "GAQLD162019345",
    "tech_change_status": "Not Planned",
    "program_type": "Fixed Wireless and Satellite Upgrade Program",
    "target_eligibility_quarter": "NA"
   }
  },
  {
   "type": "Feature",
   "geometry": {
    "type": "Point",
    "coordinates": [
     152.50227806,
     -27.1193611
    ]
   },
   "properties": {
    "name": "229 COOEEIMBARDI ROAD COOEEIMBARDI 4313",
    "locID": "LOC000076494597",
    "tech": "WIRELESS",
    "upgrade": "NULL_NA",
    "gnaf_pid": "GAQLD162083157",
    "tech_change_status": "Not Planned",
    "program_type": "Fixed Wireless and Satellite Upgrade Program",
    "target_eligibility_quarter": "NA"
   }
  },
  {
   "type": "Feature",
   "geometry": {
    "type": "Point",
    "coordinates": [
     152.50069048,
     -27.12645969
    ]
   },
   "properties": {
    "name": "213 COOEEIMBARDI ROAD COOEEIMBARDI 4313",
    "locID": "LOC000189872655",
    "tech": "WIRELESS",
    "upgrade": "NULL_NA",
    "gnaf_pid": "GAQLD719961504",
    "tech_change_status": "Not Planned",
    "program_type": "Fixed Wireless and Satellite Upgrade Program",
    "target_eligibility_quarter": "NA"
   }
  }
 ]
}