{
 "type": "FeatureCollection",
 "generated": "2023-09-23T10:58:58.537445",
 "suburb": "DJIRU",
 "features": [
  {
   "type": "Feature",
   "geometry": {
    "type": "Point",
    "coordinates": [
     146.08399948,
     -17.8636508
    ]
   },
   "properties": {
    "name": "1303 EL ARISH - MISSION BEACH ROAD DJIRU 4852",
    "locID": "LOC000051122065",
    "tech": "SATELLITE",
    "upgrade": "NULL_NA",
    "gnaf_pid": "GAQLD162601749"
   }
  },
  {
   "type": "Feature",
   "geometry": {
    "type": "Point",
    "coordinates": [
     146.06275555,
     -17.86663942
    ]
   },
   "properties": {
    "name": "LOT 1 EL ARISH - MISSION BEACH ROAD DJIRU 4852",
    "locID": "LOC000051122065",
    "tech": "SATELLITE",
    "upgrade": "NULL_NA",
    "gnaf_pid": "GAQLD425203670"
   }
  },
  {
   "type": "Feature",
   "geometry": {
    "type": "Point",
    "coordinates": [
     146.08691469,
     -17.84895147
    ]
   },
   "properties": {
    "name": "LOT 115 BINGIL BAY ROAD DJIRU 4852",
    "locID": "EjExMTUgQmluZ2lsIEJheSBSZCwgQmluZ2lsIEJheSBRTEQgNDg1MiwgQXVzdHJhbGlhIjASLgoUChIJF4twZT0sf2kR8AVw5DrWMggQcyoUChIJ6aW5wjEsf2kRqSWYlE9vfEA",
    "tech": "SATELLITE",
    "upgrade": "UNKNOWN",
    "gnaf_pid": "GAQLD720592626"
   }
  }
 ]
}