{
 "type": "FeatureCollection",
 "generated": "2024-04-22T01:44:24.735348",
 "suburb": "DJIRU",
 "features": [
  {
   "type": "Feature",
   "geometry": {
    "type": "Point",
    "coordinates": [
     146.08399948,
     -17.8636508
    ]
   },
   "properties": {
    "name": "1303 EL ARISH - MISSION BEACH ROAD DJIRU 4852",
    "locID": "LOC000051122065",
    "tech": "SATELLITE",
    "upgrade": "NULL_NA",
    "gnaf_pid": "GAQLD162601749"
   }
  },
  {
   "type": "Feature",
   "geometry": {
    "type": "Point",
    "coordinates": [
     146.06275555,
     -17.86663942
    ]
   },
   "properties": {
    "name": "LOT 1 EL ARISH - MISSION BEACH ROAD DJIRU 4852",
    "locID": "LOC000051122065",
    "tech": "SATELLITE",
    "upgrade": "NULL_NA",
    "gnaf_pid": "GAQLD425203670"
   }
  }
 ]
}