{
 "type": "FeatureCollection",
 "generated": "2023-07-11T14:53:44.374393",
 "suburb": "FISHER",
 "features": [
  {
   "type": "Feature",
   "geometry": {
    "type": "Point",
    "coordinates": [
     139.51082415,
     -20.73223914
    ]
   },
   "properties": {
    "name": "LOT 97 PAMELA STREET FISHER 4825",
    "locID": "LOC000129535817",
    "tech": "FTTN",
    "upgrade": "NULL_NA",
    "gnaf_pid": "GAQLD155593614"
   }
  },
  {
   "type": "Feature",
   "geometry": {
    "type": "Point",
    "coordinates": [
     139.51261123,
     -20.73657925
    ]
   },
   "properties": {
    "name": "LOT 30 PAMELA STREET FISHER 4825",
    "locID": "LOC000129544856",
    "tech": "FTTN",
    "upgrade": "NULL_NA",
    "gnaf_pid": "GAQLD161270293"
   }
  },
  {
   "type": "Feature",
   "geometry": {
    "type": "Point",
    "coordinates": [
     139.51197489,
     -20.73316924
    ]
   },
   "properties": {
    "name": "LOT 31 PAMELA STREET FISHER 4825",
    "locID": "LOC000002598109",
    "tech": "FTTN",
    "upgrade": "NULL_NA",
    "gnaf_pid": "GAQLD161270294"
   }
  },
  {
   "type": "Feature",
   "geometry": {
    "type": "Point",
    "coordinates": [
     139.51233649,
     -20.73449297
    ]
   },
   "properties": {
    "name": "LOT 43 PAMELA STREET FISHER 4825",
    "locID": "LOC000129535801",
    "tech": "FTTN",
    "upgrade": "NULL_NA",
    "gnaf_pid": "GAQLD161270295"
   }
  },
  {
   "type": "Feature",
   "geometry": {
    "type": "Point",
    "coordinates": [
     139.50848396,
     -20.74332293
    ]
   },
   "properties": {
    "name": "LOT 56 RUSSELL CRESCENT FISHER 4825",
    "locID": "Eio1NiBSdXNzZWxsIENyZXMsIEhlYWx5IFFMRCA0ODI1LCBBdXN0cmFsaWEiMBIuChQKEglfq-Z1XVIWahFxr2xY8e4AExA4KhQKEgkt77IeXVIWahE3UcD0ndxtbw",
    "tech": "FTTN",
    "upgrade": "UNKNOWN",
    "gnaf_pid": "GAQLD161742479"
   }
  },
  {
   "type": "Feature",
   "geometry": {
    "type": "Point",
    "coordinates": [
     139.5192344,
     -20.72493257
    ]
   },
   "properties": {
    "name": "LOT 24 BARKLY HIGHWAY FISHER 4825",
    "locID": "ChIJIxWaPPBSFmoRCztYIfiQA8U",
    "tech": "FTTN",
    "upgrade": "UNKNOWN",
    "gnaf_pid": "GAQLD425260501"
   }
  },
  {
   "type": "Feature",
   "geometry": {
    "type": "Point",
    "coordinates": [
     139.51809233,
     -20.72529085
    ]
   },
   "properties": {
    "name": "LOT 69 BARKLY HIGHWAY FISHER 4825",
    "locID": "LOC000045578979",
    "tech": "FTTN",
    "upgrade": "NULL_NA",
    "gnaf_pid": "GAQLD425260502"
   }
  },
  {
   "type": "Feature",
   "geometry": {
    "type": "Point",
    "coordinates": [
     139.51953267,
     -20.72162314
    ]
   },
   "properties": {
    "name": "LOT 87 BARKLY HIGHWAY FISHER 4825",
    "locID": "Eik4NyBCYXJrbHkgSHd5LCBGaXNoZXIgUUxEIDQ4MjUsIEF1c3RyYWxpYSIwEi4KFAoSCeesMa-TUhZqEfcn3C9p6PafEFcqFAoSCRUPj2ul1QhqEbKxfJnADrW5",
    "tech": "FTTN",
    "upgrade": "UNKNOWN",
    "gnaf_pid": "GAQLD425260503"
   }
  },
  {
   "type": "Feature",
   "geometry": {
    "type": "Point",
    "coordinates": [
     139.51368233,
     -20.73144912
    ]
   },
   "properties": {
    "name": "LOT 93 PAMELA STREET FISHER 4825",
    "locID": "Eig5MyBQYW1lbGEgU3QsIEZpc2hlciBRTEQgNDgyNSwgQXVzdHJhbGlhIjASLgoUChIJkVVejoxSFmoRYUrHePHuABMQXSoUChIJveRw-fNSFmoRXfg7UmL9ixA",
    "tech": "FTTN",
    "upgrade": "UNKNOWN",
    "gnaf_pid": "GAQLD425265890"
   }
  },
  {
   "type": "Feature",
   "geometry": {
    "type": "Point",
    "coordinates": [
     139.50931805,
     -20.7463322
    ]
   },
   "properties": {
    "name": "LOT 2 PATERSON CRESCENT FISHER 4825",
    "locID": "LOC000094168731",
    "tech": "FTTN",
    "upgrade": "NULL_NA",
    "gnaf_pid": "GAQLD425265931"
   }
  },
  {
   "type": "Feature",
   "geometry": {
    "type": "Point",
    "coordinates": [
     139.51341803,
     -20.72596902
    ]
   },
   "properties": {
    "name": "LOT 1 BARKLY HIGHWAY FISHER 4825",
    "locID": "LOC000028953073",
    "tech": "FTTN",
    "upgrade": "NULL_NA",
    "gnaf_pid": "GAQLD720467065"
   }
  },
  {
   "type": "Feature",
   "geometry": {
    "type": "Point",
    "coordinates": [
     139.51634043,
     -20.72400049
    ]
   },
   "properties": {
    "name": "LOT 96 BARKLY HIGHWAY FISHER 4825",
    "locID": "Eik5NiBCYXJrbHkgSHd5LCBGaXNoZXIgUUxEIDQ4MjUsIEF1c3RyYWxpYSIwEi4KFAoSCW9QNO-TUhZqEXpjUpYW7mGxEGAqFAoSCRUPj2ul1QhqEbKxfJnADrW5",
    "tech": "FTTN",
    "upgrade": "UNKNOWN",
    "gnaf_pid": "GAQLD720482811"
   }
  }
 ]
}