{
 "type": "FeatureCollection",
 "generated": "2024-07-11T12:22:00.386477",
 "suburb": "FISHER",
 "features": [
  {
   "type": "Feature",
   "geometry": {
    "type": "Point",
    "coordinates": [
     139.51082415,
     -20.73223914
    ]
   },
   "properties": {
    "name": "LOT 97 PAMELA STREET FISHER 4825",
    "locID": "LOC000129535817",
    "tech": "FTTN",
    "upgrade": "NULL_NA",
    "gnaf_pid": "GAQLD155593614",
    "tech_change_status": "Not Planned"
   }
  },
  {
   "type": "Feature",
   "geometry": {
    "type": "Point",
    "coordinates": [
     139.51261123,
     -20.73657925
    ]
   },
   "properties": {
    "name": "LOT 30 PAMELA STREET FISHER 4825",
    "locID": "LOC000129544856",
    "tech": "FTTN",
    "upgrade": "FTTP_NA",
    "gnaf_pid": "GAQLD161270293",
    "tech_change_status": "Committed",
    "program_type": "On-Demand N2P SDU/MDU Simple",
    "target_eligibility_quarter": "Dec 2024"
   }
  },
  {
   "type": "Feature",
   "geometry": {
    "type": "Point",
    "coordinates": [
     139.51197489,
     -20.73316924
    ]
   },
   "properties": {
    "name": "LOT 31 PAMELA STREET FISHER 4825",
    "locID": "LOC000002598109",
    "tech": "FTTN",
    "upgrade": "FTTP_NA",
    "gnaf_pid": "GAQLD161270294",
    "tech_change_status": "Committed",
    "program_type": "On-Demand N2P SDU/MDU Simple",
    "target_eligibility_quarter": "Dec 2024"
   }
  },
  {
   "type": "Feature",
   "geometry": {
    "type": "Point",
    "coordinates": [
     139.51233649,
     -20.73449297
    ]
   },
   "properties": {
    "name": "LOT 43 PAMELA STREET FISHER 4825",
    "locID": "LOC000129535801",
    "tech": "FTTN",
    "upgrade": "NULL_NA",
    "gnaf_pid": "GAQLD161270295",
    "tech_change_status": "Not Planned"
   }
  },
  {
   "type": "Feature",
   "geometry": {
    "type": "Point",
    "coordinates": [
     139.51809233,
     -20.72529085
    ]
   },
   "properties": {
    "name": "LOT 69 BARKLY HIGHWAY FISHER 4825",
    "locID": "LOC000045578979",
    "tech": "FTTN",
    "upgrade": "NULL_NA",
    "gnaf_pid": "GAQLD425260502",
    "tech_change_status": "Not Planned"
   }
  },
  {
   "type": "Feature",
   "geometry": {
    "type": "Point",
    "coordinates": [
     139.50931805,
     -20.7463322
    ]
   },
   "properties": {
    "name": "LOT 2 PATERSON CRESCENT FISHER 4825",
    "locID": "LOC000094168731",
    "tech": "FTTN",
    "upgrade": "NULL_NA",
    "gnaf_pid": "GAQLD425265931",
    "tech_change_status": "Not Planned"
   }
  },
  {
   "type": "Feature",
   "geometry": {
    "type": "Point",
    "coordinates": [
     139.51341803,
     -20.72596902
    ]
   },
   "properties": {
    "name": "LOT 1 BARKLY HIGHWAY FISHER 4825",
    "locID": "LOC000028953073",
    "tech": "FTTN",
    "upgrade": "NULL_NA",
    "gnaf_pid": "GAQLD720467065",
    "tech_change_status": "Not Planned"
   }
  },
  {
   "type": "Feature",
   "geometry": {
    "type": "Point",
    "coordinates": [
     139.51548929,
     -20.72208557
    ]
   },
   "properties": {
    "name": "140 MARIAN STREET FISHER 4825",
    "locID": "LOC000170070151",
    "tech": "FTTN",
    "upgrade": "FTTP_NA",
    "gnaf_pid": "GAQLD721428020",
    "tech_change_status": "Committed",
    "program_type": "Customer-initiated N2P MDU Complex",
    "target_eligibility_quarter": "Mar 2025"
   }
  }
 ]
}