{
 "type": "FeatureCollection",
 "generated": "2023-09-23T13:35:12.484614",
 "suburb": "GAMBOOLA",
 "features": [
  {
   "type": "Feature",
   "geometry": {
    "type": "Point",
    "coordinates": [
     143.7295296,
     -16.37763944
    ]
   },
   "properties": {
    "name": "LOT 202 BURKE DEVELOPMENTAL ROAD GAMBOOLA 4892",
    "locID": "LOC000157491393",
    "tech": "SATELLITE",
    "upgrade": "NULL_NA",
    "gnaf_pid": "GAQLD162599205"
   }
  },
  {
   "type": "Feature",
   "geometry": {
    "type": "Point",
    "coordinates": [
     143.29515905,
     -16.24477683
    ]
   },
   "properties": {
    "name": "LOT 4568 BURKE DEVELOPMENTAL ROAD GAMBOOLA 4892",
    "locID": "LOC000157491393",
    "tech": "SATELLITE",
    "upgrade": "NULL_NA",
    "gnaf_pid": "GAQLD162599207"
   }
  },
  {
   "type": "Feature",
   "geometry": {
    "type": "Point",
    "coordinates": [
     143.00006287,
     -16.09528363
    ]
   },
   "properties": {
    "name": "LOT 2 BURKE DEVELOPMENTAL ROAD GAMBOOLA 4892",
    "locID": "LOC000157491393",
    "tech": "SATELLITE",
    "upgrade": "NULL_NA",
    "gnaf_pid": "GAQLD425288701"
   }
  },
  {
   "type": "Feature",
   "geometry": {
    "type": "Point",
    "coordinates": [
     143.53517304,
     -16.31777796
    ]
   },
   "properties": {
    "name": "LOT 434 STRATHLEVEN ROAD GAMBOOLA 4892",
    "locID": "LOC000154141109",
    "tech": "SATELLITE",
    "upgrade": "NULL_NA",
    "gnaf_pid": "GAQLD425291428"
   }
  },
  {
   "type": "Feature",
   "geometry": {
    "type": "Point",
    "coordinates": [
     143.71877176,
     -16.7220053
    ]
   },
   "properties": {
    "name": "48720 BURKE DEVELOPMENTAL ROAD GAMBOOLA 4892",
    "locID": "ChIJjTiz7ehdhGkRlkmLeP268MU",
    "tech": "SATELLITE",
    "upgrade": "UNKNOWN",
    "gnaf_pid": "GAQLD425586293"
   }
  }
 ]
}