{
 "type": "FeatureCollection",
 "generated": "2024-10-01T13:45:52.802931",
 "suburb": "GAMBOOLA",
 "features": [
  {
   "type": "Feature",
   "geometry": {
    "type": "Point",
    "coordinates": [
     143.7295296,
     -16.37763944
    ]
   },
   "properties": {
    "name": "LOT 202 BURKE DEVELOPMENTAL ROAD GAMBOOLA 4892",
    "locID": "LOC000157491393",
    "tech": "SATELLITE",
    "upgrade": "NULL_NA",
    "gnaf_pid": "GAQLD162599205",
    "tech_change_status": "Not Planned"
   }
  },
  {
   "type": "Feature",
   "geometry": {
    "type": "Point",
    "coordinates": [
     143.29515905,
     -16.24477683
    ]
   },
   "properties": {
    "name": "LOT 4568 BURKE DEVELOPMENTAL ROAD GAMBOOLA 4892",
    "locID": "LOC000157491393",
    "tech": "SATELLITE",
    "upgrade": "NULL_NA",
    "gnaf_pid": "GAQLD162599207",
    "tech_change_status": "Not Planned"
   }
  },
  {
   "type": "Feature",
   "geometry": {
    "type": "Point",
    "coordinates": [
     143.00006287,
     -16.09528363
    ]
   },
   "properties": {
    "name": "LOT 2 BURKE DEVELOPMENTAL ROAD GAMBOOLA 4892",
    "locID": "LOC000157491393",
    "tech": "SATELLITE",
    "upgrade": "NULL_NA",
    "gnaf_pid": "GAQLD425288701",
    "tech_change_status": "Not Planned"
   }
  },
  {
   "type": "Feature",
   "geometry": {
    "type": "Point",
    "coordinates": [
     143.53517304,
     -16.31777796
    ]
   },
   "properties": {
    "name": "LOT 434 STRATHLEVEN ROAD GAMBOOLA 4892",
    "locID": "LOC000154141109",
    "tech": "SATELLITE",
    "upgrade": "NULL_NA",
    "gnaf_pid": "GAQLD425291428",
    "tech_change_status": "Not Planned"
   }
  }
 ]
}