{
 "type": "FeatureCollection",
 "generated": "2024-08-02T07:30:44.976919",
 "suburb": "GIRRAWEEN",
 "features": [
  {
   "type": "Feature",
   "geometry": {
    "type": "Point",
    "coordinates": [
     151.95179638,
     -28.82625239
    ]
   },
   "properties": {
    "name": "1689 PYRAMIDS ROAD GIRRAWEEN 4382",
    "locID": "LOC000100871948",
    "tech": "SATELLITE",
    "upgrade": "NULL_NA",
    "gnaf_pid": "GAQLD160693079",
    "tech_change_status": "Not Planned"
   }
  }
 ]
}