{
 "type": "FeatureCollection",
 "generated": "2023-07-13T23:29:32.716270",
 "suburb": "GIRRAWEEN",
 "features": [
  {
   "type": "Feature",
   "geometry": {
    "type": "Point",
    "coordinates": [
     151.95179638,
     -28.82625239
    ]
   },
   "properties": {
    "name": "1486 PYRAMIDS ROAD GIRRAWEEN 4382",
    "locID": "ChIJJ13lAfY2mGsRLrCicw7SJaQ",
    "tech": "SATELLITE",
    "upgrade": "UNKNOWN",
    "gnaf_pid": "GAQLD157959170"
   }
  },
  {
   "type": "Feature",
   "geometry": {
    "type": "Point",
    "coordinates": [
     151.95179638,
     -28.82625239
    ]
   },
   "properties": {
    "name": "1689 PYRAMIDS ROAD GIRRAWEEN 4382",
    "locID": "LOC000100871948",
    "tech": "SATELLITE",
    "upgrade": "NULL_NA",
    "gnaf_pid": "GAQLD160693079"
   }
  },
  {
   "type": "Feature",
   "geometry": {
    "type": "Point",
    "coordinates": [
     151.95137227,
     -28.85355218
    ]
   },
   "properties": {
    "name": "LOT 29 PYRAMIDS ROAD GIRRAWEEN 4382",
    "locID": "EjFUaGUgUHlyYW1pZHMgVHJhaWwsIEdpcnJhd2VlbiBRTEQgNDM4MiwgQXVzdHJhbGlhIi4qLAoUChIJBxasb1Y2mGsRfCW7lVq2oLQSFAoSCcnQMMlDNphrEWCzIH_x7gAE",
    "tech": "SATELLITE",
    "upgrade": "UNKNOWN",
    "gnaf_pid": "GAQLD719444059"
   }
  }
 ]
}