{
 "type": "FeatureCollection",
 "generated": "2023-07-14T02:40:31.596632",
 "suburb": "GREAT SANDY STRAIT",
 "features": [
  {
   "type": "Feature",
   "geometry": {
    "type": "Point",
    "coordinates": [
     152.95386204,
     -25.61694658
    ]
   },
   "properties": {
    "name": "LOT 1 ESPLANADE GREAT SANDY STRAIT 4655",
    "locID": "LOC000015792460",
    "tech": "FTTN",
    "upgrade": "NULL_NA",
    "gnaf_pid": "GAQLD163162964"
   }
  },
  {
   "type": "Feature",
   "geometry": {
    "type": "Point",
    "coordinates": [
     152.95410571,
     -25.61720313
    ]
   },
   "properties": {
    "name": "LOT 2 ESPLANADE GREAT SANDY STRAIT 4655",
    "locID": "EicyIEVzcGxhbmFkZSwgUXVlZW5zbGFuZCA0NjU1LCBBdXN0cmFsaWEiLiosChQKEgklQ_azRY_saxFZQaPyUCz6PhIUChIJK2wS_GSe7GsR8BwJ0_TuABw",
    "tech": "SATELLITE",
    "upgrade": "UNKNOWN",
    "gnaf_pid": "GAQLD163162965"
   }
  },
  {
   "type": "Feature",
   "geometry": {
    "type": "Point",
    "coordinates": [
     152.95368549,
     -25.61654599
    ]
   },
   "properties": {
    "name": "LOT 3 ESPLANADE GREAT SANDY STRAIT 4655",
    "locID": "EiczIEVzcGxhbmFkZSwgUXVlZW5zbGFuZCA0NjU1LCBBdXN0cmFsaWEiLiosChQKEgklQ_azRY_saxFZQaPyUCz6PhIUChIJK2wS_GSe7GsR8BwJ0_TuABw",
    "tech": "SATELLITE",
    "upgrade": "UNKNOWN",
    "gnaf_pid": "GAQLD163162966"
   }
  },
  {
   "type": "Feature",
   "geometry": {
    "type": "Point",
    "coordinates": [
     152.90861179,
     -25.33998392
    ]
   },
   "properties": {
    "name": "163 SEA EAGLES ROAD GREAT SANDY STRAIT 4655",
    "locID": "ChIJdZbTnFqB7GsRUQINgncLra4",
    "tech": "SATELLITE",
    "upgrade": "UNKNOWN",
    "gnaf_pid": "GAQLD163174191"
   }
  }
 ]
}