{
 "type": "FeatureCollection",
 "generated": "2024-10-02T08:37:12.428782",
 "suburb": "GREAT SANDY STRAIT",
 "features": [
  {
   "type": "Feature",
   "geometry": {
    "type": "Point",
    "coordinates": [
     152.95386204,
     -25.61694658
    ]
   },
   "properties": {
    "name": "LOT 1 ESPLANADE GREAT SANDY STRAIT 4655",
    "locID": "LOC000015792460",
    "tech": "FTTN",
    "upgrade": "FTTP_SA",
    "gnaf_pid": "GAQLD163162964",
    "tech_change_status": "Eligible to Order",
    "program_type": "On-Demand N2P SDU/MDU Simple",
    "target_eligibility_quarter": "NA"
   }
  }
 ]
}