{
 "type": "FeatureCollection",
 "generated": "2024-06-07T00:57:58.819226",
 "suburb": "GREAT SANDY STRAIT",
 "features": [
  {
   "type": "Feature",
   "geometry": {
    "type": "Point",
    "coordinates": [
     152.95386204,
     -25.61694658
    ]
   },
   "properties": {
    "name": "LOT 1 ESPLANADE GREAT SANDY STRAIT 4655",
    "locID": "LOC000015792460",
    "tech": "FTTN",
    "upgrade": "NULL_NA",
    "gnaf_pid": "GAQLD163162964",
    "tech_change_status": "Not Planned"
   }
  }
 ]
}