{
 "type": "FeatureCollection",
 "generated": "2024-07-16T14:42:11.703525",
 "suburb": "GWAMBEGWINE",
 "features": [
  {
   "type": "Feature",
   "geometry": {
    "type": "Point",
    "coordinates": [
     149.75814549,
     -25.43925679
    ]
   },
   "properties": {
    "name": "LOT 2 FITZROY DEVELOPMENTAL ROAD GWAMBEGWINE 4420",
    "locID": "LOC000128190949",
    "tech": "SATELLITE",
    "upgrade": "NULL_NA",
    "gnaf_pid": "GAQLD161148569",
    "tech_change_status": "Not Planned"
   }
  },
  {
   "type": "Feature",
   "geometry": {
    "type": "Point",
    "coordinates": [
     149.60132389,
     -25.39801877
    ]
   },
   "properties": {
    "name": "LOT 3 FITZROY DEVELOPMENTAL ROAD GWAMBEGWINE 4420",
    "locID": "LOC000128198075",
    "tech": "SATELLITE",
    "upgrade": "NULL_NA",
    "gnaf_pid": "GAQLD161148570",
    "tech_change_status": "Not Planned"
   }
  },
  {
   "type": "Feature",
   "geometry": {
    "type": "Point",
    "coordinates": [
     149.70817226,
     -25.39021267
    ]
   },
   "properties": {
    "name": "LOT 5 FITZROY DEVELOPMENTAL ROAD GWAMBEGWINE 4420",
    "locID": "LOC000128205566",
    "tech": "SATELLITE",
    "upgrade": "NULL_NA",
    "gnaf_pid": "GAQLD161148572",
    "tech_change_status": "Not Planned"
   }
  },
  {
   "type": "Feature",
   "geometry": {
    "type": "Point",
    "coordinates": [
     149.77582441,
     -25.42833275
    ]
   },
   "properties": {
    "name": "LOT 6 FITZROY DEVELOPMENTAL ROAD GWAMBEGWINE 4420",
    "locID": "LOC000128170319",
    "tech": "SATELLITE",
    "upgrade": "NULL_NA",
    "gnaf_pid": "GAQLD161148573",
    "tech_change_status": "Not Planned"
   }
  },
  {
   "type": "Feature",
   "geometry": {
    "type": "Point",
    "coordinates": [
     149.59934123,
     -25.40073552
    ]
   },
   "properties": {
    "name": "LOT 52 GLENHAUGHTON ROAD GWAMBEGWINE 4420",
    "locID": "LOC000128205495",
    "tech": "SATELLITE",
    "upgrade": "NULL_NA",
    "gnaf_pid": "GAQLD161161189",
    "tech_change_status": "Not Planned"
   }
  },
  {
   "type": "Feature",
   "geometry": {
    "type": "Point",
    "coordinates": [
     149.63622449,
     -25.35907844
    ]
   },
   "properties": {
    "name": "2163 FITZROY DEVELOPMENTAL ROAD GWAMBEGWINE 4420",
    "locID": "LOC000128194303",
    "tech": "SATELLITE",
    "upgrade": "NULL_NA",
    "gnaf_pid": "GAQLD162144164",
    "tech_change_status": "Not Planned"
   }
  },
  {
   "type": "Feature",
   "geometry": {
    "type": "Point",
    "coordinates": [
     149.39097897,
     -25.25399322
    ]
   },
   "properties": {
    "name": "3103 FITZROY DEVELOPMENTAL ROAD GWAMBEGWINE 4420",
    "locID": "LOC000128198075",
    "tech": "SATELLITE",
    "upgrade": "NULL_NA",
    "gnaf_pid": "GAQLD162144166",
    "tech_change_status": "Not Planned"
   }
  },
  {
   "type": "Feature",
   "geometry": {
    "type": "Point",
    "coordinates": [
     149.72590765,
     -25.43645431
    ]
   },
   "properties": {
    "name": "589 FITZROY DEVELOPMENTAL ROAD GWAMBEGWINE 4420",
    "locID": "LOC000128205566",
    "tech": "SATELLITE",
    "upgrade": "NULL_NA",
    "gnaf_pid": "GAQLD162144167",
    "tech_change_status": "Not Planned"
   }
  },
  {
   "type": "Feature",
   "geometry": {
    "type": "Point",
    "coordinates": [
     149.70014504,
     -25.34834344
    ]
   },
   "properties": {
    "name": "1025 GHINGHINDA ROAD GWAMBEGWINE 4420",
    "locID": "LOC100078016149",
    "tech": "SATELLITE",
    "upgrade": "NULL_NA",
    "gnaf_pid": "GAQLD162147208",
    "tech_change_status": "Not Planned"
   }
  },
  {
   "type": "Feature",
   "geometry": {
    "type": "Point",
    "coordinates": [
     149.52765781,
     -25.37571011
    ]
   },
   "properties": {
    "name": "3336 GLENHAUGHTON ROAD GWAMBEGWINE 4420",
    "locID": "LOC000173575337",
    "tech": "SATELLITE",
    "upgrade": "NULL_NA",
    "gnaf_pid": "GAQLD162148222",
    "tech_change_status": "Not Planned"
   }
  },
  {
   "type": "Feature",
   "geometry": {
    "type": "Point",
    "coordinates": [
     149.77358119,
     -25.37302695
    ]
   },
   "properties": {
    "name": "198 GHINGHINDA ROAD GWAMBEGWINE 4420",
    "locID": "LOC000180956427",
    "tech": "SATELLITE",
    "upgrade": "NULL_NA",
    "gnaf_pid": "GAQLD720663765",
    "tech_change_status": "Not Planned"
   }
  },
  {
   "type": "Feature",
   "geometry": {
    "type": "Point",
    "coordinates": [
     149.73664704,
     -25.40266213
    ]
   },
   "properties": {
    "name": "LOT 4 FITZROY DEVELOPMENTAL ROAD GWAMBEGWINE 4420",
    "locID": "LOC000128170319",
    "tech": "SATELLITE",
    "upgrade": "NULL_NA",
    "gnaf_pid": "GAQLD720676991",
    "tech_change_status": "Not Planned"
   }
  }
 ]
}