{
 "type": "FeatureCollection",
 "generated": "2024-09-16T04:07:09.907349",
 "suburb": "INSKIP",
 "features": [
  {
   "type": "Feature",
   "geometry": {
    "type": "Point",
    "coordinates": [
     153.0694432,
     -25.85220987
    ]
   },
   "properties": {
    "name": "LOT 1 INSKIP AVENUE INSKIP 4581",
    "locID": "LOC000128483348",
    "tech": "NULL",
    "upgrade": "NULL_NA",
    "gnaf_pid": "GAQLD161440704",
    "tech_change_status": "Not Planned"
   }
  },
  {
   "type": "Feature",
   "geometry": {
    "type": "Point",
    "coordinates": [
     153.06297337,
     -25.83279976
    ]
   },
   "properties": {
    "name": "LOT 21 INSKIP AVENUE INSKIP 4581",
    "locID": "LOC000171617271",
    "tech": "FTTP",
    "upgrade": "FTTP_NA",
    "gnaf_pid": "GAQLD161440705",
    "tech_change_status": "Previous Tech Disconnected",
    "program_type": "On-Demand N2P SDU/MDU Simple",
    "target_eligibility_quarter": "NA"
   }
  },
  {
   "type": "Feature",
   "geometry": {
    "type": "Point",
    "coordinates": [
     153.07160022,
     -25.84761554
    ]
   },
   "properties": {
    "name": "LOT 22 INSKIP AVENUE INSKIP 4581",
    "locID": "LOC000171617271",
    "tech": "FTTP",
    "upgrade": "FTTP_NA",
    "gnaf_pid": "GAQLD161440706",
    "tech_change_status": "Previous Tech Disconnected",
    "program_type": "On-Demand N2P SDU/MDU Simple",
    "target_eligibility_quarter": "NA"
   }
  },
  {
   "type": "Feature",
   "geometry": {
    "type": "Point",
    "coordinates": [
     153.07784165,
     -25.87571935
    ]
   },
   "properties": {
    "name": "LOT 24 INSKIP AVENUE INSKIP 4581",
    "locID": "LOC000171617271",
    "tech": "FTTP",
    "upgrade": "FTTP_NA",
    "gnaf_pid": "GAQLD161440707",
    "tech_change_status": "Previous Tech Disconnected",
    "program_type": "On-Demand N2P SDU/MDU Simple",
    "target_eligibility_quarter": "NA"
   }
  },
  {
   "type": "Feature",
   "geometry": {
    "type": "Point",
    "coordinates": [
     153.06827349,
     -25.81244151
    ]
   },
   "properties": {
    "name": "LOT 28 INSKIP AVENUE INSKIP 4581",
    "locID": "LOC000171617271",
    "tech": "FTTP",
    "upgrade": "FTTP_NA",
    "gnaf_pid": "GAQLD161440708",
    "tech_change_status": "Previous Tech Disconnected",
    "program_type": "On-Demand N2P SDU/MDU Simple",
    "target_eligibility_quarter": "NA"
   }
  },
  {
   "type": "Feature",
   "geometry": {
    "type": "Point",
    "coordinates": [
     153.06709642,
     -25.87082391
    ]
   },
   "properties": {
    "name": "LOT 4 BRIAN SMITH DRIVE INSKIP 4581",
    "locID": "LOC000128532776",
    "tech": "NULL",
    "upgrade": "NULL_NA",
    "gnaf_pid": "GAQLD719798295",
    "tech_change_status": "Not Planned"
   }
  }
 ]
}