{
 "type": "FeatureCollection",
 "generated": "2023-09-25T23:58:48.233462",
 "suburb": "INSKIP",
 "features": [
  {
   "type": "Feature",
   "geometry": {
    "type": "Point",
    "coordinates": [
     153.0694432,
     -25.85220987
    ]
   },
   "properties": {
    "name": "LOT 1 INSKIP AVENUE INSKIP 4581",
    "locID": "LOC000128483348",
    "tech": "SATELLITE",
    "upgrade": "NULL_NA",
    "gnaf_pid": "GAQLD161440704"
   }
  },
  {
   "type": "Feature",
   "geometry": {
    "type": "Point",
    "coordinates": [
     153.06297337,
     -25.83279976
    ]
   },
   "properties": {
    "name": "LOT 21 INSKIP AVENUE INSKIP 4581",
    "locID": "LOC000171617271",
    "tech": "FTTN",
    "upgrade": "NULL_NA",
    "gnaf_pid": "GAQLD161440705"
   }
  },
  {
   "type": "Feature",
   "geometry": {
    "type": "Point",
    "coordinates": [
     153.07160022,
     -25.84761554
    ]
   },
   "properties": {
    "name": "LOT 22 INSKIP AVENUE INSKIP 4581",
    "locID": "LOC000171617271",
    "tech": "FTTN",
    "upgrade": "NULL_NA",
    "gnaf_pid": "GAQLD161440706"
   }
  },
  {
   "type": "Feature",
   "geometry": {
    "type": "Point",
    "coordinates": [
     153.07784165,
     -25.87571935
    ]
   },
   "properties": {
    "name": "LOT 24 INSKIP AVENUE INSKIP 4581",
    "locID": "LOC000171617271",
    "tech": "FTTN",
    "upgrade": "NULL_NA",
    "gnaf_pid": "GAQLD161440707"
   }
  },
  {
   "type": "Feature",
   "geometry": {
    "type": "Point",
    "coordinates": [
     153.06827349,
     -25.81244151
    ]
   },
   "properties": {
    "name": "LOT 28 INSKIP AVENUE INSKIP 4581",
    "locID": "LOC000171617271",
    "tech": "FTTN",
    "upgrade": "NULL_NA",
    "gnaf_pid": "GAQLD161440708"
   }
  },
  {
   "type": "Feature",
   "geometry": {
    "type": "Point",
    "coordinates": [
     153.06134886,
     -25.86762311
    ]
   },
   "properties": {
    "name": "LOT 1 BRIAN SMITH DRIVE INSKIP 4581",
    "locID": "LOC000128532776",
    "tech": "SATELLITE",
    "upgrade": "NULL_NA",
    "gnaf_pid": "GAQLD162951426"
   }
  },
  {
   "type": "Feature",
   "geometry": {
    "type": "Point",
    "coordinates": [
     153.06432746,
     -25.82613193
    ]
   },
   "properties": {
    "name": "LOT 80 BULLOCK POINT ROAD INSKIP 4581",
    "locID": "EixCdWxsb2NrIFBvaW50IFJkLCBJbnNraXAgUUxEIDQ1ODEsIEF1c3RyYWxpYSIuKiwKFAoSCQWfTMhisOxrEau8lKzAz5eXEhQKEgkP4IKEsbHsaxFw8iB_8e4ABA",
    "tech": "SATELLITE",
    "upgrade": "UNKNOWN",
    "gnaf_pid": "GAQLD719271815"
   }
  },
  {
   "type": "Feature",
   "geometry": {
    "type": "Point",
    "coordinates": [
     153.06709642,
     -25.87082391
    ]
   },
   "properties": {
    "name": "LOT 4 BRIAN SMITH DRIVE INSKIP 4581",
    "locID": "LOC000128532776",
    "tech": "SATELLITE",
    "upgrade": "NULL_NA",
    "gnaf_pid": "GAQLD719798295"
   }
  },
  {
   "type": "Feature",
   "geometry": {
    "type": "Point",
    "coordinates": [
     153.06843808,
     -25.82841785
    ]
   },
   "properties": {
    "name": "LOT 81 INSKIP POINT ROAD INSKIP 4581",
    "locID": "EitJbnNraXAgUG9pbnQgUmQsIEluc2tpcCBRTEQgNDU4MSwgQXVzdHJhbGlhIi4qLAoUChIJA-onSX6w7GsRwrASLBPg9kcSFAoSCQ_ggoSxsexrEXDyIH_x7gAE",
    "tech": "SATELLITE",
    "upgrade": "UNKNOWN",
    "gnaf_pid": "GAQLD719801449"
   }
  },
  {
   "type": "Feature",
   "geometry": {
    "type": "Point",
    "coordinates": [
     153.07514914,
     -25.8480517
    ]
   },
   "properties": {
    "name": "LOT 1 INSKIP POINT ROAD INSKIP 4581",
    "locID": "EitJbnNraXAgUG9pbnQgUmQsIEluc2tpcCBRTEQgNDU4MSwgQXVzdHJhbGlhIi4qLAoUChIJA-onSX6w7GsRwrASLBPg9kcSFAoSCQ_ggoSxsexrEXDyIH_x7gAE",
    "tech": "SATELLITE",
    "upgrade": "UNKNOWN",
    "gnaf_pid": "GAQLD719847193"
   }
  }
 ]
}