{
 "type": "FeatureCollection",
 "generated": "2024-08-27T13:36:50.179834",
 "suburb": "KILMOREY FALLS",
 "features": [
  {
   "type": "Feature",
   "geometry": {
    "type": "Point",
    "coordinates": [
     148.11139926,
     -26.3235933
    ]
   },
   "properties": {
    "name": "730 EASTERN CREEK ROAD KILMOREY FALLS 4465",
    "locID": "LOC000096147417",
    "tech": "SATELLITE",
    "upgrade": "NULL_NA",
    "gnaf_pid": "GAQLD163122933",
    "tech_change_status": "Not Planned"
   }
  },
  {
   "type": "Feature",
   "geometry": {
    "type": "Point",
    "coordinates": [
     148.36744503,
     -26.16831521
    ]
   },
   "properties": {
    "name": "161 ALCURAH ROAD KILMOREY FALLS 4465",
    "locID": "LOC100078018956",
    "tech": "SATELLITE",
    "upgrade": "NULL_NA",
    "gnaf_pid": "GAQLD425472547",
    "tech_change_status": "Not Planned"
   }
  },
  {
   "type": "Feature",
   "geometry": {
    "type": "Point",
    "coordinates": [
     148.29359046,
     -26.11406687
    ]
   },
   "properties": {
    "name": "1680 ALCURAH ROAD KILMOREY FALLS 4465",
    "locID": "LOC000150185619",
    "tech": "SATELLITE",
    "upgrade": "NULL_NA",
    "gnaf_pid": "GAQLD425472549",
    "tech_change_status": "Not Planned"
   }
  },
  {
   "type": "Feature",
   "geometry": {
    "type": "Point",
    "coordinates": [
     148.3545332,
     -26.07277676
    ]
   },
   "properties": {
    "name": "788 ALCURAH ROAD KILMOREY FALLS 4465",
    "locID": "LOC000150185626",
    "tech": "SATELLITE",
    "upgrade": "NULL_NA",
    "gnaf_pid": "GAQLD425472550",
    "tech_change_status": "Not Planned"
   }
  },
  {
   "type": "Feature",
   "geometry": {
    "type": "Point",
    "coordinates": [
     148.18503065,
     -25.92503572
    ]
   },
   "properties": {
    "name": "7928 COOPERMURRA ROAD KILMOREY FALLS 4465",
    "locID": "LOC000142362508",
    "tech": "SATELLITE",
    "upgrade": "NULL_NA",
    "gnaf_pid": "GAQLD425474118",
    "tech_change_status": "Not Planned"
   }
  },
  {
   "type": "Feature",
   "geometry": {
    "type": "Point",
    "coordinates": [
     148.11042932,
     -26.33590887
    ]
   },
   "properties": {
    "name": "2438 WARRONG ROAD KILMOREY FALLS 4465",
    "locID": "LOC000150185661",
    "tech": "SATELLITE",
    "upgrade": "NULL_NA",
    "gnaf_pid": "GAQLD425480209",
    "tech_change_status": "Not Planned"
   }
  },
  {
   "type": "Feature",
   "geometry": {
    "type": "Point",
    "coordinates": [
     148.14347658,
     -26.13176619
    ]
   },
   "properties": {
    "name": "5003 WARRONG ROAD KILMOREY FALLS 4465",
    "locID": "LOC000160476050",
    "tech": "SATELLITE",
    "upgrade": "NULL_NA",
    "gnaf_pid": "GAQLD425480210",
    "tech_change_status": "Not Planned"
   }
  },
  {
   "type": "Feature",
   "geometry": {
    "type": "Point",
    "coordinates": [
     148.23463372,
     -26.03282662
    ]
   },
   "properties": {
    "name": "5914 WARRONG ROAD KILMOREY FALLS 4465",
    "locID": "LOC000182278045",
    "tech": "SATELLITE",
    "upgrade": "NULL_NA",
    "gnaf_pid": "GAQLD425480211",
    "tech_change_status": "Not Planned"
   }
  }
 ]
}