{
 "type": "FeatureCollection",
 "generated": "2024-03-13T17:55:11.478225",
 "suburb": "KIOMA",
 "features": [
  {
   "type": "Feature",
   "geometry": {
    "type": "Point",
    "coordinates": [
     149.82393678,
     -28.23999636
    ]
   },
   "properties": {
    "name": "LOT 8 KIOMA ROAD KIOMA 4498",
    "locID": "LOC000033296651",
    "tech": "SATELLITE",
    "upgrade": "NULL_NA",
    "gnaf_pid": "GAQLD161202349"
   }
  },
  {
   "type": "Feature",
   "geometry": {
    "type": "Point",
    "coordinates": [
     149.80486505,
     -28.14643801
    ]
   },
   "properties": {
    "name": "34 BUCKHAVEN ROAD KIOMA 4498",
    "locID": "LOC000022623976",
    "tech": "SATELLITE",
    "upgrade": "NULL_NA",
    "gnaf_pid": "GAQLD162343166"
   }
  },
  {
   "type": "Feature",
   "geometry": {
    "type": "Point",
    "coordinates": [
     149.80394565,
     -28.27042692
    ]
   },
   "properties": {
    "name": "1212 KIOMA ROAD KIOMA 4498",
    "locID": "LOC000004487150",
    "tech": "SATELLITE",
    "upgrade": "NULL_NA",
    "gnaf_pid": "GAQLD162354319"
   }
  },
  {
   "type": "Feature",
   "geometry": {
    "type": "Point",
    "coordinates": [
     149.83092491,
     -28.14976966
    ]
   },
   "properties": {
    "name": "2949 KIOMA ROAD KIOMA 4498",
    "locID": "LOC000096802208",
    "tech": "SATELLITE",
    "upgrade": "NULL_NA",
    "gnaf_pid": "GAQLD162354320"
   }
  },
  {
   "type": "Feature",
   "geometry": {
    "type": "Point",
    "coordinates": [
     149.85685889,
     -28.15273759
    ]
   },
   "properties": {
    "name": "3543 KIOMA ROAD KIOMA 4498",
    "locID": "LOC000021555408",
    "tech": "SATELLITE",
    "upgrade": "NULL_NA",
    "gnaf_pid": "GAQLD162354321"
   }
  },
  {
   "type": "Feature",
   "geometry": {
    "type": "Point",
    "coordinates": [
     149.75882886,
     -28.23062815
    ]
   },
   "properties": {
    "name": "1883 MOLINDA ROAD KIOMA 4498",
    "locID": "LOC000085509580",
    "tech": "SATELLITE",
    "upgrade": "NULL_NA",
    "gnaf_pid": "GAQLD162358182"
   }
  },
  {
   "type": "Feature",
   "geometry": {
    "type": "Point",
    "coordinates": [
     149.77465253,
     -28.28999183
    ]
   },
   "properties": {
    "name": "LOT 1 GLENGOWER ROAD KIOMA 4498",
    "locID": "LOC000070030296",
    "tech": "SATELLITE",
    "upgrade": "NULL_NA",
    "gnaf_pid": "GAQLD162508095"
   }
  },
  {
   "type": "Feature",
   "geometry": {
    "type": "Point",
    "coordinates": [
     149.76186962,
     -28.19889952
    ]
   },
   "properties": {
    "name": "2155 KIOMA ROAD KIOMA 4498",
    "locID": "LOC000017403060",
    "tech": "SATELLITE",
    "upgrade": "NULL_NA",
    "gnaf_pid": "GAQLD162511597"
   }
  },
  {
   "type": "Feature",
   "geometry": {
    "type": "Point",
    "coordinates": [
     149.68034767,
     -28.25015341
    ]
   },
   "properties": {
    "name": "1298 MOLINDA ROAD KIOMA 4498",
    "locID": "LOC000033296651",
    "tech": "SATELLITE",
    "upgrade": "NULL_NA",
    "gnaf_pid": "GAQLD162515010"
   }
  },
  {
   "type": "Feature",
   "geometry": {
    "type": "Point",
    "coordinates": [
     149.75422921,
     -28.26708069
    ]
   },
   "properties": {
    "name": "1864 MOLINDA ROAD KIOMA 4498",
    "locID": "LOC000070030296",
    "tech": "SATELLITE",
    "upgrade": "NULL_NA",
    "gnaf_pid": "GAQLD162515011"
   }
  },
  {
   "type": "Feature",
   "geometry": {
    "type": "Point",
    "coordinates": [
     149.79516847,
     -28.21179104
    ]
   },
   "properties": {
    "name": "20 KIOMA ROAD KIOMA 4498",
    "locID": "LOC000096802208",
    "tech": "SATELLITE",
    "upgrade": "NULL_NA",
    "gnaf_pid": "GAQLD163263877"
   }
  },
  {
   "type": "Feature",
   "geometry": {
    "type": "Point",
    "coordinates": [
     149.79352666,
     -28.21700254
    ]
   },
   "properties": {
    "name": "2131 KIOMA ROAD KIOMA 4498",
    "locID": "LOC000009288276",
    "tech": "SATELLITE",
    "upgrade": "NULL_NA",
    "gnaf_pid": "GAQLD163263878"
   }
  }
 ]
}