{
 "type": "FeatureCollection",
 "generated": "2023-07-14T17:49:13.253483",
 "suburb": "LAKE TINAROO",
 "features": [
  {
   "type": "Feature",
   "geometry": {
    "type": "Point",
    "coordinates": [
     145.55381356,
     -17.1813416
    ]
   },
   "properties": {
    "name": "LOT 624 BLACK GULLY ROAD LAKE TINAROO 4872",
    "locID": "LOC000142848024",
    "tech": "WIRELESS",
    "upgrade": "NULL_NA",
    "gnaf_pid": "GAQLD161068806"
   }
  },
  {
   "type": "Feature",
   "geometry": {
    "type": "Point",
    "coordinates": [
     145.54899691,
     -17.1624189
    ]
   },
   "properties": {
    "name": "LOT 10 TINAROO FALLS DAM ROAD LAKE TINAROO 4872",
    "locID": "EjkxMCBUaW5hcm9vIEZhbGxzIERhbSBSZCwgTGFrZSBUaW5hcm9vIFFMRCA0ODcyLCBBdXN0cmFsaWEiMBIuChQKEgmFCQJw3Zx4aRF4UDKEEJB8uxAKKhQKEgmv06Ps-Zx4aRH2PBpoUKlsYA",
    "tech": "WIRELESS",
    "upgrade": "UNKNOWN",
    "gnaf_pid": "GAQLD161331444"
   }
  },
  {
   "type": "Feature",
   "geometry": {
    "type": "Point",
    "coordinates": [
     145.55425269,
     -17.18140456
    ]
   },
   "properties": {
    "name": "LOT 843 BLACK GULLY ROAD LAKE TINAROO 4872",
    "locID": "LOC000142848024",
    "tech": "WIRELESS",
    "upgrade": "NULL_NA",
    "gnaf_pid": "GAQLD161427021"
   }
  },
  {
   "type": "Feature",
   "geometry": {
    "type": "Point",
    "coordinates": [
     145.5679676,
     -17.18461672
    ]
   },
   "properties": {
    "name": "47 FOSTER ROAD LAKE TINAROO 4872",
    "locID": "LOC000116182545",
    "tech": "WIRELESS",
    "upgrade": "NULL_NA",
    "gnaf_pid": "GAQLD162349524"
   }
  }
 ]
}