{
 "type": "FeatureCollection",
 "generated": "2024-08-27T20:41:24.009967",
 "suburb": "LAKE BORUMBA",
 "features": [
  {
   "type": "Feature",
   "geometry": {
    "type": "Point",
    "coordinates": [
     152.50158396,
     -26.52213798
    ]
   },
   "properties": {
    "name": "4 BELLA CREEK ROAD LAKE BORUMBA 4570",
    "locID": "LOC000062735726",
    "tech": "SATELLITE",
    "upgrade": "NULL_NA",
    "gnaf_pid": "GAQLD160161165",
    "tech_change_status": "Not Planned"
   }
  },
  {
   "type": "Feature",
   "geometry": {
    "type": "Point",
    "coordinates": [
     152.50158396,
     -26.52213798
    ]
   },
   "properties": {
    "name": "1 BELLA CREEK ROAD LAKE BORUMBA 4570",
    "locID": "LOC000035772984",
    "tech": "SATELLITE",
    "upgrade": "NULL_NA",
    "gnaf_pid": "GAQLD160174503",
    "tech_change_status": "Not Planned"
   }
  },
  {
   "type": "Feature",
   "geometry": {
    "type": "Point",
    "coordinates": [
     152.50158396,
     -26.52213798
    ]
   },
   "properties": {
    "name": "3 BELLA CREEK ROAD LAKE BORUMBA 4570",
    "locID": "LOC000062735726",
    "tech": "SATELLITE",
    "upgrade": "NULL_NA",
    "gnaf_pid": "GAQLD160174505",
    "tech_change_status": "Not Planned"
   }
  },
  {
   "type": "Feature",
   "geometry": {
    "type": "Point",
    "coordinates": [
     152.48916469,
     -26.51796904
    ]
   },
   "properties": {
    "name": "LOT 1 BELLA CREEK ROAD LAKE BORUMBA 4570",
    "locID": "LOC000035772984",
    "tech": "SATELLITE",
    "upgrade": "NULL_NA",
    "gnaf_pid": "GAQLD161064125",
    "tech_change_status": "Not Planned"
   }
  },
  {
   "type": "Feature",
   "geometry": {
    "type": "Point",
    "coordinates": [
     152.524675,
     -26.50446324
    ]
   },
   "properties": {
    "name": "LOT 3 BELLA CREEK ROAD LAKE BORUMBA 4570",
    "locID": "LOC000062735726",
    "tech": "SATELLITE",
    "upgrade": "NULL_NA",
    "gnaf_pid": "GAQLD161064130",
    "tech_change_status": "Not Planned"
   }
  },
  {
   "type": "Feature",
   "geometry": {
    "type": "Point",
    "coordinates": [
     152.52745894,
     -26.5069618
    ]
   },
   "properties": {
    "name": "LOT 4 BELLA CREEK ROAD LAKE BORUMBA 4570",
    "locID": "LOC000035772984",
    "tech": "SATELLITE",
    "upgrade": "NULL_NA",
    "gnaf_pid": "GAQLD161064131",
    "tech_change_status": "Not Planned"
   }
  },
  {
   "type": "Feature",
   "geometry": {
    "type": "Point",
    "coordinates": [
     152.50998506,
     -26.51373143
    ]
   },
   "properties": {
    "name": "1083 BELLA CREEK ROAD LAKE BORUMBA 4570",
    "locID": "LOC000035772984",
    "tech": "SATELLITE",
    "upgrade": "NULL_NA",
    "gnaf_pid": "GAQLD161426305",
    "tech_change_status": "Not Planned"
   }
  },
  {
   "type": "Feature",
   "geometry": {
    "type": "Point",
    "coordinates": [
     152.5833615,
     -26.50650397
    ]
   },
   "properties": {
    "name": "1484 YABBA CREEK ROAD LAKE BORUMBA 4570",
    "locID": "LOC000174768267",
    "tech": "SATELLITE",
    "upgrade": "NULL_NA",
    "gnaf_pid": "GAQLD161464702",
    "tech_change_status": "Not Planned"
   }
  }
 ]
}