{
 "type": "FeatureCollection",
 "generated": "2024-01-07T19:18:30.601534",
 "suburb": "LAKE MONDURAN",
 "features": [
  {
   "type": "Feature",
   "geometry": {
    "type": "Point",
    "coordinates": [
     151.81442235,
     -24.81843717
    ]
   },
   "properties": {
    "name": "38132 BRUCE HIGHWAY LAKE MONDURAN 4671",
    "locID": "ChIJgxjfKmFE6msRXMm680_0C9c",
    "tech": "SATELLITE",
    "upgrade": "UNKNOWN",
    "gnaf_pid": "GAQLD155478906"
   }
  },
  {
   "type": "Feature",
   "geometry": {
    "type": "Point",
    "coordinates": [
     151.75087427,
     -24.88208043
    ]
   },
   "properties": {
    "name": "38972 BRUCE HIGHWAY LAKE MONDURAN 4671",
    "locID": "ChIJdbcg0ONc6msRP-qfBQylBDg",
    "tech": "SATELLITE",
    "upgrade": "UNKNOWN",
    "gnaf_pid": "GAQLD163055482"
   }
  },
  {
   "type": "Feature",
   "geometry": {
    "type": "Point",
    "coordinates": [
     151.75087427,
     -24.88208043
    ]
   },
   "properties": {
    "name": "39040 BRUCE HIGHWAY LAKE MONDURAN 4671",
    "locID": "ChIJdbcg0ONc6msRE2iXV_jIADA",
    "tech": "SATELLITE",
    "upgrade": "UNKNOWN",
    "gnaf_pid": "GAQLD163055483"
   }
  },
  {
   "type": "Feature",
   "geometry": {
    "type": "Point",
    "coordinates": [
     151.75087427,
     -24.88208043
    ]
   },
   "properties": {
    "name": "39329 BRUCE HIGHWAY LAKE MONDURAN 4671",
    "locID": "ChIJl-rsi3tq6msRuqKxHndbbOg",
    "tech": "SATELLITE",
    "upgrade": "UNKNOWN",
    "gnaf_pid": "GAQLD163055484"
   }
  },
  {
   "type": "Feature",
   "geometry": {
    "type": "Point",
    "coordinates": [
     151.82704584,
     -24.86705814
    ]
   },
   "properties": {
    "name": "LOT 46 BRUCE HIGHWAY LAKE MONDURAN 4671",
    "locID": "LOC000185645399",
    "tech": "WIRELESS",
    "upgrade": "NULL_NA",
    "gnaf_pid": "GAQLD163055485"
   }
  },
  {
   "type": "Feature",
   "geometry": {
    "type": "Point",
    "coordinates": [
     151.84982115,
     -24.88672049
    ]
   },
   "properties": {
    "name": "LOT 4 MONDURAN DAM ROAD LAKE MONDURAN 4671",
    "locID": "LOC000116079664",
    "tech": "SATELLITE",
    "upgrade": "NULL_NA",
    "gnaf_pid": "GAQLD720469552"
   }
  }
 ]
}