{
 "type": "FeatureCollection",
 "generated": "2024-07-18T02:57:02.343421",
 "suburb": "LAKE TINAROO",
 "features": [
  {
   "type": "Feature",
   "geometry": {
    "type": "Point",
    "coordinates": [
     145.55381356,
     -17.1813416
    ]
   },
   "properties": {
    "name": "LOT 624 BLACK GULLY ROAD LAKE TINAROO 4872",
    "locID": "LOC000142848024",
    "tech": "WIRELESS",
    "upgrade": "NULL_NA",
    "gnaf_pid": "GAQLD161068806",
    "tech_change_status": "Not Planned",
    "program_type": "Fixed Wireless and Satellite Upgrade Program",
    "target_eligibility_quarter": "NA"
   }
  },
  {
   "type": "Feature",
   "geometry": {
    "type": "Point",
    "coordinates": [
     145.55425269,
     -17.18140456
    ]
   },
   "properties": {
    "name": "LOT 843 BLACK GULLY ROAD LAKE TINAROO 4872",
    "locID": "LOC000142848024",
    "tech": "WIRELESS",
    "upgrade": "NULL_NA",
    "gnaf_pid": "GAQLD161427021",
    "tech_change_status": "Not Planned",
    "program_type": "Fixed Wireless and Satellite Upgrade Program",
    "target_eligibility_quarter": "NA"
   }
  },
  {
   "type": "Feature",
   "geometry": {
    "type": "Point",
    "coordinates": [
     145.61395393,
     -17.20543382
    ]
   },
   "properties": {
    "name": "LOT 16 CHANNEL ROAD LAKE TINAROO 4872",
    "locID": "LOC000147540541",
    "tech": "WIRELESS",
    "upgrade": "NULL_NA",
    "gnaf_pid": "GAQLD161430495",
    "tech_change_status": "Not Planned",
    "program_type": "Fixed Wireless and Satellite Upgrade Program",
    "target_eligibility_quarter": "NA"
   }
  },
  {
   "type": "Feature",
   "geometry": {
    "type": "Point",
    "coordinates": [
     145.5679676,
     -17.18461672
    ]
   },
   "properties": {
    "name": "47 FOSTER ROAD LAKE TINAROO 4872",
    "locID": "LOC000116182545",
    "tech": "WIRELESS",
    "upgrade": "NULL_NA",
    "gnaf_pid": "GAQLD162349524",
    "tech_change_status": "Not Planned",
    "program_type": "Fixed Wireless and Satellite Upgrade Program",
    "target_eligibility_quarter": "NA"
   }
  }
 ]
}