{
 "type": "FeatureCollection",
 "generated": "2024-08-27T20:53:17.646340",
 "suburb": "LANSDOWNE",
 "features": [
  {
   "type": "Feature",
   "geometry": {
    "type": "Point",
    "coordinates": [
     146.26869394,
     -25.1879013
    ]
   },
   "properties": {
    "name": "LOT 4 WARD ROAD LANSDOWNE 4478",
    "locID": "LOC000128034201",
    "tech": "SATELLITE",
    "upgrade": "NULL_NA",
    "gnaf_pid": "GAQLD162611893",
    "tech_change_status": "Not Planned"
   }
  },
  {
   "type": "Feature",
   "geometry": {
    "type": "Point",
    "coordinates": [
     146.15048945,
     -25.16796347
    ]
   },
   "properties": {
    "name": "LOT 8 WARD ROAD LANSDOWNE 4478",
    "locID": "LOC000128034433",
    "tech": "SATELLITE",
    "upgrade": "NULL_NA",
    "gnaf_pid": "GAQLD162611894",
    "tech_change_status": "Not Planned"
   }
  },
  {
   "type": "Feature",
   "geometry": {
    "type": "Point",
    "coordinates": [
     146.09895281,
     -25.09135086
    ]
   },
   "properties": {
    "name": "3418 WARD ROAD LANSDOWNE 4478",
    "locID": "LOC000111609489",
    "tech": "SATELLITE",
    "upgrade": "NULL_NA",
    "gnaf_pid": "GAQLD163224703",
    "tech_change_status": "Not Planned"
   }
  },
  {
   "type": "Feature",
   "geometry": {
    "type": "Point",
    "coordinates": [
     146.11185119,
     -25.1585642
    ]
   },
   "properties": {
    "name": "3982 WARD ROAD LANSDOWNE 4478",
    "locID": "LOC000128034201",
    "tech": "SATELLITE",
    "upgrade": "NULL_NA",
    "gnaf_pid": "GAQLD163224704",
    "tech_change_status": "Not Planned"
   }
  },
  {
   "type": "Feature",
   "geometry": {
    "type": "Point",
    "coordinates": [
     146.21923774,
     -25.23382909
    ]
   },
   "properties": {
    "name": "4147 WARD ROAD LANSDOWNE 4478",
    "locID": "LOC000128034217",
    "tech": "SATELLITE",
    "upgrade": "NULL_NA",
    "gnaf_pid": "GAQLD163224705",
    "tech_change_status": "Not Planned"
   }
  },
  {
   "type": "Feature",
   "geometry": {
    "type": "Point",
    "coordinates": [
     145.99827168,
     -25.20514008
    ]
   },
   "properties": {
    "name": "1311 WOOLGA ROAD LANSDOWNE 4478",
    "locID": "LOC000110229306",
    "tech": "SATELLITE",
    "upgrade": "NULL_NA",
    "gnaf_pid": "GAQLD163224965",
    "tech_change_status": "Not Planned"
   }
  },
  {
   "type": "Feature",
   "geometry": {
    "type": "Point",
    "coordinates": [
     146.11365968,
     -25.20559935
    ]
   },
   "properties": {
    "name": "200 WOOLGA ROAD LANSDOWNE 4478",
    "locID": "LOC000075975641",
    "tech": "SATELLITE",
    "upgrade": "NULL_NA",
    "gnaf_pid": "GAQLD163300445",
    "tech_change_status": "Not Planned"
   }
  },
  {
   "type": "Feature",
   "geometry": {
    "type": "Point",
    "coordinates": [
     146.27113615,
     -25.11403002
    ]
   },
   "properties": {
    "name": "1975 WARD ROAD LANSDOWNE 4478",
    "locID": "LOC000160727395",
    "tech": "SATELLITE",
    "upgrade": "NULL_NA",
    "gnaf_pid": "GAQLD163321264",
    "tech_change_status": "Not Planned"
   }
  },
  {
   "type": "Feature",
   "geometry": {
    "type": "Point",
    "coordinates": [
     146.20168304,
     -25.18173864
    ]
   },
   "properties": {
    "name": "LOT 3 WARD ROAD LANSDOWNE 4478",
    "locID": "LOC000111609489",
    "tech": "SATELLITE",
    "upgrade": "NULL_NA",
    "gnaf_pid": "GAQLD425134561",
    "tech_change_status": "Not Planned"
   }
  },
  {
   "type": "Feature",
   "geometry": {
    "type": "Point",
    "coordinates": [
     146.03925004,
     -25.14276268
    ]
   },
   "properties": {
    "name": "LOT 1 WOOLGA ROAD LANSDOWNE 4478",
    "locID": "LOC000110229306",
    "tech": "SATELLITE",
    "upgrade": "NULL_NA",
    "gnaf_pid": "GAQLD425135159",
    "tech_change_status": "Not Planned"
   }
  },
  {
   "type": "Feature",
   "geometry": {
    "type": "Point",
    "coordinates": [
     146.01989814,
     -25.17775809
    ]
   },
   "properties": {
    "name": "LOT 2 WOOLGA ROAD LANSDOWNE 4478",
    "locID": "LOC000075975641",
    "tech": "SATELLITE",
    "upgrade": "NULL_NA",
    "gnaf_pid": "GAQLD425135160",
    "tech_change_status": "Not Planned"
   }
  },
  {
   "type": "Feature",
   "geometry": {
    "type": "Point",
    "coordinates": [
     146.1911646,
     -25.14587295
    ]
   },
   "properties": {
    "name": "1 WARD ROAD LANSDOWNE 4478",
    "locID": "LOC000161295620",
    "tech": "SATELLITE",
    "upgrade": "NULL_NA",
    "gnaf_pid": "GAQLD425702262",
    "tech_change_status": "Not Planned"
   }
  }
 ]
}