{
 "type": "FeatureCollection",
 "generated": "2024-05-16T21:47:43.886314",
 "suburb": "LESLIE",
 "features": [
  {
   "type": "Feature",
   "geometry": {
    "type": "Point",
    "coordinates": [
     151.89881901,
     -28.16460473
    ]
   },
   "properties": {
    "name": "928 SANDY CREEK ROAD LESLIE 4370",
    "locID": "LOC000090006498",
    "tech": "WIRELESS",
    "upgrade": "NULL_NA",
    "gnaf_pid": "GAQLD158190723"
   }
  },
  {
   "type": "Feature",
   "geometry": {
    "type": "Point",
    "coordinates": [
     151.90521585,
     -28.16450124
    ]
   },
   "properties": {
    "name": "834 SANDY CREEK ROAD LESLIE 4370",
    "locID": "LOC000105670976",
    "tech": "WIRELESS",
    "upgrade": "NULL_NA",
    "gnaf_pid": "GAQLD160686144"
   }
  },
  {
   "type": "Feature",
   "geometry": {
    "type": "Point",
    "coordinates": [
     151.89710136,
     -28.17254044
    ]
   },
   "properties": {
    "name": "865 SANDY CREEK ROAD LESLIE 4370",
    "locID": "LOC000127863271",
    "tech": "WIRELESS",
    "upgrade": "NULL_NA",
    "gnaf_pid": "GAQLD161456770"
   }
  },
  {
   "type": "Feature",
   "geometry": {
    "type": "Point",
    "coordinates": [
     151.93694758,
     -28.17484663
    ]
   },
   "properties": {
    "name": "25 SERISIER ROAD LESLIE 4370",
    "locID": "LOC000056755109",
    "tech": "WIRELESS",
    "upgrade": "NULL_NA",
    "gnaf_pid": "GAQLD161457388"
   }
  },
  {
   "type": "Feature",
   "geometry": {
    "type": "Point",
    "coordinates": [
     151.91084663,
     -28.16751616
    ]
   },
   "properties": {
    "name": "611 SANDY CREEK ROAD LESLIE 4370",
    "locID": "LOC000127896861",
    "tech": "WIRELESS",
    "upgrade": "NULL_NA",
    "gnaf_pid": "GAQLD161965742"
   }
  },
  {
   "type": "Feature",
   "geometry": {
    "type": "Point",
    "coordinates": [
     151.90315224,
     -28.1644461
    ]
   },
   "properties": {
    "name": "862 SANDY CREEK ROAD LESLIE 4370",
    "locID": "LOC000092627919",
    "tech": "WIRELESS",
    "upgrade": "NULL_NA",
    "gnaf_pid": "GAQLD161965743"
   }
  },
  {
   "type": "Feature",
   "geometry": {
    "type": "Point",
    "coordinates": [
     151.90253044,
     -28.17288743
    ]
   },
   "properties": {
    "name": "LOT 2 SANDY CREEK ROAD LESLIE 4370",
    "locID": "LOC000105670976",
    "tech": "WIRELESS",
    "upgrade": "NULL_NA",
    "gnaf_pid": "GAQLD162964205"
   }
  },
  {
   "type": "Feature",
   "geometry": {
    "type": "Point",
    "coordinates": [
     151.89710136,
     -28.17254044
    ]
   },
   "properties": {
    "name": "UNIT 1, 865 SANDY CREEK ROAD LESLIE 4370",
    "locID": "LOC000127863263",
    "tech": "WIRELESS",
    "upgrade": "NULL_NA",
    "gnaf_pid": "GAQLD425052048"
   }
  },
  {
   "type": "Feature",
   "geometry": {
    "type": "Point",
    "coordinates": [
     151.89710136,
     -28.17254044
    ]
   },
   "properties": {
    "name": "UNIT 2, 865 SANDY CREEK ROAD LESLIE 4370",
    "locID": "LOC000127863271",
    "tech": "WIRELESS",
    "upgrade": "NULL_NA",
    "gnaf_pid": "GAQLD425052049"
   }
  },
  {
   "type": "Feature",
   "geometry": {
    "type": "Point",
    "coordinates": [
     151.90746345,
     -28.16531736
    ]
   },
   "properties": {
    "name": "LOT 61 SANDY CREEK ROAD LESLIE 4370",
    "locID": "LOC000127896861",
    "tech": "WIRELESS",
    "upgrade": "NULL_NA",
    "gnaf_pid": "GAQLD719450633"
   }
  }
 ]
}