{
 "type": "FeatureCollection",
 "generated": "2024-08-08T10:56:06.180016",
 "suburb": "MERRYVALE",
 "features": [
  {
   "type": "Feature",
   "geometry": {
    "type": "Point",
    "coordinates": [
     152.48545359,
     -27.80438084
    ]
   },
   "properties": {
    "name": "757 GREYS PLAINS ROAD MERRYVALE 4340",
    "locID": "LOC000063289502",
    "tech": "SATELLITE",
    "upgrade": "NULL_NA",
    "gnaf_pid": "GAQLD160706509",
    "tech_change_status": "Not Planned"
   }
  },
  {
   "type": "Feature",
   "geometry": {
    "type": "Point",
    "coordinates": [
     152.46995047,
     -27.79989491
    ]
   },
   "properties": {
    "name": "443 GREYS PLAINS ROAD MERRYVALE 4340",
    "locID": "LOC000090201737",
    "tech": "SATELLITE",
    "upgrade": "NULL_NA",
    "gnaf_pid": "GAQLD160713234",
    "tech_change_status": "Not Planned"
   }
  },
  {
   "type": "Feature",
   "geometry": {
    "type": "Point",
    "coordinates": [
     152.47446737,
     -27.80121084
    ]
   },
   "properties": {
    "name": "LOT 3 GREYS PLAINS ROAD MERRYVALE 4340",
    "locID": "LOC100078853279",
    "tech": "SATELLITE",
    "upgrade": "NULL_NA",
    "gnaf_pid": "GAQLD161169035",
    "tech_change_status": "Not Planned"
   }
  },
  {
   "type": "Feature",
   "geometry": {
    "type": "Point",
    "coordinates": [
     152.50256439,
     -27.79115798
    ]
   },
   "properties": {
    "name": "LOT 33 MOUNT WALKER WEST ROAD MERRYVALE 4340",
    "locID": "LOC100078029623",
    "tech": "SATELLITE",
    "upgrade": "NULL_NA",
    "gnaf_pid": "GAQLD161246868",
    "tech_change_status": "Not Planned"
   }
  },
  {
   "type": "Feature",
   "geometry": {
    "type": "Point",
    "coordinates": [
     152.48786221,
     -27.78437892
    ]
   },
   "properties": {
    "name": "114 TRALEE ROAD MERRYVALE 4340",
    "locID": "LOC000097012932",
    "tech": "SATELLITE",
    "upgrade": "NULL_NA",
    "gnaf_pid": "GAQLD161372209",
    "tech_change_status": "Not Planned"
   }
  },
  {
   "type": "Feature",
   "geometry": {
    "type": "Point",
    "coordinates": [
     152.48631389,
     -27.79128695
    ]
   },
   "properties": {
    "name": "191 TRALEE ROAD MERRYVALE 4340",
    "locID": "LOC000049225218",
    "tech": "SATELLITE",
    "upgrade": "NULL_NA",
    "gnaf_pid": "GAQLD161381652",
    "tech_change_status": "Not Planned"
   }
  },
  {
   "type": "Feature",
   "geometry": {
    "type": "Point",
    "coordinates": [
     152.49536477,
     -27.80290484
    ]
   },
   "properties": {
    "name": "1516 MOUNT WALKER WEST ROAD MERRYVALE 4340",
    "locID": "LOC000101439598",
    "tech": "SATELLITE",
    "upgrade": "NULL_NA",
    "gnaf_pid": "GAQLD161921818",
    "tech_change_status": "Not Planned"
   }
  },
  {
   "type": "Feature",
   "geometry": {
    "type": "Point",
    "coordinates": [
     152.49690443,
     -27.79810805
    ]
   },
   "properties": {
    "name": "1442 MOUNT WALKER WEST ROAD MERRYVALE 4340",
    "locID": "LOC000083050599",
    "tech": "SATELLITE",
    "upgrade": "NULL_NA",
    "gnaf_pid": "GAQLD161961291",
    "tech_change_status": "Not Planned"
   }
  },
  {
   "type": "Feature",
   "geometry": {
    "type": "Point",
    "coordinates": [
     152.49351048,
     -27.78331957
    ]
   },
   "properties": {
    "name": "90 TRALEE ROAD MERRYVALE 4340",
    "locID": "LOC000097012932",
    "tech": "SATELLITE",
    "upgrade": "NULL_NA",
    "gnaf_pid": "GAQLD162324416",
    "tech_change_status": "Not Planned"
   }
  },
  {
   "type": "Feature",
   "geometry": {
    "type": "Point",
    "coordinates": [
     152.46716384,
     -27.79748246
    ]
   },
   "properties": {
    "name": "369 GREYS PLAINS ROAD MERRYVALE 4340",
    "locID": "LOC000127660179",
    "tech": "SATELLITE",
    "upgrade": "NULL_NA",
    "gnaf_pid": "GAQLD424937403",
    "tech_change_status": "Not Planned"
   }
  },
  {
   "type": "Feature",
   "geometry": {
    "type": "Point",
    "coordinates": [
     152.50156622,
     -27.79470421
    ]
   },
   "properties": {
    "name": "1414 MOUNT WALKER WEST ROAD MERRYVALE 4340",
    "locID": "LOC100071922406",
    "tech": "SATELLITE",
    "upgrade": "NULL_NA",
    "gnaf_pid": "GAQLD719848796",
    "tech_change_status": "Not Planned"
   }
  },
  {
   "type": "Feature",
   "geometry": {
    "type": "Point",
    "coordinates": [
     152.49485068,
     -27.80833505
    ]
   },
   "properties": {
    "name": "1558 MOUNT WALKER WEST ROAD MERRYVALE 4340",
    "locID": "LOC100071922508",
    "tech": "SATELLITE",
    "upgrade": "NULL_NA",
    "gnaf_pid": "GAQLD719954905",
    "tech_change_status": "Not Planned"
   }
  },
  {
   "type": "Feature",
   "geometry": {
    "type": "Point",
    "coordinates": [
     152.47745687,
     -27.79901322
    ]
   },
   "properties": {
    "name": "531 GREYS PLAINS ROAD MERRYVALE 4340",
    "locID": "LOC100078853279",
    "tech": "SATELLITE",
    "upgrade": "NULL_NA",
    "gnaf_pid": "GAQLD720031741",
    "tech_change_status": "Not Planned"
   }
  }
 ]
}