{
 "type": "FeatureCollection",
 "generated": "2023-07-15T10:13:30.293270",
 "suburb": "MURWEH",
 "features": [
  {
   "type": "Feature",
   "geometry": {
    "type": "Point",
    "coordinates": [
     146.03555269,
     -26.96445796
    ]
   },
   "properties": {
    "name": "25223 MITCHELL HIGHWAY MURWEH 4470",
    "locID": "ChIJ86xuBbCEsmsRcd90aTTW3Vo",
    "tech": "SATELLITE",
    "upgrade": "UNKNOWN",
    "gnaf_pid": "GAQLD162848378"
   }
  },
  {
   "type": "Feature",
   "geometry": {
    "type": "Point",
    "coordinates": [
     145.9712377,
     -26.95902029
    ]
   },
   "properties": {
    "name": "99 MURWEH ROAD MURWEH 4470",
    "locID": "ChIJbYJZaHicsmsRPzHwTN3p2Q8",
    "tech": "SATELLITE",
    "upgrade": "UNKNOWN",
    "gnaf_pid": "GAQLD162928352"
   }
  },
  {
   "type": "Feature",
   "geometry": {
    "type": "Point",
    "coordinates": [
     145.86174444,
     -26.91929773
    ]
   },
   "properties": {
    "name": "1901 GUESTLING ROAD MURWEH 4470",
    "locID": "ChIJGWe17rCYsmsRdAGAtrNUmBU",
    "tech": "SATELLITE",
    "upgrade": "UNKNOWN",
    "gnaf_pid": "GAQLD720329397"
   }
  },
  {
   "type": "Feature",
   "geometry": {
    "type": "Point",
    "coordinates": [
     145.86174444,
     -26.91929773
    ]
   },
   "properties": {
    "name": "2060 GUESTLING ROAD MURWEH 4470",
    "locID": "LOC000142978330",
    "tech": "SATELLITE",
    "upgrade": "NULL_NA",
    "gnaf_pid": "GAQLD720331266"
   }
  },
  {
   "type": "Feature",
   "geometry": {
    "type": "Point",
    "coordinates": [
     145.86174444,
     -26.91929773
    ]
   },
   "properties": {
    "name": "1500 GUESTLING ROAD MURWEH 4470",
    "locID": "ChIJGWe17rCYsmsRMZHI8toek2c",
    "tech": "SATELLITE",
    "upgrade": "UNKNOWN",
    "gnaf_pid": "GAQLD720557318"
   }
  }
 ]
}