{
 "type": "FeatureCollection",
 "generated": "2024-03-16T23:37:30.537748",
 "suburb": "MURWEH",
 "features": [
  {
   "type": "Feature",
   "geometry": {
    "type": "Point",
    "coordinates": [
     145.86174444,
     -26.91929773
    ]
   },
   "properties": {
    "name": "2060 GUESTLING ROAD MURWEH 4470",
    "locID": "LOC000142978330",
    "tech": "SATELLITE",
    "upgrade": "NULL_NA",
    "gnaf_pid": "GAQLD720331266"
   }
  }
 ]
}