{
 "type": "FeatureCollection",
 "generated": "2024-04-28T02:50:53.955208",
 "suburb": "NO 5 BRANCH",
 "features": [
  {
   "type": "Feature",
   "geometry": {
    "type": "Point",
    "coordinates": [
     146.00028383,
     -17.7247458
    ]
   },
   "properties": {
    "name": "15 NUMBER FIVE BRANCH ROAD NO 5 BRANCH 4856",
    "locID": "LOC100077999588",
    "tech": "WIRELESS",
    "upgrade": "NULL_NA",
    "gnaf_pid": "GAQLD162659632"
   }
  },
  {
   "type": "Feature",
   "geometry": {
    "type": "Point",
    "coordinates": [
     146.00990274,
     -17.72102582
    ]
   },
   "properties": {
    "name": "LOT 1 NUMBER FIVE BRANCH ROAD NO 5 BRANCH 4856",
    "locID": "LOC100077999588",
    "tech": "WIRELESS",
    "upgrade": "NULL_NA",
    "gnaf_pid": "GAQLD162659633"
   }
  },
  {
   "type": "Feature",
   "geometry": {
    "type": "Point",
    "coordinates": [
     146.017437,
     -17.72243711
    ]
   },
   "properties": {
    "name": "LOT 2 NUMBER FIVE BRANCH ROAD NO 5 BRANCH 4856",
    "locID": "LOC000129888478",
    "tech": "WIRELESS",
    "upgrade": "NULL_NA",
    "gnaf_pid": "GAQLD162659635"
   }
  },
  {
   "type": "Feature",
   "geometry": {
    "type": "Point",
    "coordinates": [
     146.00196625,
     -17.73086913
    ]
   },
   "properties": {
    "name": "LOT 4 NUMBER FIVE BRANCH ROAD NO 5 BRANCH 4856",
    "locID": "LOC000129888478",
    "tech": "WIRELESS",
    "upgrade": "NULL_NA",
    "gnaf_pid": "GAQLD162659637"
   }
  },
  {
   "type": "Feature",
   "geometry": {
    "type": "Point",
    "coordinates": [
     146.00437578,
     -17.73099613
    ]
   },
   "properties": {
    "name": "LOT 5 NUMBER FIVE BRANCH ROAD NO 5 BRANCH 4856",
    "locID": "LOC000129888478",
    "tech": "WIRELESS",
    "upgrade": "NULL_NA",
    "gnaf_pid": "GAQLD162659638"
   }
  },
  {
   "type": "Feature",
   "geometry": {
    "type": "Point",
    "coordinates": [
     146.0050815,
     -17.72521675
    ]
   },
   "properties": {
    "name": "61 NUMBER FIVE BRANCH ROAD NO 5 BRANCH 4856",
    "locID": "LOC100077999590",
    "tech": "WIRELESS",
    "upgrade": "NULL_NA",
    "gnaf_pid": "GAQLD162659639"
   }
  },
  {
   "type": "Feature",
   "geometry": {
    "type": "Point",
    "coordinates": [
     146.01188056,
     -17.72787219
    ]
   },
   "properties": {
    "name": "LOT 1 BRANCH ROAD NO 5 BRANCH 4856",
    "locID": "LOC100077999588",
    "tech": "WIRELESS",
    "upgrade": "NULL_NA",
    "gnaf_pid": "GAQLD424932888"
   }
  }
 ]
}