{
 "type": "FeatureCollection",
 "generated": "2024-01-14T05:53:25.562766",
 "suburb": "SAVANNAH",
 "features": [
  {
   "type": "Feature",
   "geometry": {
    "type": "Point",
    "coordinates": [
     142.075,
     -19.3075
    ]
   },
   "properties": {
    "name": "LOT 258 TRENTON ROAD SAVANNAH 4816",
    "locID": "LOC000143224590",
    "tech": "SATELLITE",
    "upgrade": "NULL_NA",
    "gnaf_pid": "GAQLD720670728"
   }
  },
  {
   "type": "Feature",
   "geometry": {
    "type": "Point",
    "coordinates": [
     141.836356,
     -19.231031
    ]
   },
   "properties": {
    "name": "LOT 2254 TRENTON ROAD SAVANNAH 4816",
    "locID": "LOC000143224590",
    "tech": "SATELLITE",
    "upgrade": "NULL_NA",
    "gnaf_pid": "GAQLD720672365"
   }
  }
 ]
}