{
 "type": "FeatureCollection",
 "generated": "2023-11-07T23:06:38.307756",
 "suburb": "SILVERBARK RIDGE",
 "features": [
  {
   "type": "Feature",
   "geometry": {
    "type": "Point",
    "coordinates": [
     152.91425771,
     -27.78761576
    ]
   },
   "properties": {
    "name": "LOT 5 EVERDELL ROAD SILVERBARK RIDGE 4124",
    "locID": "EiZFdmVyZGVsbCBSZCwgTHlvbnMgUUxEIDQxMjQsIEF1c3RyYWxpYSIuKiwKFAoSCf32AgIPNJFrESR_j73yxKXpEhQKEgnZyuQygzSRaxFgj97zWqMCBQ",
    "tech": "SATELLITE",
    "upgrade": "UNKNOWN",
    "gnaf_pid": "GAQLD719070595"
   }
  },
  {
   "type": "Feature",
   "geometry": {
    "type": "Point",
    "coordinates": [
     152.93985389,
     -27.78493824
    ]
   },
   "properties": {
    "name": "LOT 2 NEW BEITH ROAD SILVERBARK RIDGE 4124",
    "locID": "LOC000058271946",
    "tech": "FTTN",
    "upgrade": "FTTP_SA",
    "gnaf_pid": "GAQLD719070596",
    "tech_change_status": "Eligible To Order",
    "program_type": "On-Demand N2P SDU/MDU Simple",
    "target_eligibility_quarter": "NA"
   }
  },
  {
   "type": "Feature",
   "geometry": {
    "type": "Point",
    "coordinates": [
     152.91920415,
     -27.78708494
    ]
   },
   "properties": {
    "name": "LOT 988 EVERDELL ROAD SILVERBARK RIDGE 4124",
    "locID": "EiZFdmVyZGVsbCBSZCwgTHlvbnMgUUxEIDQxMjQsIEF1c3RyYWxpYSIuKiwKFAoSCf32AgIPNJFrESR_j73yxKXpEhQKEgnZyuQygzSRaxFgj97zWqMCBQ",
    "tech": "SATELLITE",
    "upgrade": "UNKNOWN",
    "gnaf_pid": "GAQLD719071138"
   }
  },
  {
   "type": "Feature",
   "geometry": {
    "type": "Point",
    "coordinates": [
     152.93101376,
     -27.78208269
    ]
   },
   "properties": {
    "name": "LOT 1 NEW BEITH ROAD SILVERBARK RIDGE 4124",
    "locID": "LOC000024107040",
    "tech": "FTTP",
    "upgrade": "FTTP_NA",
    "gnaf_pid": "GAQLD719071139",
    "tech_change_status": "Previous Tech Disconnected",
    "program_type": "On-Demand N2P SDU/MDU Simple",
    "target_eligibility_quarter": "NA"
   }
  },
  {
   "type": "Feature",
   "geometry": {
    "type": "Point",
    "coordinates": [
     152.91540077,
     -27.79454016
    ]
   },
   "properties": {
    "name": "LOT 9 EVERDELL ROAD SILVERBARK RIDGE 4124",
    "locID": "EiZFdmVyZGVsbCBSZCwgTHlvbnMgUUxEIDQxMjQsIEF1c3RyYWxpYSIuKiwKFAoSCf32AgIPNJFrESR_j73yxKXpEhQKEgnZyuQygzSRaxFgj97zWqMCBQ",
    "tech": "SATELLITE",
    "upgrade": "UNKNOWN",
    "gnaf_pid": "GAQLD719072311"
   }
  }
 ]
}