{
 "type": "FeatureCollection",
 "generated": "2024-07-21T23:51:36.112497",
 "suburb": "SILVERBARK RIDGE",
 "features": [
  {
   "type": "Feature",
   "geometry": {
    "type": "Point",
    "coordinates": [
     152.93985389,
     -27.78493824
    ]
   },
   "properties": {
    "name": "LOT 2 NEW BEITH ROAD SILVERBARK RIDGE 4124",
    "locID": "LOC000058271946",
    "tech": "FTTP",
    "upgrade": "NULL_NA",
    "gnaf_pid": "GAQLD719070596",
    "program_type": "On-Demand N2P SDU/MDU Simple",
    "target_eligibility_quarter": "NA"
   }
  },
  {
   "type": "Feature",
   "geometry": {
    "type": "Point",
    "coordinates": [
     152.93101376,
     -27.78208269
    ]
   },
   "properties": {
    "name": "LOT 1 NEW BEITH ROAD SILVERBARK RIDGE 4124",
    "locID": "LOC000024107040",
    "tech": "FTTP",
    "upgrade": "FTTP_NA",
    "gnaf_pid": "GAQLD719071139",
    "tech_change_status": "Previous Tech Disconnected",
    "program_type": "On-Demand N2P SDU/MDU Simple",
    "target_eligibility_quarter": "NA"
   }
  }
 ]
}