{
 "type": "FeatureCollection",
 "generated": "2024-07-22T02:24:24.181800",
 "suburb": "TARAGOOLA",
 "features": [
  {
   "type": "Feature",
   "geometry": {
    "type": "Point",
    "coordinates": [
     151.23992041,
     -24.11785842
    ]
   },
   "properties": {
    "name": "1295 TARAGOOLA ROAD TARAGOOLA 4680",
    "locID": "LOC000052304593",
    "tech": "SATELLITE",
    "upgrade": "NULL_NA",
    "gnaf_pid": "GAQLD160345771",
    "tech_change_status": "Not Planned"
   }
  },
  {
   "type": "Feature",
   "geometry": {
    "type": "Point",
    "coordinates": [
     151.24990177,
     -24.08319627
    ]
   },
   "properties": {
    "name": "LOT 17 TARAGOOLA ROAD TARAGOOLA 4680",
    "locID": "LOC000128951299",
    "tech": "FTTN",
    "upgrade": "FTTP_SA",
    "gnaf_pid": "GAQLD161325292",
    "tech_change_status": "Eligible To Order",
    "program_type": "On-Demand N2P SDU/MDU Simple",
    "target_eligibility_quarter": "NA"
   }
  },
  {
   "type": "Feature",
   "geometry": {
    "type": "Point",
    "coordinates": [
     151.21906167,
     -24.10090514
    ]
   },
   "properties": {
    "name": "LOT 1 TARAGOOLA ROAD TARAGOOLA 4680",
    "locID": "LOC000052304593",
    "tech": "SATELLITE",
    "upgrade": "NULL_NA",
    "gnaf_pid": "GAQLD161325294",
    "tech_change_status": "Not Planned"
   }
  },
  {
   "type": "Feature",
   "geometry": {
    "type": "Point",
    "coordinates": [
     151.21831053,
     -24.09912616
    ]
   },
   "properties": {
    "name": "LOT 19 TARAGOOLA ROAD TARAGOOLA 4680",
    "locID": "LOC000106042741",
    "tech": "FTTN",
    "upgrade": "FTTP_SA",
    "gnaf_pid": "GAQLD162523621",
    "tech_change_status": "Eligible To Order",
    "program_type": "On-Demand N2P SDU/MDU Simple",
    "target_eligibility_quarter": "NA"
   }
  },
  {
   "type": "Feature",
   "geometry": {
    "type": "Point",
    "coordinates": [
     151.23041869,
     -24.09273684
    ]
   },
   "properties": {
    "name": "24 TARAGOOLA ROAD TARAGOOLA 4680",
    "locID": "LOC000128974118",
    "tech": "FTTN",
    "upgrade": "NULL_NA",
    "gnaf_pid": "GAQLD162548391",
    "tech_change_status": "Not Planned"
   }
  },
  {
   "type": "Feature",
   "geometry": {
    "type": "Point",
    "coordinates": [
     151.23333633,
     -24.0792869
    ]
   },
   "properties": {
    "name": "LOT 91 TARAGOOLA ROAD TARAGOOLA 4680",
    "locID": "LOC000150201312",
    "tech": "SATELLITE",
    "upgrade": "NULL_NA",
    "gnaf_pid": "GAQLD425153236",
    "tech_change_status": "Not Planned"
   }
  },
  {
   "type": "Feature",
   "geometry": {
    "type": "Point",
    "coordinates": [
     151.23041869,
     -24.09273684
    ]
   },
   "properties": {
    "name": "LOT 92 TARAGOOLA ROAD TARAGOOLA 4680",
    "locID": "LOC000150201312",
    "tech": "SATELLITE",
    "upgrade": "NULL_NA",
    "gnaf_pid": "GAQLD425153237",
    "tech_change_status": "Not Planned"
   }
  },
  {
   "type": "Feature",
   "geometry": {
    "type": "Point",
    "coordinates": [
     151.246607,
     -24.06805681
    ]
   },
   "properties": {
    "name": "795 TARAGOOLA ROAD TARAGOOLA 4680",
    "locID": "LOC000150201312",
    "tech": "SATELLITE",
    "upgrade": "NULL_NA",
    "gnaf_pid": "GAQLD425701620",
    "tech_change_status": "Not Planned"
   }
  },
  {
   "type": "Feature",
   "geometry": {
    "type": "Point",
    "coordinates": [
     151.2454958,
     -24.06229984
    ]
   },
   "properties": {
    "name": "LOT 2 TARAGOOLA ROAD TARAGOOLA 4680",
    "locID": "LOC000052304593",
    "tech": "SATELLITE",
    "upgrade": "NULL_NA",
    "gnaf_pid": "GAQLD425754981",
    "tech_change_status": "Not Planned"
   }
  }
 ]
}