{
 "type": "FeatureCollection",
 "generated": "2024-10-08T09:17:06.430856",
 "suburb": "TUEN",
 "features": [
  {
   "type": "Feature",
   "geometry": {
    "type": "Point",
    "coordinates": [
     145.86106394,
     -28.39951905
    ]
   },
   "properties": {
    "name": "1436 JOBS GATE ROAD TUEN 4490",
    "locID": "LOC000128115532",
    "tech": "SATELLITE",
    "upgrade": "NULL_NA",
    "gnaf_pid": "GAQLD162039677",
    "tech_change_status": "Not Planned"
   }
  },
  {
   "type": "Feature",
   "geometry": {
    "type": "Point",
    "coordinates": [
     145.72646194,
     -28.67743935
    ]
   },
   "properties": {
    "name": "938 JOBS GATE ROAD TUEN 4490",
    "locID": "LOC000128143914",
    "tech": "NULL",
    "upgrade": "NULL_NA",
    "gnaf_pid": "GAQLD162039678",
    "tech_change_status": "Not Planned"
   }
  },
  {
   "type": "Feature",
   "geometry": {
    "type": "Point",
    "coordinates": [
     145.66311473,
     -28.49291185
    ]
   },
   "properties": {
    "name": "5789 BARRINGUN ROAD TUEN 4490",
    "locID": "LOC000029886552",
    "tech": "SATELLITE",
    "upgrade": "NULL_NA",
    "gnaf_pid": "GAQLD162240069",
    "tech_change_status": "Not Planned"
   }
  },
  {
   "type": "Feature",
   "geometry": {
    "type": "Point",
    "coordinates": [
     145.79222377,
     -28.50612129
    ]
   },
   "properties": {
    "name": "6460 BARRINGUN ROAD TUEN 4490",
    "locID": "LOC000019951328",
    "tech": "NULL",
    "upgrade": "NULL_NA",
    "gnaf_pid": "GAQLD162240070",
    "tech_change_status": "Not Planned"
   }
  },
  {
   "type": "Feature",
   "geometry": {
    "type": "Point",
    "coordinates": [
     145.78281028,
     -28.64052007
    ]
   },
   "properties": {
    "name": "824 THURULGOONA ROAD TUEN 4490",
    "locID": "LOC000186169816",
    "tech": "NULL",
    "upgrade": "NULL_NA",
    "gnaf_pid": "GAQLD719708137",
    "tech_change_status": "Not Planned"
   }
  },
  {
   "type": "Feature",
   "geometry": {
    "type": "Point",
    "coordinates": [
     145.8485614,
     -28.56159394
    ]
   },
   "properties": {
    "name": "667 THURULGOONA ROAD TUEN 4490",
    "locID": "LOC000025809577",
    "tech": "NULL",
    "upgrade": "NULL_NA",
    "gnaf_pid": "GAQLD719711026",
    "tech_change_status": "Not Planned"
   }
  }
 ]
}