{
 "type": "FeatureCollection",
 "generated": "2023-07-16T14:47:21.425672",
 "suburb": "TUEN",
 "features": [
  {
   "type": "Feature",
   "geometry": {
    "type": "Point",
    "coordinates": [
     145.70618988,
     -28.55160107
    ]
   },
   "properties": {
    "name": "LOT 10 MITCHELL HIGHWAY TUEN 4490",
    "locID": "EiZNaXRjaGVsbCBId3ksIFR1ZW4gUUxEIDQ0OTAsIEF1c3RyYWxpYSIuKiwKFAoSCV06VwR8pKxrEbNIiaCxg4-UEhQKEglXH2idwkKraxFQoyB_8e4ABA",
    "tech": "SATELLITE",
    "upgrade": "UNKNOWN",
    "gnaf_pid": "GAQLD161239531"
   }
  },
  {
   "type": "Feature",
   "geometry": {
    "type": "Point",
    "coordinates": [
     145.78961412,
     -28.40337595
    ]
   },
   "properties": {
    "name": "LOT 2 MITCHELL HIGHWAY TUEN 4490",
    "locID": "ChIJjX5tt6pvrWsRd77F1zZDV-A",
    "tech": "SATELLITE",
    "upgrade": "UNKNOWN",
    "gnaf_pid": "GAQLD161239532"
   }
  },
  {
   "type": "Feature",
   "geometry": {
    "type": "Point",
    "coordinates": [
     145.86106394,
     -28.39951905
    ]
   },
   "properties": {
    "name": "1436 JOBS GATE ROAD TUEN 4490",
    "locID": "LOC000128115532",
    "tech": "SATELLITE",
    "upgrade": "NULL_NA",
    "gnaf_pid": "GAQLD162039677"
   }
  },
  {
   "type": "Feature",
   "geometry": {
    "type": "Point",
    "coordinates": [
     145.72646194,
     -28.67743935
    ]
   },
   "properties": {
    "name": "938 JOBS GATE ROAD TUEN 4490",
    "locID": "LOC000128143914",
    "tech": "SATELLITE",
    "upgrade": "NULL_NA",
    "gnaf_pid": "GAQLD162039678"
   }
  },
  {
   "type": "Feature",
   "geometry": {
    "type": "Point",
    "coordinates": [
     145.66311473,
     -28.49291185
    ]
   },
   "properties": {
    "name": "5789 BARRINGUN ROAD TUEN 4490",
    "locID": "LOC000029886552",
    "tech": "SATELLITE",
    "upgrade": "NULL_NA",
    "gnaf_pid": "GAQLD162240069"
   }
  },
  {
   "type": "Feature",
   "geometry": {
    "type": "Point",
    "coordinates": [
     145.79222377,
     -28.50612129
    ]
   },
   "properties": {
    "name": "6460 BARRINGUN ROAD TUEN 4490",
    "locID": "LOC000019951328",
    "tech": "SATELLITE",
    "upgrade": "NULL_NA",
    "gnaf_pid": "GAQLD162240070"
   }
  },
  {
   "type": "Feature",
   "geometry": {
    "type": "Point",
    "coordinates": [
     145.65584239,
     -28.45248263
    ]
   },
   "properties": {
    "name": "6321 BARRINGUN ROAD TUEN 4490",
    "locID": "ChIJg-A2xu1Pq2sR_OjBlJAgLjw",
    "tech": "SATELLITE",
    "upgrade": "UNKNOWN",
    "gnaf_pid": "GAQLD162341054"
   }
  },
  {
   "type": "Feature",
   "geometry": {
    "type": "Point",
    "coordinates": [
     145.65823281,
     -28.40160632
    ]
   },
   "properties": {
    "name": "7000 BARRINGUN ROAD TUEN 4490",
    "locID": "ChIJTYmETntQq2sRyR2rBsSFOyE",
    "tech": "SATELLITE",
    "upgrade": "UNKNOWN",
    "gnaf_pid": "GAQLD162341055"
   }
  },
  {
   "type": "Feature",
   "geometry": {
    "type": "Point",
    "coordinates": [
     145.88955078,
     -28.36375775
    ]
   },
   "properties": {
    "name": "1702 JOBS GATE ROAD TUEN 4490",
    "locID": "ChIJeYYsYktgq2sR0XCTxmGKw5U",
    "tech": "SATELLITE",
    "upgrade": "UNKNOWN",
    "gnaf_pid": "GAQLD425049416"
   }
  },
  {
   "type": "Feature",
   "geometry": {
    "type": "Point",
    "coordinates": [
     145.78281028,
     -28.64052007
    ]
   },
   "properties": {
    "name": "824 THURULGOONA ROAD TUEN 4490",
    "locID": "LOC000186169816",
    "tech": "SATELLITE",
    "upgrade": "NULL_NA",
    "gnaf_pid": "GAQLD719708137"
   }
  },
  {
   "type": "Feature",
   "geometry": {
    "type": "Point",
    "coordinates": [
     145.8485614,
     -28.56159394
    ]
   },
   "properties": {
    "name": "667 THURULGOONA ROAD TUEN 4490",
    "locID": "LOC000025809577",
    "tech": "SATELLITE",
    "upgrade": "NULL_NA",
    "gnaf_pid": "GAQLD719711026"
   }
  },
  {
   "type": "Feature",
   "geometry": {
    "type": "Point",
    "coordinates": [
     145.72558384,
     -28.61040874
    ]
   },
   "properties": {
    "name": "552 THURULGOONA ROAD TUEN 4490",
    "locID": "ChIJ3YKtXGVHq2sRxJ63b4uLBuo",
    "tech": "SATELLITE",
    "upgrade": "UNKNOWN",
    "gnaf_pid": "GAQLD719712304"
   }
  },
  {
   "type": "Feature",
   "geometry": {
    "type": "Point",
    "coordinates": [
     145.79479594,
     -28.59158986
    ]
   },
   "properties": {
    "name": "2655 THURULGOONA ROAD TUEN 4490",
    "locID": "ChIJOY1RTgRBq2sRboIAjBkrELM",
    "tech": "SATELLITE",
    "upgrade": "UNKNOWN",
    "gnaf_pid": "GAQLD719718829"
   }
  },
  {
   "type": "Feature",
   "geometry": {
    "type": "Point",
    "coordinates": [
     145.79479594,
     -28.59158986
    ]
   },
   "properties": {
    "name": "3661 THURULGOONA ROAD TUEN 4490",
    "locID": "ChIJOY1RTgRBq2sRfx1G13lH_x8",
    "tech": "SATELLITE",
    "upgrade": "UNKNOWN",
    "gnaf_pid": "GAQLD719727711"
   }
  }
 ]
}