{
 "type": "FeatureCollection",
 "generated": "2023-07-16T15:00:32.163732",
 "suburb": "TURRAWULLA",
 "features": [
  {
   "type": "Feature",
   "geometry": {
    "type": "Point",
    "coordinates": [
     148.28523181,
     -21.29361157
    ]
   },
   "properties": {
    "name": "LOT 11 TURRAWULLA ROAD TURRAWULLA 4742",
    "locID": "LOC000172886122",
    "tech": "SATELLITE",
    "upgrade": "NULL_NA",
    "gnaf_pid": "GAQLD163175904"
   }
  },
  {
   "type": "Feature",
   "geometry": {
    "type": "Point",
    "coordinates": [
     148.15317393,
     -21.05917988
    ]
   },
   "properties": {
    "name": "LOT 3357 TURRAWULLA ROAD TURRAWULLA 4742",
    "locID": "EjIzMzU3IFR1cnJhd3VsbGEgUmQsIEhhaWwgQ3JlZWsgUUxEIDQ3NDIsIEF1c3RyYWxpYSIxEi8KFAoSCcOJ_UNoY9prEYOdf5b1HToNEJ0aKhQKEgkzYH5nxZ7QaxEPC7SL0msIdg",
    "tech": "SATELLITE",
    "upgrade": "UNKNOWN",
    "gnaf_pid": "GAQLD425799436"
   }
  },
  {
   "type": "Feature",
   "geometry": {
    "type": "Point",
    "coordinates": [
     148.24719352,
     -21.27453715
    ]
   },
   "properties": {
    "name": "5535 TURRAWULLA ROAD TURRAWULLA 4742",
    "locID": "EjI1NTM1IFR1cnJhd3VsbGEgUmQsIEhhaWwgQ3JlZWsgUUxEIDQ3NDIsIEF1c3RyYWxpYSIxEi8KFAoSCcOJ_UNoY9prEYOdf5b1HToNEJ8rKhQKEgkzYH5nxZ7QaxEPC7SL0msIdg",
    "tech": "SATELLITE",
    "upgrade": "UNKNOWN",
    "gnaf_pid": "GAQLD719445629"
   }
  }
 ]
}