{
 "type": "FeatureCollection",
 "generated": "2024-10-08T09:31:18.292518",
 "suburb": "TURRAWULLA",
 "features": [
  {
   "type": "Feature",
   "geometry": {
    "type": "Point",
    "coordinates": [
     148.28523181,
     -21.29361157
    ]
   },
   "properties": {
    "name": "LOT 11 TURRAWULLA ROAD TURRAWULLA 4742",
    "locID": "LOC000172886122",
    "tech": "SATELLITE",
    "upgrade": "NULL_NA",
    "gnaf_pid": "GAQLD163175904",
    "tech_change_status": "Not Planned"
   }
  }
 ]
}