{
 "type": "FeatureCollection",
 "generated": "2023-10-20T15:24:31.650668",
 "suburb": "WAINUI",
 "features": [
  {
   "type": "Feature",
   "geometry": {
    "type": "Point",
    "coordinates": [
     151.4561145,
     -27.325385
    ]
   },
   "properties": {
    "name": "LOT 107 WATER STREET WAINUI 4404",
    "locID": "EiRXYXRlciBTdCwgV2FpbnVpIFFMRCA0NDA0LCBBdXN0cmFsaWEiLiosChQKEglTjfMHEhmWaxFzFSAXw34mrRIUChIJs3wfXwkZlmsR8Lsgf_HuAAQ",
    "tech": "SATELLITE",
    "upgrade": "UNKNOWN",
    "gnaf_pid": "GAQLD155062812"
   }
  },
  {
   "type": "Feature",
   "geometry": {
    "type": "Point",
    "coordinates": [
     151.45646212,
     -27.32557406
    ]
   },
   "properties": {
    "name": "LOT 108 WATER STREET WAINUI 4404",
    "locID": "EiRXYXRlciBTdCwgV2FpbnVpIFFMRCA0NDA0LCBBdXN0cmFsaWEiLiosChQKEglTjfMHEhmWaxFzFSAXw34mrRIUChIJs3wfXwkZlmsR8Lsgf_HuAAQ",
    "tech": "SATELLITE",
    "upgrade": "UNKNOWN",
    "gnaf_pid": "GAQLD161347626"
   }
  },
  {
   "type": "Feature",
   "geometry": {
    "type": "Point",
    "coordinates": [
     151.45300749,
     -27.31943846
    ]
   },
   "properties": {
    "name": "LOT 76 BOWENVILLE RESERVE ROAD WAINUI 4404",
    "locID": "EjFCb3dlbnZpbGxlIFJlc2VydmUgUmQsIFdhaW51aSBRTEQgNDQwNCwgQXVzdHJhbGlhIi4qLAoUChIJvxRvlhIZlmsR6dX6e7YxYP4SFAoSCbN8H18JGZZrEfC7IH_x7gAE",
    "tech": "SATELLITE",
    "upgrade": "UNKNOWN",
    "gnaf_pid": "GAQLD163303097"
   }
  },
  {
   "type": "Feature",
   "geometry": {
    "type": "Point",
    "coordinates": [
     151.44166114,
     -27.32529765
    ]
   },
   "properties": {
    "name": "15507 WARREGO HIGHWAY WAINUI 4404",
    "locID": "ChIJKTQOvjwZlmsRoFmCDMs3FhE",
    "tech": "SATELLITE",
    "upgrade": "UNKNOWN",
    "gnaf_pid": "GAQLD163321348"
   }
  },
  {
   "type": "Feature",
   "geometry": {
    "type": "Point",
    "coordinates": [
     151.44659319,
     -27.31450605
    ]
   },
   "properties": {
    "name": "LOT 62 WAINUI ROAD WAINUI 4404",
    "locID": "LOC000188791309",
    "tech": "SATELLITE",
    "upgrade": "NULL_NA",
    "gnaf_pid": "GAQLD424936351"
   }
  },
  {
   "type": "Feature",
   "geometry": {
    "type": "Point",
    "coordinates": [
     151.44737688,
     -27.33383731
    ]
   },
   "properties": {
    "name": "15471 WARREGO HIGHWAY WAINUI 4404",
    "locID": "ChIJNauKPBkZlmsRHwngPCtgYQA",
    "tech": "WIRELESS",
    "upgrade": "UNKNOWN",
    "gnaf_pid": "GAQLD719328039"
   }
  },
  {
   "type": "Feature",
   "geometry": {
    "type": "Point",
    "coordinates": [
     151.45018791,
     -27.33152104
    ]
   },
   "properties": {
    "name": "14947 WARREGO HIGHWAY WAINUI 4404",
    "locID": "ChIJNauKPBkZlmsRuBwfw7zMcLM",
    "tech": "WIRELESS",
    "upgrade": "UNKNOWN",
    "gnaf_pid": "GAQLD719330053"
   }
  },
  {
   "type": "Feature",
   "geometry": {
    "type": "Point",
    "coordinates": [
     151.44737688,
     -27.33383731
    ]
   },
   "properties": {
    "name": "15252 WARREGO HIGHWAY WAINUI 4404",
    "locID": "ChIJNauKPBkZlmsRpS9ZX9U-K3c",
    "tech": "WIRELESS",
    "upgrade": "UNKNOWN",
    "gnaf_pid": "GAQLD719330311"
   }
  },
  {
   "type": "Feature",
   "geometry": {
    "type": "Point",
    "coordinates": [
     151.45018791,
     -27.33152104
    ]
   },
   "properties": {
    "name": "15297 WARREGO HIGHWAY WAINUI 4404",
    "locID": "ChIJNauKPBkZlmsR-kjWGBiNff4",
    "tech": "WIRELESS",
    "upgrade": "UNKNOWN",
    "gnaf_pid": "GAQLD719337351"
   }
  },
  {
   "type": "Feature",
   "geometry": {
    "type": "Point",
    "coordinates": [
     151.47891972,
     -27.33976123
    ]
   },
   "properties": {
    "name": "15305 WARREGO HIGHWAY WAINUI 4404",
    "locID": "ChIJNauKPBkZlmsRyYC84UYM9oM",
    "tech": "WIRELESS",
    "upgrade": "UNKNOWN",
    "gnaf_pid": "GAQLD719338632"
   }
  }
 ]
}