{
 "type": "FeatureCollection",
 "generated": "2024-02-12T16:25:57.207011",
 "suburb": "WAINUI",
 "features": [
  {
   "type": "Feature",
   "geometry": {
    "type": "Point",
    "coordinates": [
     151.44659319,
     -27.31450605
    ]
   },
   "properties": {
    "name": "LOT 62 WAINUI ROAD WAINUI 4404",
    "locID": "LOC000188791309",
    "tech": "SATELLITE",
    "upgrade": "NULL_NA",
    "gnaf_pid": "GAQLD424936351"
   }
  }
 ]
}