{
 "type": "FeatureCollection",
 "generated": "2024-07-22T05:15:44.450435",
 "suburb": "WAINUI",
 "features": [
  {
   "type": "Feature",
   "geometry": {
    "type": "Point",
    "coordinates": [
     151.44659319,
     -27.31450605
    ]
   },
   "properties": {
    "name": "LOT 62 WAINUI ROAD WAINUI 4404",
    "locID": "LOC000188791309",
    "tech": "WIRELESS",
    "upgrade": "NULL_NA",
    "gnaf_pid": "GAQLD424936351",
    "tech_change_status": "Not Planned",
    "program_type": "Fixed Wireless and Satellite Upgrade Program",
    "target_eligibility_quarter": "NA"
   }
  }
 ]
}