{
 "type": "FeatureCollection",
 "generated": "2024-06-13T20:55:10.265338",
 "suburb": "WALLIEBUM",
 "features": [
  {
   "type": "Feature",
   "geometry": {
    "type": "Point",
    "coordinates": [
     152.74419126,
     -25.45066478
    ]
   },
   "properties": {
    "name": "LOT 47 MARYBOROUGH - HERVEY BAY ROAD WALLIEBUM 4655",
    "locID": "LOC000179803907",
    "tech": "FTTP",
    "upgrade": "NULL_NA",
    "gnaf_pid": "GAQLD163169411"
   }
  },
  {
   "type": "Feature",
   "geometry": {
    "type": "Point",
    "coordinates": [
     152.67456773,
     -25.40472249
    ]
   },
   "properties": {
    "name": "LOT 32 CHURCHILL MINE ROAD WALLIEBUM 4655",
    "locID": "LOC000095560718",
    "tech": "WIRELESS",
    "upgrade": "NULL_NA",
    "gnaf_pid": "GAQLD425747665"
   }
  },
  {
   "type": "Feature",
   "geometry": {
    "type": "Point",
    "coordinates": [
     152.72535263,
     -25.37269735
    ]
   },
   "properties": {
    "name": "LOT 33 CHURCHILL MINE ROAD WALLIEBUM 4655",
    "locID": "LOC000015345852",
    "tech": "WIRELESS",
    "upgrade": "NULL_NA",
    "gnaf_pid": "GAQLD720590809"
   }
  }
 ]
}