{
 "type": "FeatureCollection",
 "generated": "2023-10-20T15:39:03.402662",
 "suburb": "WARENDA",
 "features": [
  {
   "type": "Feature",
   "geometry": {
    "type": "Point",
    "coordinates": [
     140.06694642,
     -22.57172332
    ]
   },
   "properties": {
    "name": "LOT 5210 SELWYN ROAD WARENDA 4829",
    "locID": "LOC000185408983",
    "tech": "SATELLITE",
    "upgrade": "NULL_NA",
    "gnaf_pid": "GAQLD719445146"
   }
  },
  {
   "type": "Feature",
   "geometry": {
    "type": "Point",
    "coordinates": [
     140.11207343,
     -22.43618318
    ]
   },
   "properties": {
    "name": "LOT 4747 SELWYN ROAD WARENDA 4829",
    "locID": "LOC000185408983",
    "tech": "SATELLITE",
    "upgrade": "NULL_NA",
    "gnaf_pid": "GAQLD719446846"
   }
  }
 ]
}