{
 "type": "FeatureCollection",
 "generated": "2023-10-20T18:19:58.383860",
 "suburb": "WOOROONOORAN",
 "features": [
  {
   "type": "Feature",
   "geometry": {
    "type": "Point",
    "coordinates": [
     145.79812576,
     -17.61147681
    ]
   },
   "properties": {
    "name": "LOT 99 PALMERSTON HIGHWAY WOOROONOORAN 4860",
    "locID": "EjBQYWxtZXJzdG9uIEh3eSwgV29vcm9vbm9vcmFuIFFMRCA0ODYwLCBBdXN0cmFsaWEiLiosChQKEgkRU7B7KbF4aRFWNIgCbzpi4RIUChIJT1yJsrzAeGkRummI4JXev6k",
    "tech": "SATELLITE",
    "upgrade": "UNKNOWN",
    "gnaf_pid": "GAQLD720727473"
   }
  },
  {
   "type": "Feature",
   "geometry": {
    "type": "Point",
    "coordinates": [
     145.85838393,
     -17.44350022
    ]
   },
   "properties": {
    "name": "326 BIGGS ROAD WOOROONOORAN 4860",
    "locID": "LOC000035007662",
    "tech": "WIRELESS",
    "upgrade": "NULL_NA",
    "gnaf_pid": "GAQLD720733080"
   }
  }
 ]
}