{
 "type": "FeatureCollection",
 "generated": "2024-10-08T13:35:33.349844",
 "suburb": "WOOROONOORAN",
 "features": [
  {
   "type": "Feature",
   "geometry": {
    "type": "Point",
    "coordinates": [
     145.85838393,
     -17.44350022
    ]
   },
   "properties": {
    "name": "326 BIGGS ROAD WOOROONOORAN 4860",
    "locID": "LOC000035007662",
    "tech": "WIRELESS",
    "upgrade": "NULL_NA",
    "gnaf_pid": "GAQLD720733080",
    "tech_change_status": "Not Planned",
    "program_type": "Fixed Wireless and Satellite Upgrade Program",
    "target_eligibility_quarter": "NA"
   }
  }
 ]
}