{
 "type": "FeatureCollection",
 "generated": "2023-07-16T23:57:55.444877",
 "suburb": "WOOROONOORAN",
 "features": [
  {
   "type": "Feature",
   "geometry": {
    "type": "Point",
    "coordinates": [
     145.79812576,
     -17.61147681
    ]
   },
   "properties": {
    "name": "LOT 99 PALMERSTON HIGHWAY WOOROONOORAN 4860",
    "locID": "EjA5OSBQYWxtZXJzdG9uIEh3eSwgQmVsdmVkZXJlIFFMRCA0ODYwLCBBdXN0cmFsaWEiMBIuChQKEgkrMMtaAMV4aRGsX3OVzfFvZBBjKhQKEgkRU7B7KbF4aRFWNIgCbzpi4Q",
    "tech": "WIRELESS",
    "upgrade": "UNKNOWN",
    "gnaf_pid": "GAQLD720727473"
   }
  },
  {
   "type": "Feature",
   "geometry": {
    "type": "Point",
    "coordinates": [
     145.85838393,
     -17.44350022
    ]
   },
   "properties": {
    "name": "326 BIGGS ROAD WOOROONOORAN 4860",
    "locID": "LOC000035007662",
    "tech": "WIRELESS",
    "upgrade": "NULL_NA",
    "gnaf_pid": "GAQLD720733080"
   }
  }
 ]
}