{
 "type": "FeatureCollection",
 "generated": "2024-02-12T23:24:19.769419",
 "suburb": "WOOROONOORAN",
 "features": [
  {
   "type": "Feature",
   "geometry": {
    "type": "Point",
    "coordinates": [
     145.85838393,
     -17.44350022
    ]
   },
   "properties": {
    "name": "326 BIGGS ROAD WOOROONOORAN 4860",
    "locID": "LOC000035007662",
    "tech": "WIRELESS",
    "upgrade": "NULL_NA",
    "gnaf_pid": "GAQLD720733080"
   }
  }
 ]
}